Workbook
Name ECONACIONAL: 'Nomina Econacional'!$A$4:$AB$153
Name Excel_BuiltIn__FilterDatabase: 'boleto de ornato'!#REF!
Name Excel_BuiltIn__FilterDatabase: distribucion!$P$6:$P$341
Name Excel_BuiltIn__FilterDatabase: 'INCREMENTO SALARIO MINIMO '!#REF!
Name Excel_BuiltIn__FilterDatabase: 'RECIBO E IGSS ECONACIONAL'!$B$1:$AB$2
Name Excel_BuiltIn__FilterDatabase: 'RECIBO E IGSS PROQUIMA'!$B$2:$AC$4
Name Excel_BuiltIn__FilterDatabase: 'RECIBO E IGSS UNHESA'!$B$2:$AB$4

Sheet boleto de ornato
B1: 1 | C1: 2 | D1: 3 | E1: 4 | F1: 5 | G1: 6 | H1: 6
B2: DISTRIBUCION DE PERSONAL Y COSTO POR EMPRESA
B3: NOMINA MES DE: ENERO 2,022 1a. Quincena)
E5: 5 | F5: 6
D6: DISTRIBUCION DE EMPLEADOS
B7: Nombre | C7: Puesto | D7: Empresa Real | E7: Salario Ordinario | F7: Bono Decreto | G7: Total | H7: MONTO BOLETO
B8: AREA ADMINISTRATIVA
B9: PRESIDENCIA
A10: 1 | B10: Flores Ruano Yandira Beatriz | C10: Asistente de Gerencia General | D10: UNHESA | E10: 3750 | F10: =2000+250 -> 2250 | G10: =+E10+F10 -> 6000 | H10: 50
A11: =+A10+1 -> 2 | B11: Veliz Carias Elder Danilo | C11: Piloto | D11: UNHESA | E11: 2959.24 | F11: 250 | G11: =+E11+F11 -> 3209.24 | H11: 50
A12: =+A11+1 -> 3 | B12: Pirir Toj Luis Alberto | C12: Piloto | D12: PROQUIMA | E12: 3250 | F12: 250 | G12: =+E12+F12 -> 3500 | H12: 50
C13: Total Presidencia | E13: =SUM(E10:E12) -> 9959.24 | F13: =SUM(F10:F12) -> 2750 | G13: =SUM(G10:G12) -> 12709.24 | H13: =SUM(H10:H12) -> 150
B15: ADMINISTRATIVO
A16: =A12+1 -> 4 | B16: Gaitan Hernandez Luis Daniel | C16: Piloto de Presidencia | D16: PROQUIMA | E16: 3262.5 | F16: 2250 | G16: =+E16+F16 -> 5512.5 | H16: 50
A17: =+A16+1 -> 5 | B17: Alvarez Caceros Genesis Arleth | C17: Recepcionista | D17: PROQUIMA | E17: 2959.24 | F17: 725 | G17: =+E17+F17 -> 3684.24 | H17: 50
A18: =+A17+1 -> 6 | B18: Pu Canto Domingo | C18: Conserje | D18: PROQUIMA | E18: 2959.24 | F18: 250 | G18: =+E18+F18 -> 3209.24 | H18: 50
A19: =+A18+1 -> 7 | B19: Chamay Gomez Susana Noemi | C19: conserje | D19: UNHESA | E19: 2959.24 | F19: 250 | G19: =+E19+F19 -> 3209.24 | H19: 50
A20: =+A19+1 -> 8 | B20: Cruz Juarez Santos Ernesto | C20: Mensajero | D20: PROQUIMA | E20: 2959.24 | F20: =250+120 -> 370 | G20: =+E20+F20 -> 3329.24 | H20: 50
A21: =+A20+1 -> 9 | B21: Alpuaque Aragon Sergio Antonio | C21: Mensajero | D21: PROQUIMA | E21: 2959.24 | F21: 370 | G21: =+E21+F21 -> 3329.24 | H21: 50
C22: Total Administrativo | E22: =SUM(E16:E21) -> 18058.7 | F22: =SUM(F16:F21) -> 4215 | G22: =SUM(G16:G21) -> 22273.7 | H22: =SUM(H16:H21) -> 300
B24: CONTABILIDAD Y FINANZAS
A25: =A21+1 -> 10 | B25: Patzan Quib Lucrecia | C25: Contador General | D25: UNHESA | E25: 2959.24 | F25: 250 | G25: =+E25+F25 -> 3209.24 | H25: 50
A26: =A25+1 -> 11 | B26: Sical Cruz Manuel Estuardo | C26: Supervisor Contable | D26: UNHESA | E26: 4200 | F26: 2800 | G26: =+E26+F26 -> 7000 | H26: 75
A27: =A26+1 -> 12 | B27: Mendez Flores Juan Andres | C27: Gerente Financiero | D27: PROQUIMA | E27: 13000 | F27: 7000 | G27: =+E27+F27 -> 20000 | H27: 150
A28: =A27+1 -> 13 | B28: Castañeda Osorio Estela Angelina | C28: Tesorera-Contador | D28: UNHESA | E28: 3250 | F28: 750 | G28: =+E28+F28 -> 4000 | H28: 50
A29: =A28+1 -> 14 | B29: Lopez Vasquez Flor de Maria | C29: Asistente Juridico | D29: PROQUIMA | E29: 3500 | F29: 500 | G29: =+E29+F29 -> 4000 | H29: 50
A30: =A29+1 -> 15 | B30: Gómez Laparra Glenda Esmeralda | C30: Auxiliar Contable | D30: PROQUIMA | E30: 3500 | F30: =1000 -> 1000 | G30: =+E30+F30 -> 4500 | H30: 50
A31: =A30+1 -> 16 | B31: Chavez Garcia Benner Amilcar | C31: Auxiliar Contable | D31: UNHESA | E31: 2959.24 | F31: 250 | G31: =+E31+F31 -> 3209.24 | H31: 50
A32: =A31+1 -> 17 | B32: Mendez Cruz Walter Emilio | C32: Auditor interno | D32: PROQUIMA | E32: 5055 | F32: 3045 | G32: =+E32+F32 -> 8100 | H32: 75
A33: =A32+1 -> 18 | B33: Ramos Caracun Jose Ottoniel | C33: Auxiliar Contable | D33: UNHESA | E33: 3250 | F33: 750 | G33: =+E33+F33 -> 4000 | H33: 50
C34: Total Contabilidad y Finanzas | E34: =SUM(E25:E33) -> 41673.48 | F34: =SUM(F25:F33) -> 16345 | G34: =SUM(G25:G33) -> 58018.48 | H34: =SUM(H25:H33) -> 600
B36: INVESTIGACION Y DESARROLLO
A37: =A33+1 -> 19 | B37: De Floran Rodas Luis Arnau Estanislao | C37: Jefe I & D | D37: PROQUIMA | E37: 5000 | F37: =250+750 -> 1000 | G37: =+E37+F37 -> 6000 | H37: 50
A38: =+A37+1 -> 20 | B38: Orozco Tzic Yenifer Jimena | C38: Asistente de Investigacion y Desarrollo | D38: PROQUIMA | E38: 4000 | F38: 500 | G38: =+E38+F38 -> 4500 | H38: 50
A39: =+A38+1 -> 21 | B39: Castro Aceituno Rodrigo Jose | C39: Auxiliar de Investigacion y Desarrollo | D39: PROQUIMA | E39: 2959.24 | F39: 250 | G39: =+E39+F39 -> 3209.24 | H39: 50
C40: TotaL Investigacion y desarrollo | E40: =SUM(E37:E39) -> 11959.24 | F40: =SUM(F37:F39) -> 1750 | G40: =SUM(G37:G39) -> 13709.24 | H40: =SUM(H37:H39) -> 150
B42: CONTROL DE CALIDAD
A43: 22 | B43: Melgar Najera Alfredo Emilio | C43: Jefe de Gestion de calidad | D43: PROQUIMA | E43: =4250+500 -> 4750 | F43: =250+2000 -> 2250 | G43: =+E43+F43 -> 7000 | H43: 75
A44: =+A43+1 -> 23 | B44: Muñoz Laparra Orly Gabriela | C44: Asistente de Control de Calidad | D44: PROQUIMA | E44: =4250+250 -> 4500 | F44: =250+250 -> 500 | G44: =+E44+F44 -> 5000 | H44: 50
A45: =+A44+1 -> 24 | B45: Lopez Orellana Genesis Alejandra | C45: Asistente de Control de Calidad | D45: UNHESA | E45: 4250 | F45: 750 | G45: =+E45+F45 -> 5000 | H45: 50
A46: =+A45+1 -> 25 | B46: Guzman Hernandez Edgar Geovanni | C46: Auxiliar de control de calidad | D46: PROQUIMA | E46: 2959.24 | F46: 400 | G46: =+E46+F46 -> 3359.24 | H46: 50
A47: =+A46+1 -> 26 | B47: Martinez Garcia Erick Rolando | C47: Auxiliar de control de calidad | D47: PROQUIMA | E47: 2959.24 | F47: 250 | G47: =+E47+F47 -> 3209.24 | H47: 50
C48: TotaL Control de Calidad | E48: =SUM(E43:E47) -> 19418.48 | F48: =SUM(F43:F47) -> 4150 | G48: =SUM(G43:G47) -> 23568.48 | H48: =SUM(H43:H47) -> 275
B50: INFORMATICA
A51: =A47+1 -> 27 | B51: Jimenez Sosa Luis Eduardo | C51: Jefe de Informática | D51: PROQUIMA | E51: 5775 | F51: 5250 | G51: =+E51+F51 -> 11025 | H51: 100
A52: =+A51+1 -> 28 | B52: Palma Salvatierra Harim Abdala | C52: Project Manager | D52: PROQUIMA | E52: 5250 | F52: =1900+715 -> 2615 | G52: =+E52+F52 -> 7865 | H52: 75
A53: 29 | B53: Guerra Lopez Jonathan Otoniel | C53: Analista Programador | D53: PROQUIMA | E53: 2959.24 | F53: 250 | G53: =+E53+F53 -> 3209.24 | H53: 50
C54: Total Informatica | E54: =+SUM(E51:E53) -> 13984.24 | F54: =+SUM(F51:F53) -> 8115 | G54: =+SUM(G51:G53) -> 22099.24 | H54: =+SUM(H51:H53) -> 225
B56: RECURSOS HUMANOS
A57: =A53+1 -> 30 | B57: Hernandez de Lemus Iris Carolina | C57: Jefe de Recursos Humanos | D57: UNHESA | E57: 7025 | F57: 4000 | G57: =+E57+F57 -> 11025 | H57: 100
A58: =+A57+1 -> 31 | B58: Perez Menendez Mayra Alejandra | C58: Asistente de Recursos Humanos | D58: PROQUIMA | E58: 3500 | F58: 825 | G58: =+E58+F58 -> 4325 | H58: 50
A59: =+A58+1 -> 32 | B59: Zarate De Leon, Enma Yaneth | C59: Asistente de Reclutamiento | D59: PROQUIMA | E59: 3750 | F59: 250 | G59: =+E59+F59 -> 4000 | H59: 50
C60: TotaL Recursos Humanos | E60: =SUM(E57:E59) -> 14275 | F60: =SUM(F57:F59) -> 5075 | G60: =SUM(G57:G59) -> 19350 | H60: =SUM(H57:H59) -> 200
C61: Total AREA ADMINISTRATIVA | E61: =SUM(E13+E22+E34+E40+E48+E54+E60) -> 129328.38 | F61: =SUM(F13+F22+F34+F40+F48+F54+F60) -> 42400 | G61: =SUM(G13+G22+G34+G40+G48+G54+G60) -> 171728.38 | H61: =SUM(H13+H22+H34+H40+H48+H54+H60) -> 1900
B63: COMPRAS IMPORTACIONES Y EXPORTACIONES
A64: 33 | B64: Gomez Likez Rene Alexander | C64: Encargado de Proveeduria | D64: UNHESA | E64: 3450 | F64: 550 | G64: =+E64+F64 -> 4000 | H64: 50
A65: =A64+1 -> 34 | B65: Santizo Santizo Rodrigo Eduardo | C65: Asistente de Compras | D65: PROQUIMA | E65: 4550 | F65: 950 | G65: =+E65+F65 -> 5500 | H65: 50
A66: =A65+1 -> 35 | B66: Ramirez Ovando Marilyn Crystal | C66: Asistente de Compras | D66: UNHESA | E66: 4400 | F66: 1100 | G66: =+E66+F66 -> 5500 | H66: 50
A67: =A66+1 -> 36 | B67: Gonzalez Gomez Glendy Paola | C67: Gerente Compras expo e impo | D67: UNHESA | E67: 10000 | F67: 3000 | G67: =+E67+F67 -> 13000 | H67: 150
C68: Total Compras e importaciones | E68: =SUM(E64:E67) -> 22400 | F68: =SUM(F64:F67) -> 5600 | G68: =SUM(G64:G67) -> 28000 | H68: =SUM(H64:H67) -> 300
B69: AREA DE OPERACIONES
B70: PRODUCCION
B71: DIRECCION
A72: =+A67+1 -> 37 | B72: Monterroso Barrios Juan Carlos | C72: Gerente de Operaciones | D72: PROQUIMA | E72: =13000 -> 13000 | F72: 9000 | G72: =+E72+F72 -> 22000 | H72: 150
A73: =+A72+1 -> 38 | B73: Hernandez Contreras Kewin Josue | C73: Supervisor | D73: PROQUIMA | E73: 2959.24 | F73: 250 | G73: =+E73+F73 -> 3209.24 | H73: 50
A74: 39 | B74: Osoy Gonzalez Luis Antonio | C74: Supervisor | D74: UNHESA | E74: 3450 | F74: 450 | G74: 3900 | H74: 50
A75: 40 | B75: Maldonado Solval Karla Elizabeth | C75: Supervisor | D75: UNHESA | E75: 3450 | F75: 450 | G75: 3900 | H75: 50
A76: 41 | B76: Cisneros Gonzales Esvin Antonio | C76: Jefe de Producción | D76: PROQUIMA | E76: 5000 | F76: 1500 | G76: =+E76+F76 -> 6500 | H76: 75
A77: =+A76+1 -> 42 | B77: De Paz Corado Erick Geovanni | C77: Digitador | D77: PROQUIMA | E77: 3250 | F77: 750 | G77: =+E77+F77 -> 4000 | H77: 50
E78: =SUM(E72:E77) -> 31109.24 | F78: =SUM(F72:F77) -> 12400 | G78: =SUM(G72:G77) -> 43509.24 | H78: =SUM(H72:H77) -> 425
B79: UNHESA
A80: =+A77+1 -> 43 | B80: Garrido Aguilar Maria Elena | C80: Empacadora de Sobres | D80: UNHESA | E80: 2959.24 | F80: 250 | G80: =+E80+F80 -> 3209.24 | H80: 50
A81: =+A80+1 -> 44 | B81: Boche Mendez Olga Veronica | C81: Empacadora de Sobres | D81: UNHESA | E81: 2959.24 | F81: 250 | G81: =+E81+F81 -> 3209.24 | H81: 50
A82: =+A81+1 -> 45 | B82: Sontay Cifuentes Leydi Rosivel | C82: Linea de Botes | D82: UNHESA | E82: 2959.24 | F82: 250 | G82: =+E82+F82 -> 3209.24 | H82: 50
A83: =+A82+1 -> 46 | B83: Samora Sacul Yocelin Paola | C83: Linea de Botes | D83: UNHESA | E83: 2959.24 | F83: =250 -> 250 | G83: =+E83+F83 -> 3209.24 | H83: 50
A84: =+A83+1 -> 47 | B84: Cisneros Lopez Marvin Daniel | C84: Operario Sobres | D84: UNHESA | E84: 2959.24 | F84: =250 -> 250 | G84: =+E84+F84 -> 3209.24 | H84: 50
A85: =+A84+1 -> 48 | B85: Guerra Tobar Melvin Esleiter | C85: Operario Sobres | D85: UNHESA | E85: 2959.24 | F85: 250 | G85: =+E85+F85 -> 3209.24 | H85: 50
A86: =+A85+1 -> 49 | B86: Vasquez Bamaca Walter Leonidas | C86: Operario Sobres | D86: UNHESA | E86: 2959.24 | F86: 250 | G86: =+E86+F86 -> 3209.24 | H86: 50
A87: =+A86+1 -> 50 | B87: Gomez Martinez Sandor Felipe | C87: Operador | D87: UNHESA | E87: 2959.24 | F87: 250 | G87: =+E87+F87 -> 3209.24 | H87: 50
A88: =+A87+1 -> 51 | B88: Ramirez Vasquez Audelio | C88: Operario | D88: UNHESA | E88: 2959.24 | F88: 250 | G88: =+E88+F88 -> 3209.24 | H88: 50
A89: =+A88+1 -> 52 | B89: Garcia Sarceño Mayvin Armando | C89: Operario | D89: UNHESA | E89: 2959.24 | F89: 250 | G89: =+E89+F89 -> 3209.24 | H89: 50
A90: =+A89+1 -> 53 | B90: Salvatierra de Leon Jakeline Marisela | C90: Empacadora | D90: UNHESA | E90: 2959.24 | F90: 250 | G90: =+E90+F90 -> 3209.24 | H90: 50
A91: =+A90+1 -> 54 | B91: Hernandez Aquino Wendy Lizbeth | C91: Empacadora | D91: UNHESA | E91: 2959.24 | F91: 250 | G91: =+E91+F91 -> 3209.24 | H91: 50
A92: =+A91+1 -> 55 | B92: Morales Hernandez Joselyn Arceli | C92: Empacadora | D92: UNHESA | E92: 2959.24 | F92: 250 | G92: =+E92+F92 -> 3209.24 | H92: 50
A93: =+A92+1 -> 56 | B93: Méndez González Grecia Marbella | C93: Empacadora | D93: UNHESA | E93: 2959.24 | F93: 250 | G93: =+E93+F93 -> 3209.24 | H93: 50
A94: =+A93+1 -> 57 | B94: Sian Ortega Mildred Liliana | C94: Empacadora | D94: UNHESA | E94: 2959.24 | F94: 250 | G94: =+E94+F94 -> 3209.24 | H94: 50
A95: =+A94+1 -> 58 | B95: Ramirez Arcon Maria Nury | C95: Empacadora | D95: UNHESA | E95: 2959.24 | F95: 250 | G95: =+E95+F95 -> 3209.24 | H95: 50
A96: =+A95+1 -> 59 | B96: Ruche Bor José Antonio | C96: Auxiliar de Carga | D96: UNHESA | E96: 2959.24 | F96: 250 | G96: =+E96+F96 -> 3209.24 | H96: 50
C97: Total Unhesa | E97: =SUM(E80:E96) -> 50307.08 | F97: =SUM(F80:F96) -> 4250 | G97: =SUM(G80:G96) -> 54557.08 | H97: =SUM(H80:H96) -> 850
B99: PROQUMA
A100: =A96+1 -> 60 | B100: Yat Mo Marvin Obdulio | C100: Operario | D100: PROQUIMA | E100: 2959.24 | F100: 250 | G100: =+E100+F100 -> 3209.24 | H100: 50
A101: =A100+1 -> 61 | B101: Cisneros Escobar Walter De Jesus | C101: Operario | D101: PROQUIMA | E101: 2959.24 | F101: 250 | G101: =+E101+F101 -> 3209.24 | H101: 50
A102: =A101+1 -> 62 | B102: Samayoa Martir Mario Humberto | C102: Operario | D102: PROQUIMA | E102: 2959.24 | F102: 250 | G102: =+E102+F102 -> 3209.24 | H102: 50
A103: =A102+1 -> 63 | B103: Boror Pirir Jose Cruz | C103: Operario | D103: PROQUIMA | E103: 2959.24 | F103: 250 | G103: =+E103+F103 -> 3209.24 | H103: 50
A104: =A103+1 -> 64 | B104: Cotzajay Lopez Aura Leticia | C104: Empacadora | D104: PROQUIMA | E104: 2959.24 | F104: 250 | G104: =+E104+F104 -> 3209.24 | H104: 50
A105: =A104+1 -> 65 | B105: Boror López Mayra Guadalupe | C105: Empacadora | D105: PROQUIMA | E105: 2959.24 | F105: 250 | G105: =+E105+F105 -> 3209.24 | H105: 50
A106: =A105+1 -> 66 | B106: Choc Caal Augusto Adan | C106: Operario | D106: PROQUIMA | E106: 2959.24 | F106: =250 -> 250 | G106: =+E106+F106 -> 3209.24 | H106: 50
A107: =A106+1 -> 67 | B107: López Gerber Alexander | C107: Operario | D107: PROQUIMA | E107: 2959.24 | F107: =250 -> 250 | G107: =+E107+F107 -> 3209.24 | H107: 50
A108: =A107+1 -> 68 | B108: Quej Cau Jose Angel | C108: Operario | D108: PROQUIMA | E108: 2959.24 | F108: =250 -> 250 | G108: =+E108+F108 -> 3209.24 | H108: 50
A109: =A108+1 -> 69 | B109: Contreras Vasquez Oscar Jose | C109: Operario | D109: PROQUIMA | E109: 2959.24 | F109: =250 -> 250 | G109: =+E109+F109 -> 3209.24 | H109: 50
...

Sheet INCREMENTO SALARIO MINIMO 
B1: 1 | C1: 2 | D1: 3 | E1: 4 | F1: 5 | G1: 6 | H1: 8 | I1: 9 | J1: 10 | K1: 13 | M1: 1 | N1: 2 | O1: 3 | P1: 4 | Q1: 5 | R1: 6 | S1: 8 | T1: 9 | U1: 10 | V1: 13
B2: DISTRIBUCION DE PERSONAL Y COSTO POR EMPRESA | M2: DISTRIBUCION DE PERSONAL Y COSTO POR EMPRESA
B3: NOMINA MES DE: ENERO 2,022 1a. Quincena) | M3: NOMINA MES DE: ENERO 2,022 1a. Quincena)
E5: 5 | F5: 6 | P5: 5 | Q5: 6
D6: DISTRIBUCION DE EMPLEADOS | O6: DISTRIBUCION DE EMPLEADOS
B7: Nombre | C7: Puesto | D7: Empresa Real | E7: Salario Ordinario | F7: Bono Decreto | G7: Total | H7: % Proquima | I7: % Unhesa | J7: % Unhesa Liq. | K7: Total % Distribución | M7: Nombre | N7: Puesto | O7: Empresa Real | P7: Salario Ordinario | Q7: Bono Decreto | R7: Total | S7: % Proquima | T7: % Unhesa | U7: % Unhesa Liq. | V7: Total % Distribución
B8: AREA ADMINISTRATIVA | M8: AREA ADMINISTRATIVA
B9: PRESIDENCIA | M9: PRESIDENCIA
A10: 2 | B10: Estrada Robles Victor Gerardo 1 | C10: Asesor | D10: PROQUIMA | E10: 2825.1 | F10: 250 | G10: =+E10+F10 -> 3075.1 | H10: 1 | I10: 0 | J10: 0 | K10: =SUM(H10:J10) -> 1 | M10: Estrada Robles Victor Gerardo 1 | N10: Asesor | O10: PROQUIMA | P10: 2959.24 | Q10: 250 | R10: =+P10+Q10 -> 3209.24 | S10: 1 | T10: 0 | U10: 0 | V10: =SUM(S10:U10) -> 1
B11: Estrada Robles Juan Pablo | C11: Asesor | D11: PROQUIMA | E11: 2825.1 | F11: 250 | G11: =+E11+F11 -> 3075.1 | H11: 1 | I11: 0 | J11: 0 | K11: =SUM(H11:J11) -> 1 | M11: Estrada Robles Juan Pablo | N11: Asesor | O11: PROQUIMA | P11: 2959.24 | Q11: 250 | R11: =+P11+Q11 -> 3209.24 | S11: 1 | T11: 0 | U11: 0 | V11: =SUM(S11:U11) -> 1
A12: 5 | B12: Veliz Carias Elder Danilo | C12: Piloto | D12: UNHESA | E12: 2825.1 | F12: 250 | G12: =+E12+F12 -> 3075.1 | H12: 0 | I12: 1 | J12: 0 | K12: =SUM(H12:J12) -> 1 | M12: Veliz Carias Elder Danilo | N12: Piloto | O12: UNHESA | P12: 2959.24 | Q12: 250 | R12: =+P12+Q12 -> 3209.24 | S12: 0 | T12: 1 | U12: 0 | V12: =SUM(S12:U12) -> 1
C13: Total Presidencia | E13: =SUM(E10:E12) -> 8475.3 | F13: =SUM(F10:F12) -> 750 | G13: =SUM(G10:G12) -> 9225.3 | N13: Total Presidencia | P13: =SUM(P10:P12) -> 8877.72 | Q13: =SUM(Q10:Q12) -> 750 | R13: =SUM(R10:R12) -> 9627.72
B17: ADMINISTRATIVO | M17: ADMINISTRATIVO
A18: 8 | B18: Alvarez Caceros Genesis Arleth | C18: Recepcionista | D18: PROQUIMA | E18: 2825.1 | F18: 725 | G18: =+E18+F18 -> 3550.1 | H18: 0.5 | I18: 0.5 | J18: 0 | K18: =SUM(H18:J18) -> 1 | M18: Alvarez Caceros Genesis Arleth | N18: Recepcionista | O18: PROQUIMA | P18: 2959.24 | Q18: 725 | R18: =+P18+Q18 -> 3684.24 | S18: 0.5 | T18: 0.5 | U18: 0 | V18: =SUM(S18:U18) -> 1
A19: 9 | B19: Pu Canto Domingo | C19: Conserje | D19: PROQUIMA | E19: 2825.1 | F19: 250 | G19: =+E19+F19 -> 3075.1 | H19: 0.5 | I19: 0.5 | J19: 0 | K19: =SUM(H19:J19) -> 1 | M19: Pu Canto Domingo | N19: Conserje | O19: PROQUIMA | P19: 2959.24 | Q19: 250 | R19: =+P19+Q19 -> 3209.24 | S19: 0.5 | T19: 0.5 | U19: 0 | V19: =SUM(S19:U19) -> 1
A20: 10 | B20: Chamay Gomez Susana Noemi | C20: conserje | D20: UNHESA | E20: 2825.1 | F20: 250 | G20: =+E20+F20 -> 3075.1 | H20: 0 | I20: 1 | J20: 0 | K20: =SUM(H20:J20) -> 1 | M20: Chamay Gomez Susana Noemi | N20: conserje | O20: UNHESA | P20: 2959.24 | Q20: 250 | R20: =+P20+Q20 -> 3209.24 | S20: 0 | T20: 1 | U20: 0 | V20: =SUM(S20:U20) -> 1
A21: 11 | B21: Cruz Juarez Santos Ernesto | C21: Mensajero | D21: PROQUIMA | E21: 2825.1 | F21: =250+120 -> 370 | G21: =+E21+F21 -> 3195.1 | H21: 1 | I21: 0 | J21: 0 | K21: =SUM(H21:J21) -> 1 | M21: Cruz Juarez Santos Ernesto | N21: Mensajero | O21: PROQUIMA | P21: 2959.24 | Q21: =250+120 -> 370 | R21: =+P21+Q21 -> 3329.24 | S21: 1 | T21: 0 | U21: 0 | V21: =SUM(S21:U21) -> 1
A22: 12 | B22: Alpuaque Aragon Sergio Antonio | C22: Mensajero | D22: PROQUIMA | E22: 2825.1 | F22: 370 | G22: =+E22+F22 -> 3195.1 | H22: 1 | I22: 0 | J22: 0 | K22: =SUM(H22:J22) -> 1 | M22: Alpuaque Aragon Sergio Antonio | N22: Mensajero | O22: PROQUIMA | P22: 2959.24 | Q22: 370 | R22: =+P22+Q22 -> 3329.24 | S22: 1 | T22: 0 | U22: 0 | V22: =SUM(S22:U22) -> 1
C23: Total Administrativo | E23: =SUM(E18:E22) -> 14125.5 | F23: =SUM(F18:F22) -> 1965 | G23: =SUM(G18:G22) -> 16090.5 | N23: Total Administrativo | P23: =SUM(P18:P22) -> 14796.2 | Q23: =SUM(Q18:Q22) -> 1965 | R23: =SUM(R18:R22) -> 16761.2
B25: CONTABILIDAD Y FINANZAS | M25: CONTABILIDAD Y FINANZAS
A26: =A22+1 -> 13 | B26: Patzan Quib Lucrecia | C26: Contador General | D26: UNHESA | E26: 2825.1 | F26: 250 | G26: =+E26+F26 -> 3075.1 | H26: 0.65 | I26: 0.35 | J26: 0 | K26: =SUM(H26:J26) -> 1 | M26: Patzan Quib Lucrecia | N26: Contador General | O26: UNHESA | P26: 2959.24 | Q26: 250 | R26: =+P26+Q26 -> 3209.24 | S26: 0.65 | T26: 0.35 | U26: 0 | V26: =SUM(S26:U26) -> 1
A27: =#REF!+1 -> #REF! | B27: Chavez Garcia Benner Amilcar | C27: Auxiliar Contable | D27: UNHESA | E27: 2825.1 | F27: 250 | G27: =+E27+F27 -> 3075.1 | H27: 0.5 | I27: 0.5 | J27: 0 | K27: =SUM(H27:J27) -> 1 | M27: Chavez Garcia Benner Amilcar | N27: Auxiliar Contable | O27: UNHESA | P27: 2959.24 | Q27: 250 | R27: =+P27+Q27 -> 3209.24 | S27: 0.5 | T27: 0.5 | U27: 0 | V27: =SUM(S27:U27) -> 1
C28: Total Contabilidad y Finanzas | E28: =SUM(E26:E27) -> 5650.2 | F28: =SUM(F26:F27) -> 500 | G28: =SUM(G26:G27) -> 6150.2 | N28: Total Contabilidad y Finanzas | P28: =SUM(P26:P27) -> 5918.48 | Q28: =SUM(Q26:Q27) -> 500 | R28: =SUM(R26:R27) -> 6418.48
B30: INVESTIGACION Y DESARROLLO | M30: INVESTIGACION Y DESARROLLO
A31: =+#REF!+1 -> #REF! | B31: Castro Aceituno Rodrigo Jose | C31: Auxiliar de Investigacion y Desarrollo | D31: PROQUIMA | E31: 2825.1 | F31: 250 | G31: =+E31+F31 -> 3075.1 | H31: 1 | I31: 0 | J31: 0 | K31: =SUM(H31:J31) -> 1 | M31: Castro Aceituno Rodrigo Jose | N31: Auxiliar de Investigacion y Desarrollo | O31: PROQUIMA | P31: 2959.24 | Q31: 250 | R31: =+P31+Q31 -> 3209.24 | S31: 1 | T31: 0 | U31: 0 | V31: =SUM(S31:U31) -> 1
C32: TotaL Investigacion y desarrollo | E32: =SUM(E31:E31) -> 2825.1 | F32: =SUM(F31:F31) -> 250 | G32: =SUM(G31:G31) -> 3075.1 | N32: TotaL Investigacion y desarrollo | P32: =SUM(P31:P31) -> 2959.24 | Q32: =SUM(Q31:Q31) -> 250 | R32: =SUM(R31:R31) -> 3209.24
B34: CONTROL DE CALIDAD | M34: CONTROL DE CALIDAD
A35: =+#REF!+1 -> #REF! | B35: Guzman Hernandez Edgar Geovanni | C35: Auxiliar de control de calidad | D35: PROQUIMA | E35: 2825.1 | F35: 400 | G35: =+E35+F35 -> 3225.1 | H35: 0.6 | I35: 0.4 | J35: 0 | K35: =SUM(H35:J35) -> 1 | M35: Guzman Hernandez Edgar Geovanni | N35: Auxiliar de control de calidad | O35: PROQUIMA | P35: 2959.24 | Q35: 400 | R35: =+P35+Q35 -> 3359.24 | S35: 0.6 | T35: 0.4 | U35: 0 | V35: =SUM(S35:U35) -> 1
A36: =+A35+1 -> #REF! | B36: Martinez Garcia Erick Rolando | C36: Auxiliar de control de calidad | D36: PROQUIMA | E36: 2825.1 | F36: 250 | G36: =+E36+F36 -> 3075.1 | H36: 0.6 | I36: 0.4 | J36: 0 | K36: =SUM(H36:J36) -> 1 | M36: Martinez Garcia Erick Rolando | N36: Auxiliar de control de calidad | O36: PROQUIMA | P36: 2959.24 | Q36: 250 | R36: =+P36+Q36 -> 3209.24 | S36: 0.6 | T36: 0.4 | U36: 0 | V36: =SUM(S36:U36) -> 1
C37: TotaL Control de Calidad | E37: =SUM(E35:E36) -> 5650.2 | F37: =SUM(F35:F36) -> 650 | G37: =SUM(G35:G36) -> 6300.2 | N37: TotaL Control de Calidad | P37: =SUM(P35:P36) -> 5918.48 | Q37: =SUM(Q35:Q36) -> 650 | R37: =SUM(R35:R36) -> 6568.48
B39: INFORMATICA | M39: INFORMATICA
A40: =+#REF!+1 -> #REF! | B40: Lopez Calderon Cesar Anibal | C40: Analista Programador | D40: UNHESA | E40: 2825.1 | F40: 250 | G40: =+E40+F40 -> 3075.1 | H40: 0.5 | I40: 0.5 | J40: 0 | K40: =SUM(H40:J40) -> 1 | M40: Lopez Calderon Cesar Anibal | N40: Analista Programador | O40: UNHESA | P40: 2959.24 | Q40: 250 | R40: =+P40+Q40 -> 3209.24 | S40: 0.5 | T40: 0.5 | U40: 0 | V40: =SUM(S40:U40) -> 1
A41: =+A40+1 -> #REF! | B41: Cabrera Guzman Javier Antonio | C41: Analista Programador | D41: UNHESA | E41: 2825.1 | F41: 250 | G41: =+E41+F41 -> 3075.1 | H41: 0.5 | I41: 0.5 | J41: 0 | K41: =SUM(H41:J41) -> 1 | M41: Cabrera Guzman Javier Antonio | N41: Analista Programador | O41: UNHESA | P41: 2959.24 | Q41: 250 | R41: =+P41+Q41 -> 3209.24 | S41: 0.5 | T41: 0.5 | U41: 0 | V41: =SUM(S41:U41) -> 1
A42: =+A41+1 -> #REF! | B42: Figueros Cardona Gabriel | C42: Analista Programador | D42: UNHESA | E42: 2825.1 | F42: 250 | G42: =+E42+F42 -> 3075.1 | H42: 0.5 | I42: 0.5 | J42: 0 | K42: =SUM(H42:J42) -> 1 | M42: Figueros Cardona Gabriel | N42: Analista Programador | O42: UNHESA | P42: 2959.24 | Q42: 250 | R42: =+P42+Q42 -> 3209.24 | S42: 0.5 | T42: 0.5 | U42: 0 | V42: =SUM(S42:U42) -> 1
A43: =+A42+1 -> #REF! | B43: Guerra Lopez Jonathan Otoniel | C43: Analista Programador | D43: PROQUIMA | E43: 2825.1 | F43: 250 | G43: =+E43+F43 -> 3075.1 | H43: 0.5 | I43: 0.5 | J43: 0 | K43: =SUM(H43:J43) -> 1 | M43: Guerra Lopez Jonathan Otoniel | N43: Analista Programador | O43: PROQUIMA | P43: 2959.24 | Q43: 250 | R43: =+P43+Q43 -> 3209.24 | S43: 0.5 | T43: 0.5 | U43: 0 | V43: =SUM(S43:U43) -> 1
C44: Total Informatica | E44: =+SUM(E40:E43) -> 11300.4 | F44: =+SUM(F40:F43) -> 1000 | G44: =+SUM(G40:G43) -> 12300.4 | N44: Total Informatica | P44: =+SUM(P40:P43) -> 11836.96 | Q44: =+SUM(Q40:Q43) -> 1000 | R44: =+SUM(R40:R43) -> 12836.96
B45: AREA DE OPERACIONES | M45: AREA DE OPERACIONES
B46: PRODUCCION | M46: PRODUCCION
B47: DIRECCION | M47: DIRECCION
A48: =+#REF!+1 -> #REF! | B48: Hernandez Contreras Kewin Josue | C48: Supervisor | D48: PROQUIMA | E48: 2825.1 | F48: 250 | G48: =+E48+F48 -> 3075.1 | H48: 1 | I48: 0 | J48: 0 | K48: =SUM(H48:J48) -> 1 | M48: Hernandez Contreras Kewin Josue | N48: Supervisor | O48: PROQUIMA | P48: 2959.24 | Q48: 250 | R48: =+P48+Q48 -> 3209.24 | S48: 1 | T48: 0 | U48: 0 | V48: =SUM(S48:U48) -> 1
E49: =SUM(E48:E48) -> 2825.1 | F49: =SUM(F48:F48) -> 250 | G49: =SUM(G48:G48) -> 3075.1 | P49: =SUM(P48:P48) -> 2959.24 | Q49: =SUM(Q48:Q48) -> 250 | R49: =SUM(R48:R48) -> 3209.24
B50: UNHESA | M50: UNHESA
A51: =+#REF!+1 -> #REF! | B51: Garrido Aguilar Maria Elena | C51: Empacadora de Sobres | D51: UNHESA | E51: 2825.1 | F51: 250 | G51: =+E51+F51 -> 3075.1 | H51: 0 | I51: 1 | J51: 0 | K51: =SUM(H51:J51) -> 1 | M51: Garrido Aguilar Maria Elena | N51: Empacadora de Sobres | O51: UNHESA | P51: 2959.24 | Q51: 250 | R51: =+P51+Q51 -> 3209.24 | S51: 0 | T51: 1 | U51: 0 | V51: =SUM(S51:U51) -> 1
A52: =+A51+1 -> #REF! | B52: Boche Mendez Olga Veronica | C52: Empacadora de Sobres | D52: UNHESA | E52: 2825.1 | F52: 250 | G52: =+E52+F52 -> 3075.1 | H52: 0 | I52: 1 | J52: 0 | K52: =SUM(H52:J52) -> 1 | M52: Boche Mendez Olga Veronica | N52: Empacadora de Sobres | O52: UNHESA | P52: 2959.24 | Q52: 250 | R52: =+P52+Q52 -> 3209.24 | S52: 0 | T52: 1 | U52: 0 | V52: =SUM(S52:U52) -> 1
A53: =+A52+1 -> #REF! | B53: Sontay Cifuentes Leydi Rosivel | C53: Linea de Botes | D53: UNHESA | E53: 2825.1 | F53: 250 | G53: =+E53+F53 -> 3075.1 | H53: 0 | I53: 1 | J53: 0 | K53: =SUM(H53:J53) -> 1 | M53: Sontay Cifuentes Leydi Rosivel | N53: Linea de Botes | O53: UNHESA | P53: 2959.24 | Q53: 250 | R53: =+P53+Q53 -> 3209.24 | S53: 0 | T53: 1 | U53: 0 | V53: =SUM(S53:U53) -> 1
A54: =+A53+1 -> #REF! | B54: Samora Sacul Yocelin Paola | C54: Linea de Botes | D54: UNHESA | E54: 2825.1 | F54: =250 -> 250 | G54: =+E54+F54 -> 3075.1 | H54: 0 | I54: 1 | J54: 0 | K54: =SUM(H54:J54) -> 1 | L54: 450 | M54: Samora Sacul Yocelin Paola | N54: Linea de Botes | O54: UNHESA | P54: 2959.24 | Q54: =250 -> 250 | R54: =+P54+Q54 -> 3209.24 | S54: 0 | T54: 1 | U54: 0 | V54: =SUM(S54:U54) -> 1
A55: =+A54+1 -> #REF! | B55: Cisneros Lopez Marvin Daniel | C55: Operario Sobres | D55: UNHESA | E55: 2825.1 | F55: =250 -> 250 | G55: =+E55+F55 -> 3075.1 | H55: 0 | I55: 1 | J55: 0 | K55: =SUM(H55:J55) -> 1 | M55: Cisneros Lopez Marvin Daniel | N55: Operario Sobres | O55: UNHESA | P55: 2959.24 | Q55: =250 -> 250 | R55: =+P55+Q55 -> 3209.24 | S55: 0 | T55: 1 | U55: 0 | V55: =SUM(S55:U55) -> 1
A56: =+A55+1 -> #REF! | B56: Guerra Tobar Melvin Esleiter | C56: Operario Sobres | D56: UNHESA | E56: 2825.1 | F56: 250 | G56: =+E56+F56 -> 3075.1 | H56: 0 | I56: 1 | J56: 0 | K56: =SUM(H56:J56) -> 1 | M56: Guerra Tobar Melvin Esleiter | N56: Operario Sobres | O56: UNHESA | P56: 2959.24 | Q56: 250 | R56: =+P56+Q56 -> 3209.24 | S56: 0 | T56: 1 | U56: 0 | V56: =SUM(S56:U56) -> 1
A57: =+A56+1 -> #REF! | B57: Vasquez Bamaca Walter Leonidas | C57: Operario Sobres | D57: UNHESA | E57: 2825.1 | F57: 250 | G57: =+E57+F57 -> 3075.1 | H57: 0 | I57: 1 | J57: 0 | K57: =SUM(H57:J57) -> 1 | M57: Vasquez Bamaca Walter Leonidas | N57: Operario Sobres | O57: UNHESA | P57: 2959.24 | Q57: 250 | R57: =+P57+Q57 -> 3209.24 | S57: 0 | T57: 1 | U57: 0 | V57: =SUM(S57:U57) -> 1
A58: =+A57+1 -> #REF! | B58: Gomez Martinez Sandor Felipe | C58: Operador | D58: UNHESA | E58: 2825.1 | F58: 250 | G58: 3075.1 | H58: 0 | I58: 1 | J58: 0 | K58: =SUM(H58:J58) -> 1 | M58: Gomez Martinez Sandor Felipe | N58: Operador | O58: UNHESA | P58: 2959.24 | Q58: 250 | R58: 3075.1 | S58: 0 | T58: 1 | U58: 0 | V58: =SUM(S58:U58) -> 1
A59: =+A58+1 -> #REF! | B59: Ramirez Vasquez Audelio | C59: Operario | D59: UNHESA | E59: 2825.1 | F59: 250 | G59: =+E59+F59 -> 3075.1 | H59: 0 | I59: 1 | J59: 0 | K59: =SUM(H59:J59) -> 1 | M59: Ramirez Vasquez Audelio | N59: Operario | O59: UNHESA | P59: 2959.24 | Q59: 250 | R59: =+P59+Q59 -> 3209.24 | S59: 0 | T59: 1 | U59: 0 | V59: =SUM(S59:U59) -> 1
A60: =+A59+1 -> #REF! | B60: Garcia Sarceño Mayvin Armando | C60: Operario | D60: UNHESA | E60: 2825.1 | F60: 250 | G60: =+E60+F60 -> 3075.1 | H60: 0 | I60: 1 | J60: 0 | K60: =SUM(H60:J60) -> 1 | M60: Garcia Sarceño Mayvin Armando | N60: Operario | O60: UNHESA | P60: 2959.24 | Q60: 250 | R60: =+P60+Q60 -> 3209.24 | S60: 0 | T60: 1 | U60: 0 | V60: =SUM(S60:U60) -> 1
A61: =+A60+1 -> #REF! | B61: Salvatierra de Leon Jakeline Marisela | C61: Empacadora | D61: UNHESA | E61: 2825.1 | F61: 250 | G61: =+E61+F61 -> 3075.1 | H61: 0 | I61: 1 | J61: 0 | K61: =SUM(H61:J61) -> 1 | M61: Salvatierra de Leon Jakeline Marisela | N61: Empacadora | O61: UNHESA | P61: 2959.24 | Q61: 250 | R61: =+P61+Q61 -> 3209.24 | S61: 0 | T61: 1 | U61: 0 | V61: =SUM(S61:U61) -> 1
A62: =+A61+1 -> #REF! | B62: Hernandez Aquino Wendy Lizbeth | C62: Empacadora | D62: UNHESA | E62: 2825.1 | F62: 250 | G62: =+E62+F62 -> 3075.1 | H62: 0 | I62: 1 | J62: 0 | K62: =SUM(H62:J62) -> 1 | M62: Hernandez Aquino Wendy Lizbeth | N62: Empacadora | O62: UNHESA | P62: 2959.24 | Q62: 250 | R62: =+P62+Q62 -> 3209.24 | S62: 0 | T62: 1 | U62: 0 | V62: =SUM(S62:U62) -> 1
A63: =+A62+1 -> #REF! | B63: Morales Hernandez Joselyn Arceli | C63: Empacadora | D63: UNHESA | E63: 2825.1 | F63: 250 | G63: =+E63+F63 -> 3075.1 | H63: 0 | I63: 1 | J63: 0 | K63: =SUM(H63:J63) -> 1 | M63: Morales Hernandez Joselyn Arceli | N63: Empacadora | O63: UNHESA | P63: 2959.24 | Q63: 250 | R63: =+P63+Q63 -> 3209.24 | S63: 0 | T63: 1 | U63: 0 | V63: =SUM(S63:U63) -> 1
A64: =+A63+1 -> #REF! | B64: Méndez González Grecia Marbella | C64: Empacadora | D64: UNHESA | E64: 2825.1 | F64: 250 | G64: =+E64+F64 -> 3075.1 | H64: 0 | I64: 1 | J64: 0 | K64: =SUM(H64:J64) -> 1 | M64: Méndez González Grecia Marbella | N64: Empacadora | O64: UNHESA | P64: 2959.24 | Q64: 250 | R64: =+P64+Q64 -> 3209.24 | S64: 0 | T64: 1 | U64: 0 | V64: =SUM(S64:U64) -> 1
A65: =+A64+1 -> #REF! | B65: Sian Ortega Mildred Liliana | C65: Empacadora | D65: UNHESA | E65: 2825.1 | F65: 250 | G65: =+E65+F65 -> 3075.1 | H65: 0 | I65: 1 | J65: 0 | K65: =SUM(H65:J65) -> 1 | M65: Sian Ortega Mildred Liliana | N65: Empacadora | O65: UNHESA | P65: 2959.24 | Q65: 250 | R65: =+P65+Q65 -> 3209.24 | S65: 0 | T65: 1 | U65: 0 | V65: =SUM(S65:U65) -> 1
A66: =+A65+1 -> #REF! | B66: Ramirez Arcon Maria Nury | C66: Empacadora | D66: UNHESA | E66: 2825.1 | F66: 250 | G66: =+E66+F66 -> 3075.1 | H66: 0 | I66: 1 | J66: 0 | K66: =SUM(H66:J66) -> 1 | M66: Ramirez Arcon Maria Nury | N66: Empacadora | O66: UNHESA | P66: 2959.24 | Q66: 250 | R66: =+P66+Q66 -> 3209.24 | S66: 0 | T66: 1 | U66: 0 | V66: =SUM(S66:U66) -> 1
A67: =+A66+1 -> #REF! | B67: Ruche Bor José Antonio | C67: Auxiliar de Carga | D67: UNHESA | E67: 2825.1 | F67: 250 | G67: 3075.1 | H67: 0 | I67: 1 | J67: 0 | K67: =SUM(H67:J67) -> 1 | M67: Ruche Bor José Antonio | N67: Auxiliar de Carga | O67: UNHESA | P67: 2959.24 | Q67: 250 | R67: 3075.1 | S67: 0 | T67: 1 | U67: 0 | V67: =SUM(S67:U67) -> 1
C68: Total Unhesa | E68: =SUM(E51:E67) -> 48026.7 | F68: =SUM(F51:F67) -> 4250 | G68: =SUM(G51:G67) -> 52276.7 | N68: Total Unhesa | P68: =SUM(P51:P67) -> 50307.08 | Q68: =SUM(Q51:Q67) -> 4250 | R68: =SUM(R51:R67) -> 54288.8
B70: PROQUMA | M70: PROQUMA
A71: =A67+1 -> #REF! | B71: Yat Mo Marvin Obdulio | C71: Operario | D71: PROQUIMA | E71: 2825.1 | F71: 250 | G71: =+E71+F71 -> 3075.1 | H71: 1 | I71: 0 | J71: 0 | K71: =SUM(H71:J71) -> 1 | M71: Yat Mo Marvin Obdulio | N71: Operario | O71: PROQUIMA | P71: 2959.24 | Q71: 250 | R71: =+P71+Q71 -> 3209.24 | S71: 1 | T71: 0 | U71: 0 | V71: =SUM(S71:U71) -> 1
A72: =A71+1 -> #REF! | B72: Cisneros Escobar Walter De Jesus | C72: Operario | D72: PROQUIMA | E72: 2825.1 | F72: 250 | G72: =+E72+F72 -> 3075.1 | H72: 1 | I72: 0 | J72: 0 | K72: =SUM(H72:J72) -> 1 | M72: Cisneros Escobar Walter De Jesus | N72: Operario | O72: PROQUIMA | P72: 2959.24 | Q72: 250 | R72: =+P72+Q72 -> 3209.24 | S72: 1 | T72: 0 | U72: 0 | V72: =SUM(S72:U72) -> 1
A73: =A72+1 -> #REF! | B73: Samayoa Martir Mario Humberto | C73: Operario | D73: PROQUIMA | E73: 2825.1 | F73: 250 | G73: =+E73+F73 -> 3075.1 | H73: 1 | I73: 0 | J73: 0 | K73: =SUM(H73:J73) -> 1 | M73: Samayoa Martir Mario Humberto | N73: Operario | O73: PROQUIMA | P73: 2959.24 | Q73: 250 | R73: =+P73+Q73 -> 3209.24 | S73: 1 | T73: 0 | U73: 0 | V73: =SUM(S73:U73) -> 1
A74: =A73+1 -> #REF! | B74: Boror Pirir Jose Cruz | C74: Operario | D74: PROQUIMA | E74: 2825.1 | F74: 250 | G74: =+E74+F74 -> 3075.1 | H74: 1 | I74: 0 | J74: 0 | K74: =SUM(H74:J74) -> 1 | M74: Boror Pirir Jose Cruz | N74: Operario | O74: PROQUIMA | P74: 2959.24 | Q74: 250 | R74: =+P74+Q74 -> 3209.24 | S74: 1 | T74: 0 | U74: 0 | V74: =SUM(S74:U74) -> 1
A75: =A74+1 -> #REF! | B75: Cotzajay Lopez Aura Leticia | C75: Empacadora | D75: PROQUIMA | E75: 2825.1 | F75: 250 | G75: =+E75+F75 -> 3075.1 | H75: 1 | I75: 0 | J75: 0 | K75: =SUM(H75:J75) -> 1 | M75: Cotzajay Lopez Aura Leticia | N75: Empacadora | O75: PROQUIMA | P75: 2959.24 | Q75: 250 | R75: =+P75+Q75 -> 3209.24 | S75: 1 | T75: 0 | U75: 0 | V75: =SUM(S75:U75) -> 1
A76: =A75+1 -> #REF! | B76: Boror López Mayra Guadalupe | C76: Empacadora | D76: PROQUIMA | E76: 2825.1 | F76: 250 | G76: =+E76+F76 -> 3075.1 | H76: 1 | I76: 0 | J76: 0 | K76: =SUM(H76:J76) -> 1 | M76: Boror López Mayra Guadalupe | N76: Empacadora | O76: PROQUIMA | P76: 2959.24 | Q76: 250 | R76: =+P76+Q76 -> 3209.24 | S76: 1 | T76: 0 | U76: 0 | V76: =SUM(S76:U76) -> 1
A77: =A76+1 -> #REF! | B77: Choc Caal Augusto Adan | C77: Operario | D77: PROQUIMA | E77: 2825.1 | F77: =250 -> 250 | G77: =+E77+F77 -> 3075.1 | H77: 1 | I77: 0 | J77: 0 | K77: =SUM(H77:J77) -> 1 | M77: Choc Caal Augusto Adan | N77: Operario | O77: PROQUIMA | P77: 2959.24 | Q77: =250 -> 250 | R77: =+P77+Q77 -> 3209.24 | S77: 1 | T77: 0 | U77: 0 | V77: =SUM(S77:U77) -> 1
A78: 73 | B78: López Gerber Alexander | C78: Operario | D78: PROQUIMA | E78: 2825.1 | F78: =250 -> 250 | G78: =+E78+F78 -> 3075.1 | H78: 1 | I78: 0 | J78: 0 | K78: =SUM(H78:J78) -> 1 | M78: López Gerber Alexander | N78: Operario | O78: PROQUIMA | P78: 2959.24 | Q78: =250 -> 250 | R78: =+P78+Q78 -> 3209.24 | S78: 1 | T78: 0 | U78: 0 | V78: =SUM(S78:U78) -> 1
A79: =A78+1 -> 74 | B79: Quej Cau Jose Angel | C79: Operario | D79: PROQUIMA | E79: 2825.1 | F79: =250 -> 250 | G79: =+E79+F79 -> 3075.1 | H79: 1 | I79: 0 | J79: 0 | K79: =SUM(H79:J79) -> 1 | M79: Quej Cau Jose Angel | N79: Operario | O79: PROQUIMA | P79: 2959.24 | Q79: =250 -> 250 | R79: =+P79+Q79 -> 3209.24 | S79: 1 | T79: 0 | U79: 0 | V79: =SUM(S79:U79) -> 1
A80: =A79+1 -> 75 | B80: Contreras Vasquez Oscar Jose | C80: Operario | D80: PROQUIMA | E80: 2825.1 | F80: =250 -> 250 | G80: =+E80+F80 -> 3075.1 | H80: 1 | I80: 0 | J80: 0 | K80: =SUM(H80:J80) -> 1 | M80: Contreras Vasquez Oscar Jose | N80: Operario | O80: PROQUIMA | P80: 2959.24 | Q80: =250 -> 250 | R80: =+P80+Q80 -> 3209.24 | S80: 1 | T80: 0 | U80: 0 | V80: =SUM(S80:U80) -> 1
A81: =A80+1 -> 76 | B81: Ibañez Galicia Jonatan Alexander | C81: Operario | D81: PROQUIMA | E81: 2825.1 | F81: =250 -> 250 | G81: =+E81+F81 -> 3075.1 | H81: 1 | I81: 0 | J81: 0 | K81: =SUM(H81:J81) -> 1 | M81: Ibañez Galicia Jonatan Alexander | N81: Operario | O81: PROQUIMA | P81: 2959.24 | Q81: =250 -> 250 | R81: =+P81+Q81 -> 3209.24 | S81: 1 | T81: 0 | U81: 0 | V81: =SUM(S81:U81) -> 1
A82: =A81+1 -> 77 | B82: Cano Cano Nolberto | C82: Operario | D82: PROQUIMA | E82: 2825.1 | F82: =250 -> 250 | G82: =+E82+F82 -> 3075.1 | H82: 1 | I82: 0 | J82: 0 | K82: =SUM(H82:J82) -> 1 | M82: Cano Cano Nolberto | N82: Operario | O82: PROQUIMA | P82: 2959.24 | Q82: =250 -> 250 | R82: =+P82+Q82 -> 3209.24 | S82: 1 | T82: 0 | U82: 0 | V82: =SUM(S82:U82) -> 1
C83: Total Proquima | E83: =SUM(E71:E82) -> 33901.2 | F83: =SUM(F71:F82) -> 3000 | G83: =SUM(G71:G82) -> 36901.2 | N83: Total Proquima | P83: =SUM(P71:P82) -> 35510.88 | Q83: =SUM(Q71:Q82) -> 3000 | R83: =SUM(R71:R82) -> 38510.88
B85: PRODUCCION LIMPIEZA | M85: PRODUCCION LIMPIEZA
A86: =A82+1 -> 78 | B86: Aragón Coronado Guillermo Giovanni | C86: Auxiliar de Limpieza | D86: UNHESA | E86: 2825.1 | F86: 250 | G86: =+E86+F86 -> 3075.1 | H86: 0 | I86: 1 | J86: 0 | K86: =SUM(H86:J86) -> 1 | M86: Aragón Coronado Guillermo Giovanni | N86: Auxiliar de Limpieza | O86: UNHESA | P86: 2959.24 | Q86: 250 | R86: =+P86+Q86 -> 3209.24 | S86: 0 | T86: 1 | U86: 0 | V86: =SUM(S86:U86) -> 1
A87: =A86+1 -> 79 | B87: Arriaga García Melvin Rodrigo | C87: Auxiliar de Limpieza | D87: PROQUIMA | E87: 2825.1 | F87: =250 -> 250 | G87: =+E87+F87 -> 3075.1 | H87: 1 | I87: 0 | J87: 0 | K87: =SUM(H87:J87) -> 1 | M87: Arriaga García Melvin Rodrigo | N87: Auxiliar de Limpieza | O87: PROQUIMA | P87: 2959.24 | Q87: =250 -> 250 | R87: =+P87+Q87 -> 3209.24 | S87: 1 | T87: 0 | U87: 0 | V87: =SUM(S87:U87) -> 1
C88: Total Limpieza | E88: =SUM(E86:E87) -> 5650.2 | F88: =SUM(F86:F87) -> 500 | G88: =SUM(G86:G87) -> 6150.2 | N88: Total Limpieza | P88: =SUM(P86:P87) -> 5918.48 | Q88: =SUM(Q86:Q87) -> 500 | R88: =SUM(R86:R87) -> 6418.48
B89: LOGISTICA | M89: LOGISTICA
B90: BODEGA DE PRODUCTO TERMINADO | M90: BODEGA DE PRODUCTO TERMINADO
A91: =#REF!+1 -> #REF! | B91: Lajon Puac Osmen Gudiel | C91: Auxiliar de Bodega | D91: PROQUIMA | E91: 2831.25 | F91: 450 | G91: =+E91+F91 -> 3281.25 | H91: 0.6 | I91: 0.2 | J91: 0.2 | K91: =SUM(H91:J91) -> 1 | M91: Lajon Puac Osmen Gudiel | N91: Auxiliar de Bodega | O91: PROQUIMA | P91: 2959.24 | Q91: 450 | R91: =+P91+Q91 -> 3409.24 | S91: 0.6 | T91: 0.2 | U91: 0.2 | V91: =SUM(S91:U91) -> 1
A92: =A91+1 -> #REF! | B92: Turcios Carlos Alfredo | C92: Piloto | D92: PROQUIMA | E92: 2825.1 | F92: 1400 | G92: =+E92+F92 -> 4225.1 | H92: 1 | I92: 0 | J92: 0 | K92: =SUM(H92:J92) -> 1 | M92: Turcios Carlos Alfredo | N92: Piloto | O92: PROQUIMA | P92: 2959.24 | Q92: 1400 | R92: =+P92+Q92 -> 4359.24 | S92: 1 | T92: 0 | U92: 0 | V92: =SUM(S92:U92) -> 1
A93: =A92+1 -> #REF! | B93: Mendez Velasquez Hector Eduardo | C93: Auxiliar de Piloto | D93: PROQUIMA | E93: 2825.1 | F93: 750 | G93: =+E93+F93 -> 3575.1 | H93: 1 | I93: 0 | J93: 0 | K93: =SUM(H93:J93) -> 1 | M93: Mendez Velasquez Hector Eduardo | N93: Auxiliar de Piloto | O93: PROQUIMA | P93: 2959.24 | Q93: 750 | R93: =+P93+Q93 -> 3709.24 | S93: 1 | T93: 0 | U93: 0 | V93: =SUM(S93:U93) -> 1
A94: =A93+1 -> #REF! | B94: Orellana Gonzalez Francisco Javier | C94: Auxiliar de Piloto | D94: PROQUIMA | E94: 2825.1 | F94: 750 | G94: =+E94+F94 -> 3575.1 | H94: 1 | I94: 0 | J94: 0 | K94: =SUM(H94:J94) -> 1 | M94: Orellana Gonzalez Francisco Javier | N94: Auxiliar de Piloto | O94: PROQUIMA | P94: 2959.24 | Q94: 750 | R94: =+P94+Q94 -> 3709.24 | S94: 1 | T94: 0 | U94: 0 | V94: =SUM(S94:U94) -> 1
A95: =#REF!+1 -> #REF! | B95: Solano Garcia Jorge Alberto | C95: Piloto | D95: PROQUIMA | E95: 2825.1 | F95: =1150+250 -> 1400 | G95: =+E95+F95 -> 4225.1 | H95: 1 | I95: 0 | J95: 0 | K95: =SUM(H95:J95) -> 1 | M95: Solano Garcia Jorge Alberto | N95: Piloto | O95: PROQUIMA | P95: 2959.24 | Q95: =1150+250 -> 1400 | R95: =+P95+Q95 -> 4359.24 | S95: 1 | T95: 0 | U95: 0 | V95: =SUM(S95:U95) -> 1
A96: =A95+1 -> #REF! | B96: Rosales Soberaniz Benito Pedro Pablo | C96: Auxiliar de Bodega | D96: PROQUIMA | E96: 2825.1 | F96: =250+150 -> 400 | G96: =+E96+F96 -> 3225.1 | H96: 1 | I96: 0 | J96: 0 | K96: =SUM(H96:J96) -> 1 | M96: Rosales Soberaniz Benito Pedro Pablo | N96: Auxiliar de Bodega | O96: PROQUIMA | P96: 2959.24 | Q96: =250+150 -> 400 | R96: =+P96+Q96 -> 3359.24 | S96: 1 | T96: 0 | U96: 0 | V96: =SUM(S96:U96) -> 1
C97: Total BPT | E97: =SUM(E91:E96) -> 16956.75 | F97: =SUM(F91:F96) -> 5150 | G97: =SUM(G91:G96) -> 22106.75 | N97: Total BPT | P97: =SUM(P91:P96) -> 17755.44 | Q97: =SUM(Q91:Q96) -> 5150 | R97: =SUM(R91:R96) -> 22905.44
B98: BODEGA MATERIA PRIMA | M98: BODEGA MATERIA PRIMA
A99: =A96+1 -> #REF! | B99: Sanchez José Nelson | C99: Operador de montacargas | D99: PROQUIMA | E99: 2856.35 | F99: =500 -> 500 | G99: =+E99+F99 -> 3356.35 | H99: 0.4 | I99: 0.4 | J99: 0.2 | K99: =SUM(H99:J99) -> 1 | M99: Sanchez José Nelson | N99: Operador de montacargas | O99: PROQUIMA | P99: 2959.24 | Q99: =500 -> 500 | R99: =+P99+Q99 -> 3459.24 | S99: 0.4 | T99: 0.4 | U99: 0.2 | V99: =SUM(S99:U99) -> 1
A100: =+#REF!+1 -> #REF! | B100: Paz Pacheco Otoniel Adonias | C100: Auxiliar de Bodega | D100: UNHESA | E100: 2825.1 | F100: =250+150 -> 400 | G100: =+E100+F100 -> 3225.1 | H100: 0 | I100: 1 | J100: 0 | K100: =SUM(H100:J100) -> 1 | M100: Paz Pacheco Otoniel Adonias | N100: Auxiliar de Bodega | O100: UNHESA | P100: 2959.24 | Q100: =250+150 -> 400 | R100: =+P100+Q100 -> 3359.24 | S100: 0 | T100: 1 | U100: 0 | V100: =SUM(S100:U100) -> 1
A101: =+A100+1 -> #REF! | B101: Vasquez Rodriguez Mauro Trinidad | C101: Auxiliar de Bodega | D101: PROQUIMA | E101: 2825.1 | F101: 250 | G101: =+E101+F101 -> 3075.1 | H101: 0.6 | I101: 0.4 | J101: 0 | K101: =SUM(H101:J101) -> 1 | M101: Vasquez Rodriguez Mauro Trinidad | N101: Auxiliar de Bodega | O101: PROQUIMA | P101: 2959.24 | Q101: 250 | R101: =+P101+Q101 -> 3209.24 | S101: 0.6 | T101: 0.4 | U101: 0 | V101: =SUM(S101:U101) -> 1
A102: =+A101+1 -> #REF! | B102: Morales Ojeda Yefri Misael | C102: Operador de montacargas | D102: PROQUIMA | E102: 2856.35 | F102: =500 -> 500 | G102: =+E102+F102 -> 3356.35 | H102: 1 | I102: 0 | J102: 0 | K102: =SUM(H102:J102) -> 1 | M102: Morales Ojeda Yefri Misael | N102: Operador de montacargas | O102: PROQUIMA | P102: 2959.24 | Q102: =500 -> 500 | R102: =+P102+Q102 -> 3459.24 | S102: 1 | T102: 0 | U102: 0 | V102: =SUM(S102:U102) -> 1
A103: =+A102+1 -> #REF! | B103: Ramirez Perez Mynor Estuardo | C103: Auxiliar Bodega MP | D103: PROQUIMA | E103: 2825.1 | F103: 250 | G103: =+E103+F103 -> 3075.1 | H103: 1 | I103: 0 | J103: 0 | K103: =SUM(H103:J103) -> 1 | M103: Ramirez Perez Mynor Estuardo | N103: Auxiliar Bodega MP | O103: PROQUIMA | P103: 2959.24 | Q103: 250 | R103: =+P103+Q103 -> 3209.24 | S103: 1 | T103: 0 | U103: 0 | V103: =SUM(S103:U103) -> 1
C104: Total BMP | E104: =SUM(E99:E103) -> 14188 | F104: =SUM(F99:F103) -> 1900 | G104: =SUM(G99:G103) -> 16088 | N104: Total BMP | P104: =SUM(P99:P103) -> 14796.2 | Q104: =SUM(Q99:Q103) -> 1900 | R104: =SUM(R99:R103) -> 16696.2
C105: Total Logística | E105: =SUM(E97+E104) -> 31144.75 | F105: =SUM(F97+F104) -> 7050 | G105: =SUM(G97+G104) -> 38194.75 | N105: Total Logística | P105: =SUM(P97+P104) -> 32551.64 | Q105: =SUM(Q97+Q104) -> 7050 | R105: =SUM(R97+R104) -> 39601.64
B106: MANTENIMIENTO | K106: =SUM(H106:J106) -> 0 | M106: MANTENIMIENTO | V106: =SUM(S106:U106) -> 0
A107: =+#REF!+1 -> #REF! | B107: Morales Hernandez Ausencio | C107: Auxiliar de Mantenimiento | D107: UNHESA | E107: 2825.1 | F107: 250 | G107: =+E107+F107 -> 3075.1 | H107: 0.5 | I107: 0.25 | J107: 0.25 | K107: =SUM(H107:J107) -> 1 | M107: Morales Hernandez Ausencio | N107: Auxiliar de Mantenimiento | O107: UNHESA | P107: 2959.24 | Q107: 250 | R107: =+P107+Q107 -> 3209.24 | S107: 0.5 | T107: 0.25 | U107: 0.25 | V107: =SUM(S107:U107) -> 1
C108: TotaL Mantenimiento | E108: =SUM(E107:E107) -> 2825.1 | F108: =SUM(F107:F107) -> 250 | G108: =SUM(G107:G107) -> 3075.1 | N108: TotaL Mantenimiento | P108: =SUM(P107:P107) -> 2959.24 | Q108: =SUM(Q107:Q107) -> 250 | R108: =SUM(R107:R107) -> 3209.24
C109: TOTAL AREA OPERACIONES | N109: TOTAL AREA OPERACIONES | P109: =SUM(+P49+P68+P83+P88+P97+P104+P108) -> 130206.56 | Q109: =SUM(+Q49+Q68+Q83+Q88+Q97+Q104+Q108) -> 15300 | R109: =SUM(+R49+R68+R83+R88+R97+R104+R108) -> 145238.28
B111: AREA COMERCIALIZACIÓN | M111: AREA COMERCIALIZACIÓN
...

Sheet Hoja2
A2: PARQUEOS | E2: Nombre | F2: Puesto | G2: Empresa Real | H2: Renovación Examenes | I2: Tarjetas de Salud
A3: YANDIRA | B3: 120 | E3: Lopez Orellana Genesis Alejandra | F3: Asistente de Control de Calidad | G3: UNHESA | I3: 175
A4: RONY | B4: 240 | E4: Lopez Rivera Lourdes Janeth | F4: Asistente de Control de Calidad | G4: UNHESA | I4: 87.5
A5: GABRIELA | B5: 240 | E5: Garrido Aguilar Maria Elena | F5: Empacadora de Sobres | G5: UNHESA | H5: 150
B6: =SUM(B3:B5) -> 600 | E6: Boche Mendez Olga Veronica | F6: Empacadora de Sobres | G6: UNHESA | H6: 150
E7: Sontay Cifuentes Leydi Rosivel | F7: Linea de Botes | G7: UNHESA | H7: 150
E8: Samora Sacul Yocelin Paola | F8: Linea de Botes | G8: UNHESA | I8: 175
A9: SEGUROS | E9: Cisneros Lopez Marvin Daniel | F9: Operario Sobres | G9: UNHESA | H9: 150
A10: RUTH | B10: 60 | E10: Guerra Tobar Melvin Esleiter | F10: Operario Sobres | G10: UNHESA | I10: 175
A11: SERGIO HUERTAS | B11: 125 | E11: Vasquez Bamaca Walter Leonidas | F11: Operario Sobres | G11: UNHESA | I11: 175
A12: RONY | B12: 120 | E12: Gomez Martinez Sandor Felipe | F12: Operador | G12: UNHESA | I12: 175
A13: MARVIN CISNEROS | B13: 55 | E13: Ramirez Vasquez Audelio | F13: Operario | G13: UNHESA | I13: 175
B14: =+B10+B11+B12+B13 -> 360 | E14: Garcia Sarceño Mayvin Armando | F14: Operario | G14: UNHESA | I14: 175
E15: Salvatierra de Leon Jakeline Marisela | F15: Empacadora | G15: UNHESA | I15: 175
E16: Hernandez Aquino Wendy Lizbeth | F16: Empacadora | G16: UNHESA | I16: 175
A17: ERROR OTONIEL | B17: 39.29 | E17: Morales Hernandez Joselyn Arceli | F17: Empacadora | G17: UNHESA | I17: 175
E18: Ruche Bor José Antonio | F18: Auxiliar de Carga | G18: UNHESA | I18: 175
E19: Aragón Coronado Guillermo Giovanni | F19: Auxiliar de Limpieza | G19: UNHESA | H19: 150
E20: Rodas Morales Rony Alfonso | F20: Coordinador bodegas | G20: UNHESA | H20: 150
A21: DEUDA RONY | B21: 500 | E21: Chacón Morales Katheryne Mariannela | F21: Encargada de Bodega PT | G21: UNHESA | H21: 150
E22: Solis Dominguez Angel Gabriel | F22: Facturador | G22: UNHESA | I22: 175
A23: DESCUENTOS JURIDICOS | E23: Paz Pacheco Otoniel Adonias | F23: Auxiliar de Bodega | G23: UNHESA | H23: 150
A24: JOSE RUCHE | B24: 1076.28 | E24: Morales Hernandez Ausencio | F24: Auxiliar de Mantenimiento | G24: UNHESA | H24: 150
A25: WENDY CHAVEZ | B25: 1076.29 | E25: Si Mes Pablo | F25: Operario Liquidos | G25: UNHESA | H25: 150
B26: =SUM(B24:B25) -> 2152.57 | E26: Tot Paau David Antonio | F26: Operario Liquidos | G26: UNHESA | H26: 150
E27: Xol Botzoc Hermelindo | F27: Operario Liquidos | G27: UNHESA | H27: 150
E28: Chávez Velásquez Wendy Lorena | F28: Empacadora Liquidos | G28: UNHESA | I28: 175
A29: TARJETAS DE SALUD | B29: =+J33 -> 4812.5 | E29: Gregorio Rodríguez Sulma Maribel | F29: Empacadora Liquidos | G29: UNHESA | I29: 175
E30: Velásquez López Claudia Carolina | F30: Empacadora Liquidos | G30: UNHESA | I30: 175
E31: Ixcoy de Quevedo Blanca Francisca | F31: Empacadora Liquidos | G31: UNHESA | H31: 150
A32: PRODUCTO | B32: 82.5 | E32: Toz Putul Martin | F32: Operario Liquidos | G32: UNHESA | H32: 150
H33: =SUM(H3:H32) -> 2100 | I33: =SUM(I3:I32) -> 2712.5 | J33: =+H33+I33 -> 4812.5
A34: TOTAL INTEGRACION COLUMNA | B34: =+B6+B14+B17+B21+B26+B29+J39+B32 -> 8546.86
B37: 8546.86 | C37: =+B37-B34 -> 0

Sheet distribucion
C1: 1 | D1: 2 | E1: 3 | F1: 4 | G1: 5 | H1: 6 | I1: 7 | J1: 8 | K1: 9 | L1: 10 | M1: 11 | N1: 12 | O1: 13 | P1: 14 | Q1: 15 | R1: 16 | S1: 17 | T1: 18 | U1: 19 | V1: 20 | W1: 21 | X1: 22 | Y1: 23 | Z1: 24 | AA1: 25 | AB1: 26 | AC1: 27 | AD1: 28 | AE1: 29 | AF1: 30 | AG1: 31 | AH1: 32 | AI1: 33 | AJ1: 34 | AK1: 35 | AL1: 36 | AM1: 37 | AN1: 38 | AO1: 39 | AP1: 40 | AQ1: 41 | AR1: 42 | AS1: 43 | AT1: 44 | AU1: 45 | AV1: 46 | AW1: 47 | AX1: 48 | AY1: 49 | AZ1: 50 | BA1: 51 | BB1: 52 | BC1: 53 | BD1: 54 | BE1: 55 | BF1: 56 | BG1: 57 | BH1: 58 | BI1: 59 | BJ1: 60 | BK1: 61 | BL1: 62 | BM1: 63 | BN1: 64 | BO1: 65 | BP1: 66 | BQ1: 67 | BR1: 68 | BS1: 69 | BT1: 70 | BU1: 71 | BV1: 72 | BW1: 73 | BX1: 74 | BY1: 75 | BZ1: 76 | CA1: 77 | CB1: 78 | CC1: 79 | CD1: 80 | CE1: 81 | CF1: 82 | CG1: 83 | CH1: 84 | CI1: 85 | CJ1: 86 | CK1: 87 | CL1: 88 | CM1: 89 | CN1: 90 | CO1: 91 | CP1: 92 | CQ1: 93 | CR1: 94 | CS1: 95 | CT1: 96 | CU1: 97 | CV1: 98 | CW1: 99 | CX1: 100 | CY1: 101 | CZ1: 102 | DA1: 103 | DB1: 104 | DC1: 105 | DD1: 106 | DE1: 107 | DF1: 108 | DG1: 109 | DH1: 110 | DI1: 111 | DJ1: 112 | DK1: 113 | DL1: 114 | DM1: 115 | DN1: 116 | DO1: 117 | DP1: 118 | DQ1: 119 | DR1: 120 | DS1: 121 | DT1: 122 | DU1: 123 | DV1: 124 | DW1: 125 | DX1: 126 | DY1: 127 | DZ1: 128 | EA1: 129 | EB1: 130 | EC1: 131 | ED1: 132 | EE1: 133 | EF1: 134 | EG1: 135 | EH1: 136 | EI1: 137 | EJ1: 138 | EK1: 139 | EL1: 140 | EM1: 141 | EN1: 142 | EO1: 143 | EP1: 144 | EQ1: 145 | ER1: 146 | ES1: 147 | ET1: 148 | EU1: 149 | EV1: 150 | EW1: 151 | EX1: 152 | EY1: 153 | EZ1: 154 | FA1: 155 | FB1: 156 | FC1: 157 | FD1: 158 | FE1: 159 | FF1: 160
C2: DISTRIBUCION DE PERSONAL Y COSTO POR EMPRESA
C3: NOMINA MES DE: MAYO 2026 1ERA QUINCENA | N3: .
AW4: NOMINAS SEGÚN DISTRIBUCION REAL | CR4: NOMINAS SEGÚN DISTRIBUCION CONTABILIDAD | FR4: QUINCENA: 2 MES: 1
F5: 5 | G5: 6 | Q5: HORAS EXTRAS PROQUIMA | U5: HORAS EXTRAS UNHESA | Y5: HORAS EXTRAS UNHESA LIQUIDOS | AC5: HORAS EXTRAS ECONACIONAL | AG5: HORAS EXTRAS PROQUIMA MAQUILA | AK5: Otros Ingresos | AP5: Comisiones | AW5: PROQUIMA | BF5: UNHESA | BO5: UNHESA LIQUIDOS | BX5: ECONACIONAL | CG5: ECOMEZCLAS | CR5: PROQUIMA | DA5: UNHESA | DJ5: UNHESA LIQUIDOS | DS5: ECONACIONAL | EB5: ECOMEZCLAS | FG5: DISTRIBUCION REAL | FR5: 1
E6: DISTRIBUCION DE EMPLEADOS | Q6: H.E. Simples | R6: H.E. Simples | S6: H.E. Dobles | T6: H.E. Dobles | U6: H.E. Simples | V6: H.E. Simples | W6: H.E. Dobles | X6: H.E. Dobles | Y6: H.E. Simples | Z6: H.E. Simples | AA6: H.E. Dobles | AB6: H.E. Dobles | AC6: H.E. Simples | AD6: H.E. Simples | AE6: H.E. Dobles | AF6: H.E. Dobles | AG6: H.E. Simples | AH6: H.E. Simples | AI6: H.E. Dobles | AJ6: H.E. Dobles | AK6: Proquima | AL6: Unhesa | AM6: Calidul | AN6: Econacional | AO6: Cleartec | AP6: Proquima | AQ6: Unhesa | AR6: Calidul | AS6: Econacional | AT6: Cleartec | AU6: Otrros ingresos | AV6: 0 | AW6: Salario | AX6: Bono | AY6: cantidad | AZ6: Hrs. Extra | BA6: cantidad | BB6: Hrs. Extra | BC6: Comis / | BD6: Cuota | BE6: Total | BF6: Salario | BG6: Bono | BH6: cantidad | BI6: Hrs. Extra | BJ6: cantidad | BK6: Hrs. Extra | BL6: Comis / | BM6: Cuota | BN6: Total | BO6: Salario | BP6: Bono | BQ6: cantidad | BR6: Hrs. Extra | BS6: cantidad | BT6: Hrs. Extra | BU6: Comis / | BV6: Cuota | BW6: Total | BX6: Salario | BY6: Bono | BZ6: cantidad | CA6: Hrs. Extra | CB6: cantidad | CC6: Hrs. Extra | CD6: Comis / | CE6: Cuota | CF6: Total | CG6: Salario | CH6: Bono | CI6: cantidad | CJ6: Hrs. Extra | CK6: cantidad | CL6: Hrs. Extra | CM6: Comis / | CN6: Cuota | CO6: Total | CQ6: Nueva | CR6: Salario | CS6: Bono | CT6: cantidad | CU6: Hrs. Extra | CV6: cantidad | CW6: Hrs. Extra | CX6: Comis / | CY6: Cuota | CZ6: Total | DA6: Salario | DB6: Bono | DC6: cantidad | DD6: Hrs. Extra | DE6: cantidad | DF6: Hrs. Extra | DG6: Comis / | DH6: Cuota | DI6: Total | DJ6: Salario | DK6: Bono | DL6: cantidad | DM6: Hrs. Extra | DN6: cantidad | DO6: Hrs. Extra | DP6: Comis / | DQ6: Cuota | DR6: Total | DS6: Salario | DT6: Bono | DU6: cantidad | DV6: Hrs. Extra | DW6: cantidad | DX6: Hrs. Extra | DY6: Comis / | DZ6: Cuota | EA6: Total | EB6: Salario | EC6: Bono | ED6: cantidad | EE6: Hrs. Extra | EF6: cantidad | EG6: Hrs. Extra | EH6: Comis / | EI6: Cuota | EJ6: Total | EL6: EGRESOS MENSUALES | EW6: EGRESOS | FG6: % | FH6: % | FI6: % | FJ6: % | FK6: % | FL6: %
A7: Código División | C7: Nombre | D7: Puesto | E7: Empresa Real | F7: Salario Ordinario | G7: Bono Decreto | H7: Total | I7: Días Laborados | J7: % Proquima | K7: % Unhesa | L7: % Unhesa Liq. | M7: % Econacional | N7: % Ecomezclas | O7: Total % Distribución | P7: Observaciones | Q7: Cantidad | R7: Valor | S7: Cantidad | T7: Valor | U7: Cantidad | V7: Valor | W7: Cantidad | X7: Valor | Y7: Cantidad | Z7: Valor | AA7: Cantidad | AB7: Valor | AC7: Cantidad | AD7: Valor | AE7: Cantidad | AF7: Valor | AG7: Cantidad | AH7: Valor | AI7: Cantidad | AJ7: Valor | AW7: Ordinario | AX7: Decreto | AY7: simples | AZ7: simples | BA7: dobles | BB7: dobles | BC7: Otros | BD7: Patronal | BF7: Ordinario | BG7: Decreto | BH7: simples | BI7: simples | BJ7: dobles | BK7: dobles | BL7: Otros | BM7: Patronal | BO7: Ordinario | BP7: Decreto | BQ7: simples | BR7: simples | BS7: dobles | BT7: dobles | BU7: Otros | BV7: Patronal | BX7: Ordinario | BY7: Decreto | BZ7: simples | CA7: simples | CB7: dobles | CC7: dobles | CD7: Otros | CE7: Patronal | CG7: Ordinario | CH7: Decreto | CI7: simples | CJ7: simples | CK7: dobles | CL7: dobles | CM7: Otros | CN7: Patronal | CQ7: Empresa | CR7: Ordinario | CS7: Decreto | CT7: simples | CU7: simples | CV7: dobles | CW7: dobles | CX7: Otros | CY7: Patronal | DA7: Ordinario | DB7: Decreto | DC7: simples | DD7: simples | DE7: dobles | DF7: dobles | DG7: Otros | DH7: Patronal | DJ7: Ordinario | DK7: Decreto | DL7: simples | DM7: simples | DN7: dobles | DO7: dobles | DP7: Otros | DQ7: Patronal | DS7: Ordinario | DT7: Decreto | DU7: simples | DV7: simples | DW7: dobles | DX7: dobles | DY7: Otros | DZ7: Patronal | EB7: Ordinario | EC7: Decreto | ED7: simples | EE7: simples | EF7: dobles | EG7: dobles | EH7: Otros | EI7: Patronal | EL7: ISR | EM7: BANCOS | EN7: CELULAR | EO7: CAFETERIA | EP7: DESCUENTO producto | EQ7: SEGURO/ tarjeta de salud/boleto de ornato | ER7: Otros Descuentos | ES7: CALZADO | ET7: UNIFORME | EU7: TOTAL EGRESOS Bol Ornato, Seguro, Otros | EW7: ISR | EX7: BANCOS | EY7: CELULAR | EZ7: CAFETERIA | FA7: DESCUENTO PRODUCTO | FB7: SEGURO/BOLETO DE ORNATO | FC7: Otros Descuentos | FD7: CALZADO | FE7: UNIFORME | FF7: OTROS EGRESOS | FG7: % Proquima | FH7: % Unhesa | FI7: % Unhesa Liq. | FJ7: % Econacional | FK7: % Ecomezclas | FL7: Total % Distribución
C8: AREA ADMINISTRATIVA | FJ8: cional
C9: PRESIDENCIA
A10: 101020 | B10: 1 | C10: Estrada Robles Victor Gerardo | D10: Presidente | E10: UNHESA | F10: 5000 | G10: =15000+1505.89 -> 16505.89 | H10: =+F10+G10 -> 21505.89 | I10: 15 | J10: 0 | K10: 1 | L10: 0 | M10: 0 | N10: 0 | O10: =SUM(J10:N10) -> 1 | R10: =($F10/30/8*1.5)*Q10 -> 0 | T10: 0 | V10: =($F10/30/8*1.5)*U10 -> 0 | X10: =($F10/30/8*2)*W10 -> 0 | Z10: =(($F10/30/8)*1.5)*Y10 -> 0 | AB10: =(($F10/30/8)*2)*AA10 -> 0 | AD10: =(($F10/30/8)*1.5)*AC10 -> 0 | AF10: =(($F10/30/8)*2)*AE10 -> 0 | AH10: =(($F10/30/8)*1.5)*AG10 -> 0 | AJ10: =(($F10/30/8)*2)*AI10 -> 0 | AW10: =(($F10/30)*$I10)*$J10 -> 0 | AX10: =((G10/30)*I10)*$J10 -> 0 | AY10: =Q10 -> 0 | AZ10: =R10 -> 0 | BA10: =S10 -> 0 | BB10: =T10 -> 0 | BC10: =AK10+AP10 -> 0 | BD10: =(AW10+AZ10+BB10+BC10)*0.1267 -> 0 | BE10: =SUM(AW10:BD10)-AY10-BA10 -> 0 | BF10: =(($F10/30)*$I10)*$K10 -> 2500 | BG10: =(($G10/30)*$I10)*$K10 -> 8252.945 | BH10: =U10 -> 0 | BI10: =V10 -> 0 | BJ10: =W10 -> 0 | BK10: =X10 -> 0 | BL10: =AL10+AQ10 -> 0 | BM10: =(+BF10+BI10+BK10+BL10)*0.1267 -> 316.75 | BN10: =SUM(BF10:BM10)-BH10-BJ10 -> 11069.695 | BO10: =(($F10/30)*$I10)*$L10 -> 0 | BP10: =(($G10/30)*$I10)*$L10 -> 0 | BQ10: =Y10 -> 0 | BR10: =Z10 -> 0 | BS10: =AA10 -> 0 | BT10: =AB10 -> 0 | BU10: =AM10+AR10 -> 0 | BV10: =(BO10+BR10+BT10+BU10)*0.1267 -> 0 | BW10: =SUM(BO10:BV10)-BQ10-BS10 -> 0 | BX10: =(($F10/30)*$I10)*$M10 -> 0 | BY10: =(($G10/30)*$I10)*$M10 -> 0 | BZ10: =AC10 -> 0 | CA10: =AD10 -> 0 | CB10: =AE10 -> 0 | CC10: =AF10 -> 0 | CD10: =AN10+AS10 -> 0 | CE10: =(BX10+CA10+CC10)*0.1267 -> 0 | CF10: =SUM(BX10:CE10)-BZ10-CB10 -> 0 | CG10: =(($F10/30)*$I10)*N10 -> 0 | CH10: =(($G10/30)*$I10)*$N10 -> 0 | CI10: =+AG10 -> 0 | CJ10: =AH10 -> 0 | CK10: =AI10 -> 0 | CL10: =AJ10 -> 0 | CM10: =AO10+AT10 -> 0 | CN10: =(CG10+CJ10+CL10)*0.1267 -> 0 | CO10: =SUM(CG10:CN10)-CI10-CK10 -> 0 | CQ10: UNHESA | CR10: =IF($CQ10="PROQUIMA",$AW10+$BF10+$BO10+$BX10+$CG10,0) -> 0 | CS10: =IF($CQ10="PROQUIMA",$AX10+$BG10+$BP10+$BY10+$CH10,0) -> 0 | CT10: =IF($CQ10="PROQUIMA",$AY10+$BH10+$BQ10+$BZ10+$CI10,0) -> 0 | CU10: =IF($CQ10="PROQUIMA",$AZ10+$BI10+$BR10+$CA10+$CJ10,0) -> 0 | CV10: =IF($CQ10="PROQUIMA",$BA10+$BJ10+$BS10+$CB10+$CK10,0) -> 0 | CW10: =IF($CQ10="PROQUIMA",$BB10+$BK10+$BT10+$CC10+$CL10,0) -> 0 | CX10: =IF($CQ10="PROQUIMA",$BC10+$BL10+$BU10+$CD10+$CM10,0) -> 0 | CY10: =IF($CQ10="PROQUIMA",$BD10+$BM10+$BV10+$CE10+CN10,0) -> 0 | CZ10: =SUM(CR10:CY10)-CT10-CV10 -> 0 | DA10: =IF($CQ10="UNHESA",$AW10+$BF10+$BO10+$BX10+$CG10,0) -> 2500 | DB10: =IF($CQ10="UNHESA",$AX10+$BG10+$BP10+$BY10+$CH10,0) -> 8252.945 | DC10: =IF($CQ10="UNHESA",$AY10+$BH10+$BQ10+$BZ10+$CI10,0) -> 0 | DD10: =IF($CQ10="UNHESA",$AZ10+$BI10+$BR10+$CA10+$CJ10,0) -> 0 | DE10: =IF($CQ10="UNHESA",$BA10+$BJ10+$BS10+$CB10+$CK10,0) -> 0 | DF10: =IF($CQ10="UNHESA",$BB10+$BK10+$BT10+$CC10+$CL10,0) -> 0 | DG10: =IF($CQ10="UNHESA",$BC10+$BL10+$BU10+$CD10+$CM10,0) -> 0 | DH10: =IF($CQ10="UNHESA",$BD10+$BM10+$BV10+$CE10+$CN10,0) -> 316.75 | DI10: =SUM(DA10:DH10)-DC10-DE10 -> 11069.695 | EL10: 1776.01 | EM10: 3232.32 | EU10: =+EP10+EQ10+ER10 -> 0 | EW10: =IF($I10<=15,EL10/2,EL10) -> 888.005 | EX10: =IF($I10<=15,EM10/2,EM10) -> 1616.16 | EY10: =IF($I10<=15,EN10/2,EN10) -> 0 | EZ10: =IF($I10<=15,EO10/2,EO10) -> 0 | FA10: =IF($I10<=15,EP10/2,EP10) -> 0 | FB10: =IF($I10<=15,EQ10/2,EQ10) -> 0 | FC10: =IF($I10<=15,ER10/2,ER10) -> 0 | FD10: =IF($I10<=15,ES10/2,ES10) -> 0 | ... FF10: =IF($I10<=15,EU10/2,EU10) -> 0 | FG10: 0 | FH10: 1 | FI10: 0 | FJ10: 0 | FK10: 0 | FL10: 1 | FN10: =(((F10/30/8)*1.5)*(Q10+U10+Y10))-(AZ10+BI10+BR10) -> 0 | FO10: =(((F10/30/8)*2)*(S10+W10+AA10))-(BB10+BK10+BT10) -> 0 | FP10: =(SUM(AW10:CF10))-(SUM(CR10:DR10)) -> 0 | FQ10: =(F10/30*I10)-(CR10+DA10+DJ10) -> 0 | FR10: =(SUM(EL10:EU10))-((SUM(EW10:FF10))*$FR$5) -> 2504.165
A11: 101020 | D11: Total presidencia | F11: =+F10 -> 5000 | G11: =+G10 -> 16505.89 | H11: =+H10 -> 21505.89 | Q11: =+Q10 -> 0 | R11: =+R10 -> 0 | S11: =+S10 -> 0 | T11: =+T10 -> 0 | U11: =+U10 -> 0 | V11: =+V10 -> 0 | W11: =+W10 -> 0 | X11: =+X10 -> 0 | ... FF11: =+FF10 -> 0
A13: 101010 | B13: 2 | C13: Estrada Robles Victor Gerardo1 | D13: Gerente General | E13: PROQUIMA | F13: 5000 | G13: 10000 | H13: =+F13+G13 -> 15000 | I13: 0 | J13: 1 | K13: 0 | L13: 0 | M13: 0 | N13: 0 | O13: =SUM(J13:N13) -> 1 | R13: =($F13/30/8*1.5)*Q13 -> 0 | T13: =($F13/30/8*2)*S13 -> 0 | V13: =($F13/30/8*1.5)*U13 -> 0 | X13: =($F13/30/8*2)*W13 -> 0 | Z13: =(($F13/30/8)*1.5)*Y13 -> 0 | AB13: =(($F13/30/8)*2)*AA13 -> 0 | AD13: =(($F13/30/8)*1.5)*AC13 -> 0 | AF13: =(($F13/30/8)*2)*AE13 -> 0 | AH13: =(($F13/30/8)*1.5)*AG13 -> 0 | AJ13: =(($F13/30/8)*2)*AI13 -> 0 | AW13: =(($F13/30)*$I13)*$J13 -> 0 | AX13: =(($G13/30)*$I13)*$J13 -> 0 | AY13: =Q13 -> 0 | AZ13: =R13 -> 0 | BA13: =S13 -> 0 | BB13: =T13 -> 0 | BC13: =AK13+AP13 -> 0 | BD13: =(AW13+AZ13+BB13+BC13)*0.1267 -> 0 | BE13: =SUM(AW13:BD13)-AY13-BA13 -> 0 | BF13: =(($F13/30)*$I13)*$K13 -> 0 | BG13: =(($G13/30)*$I13)*$K13 -> 0 | BH13: =U13 -> 0 | BI13: =V13 -> 0 | BJ13: =W13 -> 0 | BK13: =X13 -> 0 | BL13: =AL13+AQ13 -> 0 | BM13: =(+BF13+BI13+BK13+BL13)*0.1267 -> 0 | BN13: =SUM(BF13:BM13)-BH13-BJ13 -> 0 | BO13: =(($F13/30)*$I13)*$L13 -> 0 | BP13: =(($G13/30)*$I13)*$L13 -> 0 | BQ13: =Y13 -> 0 | BR13: =Z13 -> 0 | BS13: =AA13 -> 0 | BT13: =AB13 -> 0 | BU13: =AM13+AR13 -> 0 | BV13: =(BO13+BR13+BT13+BU13)*0.1267 -> 0 | BW13: =SUM(BO13:BV13)-BQ13-BS13 -> 0 | BX13: =(($F13/30)*$I13)*$M13 -> 0 | BY13: =(($G13/30)*$I13)*$M13 -> 0 | BZ13: =AC13 -> 0 | CA13: =AD13 -> 0 | CB13: =AE13 -> 0 | CC13: =AF13 -> 0 | CD13: =AN13+AS13 -> 0 | CE13: =(BX13+CA13+CC13)*0.1267 -> 0 | CF13: =SUM(BX13:CE13)-BZ13-CB13 -> 0 | CG13: =(($F13/30)*$I13)*N13 -> 0 | CH13: =(($G13/30)*$I13)*$N13 -> 0 | CI13: =+AG13 -> 0 | CJ13: =AH13 -> 0 | CK13: =AI13 -> 0 | CL13: =AJ13 -> 0 | CM13: =AO13+AT13 -> 0 | CN13: =(CG13+CJ13+CL13)*0.1267 -> 0 | CO13: =SUM(CG13:CN13)-CI13-CK13 -> 0 | CQ13: PROQUIMA | CR13: =IF($CQ13="PROQUIMA",$AW13+$BF13+$BO13+$BX13+$CG13,0) -> 0 | CS13: =IF($CQ13="PROQUIMA",$AX13+$BG13+$BP13+$BY13+$CH13,0) -> 0 | CT13: =IF($CQ13="PROQUIMA",$AY13+$BH13+$BQ13+$BZ13+$CI13,0) -> 0 | CU13: =IF($CQ13="PROQUIMA",$AZ13+$BI13+$BR13+$CA13+$CJ13,0) -> 0 | CV13: =IF($CQ13="PROQUIMA",$BA13+$BJ13+$BS13+$CB13+$CK13,0) -> 0 | CW13: =IF($CQ13="PROQUIMA",$BB13+$BK13+$BT13+$CC13+$CL13,0) -> 0 | CX13: =IF($CQ13="PROQUIMA",$BC13+$BL13+$BU13+$CD13+$CM13,0) -> 0 | CY13: =IF($CQ13="PROQUIMA",$BD13+$BM13+$BV13+$CE13+CN13,0) -> 0 | CZ13: =SUM(CR13:CY13)-CT13-CV13 -> 0 | DA13: =IF($CQ13="UNHESA",$AW13+$BF13+$BO13+$BX13+$CG13,0) -> 0 | DB13: =IF($CQ13="UNHESA",$AX13+$BG13+$BP13+$BY13+$CH13,0) -> 0 | DC13: =IF($CQ13="UNHESA",$AY13+$BH13+$BQ13+$BZ13+$CI13,0) -> 0 | DD13: =IF($CQ13="UNHESA",$AZ13+$BI13+$BR13+$CA13+$CJ13,0) -> 0 | DE13: =IF($CQ13="UNHESA",$BA13+$BJ13+$BS13+$CB13+$CK13,0) -> 0 | DF13: =IF($CQ13="UNHESA",$BB13+$BK13+$BT13+$CC13+$CL13,0) -> 0 | DG13: =IF($CQ13="UNHESA",$BC13+$BL13+$BU13+$CD13+$CM13,0) -> 0 | DH13: =IF($CQ13="UNHESA",$BD13+$BM13+$BV13+$CE13+$CN13,0) -> 0 | DI13: =SUM(DA13:DH13)-DC13-DE13 -> 0 | EU13: =+EP13+EQ13+ER13 -> 0 | EW13: =IF($I13<=15,EL13/2,EL13) -> 0 | EX13: =IF($I13<=15,EM13/2,EM13) -> 0 | EY13: =IF($I13<=15,EN13/2,EN13) -> 0 | EZ13: =IF($I13<=15,EO13/2,EO13) -> 0 | FA13: =IF($I13<=15,EP13/2,EP13) -> 0 | FB13: =IF($I13<=15,EQ13/2,EQ13) -> 0 | FC13: =IF($I13<=15,ER13/2,ER13) -> 0 | FD13: =IF($I13<=15,ES13/2,ES13) -> 0 | ... FF13: =IF($I13<=15,EU13/2,EU13) -> 0 | FN13: =(((F13/30/8)*1.5)*(Q13+U13+Y13))-(AZ13+BI13+BR13) -> 0 | FO13: =(((F13/30/8)*2)*(S13+W13+AA13))-(BB13+BK13+BT13) -> 0 | FP13: =(SUM(AW13:CF13))-(SUM(CR13:DR13)) -> 0 | FQ13: =(F13/30*I13)-(CR13+DA13+DJ13) -> 0 | FR13: =(SUM(EL13:EU13))-((SUM(EW13:FF13))*$FR$5) -> 0
A14: 101010 | D14: total Gerencia General | F14: =+F13 -> 5000 | G14: =+G13 -> 10000 | H14: =+H13 -> 15000 | Q14: =+Q13 -> 0 | R14: =+R13 -> 0 | S14: =+S13 -> 0 | T14: =+T13 -> 0 | U14: =+U13 -> 0 | V14: =+V13 -> 0 | W14: =+W13 -> 0 | X14: =+X13 -> 0 | ... FF14: =+FF13 -> 0
A15: 101030 | C15: Asesoria
A16: 101030 | B16: 3 | C16: Estrada Robles Juan Pablo | D16: Asesor | E16: PROQUIMA | F16: 5000 | G16: 10000 | H16: =+F16+G16 -> 15000 | I16: 15 | J16: 1 | K16: 0 | L16: 0 | M16: 0 | N16: 0 | O16: =SUM(J16:N16) -> 1 | R16: =($F16/30/8*1.5)*Q16 -> 0 | T16: =($F16/30/8*2)*S16 -> 0 | V16: =($F16/30/8*1.5)*U16 -> 0 | X16: =($F16/30/8*2)*W16 -> 0 | Z16: =(($F16/30/8)*1.5)*Y16 -> 0 | AB16: =(($F16/30/8)*2)*AA16 -> 0 | AD16: =(($F16/30/8)*1.5)*AC16 -> 0 | AF16: =(($F16/30/8)*2)*AE16 -> 0 | AH16: =(($F16/30/8)*1.5)*AG16 -> 0 | AJ16: =(($F16/30/8)*2)*AI16 -> 0 | AW16: =(($F16/30)*$I16)*$J16 -> 2500 | AX16: =(($G16/30)*$I16)*$J16 -> 5000 | AY16: =Q16 -> 0 | AZ16: =R16 -> 0 | BA16: =S16 -> 0 | BB16: =T16 -> 0 | BC16: =AK16+AP16 -> 0 | BD16: =(AW16+AZ16+BB16+BC16)*0.1267 -> 316.75 | BE16: =SUM(AW16:BD16)-AY16-BA16 -> 7816.75 | BF16: =(($F16/30)*$I16)*$K16 -> 0 | BG16: =(($G16/30)*$I16)*$K16 -> 0 | BH16: =U16 -> 0 | BI16: =V16 -> 0 | BJ16: =W16 -> 0 | BK16: =X16 -> 0 | BL16: =AL16+AQ16 -> 0 | BM16: =(+BF16+BI16+BK16+BL16)*0.1267 -> 0 | BN16: =SUM(BF16:BM16)-BH16-BJ16 -> 0 | BO16: =(($F16/30)*$I16)*$L16 -> 0 | BP16: =(($G16/30)*$I16)*$L16 -> 0 | BQ16: =Y16 -> 0 | BR16: =Z16 -> 0 | BS16: =AA16 -> 0 | BT16: =AB16 -> 0 | BU16: =AM16+AR16 -> 0 | BV16: =(BO16+BR16+BT16+BU16)*0.1267 -> 0 | BW16: =SUM(BO16:BV16)-BQ16-BS16 -> 0 | BX16: =(($F16/30)*$I16)*$M16 -> 0 | BY16: =(($G16/30)*$I16)*$M16 -> 0 | BZ16: =AC16 -> 0 | CA16: =AD16 -> 0 | CB16: =AE16 -> 0 | CC16: =AF16 -> 0 | CD16: =AN16+AS16 -> 0 | CE16: =(BX16+CA16+CC16)*0.1267 -> 0 | CF16: =SUM(BX16:CE16)-BZ16-CB16 -> 0 | CG16: =(($F16/30)*$I16)*N16 -> 0 | CH16: =(($G16/30)*$I16)*$N16 -> 0 | CI16: =+AG16 -> 0 | CJ16: =AH16 -> 0 | CK16: =AI16 -> 0 | CL16: =AJ16 -> 0 | CM16: =AO16+AT16 -> 0 | CN16: =(CG16+CJ16+CL16)*0.1267 -> 0 | CO16: =SUM(CG16:CN16)-CI16-CK16 -> 0 | CQ16: PROQUIMA | CR16: =IF($CQ16="PROQUIMA",$AW16+$BF16+$BO16+$BX16+$CG16,0) -> 2500 | CS16: =IF($CQ16="PROQUIMA",$AX16+$BG16+$BP16+$BY16+$CH16,0) -> 5000 | CT16: =IF($CQ16="PROQUIMA",$AY16+$BH16+$BQ16+$BZ16+$CI16,0) -> 0 | CU16: =IF($CQ16="PROQUIMA",$AZ16+$BI16+$BR16+$CA16+$CJ16,0) -> 0 | CV16: =IF($CQ16="PROQUIMA",$BA16+$BJ16+$BS16+$CB16+$CK16,0) -> 0 | CW16: =IF($CQ16="PROQUIMA",$BB16+$BK16+$BT16+$CC16+$CL16,0) -> 0 | CX16: =IF($CQ16="PROQUIMA",$BC16+$BL16+$BU16+$CD16+$CM16,0) -> 0 | CY16: =IF($CQ16="PROQUIMA",$BD16+$BM16+$BV16+$CE16+CN16,0) -> 316.75 | CZ16: =SUM(CR16:CY16)-CT16-CV16 -> 7816.75 | DA16: =IF($CQ16="UNHESA",$AW16+$BF16+$BO16+$BX16+$CG16,0) -> 0 | DB16: =IF($CQ16="UNHESA",$AX16+$BG16+$BP16+$BY16+$CH16,0) -> 0 | DC16: =IF($CQ16="UNHESA",$AY16+$BH16+$BQ16+$BZ16+$CI16,0) -> 0 | DD16: =IF($CQ16="UNHESA",$AZ16+$BI16+$BR16+$CA16+$CJ16,0) -> 0 | DE16: =IF($CQ16="UNHESA",$BA16+$BJ16+$BS16+$CB16+$CK16,0) -> 0 | DF16: =IF($CQ16="UNHESA",$BB16+$BK16+$BT16+$CC16+$CL16,0) -> 0 | DG16: =IF($CQ16="UNHESA",$BC16+$BL16+$BU16+$CD16+$CM16,0) -> 0 | DH16: =IF($CQ16="UNHESA",$BD16+$BM16+$BV16+$CE16+$CN16,0) -> 0 | DI16: =SUM(DA16:DH16)-DC16-DE16 -> 0 | EL16: 620.12 | EU16: =+EP16+EQ16+ER16 -> 0 | EW16: =IF($I16<=15,EL16/2,EL16) -> 310.06 | EX16: =IF($I16<=15,EM16/2,EM16) -> 0 | EY16: =IF($I16<=15,EN16/2,EN16) -> 0 | EZ16: =IF($I16<=15,EO16/2,EO16) -> 0 | FA16: =IF($I16<=15,EP16/2,EP16) -> 0 | FB16: =IF($I16<=15,EQ16/2,EQ16) -> 0 | FC16: =IF($I16<=15,ER16/2,ER16) -> 0 | FD16: =IF($I16<=15,ES16/2,ES16) -> 0 | ... FF16: =IF($I16<=15,EU16/2,EU16) -> 0 | FN16: =(((F16/30/8)*1.5)*(Q16+U16+Y16))-(AZ16+BI16+BR16) -> 0 | FO16: =(((F16/30/8)*2)*(S16+W16+AA16))-(BB16+BK16+BT16) -> 0 | FP16: =(SUM(AW16:CF16))-(SUM(CR16:DR16)) -> 0 | FQ16: =(F16/30*I16)-(CR16+DA16+DJ16) -> 0 | FR16: =(SUM(EL16:EU16))-((SUM(EW16:FF16))*$FR$5) -> 310.06
A17: 101030 | D17: Total Asesoria | F17: =+F16 -> 5000 | G17: =+G16 -> 10000 | H17: =+H16 -> 15000 | Q17: =+Q16 -> 0 | R17: =+R16 -> 0 | S17: =+S16 -> 0 | T17: =+T16 -> 0 | U17: =+U16 -> 0 | V17: =+V16 -> 0 | W17: =+W16 -> 0 | X17: =+X16 -> 0 | ... FF17: =+FF16 -> 0
A19: 101040 | C19: Pilotos
A20: 101040 | B20: 4 | C20: Chavez Najera Fredy Amilcar | D20: Piloto | E20: UNHESA | F20: 4002.28 | G20: 1500 | H20: =+F20+G20 -> 5502.28 | I20: 15 | J20: 0 | K20: 1 | L20: 0 | M20: 0 | N20: 0 | O20: =SUM(J20:N20) -> 1 | R20: =($F20/30/8*1.5)*Q20 -> 0 | T20: =($F20/30/8*2)*S20 -> 0 | V20: =($F20/30/8*1.5)*U20 -> 0 | X20: =($F20/30/8*2)*W20 -> 0 | Z20: =(($F20/30/8)*1.5)*Y20 -> 0 | AB20: =(($F20/30/8)*2)*AA20 -> 0 | AD20: =(($F20/30/8)*1.5)*AC20 -> 0 | AF20: =(($F20/30/8)*2)*AE20 -> 0 | AH20: =(($F20/30/8)*1.5)*AG20 -> 0 | AJ20: =(($F20/30/8)*2)*AI20 -> 0 | AW20: =(($F20/30)*$I20)*$J20 -> 0 | AX20: =(($G20/30)*$I20)*$J20 -> 0 | AY20: =Q20 -> 0 | AZ20: =R20 -> 0 | BA20: =S20 -> 0 | BB20: =T20 -> 0 | BC20: =AK20+AP20 -> 0 | BD20: =(AW20+AZ20+BB20+BC20)*0.1267 -> 0 | BE20: =SUM(AW20:BD20)-AY20-BA20 -> 0 | BF20: =(($F20/30)*$I20)*$K20 -> 2001.14 | BG20: =(($G20/30)*$I20)*$K20 -> 750 | BH20: =U20 -> 0 | BI20: =V20 -> 0 | BJ20: =W20 -> 0 | BK20: =X20 -> 0 | BL20: =AL20+AQ20 -> 0 | BM20: =(+BF20+BI20+BK20+BL20)*0.1267 -> 253.54444 | BN20: =SUM(BF20:BM20)-BH20-BJ20 -> 3004.6844 | BO20: =(($F20/30)*$I20)*$L20 -> 0 | BP20: =(($G20/30)*$I20)*$L20 -> 0 | BQ20: =Y20 -> 0 | BR20: =Z20 -> 0 | BS20: =AA20 -> 0 | BT20: =AB20 -> 0 | BU20: =AM20+AR20 -> 0 | BV20: =(BO20+BR20+BT20+BU20)*0.1267 -> 0 | BW20: =SUM(BO20:BV20)-BQ20-BS20 -> 0 | BX20: =(($F20/30)*$I20)*$M20 -> 0 | BY20: =(($G20/30)*$I20)*$M20 -> 0 | BZ20: =AC20 -> 0 | CA20: =AD20 -> 0 | CB20: =AE20 -> 0 | CC20: =AF20 -> 0 | CD20: =AN20+AS20 -> 0 | CE20: =(BX20+CA20+CC20)*0.1267 -> 0 | CF20: =SUM(BX20:CE20)-BZ20-CB20 -> 0 | CG20: =(($F20/30)*$I20)*N20 -> 0 | CH20: =(($G20/30)*$I20)*$N20 -> 0 | CI20: =+AG20 -> 0 | CJ20: =AH20 -> 0 | CK20: =AI20 -> 0 | CL20: =AJ20 -> 0 | CM20: =AO20+AT20 -> 0 | CN20: =(CG20+CJ20+CL20)*0.1267 -> 0 | CO20: =SUM(CG20:CN20)-CI20-CK20 -> 0 | CQ20: UNHESA | CR20: =IF($CQ20="PROQUIMA",$AW20+$BF20+$BO20+$BX20+$CG20,0) -> 0 | CS20: =IF($CQ20="PROQUIMA",$AX20+$BG20+$BP20+$BY20+$CH20,0) -> 0 | CT20: =IF($CQ20="PROQUIMA",$AY20+$BH20+$BQ20+$BZ20+$CI20,0) -> 0 | CU20: =IF($CQ20="PROQUIMA",$AZ20+$BI20+$BR20+$CA20+$CJ20,0) -> 0 | CV20: =IF($CQ20="PROQUIMA",$BA20+$BJ20+$BS20+$CB20+$CK20,0) -> 0 | CW20: =IF($CQ20="PROQUIMA",$BB20+$BK20+$BT20+$CC20+$CL20,0) -> 0 | CX20: =IF($CQ20="PROQUIMA",$BC20+$BL20+$BU20+$CD20+$CM20,0) -> 0 | CY20: =IF($CQ20="PROQUIMA",$BD20+$BM20+$BV20+$CE20+CN20,0) -> 0 | CZ20: =SUM(CR20:CY20)-CT20-CV20 -> 0 | DA20: =IF($CQ20="UNHESA",$AW20+$BF20+$BO20+$BX20+$CG20,0) -> 2001.14 | DB20: =IF($CQ20="UNHESA",$AX20+$BG20+$BP20+$BY20+$CH20,0) -> 750 | DC20: =IF($CQ20="UNHESA",$AY20+$BH20+$BQ20+$BZ20+$CI20,0) -> 0 | DD20: =IF($CQ20="UNHESA",$AZ20+$BI20+$BR20+$CA20+$CJ20,0) -> 0 | DE20: =IF($CQ20="UNHESA",$BA20+$BJ20+$BS20+$CB20+$CK20,0) -> 0 | DF20: =IF($CQ20="UNHESA",$BB20+$BK20+$BT20+$CC20+$CL20,0) -> 0 | DG20: =IF($CQ20="UNHESA",$BC20+$BL20+$BU20+$CD20+$CM20,0) -> 0 | DH20: =IF($CQ20="UNHESA",$BD20+$BM20+$BV20+$CE20+$CN20,0) -> 253.54444 | DI20: =SUM(DA20:DH20)-DC20-DE20 -> 3004.6844 | EL20: 65.45 | EU20: =+EP20+EQ20+ER20 -> 0 | EW20: =IF($I20<=15,EL20/2,EL20) -> 32.725 | EX20: =IF($I20<=15,EM20/2,EM20) -> 0 | EY20: =IF($I20<=15,EN20/2,EN20) -> 0 | EZ20: =IF($I20<=15,EO20/2,EO20) -> 0 | FA20: =IF($I20<=15,EP20/2,EP20) -> 0 | FB20: =IF($I20<=15,EQ20/2,EQ20) -> 0 | FC20: =IF($I20<=15,ER20/2,ER20) -> 0 | FD20: =IF($I20<=15,ES20/2,ES20) -> 0 | ... FF20: =IF($I20<=15,EU20/2,EU20) -> 0 | FN20: =(((F20/30/8)*1.5)*(Q20+U20+Y20))-(AZ20+BI20+BR20) -> 0 | FO20: =(((F20/30/8)*2)*(S20+W20+AA20))-(BB20+BK20+BT20) -> 0 | FP20: =(SUM(AW20:CF20))-(SUM(CR20:DR20)) -> 0 | FQ20: =(F20/30*I20)-(CR20+DA20+DJ20) -> 0 | FR20: =(SUM(EL20:EU20))-((SUM(EW20:FF20))*$FR$5) -> 32.725
A21: 101040 | C21: Gaitan Hernandez Luis Daniel | D21: Piloto | E21: PROQUIMA | F21: 6000 | G21: 1500 | H21: =+F21+G21 -> 7500 | I21: 15 | J21: 1 | K21: 0 | L21: 0 | M21: 0 | N21: 0 | O21: =SUM(J21:N21) -> 1 | R21: =($F21/30/8*1.5)*Q21 -> 0 | T21: =($F21/30/8*2)*S21 -> 0 | V21: =($F21/30/8*1.5)*U21 -> 0 | X21: =($F21/30/8*2)*W21 -> 0 | Z21: =(($F21/30/8)*1.5)*Y21 -> 0 | AB21: =(($F21/30/8)*2)*AA21 -> 0 | AD21: =(($F21/30/8)*1.5)*AC21 -> 0 | AF21: =(($F21/30/8)*2)*AE21 -> 0 | AH21: =(($F21/30/8)*1.5)*AG21 -> 0 | AJ21: =(($F21/30/8)*2)*AI21 -> 0 | AW21: =(($F21/30)*$I21)*$J21 -> 3000 | AX21: =(($G21/30)*$I21)*$J21 -> 750 | AY21: =Q21 -> 0 | AZ21: =R21 -> 0 | BA21: =S21 -> 0 | BB21: =T21 -> 0 | BC21: =AK21+AP21 -> 0 | BD21: =(AW21+AZ21+BB21+BC21)*0.1267 -> 380.1 | BE21: =SUM(AW21:BD21)-AY21-BA21 -> 4130.1 | BF21: =(($F21/30)*$I21)*$K21 -> 0 | BG21: =(($G21/30)*$I21)*$K21 -> 0 | BH21: =U21 -> 0 | BI21: =V21 -> 0 | BJ21: =W21 -> 0 | BK21: =X21 -> 0 | BL21: =AL21+AQ21 -> 0 | BM21: =(+BF21+BI21+BK21+BL21)*0.1267 -> 0 | BN21: =SUM(BF21:BM21)-BH21-BJ21 -> 0 | BO21: =(($F21/30)*$I21)*$L21 -> 0 | BP21: =(($G21/30)*$I21)*$L21 -> 0 | BQ21: =Y21 -> 0 | BR21: =Z21 -> 0 | BS21: =AA21 -> 0 | BT21: =AB21 -> 0 | BU21: =AM21+AR21 -> 0 | BV21: =(BO21+BR21+BT21+BU21)*0.1267 -> 0 | BW21: =SUM(BO21:BV21)-BQ21-BS21 -> 0 | BX21: =(($F21/30)*$I21)*$M21 -> 0 | BY21: =(($G21/30)*$I21)*$M21 -> 0 | BZ21: =AC21 -> 0 | CA21: =AD21 -> 0 | CB21: =AE21 -> 0 | CC21: =AF21 -> 0 | CD21: =AN21+AS21 -> 0 | CE21: =(BX21+CA21+CC21)*0.1267 -> 0 | CF21: =SUM(BX21:CE21)-BZ21-CB21 -> 0 | CG21: =(($F21/30)*$I21)*N21 -> 0 | CH21: =(($G21/30)*$I21)*$N21 -> 0 | CI21: =+AG21 -> 0 | CJ21: =AH21 -> 0 | CK21: =AI21 -> 0 | CL21: =AJ21 -> 0 | CM21: =AO21+AT21 -> 0 | CN21: =(CG21+CJ21+CL21)*0.1267 -> 0 | CO21: =SUM(CG21:CN21)-CI21-CK21 -> 0 | CQ21: PROQUIMA | CR21: =IF($CQ21="PROQUIMA",$AW21+$BF21+$BO21+$BX21+$CG21,0) -> 3000 | CS21: =IF($CQ21="PROQUIMA",$AX21+$BG21+$BP21+$BY21+$CH21,0) -> 750 | CT21: =IF($CQ21="PROQUIMA",$AY21+$BH21+$BQ21+$BZ21+$CI21,0) -> 0 | CU21: =IF($CQ21="PROQUIMA",$AZ21+$BI21+$BR21+$CA21+$CJ21,0) -> 0 | CV21: =IF($CQ21="PROQUIMA",$BA21+$BJ21+$BS21+$CB21+$CK21,0) -> 0 | CW21: =IF($CQ21="PROQUIMA",$BB21+$BK21+$BT21+$CC21+$CL21,0) -> 0 | CX21: =IF($CQ21="PROQUIMA",$BC21+$BL21+$BU21+$CD21+$CM21,0) -> 0 | CY21: =IF($CQ21="PROQUIMA",$BD21+$BM21+$BV21+$CE21+CN21,0) -> 380.1 | CZ21: =SUM(CR21:CY21)-CT21-CV21 -> 4130.1 | DA21: =IF($CQ21="UNHESA",$AW21+$BF21+$BO21+$BX21+$CG21,0) -> 0 | DB21: =IF($CQ21="UNHESA",$AX21+$BG21+$BP21+$BY21+$CH21,0) -> 0 | DC21: =IF($CQ21="UNHESA",$AY21+$BH21+$BQ21+$BZ21+$CI21,0) -> 0 | DD21: =IF($CQ21="UNHESA",$AZ21+$BI21+$BR21+$CA21+$CJ21,0) -> 0 | DE21: =IF($CQ21="UNHESA",$BA21+$BJ21+$BS21+$CB21+$CK21,0) -> 0 | DF21: =IF($CQ21="UNHESA",$BB21+$BK21+$BT21+$CC21+$CL21,0) -> 0 | DG21: =IF($CQ21="UNHESA",$BC21+$BL21+$BU21+$CD21+$CM21,0) -> 0 | DH21: =IF($CQ21="UNHESA",$BD21+$BM21+$BV21+$CE21+$CN21,0) -> 0 | DI21: =SUM(DA21:DH21)-DC21-DE21 -> 0 | EL21: 160.51 | EU21: =+EP21+EQ21+ER21 -> 0 | EW21: =IF($I21<=15,EL21/2,EL21) -> 80.255 | EX21: =IF($I21<=15,EM21/2,EM21) -> 0 | EY21: =IF($I21<=15,EN21/2,EN21) -> 0 | EZ21: =IF($I21<=15,EO21/2,EO21) -> 0 | FA21: =IF($I21<=15,EP21/2,EP21) -> 0 | FB21: =IF($I21<=15,EQ21/2,EQ21) -> 0 | FC21: =IF($I21<=15,ER21/2,ER21) -> 0 | FD21: =IF($I21<=15,ES21/2,ES21) -> 0 | ... FF21: =IF($I21<=15,EU21/2,EU21) -> 0
F23: =SUM(F20:F22) -> 10002.28 | G23: =SUM(G20:G22) -> 3000 | H23: =SUM(H20:H22) -> 13002.28 | Q23: =SUM(Q20:Q22) -> 0 | R23: =SUM(R20:R22) -> 0 | S23: =SUM(S20:S22) -> 0 | T23: =SUM(T20:T22) -> 0 | U23: =SUM(U20:U22) -> 0 | V23: =SUM(V20:V22) -> 0 | W23: =SUM(W20:W22) -> 0 | X23: =SUM(X20:X22) -> 0 | ... FF23: =SUM(FF20:FF22) -> 0
D24: Total Presidencia | Q24: =+Q10+Q13+Q17+Q23 -> 0 | R24: =+R10+R13+R17+R23 -> 0 | S24: =+S10+S13+S17+S23 -> 0 | T24: =+T10+T13+T17+T23 -> 0 | U24: =+U10+U13+U17+U23 -> 0 | V24: =+V10+V13+V17+V23 -> 0 | W24: =+W10+W13+W17+W23 -> 0 | X24: =+X10+X13+X17+X23 -> 0 | ... FF24: =+FF10+FF13+FF17+FF23 -> 0
A26: 102010 | C26: Administrativo
A29: 102050 | B29: 7 | C29: Quevedo Lopez Ingrid Aracely | D29: Conserje | E29: UNHESA | F29: 4002.28 | G29: 250 | H29: =+F29+G29 -> 4252.28 | I29: 15 | J29: 0 | K29: 1 | L29: 0 | M29: 0 | N29: 0 | O29: =SUM(J29:N29) -> 1 | R29: =($F29/30/8*1.5)*Q29 -> 0 | T29: =($F29/30/8*2)*S29 -> 0 | V29: =($F29/30/8*1.5)*U29 -> 0 | X29: =($F29/30/8*2)*W29 -> 0 | Z29: =(($F29/30/8)*1.5)*Y29 -> 0 | AB29: =(($F29/30/8)*2)*AA29 -> 0 | AD29: =(($F29/30/8)*1.5)*AC29 -> 0 | AF29: =(($F29/30/8)*2)*AE29 -> 0 | AH29: =(($F29/30/8)*1.5)*AG29 -> 0 | AJ29: =(($F29/30/8)*2)*AI29 -> 0 | AW29: =((F29/30)*I29)*$J29 -> 0 | AX29: =((G29/30)*I29)*$J29 -> 0 | AY29: =Q29 -> 0 | AZ29: =R29 -> 0 | BA29: =S29 -> 0 | BB29: =T29 -> 0 | BC29: =AK29+AP29 -> 0 | BD29: =(AW29+AZ29+BB29+BC29)*0.1267 -> 0 | BE29: =SUM(AW29:BD29)-AY29-BA29 -> 0 | BF29: =(($F29/30)*$I29)*$K29 -> 2001.14 | BG29: =(($G29/30)*$I29)*$K29 -> 125 | BH29: =U29 -> 0 | BI29: =V29 -> 0 | BJ29: =W29 -> 0 | BK29: =X29 -> 0 | BL29: =AL29+AQ29 -> 0 | BM29: =(+BF29+BI29+BK29+BL29)*0.1267 -> 253.54444 | BN29: =SUM(BF29:BM29)-BH29-BJ29 -> 2379.6844 | BO29: =(($F29/30)*$I29)*$L29 -> 0 | BP29: =(($G29/30)*$I29)*$L29 -> 0 | BQ29: =Y29 -> 0 | BR29: =Z29 -> 0 | BS29: =AA29 -> 0 | BT29: =AB29 -> 0 | BU29: =AM29+AR29 -> 0 | BV29: =(BO29+BR29+BT29+BU29)*0.1267 -> 0 | BW29: =SUM(BO29:BV29)-BQ29-BS29 -> 0 | BX29: =(($F29/30)*$I29)*$M29 -> 0 | BY29: =(($G29/30)*$I29)*$M29 -> 0 | BZ29: =AC29 -> 0 | CA29: =AD29 -> 0 | CB29: =AE29 -> 0 | CC29: =AF29 -> 0 | CD29: =AN29+AS29 -> 0 | CE29: =(BX29+CA29+CC29)*0.1267 -> 0 | CF29: =SUM(BX29:CE29)-BZ29-CB29 -> 0 | CG29: =(($F29/30)*$I29)*N29 -> 0 | CH29: =(($G29/30)*$I29)*$N29 -> 0 | CI29: =+AG29 -> 0 | CJ29: =AH29 -> 0 | CK29: =AI29 -> 0 | CL29: =AJ29 -> 0 | CM29: =AO29+AT29 -> 0 | CN29: =(CG29+CJ29+CL29)*0.1267 -> 0 | CO29: =SUM(CG29:CN29)-CI29-CK29 -> 0 | CQ29: UNHESA | CR29: =IF($CQ29="PROQUIMA",$AW29+$BF29+$BO29+$BX29+$CG29,0) -> 0 | CS29: =IF($CQ29="PROQUIMA",$AX29+$BG29+$BP29+$BY29+$CH29,0) -> 0 | CT29: =IF($CQ29="PROQUIMA",$AY29+$BH29+$BQ29+$BZ29+$CI29,0) -> 0 | CU29: =IF($CQ29="PROQUIMA",$AZ29+$BI29+$BR29+$CA29+$CJ29,0) -> 0 | CV29: =IF($CQ29="PROQUIMA",$BA29+$BJ29+$BS29+$CB29+$CK29,0) -> 0 | CW29: =IF($CQ29="PROQUIMA",$BB29+$BK29+$BT29+$CC29+$CL29,0) -> 0 | CX29: =IF($CQ29="PROQUIMA",$BC29+$BL29+$BU29+$CD29+$CM29,0) -> 0 | CY29: =IF($CQ29="PROQUIMA",$BD29+$BM29+$BV29+$CE29+CN29,0) -> 0 | CZ29: =SUM(CR29:CY29)-CT29-CV29 -> 0 | DA29: =IF($CQ29="UNHESA",$AW29+$BF29+$BO29+$BX29+$CG29,0) -> 2001.14 | DB29: =IF($CQ29="UNHESA",$AX29+$BG29+$BP29+$BY29+$CH29,0) -> 125 | DC29: =IF($CQ29="UNHESA",$AY29+$BH29+$BQ29+$BZ29+$CI29,0) -> 0 | DD29: =IF($CQ29="UNHESA",$AZ29+$BI29+$BR29+$CA29+$CJ29,0) -> 0 | DE29: =IF($CQ29="UNHESA",$BA29+$BJ29+$BS29+$CB29+$CK29,0) -> 0 | DF29: =IF($CQ29="UNHESA",$BB29+$BK29+$BT29+$CC29+$CL29,0) -> 0 | DG29: =IF($CQ29="UNHESA",$BC29+$BL29+$BU29+$CD29+$CM29,0) -> 0 | DH29: =IF($CQ29="UNHESA",$BD29+$BM29+$BV29+$CE29+$CN29,0) -> 253.54444 | DI29: =SUM(DA29:DH29)-DC29-DE29 -> 2379.6844 | DJ29: =IF($CQ29="UNHESA LIQUIDOS",$AW29+$BF29+$BO29+$BX29+$CG29,0) -> 0 | DK29: =IF($CQ29="CALIDUL",$AX29+$BG29+$BP29+$BY29+$CH29,0) -> 0 | DL29: =IF($CQ29="CALIDUL",$AY29+$BH29+$BQ29+$BZ29+$CI29,0) -> 0 | DM29: =IF($CQ29="CALIDUL",$AZ29+$BI29+$BR29+$CA29+$CJ29,0) -> 0 | DN29: =IF($CQ29="CALIDUL",$BA29+$BJ29+$BS29+$CB29+$CK29,0) -> 0 | DO29: =IF($CQ29="CALIDUL",$BB29+$BK29+$BT29+$CC29+$CL29,0) -> 0 | DP29: =IF($CQ29="CALIDUL",$BC29+$BL29+$BU29+$CD29+$CM29,0) -> 0 | DQ29: =IF($CQ29="CALIDUL",$BD29+$BM29+$BV29+$CE29+$CN29,0) -> 0 | DR29: =SUM(DJ29:DQ29)-DL29-DN29 -> 0 | DS29: =IF($CQ29="ECONACIONAL",$AW29+$BF29+$BO29+$BX29+$CG29,0) -> 0 | DT29: =IF($CQ29="ECONACIONAL",$AX29+$BG29+$BP29+$BY29+$CH29,0) -> 0 | DU29: =IF($CQ29="ECONACIONAL",$AY29+$BH29+$BQ29+$BZ29+$CI29,0) -> 0 | DV29: =IF($CQ29="ECONACIONAL",$AZ29+$BI29+$BR29+$CA29+$CJ29,0) -> 0 | DW29: =IF($CQ29="ECONACIONAL",$BA29+$BJ29+$BS29+$CB29+$CK29,0) -> 0 | DX29: =IF($CQ29="ECONACIONAL",$BB29+$BK29+$BT29+$CC29+$CL29,0) -> 0 | DY29: =IF($CQ29="ECONACIONAL",$BC29+$BL29+$BU29+$CD29+$CM29,0) -> 0 | DZ29: =IF($CQ29="ECONACIONAL",$BD29+$BM29+$BV29+$CE29+$CN29,0) -> 0 | EA29: =SUM(DS29:DZ29)-DU29-DW29 -> 0 | EB29: =IF($CQ29="CLEARTEC",$AW29+$BF29+$BO29+$BX29+$CG29,0) -> 0 | EC29: =IF($CQ29="CLEARTEC",$AX29+$BG29+$BP29+$BY29+$CH29,0) -> 0 | ED29: =IF($CQ29="CLEARTEC",$AY29+$BH29+$BQ29+$BZ29+$CI29,0) -> 0 | EE29: =IF($CQ29="CLEARTEC",$AZ29+$BI29+$BR29+$CA29+$CJ29,0) -> 0 | EF29: =IF($CQ29="CLEARTEC",$BA29+$BJ29+$BS29+$CB29+$CK29,0) -> 0 | EG29: =IF($CQ29="CLEARTEC",$BB29+$BK29+$BT29+$CC29+$CL29,0) -> 0 | EH29: =IF($CQ29="CLEARTEC",$BC29+$BL29+$BU29+$CD29+$CM29,0) -> 0 | EI29: =IF($CQ29="CLEARTEC",$BD29+$BM29+$BV29+$CE29+$CN29,0) -> 0 | EJ29: =SUM(EB29:EI29)-ED29-EF29 -> 0 | EL29: 2.95 | EM29: 1951.06 | EU29: =+EP29+EQ29+ER29 -> 0 | EW29: =IF($I29<=15,EL29/2,EL29) -> 1.475 | EX29: =IF($I29<=15,EM29/2,EM29) -> 975.53 | EY29: =IF($I29<=15,EN29/2,EN29) -> 0 | EZ29: =IF($I29<=15,EO29/2,EO29) -> 0 | FA29: =IF($I29<=15,EP29/2,EP29) -> 0 | FB29: =IF($I29<=15,EQ29/2,EQ29) -> 0 | FC29: =IF($I29<=15,ER29/2,ER29) -> 0 | FD29: =IF($I29<=15,ES29/2,ES29) -> 0 | ... FF29: =IF($I29<=15,EU29/2,EU29) -> 0 | FN29: =(((F29/30/8)*1.5)*(Q29+U29+Y29))-(AZ29+BI29+BR29) -> 0 | FO29: =(((F29/30/8)*2)*(S29+W29+AA29))-(BB29+BK29+BT29) -> 0 | FP29: =(SUM(AW29:CF29))-(SUM(CR29:DR29)) -> 0 | FQ29: =(F29/30*I29)-(CR29+DA29+DJ29) -> 0 | FR29: =(SUM(EL29:EU29))-((SUM(EW29:FF29))*$FR$5) -> 977.005
A30: 102050 | B30: 8 | C30: Morales Alvarez Yony | D30: Conserje | E30: UNHESA | F30: 4002.28 | G30: 250 | H30: =+F30+G30 -> 4252.28 | I30: 15 | J30: 0 | K30: 1 | L30: 0 | M30: 0 | N30: 0 | O30: =SUM(J30:N30) -> 1 | R30: =($F30/30/8*1.5)*Q30 -> 0 | T30: =($F30/30/8*2)*S30 -> 0 | V30: =($F30/30/8*1.5)*U30 -> 0 | X30: =($F30/30/8*2)*W30 -> 0 | Z30: =(($F30/30/8)*1.5)*Y30 -> 0 | AB30: =(($F30/30/8)*2)*AA30 -> 0 | AD30: =(($F30/30/8)*1.5)*AC30 -> 0 | AF30: =(($F30/30/8)*2)*AE30 -> 0 | AH30: =(($F30/30/8)*1.5)*AG30 -> 0 | AJ30: =(($F30/30/8)*2)*AI30 -> 0 | AW30: =((F30/30)*I30)*$J30 -> 0 | AX30: =((G30/30)*I30)*$J30 -> 0 | AY30: =Q30 -> 0 | AZ30: =R30 -> 0 | BA30: =S30 -> 0 | BB30: =T30 -> 0 | BC30: =AK30+AP30 -> 0 | BD30: =(AW30+AZ30+BB30+BC30)*0.1267 -> 0 | BE30: =SUM(AW30:BD30)-AY30-BA30 -> 0 | BF30: =(($F30/30)*$I30)*$K30 -> 2001.14 | BG30: =(($G30/30)*$I30)*$K30 -> 125 | BH30: =U30 -> 0 | BI30: =V30 -> 0 | BJ30: =W30 -> 0 | BK30: =X30 -> 0 | BL30: =AL30+AQ30 -> 0 | BM30: =(+BF30+BI30+BK30+BL30)*0.1267 -> 253.54444 | BN30: =SUM(BF30:BM30)-BH30-BJ30 -> 2379.6844 | BO30: =(($F30/30)*$I30)*$L30 -> 0 | BP30: =(($G30/30)*$I30)*$L30 -> 0 | BQ30: =Y30 -> 0 | BR30: =Z30 -> 0 | BS30: =AA30 -> 0 | BT30: =AB30 -> 0 | BU30: =AM30+AR30 -> 0 | BV30: =(BO30+BR30+BT30+BU30)*0.1267 -> 0 | BW30: =SUM(BO30:BV30)-BQ30-BS30 -> 0 | BX30: =(($F30/30)*$I30)*$M30 -> 0 | BY30: =(($G30/30)*$I30)*$M30 -> 0 | BZ30: =AC30 -> 0 | CA30: =AD30 -> 0 | CB30: =AE30 -> 0 | CC30: =AF30 -> 0 | CD30: =AN30+AS30 -> 0 | CE30: =(BX30+CA30+CC30)*0.1267 -> 0 | CF30: =SUM(BX30:CE30)-BZ30-CB30 -> 0 | CG30: =(($F30/30)*$I30)*N30 -> 0 | CH30: =(($G30/30)*$I30)*$N30 -> 0 | CI30: =+AG30 -> 0 | CJ30: =AH30 -> 0 | CK30: =AI30 -> 0 | CL30: =AJ30 -> 0 | CM30: =AO30+AT30 -> 0 | CN30: =(CG30+CJ30+CL30)*0.1267 -> 0 | CO30: =SUM(CG30:CN30)-CI30-CK30 -> 0 | CQ30: UNHESA | CR30: =IF($CQ30="PROQUIMA",$AW30+$BF30+$BO30+$BX30+$CG30,0) -> 0 | CS30: =IF($CQ30="PROQUIMA",$AX30+$BG30+$BP30+$BY30+$CH30,0) -> 0 | CT30: =IF($CQ30="PROQUIMA",$AY30+$BH30+$BQ30+$BZ30+$CI30,0) -> 0 | CU30: =IF($CQ30="PROQUIMA",$AZ30+$BI30+$BR30+$CA30+$CJ30,0) -> 0 | CV30: =IF($CQ30="PROQUIMA",$BA30+$BJ30+$BS30+$CB30+$CK30,0) -> 0 | CW30: =IF($CQ30="PROQUIMA",$BB30+$BK30+$BT30+$CC30+$CL30,0) -> 0 | CX30: =IF($CQ30="PROQUIMA",$BC30+$BL30+$BU30+$CD30+$CM30,0) -> 0 | CY30: =IF($CQ30="PROQUIMA",$BD30+$BM30+$BV30+$CE30+CN30,0) -> 0 | CZ30: =SUM(CR30:CY30)-CT30-CV30 -> 0 | DA30: =IF($CQ30="UNHESA",$AW30+$BF30+$BO30+$BX30+$CG30,0) -> 2001.14 | DB30: =IF($CQ30="UNHESA",$AX30+$BG30+$BP30+$BY30+$CH30,0) -> 125 | DC30: =IF($CQ30="UNHESA",$AY30+$BH30+$BQ30+$BZ30+$CI30,0) -> 0 | DD30: =IF($CQ30="UNHESA",$AZ30+$BI30+$BR30+$CA30+$CJ30,0) -> 0 | DE30: =IF($CQ30="UNHESA",$BA30+$BJ30+$BS30+$CB30+$CK30,0) -> 0 | DF30: =IF($CQ30="UNHESA",$BB30+$BK30+$BT30+$CC30+$CL30,0) -> 0 | DG30: =IF($CQ30="UNHESA",$BC30+$BL30+$BU30+$CD30+$CM30,0) -> 0 | DH30: =IF($CQ30="UNHESA",$BD30+$BM30+$BV30+$CE30+$CN30,0) -> 253.54444 | DI30: =SUM(DA30:DH30)-DC30-DE30 -> 2379.6844 | DJ30: =IF($CQ30="UNHESA LIQUIDOS",$AW30+$BF30+$BO30+$BX30+$CG30,0) -> 0 | DK30: =IF($CQ30="CALIDUL",$AX30+$BG30+$BP30+$BY30+$CH30,0) -> 0 | DL30: =IF($CQ30="CALIDUL",$AY30+$BH30+$BQ30+$BZ30+$CI30,0) -> 0 | DM30: =IF($CQ30="CALIDUL",$AZ30+$BI30+$BR30+$CA30+$CJ30,0) -> 0 | DN30: =IF($CQ30="CALIDUL",$BA30+$BJ30+$BS30+$CB30+$CK30,0) -> 0 | DO30: =IF($CQ30="CALIDUL",$BB30+$BK30+$BT30+$CC30+$CL30,0) -> 0 | DP30: =IF($CQ30="CALIDUL",$BC30+$BL30+$BU30+$CD30+$CM30,0) -> 0 | DQ30: =IF($CQ30="CALIDUL",$BD30+$BM30+$BV30+$CE30+$CN30,0) -> 0 | DR30: =SUM(DJ30:DQ30)-DL30-DN30 -> 0 | DS30: =IF($CQ30="ECONACIONAL",$AW30+$BF30+$BO30+$BX30+$CG30,0) -> 0 | DT30: =IF($CQ30="ECONACIONAL",$AX30+$BG30+$BP30+$BY30+$CH30,0) -> 0 | DU30: =IF($CQ30="ECONACIONAL",$AY30+$BH30+$BQ30+$BZ30+$CI30,0) -> 0 | DV30: =IF($CQ30="ECONACIONAL",$AZ30+$BI30+$BR30+$CA30+$CJ30,0) -> 0 | DW30: =IF($CQ30="ECONACIONAL",$BA30+$BJ30+$BS30+$CB30+$CK30,0) -> 0 | DX30: =IF($CQ30="ECONACIONAL",$BB30+$BK30+$BT30+$CC30+$CL30,0) -> 0 | DY30: =IF($CQ30="ECONACIONAL",$BC30+$BL30+$BU30+$CD30+$CM30,0) -> 0 | DZ30: =IF($CQ30="ECONACIONAL",$BD30+$BM30+$BV30+$CE30+$CN30,0) -> 0 | EA30: =SUM(DS30:DZ30)-DU30-DW30 -> 0 | EB30: =IF($CQ30="CLEARTEC",$AW30+$BF30+$BO30+$BX30+$CG30,0) -> 0 | EC30: =IF($CQ30="CLEARTEC",$AX30+$BG30+$BP30+$BY30+$CH30,0) -> 0 | ED30: =IF($CQ30="CLEARTEC",$AY30+$BH30+$BQ30+$BZ30+$CI30,0) -> 0 | EE30: =IF($CQ30="CLEARTEC",$AZ30+$BI30+$BR30+$CA30+$CJ30,0) -> 0 | EF30: =IF($CQ30="CLEARTEC",$BA30+$BJ30+$BS30+$CB30+$CK30,0) -> 0 | EG30: =IF($CQ30="CLEARTEC",$BB30+$BK30+$BT30+$CC30+$CL30,0) -> 0 | EH30: =IF($CQ30="CLEARTEC",$BC30+$BL30+$BU30+$CD30+$CM30,0) -> 0 | EI30: =IF($CQ30="CLEARTEC",$BD30+$BM30+$BV30+$CE30+$CN30,0) -> 0 | EJ30: =SUM(EB30:EI30)-ED30-EF30 -> 0 | EL30: 2.95 | EU30: =+EP30+EQ30+ER30 -> 0 | EW30: =IF($I30<=15,EL30/2,EL30) -> 1.475 | EX30: =IF($I30<=15,EM30/2,EM30) -> 0 | EY30: =IF($I30<=15,EN30/2,EN30) -> 0 | EZ30: =IF($I30<=15,EO30/2,EO30) -> 0 | FA30: =IF($I30<=15,EP30/2,EP30) -> 0 | FB30: =IF($I30<=15,EQ30/2,EQ30) -> 0 | FC30: =IF($I30<=15,ER30/2,ER30) -> 0 | FD30: =IF($I30<=15,ES30/2,ES30) -> 0 | ... FF30: =IF($I30<=15,EU30/2,EU30) -> 0 | FN30: =(((F30/30/8)*1.5)*(Q30+U30+Y30))-(AZ30+BI30+BR30) -> 0 | FO30: =(((F30/30/8)*2)*(S30+W30+AA30))-(BB30+BK30+BT30) -> 0 | FP30: =(SUM(AW30:CF30))-(SUM(CR30:DR30)) -> 0 | FQ30: =(F30/30*I30)-(CR30+DA30+DJ30) -> 0 | FR30: =(SUM(EL30:EU30))-((SUM(EW30:FF30))*$FR$5) -> 1.475
D31: Total Administrativo | F31: =SUM(F27:F30) -> 8004.56 | G31: =SUM(G27:G30) -> 500 | H31: =SUM(H27:H30) -> 8504.56 | Q31: =SUM(Q27:Q30) -> 0 | R31: =SUM(R27:R30) -> 0 | S31: =SUM(S27:S30) -> 0 | T31: =SUM(T27:T30) -> 0 | U31: =SUM(U27:U30) -> 0 | V31: =SUM(V27:V30) -> 0 | W31: =SUM(W27:W30) -> 0 | X31: =SUM(X27:X30) -> 0 | ... FF31: =SUM(FF27:FF30) -> 0
A33: 102050 | C33: Conserjería Presidencia | FN33: =(((F33/30/8)*1.5)*(Q33+U33+Y33))-(AZ33+BI33+BR33) -> 0 | FO33: =(((F33/30/8)*2)*(S33+W33+AA33))-(BB33+BK33+BT33) -> 0 | FP33: =(SUM(AW33:CF33))-(SUM(CR33:DR33)) -> 0 | FQ33: =(F33/30*I33)-(CR33+DA33+DJ33) -> 0 | FR33: =(SUM(EL33:EU33))-((SUM(EW33:FF33))*$FR$5) -> 0
A34: 102050 | B34: 9 | C34: Cortez Ajcojon Sandra Edith | D34: Conserje | E34: PROQUIMA | F34: 4002.28 | G34: 250 | H34: =+F34+G34 -> 4252.28 | I34: 15 | J34: 1 | K34: 0 | L34: 0 | M34: 0 | N34: 0 | O34: =SUM(J34:N34) -> 1 | R34: =($F34/30/8*1.5)*Q34 -> 0 | T34: =($F34/30/8*2)*S34 -> 0 | V34: =($F34/30/8*1.5)*U34 -> 0 | X34: =($F34/30/8*2)*W34 -> 0 | Z34: =(($F34/30/8)*1.5)*Y34 -> 0 | AB34: =(($F34/30/8)*2)*AA34 -> 0 | AD34: =(($F34/30/8)*1.5)*AC34 -> 0 | AF34: =(($F34/30/8)*2)*AE34 -> 0 | AH34: =(($F34/30/8)*1.5)*AG34 -> 0 | AJ34: =(($F34/30/8)*2)*AI34 -> 0 | AW34: =((F34/30)*I34)*$J34 -> 2001.14 | AX34: =((G34/30)*I34)*$J34 -> 125 | AY34: =Q34 -> 0 | AZ34: =R34 -> 0 | BA34: =S34 -> 0 | BB34: =T34 -> 0 | BC34: =AK34+AP34 -> 0 | BD34: =(AW34+AZ34+BB34+BC34)*0.1267 -> 253.54444 | BE34: =SUM(AW34:BD34)-AY34-BA34 -> 2379.6844 | BF34: =(($F34/30)*$I34)*$K34 -> 0 | BG34: =(($G34/30)*$I34)*$K34 -> 0 | BH34: =U34 -> 0 | BI34: =V34 -> 0 | BJ34: =W34 -> 0 | BK34: =X34 -> 0 | BL34: =AL34+AQ34 -> 0 | BM34: =(+BF34+BI34+BK34+BL34)*0.1267 -> 0 | BN34: =SUM(BF34:BM34)-BH34-BJ34 -> 0 | BO34: =(($F34/30)*$I34)*$L34 -> 0 | BP34: =(($G34/30)*$I34)*$L34 -> 0 | BQ34: =Y34 -> 0 | BR34: =Z34 -> 0 | BS34: =AA34 -> 0 | BT34: =AB34 -> 0 | BU34: =AM34+AR34 -> 0 | BV34: =(BO34+BR34+BT34+BU34)*0.1267 -> 0 | BW34: =SUM(BO34:BV34)-BQ34-BS34 -> 0 | BX34: =(($F34/30)*$I34)*$M34 -> 0 | BY34: =(($G34/30)*$I34)*$M34 -> 0 | BZ34: =AC34 -> 0 | CA34: =AD34 -> 0 | CB34: =AE34 -> 0 | CC34: =AF34 -> 0 | CD34: =AN34+AS34 -> 0 | CE34: =(BX34+CA34+CC34)*0.09 -> 0 | CF34: =SUM(BX34:CE34)-BZ34-CB34 -> 0 | CG34: =(($F34/30)*$I34)*N34 -> 0 | CH34: =(($G34/30)*$I34)*$N34 -> 0 | CI34: =+AG34 -> 0 | CJ34: =AH34 -> 0 | CK34: =AI34 -> 0 | CL34: =AJ34 -> 0 | CM34: =AO34+AT34 -> 0 | CN34: =(CG34+CJ34+CL34)*0.09 -> 0 | CO34: =SUM(CG34:CN34)-CI34-CK34 -> 0 | CQ34: PROQUIMA | CR34: =IF($CQ34="PROQUIMA",$AW34+$BF34+$BO34+$BX34+$CG34,0) -> 2001.14 | CS34: =IF($CQ34="PROQUIMA",$AX34+$BG34+$BP34+$BY34+$CH34,0) -> 125 | CT34: =IF($CQ34="PROQUIMA",$AY34+$BH34+$BQ34+$BZ34+$CI34,0) -> 0 | CU34: =IF($CQ34="PROQUIMA",$AZ34+$BI34+$BR34+$CA34+$CJ34,0) -> 0 | CV34: =IF($CQ34="PROQUIMA",$BA34+$BJ34+$BS34+$CB34+$CK34,0) -> 0 | CW34: =IF($CQ34="PROQUIMA",$BB34+$BK34+$BT34+$CC34+$CL34,0) -> 0 | CX34: =IF($CQ34="PROQUIMA",$BC34+$BL34+$BU34+$CD34+$CM34,0) -> 0 | CY34: =IF($CQ34="PROQUIMA",$BD34+$BM34+$BV34+$CE34+CN34,0) -> 253.54444 | CZ34: =SUM(CR34:CY34)-CT34-CV34 -> 2379.6844 | DA34: =IF($CQ34="UNHESA",$AW34+$BF34+$BO34+$BX34+$CG34,0) -> 0 | DB34: =IF($CQ34="UNHESA",$AX34+$BG34+$BP34+$BY34+$CH34,0) -> 0 | DC34: =IF($CQ34="UNHESA",$AY34+$BH34+$BQ34+$BZ34+$CI34,0) -> 0 | DD34: =IF($CQ34="UNHESA",$AZ34+$BI34+$BR34+$CA34+$CJ34,0) -> 0 | DE34: =IF($CQ34="UNHESA",$BA34+$BJ34+$BS34+$CB34+$CK34,0) -> 0 | DF34: =IF($CQ34="UNHESA",$BB34+$BK34+$BT34+$CC34+$CL34,0) -> 0 | DG34: =IF($CQ34="UNHESA",$BC34+$BL34+$BU34+$CD34+$CM34,0) -> 0 | DH34: =IF($CQ34="UNHESA",$BD34+$BM34+$BV34+$CE34+$CN34,0) -> 0 | DI34: =SUM(DA34:DH34)-DC34-DE34 -> 0 | DJ34: =IF($CQ34="UNHESA LIQUIDOS",$AW34+$BF34+$BO34+$BX34+$CG34,0) -> 0 | DK34: =IF($CQ34="CALIDUL",$AX34+$BG34+$BP34+$BY34+$CH34,0) -> 0 | DL34: =IF($CQ34="CALIDUL",$AY34+$BH34+$BQ34+$BZ34+$CI34,0) -> 0 | DM34: =IF($CQ34="CALIDUL",$AZ34+$BI34+$BR34+$CA34+$CJ34,0) -> 0 | DN34: =IF($CQ34="CALIDUL",$BA34+$BJ34+$BS34+$CB34+$CK34,0) -> 0 | DO34: =IF($CQ34="CALIDUL",$BB34+$BK34+$BT34+$CC34+$CL34,0) -> 0 | DP34: =IF($CQ34="CALIDUL",$BC34+$BL34+$BU34+$CD34+$CM34,0) -> 0 | DQ34: =IF($CQ34="CALIDUL",$BD34+$BM34+$BV34+$CE34+$CN34,0) -> 0 | DR34: =SUM(DJ34:DQ34)-DL34-DN34 -> 0 | DS34: =IF($CQ34="ECONACIONAL",$AW34+$BF34+$BO34+$BX34+$CG34,0) -> 0 | DT34: =IF($CQ34="ECONACIONAL",$AX34+$BG34+$BP34+$BY34+$CH34,0) -> 0 | DU34: =IF($CQ34="ECONACIONAL",$AY34+$BH34+$BQ34+$BZ34+$CI34,0) -> 0 | DV34: =IF($CQ34="ECONACIONAL",$AZ34+$BI34+$BR34+$CA34+$CJ34,0) -> 0 | DW34: =IF($CQ34="ECONACIONAL",$BA34+$BJ34+$BS34+$CB34+$CK34,0) -> 0 | DX34: =IF($CQ34="ECONACIONAL",$BB34+$BK34+$BT34+$CC34+$CL34,0) -> 0 | DY34: =IF($CQ34="ECONACIONAL",$BC34+$BL34+$BU34+$CD34+$CM34,0) -> 0 | DZ34: =IF($CQ34="ECONACIONAL",$BD34+$BM34+$BV34+$CE34+$CN34,0) -> 0 | EA34: =SUM(DS34:DZ34)-DU34-DW34 -> 0 | EB34: =IF($CQ34="CLEARTEC",$AW34+$BF34+$BO34+$BX34+$CG34,0) -> 0 | EC34: =IF($CQ34="CLEARTEC",$AX34+$BG34+$BP34+$BY34+$CH34,0) -> 0 | ED34: =IF($CQ34="CLEARTEC",$AY34+$BH34+$BQ34+$BZ34+$CI34,0) -> 0 | EE34: =IF($CQ34="CLEARTEC",$AZ34+$BI34+$BR34+$CA34+$CJ34,0) -> 0 | EF34: =IF($CQ34="CLEARTEC",$BA34+$BJ34+$BS34+$CB34+$CK34,0) -> 0 | EG34: =IF($CQ34="CLEARTEC",$BB34+$BK34+$BT34+$CC34+$CL34,0) -> 0 | EH34: =IF($CQ34="CLEARTEC",$BC34+$BL34+$BU34+$CD34+$CM34,0) -> 0 | EI34: =IF($CQ34="CLEARTEC",$BD34+$BM34+$BV34+$CE34+$CN34,0) -> 0 | EJ34: =SUM(EB34:EI34)-ED34-EF34 -> 0 | EL34: 2.95 | EM34: 810.96 | EU34: =+EP34+EQ34+ER34 -> 0 | EW34: =IF($I34<=15,EL34/2,EL34) -> 1.475 | EX34: =IF($I34<=15,EM34/2,EM34) -> 405.48 | EY34: =IF($I34<=15,EN34/2,EN34) -> 0 | EZ34: =IF($I34<=15,EO34/2,EO34) -> 0 | FA34: =IF($I34<=15,EP34/2,EP34) -> 0 | FB34: =IF($I34<=15,EQ34/2,EQ34) -> 0 | FC34: =IF($I34<=15,ER34/2,ER34) -> 0 | FD34: =IF($I34<=15,ES34/2,ES34) -> 0 | ... FF34: =IF($I34<=15,EU34/2,EU34) -> 0 | FN34: =(((F34/30/8)*1.5)*(Q34+U34+Y34))-(AZ34+BI34+BR34) -> 0 | FO34: =(((F34/30/8)*2)*(S34+W34+AA34))-(BB34+BK34+BT34) -> 0 | FP34: =(SUM(AW34:CF34))-(SUM(CR34:DR34)) -> 0 | FQ34: =(F34/30*I34)-(CR34+DA34+DJ34) -> 0 | FR34: =(SUM(EL34:EU34))-((SUM(EW34:FF34))*$FR$5) -> 406.955
A35: 102050 | B35: 10 | C35: Chumil Chumil Glenda Rafaela | D35: Conserje | E35: PROQUIMA | F35: 4002.28 | G35: 250 | H35: =+F35+G35 -> 4252.28 | I35: 15 | J35: 1 | K35: 0 | L35: 0 | M35: 0 | N35: 0 | O35: =SUM(J35:N35) -> 1 | R35: =($F35/30/8*1.5)*Q35 -> 0 | T35: =($F35/30/8*2)*S35 -> 0 | V35: =($F35/30/8*1.5)*U35 -> 0 | X35: =($F35/30/8*2)*W35 -> 0 | Z35: =(($F35/30/8)*1.5)*Y35 -> 0 | AB35: =(($F35/30/8)*2)*AA35 -> 0 | AD35: =(($F35/30/8)*1.5)*AC35 -> 0 | AF35: =(($F35/30/8)*2)*AE35 -> 0 | AH35: =(($F35/30/8)*1.5)*AG35 -> 0 | AJ35: =(($F35/30/8)*2)*AI35 -> 0 | AW35: =((F35/30)*I35)*$J35 -> 2001.14 | AX35: =((G35/30)*I35)*$J35 -> 125 | AY35: =Q35 -> 0 | AZ35: =R35 -> 0 | BA35: =S35 -> 0 | BB35: =T35 -> 0 | BC35: =AK35+AP35 -> 0 | BD35: =(AW35+AZ35+BB35+BC35)*0.1267 -> 253.54444 | BE35: =SUM(AW35:BD35)-AY35-BA35 -> 2379.6844 | BF35: =(($F35/30)*$I35)*$K35 -> 0 | BG35: =(($G35/30)*$I35)*$K35 -> 0 | BH35: =U35 -> 0 | BI35: =V35 -> 0 | BJ35: =W35 -> 0 | BK35: =X35 -> 0 | BL35: =AL35+AQ35 -> 0 | BM35: =(+BF35+BI35+BK35+BL35)*0.1267 -> 0 | BN35: =SUM(BF35:BM35)-BH35-BJ35 -> 0 | BO35: =(($F35/30)*$I35)*$L35 -> 0 | BP35: =(($G35/30)*$I35)*$L35 -> 0 | BQ35: =Y35 -> 0 | BR35: =Z35 -> 0 | BS35: =AA35 -> 0 | BT35: =AB35 -> 0 | BU35: =AM35+AR35 -> 0 | BV35: =(BO35+BR35+BT35+BU35)*0.1267 -> 0 | BW35: =SUM(BO35:BV35)-BQ35-BS35 -> 0 | BX35: =(($F35/30)*$I35)*$M35 -> 0 | BY35: =(($G35/30)*$I35)*$M35 -> 0 | BZ35: =AC35 -> 0 | CA35: =AD35 -> 0 | CB35: =AE35 -> 0 | CC35: =AF35 -> 0 | CD35: =AN35+AS35 -> 0 | CE35: =(BX35+CA35+CC35)*0.09 -> 0 | CF35: =SUM(BX35:CE35)-BZ35-CB35 -> 0 | CG35: =(($F35/30)*$I35)*N35 -> 0 | CH35: =(($G35/30)*$I35)*$N35 -> 0 | CI35: =+AG35 -> 0 | CJ35: =AH35 -> 0 | CK35: =AI35 -> 0 | CL35: =AJ35 -> 0 | CM35: =AO35+AT35 -> 0 | CN35: =(CG35+CJ35+CL35)*0.09 -> 0 | CO35: =SUM(CG35:CN35)-CI35-CK35 -> 0 | CQ35: PROQUIMA | CR35: =IF($CQ35="PROQUIMA",$AW35+$BF35+$BO35+$BX35+$CG35,0) -> 2001.14 | CS35: =IF($CQ35="PROQUIMA",$AX35+$BG35+$BP35+$BY35+$CH35,0) -> 125 | CT35: =IF($CQ35="PROQUIMA",$AY35+$BH35+$BQ35+$BZ35+$CI35,0) -> 0 | CU35: =IF($CQ35="PROQUIMA",$AZ35+$BI35+$BR35+$CA35+$CJ35,0) -> 0 | CV35: =IF($CQ35="PROQUIMA",$BA35+$BJ35+$BS35+$CB35+$CK35,0) -> 0 | CW35: =IF($CQ35="PROQUIMA",$BB35+$BK35+$BT35+$CC35+$CL35,0) -> 0 | CX35: =IF($CQ35="PROQUIMA",$BC35+$BL35+$BU35+$CD35+$CM35,0) -> 0 | CY35: =IF($CQ35="PROQUIMA",$BD35+$BM35+$BV35+$CE35+CN35,0) -> 253.54444 | CZ35: =SUM(CR35:CY35)-CT35-CV35 -> 2379.6844 | DA35: =IF($CQ35="UNHESA",$AW35+$BF35+$BO35+$BX35+$CG35,0) -> 0 | DB35: =IF($CQ35="UNHESA",$AX35+$BG35+$BP35+$BY35+$CH35,0) -> 0 | DC35: =IF($CQ35="UNHESA",$AY35+$BH35+$BQ35+$BZ35+$CI35,0) -> 0 | DD35: =IF($CQ35="UNHESA",$AZ35+$BI35+$BR35+$CA35+$CJ35,0) -> 0 | DE35: =IF($CQ35="UNHESA",$BA35+$BJ35+$BS35+$CB35+$CK35,0) -> 0 | DF35: =IF($CQ35="UNHESA",$BB35+$BK35+$BT35+$CC35+$CL35,0) -> 0 | DG35: =IF($CQ35="UNHESA",$BC35+$BL35+$BU35+$CD35+$CM35,0) -> 0 | DH35: =IF($CQ35="UNHESA",$BD35+$BM35+$BV35+$CE35+$CN35,0) -> 0 | DI35: =SUM(DA35:DH35)-DC35-DE35 -> 0 | DJ35: =IF($CQ35="UNHESA LIQUIDOS",$AW35+$BF35+$BO35+$BX35+$CG35,0) -> 0 | DK35: =IF($CQ35="CALIDUL",$AX35+$BG35+$BP35+$BY35+$CH35,0) -> 0 | DL35: =IF($CQ35="CALIDUL",$AY35+$BH35+$BQ35+$BZ35+$CI35,0) -> 0 | DM35: =IF($CQ35="CALIDUL",$AZ35+$BI35+$BR35+$CA35+$CJ35,0) -> 0 | DN35: =IF($CQ35="CALIDUL",$BA35+$BJ35+$BS35+$CB35+$CK35,0) -> 0 | DO35: =IF($CQ35="CALIDUL",$BB35+$BK35+$BT35+$CC35+$CL35,0) -> 0 | DP35: =IF($CQ35="CALIDUL",$BC35+$BL35+$BU35+$CD35+$CM35,0) -> 0 | DQ35: =IF($CQ35="CALIDUL",$BD35+$BM35+$BV35+$CE35+$CN35,0) -> 0 | DR35: =SUM(DJ35:DQ35)-DL35-DN35 -> 0 | DS35: =IF($CQ35="ECONACIONAL",$AW35+$BF35+$BO35+$BX35+$CG35,0) -> 0 | DT35: =IF($CQ35="ECONACIONAL",$AX35+$BG35+$BP35+$BY35+$CH35,0) -> 0 | DU35: =IF($CQ35="ECONACIONAL",$AY35+$BH35+$BQ35+$BZ35+$CI35,0) -> 0 | DV35: =IF($CQ35="ECONACIONAL",$AZ35+$BI35+$BR35+$CA35+$CJ35,0) -> 0 | DW35: =IF($CQ35="ECONACIONAL",$BA35+$BJ35+$BS35+$CB35+$CK35,0) -> 0 | DX35: =IF($CQ35="ECONACIONAL",$BB35+$BK35+$BT35+$CC35+$CL35,0) -> 0 | DY35: =IF($CQ35="ECONACIONAL",$BC35+$BL35+$BU35+$CD35+$CM35,0) -> 0 | DZ35: =IF($CQ35="ECONACIONAL",$BD35+$BM35+$BV35+$CE35+$CN35,0) -> 0 | EA35: =SUM(DS35:DZ35)-DU35-DW35 -> 0 | EB35: =IF($CQ35="CLEARTEC",$AW35+$BF35+$BO35+$BX35+$CG35,0) -> 0 | EC35: =IF($CQ35="CLEARTEC",$AX35+$BG35+$BP35+$BY35+$CH35,0) -> 0 | ED35: =IF($CQ35="CLEARTEC",$AY35+$BH35+$BQ35+$BZ35+$CI35,0) -> 0 | EE35: =IF($CQ35="CLEARTEC",$AZ35+$BI35+$BR35+$CA35+$CJ35,0) -> 0 | EF35: =IF($CQ35="CLEARTEC",$BA35+$BJ35+$BS35+$CB35+$CK35,0) -> 0 | EG35: =IF($CQ35="CLEARTEC",$BB35+$BK35+$BT35+$CC35+$CL35,0) -> 0 | EH35: =IF($CQ35="CLEARTEC",$BC35+$BL35+$BU35+$CD35+$CM35,0) -> 0 | EI35: =IF($CQ35="CLEARTEC",$BD35+$BM35+$BV35+$CE35+$CN35,0) -> 0 | EJ35: =SUM(EB35:EI35)-ED35-EF35 -> 0 | EL35: 11.28 | EU35: =+EP35+EQ35+ER35 -> 0 | EW35: =IF($I35<=15,EL35/2,EL35) -> 5.64 | EX35: =IF($I35<=15,EM35/2,EM35) -> 0 | EY35: =IF($I35<=15,EN35/2,EN35) -> 0 | EZ35: =IF($I35<=15,EO35/2,EO35) -> 0 | FA35: =IF($I35<=15,EP35/2,EP35) -> 0 | FB35: =IF($I35<=15,EQ35/2,EQ35) -> 0 | FC35: =IF($I35<=15,ER35/2,ER35) -> 0 | FD35: =IF($I35<=15,ES35/2,ES35) -> 0 | ... FF35: =IF($I35<=15,EU35/2,EU35) -> 0 | FN35: =(((F35/30/8)*1.5)*(Q35+U35+Y35))-(AZ35+BI35+BR35) -> 0 | FO35: =(((F35/30/8)*2)*(S35+W35+AA35))-(BB35+BK35+BT35) -> 0 | FP35: =(SUM(AW35:CF35))-(SUM(CR35:DR35)) -> 0 | FQ35: =(F35/30*I35)-(CR35+DA35+DJ35) -> 0 | FR35: =(SUM(EL35:EU35))-((SUM(EW35:FF35))*$FR$5) -> 5.64
A36: 102050 | B36: 11 | C36: Equila Mejia Elsa Elena | D36: Conserje | E36: PROQUIMA | F36: 4002.28 | G36: 533.62 | H36: =+F36+G36 -> 4535.9 | I36: 15 | J36: 1 | K36: 0 | L36: 0 | M36: 0 | N36: 0 | O36: =SUM(J36:N36) -> 1 | P36: A.19/8/2025 | R36: =($F36/30/8*1.5)*Q36 -> 0 | T36: =($F36/30/8*2)*S36 -> 0 | V36: =($F36/30/8*1.5)*U36 -> 0 | X36: =($F36/30/8*2)*W36 -> 0 | Z36: =(($F36/30/8)*1.5)*Y36 -> 0 | AB36: =(($F36/30/8)*2)*AA36 -> 0 | AD36: =(($F36/30/8)*1.5)*AC36 -> 0 | AF36: =(($F36/30/8)*2)*AE36 -> 0 | AH36: =(($F36/30/8)*1.5)*AG36 -> 0 | AJ36: =(($F36/30/8)*2)*AI36 -> 0 | AW36: =((F36/30)*I36)*$J36 -> 2001.14 | AX36: =((G36/30)*I36)*$J36 -> 266.81 | AY36: =Q36 -> 0 | AZ36: =R36 -> 0 | BA36: =S36 -> 0 | BB36: =T36 -> 0 | BC36: =AK36+AP36 -> 0 | BD36: =(AW36+AZ36+BB36+BC36)*0.1267 -> 253.54444 | BE36: =SUM(AW36:BD36)-AY36-BA36 -> 2521.4944 | BF36: =(($F36/30)*$I36)*$K36 -> 0 | BG36: =(($G36/30)*$I36)*$K36 -> 0 | BH36: =U36 -> 0 | BI36: =V36 -> 0 | BJ36: =W36 -> 0 | BK36: =X36 -> 0 | BL36: =AL36+AQ36 -> 0 | BM36: =(+BF36+BI36+BK36+BL36)*0.1267 -> 0 | BN36: =SUM(BF36:BM36)-BH36-BJ36 -> 0 | BO36: =(($F36/30)*$I36)*$L36 -> 0 | BP36: =(($G36/30)*$I36)*$L36 -> 0 | BQ36: =Y36 -> 0 | BR36: =Z36 -> 0 | BS36: =AA36 -> 0 | BT36: =AB36 -> 0 | BU36: =AM36+AR36 -> 0 | BV36: =(BO36+BR36+BT36+BU36)*0.1267 -> 0 | BW36: =SUM(BO36:BV36)-BQ36-BS36 -> 0 | BX36: =(($F36/30)*$I36)*$M36 -> 0 | BY36: =(($G36/30)*$I36)*$M36 -> 0 | BZ36: =AC36 -> 0 | CA36: =AD36 -> 0 | CB36: =AE36 -> 0 | CC36: =AF36 -> 0 | CD36: =AN36+AS36 -> 0 | CE36: =(BX36+CA36+CC36)*0.09 -> 0 | CF36: =SUM(BX36:CE36)-BZ36-CB36 -> 0 | CG36: =(($F36/30)*$I36)*N36 -> 0 | CH36: =(($G36/30)*$I36)*$N36 -> 0 | CI36: =+AG36 -> 0 | CJ36: =AH36 -> 0 | CK36: =AI36 -> 0 | CL36: =AJ36 -> 0 | CM36: =AO36+AT36 -> 0 | CN36: =(CG36+CJ36+CL36)*0.09 -> 0 | CO36: =SUM(CG36:CN36)-CI36-CK36 -> 0 | CQ36: PROQUIMA | CR36: =IF($CQ36="PROQUIMA",$AW36+$BF36+$BO36+$BX36+$CG36,0) -> 2001.14 | CS36: =IF($CQ36="PROQUIMA",$AX36+$BG36+$BP36+$BY36+$CH36,0) -> 266.81 | CT36: =IF($CQ36="PROQUIMA",$AY36+$BH36+$BQ36+$BZ36+$CI36,0) -> 0 | CU36: =IF($CQ36="PROQUIMA",$AZ36+$BI36+$BR36+$CA36+$CJ36,0) -> 0 | CV36: =IF($CQ36="PROQUIMA",$BA36+$BJ36+$BS36+$CB36+$CK36,0) -> 0 | CW36: =IF($CQ36="PROQUIMA",$BB36+$BK36+$BT36+$CC36+$CL36,0) -> 0 | CX36: =IF($CQ36="PROQUIMA",$BC36+$BL36+$BU36+$CD36+$CM36,0) -> 0 | CY36: =IF($CQ36="PROQUIMA",$BD36+$BM36+$BV36+$CE36+CN36,0) -> 253.54444 | CZ36: =SUM(CR36:CY36)-CT36-CV36 -> 2521.4944 | DA36: =IF($CQ36="UNHESA",$AW36+$BF36+$BO36+$BX36+$CG36,0) -> 0 | DB36: =IF($CQ36="UNHESA",$AX36+$BG36+$BP36+$BY36+$CH36,0) -> 0 | DC36: =IF($CQ36="UNHESA",$AY36+$BH36+$BQ36+$BZ36+$CI36,0) -> 0 | DD36: =IF($CQ36="UNHESA",$AZ36+$BI36+$BR36+$CA36+$CJ36,0) -> 0 | DE36: =IF($CQ36="UNHESA",$BA36+$BJ36+$BS36+$CB36+$CK36,0) -> 0 | DF36: =IF($CQ36="UNHESA",$BB36+$BK36+$BT36+$CC36+$CL36,0) -> 0 | DG36: =IF($CQ36="UNHESA",$BC36+$BL36+$BU36+$CD36+$CM36,0) -> 0 | DH36: =IF($CQ36="UNHESA",$BD36+$BM36+$BV36+$CE36+$CN36,0) -> 0 | DI36: =SUM(DA36:DH36)-DC36-DE36 -> 0 | DJ36: =IF($CQ36="UNHESA LIQUIDOS",$AW36+$BF36+$BO36+$BX36+$CG36,0) -> 0 | DK36: =IF($CQ36="CALIDUL",$AX36+$BG36+$BP36+$BY36+$CH36,0) -> 0 | DL36: =IF($CQ36="CALIDUL",$AY36+$BH36+$BQ36+$BZ36+$CI36,0) -> 0 | DM36: =IF($CQ36="CALIDUL",$AZ36+$BI36+$BR36+$CA36+$CJ36,0) -> 0 | DN36: =IF($CQ36="CALIDUL",$BA36+$BJ36+$BS36+$CB36+$CK36,0) -> 0 | DO36: =IF($CQ36="CALIDUL",$BB36+$BK36+$BT36+$CC36+$CL36,0) -> 0 | DP36: =IF($CQ36="CALIDUL",$BC36+$BL36+$BU36+$CD36+$CM36,0) -> 0 | DQ36: =IF($CQ36="CALIDUL",$BD36+$BM36+$BV36+$CE36+$CN36,0) -> 0 | DR36: =SUM(DJ36:DQ36)-DL36-DN36 -> 0 | DS36: =IF($CQ36="ECONACIONAL",$AW36+$BF36+$BO36+$BX36+$CG36,0) -> 0 | DT36: =IF($CQ36="ECONACIONAL",$AX36+$BG36+$BP36+$BY36+$CH36,0) -> 0 | DU36: =IF($CQ36="ECONACIONAL",$AY36+$BH36+$BQ36+$BZ36+$CI36,0) -> 0 | DV36: =IF($CQ36="ECONACIONAL",$AZ36+$BI36+$BR36+$CA36+$CJ36,0) -> 0 | DW36: =IF($CQ36="ECONACIONAL",$BA36+$BJ36+$BS36+$CB36+$CK36,0) -> 0 | DX36: =IF($CQ36="ECONACIONAL",$BB36+$BK36+$BT36+$CC36+$CL36,0) -> 0 | DY36: =IF($CQ36="ECONACIONAL",$BC36+$BL36+$BU36+$CD36+$CM36,0) -> 0 | DZ36: =IF($CQ36="ECONACIONAL",$BD36+$BM36+$BV36+$CE36+$CN36,0) -> 0 | EA36: =SUM(DS36:DZ36)-DU36-DW36 -> 0 | EB36: =IF($CQ36="CLEARTEC",$AW36+$BF36+$BO36+$BX36+$CG36,0) -> 0 | EC36: =IF($CQ36="CLEARTEC",$AX36+$BG36+$BP36+$BY36+$CH36,0) -> 0 | ED36: =IF($CQ36="CLEARTEC",$AY36+$BH36+$BQ36+$BZ36+$CI36,0) -> 0 | EE36: =IF($CQ36="CLEARTEC",$AZ36+$BI36+$BR36+$CA36+$CJ36,0) -> 0 | EF36: =IF($CQ36="CLEARTEC",$BA36+$BJ36+$BS36+$CB36+$CK36,0) -> 0 | EG36: =IF($CQ36="CLEARTEC",$BB36+$BK36+$BT36+$CC36+$CL36,0) -> 0 | EH36: =IF($CQ36="CLEARTEC",$BC36+$BL36+$BU36+$CD36+$CM36,0) -> 0 | EI36: =IF($CQ36="CLEARTEC",$BD36+$BM36+$BV36+$CE36+$CN36,0) -> 0 | EJ36: =SUM(EB36:EI36)-ED36-EF36 -> 0 | EL36: 17.13 | EU36: =+EP36+EQ36+ER36 -> 0 | EW36: =IF($I36<=15,EL36/2,EL36) -> 8.565 | EX36: =IF($I36<=15,EM36/2,EM36) -> 0 | EY36: =IF($I36<=15,EN36/2,EN36) -> 0 | EZ36: =IF($I36<=15,EO36/2,EO36) -> 0 | FA36: =IF($I36<=15,EP36/2,EP36) -> 0 | FB36: =IF($I36<=15,EQ36/2,EQ36) -> 0 | FC36: =IF($I36<=15,ER36/2,ER36) -> 0 | FD36: =IF($I36<=15,ES36/2,ES36) -> 0 | ... FF36: =IF($I36<=15,EU36/2,EU36) -> 0
A37: 102050
A38: 102050 | D38: Total Administrativo | F38: =SUM(F34:F37) -> 12006.84 | G38: =SUM(G34:G37) -> 1033.62 | H38: =SUM(H34:H37) -> 13040.46 | Q38: =SUM(Q34:Q37) -> 0 | R38: =SUM(R34:R37) -> 0 | S38: =SUM(S34:S37) -> 0 | T38: =SUM(T34:T37) -> 0 | U38: =SUM(U34:U37) -> 0 | V38: =SUM(V34:V37) -> 0 | W38: =SUM(W34:W37) -> 0 | X38: =SUM(X34:X37) -> 0 | ... FF38: =SUM(FF34:FF37) -> 0
A40: 102020 | C40: MENSAJERIA
A41: 102020 | B41: 12 | C41: Alpuaque Aragon Sergio Antonio | D41: Mensajero | E41: PROQUIMA | F41: 4002.28 | G41: 370 | H41: =+F41+G41 -> 4372.28 | I41: 15 | J41: 1 | K41: 0 | L41: 0 | M41: 0 | N41: 0 | O41: =SUM(J41:N41) -> 1 | R41: =($F41/30/8*1.5)*Q41 -> 0 | T41: =($F41/30/8*2)*S41 -> 0 | V41: =($F41/30/8*1.5)*U41 -> 0 | X41: =($F41/30/8*2)*W41 -> 0 | Z41: =(($F41/30/8)*1.5)*Y41 -> 0 | AB41: =(($F41/30/8)*2)*AA41 -> 0 | AD41: =(($F41/30/8)*1.5)*AC41 -> 0 | AF41: =(($F41/30/8)*2)*AE41 -> 0 | AH41: =(($F41/30/8)*1.5)*AG41 -> 0 | AJ41: =(($F41/30/8)*2)*AI41 -> 0 | AW41: =((F41/30)*I41)*$J41 -> 2001.14 | AX41: =((G41/30)*I41)*$J41 -> 185 | AY41: =Q41 -> 0 | AZ41: =R41 -> 0 | BA41: =S41 -> 0 | BB41: =T41 -> 0 | BC41: =AK41+AP41 -> 0 | BD41: =(AW41+AZ41+BB41+BC41)*0.1267 -> 253.54444 | BE41: =SUM(AW41:BD41)-AY41-BA41 -> 2439.6844 | BF41: =(($F41/30)*$I41)*$K41 -> 0 | BG41: =(($G41/30)*$I41)*$K41 -> 0 | BH41: =U41 -> 0 | BI41: =V41 -> 0 | BJ41: =W41 -> 0 | BK41: =X41 -> 0 | BL41: =AL41+AQ41 -> 0 | BM41: =(+BF41+BI41+BK41+BL41)*0.1267 -> 0 | BN41: =SUM(BF41:BM41)-BH41-BJ41 -> 0 | BO41: =(($F41/30)*$I41)*$L41 -> 0 | BP41: =(($G41/30)*$I41)*$L41 -> 0 | BQ41: =Y41 -> 0 | BR41: =Z41 -> 0 | BS41: =AA41 -> 0 | BT41: =AB41 -> 0 | BU41: =AM41+AR41 -> 0 | BV41: =(BO41+BR41+BT41+BU41)*0.1267 -> 0 | BW41: =SUM(BO41:BV41)-BQ41-BS41 -> 0 | BX41: =(($F41/30)*$I41)*$M41 -> 0 | BY41: =(($G41/30)*$I41)*$M41 -> 0 | BZ41: =AC41 -> 0 | CA41: =AD41 -> 0 | CB41: =AE41 -> 0 | CC41: =AF41 -> 0 | CD41: =AN41+AS41 -> 0 | CE41: =(BX41+CA41+CC41)*0.09 -> 0 | CF41: =SUM(BX41:CE41)-BZ41-CB41 -> 0 | CG41: =(($F41/30)*$I41)*N41 -> 0 | CH41: =(($G41/30)*$I41)*$N41 -> 0 | CI41: =+AG41 -> 0 | CJ41: =AH41 -> 0 | CK41: =AI41 -> 0 | CL41: =AJ41 -> 0 | CM41: =AO41+AT41 -> 0 | CN41: =(CG41+CJ41+CL41)*0.09 -> 0 | CO41: =SUM(CG41:CN41)-CI41-CK41 -> 0 | CQ41: PROQUIMA | CR41: =IF($CQ41="PROQUIMA",$AW41+$BF41+$BO41+$BX41+$CG41,0) -> 2001.14 | CS41: =IF($CQ41="PROQUIMA",$AX41+$BG41+$BP41+$BY41+$CH41,0) -> 185 | CT41: =IF($CQ41="PROQUIMA",$AY41+$BH41+$BQ41+$BZ41+$CI41,0) -> 0 | CU41: =IF($CQ41="PROQUIMA",$AZ41+$BI41+$BR41+$CA41+$CJ41,0) -> 0 | CV41: =IF($CQ41="PROQUIMA",$BA41+$BJ41+$BS41+$CB41+$CK41,0) -> 0 | CW41: =IF($CQ41="PROQUIMA",$BB41+$BK41+$BT41+$CC41+$CL41,0) -> 0 | CX41: =IF($CQ41="PROQUIMA",$BC41+$BL41+$BU41+$CD41+$CM41,0) -> 0 | CY41: =IF($CQ41="PROQUIMA",$BD41+$BM41+$BV41+$CE41+CN41,0) -> 253.54444 | CZ41: =SUM(CR41:CY41)-CT41-CV41 -> 2439.6844 | DA41: =IF($CQ41="UNHESA",$AW41+$BF41+$BO41+$BX41+$CG41,0) -> 0 | DB41: =IF($CQ41="UNHESA",$AX41+$BG41+$BP41+$BY41+$CH41,0) -> 0 | DC41: =IF($CQ41="UNHESA",$AY41+$BH41+$BQ41+$BZ41+$CI41,0) -> 0 | DD41: =IF($CQ41="UNHESA",$AZ41+$BI41+$BR41+$CA41+$CJ41,0) -> 0 | DE41: =IF($CQ41="UNHESA",$BA41+$BJ41+$BS41+$CB41+$CK41,0) -> 0 | DF41: =IF($CQ41="UNHESA",$BB41+$BK41+$BT41+$CC41+$CL41,0) -> 0 | DG41: =IF($CQ41="UNHESA",$BC41+$BL41+$BU41+$CD41+$CM41,0) -> 0 | DH41: =IF($CQ41="UNHESA",$BD41+$BM41+$BV41+$CE41+$CN41,0) -> 0 | DI41: =SUM(DA41:DH41)-DC41-DE41 -> 0 | DJ41: =IF($CQ41="UNHESA LIQUIDOS",$AW41+$BF41+$BO41+$BX41+$CG41,0) -> 0 | DK41: =IF($CQ41="CALIDUL",$AX41+$BG41+$BP41+$BY41+$CH41,0) -> 0 | DL41: =IF($CQ41="CALIDUL",$AY41+$BH41+$BQ41+$BZ41+$CI41,0) -> 0 | DM41: =IF($CQ41="CALIDUL",$AZ41+$BI41+$BR41+$CA41+$CJ41,0) -> 0 | DN41: =IF($CQ41="CALIDUL",$BA41+$BJ41+$BS41+$CB41+$CK41,0) -> 0 | DO41: =IF($CQ41="CALIDUL",$BB41+$BK41+$BT41+$CC41+$CL41,0) -> 0 | DP41: =IF($CQ41="CALIDUL",$BC41+$BL41+$BU41+$CD41+$CM41,0) -> 0 | DQ41: =IF($CQ41="CALIDUL",$BD41+$BM41+$BV41+$CE41+$CN41,0) -> 0 | DR41: =SUM(DJ41:DQ41)-DL41-DN41 -> 0 | DS41: =IF($CQ41="ECONACIONAL",$AW41+$BF41+$BO41+$BX41+$CG41,0) -> 0 | DT41: =IF($CQ41="ECONACIONAL",$AX41+$BG41+$BP41+$BY41+$CH41,0) -> 0 | DU41: =IF($CQ41="ECONACIONAL",$AY41+$BH41+$BQ41+$BZ41+$CI41,0) -> 0 | DV41: =IF($CQ41="ECONACIONAL",$AZ41+$BI41+$BR41+$CA41+$CJ41,0) -> 0 | DW41: =IF($CQ41="ECONACIONAL",$BA41+$BJ41+$BS41+$CB41+$CK41,0) -> 0 | DX41: =IF($CQ41="ECONACIONAL",$BB41+$BK41+$BT41+$CC41+$CL41,0) -> 0 | DY41: =IF($CQ41="ECONACIONAL",$BC41+$BL41+$BU41+$CD41+$CM41,0) -> 0 | DZ41: =IF($CQ41="ECONACIONAL",$BD41+$BM41+$BV41+$CE41+$CN41,0) -> 0 | EA41: =SUM(DS41:DZ41)-DU41-DW41 -> 0 | EB41: =IF($CQ41="CLEARTEC",$AW41+$BF41+$BO41+$BX41+$CG41,0) -> 0 | EC41: =IF($CQ41="CLEARTEC",$AX41+$BG41+$BP41+$BY41+$CH41,0) -> 0 | ED41: =IF($CQ41="CLEARTEC",$AY41+$BH41+$BQ41+$BZ41+$CI41,0) -> 0 | EE41: =IF($CQ41="CLEARTEC",$AZ41+$BI41+$BR41+$CA41+$CJ41,0) -> 0 | EF41: =IF($CQ41="CLEARTEC",$BA41+$BJ41+$BS41+$CB41+$CK41,0) -> 0 | EG41: =IF($CQ41="CLEARTEC",$BB41+$BK41+$BT41+$CC41+$CL41,0) -> 0 | EH41: =IF($CQ41="CLEARTEC",$BC41+$BL41+$BU41+$CD41+$CM41,0) -> 0 | EI41: =IF($CQ41="CLEARTEC",$BD41+$BM41+$BV41+$CE41+$CN41,0) -> 0 | EJ41: =SUM(EB41:EI41)-ED41-EF41 -> 0 | EL41: 8.96 | EU41: =+EP41+EQ41+ER41 -> 0 | EW41: =IF($I41<=15,EL41/2,EL41) -> 4.48 | EX41: =IF($I41<=15,EM41/2,EM41) -> 0 | EY41: =IF($I41<=15,EN41/2,EN41) -> 0 | EZ41: =IF($I41<=15,EO41/2,EO41) -> 0 | FA41: =IF($I41<=15,EP41/2,EP41) -> 0 | FB41: =IF($I41<=15,EQ41/2,EQ41) -> 0 | FC41: =IF($I41<=15,ER41/2,ER41) -> 0 | FD41: =IF($I41<=15,ES41/2,ES41) -> 0 | ... FF41: =IF($I41<=15,EU41/2,EU41) -> 0 | FG41: 1 | FH41: 0 | FI41: 0 | FJ41: 0 | FK41: 0 | FL41: 1 | FN41: =(((F41/30/8)*1.5)*(Q41+U41+Y41))-(AZ41+BI41+BR41) -> 0 | FO41: =(((F41/30/8)*2)*(S41+W41+AA41))-(BB41+BK41+BT41) -> 0 | FP41: =(SUM(AW41:CF41))-(SUM(CR41:DR41)) -> 0 | FQ41: =(F41/30*I41)-(CR41+DA41+DJ41) -> 0 | FR41: =(SUM(EL41:EU41))-((SUM(EW41:FF41))*$FR$5) -> 4.48
A42: 102020 | B42: 13 | C42: Morales Boteo Oliver Edmilzon | D42: Mensajero | E42: PROQUIMA | F42: 4002.28 | G42: 370 | H42: =+F42+G42 -> 4372.28 | I42: 15 | J42: 1 | K42: 0 | L42: 0 | M42: 0 | N42: 0 | O42: =SUM(J42:N42) -> 1 | R42: =($F42/30/8*1.5)*Q42 -> 0 | T42: =($F42/30/8*2)*S42 -> 0 | V42: =($F42/30/8*1.5)*U42 -> 0 | X42: =($F42/30/8*2)*W42 -> 0 | Z42: =(($F42/30/8)*1.5)*Y42 -> 0 | AB42: =(($F42/30/8)*2)*AA42 -> 0 | AD42: =(($F42/30/8)*1.5)*AC42 -> 0 | AF42: =(($F42/30/8)*2)*AE42 -> 0 | AH42: =(($F42/30/8)*1.5)*AG42 -> 0 | AJ42: =(($F42/30/8)*2)*AI42 -> 0 | AW42: =((F42/30)*I42)*$J42 -> 2001.14 | AX42: =((G42/30)*I42)*$J42 -> 185 | AY42: =Q42 -> 0 | AZ42: =R42 -> 0 | BA42: =S42 -> 0 | BB42: =T42 -> 0 | BC42: =AK42+AP42 -> 0 | BD42: =(AW42+AZ42+BB42+BC42)*0.1267 -> 253.54444 | BE42: =SUM(AW42:BD42)-AY42-BA42 -> 2439.6844 | BF42: =(($F42/30)*$I42)*$K42 -> 0 | BG42: =(($G42/30)*$I42)*$K42 -> 0 | BH42: =U42 -> 0 | BI42: =V42 -> 0 | BJ42: =W42 -> 0 | BK42: =X42 -> 0 | BL42: =AL42+AQ42 -> 0 | BM42: =(+BF42+BI42+BK42+BL42)*0.1267 -> 0 | BN42: =SUM(BF42:BM42)-BH42-BJ42 -> 0 | BO42: =(($F42/30)*$I42)*$L42 -> 0 | BP42: =(($G42/30)*$I42)*$L42 -> 0 | BQ42: =Y42 -> 0 | BR42: =Z42 -> 0 | BS42: =AA42 -> 0 | BT42: =AB42 -> 0 | BU42: =AM42+AR42 -> 0 | BV42: =(BO42+BR42+BT42+BU42)*0.1267 -> 0 | BW42: =SUM(BO42:BV42)-BQ42-BS42 -> 0 | BX42: =(($F42/30)*$I42)*$M42 -> 0 | BY42: =(($G42/30)*$I42)*$M42 -> 0 | BZ42: =AC42 -> 0 | CA42: =AD42 -> 0 | CB42: =AE42 -> 0 | CC42: =AF42 -> 0 | CD42: =AN42+AS42 -> 0 | CE42: =(BX42+CA42+CC42)*0.09 -> 0 | CF42: =SUM(BX42:CE42)-BZ42-CB42 -> 0 | CG42: =(($F42/30)*$I42)*N42 -> 0 | CH42: =(($G42/30)*$I42)*$N42 -> 0 | CI42: =+AG42 -> 0 | CJ42: =AH42 -> 0 | CK42: =AI42 -> 0 | CL42: =AJ42 -> 0 | CM42: =AO42+AT42 -> 0 | CN42: =(CG42+CJ42+CL42)*0.09 -> 0 | CO42: =SUM(CG42:CN42)-CI42-CK42 -> 0 | CQ42: PROQUIMA | CR42: =IF($CQ42="PROQUIMA",$AW42+$BF42+$BO42+$BX42+$CG42,0) -> 2001.14 | CS42: =IF($CQ42="PROQUIMA",$AX42+$BG42+$BP42+$BY42+$CH42,0) -> 185 | CT42: =IF($CQ42="PROQUIMA",$AY42+$BH42+$BQ42+$BZ42+$CI42,0) -> 0 | CU42: =IF($CQ42="PROQUIMA",$AZ42+$BI42+$BR42+$CA42+$CJ42,0) -> 0 | CV42: =IF($CQ42="PROQUIMA",$BA42+$BJ42+$BS42+$CB42+$CK42,0) -> 0 | CW42: =IF($CQ42="PROQUIMA",$BB42+$BK42+$BT42+$CC42+$CL42,0) -> 0 | CX42: =IF($CQ42="PROQUIMA",$BC42+$BL42+$BU42+$CD42+$CM42,0) -> 0 | CY42: =IF($CQ42="PROQUIMA",$BD42+$BM42+$BV42+$CE42+CN42,0) -> 253.54444 | CZ42: =SUM(CR42:CY42)-CT42-CV42 -> 2439.6844 | DA42: =IF($CQ42="UNHESA",$AW42+$BF42+$BO42+$BX42+$CG42,0) -> 0 | DB42: =IF($CQ42="UNHESA",$AX42+$BG42+$BP42+$BY42+$CH42,0) -> 0 | DC42: =IF($CQ42="UNHESA",$AY42+$BH42+$BQ42+$BZ42+$CI42,0) -> 0 | DD42: =IF($CQ42="UNHESA",$AZ42+$BI42+$BR42+$CA42+$CJ42,0) -> 0 | DE42: =IF($CQ42="UNHESA",$BA42+$BJ42+$BS42+$CB42+$CK42,0) -> 0 | DF42: =IF($CQ42="UNHESA",$BB42+$BK42+$BT42+$CC42+$CL42,0) -> 0 | DG42: =IF($CQ42="UNHESA",$BC42+$BL42+$BU42+$CD42+$CM42,0) -> 0 | DH42: =IF($CQ42="UNHESA",$BD42+$BM42+$BV42+$CE42+$CN42,0) -> 0 | DI42: =SUM(DA42:DH42)-DC42-DE42 -> 0 | DJ42: =IF($CQ42="UNHESA LIQUIDOS",$AW42+$BF42+$BO42+$BX42+$CG42,0) -> 0 | DK42: =IF($CQ42="CALIDUL",$AX42+$BG42+$BP42+$BY42+$CH42,0) -> 0 | DL42: =IF($CQ42="CALIDUL",$AY42+$BH42+$BQ42+$BZ42+$CI42,0) -> 0 | DM42: =IF($CQ42="CALIDUL",$AZ42+$BI42+$BR42+$CA42+$CJ42,0) -> 0 | DN42: =IF($CQ42="CALIDUL",$BA42+$BJ42+$BS42+$CB42+$CK42,0) -> 0 | DO42: =IF($CQ42="CALIDUL",$BB42+$BK42+$BT42+$CC42+$CL42,0) -> 0 | DP42: =IF($CQ42="CALIDUL",$BC42+$BL42+$BU42+$CD42+$CM42,0) -> 0 | DQ42: =IF($CQ42="CALIDUL",$BD42+$BM42+$BV42+$CE42+$CN42,0) -> 0 | DR42: =SUM(DJ42:DQ42)-DL42-DN42 -> 0 | DS42: =IF($CQ42="ECONACIONAL",$AW42+$BF42+$BO42+$BX42+$CG42,0) -> 0 | DT42: =IF($CQ42="ECONACIONAL",$AX42+$BG42+$BP42+$BY42+$CH42,0) -> 0 | DU42: =IF($CQ42="ECONACIONAL",$AY42+$BH42+$BQ42+$BZ42+$CI42,0) -> 0 | DV42: =IF($CQ42="ECONACIONAL",$AZ42+$BI42+$BR42+$CA42+$CJ42,0) -> 0 | DW42: =IF($CQ42="ECONACIONAL",$BA42+$BJ42+$BS42+$CB42+$CK42,0) -> 0 | DX42: =IF($CQ42="ECONACIONAL",$BB42+$BK42+$BT42+$CC42+$CL42,0) -> 0 | DY42: =IF($CQ42="ECONACIONAL",$BC42+$BL42+$BU42+$CD42+$CM42,0) -> 0 | DZ42: =IF($CQ42="ECONACIONAL",$BD42+$BM42+$BV42+$CE42+$CN42,0) -> 0 | EA42: =SUM(DS42:DZ42)-DU42-DW42 -> 0 | EB42: =IF($CQ42="CLEARTEC",$AW42+$BF42+$BO42+$BX42+$CG42,0) -> 0 | EC42: =IF($CQ42="CLEARTEC",$AX42+$BG42+$BP42+$BY42+$CH42,0) -> 0 | ED42: =IF($CQ42="CLEARTEC",$AY42+$BH42+$BQ42+$BZ42+$CI42,0) -> 0 | EE42: =IF($CQ42="CLEARTEC",$AZ42+$BI42+$BR42+$CA42+$CJ42,0) -> 0 | EF42: =IF($CQ42="CLEARTEC",$BA42+$BJ42+$BS42+$CB42+$CK42,0) -> 0 | EG42: =IF($CQ42="CLEARTEC",$BB42+$BK42+$BT42+$CC42+$CL42,0) -> 0 | EH42: =IF($CQ42="CLEARTEC",$BC42+$BL42+$BU42+$CD42+$CM42,0) -> 0 | EI42: =IF($CQ42="CLEARTEC",$BD42+$BM42+$BV42+$CE42+$CN42,0) -> 0 | EJ42: =SUM(EB42:EI42)-ED42-EF42 -> 0 | EL42: 8.97 | ER42: 1242.87 | EU42: =+EP42+EQ42+ER42 -> 1242.87 | EW42: =IF($I42<=15,EL42/2,EL42) -> 4.485 | EX42: =IF($I42<=15,EM42/2,EM42) -> 0 | EY42: =IF($I42<=15,EN42/2,EN42) -> 0 | EZ42: =IF($I42<=15,EO42/2,EO42) -> 0 | FA42: =IF($I42<=15,EP42/2,EP42) -> 0 | FB42: =IF($I42<=15,EQ42/2,EQ42) -> 0 | FC42: =IF($I42<=15,ER42/2,ER42) -> 621.435 | FD42: =IF($I42<=15,ES42/2,ES42) -> 0 | ... FF42: =IF($I42<=15,EU42/2,EU42) -> 621.435 | FN42: =(((F42/30/8)*1.5)*(Q42+U42+Y42))-(AZ42+BI42+BR42) -> 0 | FO42: =(((F42/30/8)*2)*(S42+W42+AA42))-(BB42+BK42+BT42) -> 0 | FP42: =(SUM(AW42:CF42))-(SUM(CR42:DR42)) -> 0 | FQ42: =(F42/30*I42)-(CR42+DA42+DJ42) -> 0 | FR42: =(SUM(EL42:EU42))-((SUM(EW42:FF42))*$FR$5) -> 1247.355
A43: 102020 | D43: Total Administrativo | F43: =SUM(F41:F42) -> 8004.56 | G43: =SUM(G41:G42) -> 740 | H43: =SUM(H41:H42) -> 8744.56 | Q43: =SUM(Q41:Q42) -> 0 | R43: =SUM(R41:R42) -> 0 | S43: =SUM(S41:S42) -> 0 | T43: =SUM(T41:T42) -> 0 | U43: =SUM(U41:U42) -> 0 | V43: =SUM(V41:V42) -> 0 | W43: =SUM(W41:W42) -> 0 | X43: =SUM(X41:X42) -> 0 | ... FF43: =SUM(FF41:FF42) -> 621.435
A45: 102030 | C45: RECEPCION
A46: 102030 | EU46: =+EP46+EQ46+ER46 -> 0 | FN46: =(((F46/30/8)*1.5)*(Q46+U46+Y46))-(AZ46+BI46+BR46) -> 0 | FO46: =(((F46/30/8)*2)*(S46+W46+AA46))-(BB46+BK46+BT46) -> 0 | FP46: =(SUM(AW46:CF46))-(SUM(CR46:DR46)) -> 0 | FQ46: =(F46/30*I46)-(CR46+DA46+DJ46) -> 0 | FR46: =(SUM(EL46:EU46))-((SUM(EW46:FF46))*$FR$5) -> 0
A47: 102030 | F47: =+F46 -> 0 | G47: =+G46 -> 0 | H47: =+H46 -> 0 | Q47: =+Q46 -> 0 | R47: =+R46 -> 0 | S47: =+S46 -> 0 | T47: =+T46 -> 0 | U47: =+U46 -> 0 | V47: =+V46 -> 0 | W47: =+W46 -> 0 | X47: =+X46 -> 0 | ... FF47: =+FF46 -> 0
A49: 102040 | C49: PROYECTOS
A50: 102040 | EU50: =+EP50+EQ50+ER50 -> 0 | FN50: =(((F50/30/8)*1.5)*(Q50+U50+Y50))-(AZ50+BI50+BR50) -> 0 | FO50: =(((F50/30/8)*2)*(S50+W50+AA50))-(BB50+BK50+BT50) -> 0 | FP50: =(SUM(AW50:CF50))-(SUM(CR50:DR50)) -> 0 | FQ50: =(F50/30*I50)-(CR50+DA50+DJ50) -> 0 | FR50: =(SUM(EL50:EU50))-((SUM(EW50:FF50))*$FR$5) -> 0
A51: 102040 | D51: TOTAL ADMINISTRATIVO | F51: =+F50 -> 0 | G51: =+G50 -> 0 | H51: =+H50 -> 0 | Q51: =+Q50 -> 0 | R51: =+R50 -> 0 | S51: =+S50 -> 0 | T51: =+T50 -> 0 | U51: =+U50 -> 0 | V51: =+V50 -> 0 | W51: =+W50 -> 0 | X51: =+X50 -> 0 | ... FF51: =+FF50 -> 0
A53: 103010 | C53: RECURSOS HUMANOS
A54: 103010 | C54: Administracion
A55: 103010 | EU55: =+EP55+EQ55+ER55 -> 0 | FN55: =(((F55/30/8)*1.5)*(Q55+U55+Y55))-(AZ55+BI55+BR55) -> 0 | FO55: =(((F55/30/8)*2)*(S55+W55+AA55))-(BB55+BK55+BT55) -> 0 | FP55: =(SUM(AW55:CF55))-(SUM(CR55:DR55)) -> 0 | FQ55: =(F55/30*I55)-(CR55+DA55+DJ55) -> 0 | FR55: =(SUM(EL55:EU55))-((SUM(EW55:FF55))*$FR$5) -> 0
A56: 103010 | D56: TotaL Recursos Humanos | F56: =SUM(F55:F55) -> 0 | G56: =SUM(G55:G55) -> 0 | H56: =SUM(H55:H55) -> 0 | Q56: =SUM(Q55:Q55) -> 0 | R56: =SUM(R55:R55) -> 0 | S56: =SUM(S55:S55) -> 0 | T56: =SUM(T55:T55) -> 0 | U56: =SUM(U55:U55) -> 0 | V56: =SUM(V55:V55) -> 0 | W56: =SUM(W55:W55) -> 0 | X56: =SUM(X55:X55) -> 0 | ... FF56: =SUM(FF55:FF55) -> 0
A58: 104010 | C58: INFORMATICA
A59: 104010 | C59: Administracion
A60: 104010 | EU60: =+EP60+EQ60+ER60 -> 0 | FN60: =(((F60/30/8)*1.5)*(Q60+U60+Y60))-(AZ60+BI60+BR60) -> 0 | FO60: =(((F60/30/8)*2)*(S60+W60+AA60))-(BB60+BK60+BT60) -> 0 | FP60: =(SUM(AW60:CF60))-(SUM(CR60:DR60)) -> 0 | FQ60: =(F60/30*I60)-(CR60+DA60+DJ60) -> 0 | FR60: =(SUM(EL60:EU60))-((SUM(EW60:FF60))*$FR$5) -> 0
A61: 104010 | D61: Total Informatica | F61: =+SUM(F60:F60) -> 0 | G61: =+SUM(G60:G60) -> 0 | H61: =+SUM(H60:H60) -> 0 | Q61: =+SUM(Q60:Q60) -> 0 | R61: =+SUM(R60:R60) -> 0 | S61: =+SUM(S60:S60) -> 0 | T61: =+SUM(T60:T60) -> 0 | U61: =+SUM(U60:U60) -> 0 | V61: =+SUM(V60:V60) -> 0 | W61: =+SUM(W60:W60) -> 0 | X61: =+SUM(X60:X60) -> 0 | ... FF61: =+SUM(FF60:FF60) -> 0
A63: 105010 | C63: Auditoria Interna
A64: 105010 | C64: Administracion
A65: 105010 | FN65: =(((F65/30/8)*1.5)*(Q65+U65+Y65))-(AZ65+BI65+BR65) -> 0 | FO65: =(((F65/30/8)*2)*(S65+W65+AA65))-(BB65+BK65+BT65) -> 0 | FP65: =(SUM(AW65:CF65))-(SUM(CR65:DR65)) -> 0 | FQ65: =(F65/30*I65)-(CR65+DA65+DJ65) -> 0 | FR65: =(SUM(EL65:EU65))-((SUM(EW65:FF65))*$FR$5) -> 0
A66: 105010 | D66: total Auditoria | F66: =SUM(F65:F65) -> 0 | G66: =SUM(G65:G65) -> 0 | H66: =SUM(H65:H65) -> 0 | Q66: =SUM(Q65:Q65) -> 0 | R66: =SUM(R65:R65) -> 0 | S66: =SUM(S65:S65) -> 0 | T66: =SUM(T65:T65) -> 0 | U66: =SUM(U65:U65) -> 0 | V66: =SUM(V65:V65) -> 0 | W66: =SUM(W65:W65) -> 0 | X66: =SUM(X65:X65) -> 0 | ... FF66: =SUM(FF65:FF65) -> 0
A68: 106010 | C68: Contable Financiero
A69: 106010 | C69: Administracion
A70: 106010 | EU70: =+EP70+EQ70+ER70 -> 0
A71: c | C71: Contabiliad | EU71: =+EP71+EQ71+ER71 -> 0
A72: 106020 | C72: Lago Martinez Jhonatan Josue | D72: Contador Jr | E72: PROQUIMA | F72: 4850 | G72: 900 | H72: =+F72+G72 -> 5750 | I72: 15 | J72: 1 | L72: 0 | M72: 0 | N72: 0 | O72: =SUM(J72:N72) -> 1 | P72: a.19.11 en abril y oct 26 revision paraincremento salarial | R72: =($F72/30/8*1.5)*Q72 -> 0 | T72: =($F72/30/8*2)*S72 -> 0 | V72: =($F72/30/8*1.5)*U72 -> 0 | X72: =($F72/30/8*2)*W72 -> 0 | Z72: =(($F72/30/8)*1.5)*Y72 -> 0 | AB72: =(($F72/30/8)*2)*AA72 -> 0 | AD72: =(($F72/30/8)*1.5)*AC72 -> 0 | AF72: =(($F72/30/8)*2)*AE72 -> 0 | AH72: =(($F72/30/8)*1.5)*AG72 -> 0 | AJ72: =(($F72/30/8)*2)*AI72 -> 0 | AW72: =((F72/30)*I72)*$J72 -> 2425 | AX72: =((G72/30)*I72)*$J72 -> 450 | AY72: =Q72 -> 0 | AZ72: =R72 -> 0 | BA72: =S72 -> 0 | BB72: =T72 -> 0 | BC72: =AK72+AP72 -> 0 | BD72: =(AW72+AZ72+BB72+BC72)*0.1267 -> 307.2475 | BE72: =SUM(AW72:BD72)-AY72-BA72 -> 3182.2475 | BF72: =(($F72/30)*$I72)*$K72 -> 0 | BG72: =(($G72/30)*$I72)*$K72 -> 0 | BH72: =U72 -> 0 | BI72: =V72 -> 0 | BJ72: =W72 -> 0 | BK72: =X72 -> 0 | BL72: =AL72+AQ72 -> 0 | BM72: =(+BF72+BI72+BK72+BL72)*0.1267 -> 0 | BN72: =SUM(BF72:BM72)-BH72-BJ72 -> 0 | BO72: =(($F72/30)*$I72)*$L72 -> 0 | BP72: =(($G72/30)*$I72)*$L72 -> 0 | BQ72: =Y72 -> 0 | BR72: =Z72 -> 0 | BS72: =AA72 -> 0 | BT72: =AB72 -> 0 | BU72: =AM72+AR72 -> 0 | BV72: =(BO72+BR72+BT72+BU72)*0.1267 -> 0 | BW72: =SUM(BO72:BV72)-BQ72-BS72 -> 0 | BX72: =(($F72/30)*$I72)*$M72 -> 0 | BY72: =(($G72/30)*$I72)*$M72 -> 0 | BZ72: =AC72 -> 0 | CA72: =AD72 -> 0 | CB72: =AE72 -> 0 | CC72: =AF72 -> 0 | CD72: =AN72+AS72 -> 0 | CE72: =(BX72+CA72+CC72)*0.09 -> 0 | CF72: =SUM(BX72:CE72)-BZ72-CB72 -> 0 | CG72: =(($F72/30)*$I72)*N72 -> 0 | CH72: =(($G72/30)*$I72)*$N72 -> 0 | CI72: =+AG72 -> 0 | CJ72: =AH72 -> 0 | CK72: =AI72 -> 0 | CL72: =AJ72 -> 0 | CM72: =AO72+AT72 -> 0 | CN72: =(CG72+CJ72+CL72)*0.09 -> 0 | CO72: =SUM(CG72:CN72)-CI72-CK72 -> 0 | CQ72: PROQUIMA | CR72: =IF($CQ72="PROQUIMA",$AW72+$BF72+$BO72+$BX72+$CG72,0) -> 2425 | CS72: =IF($CQ72="PROQUIMA",$AX72+$BG72+$BP72+$BY72+$CH72,0) -> 450 | CT72: =IF($CQ72="PROQUIMA",$AY72+$BH72+$BQ72+$BZ72+$CI72,0) -> 0 | CU72: =IF($CQ72="PROQUIMA",$AZ72+$BI72+$BR72+$CA72+$CJ72,0) -> 0 | CV72: =IF($CQ72="PROQUIMA",$BA72+$BJ72+$BS72+$CB72+$CK72,0) -> 0 | CW72: =IF($CQ72="PROQUIMA",$BB72+$BK72+$BT72+$CC72+$CL72,0) -> 0 | CX72: =IF($CQ72="PROQUIMA",$BC72+$BL72+$BU72+$CD72+$CM72,0) -> 0 | CY72: =IF($CQ72="PROQUIMA",$BD72+$BM72+$BV72+$CE72+CN72,0) -> 307.2475 | CZ72: =SUM(CR72:CY72)-CT72-CV72 -> 3182.2475 | DA72: =IF($CQ72="UNHESA",$AW72+$BF72+$BO72+$BX72+$CG72,0) -> 0 | DB72: =IF($CQ72="UNHESA",$AX72+$BG72+$BP72+$BY72+$CH72,0) -> 0 | DC72: =IF($CQ72="UNHESA",$AY72+$BH72+$BQ72+$BZ72+$CI72,0) -> 0 | DD72: =IF($CQ72="UNHESA",$AZ72+$BI72+$BR72+$CA72+$CJ72,0) -> 0 | DE72: =IF($CQ72="UNHESA",$BA72+$BJ72+$BS72+$CB72+$CK72,0) -> 0 | DF72: =IF($CQ72="UNHESA",$BB72+$BK72+$BT72+$CC72+$CL72,0) -> 0 | DG72: =IF($CQ72="UNHESA",$BC72+$BL72+$BU72+$CD72+$CM72,0) -> 0 | DH72: =IF($CQ72="UNHESA",$BD72+$BM72+$BV72+$CE72+$CN72,0) -> 0 | DI72: =SUM(DA72:DH72)-DC72-DE72 -> 0 | DJ72: =IF($CQ72="UNHESA LIQUIDOS",$AW72+$BF72+$BO72+$BX72+$CG72,0) -> 0 | DK72: =IF($CQ72="CALIDUL",$AX72+$BG72+$BP72+$BY72+$CH72,0) -> 0 | DL72: =IF($CQ72="CALIDUL",$AY72+$BH72+$BQ72+$BZ72+$CI72,0) -> 0 | DM72: =IF($CQ72="CALIDUL",$AZ72+$BI72+$BR72+$CA72+$CJ72,0) -> 0 | DN72: =IF($CQ72="CALIDUL",$BA72+$BJ72+$BS72+$CB72+$CK72,0) -> 0 | DO72: =IF($CQ72="CALIDUL",$BB72+$BK72+$BT72+$CC72+$CL72,0) -> 0 | DP72: =IF($CQ72="CALIDUL",$BC72+$BL72+$BU72+$CD72+$CM72,0) -> 0 | DQ72: =IF($CQ72="CALIDUL",$BD72+$BM72+$BV72+$CE72+$CN72,0) -> 0 | DR72: =SUM(DJ72:DQ72)-DL72-DN72 -> 0 | DS72: =IF($CQ72="ECONACIONAL",$AW72+$BF72+$BO72+$BX72+$CG72,0) -> 0 | DT72: =IF($CQ72="ECONACIONAL",$AX72+$BG72+$BP72+$BY72+$CH72,0) -> 0 | DU72: =IF($CQ72="ECONACIONAL",$AY72+$BH72+$BQ72+$BZ72+$CI72,0) -> 0 | DV72: =IF($CQ72="ECONACIONAL",$AZ72+$BI72+$BR72+$CA72+$CJ72,0) -> 0 | DW72: =IF($CQ72="ECONACIONAL",$BA72+$BJ72+$BS72+$CB72+$CK72,0) -> 0 | DX72: =IF($CQ72="ECONACIONAL",$BB72+$BK72+$BT72+$CC72+$CL72,0) -> 0 | DY72: =IF($CQ72="ECONACIONAL",$BC72+$BL72+$BU72+$CD72+$CM72,0) -> 0 | DZ72: =IF($CQ72="ECONACIONAL",$BD72+$BM72+$BV72+$CE72+$CN72,0) -> 0 | EA72: =SUM(DS72:DZ72)-DU72-DW72 -> 0 | EB72: =IF($CQ72="CLEARTEC",$AW72+$BF72+$BO72+$BX72+$CG72,0) -> 0 | EC72: =IF($CQ72="CLEARTEC",$AX72+$BG72+$BP72+$BY72+$CH72,0) -> 0 | ED72: =IF($CQ72="CLEARTEC",$AY72+$BH72+$BQ72+$BZ72+$CI72,0) -> 0 | EE72: =IF($CQ72="CLEARTEC",$AZ72+$BI72+$BR72+$CA72+$CJ72,0) -> 0 | EF72: =IF($CQ72="CLEARTEC",$BA72+$BJ72+$BS72+$CB72+$CK72,0) -> 0 | EG72: =IF($CQ72="CLEARTEC",$BB72+$BK72+$BT72+$CC72+$CL72,0) -> 0 | EH72: =IF($CQ72="CLEARTEC",$BC72+$BL72+$BU72+$CD72+$CM72,0) -> 0 | EI72: =IF($CQ72="CLEARTEC",$BD72+$BM72+$BV72+$CE72+$CN72,0) -> 0 | EJ72: =SUM(EB72:EI72)-ED72-EF72 -> 0 | EL72: 99.64 | EU72: =+EP72+EQ72+ER72 -> 0 | EW72: =IF($I72<=15,EL72/2,EL72) -> 49.82 | EX72: =IF($I72<=15,EM72/2,EM72) -> 0 | EY72: =IF($I72<=15,EN72/2,EN72) -> 0 | EZ72: =IF($I72<=15,EO72/2,EO72) -> 0 | FA72: =IF($I72<=15,EP72/2,EP72) -> 0 | FB72: =IF($I72<=15,EQ72/2,EQ72) -> 0 | FC72: =IF($I72<=15,ER72/2,ER72) -> 0 | FD72: =IF($I72<=15,ES72/2,ES72) -> 0 | ... FF72: =IF($I72<=15,EU72/2,EU72) -> 0
A73: 106020 | B73: 15 | C73: Garcia Sanchez Juan Pablo | D73: Aux contable | E73: UNHESA | F73: 4850 | G73: 900 | H73: =+F73+G73 -> 5750 | I73: 15 | K73: 1 | L73: 0 | M73: 0 | N73: 0 | O73: =SUM(J73:N73) -> 1 | R73: =($F73/30/8*1.5)*Q73 -> 0 | T73: =($F73/30/8*2)*S73 -> 0 | V73: =($F73/30/8*1.5)*U73 -> 0 | X73: =($F73/30/8*2)*W73 -> 0 | Z73: =(($F73/30/8)*1.5)*Y73 -> 0 | AB73: =(($F73/30/8)*2)*AA73 -> 0 | AD73: =(($F73/30/8)*1.5)*AC73 -> 0 | AF73: =(($F73/30/8)*2)*AE73 -> 0 | AH73: =(($F73/30/8)*1.5)*AG73 -> 0 | AJ73: =(($F73/30/8)*2)*AI73 -> 0 | AW73: =((F73/30)*I73)*$J73 -> 0 | AX73: =((G73/30)*I73)*$J73 -> 0 | AY73: =Q73 -> 0 | AZ73: =R73 -> 0 | BA73: =S73 -> 0 | BB73: =T73 -> 0 | BC73: =AK73+AP73 -> 0 | BD73: =(AW73+AZ73+BB73+BC73)*0.1267 -> 0 | BE73: =SUM(AW73:BD73)-AY73-BA73 -> 0 | BF73: =(($F73/30)*$I73)*$K73 -> 2425 | BG73: =(($G73/30)*$I73)*$K73 -> 450 | BH73: =U73 -> 0 | BI73: =V73 -> 0 | BJ73: =W73 -> 0 | BK73: =X73 -> 0 | BL73: =AL73+AQ73 -> 0 | BM73: =(+BF73+BI73+BK73+BL73)*0.1267 -> 307.2475 | BN73: =SUM(BF73:BM73)-BH73-BJ73 -> 3182.2475 | BO73: =(($F73/30)*$I73)*$L73 -> 0 | BP73: =(($G73/30)*$I73)*$L73 -> 0 | BQ73: =Y73 -> 0 | BR73: =Z73 -> 0 | BS73: =AA73 -> 0 | BT73: =AB73 -> 0 | BU73: =AM73+AR73 -> 0 | BV73: =(BO73+BR73+BT73+BU73)*0.1267 -> 0 | BW73: =SUM(BO73:BV73)-BQ73-BS73 -> 0 | BX73: =(($F73/30)*$I73)*$M73 -> 0 | BY73: =(($G73/30)*$I73)*$M73 -> 0 | BZ73: =AC73 -> 0 | CA73: =AD73 -> 0 | CB73: =AE73 -> 0 | CC73: =AF73 -> 0 | CD73: =AN73+AS73 -> 0 | CE73: =(BX73+CA73+CC73)*0.09 -> 0 | CF73: =SUM(BX73:CE73)-BZ73-CB73 -> 0 | CG73: =(($F73/30)*$I73)*N73 -> 0 | CH73: =(($G73/30)*$I73)*$N73 -> 0 | CI73: =+AG73 -> 0 | CJ73: =AH73 -> 0 | CK73: =AI73 -> 0 | CL73: =AJ73 -> 0 | CM73: =AO73+AT73 -> 0 | CN73: =(CG73+CJ73+CL73)*0.09 -> 0 | CO73: =SUM(CG73:CN73)-CI73-CK73 -> 0 | CQ73: UNHESA | CR73: =IF($CQ73="PROQUIMA",$AW73+$BF73+$BO73+$BX73+$CG73,0) -> 0 | CS73: =IF($CQ73="PROQUIMA",$AX73+$BG73+$BP73+$BY73+$CH73,0) -> 0 | CT73: =IF($CQ73="PROQUIMA",$AY73+$BH73+$BQ73+$BZ73+$CI73,0) -> 0 | CU73: =IF($CQ73="PROQUIMA",$AZ73+$BI73+$BR73+$CA73+$CJ73,0) -> 0 | CV73: =IF($CQ73="PROQUIMA",$BA73+$BJ73+$BS73+$CB73+$CK73,0) -> 0 | CW73: =IF($CQ73="PROQUIMA",$BB73+$BK73+$BT73+$CC73+$CL73,0) -> 0 | CX73: =IF($CQ73="PROQUIMA",$BC73+$BL73+$BU73+$CD73+$CM73,0) -> 0 | CY73: =IF($CQ73="PROQUIMA",$BD73+$BM73+$BV73+$CE73+CN73,0) -> 0 | CZ73: =SUM(CR73:CY73)-CT73-CV73 -> 0 | DA73: =IF($CQ73="UNHESA",$AW73+$BF73+$BO73+$BX73+$CG73,0) -> 2425 | DB73: =IF($CQ73="UNHESA",$AX73+$BG73+$BP73+$BY73+$CH73,0) -> 450 | DC73: =IF($CQ73="UNHESA",$AY73+$BH73+$BQ73+$BZ73+$CI73,0) -> 0 | DD73: =IF($CQ73="UNHESA",$AZ73+$BI73+$BR73+$CA73+$CJ73,0) -> 0 | DE73: =IF($CQ73="UNHESA",$BA73+$BJ73+$BS73+$CB73+$CK73,0) -> 0 | DF73: =IF($CQ73="UNHESA",$BB73+$BK73+$BT73+$CC73+$CL73,0) -> 0 | DG73: =IF($CQ73="UNHESA",$BC73+$BL73+$BU73+$CD73+$CM73,0) -> 0 | DH73: =IF($CQ73="UNHESA",$BD73+$BM73+$BV73+$CE73+$CN73,0) -> 307.2475 | DI73: =SUM(DA73:DH73)-DC73-DE73 -> 3182.2475 | DJ73: =IF($CQ73="UNHESA LIQUIDOS",$AW73+$BF73+$BO73+$BX73+$CG73,0) -> 0 | DK73: =IF($CQ73="CALIDUL",$AX73+$BG73+$BP73+$BY73+$CH73,0) -> 0 | DL73: =IF($CQ73="CALIDUL",$AY73+$BH73+$BQ73+$BZ73+$CI73,0) -> 0 | DM73: =IF($CQ73="CALIDUL",$AZ73+$BI73+$BR73+$CA73+$CJ73,0) -> 0 | DN73: =IF($CQ73="CALIDUL",$BA73+$BJ73+$BS73+$CB73+$CK73,0) -> 0 | DO73: =IF($CQ73="CALIDUL",$BB73+$BK73+$BT73+$CC73+$CL73,0) -> 0 | DP73: =IF($CQ73="CALIDUL",$BC73+$BL73+$BU73+$CD73+$CM73,0) -> 0 | DQ73: =IF($CQ73="CALIDUL",$BD73+$BM73+$BV73+$CE73+$CN73,0) -> 0 | DR73: =SUM(DJ73:DQ73)-DL73-DN73 -> 0 | DS73: =IF($CQ73="ECONACIONAL",$AW73+$BF73+$BO73+$BX73+$CG73,0) -> 0 | DT73: =IF($CQ73="ECONACIONAL",$AX73+$BG73+$BP73+$BY73+$CH73,0) -> 0 | DU73: =IF($CQ73="ECONACIONAL",$AY73+$BH73+$BQ73+$BZ73+$CI73,0) -> 0 | DV73: =IF($CQ73="ECONACIONAL",$AZ73+$BI73+$BR73+$CA73+$CJ73,0) -> 0 | DW73: =IF($CQ73="ECONACIONAL",$BA73+$BJ73+$BS73+$CB73+$CK73,0) -> 0 | DX73: =IF($CQ73="ECONACIONAL",$BB73+$BK73+$BT73+$CC73+$CL73,0) -> 0 | DY73: =IF($CQ73="ECONACIONAL",$BC73+$BL73+$BU73+$CD73+$CM73,0) -> 0 | DZ73: =IF($CQ73="ECONACIONAL",$BD73+$BM73+$BV73+$CE73+$CN73,0) -> 0 | EA73: =SUM(DS73:DZ73)-DU73-DW73 -> 0 | EB73: =IF($CQ73="CLEARTEC",$AW73+$BF73+$BO73+$BX73+$CG73,0) -> 0 | EC73: =IF($CQ73="CLEARTEC",$AX73+$BG73+$BP73+$BY73+$CH73,0) -> 0 | ED73: =IF($CQ73="CLEARTEC",$AY73+$BH73+$BQ73+$BZ73+$CI73,0) -> 0 | EE73: =IF($CQ73="CLEARTEC",$AZ73+$BI73+$BR73+$CA73+$CJ73,0) -> 0 | EF73: =IF($CQ73="CLEARTEC",$BA73+$BJ73+$BS73+$CB73+$CK73,0) -> 0 | EG73: =IF($CQ73="CLEARTEC",$BB73+$BK73+$BT73+$CC73+$CL73,0) -> 0 | EH73: =IF($CQ73="CLEARTEC",$BC73+$BL73+$BU73+$CD73+$CM73,0) -> 0 | EI73: =IF($CQ73="CLEARTEC",$BD73+$BM73+$BV73+$CE73+$CN73,0) -> 0 | EJ73: =SUM(EB73:EI73)-ED73-EF73 -> 0 | EL73: 105.2 | EU73: =+EP73+EQ73+ER73 -> 0 | EW73: =IF($I73<=15,EL73/2,EL73) -> 52.6 | EX73: =IF($I73<=15,EM73/2,EM73) -> 0 | EY73: =IF($I73<=15,EN73/2,EN73) -> 0 | EZ73: =IF($I73<=15,EO73/2,EO73) -> 0 | FA73: =IF($I73<=15,EP73/2,EP73) -> 0 | FB73: =IF($I73<=15,EQ73/2,EQ73) -> 0 | FC73: =IF($I73<=15,ER73/2,ER73) -> 0 | FD73: =IF($I73<=15,ES73/2,ES73) -> 0 | ... FF73: =IF($I73<=15,EU73/2,EU73) -> 0
A74: 106020 | D74: Total Contabilidad y Finanzas | F74: =SUM(F70:F73) -> 9700 | G74: =SUM(G70:G73) -> 1800 | H74: =SUM(H70:H73) -> 11500 | Q74: =SUM(Q70:Q73) -> 0 | R74: =SUM(R70:R73) -> 0 | S74: =SUM(S70:S73) -> 0 | T74: =SUM(T70:T73) -> 0 | U74: =SUM(U70:U73) -> 0 | V74: =SUM(V70:V73) -> 0 | W74: =SUM(W70:W73) -> 0 | X74: =SUM(X70:X73) -> 0 | ... FF74: =SUM(FF70:FF73) -> 0
A76: 106030 | C76: Tesoreria
A77: 106030
A78: 106030 | D78: total tesoreria | F78: =+F77 -> 0 | G78: =+G77 -> 0 | H78: =+H77 -> 0 | Q78: =+Q77 -> 0 | R78: =+R77 -> 0 | S78: =+S77 -> 0 | T78: =+T77 -> 0 | U78: =+U77 -> 0 | V78: =+V77 -> 0 | W78: =+W77 -> 0 | X78: =+X77 -> 0 | ... FF78: =+FF77 -> 0
A80: 106050 | C80: Legal
A81: 106050
A82: 106050 | D82: total creditos y cobros | F82: =+F81 -> 0 | G82: =+G81 -> 0 | H82: =+H81 -> 0 | Q82: =+Q81 -> 0 | R82: =+R81 -> 0 | S82: =+S81 -> 0 | T82: =+T81 -> 0 | U82: =+U81 -> 0 | V82: =+V81 -> 0 | W82: =+W81 -> 0 | X82: =+X81 -> 0 | ... FF82: =+FF81 -> 0
D83: TOTAL CONTABLE FINANCIERO
C85: Costos y Presupuestos
Q87: =+Q86 -> 0 | R87: =+R86 -> 0 | S87: =+S86 -> 0 | T87: =+T86 -> 0 | U87: =+U86 -> 0 | V87: =+V86 -> 0 | W87: =+W86 -> 0 | X87: =+X86 -> 0 | ... FF87: =+FF86 -> 0
A88: 201010 | C88: Comercial
A89: 201010 | C89: Administracion
A90: 201010 | B90: 16 | C90: Jolon Carrascoza Erwin Antonio | D90: Gerente Comercial | E90: UNHESA | F90: 19460 | G90: 250 | H90: =+F90+G90 -> 19710 | I90: 15 | J90: 0 | K90: 1 | L90: 0 | M90: 0 | N90: 0 | O90: =SUM(J90:N90) -> 1 | R90: =($F90/30/8*1.5)*Q90 -> 0 | T90: =($F90/30/8*2)*S90 -> 0 | V90: =($F90/30/8*1.5)*U90 -> 0 | X90: =($F90/30/8*2)*W90 -> 0 | Z90: =(($F90/30/8)*1.5)*Y90 -> 0 | AB90: =(($F90/30/8)*2)*AA90 -> 0 | AD90: =(($F90/30/8)*1.5)*AC90 -> 0 | AF90: =(($F90/30/8)*2)*AE90 -> 0 | AH90: =(($F90/30/8)*1.5)*AG90 -> 0 | AJ90: =(($F90/30/8)*2)*AI90 -> 0 | AW90: =((F90/30)*I90)*$J90 -> 0 | AX90: =((G90/30)*I90)*$J90 -> 0 | AY90: =Q90 -> 0 | AZ90: =R90 -> 0 | BA90: =S90 -> 0 | BB90: =T90 -> 0 | BC90: =AK90+AP90 -> 0 | BD90: =(AW90+AZ90+BB90+BC90)*0.1267 -> 0 | BE90: =SUM(AW90:BD90)-AY90-BA90 -> 0 | BF90: =(($F90/30)*$I90)*$K90 -> 9730 | BG90: =(($G90/30)*$I90)*$K90+9000 -> 9125 | BH90: =U90 -> 0 | BI90: =V90 -> 0 | BJ90: =W90 -> 0 | BK90: =X90 -> 0 | BL90: =AL90+AQ90 -> 0 | BM90: =(+BF90+BI90+BK90+BL90)*0.1267 -> 1232.791 | BN90: =SUM(BF90:BM90)-BH90-BJ90 -> 20087.791 | BO90: =(($F90/30)*$I90)*$L90 -> 0 | BP90: =(($G90/30)*$I90)*$L90 -> 0 | BQ90: =Y90 -> 0 | BR90: =Z90 -> 0 | BS90: =AA90 -> 0 | BT90: =AB90 -> 0 | BU90: =AM90+AR90 -> 0 | BV90: =(BO90+BR90+BT90+BU90)*0.1267 -> 0 | BW90: =SUM(BO90:BV90)-BQ90-BS90 -> 0 | BX90: =(($F90/30)*$I90)*$M90 -> 0 | BY90: =(($G90/30)*$I90)*$M90 -> 0 | BZ90: =AC90 -> 0 | CA90: =AD90 -> 0 | CB90: =AE90 -> 0 | CC90: =AF90 -> 0 | CD90: =AN90+AS90 -> 0 | CE90: =(BX90+CA90+CC90)*0.1267 -> 0 | CF90: =SUM(BX90:CE90)-BZ90-CB90 -> 0 | CG90: =(($F90/30)*$I90)*N90 -> 0 | CH90: =(($G90/30)*$I90)*$N90 -> 0 | CI90: =+AG90 -> 0 | CJ90: =AH90 -> 0 | CK90: =AI90 -> 0 | CL90: =AJ90 -> 0 | CM90: =AO90+AT90 -> 0 | CN90: =(CG90+CJ90+CL90)*0.1267 -> 0 | CO90: =SUM(CG90:CN90)-CI90-CK90 -> 0 | CQ90: UNHESA | CR90: =IF($CQ90="PROQUIMA",$AW90+$BF90+$BO90+$BX90+$CG90,0) -> 0 | CS90: =IF($CQ90="PROQUIMA",$AX90+$BG90+$BP90+$BY90+$CH90,0) -> 0 | CT90: =IF($CQ90="PROQUIMA",$AY90+$BH90+$BQ90+$BZ90+$CI90,0) -> 0 | CU90: =IF($CQ90="PROQUIMA",$AZ90+$BI90+$BR90+$CA90+$CJ90,0) -> 0 | CV90: =IF($CQ90="PROQUIMA",$BA90+$BJ90+$BS90+$CB90+$CK90,0) -> 0 | CW90: =IF($CQ90="PROQUIMA",$BB90+$BK90+$BT90+$CC90+$CL90,0) -> 0 | CX90: =IF($CQ90="PROQUIMA",$BC90+$BL90+$BU90+$CD90+$CM90,0) -> 0 | CY90: =IF($CQ90="PROQUIMA",$BD90+$BM90+$BV90+$CE90+CN90,0) -> 0 | CZ90: =SUM(CR90:CY90)-CT90-CV90 -> 0 | DA90: =IF($CQ90="UNHESA",$AW90+$BF90+$BO90+$BX90+$CG90,0) -> 9730 | DB90: =IF($CQ90="UNHESA",$AX90+$BG90+$BP90+$BY90+$CH90,0) -> 9125 | DC90: =IF($CQ90="UNHESA",$AY90+$BH90+$BQ90+$BZ90+$CI90,0) -> 0 | DD90: =IF($CQ90="UNHESA",$AZ90+$BI90+$BR90+$CA90+$CJ90,0) -> 0 | DE90: =IF($CQ90="UNHESA",$BA90+$BJ90+$BS90+$CB90+$CK90,0) -> 0 | DF90: =IF($CQ90="UNHESA",$BB90+$BK90+$BT90+$CC90+$CL90,0) -> 0 | DG90: =IF($CQ90="UNHESA",$BC90+$BL90+$BU90+$CD90+$CM90,0) -> 0 | DH90: =IF($CQ90="UNHESA",$BD90+$BM90+$BV90+$CE90+$CN90,0) -> 1232.791 | DI90: =SUM(DA90:DH90)-DC90-DE90 -> 20087.791 | DJ90: =IF($CQ90="UNHESA LIQUIDOS",$AW90+$BF90+$BO90+$BX90+$CG90,0) -> 0 | DK90: =IF($CQ90="UNHESA LIQUIDOS",$AX90+$BG90+$BP90+$BY90+$CH90,0) -> 0 | DL90: =IF($CQ90="UNHESA LIQUIDOS",$AY90+$BH90+$BQ90+$BZ90+$CI90,0) -> 0 | DM90: =IF($CQ90="UNHESA LIQUIDOS",$AZ90+$BI90+$BR90+$CA90+$CJ90,0) -> 0 | DN90: =IF($CQ90="UNHESA LIQUIDOS",$BA90+$BJ90+$BS90+$CB90+$CK90,0) -> 0 | DO90: =IF($CQ90="UNHESA LIQUIDOS",$BB90+$BK90+$BT90+$CC90+$CL90,0) -> 0 | DP90: =IF($CQ90="UNHESA LIQUIDOS",$BC90+$BL90+$BU90+$CD90+$CM90,0) -> 0 | DQ90: =IF($CQ90="UNHESA LIQUIDOS",$BD90+$BM90+$BV90+$CE90+$CN90,0) -> 0 | DR90: =SUM(DJ90:DQ90)-DL90-DN90 -> 0 | DS90: =IF($CQ90="ECONACIONAL",$AW90+$BF90+$BO90+$BX90+$CG90,0) -> 0 | DT90: =IF($CQ90="ECONACIONAL",$AX90+$BG90+$BP90+$BY90+$CH90,0) -> 0 | DU90: =IF($CQ90="ECONACIONAL",$AY90+$BH90+$BQ90+$BZ90+$CI90,0) -> 0 | DV90: =IF($CQ90="ECONACIONAL",$AZ90+$BI90+$BR90+$CA90+$CJ90,0) -> 0 | DW90: =IF($CQ90="ECONACIONAL",$BA90+$BJ90+$BS90+$CB90+$CK90,0) -> 0 | DX90: =IF($CQ90="ECONACIONAL",$BB90+$BK90+$BT90+$CC90+$CL90,0) -> 0 | DY90: =IF($CQ90="ECONACIONAL",$BC90+$BL90+$BU90+$CD90+$CM90,0) -> 0 | DZ90: =IF($CQ90="ECONACIONAL",$BD90+$BM90+$BV90+$CE90+$CN90,0) -> 0 | EA90: =SUM(DS90:DZ90)-DU90-DW90 -> 0 | EB90: =IF($CQ90="CLEARTEC",$AW90+$BF90+$BO90+$BX90+$CG90,0) -> 0 | EC90: =IF($CQ90="CLEARTEC",$AX90+$BG90+$BP90+$BY90+$CH90,0) -> 0 | ED90: =IF($CQ90="CLEARTEC",$AY90+$BH90+$BQ90+$BZ90+$CI90,0) -> 0 | EE90: =IF($CQ90="CLEARTEC",$AZ90+$BI90+$BR90+$CA90+$CJ90,0) -> 0 | EF90: =IF($CQ90="CLEARTEC",$BA90+$BJ90+$BS90+$CB90+$CK90,0) -> 0 | EG90: =IF($CQ90="CLEARTEC",$BB90+$BK90+$BT90+$CC90+$CL90,0) -> 0 | EH90: =IF($CQ90="CLEARTEC",$BC90+$BL90+$BU90+$CD90+$CM90,0) -> 0 | EI90: =IF($CQ90="CLEARTEC",$BD90+$BM90+$BV90+$CE90+$CN90,0) -> 0 | EJ90: =SUM(EB90:EI90)-ED90-EF90 -> 0 | EL90: 1451.66 | EM90: 8453.15 | EU90: =+EP90+EQ90+ER90 -> 0 | EW90: =IF($I90<=15,EL90/2,EL90) -> 725.83 | EX90: =IF($I90<=15,EM90/2,EM90) -> 4226.575 | EY90: =IF($I90<=15,EN90/2,EN90) -> 0 | EZ90: =IF($I90<=15,EO90/2,EO90) -> 0 | FA90: =IF($I90<=15,EP90/2,EP90) -> 0 | FB90: =IF($I90<=15,EQ90/2,EQ90) -> 0 | FC90: =IF($I90<=15,ER90/2,ER90) -> 0 | FD90: =IF($I90<=15,ES90/2,ES90) -> 0 | ... FF90: =IF($I90<=15,EU90/2,EU90) -> 0 | FG90: 0.4 | FH90: 0.6 | FI90: 0 | FJ90: 0 | FK90: 0 | FL90: 1 | FN90: =(((F90/30/8)*1.5)*(Q90+U90+Y90))-(AZ90+BI90+BR90) -> 0 | FO90: =(((F90/30/8)*2)*(S90+W90+AA90))-(BB90+BK90+BT90) -> 0 | FP90: =(SUM(AW90:CF90))-(SUM(CR90:DR90)) -> 0 | FQ90: =(F90/30*I90)-(CR90+DA90+DJ90) -> 0 | FR90: =(SUM(EL90:EU90))-((SUM(EW90:FF90))*$FR$5) -> 4952.405
A91: 201010 | B91: 17 | C91: Flores Garcia Andres David | D91: Jefe Administrativo Comercial | E91: PROQUIMA | F91: 9000 | G91: 5000 | H91: =+F91+G91 -> 14000 | I91: 15 | J91: 1 | K91: 0 | L91: 0 | M91: 0 | N91: 0 | O91: =SUM(J91:N91) -> 1 | P91: bonif autorizada por jp 1000 mensuales | R91: =($F91/30/8*1.5)*Q91 -> 0 | T91: =($F91/30/8*2)*S91 -> 0 | V91: =($F91/30/8*1.5)*U91 -> 0 | X91: =($F91/30/8*2)*W91 -> 0 | Z91: =(($F91/30/8)*1.5)*Y91 -> 0 | AB91: =(($F91/30/8)*2)*AA91 -> 0 | AD91: =(($F91/30/8)*1.5)*AC91 -> 0 | AF91: =(($F91/30/8)*2)*AE91 -> 0 | AH91: =(($F91/30/8)*1.5)*AG91 -> 0 | AJ91: =(($F91/30/8)*2)*AI91 -> 0 | AL91: 0 | AW91: =((F91/30)*I91)*$J91 -> 4500 | AX91: =((G91/30)*I91)*$J91+1960.45 -> 4460.45 | AY91: =Q91 -> 0 | AZ91: =R91 -> 0 | BA91: =S91 -> 0 | BB91: =T91 -> 0 | BC91: =AK91+AP91 -> 0 | BD91: =(AW91+AZ91+BB91+BC91)*0.1267 -> 570.15 | BE91: =SUM(AW91:BD91)-AY91-BA91 -> 9530.6 | BF91: =(($F91/30)*$I91)*$K91 -> 0 | BG91: =(($G91/30)*$I91)*$K91 -> 0 | BH91: =U91 -> 0 | BI91: =V91 -> 0 | BJ91: =W91 -> 0 | BK91: =X91 -> 0 | BL91: =AL91+AQ91 -> 0 | BM91: =(+BF91+BI91+BK91+BL91)*0.1267 -> 0 | BN91: =SUM(BF91:BM91)-BH91-BJ91 -> 0 | BO91: =(($F91/30)*$I91)*$L91 -> 0 | BP91: =(($G91/30)*$I91)*$L91 -> 0 | BQ91: =Y91 -> 0 | BR91: =Z91 -> 0 | BS91: =AA91 -> 0 | BT91: =AB91 -> 0 | BU91: =AM91+AR91 -> 0 | BV91: =(BO91+BR91+BT91+BU91)*0.1267 -> 0 | BW91: =SUM(BO91:BV91)-BQ91-BS91 -> 0 | BX91: =(($F91/30)*$I91)*$M91 -> 0 | BY91: =(($G91/30)*$I91)*$M91 -> 0 | BZ91: =AC91 -> 0 | CA91: =AD91 -> 0 | CB91: =AE91 -> 0 | CC91: =AF91 -> 0 | CD91: =AN91+AS91 -> 0 | CE91: =(BX91+CA91+CC91)*0.1267 -> 0 | CF91: =SUM(BX91:CE91)-BZ91-CB91 -> 0 | CG91: =(($F91/30)*$I91)*N91 -> 0 | CH91: =(($G91/30)*$I91)*$N91 -> 0 | CI91: =+AG91 -> 0 | CJ91: =AH91 -> 0 | CK91: =AI91 -> 0 | CL91: =AJ91 -> 0 | CM91: =AO91+AT91 -> 0 | CN91: =(CG91+CJ91+CL91)*0.1267 -> 0 | CO91: =SUM(CG91:CN91)-CI91-CK91 -> 0 | CQ91: PROQUIMA | CR91: =IF($CQ91="PROQUIMA",$AW91+$BF91+$BO91+$BX91+$CG91,0) -> 4500 | CS91: =IF($CQ91="PROQUIMA",$AX91+$BG91+$BP91+$BY91+$CH91,0) -> 4460.45 | CT91: =IF($CQ91="PROQUIMA",$AY91+$BH91+$BQ91+$BZ91+$CI91,0) -> 0 | CU91: =IF($CQ91="PROQUIMA",$AZ91+$BI91+$BR91+$CA91+$CJ91,0) -> 0 | CV91: =IF($CQ91="PROQUIMA",$BA91+$BJ91+$BS91+$CB91+$CK91,0) -> 0 | CW91: =IF($CQ91="PROQUIMA",$BB91+$BK91+$BT91+$CC91+$CL91,0) -> 0 | CX91: =IF($CQ91="PROQUIMA",$BC91+$BL91+$BU91+$CD91+$CM91,0) -> 0 | CY91: =IF($CQ91="PROQUIMA",$BD91+$BM91+$BV91+$CE91+CN91,0) -> 570.15 | CZ91: =SUM(CR91:CY91)-CT91-CV91 -> 9530.6 | DA91: =IF($CQ91="UNHESA",$AW91+$BF91+$BO91+$BX91+$CG91,0) -> 0 | DB91: =IF($CQ91="UNHESA",$AX91+$BG91+$BP91+$BY91+$CH91,0) -> 0 | DC91: =IF($CQ91="UNHESA",$AY91+$BH91+$BQ91+$BZ91+$CI91,0) -> 0 | DD91: =IF($CQ91="UNHESA",$AZ91+$BI91+$BR91+$CA91+$CJ91,0) -> 0 | DE91: =IF($CQ91="UNHESA",$BA91+$BJ91+$BS91+$CB91+$CK91,0) -> 0 | DF91: =IF($CQ91="UNHESA",$BB91+$BK91+$BT91+$CC91+$CL91,0) -> 0 | DG91: =IF($CQ91="UNHESA",$BC91+$BL91+$BU91+$CD91+$CM91,0) -> 0 | DH91: =IF($CQ91="UNHESA",$BD91+$BM91+$BV91+$CE91+$CN91,0) -> 0 | DI91: =SUM(DA91:DH91)-DC91-DE91 -> 0 | DJ91: =IF($CQ91="UNHESA LIQUIDOS",$AW91+$BF91+$BO91+$BX91+$CG91,0) -> 0 | DK91: =IF($CQ91="UNHESA LIQUIDOS",$AX91+$BG91+$BP91+$BY91+$CH91,0) -> 0 | DL91: =IF($CQ91="UNHESA LIQUIDOS",$AY91+$BH91+$BQ91+$BZ91+$CI91,0) -> 0 | DM91: =IF($CQ91="UNHESA LIQUIDOS",$AZ91+$BI91+$BR91+$CA91+$CJ91,0) -> 0 | DN91: =IF($CQ91="UNHESA LIQUIDOS",$BA91+$BJ91+$BS91+$CB91+$CK91,0) -> 0 | DO91: =IF($CQ91="UNHESA LIQUIDOS",$BB91+$BK91+$BT91+$CC91+$CL91,0) -> 0 | DP91: =IF($CQ91="UNHESA LIQUIDOS",$BC91+$BL91+$BU91+$CD91+$CM91,0) -> 0 | DQ91: =IF($CQ91="UNHESA LIQUIDOS",$BD91+$BM91+$BV91+$CE91+$CN91,0) -> 0 | DR91: =SUM(DJ91:DQ91)-DL91-DN91 -> 0 | DS91: =IF($CQ91="ECONACIONAL",$AW91+$BF91+$BO91+$BX91+$CG91,0) -> 0 | DT91: =IF($CQ91="ECONACIONAL",$AX91+$BG91+$BP91+$BY91+$CH91,0) -> 0 | DU91: =IF($CQ91="ECONACIONAL",$AY91+$BH91+$BQ91+$BZ91+$CI91,0) -> 0 | DV91: =IF($CQ91="ECONACIONAL",$AZ91+$BI91+$BR91+$CA91+$CJ91,0) -> 0 | DW91: =IF($CQ91="ECONACIONAL",$BA91+$BJ91+$BS91+$CB91+$CK91,0) -> 0 | DX91: =IF($CQ91="ECONACIONAL",$BB91+$BK91+$BT91+$CC91+$CL91,0) -> 0 | DY91: =IF($CQ91="ECONACIONAL",$BC91+$BL91+$BU91+$CD91+$CM91,0) -> 0 | DZ91: =IF($CQ91="ECONACIONAL",$BD91+$BM91+$BV91+$CE91+$CN91,0) -> 0 | EA91: =SUM(DS91:DZ91)-DU91-DW91 -> 0 | EB91: =IF($CQ91="CLEARTEC",$AW91+$BF91+$BO91+$BX91+$CG91,0) -> 0 | EC91: =IF($CQ91="CLEARTEC",$AX91+$BG91+$BP91+$BY91+$CH91,0) -> 0 | ED91: =IF($CQ91="CLEARTEC",$AY91+$BH91+$BQ91+$BZ91+$CI91,0) -> 0 | EE91: =IF($CQ91="CLEARTEC",$AZ91+$BI91+$BR91+$CA91+$CJ91,0) -> 0 | EF91: =IF($CQ91="CLEARTEC",$BA91+$BJ91+$BS91+$CB91+$CK91,0) -> 0 | EG91: =IF($CQ91="CLEARTEC",$BB91+$BK91+$BT91+$CC91+$CL91,0) -> 0 | EH91: =IF($CQ91="CLEARTEC",$BC91+$BL91+$BU91+$CD91+$CM91,0) -> 0 | EI91: =IF($CQ91="CLEARTEC",$BD91+$BM91+$BV91+$CE91+$CN91,0) -> 0 | EJ91: =SUM(EB91:EI91)-ED91-EF91 -> 0 | EL91: 335.79 | EO91: =57*2 -> 114 | ER91: 350 | EU91: =+EP91+EQ91+ER91 -> 350 | EW91: =IF($I91<=15,EL91/2,EL91) -> 167.895 | EX91: =IF($I91<=15,EM91/2,EM91) -> 0 | EY91: =IF($I91<=15,EN91/2,EN91) -> 0 | EZ91: =IF($I91<=15,EO91/2,EO91) -> 57 | FA91: =IF($I91<=15,EP91/2,EP91) -> 0 | FB91: =IF($I91<=15,EQ91/2,EQ91) -> 0 | FC91: =IF($I91<=15,ER91/2,ER91) -> 175 | FD91: =IF($I91<=15,ES91/2,ES91) -> 0 | ... FF91: =IF($I91<=15,EU91/2,EU91) -> 175 | FN91: =(((F91/30/8)*1.5)*(Q91+U91+Y91))-(AZ91+BI91+BR91) -> 0 | FO91: =(((F91/30/8)*2)*(S91+W91+AA91))-(BB91+BK91+BT91) -> 0 | FP91: =(SUM(AW91:CF91))-(SUM(CR91:DR91)) -> 0 | FQ91: =(F91/30*I91)-(CR91+DA91+DJ91) -> 0 | FR91: =(SUM(EL91:EU91))-((SUM(EW91:FF91))*$FR$5) -> 574.895
A92: 201010 | D92: total comercial Administracion | F92: =SUM(F90:F91) -> 28460 | G92: =SUM(G90:G91) -> 5250 | H92: =SUM(H90:H91) -> 33710 | Q92: =SUM(Q90:Q91) -> 0 | R92: =SUM(R90:R91) -> 0 | S92: =SUM(S90:S91) -> 0 | T92: =SUM(T90:T91) -> 0 | U92: =SUM(U90:U91) -> 0 | V92: =SUM(V90:V91) -> 0 | W92: =SUM(W90:W91) -> 0 | X92: =SUM(X90:X91) -> 0 | ... FT92: =SUM(FT90:FT91) -> 0
C94: Ruta Administrativa
A95: 201010 | B95: 20 | C95: Ambrocio Sanchez Rolando | D95: Encargado Administrativo | E95: UNHESA | F95: 4150 | G95: 3000 | H95: =+F95+G95 -> 7150 | I95: 15 | J95: 0 | K95: 1 | L95: 0 | M95: 0 | N95: 0 | O95: =SUM(J95:N95) -> 1 | R95: =($F95/30/8*1.5)*Q95 -> 0 | T95: =($F95/30/8*2)*S95 -> 0 | U95: 0 | V95: =($F95/30/8*1.5)*U95 -> 0 | X95: =($F95/30/8*2)*W95 -> 0 | Z95: =(($F95/30/8)*1.5)*Y95 -> 0 | AB95: =(($F95/30/8)*2)*AA95 -> 0 | AD95: =(($F95/30/8)*1.5)*AC95 -> 0 | AF95: =(($F95/30/8)*2)*AE95 -> 0 | AH95: =(($F95/30/8)*1.5)*AG95 -> 0 | AJ95: =(($F95/30/8)*2)*AI95 -> 0 | AW95: =((F95/30)*I95)*$J95 -> 0 | AX95: =((G95/30)*I95)*$J95 -> 0 | AY95: =Q95 -> 0 | AZ95: =R95 -> 0 | BA95: =S95 -> 0 | BB95: =T95 -> 0 | BC95: =AK95+AP95 -> 0 | BD95: =(AW95+AZ95+BB95+BC95)*0.1267 -> 0 | BE95: =SUM(AW95:BD95)-AY95-BA95 -> 0 | BF95: =(($F95/30)*$I95)*$K95 -> 2075 | BG95: =(($G95/30)*$I95)*$K95 -> 1500 | BH95: =U95 -> 0 | BI95: =V95 -> 0 | BJ95: =W95 -> 0 | BK95: =X95 -> 0 | BL95: =AL95+AQ95 -> 0 | BM95: =(+BF95+BI95+BK95+BL95)*0.1267 -> 262.9025 | BN95: =SUM(BF95:BM95)-BH95-BJ95 -> 3837.9025 | BO95: =(($F95/30)*$I95)*$L95 -> 0 | BP95: =(($G95/30)*$I95)*$L95 -> 0 | BQ95: =Y95 -> 0 | BR95: =Z95 -> 0 | BS95: =AA95 -> 0 | BT95: =AB95 -> 0 | BU95: =AM95+AR95 -> 0 | BV95: =(BO95+BR95+BT95+BU95)*0.1267 -> 0 | BW95: =SUM(BO95:BV95)-BQ95-BS95 -> 0 | BX95: =(($F95/30)*$I95)*$M95 -> 0 | BY95: =(($G95/30)*$I95)*$M95 -> 0 | BZ95: =AC95 -> 0 | CA95: =AD95 -> 0 | CB95: =AE95 -> 0 | CC95: =AF95 -> 0 | CD95: =AN95+AS95 -> 0 | CE95: =(BX95+CA95+CC95)*0.1267 -> 0 | CF95: =SUM(BX95:CE95)-BZ95-CB95 -> 0 | CG95: =(($F95/30)*$I95)*N95 -> 0 | CH95: =(($G95/30)*$I95)*$N95 -> 0 | CI95: =+AG95 -> 0 | CJ95: =AH95 -> 0 | CK95: =AI95 -> 0 | CL95: =AJ95 -> 0 | CM95: =AO95+AT95 -> 0 | CN95: =(CG95+CJ95+CL95)*0.1267 -> 0 | CO95: =SUM(CG95:CN95)-CI95-CK95 -> 0 | CQ95: UNHESA | CR95: =IF($CQ95="PROQUIMA",$AW95+$BF95+$BO95+$BX95+$CG95,0) -> 0 | CS95: =IF($CQ95="PROQUIMA",$AX95+$BG95+$BP95+$BY95+$CH95,0) -> 0 | CT95: =IF($CQ95="PROQUIMA",$AY95+$BH95+$BQ95+$BZ95+$CI95,0) -> 0 | CU95: =IF($CQ95="PROQUIMA",$AZ95+$BI95+$BR95+$CA95+$CJ95,0) -> 0 | CV95: =IF($CQ95="PROQUIMA",$BA95+$BJ95+$BS95+$CB95+$CK95,0) -> 0 | CW95: =IF($CQ95="PROQUIMA",$BB95+$BK95+$BT95+$CC95+$CL95,0) -> 0 | CX95: =IF($CQ95="PROQUIMA",$BC95+$BL95+$BU95+$CD95+$CM95,0) -> 0 | CY95: =IF($CQ95="PROQUIMA",$BD95+$BM95+$BV95+$CE95+CN95,0) -> 0 | CZ95: =SUM(CR95:CY95)-CT95-CV95 -> 0 | DA95: =IF($CQ95="UNHESA",$AW95+$BF95+$BO95+$BX95+$CG95,0) -> 2075 | DB95: =IF($CQ95="UNHESA",$AX95+$BG95+$BP95+$BY95+$CH95,0) -> 1500 | DC95: =IF($CQ95="UNHESA",$AY95+$BH95+$BQ95+$BZ95+$CI95,0) -> 0 | DD95: =IF($CQ95="UNHESA",$AZ95+$BI95+$BR95+$CA95+$CJ95,0) -> 0 | DE95: =IF($CQ95="UNHESA",$BA95+$BJ95+$BS95+$CB95+$CK95,0) -> 0 | DF95: =IF($CQ95="UNHESA",$BB95+$BK95+$BT95+$CC95+$CL95,0) -> 0 | DG95: =IF($CQ95="UNHESA",$BC95+$BL95+$BU95+$CD95+$CM95,0) -> 0 | DH95: =IF($CQ95="UNHESA",$BD95+$BM95+$BV95+$CE95+$CN95,0) -> 262.9025 | DI95: =SUM(DA95:DH95)-DC95-DE95 -> 3837.9025 | DJ95: =IF($CQ95="UNHESA LIQUIDOS",$AW95+$BF95+$BO95+$BX95+$CG95,0) -> 0 | DK95: =IF($CQ95="UNHESA LIQUIDOS",$AX95+$BG95+$BP95+$BY95+$CH95,0) -> 0 | DL95: =IF($CQ95="UNHESA LIQUIDOS",$AY95+$BH95+$BQ95+$BZ95+$CI95,0) -> 0 | DM95: =IF($CQ95="UNHESA LIQUIDOS",$AZ95+$BI95+$BR95+$CA95+$CJ95,0) -> 0 | DN95: =IF($CQ95="UNHESA LIQUIDOS",$BA95+$BJ95+$BS95+$CB95+$CK95,0) -> 0 | DO95: =IF($CQ95="UNHESA LIQUIDOS",$BB95+$BK95+$BT95+$CC95+$CL95,0) -> 0 | DP95: =IF($CQ95="UNHESA LIQUIDOS",$BC95+$BL95+$BU95+$CD95+$CM95,0) -> 0 | DQ95: =IF($CQ95="UNHESA LIQUIDOS",$BD95+$BM95+$BV95+$CE95+$CN95,0) -> 0 | DR95: =SUM(DJ95:DQ95)-DL95-DN95 -> 0 | DS95: =IF($CQ95="ECONACIONAL",$AW95+$BF95+$BO95+$BX95+$CG95,0) -> 0 | DT95: =IF($CQ95="ECONACIONAL",$AX95+$BG95+$BP95+$BY95+$CH95,0) -> 0 | DU95: =IF($CQ95="ECONACIONAL",$AY95+$BH95+$BQ95+$BZ95+$CI95,0) -> 0 | DV95: =IF($CQ95="ECONACIONAL",$AZ95+$BI95+$BR95+$CA95+$CJ95,0) -> 0 | DW95: =IF($CQ95="ECONACIONAL",$BA95+$BJ95+$BS95+$CB95+$CK95,0) -> 0 | DX95: =IF($CQ95="ECONACIONAL",$BB95+$BK95+$BT95+$CC95+$CL95,0) -> 0 | DY95: =IF($CQ95="ECONACIONAL",$BC95+$BL95+$BU95+$CD95+$CM95,0) -> 0 | DZ95: =IF($CQ95="ECONACIONAL",$BD95+$BM95+$BV95+$CE95+$CN95,0) -> 0 | EA95: =SUM(DS95:DZ95)-DU95-DW95 -> 0 | EB95: =IF($CQ95="CLEARTEC",$AW95+$BF95+$BO95+$BX95+$CG95,0) -> 0 | EC95: =IF($CQ95="CLEARTEC",$AX95+$BG95+$BP95+$BY95+$CH95,0) -> 0 | ED95: =IF($CQ95="CLEARTEC",$AY95+$BH95+$BQ95+$BZ95+$CI95,0) -> 0 | EE95: =IF($CQ95="CLEARTEC",$AZ95+$BI95+$BR95+$CA95+$CJ95,0) -> 0 | EF95: =IF($CQ95="CLEARTEC",$BA95+$BJ95+$BS95+$CB95+$CK95,0) -> 0 | EG95: =IF($CQ95="CLEARTEC",$BB95+$BK95+$BT95+$CC95+$CL95,0) -> 0 | EH95: =IF($CQ95="CLEARTEC",$BC95+$BL95+$BU95+$CD95+$CM95,0) -> 0 | EI95: =IF($CQ95="CLEARTEC",$BD95+$BM95+$BV95+$CE95+$CN95,0) -> 0 | EJ95: =SUM(EB95:EI95)-ED95-EF95 -> 0 | EL95: 139.52 | EU95: =+EP95+EQ95+ER95 -> 0 | EW95: =IF($I95<=15,EL95/2,EL95) -> 69.76 | EX95: =IF($I95<=15,EM95/2,EM95) -> 0 | EY95: =IF($I95<=15,EN95/2,EN95) -> 0 | EZ95: =IF($I95<=15,EO95/2,EO95) -> 0 | FA95: =IF($I95<=15,EP95/2,EP95) -> 0 | FB95: =IF($I95<=15,EQ95/2,EQ95) -> 0 | FC95: =IF($I95<=15,ER95/2,ER95) -> 0 | FD95: =IF($I95<=15,ES95/2,ES95) -> 0 | ... FF95: =IF($I95<=15,EU95/2,EU95) -> 0 | FG95: 0 | FH95: 1 | FI95: 0 | FJ95: 0 | FK95: 0 | FL95: 1 | FN95: =(((F95/30/8)*1.5)*(Q95+U95+Y95))-(AZ95+BI95+BR95) -> 0 | FO95: =(((F95/30/8)*2)*(S95+W95+AA95))-(BB95+BK95+BT95) -> 0 | FP95: =(SUM(AW95:CF95))-(SUM(CR95:DR95)) -> 0 | FQ95: =(F95/30*I95)-(CR95+DA95+DJ95) -> 0 | FR95: =(SUM(EL95:EU95))-((SUM(EW95:FF95))*$FR$5) -> 69.76
A96: 201060 | B96: =+B95+1 -> 21 | C96: Ramos Pinto Farian Estuardo | D96: Jefe de Ventas Online | E96: UNHESA | F96: 5000 | G96: 1500 | H96: =+F96+G96 -> 6500 | I96: 15 | J96: 0 | K96: 1 | L96: 0 | M96: 0 | N96: 0 | O96: =SUM(J96:N96) -> 1 | R96: =($F96/30/8*1.5)*Q96 -> 0 | T96: =($F96/30/8*2)*S96 -> 0 | V96: =($F96/30/8*1.5)*U96 -> 0 | X96: =($F96/30/8*2)*W96 -> 0 | Z96: =(($F96/30/8)*1.5)*Y96 -> 0 | AB96: =(($F96/30/8)*2)*AA96 -> 0 | AD96: =(($F96/30/8)*1.5)*AC96 -> 0 | AF96: =(($F96/30/8)*2)*AE96 -> 0 | AH96: =(($F96/30/8)*1.5)*AG96 -> 0 | AJ96: =(($F96/30/8)*2)*AI96 -> 0 | AW96: =((F96/30)*I96)*$J96 -> 0 | AX96: =((G96/30)*I96)*$J96 -> 0 | AY96: =Q96 -> 0 | AZ96: =R96 -> 0 | BA96: =S96 -> 0 | BB96: =T96 -> 0 | BC96: =AK96+AP96 -> 0 | BD96: =(AW96+AZ96+BB96+BC96)*0.1267 -> 0 | BE96: =SUM(AW96:BD96)-AY96-BA96 -> 0 | BF96: =(($F96/30)*$I96)*$K96 -> 2500 | BG96: =(($G96/30)*$I96)+1125 -> 1875 | BH96: =U96 -> 0 | BI96: =V96 -> 0 | BJ96: =W96 -> 0 | BK96: =X96 -> 0 | BL96: =AL96+AQ96 -> 0 | BM96: =(+BF96+BI96+BK96+BL96)*0.1267 -> 316.75 | BN96: =SUM(BF96:BM96)-BH96-BJ96 -> 4691.75 | BO96: =(($F96/30)*$I96)*$L96 -> 0 | BP96: =(($G96/30)*$I96)*$L96 -> 0 | BQ96: =Y96 -> 0 | BR96: =Z96 -> 0 | BS96: =AA96 -> 0 | BT96: =AB96 -> 0 | BU96: =AM96+AR96 -> 0 | BV96: =(BO96+BR96+BT96+BU96)*0.1267 -> 0 | BW96: =SUM(BO96:BV96)-BQ96-BS96 -> 0 | BX96: =(($F96/30)*$I96)*$M96 -> 0 | BY96: =(($G96/30)*$I96)*$M96 -> 0 | BZ96: =AC96 -> 0 | CA96: =AD96 -> 0 | CB96: =AE96 -> 0 | CC96: =AF96 -> 0 | CD96: =AN96+AS96 -> 0 | CE96: =(BX96+CA96+CC96)*0.1267 -> 0 | CF96: =SUM(BX96:CE96)-BZ96-CB96 -> 0 | CG96: =(($F96/30)*$I96)*N96 -> 0 | CH96: =(($G96/30)*$I96)*$N96 -> 0 | CI96: =+AG96 -> 0 | CJ96: =AH96 -> 0 | CK96: =AI96 -> 0 | CL96: =AJ96 -> 0 | CM96: =AO96+AT96 -> 0 | CN96: =(CG96+CJ96+CL96)*0.1267 -> 0 | CO96: =SUM(CG96:CN96)-CI96-CK96 -> 0 | CQ96: UNHESA | CR96: =IF($CQ96="PROQUIMA",$AW96+$BF96+$BO96+$BX96+$CG96,0) -> 0 | CS96: =IF($CQ96="PROQUIMA",$AX96+$BG96+$BP96+$BY96+$CH96,0) -> 0 | CT96: =IF($CQ96="PROQUIMA",$AY96+$BH96+$BQ96+$BZ96+$CI96,0) -> 0 | CU96: =IF($CQ96="PROQUIMA",$AZ96+$BI96+$BR96+$CA96+$CJ96,0) -> 0 | CV96: =IF($CQ96="PROQUIMA",$BA96+$BJ96+$BS96+$CB96+$CK96,0) -> 0 | CW96: =IF($CQ96="PROQUIMA",$BB96+$BK96+$BT96+$CC96+$CL96,0) -> 0 | CX96: =IF($CQ96="PROQUIMA",$BC96+$BL96+$BU96+$CD96+$CM96,0) -> 0 | CY96: =IF($CQ96="PROQUIMA",$BD96+$BM96+$BV96+$CE96+CN96,0) -> 0 | CZ96: =SUM(CR96:CY96)-CT96-CV96 -> 0 | DA96: =IF($CQ96="UNHESA",$AW96+$BF96+$BO96+$BX96+$CG96,0) -> 2500 | DB96: =IF($CQ96="UNHESA",$AX96+$BG96+$BP96+$BY96+$CH96,0) -> 1875 | DC96: =IF($CQ96="UNHESA",$AY96+$BH96+$BQ96+$BZ96+$CI96,0) -> 0 | DD96: =IF($CQ96="UNHESA",$AZ96+$BI96+$BR96+$CA96+$CJ96,0) -> 0 | DE96: =IF($CQ96="UNHESA",$BA96+$BJ96+$BS96+$CB96+$CK96,0) -> 0 | DF96: =IF($CQ96="UNHESA",$BB96+$BK96+$BT96+$CC96+$CL96,0) -> 0 | DG96: =IF($CQ96="UNHESA",$BC96+$BL96+$BU96+$CD96+$CM96,0) -> 0 | DH96: =IF($CQ96="UNHESA",$BD96+$BM96+$BV96+$CE96+$CN96,0) -> 316.75 | DI96: =SUM(DA96:DH96)-DC96-DE96 -> 4691.75 | DJ96: =IF($CQ96="UNHESA LIQUIDOS",$AW96+$BF96+$BO96+$BX96+$CG96,0) -> 0 | DK96: =IF($CQ96="UNHESA LIQUIDOS",$AX96+$BG96+$BP96+$BY96+$CH96,0) -> 0 | DL96: =IF($CQ96="UNHESA LIQUIDOS",$AY96+$BH96+$BQ96+$BZ96+$CI96,0) -> 0 | DM96: =IF($CQ96="UNHESA LIQUIDOS",$AZ96+$BI96+$BR96+$CA96+$CJ96,0) -> 0 | DN96: =IF($CQ96="UNHESA LIQUIDOS",$BA96+$BJ96+$BS96+$CB96+$CK96,0) -> 0 | DO96: =IF($CQ96="UNHESA LIQUIDOS",$BB96+$BK96+$BT96+$CC96+$CL96,0) -> 0 | DP96: =IF($CQ96="UNHESA LIQUIDOS",$BC96+$BL96+$BU96+$CD96+$CM96,0) -> 0 | DQ96: =IF($CQ96="UNHESA LIQUIDOS",$BD96+$BM96+$BV96+$CE96+$CN96,0) -> 0 | DR96: =SUM(DJ96:DQ96)-DL96-DN96 -> 0 | DS96: =IF($CQ96="ECONACIONAL",$AW96+$BF96+$BO96+$BX96+$CG96,0) -> 0 | DT96: =IF($CQ96="ECONACIONAL",$AX96+$BG96+$BP96+$BY96+$CH96,0) -> 0 | DU96: =IF($CQ96="ECONACIONAL",$AY96+$BH96+$BQ96+$BZ96+$CI96,0) -> 0 | DV96: =IF($CQ96="ECONACIONAL",$AZ96+$BI96+$BR96+$CA96+$CJ96,0) -> 0 | DW96: =IF($CQ96="ECONACIONAL",$BA96+$BJ96+$BS96+$CB96+$CK96,0) -> 0 | DX96: =IF($CQ96="ECONACIONAL",$BB96+$BK96+$BT96+$CC96+$CL96,0) -> 0 | DY96: =IF($CQ96="ECONACIONAL",$BC96+$BL96+$BU96+$CD96+$CM96,0) -> 0 | DZ96: =IF($CQ96="ECONACIONAL",$BD96+$BM96+$BV96+$CE96+$CN96,0) -> 0 | EA96: =SUM(DS96:DZ96)-DU96-DW96 -> 0 | EB96: =IF($CQ96="CLEARTEC",$AW96+$BF96+$BO96+$BX96+$CG96,0) -> 0 | EC96: =IF($CQ96="CLEARTEC",$AX96+$BG96+$BP96+$BY96+$CH96,0) -> 0 | ED96: =IF($CQ96="CLEARTEC",$AY96+$BH96+$BQ96+$BZ96+$CI96,0) -> 0 | EE96: =IF($CQ96="CLEARTEC",$AZ96+$BI96+$BR96+$CA96+$CJ96,0) -> 0 | EF96: =IF($CQ96="CLEARTEC",$BA96+$BJ96+$BS96+$CB96+$CK96,0) -> 0 | EG96: =IF($CQ96="CLEARTEC",$BB96+$BK96+$BT96+$CC96+$CL96,0) -> 0 | EH96: =IF($CQ96="CLEARTEC",$BC96+$BL96+$BU96+$CD96+$CM96,0) -> 0 | EI96: =IF($CQ96="CLEARTEC",$BD96+$BM96+$BV96+$CE96+$CN96,0) -> 0 | EJ96: =SUM(EB96:EI96)-ED96-EF96 -> 0 | EL96: 212.92 | EU96: =+EP96+EQ96+ER96 -> 0 | EW96: =IF($I96<=15,EL96/2,EL96) -> 106.46 | EX96: =IF($I96<=15,EM96/2,EM96) -> 0 | EY96: =IF($I96<=15,EN96/2,EN96) -> 0 | EZ96: =IF($I96<=15,EO96/2,EO96) -> 0 | FA96: =IF($I96<=15,EP96/2,EP96) -> 0 | FB96: =IF($I96<=15,EQ96/2,EQ96) -> 0 | FC96: =IF($I96<=15,ER96/2,ER96) -> 0 | FD96: =IF($I96<=15,ES96/2,ES96) -> 0 | ... FF96: =IF($I96<=15,EU96/2,EU96) -> 0 | FN96: =(((F96/30/8)*1.5)*(Q96+U96+Y96))-(AZ96+BI96+BR96) -> 0 | FO96: =(((F96/30/8)*2)*(S96+W96+AA96))-(BB96+BK96+BT96) -> 0 | FP96: =(SUM(AW96:CF96))-(SUM(CR96:DR96)) -> 0 | FQ96: =(F96/30*I96)-(CR96+DA96+DJ96) -> 0 | FR96: =(SUM(EL96:EU96))-((SUM(EW96:FF96))*$FR$5) -> 106.46
A97: 201010 | B97: =+B96+1 -> 22 | C97: Chun Zacarias Fernando Ovidio | D97: Supervisor de Ventas | E97: UNHESA | F97: 5000 | G97: 250 | H97: =+F97+G97 -> 5250 | I97: 15 | J97: 0 | K97: 1 | L97: 0 | M97: 0 | N97: 0 | O97: =SUM(J97:N97) -> 1 | R97: =($F97/30/8*1.5)*Q97 -> 0 | T97: =($F97/30/8*2)*S97 -> 0 | V97: =($F97/30/8*1.5)*U97 -> 0 | X97: =($F97/30/8*2)*W97 -> 0 | Z97: =(($F97/30/8)*1.5)*Y97 -> 0 | AB97: =(($F97/30/8)*2)*AA97 -> 0 | AD97: =(($F97/30/8)*1.5)*AC97 -> 0 | AF97: =(($F97/30/8)*2)*AE97 -> 0 | AH97: =(($F97/30/8)*1.5)*AG97 -> 0 | AJ97: =(($F97/30/8)*2)*AI97 -> 0 | AW97: =((F97/30)*I97)*$J97 -> 0 | AX97: =((G97/30)*I97)*$J97 -> 0 | AY97: =Q97 -> 0 | AZ97: =R97 -> 0 | BA97: =S97 -> 0 | BB97: =T97 -> 0 | BC97: =+AP97 -> 0 | BD97: =(AW97+AZ97+BB97+BC97)*0.1267 -> 0 | BE97: =SUM(AW97:BD97)-AY97-BA97 -> 0 | BF97: =(($F97/30)*$I97)*$K97 -> 2500 | BG97: =(($G97/30)*$I97)*$K97+3000 -> 3125 | BH97: =U97 -> 0 | BI97: =V97 -> 0 | BJ97: =W97 -> 0 | BK97: =X97 -> 0 | BL97: =AL97+AQ97 -> 0 | BM97: =(+BF97+BI97+BK97+BL97)*0.1267 -> 316.75 | BN97: =SUM(BF97:BM97)-BH97-BJ97 -> 5941.75 | BO97: =(($F97/30)*$I97)*$L97 -> 0 | BP97: =(($G97/30)*$I97)*$L97 -> 0 | BQ97: =Y97 -> 0 | BR97: =Z97 -> 0 | BS97: =AA97 -> 0 | BT97: =AB97 -> 0 | BU97: =AM97+AR97 -> 0 | BV97: =(BO97+BR97+BT97+BU97)*0.1267 -> 0 | BW97: =SUM(BO97:BV97)-BQ97-BS97 -> 0 | BX97: =(($F97/30)*$I97)*$M97 -> 0 | BY97: =(($G97/30)*$I97)*$M97 -> 0 | BZ97: =AC97 -> 0 | CA97: =AD97 -> 0 | CB97: =AE97 -> 0 | CC97: =AF97 -> 0 | CD97: =AN97+AS97 -> 0 | CE97: =(BX97+CA97+CC97)*0.1267 -> 0 | CF97: =SUM(BX97:CE97)-BZ97-CB97 -> 0 | CG97: =(($F97/30)*$I97)*N97 -> 0 | CH97: =(($G97/30)*$I97)*$N97 -> 0 | CI97: =+AG97 -> 0 | CJ97: =AH97 -> 0 | CK97: =AI97 -> 0 | CL97: =AJ97 -> 0 | CM97: =AO97+AT97 -> 0 | CN97: =(CG97+CJ97+CL97)*0.1267 -> 0 | CO97: =SUM(CG97:CN97)-CI97-CK97 -> 0 | CQ97: UNHESA | CR97: =IF($CQ97="PROQUIMA",$AW97+$BF97+$BO97+$BX97+$CG97,0) -> 0 | CS97: =IF($CQ97="PROQUIMA",$AX97+$BG97+$BP97+$BY97+$CH97,0) -> 0 | CT97: =IF($CQ97="PROQUIMA",$AY97+$BH97+$BQ97+$BZ97+$CI97,0) -> 0 | CU97: =IF($CQ97="PROQUIMA",$AZ97+$BI97+$BR97+$CA97+$CJ97,0) -> 0 | CV97: =IF($CQ97="PROQUIMA",$BA97+$BJ97+$BS97+$CB97+$CK97,0) -> 0 | CW97: =IF($CQ97="PROQUIMA",$BB97+$BK97+$BT97+$CC97+$CL97,0) -> 0 | CX97: =IF($CQ97="PROQUIMA",$BC97+$BL97+$BU97+$CD97+$CM97,0) -> 0 | CY97: =IF($CQ97="PROQUIMA",$BD97+$BM97+$BV97+$CE97+CN97,0) -> 0 | CZ97: =SUM(CR97:CY97)-CT97-CV97 -> 0 | DA97: =IF($CQ97="UNHESA",$AW97+$BF97+$BO97+$BX97+$CG97,0) -> 2500 | DB97: =IF($CQ97="UNHESA",$AX97+$BG97+$BP97+$BY97+$CH97,0) -> 3125 | DC97: =IF($CQ97="UNHESA",$AY97+$BH97+$BQ97+$BZ97+$CI97,0) -> 0 | DD97: =IF($CQ97="UNHESA",$AZ97+$BI97+$BR97+$CA97+$CJ97,0) -> 0 | DE97: =IF($CQ97="UNHESA",$BA97+$BJ97+$BS97+$CB97+$CK97,0) -> 0 | DF97: =IF($CQ97="UNHESA",$BB97+$BK97+$BT97+$CC97+$CL97,0) -> 0 | DG97: =IF($CQ97="UNHESA",$BC97+$BL97+$BU97+$CD97+$CM97,0) -> 0 | DH97: =IF($CQ97="UNHESA",$BD97+$BM97+$BV97+$CE97+$CN97,0) -> 316.75 | DI97: =SUM(DA97:DH97)-DC97-DE97 -> 5941.75 | DJ97: =IF($CQ97="UNHESA LIQUIDOS",$AW97+$BF97+$BO97+$BX97+$CG97,0) -> 0 | DK97: =IF($CQ97="CALIDUL",$AX97+$BG97+$BP97+$BY97+$CH97,0) -> 0 | DL97: =IF($CQ97="CALIDUL",$AY97+$BH97+$BQ97+$BZ97+$CI97,0) -> 0 | DM97: =IF($CQ97="CALIDUL",$AZ97+$BI97+$BR97+$CA97+$CJ97,0) -> 0 | DN97: =IF($CQ97="CALIDUL",$BA97+$BJ97+$BS97+$CB97+$CK97,0) -> 0 | DO97: =IF($CQ97="CALIDUL",$BB97+$BK97+$BT97+$CC97+$CL97,0) -> 0 | DP97: =IF($CQ97="CALIDUL",$BC97+$BL97+$BU97+$CD97+$CM97,0) -> 0 | DQ97: =IF($CQ97="CALIDUL",$BD97+$BM97+$BV97+$CE97+$CN97,0) -> 0 | DR97: =SUM(DJ97:DQ97)-DL97-DN97 -> 0 | DS97: =IF($CQ97="ECONACIONAL",$AW97+$BF97+$BO97+$BX97+$CG97,0) -> 0 | DT97: =IF($CQ97="ECONACIONAL",$AX97+$BG97+$BP97+$BY97+$CH97,0) -> 0 | DU97: =IF($CQ97="ECONACIONAL",$AY97+$BH97+$BQ97+$BZ97+$CI97,0) -> 0 | DV97: =IF($CQ97="ECONACIONAL",$AZ97+$BI97+$BR97+$CA97+$CJ97,0) -> 0 | DW97: =IF($CQ97="ECONACIONAL",$BA97+$BJ97+$BS97+$CB97+$CK97,0) -> 0 | DX97: =IF($CQ97="ECONACIONAL",$BB97+$BK97+$BT97+$CC97+$CL97,0) -> 0 | DY97: =IF($CQ97="ECONACIONAL",$BC97+$BL97+$BU97+$CD97+$CM97,0) -> 0 | DZ97: =IF($CQ97="ECONACIONAL",$BD97+$BM97+$BV97+$CE97+$CN97,0) -> 0 | EA97: =SUM(DS97:DZ97)-DU97-DW97 -> 0 | EB97: =IF($CQ97="CLEARTEC",$AW97+$BF97+$BO97+$BX97+$CG97,0) -> 0 | EC97: =IF($CQ97="CLEARTEC",$AX97+$BG97+$BP97+$BY97+$CH97,0) -> 0 | ED97: =IF($CQ97="CLEARTEC",$AY97+$BH97+$BQ97+$BZ97+$CI97,0) -> 0 | EE97: =IF($CQ97="CLEARTEC",$AZ97+$BI97+$BR97+$CA97+$CJ97,0) -> 0 | EF97: =IF($CQ97="CLEARTEC",$BA97+$BJ97+$BS97+$CB97+$CK97,0) -> 0 | EG97: =IF($CQ97="CLEARTEC",$BB97+$BK97+$BT97+$CC97+$CL97,0) -> 0 | EH97: =IF($CQ97="CLEARTEC",$BC97+$BL97+$BU97+$CD97+$CM97,0) -> 0 | EI97: =IF($CQ97="CLEARTEC",$BD97+$BM97+$BV97+$CE97+$CN97,0) -> 0 | EJ97: =SUM(EB97:EI97)-ED97-EF97 -> 0 | EL97: 234.01 | ER97: 622.34 | EU97: =+EP97+EQ97+ER97 -> 622.34 | EW97: =IF($I97<=15,EL97/2,EL97) -> 117.005 | EX97: =IF($I97<=15,EM97/2,EM97) -> 0 | EY97: =IF($I97<=15,EN97/2,EN97) -> 0 | EZ97: =IF($I97<=15,EO97/2,EO97) -> 0 | FA97: =IF($I97<=15,EP97/2,EP97) -> 0 | FB97: =IF($I97<=15,EQ97/2,EQ97) -> 0 | FC97: =IF($I97<=15,ER97/2,ER97) -> 311.17 | FD97: =IF($I97<=15,ES97/2,ES97) -> 0 | ... FF97: =IF($I97<=15,EU97/2,EU97) -> 311.17 | FN97: =(((F97/30/8)*1.5)*(Q97+U97+Y97))-(AZ97+BI97+BR97) -> 0 | FO97: =(((F97/30/8)*2)*(S97+W97+AA97))-(BB97+BK97+BT97) -> 0 | FP97: =(SUM(AW97:CF97))-(SUM(CR97:DR97)) -> 0 | FQ97: =(F97/30*I97)-(CR97+DA97+DJ97) -> 0 | FR97: =(SUM(EL97:EU97))-((SUM(EW97:FF97))*$FR$5) -> 739.345
A98: 201010 | B98: =+B97+1 -> 23 | C98: Chavez Garcia Benner Amilcar | D98: Coordinador Administrativo | E98: PROQUIMA | F98: 4300 | G98: 250 | H98: =+F98+G98 -> 4550 | I98: 15 | J98: 1 | K98: 0 | L98: 0 | M98: 0 | N98: 0 | O98: =SUM(J98:N98) -> 1 | R98: =($F98/30/8*1.5)*Q98 -> 0 | T98: =($F98/30/8*2)*S98 -> 0 | U98: 0 | V98: =($F98/30/8*1.5)*U98 -> 0 | X98: =($F98/30/8*2)*W98 -> 0 | Z98: =(($F98/30/8)*1.5)*Y98 -> 0 | AB98: =(($F98/30/8)*2)*AA98 -> 0 | AD98: =(($F98/30/8)*1.5)*AC98 -> 0 | AF98: =(($F98/30/8)*2)*AE98 -> 0 | AH98: =(($F98/30/8)*1.5)*AG98 -> 0 | AJ98: =(($F98/30/8)*2)*AI98 -> 0 | AW98: =((F98/30)*I98)*$J98 -> 2150 | AX98: =((G98/30)*I98)*$J98+375 -> 500 | AY98: =Q98 -> 0 | AZ98: =R98 -> 0 | BA98: =S98 -> 0 | BB98: =T98 -> 0 | BC98: =AK98+AP98 -> 0 | BD98: =(AW98+AZ98+BB98+BC98)*0.1267 -> 272.405 | BE98: =SUM(AW98:BD98)-AY98-BA98 -> 2922.405 | BF98: =(($F98/30)*$I98)*$K98 -> 0 | BG98: =(($G98/30)*$I98)*$K98 -> 0 | BH98: =U98 -> 0 | BI98: =V98 -> 0 | BJ98: =W98 -> 0 | BK98: =X98 -> 0 | BL98: =AL98+AQ98 -> 0 | BM98: =(+BF98+BI98+BK98+BL98)*0.1267 -> 0 | BN98: =SUM(BF98:BM98)-BH98-BJ98 -> 0 | BO98: =(($F98/30)*$I98)*$L98 -> 0 | BP98: =(($G98/30)*$I98)*$L98 -> 0 | BQ98: =Y98 -> 0 | BR98: =Z98 -> 0 | BS98: =AA98 -> 0 | BT98: =AB98 -> 0 | BU98: =AM98+AR98 -> 0 | BV98: =(BO98+BR98+BT98+BU98)*0.1267 -> 0 | BW98: =SUM(BO98:BV98)-BQ98-BS98 -> 0 | BX98: =(($F98/30)*$I98)*$M98 -> 0 | BY98: =(($G98/30)*$I98)*$M98 -> 0 | BZ98: =AC98 -> 0 | CA98: =AD98 -> 0 | CB98: =AE98 -> 0 | CC98: =AF98 -> 0 | CD98: =AN98+AS98 -> 0 | CE98: =(BX98+CA98+CC98)*0.1267 -> 0 | CF98: =SUM(BX98:CE98)-BZ98-CB98 -> 0 | CG98: =(($F98/30)*$I98)*N98 -> 0 | CH98: =(($G98/30)*$I98)*$N98 -> 0 | CI98: =+AG98 -> 0 | CJ98: =AH98 -> 0 | CK98: =AI98 -> 0 | CL98: =AJ98 -> 0 | CM98: =AO98+AT98 -> 0 | CN98: =(CG98+CJ98+CL98)*0.1267 -> 0 | CO98: =SUM(CG98:CN98)-CI98-CK98 -> 0 | CQ98: PROQUIMA | CR98: =IF($CQ98="PROQUIMA",$AW98+$BF98+$BO98+$BX98+$CG98,0) -> 2150 | CS98: =IF($CQ98="PROQUIMA",$AX98+$BG98+$BP98+$BY98+$CH98,0) -> 500 | CT98: =IF($CQ98="PROQUIMA",$AY98+$BH98+$BQ98+$BZ98+$CI98,0) -> 0 | CU98: =IF($CQ98="PROQUIMA",$AZ98+$BI98+$BR98+$CA98+$CJ98,0) -> 0 | CV98: =IF($CQ98="PROQUIMA",$BA98+$BJ98+$BS98+$CB98+$CK98,0) -> 0 | CW98: =IF($CQ98="PROQUIMA",$BB98+$BK98+$BT98+$CC98+$CL98,0) -> 0 | CX98: =IF($CQ98="PROQUIMA",$BC98+$BL98+$BU98+$CD98+$CM98,0) -> 0 | CY98: =IF($CQ98="PROQUIMA",$BD98+$BM98+$BV98+$CE98+CN98,0) -> 272.405 | CZ98: =SUM(CR98:CY98)-CT98-CV98 -> 2922.405 | DA98: =IF($CQ98="UNHESA",$AW98+$BF98+$BO98+$BX98+$CG98,0) -> 0 | DB98: =IF($CQ98="UNHESA",$AX98+$BG98+$BP98+$BY98+$CH98,0) -> 0 | DC98: =IF($CQ98="UNHESA",$AY98+$BH98+$BQ98+$BZ98+$CI98,0) -> 0 | DD98: =IF($CQ98="UNHESA",$AZ98+$BI98+$BR98+$CA98+$CJ98,0) -> 0 | DE98: =IF($CQ98="UNHESA",$BA98+$BJ98+$BS98+$CB98+$CK98,0) -> 0 | DF98: =IF($CQ98="UNHESA",$BB98+$BK98+$BT98+$CC98+$CL98,0) -> 0 | DG98: =IF($CQ98="UNHESA",$BC98+$BL98+$BU98+$CD98+$CM98,0) -> 0 | DH98: =IF($CQ98="UNHESA",$BD98+$BM98+$BV98+$CE98+$CN98,0) -> 0 | DI98: =SUM(DA98:DH98)-DC98-DE98 -> 0 | DJ98: =IF($CQ98="UNHESA LIQUIDOS",$AW98+$BF98+$BO98+$BX98+$CG98,0) -> 0 | DK98: =IF($CQ98="UNHESA LIQUIDOS",$AX98+$BG98+$BP98+$BY98+$CH98,0) -> 0 | DL98: =IF($CQ98="UNHESA LIQUIDOS",$AY98+$BH98+$BQ98+$BZ98+$CI98,0) -> 0 | DM98: =IF($CQ98="UNHESA LIQUIDOS",$AZ98+$BI98+$BR98+$CA98+$CJ98,0) -> 0 | DN98: =IF($CQ98="UNHESA LIQUIDOS",$BA98+$BJ98+$BS98+$CB98+$CK98,0) -> 0 | DO98: =IF($CQ98="UNHESA LIQUIDOS",$BB98+$BK98+$BT98+$CC98+$CL98,0) -> 0 | DP98: =IF($CQ98="UNHESA LIQUIDOS",$BC98+$BL98+$BU98+$CD98+$CM98,0) -> 0 | DQ98: =IF($CQ98="UNHESA LIQUIDOS",$BD98+$BM98+$BV98+$CE98+$CN98,0) -> 0 | DR98: =SUM(DJ98:DQ98)-DL98-DN98 -> 0 | DS98: =IF($CQ98="ECONACIONAL",$AW98+$BF98+$BO98+$BX98+$CG98,0) -> 0 | DT98: =IF($CQ98="ECONACIONAL",$AX98+$BG98+$BP98+$BY98+$CH98,0) -> 0 | DU98: =IF($CQ98="ECONACIONAL",$AY98+$BH98+$BQ98+$BZ98+$CI98,0) -> 0 | DV98: =IF($CQ98="ECONACIONAL",$AZ98+$BI98+$BR98+$CA98+$CJ98,0) -> 0 | DW98: =IF($CQ98="ECONACIONAL",$BA98+$BJ98+$BS98+$CB98+$CK98,0) -> 0 | DX98: =IF($CQ98="ECONACIONAL",$BB98+$BK98+$BT98+$CC98+$CL98,0) -> 0 | DY98: =IF($CQ98="ECONACIONAL",$BC98+$BL98+$BU98+$CD98+$CM98,0) -> 0 | DZ98: =IF($CQ98="ECONACIONAL",$BD98+$BM98+$BV98+$CE98+$CN98,0) -> 0 | EA98: =SUM(DS98:DZ98)-DU98-DW98 -> 0 | EB98: =IF($CQ98="CLEARTEC",$AW98+$BF98+$BO98+$BX98+$CG98,0) -> 0 | EC98: =IF($CQ98="CLEARTEC",$AX98+$BG98+$BP98+$BY98+$CH98,0) -> 0 | ED98: =IF($CQ98="CLEARTEC",$AY98+$BH98+$BQ98+$BZ98+$CI98,0) -> 0 | EE98: =IF($CQ98="CLEARTEC",$AZ98+$BI98+$BR98+$CA98+$CJ98,0) -> 0 | EF98: =IF($CQ98="CLEARTEC",$BA98+$BJ98+$BS98+$CB98+$CK98,0) -> 0 | EG98: =IF($CQ98="CLEARTEC",$BB98+$BK98+$BT98+$CC98+$CL98,0) -> 0 | EH98: =IF($CQ98="CLEARTEC",$BC98+$BL98+$BU98+$CD98+$CM98,0) -> 0 | EI98: =IF($CQ98="CLEARTEC",$BD98+$BM98+$BV98+$CE98+$CN98,0) -> 0 | EJ98: =SUM(EB98:EI98)-ED98-EF98 -> 0 | EL98: 52.23 | EO98: =283.5*2 -> 567 | EU98: =+EP98+EQ98+ER98 -> 0 | EW98: =IF($I98<=15,EL98/2,EL98) -> 26.115 | EX98: =IF($I98<=15,EM98/2,EM98) -> 0 | EY98: =IF($I98<=15,EN98/2,EN98) -> 0 | EZ98: =IF($I98<=15,EO98/2,EO98) -> 283.5 | FA98: =IF($I98<=15,EP98/2,EP98) -> 0 | FB98: =IF($I98<=15,EQ98/2,EQ98) -> 0 | FC98: =IF($I98<=15,ER98/2,ER98) -> 0 | FD98: =IF($I98<=15,ES98/2,ES98) -> 0 | ... FF98: =IF($I98<=15,EU98/2,EU98) -> 0 | FG98: 0.5 | FH98: 0.5 | FI98: 0 | FJ98: 0 | FK98: 0 | FL98: 1 | FN98: =(((F98/30/8)*1.5)*(Q98+U98+Y98))-(AZ98+BI98+BR98) -> 0 | FO98: =(((F98/30/8)*2)*(S98+W98+AA98))-(BB98+BK98+BT98) -> 0 | FP98: =(SUM(AW98:CF98))-(SUM(CR98:DR98)) -> 0 | FQ98: =(F98/30*I98)-(CR98+DA98+DJ98) -> 0 | FR98: =(SUM(EL98:EU98))-((SUM(EW98:FF98))*$FR$5) -> 309.615
D99: total Ruta Administrativa | F99: =SUM(F95:F98) -> 18450 | G99: =SUM(G95:G98) -> 5000 | H99: =SUM(H95:H98) -> 23450 | Q99: =SUM(Q95:Q98) -> 0 | R99: =SUM(R95:R98) -> 0 | S99: =SUM(S95:S98) -> 0 | T99: =SUM(T95:T98) -> 0 | U99: =SUM(U95:U98) -> 0 | V99: =SUM(V95:V98) -> 0 | W99: =SUM(W95:W98) -> 0 | X99: =SUM(X95:X98) -> 0 | ... FF99: =SUM(FF95:FF98) -> 311.17
G100: =+G98-250 -> 0
C101: Venta Tecnica
A102: 201020 | C102: Ruta Agroindustria
A103: 201020 | B103: 24 | C103: Lopez de Lopez Angelica Elizabeth | D103: Asesor JR Comercial | E103: PROQUIMA | F103: 5000 | G103: =250 -> 250 | H103: =+F103+G103 -> 5250 | I103: 15 | J103: 1 | K103: 0 | L103: 0 | M103: 0 | N103: 0 | O103: =SUM(J103:N103) -> 1 | R103: =($F103/30/8*1.5)*Q103 -> 0 | T103: =($F103/30/8*2)*S103 -> 0 | U103: 0 | V103: =($F103/30/8*1.5)*U103 -> 0 | X103: =($F103/30/8*2)*W103 -> 0 | Z103: =(($F103/30/8)*1.5)*Y103 -> 0 | AB103: =(($F103/30/8)*2)*AA103 -> 0 | AD103: =(($F103/30/8)*1.5)*AC103 -> 0 | AF103: =(($F103/30/8)*2)*AE103 -> 0 | AH103: =(($F103/30/8)*1.5)*AG103 -> 0 | AJ103: =(($F103/30/8)*2)*AI103 -> 0 | AW103: =((F103/30)*I103)*$J103 -> 2500 | AX103: =((G103/30)*I103)*$J103+5250 -> 5375 | AY103: =Q103 -> 0 | AZ103: =R103 -> 0 | BA103: =S103 -> 0 | BB103: =T103 -> 0 | BC103: =AK103+AP103 -> 0 | BD103: =(AW103+AZ103+BB103+BC103)*0.1267 -> 316.75 | BE103: =SUM(AW103:BD103)-AY103-BA103 -> 8191.75 | BF103: =(($F103/30)*$I103)*$K103 -> 0 | BG103: =(($G103/30)*$I103)*$K103 -> 0 | BH103: =U103 -> 0 | BI103: =V103 -> 0 | BJ103: =W103 -> 0 | BK103: =X103 -> 0 | BL103: =AL103+AQ103 -> 0 | BM103: =(+BF103+BI103+BK103+BL103)*0.1267 -> 0 | BN103: =SUM(BF103:BM103)-BH103-BJ103 -> 0 | BO103: =(($F103/30)*$I103)*$L103 -> 0 | BP103: =(($G103/30)*$I103)*$L103 -> 0 | BQ103: =Y103 -> 0 | BR103: =Z103 -> 0 | BS103: =AA103 -> 0 | BT103: =AB103 -> 0 | BU103: =AM103+AR103 -> 0 | BV103: =(BO103+BR103+BT103+BU103)*0.1267 -> 0 | BW103: =SUM(BO103:BV103)-BQ103-BS103 -> 0 | BX103: =(($F103/30)*$I103)*$M103 -> 0 | BY103: =(($G103/30)*$I103)*$M103 -> 0 | BZ103: =AC103 -> 0 | CA103: =AD103 -> 0 | CB103: =AE103 -> 0 | CC103: =AF103 -> 0 | CD103: =AN103+AS103 -> 0 | CE103: =(BX103+CA103+CC103)*0.1267 -> 0 | CF103: =SUM(BX103:CE103)-BZ103-CB103 -> 0 | CG103: =(($F103/30)*$I103)*N103 -> 0 | CH103: =(($G103/30)*$I103)*$N103 -> 0 | CI103: =+AG103 -> 0 | CJ103: =AH103 -> 0 | CK103: =AI103 -> 0 | CL103: =AJ103 -> 0 | CM103: =AO103+AT103 -> 0 | CN103: =(CG103+CJ103+CL103)*0.1267 -> 0 | CO103: =SUM(CG103:CN103)-CI103-CK103 -> 0 | CQ103: PROQUIMA | CR103: =IF($CQ103="PROQUIMA",$AW103+$BF103+$BO103+$BX103+$CG103,0) -> 2500 | CS103: =IF($CQ103="PROQUIMA",$AX103+$BG103+$BP103+$BY103+$CH103,0) -> 5375 | CT103: =IF($CQ103="PROQUIMA",$AY103+$BH103+$BQ103+$BZ103+$CI103,0) -> 0 | CU103: =IF($CQ103="PROQUIMA",$AZ103+$BI103+$BR103+$CA103+$CJ103,0) -> 0 | CV103: =IF($CQ103="PROQUIMA",$BA103+$BJ103+$BS103+$CB103+$CK103,0) -> 0 | CW103: =IF($CQ103="PROQUIMA",$BB103+$BK103+$BT103+$CC103+$CL103,0) -> 0 | CX103: =IF($CQ103="PROQUIMA",$BC103+$BL103+$BU103+$CD103+$CM103,0) -> 0 | CY103: =IF($CQ103="PROQUIMA",$BD103+$BM103+$BV103+$CE103+CN103,0) -> 316.75 | CZ103: =SUM(CR103:CY103)-CT103-CV103 -> 8191.75 | DA103: =IF($CQ103="UNHESA",$AW103+$BF103+$BO103+$BX103+$CG103,0) -> 0 | DB103: =IF($CQ103="UNHESA",$AX103+$BG103+$BP103+$BY103+$CH103,0) -> 0 | DC103: =IF($CQ103="UNHESA",$AY103+$BH103+$BQ103+$BZ103+$CI103,0) -> 0 | DD103: =IF($CQ103="UNHESA",$AZ103+$BI103+$BR103+$CA103+$CJ103,0) -> 0 | DE103: =IF($CQ103="UNHESA",$BA103+$BJ103+$BS103+$CB103+$CK103,0) -> 0 | DF103: =IF($CQ103="UNHESA",$BB103+$BK103+$BT103+$CC103+$CL103,0) -> 0 | DG103: =IF($CQ103="UNHESA",$BC103+$BL103+$BU103+$CD103+$CM103,0) -> 0 | DH103: =IF($CQ103="UNHESA",$BD103+$BM103+$BV103+$CE103+$CN103,0) -> 0 | DI103: =SUM(DA103:DH103)-DC103-DE103 -> 0 | DJ103: =IF($CQ103="UNHESA LIQUIDOS",$AW103+$BF103+$BO103+$BX103+$CG103,0) -> 0 | DK103: =IF($CQ103="UNHESA LIQUIDOS",$AX103+$BG103+$BP103+$BY103+$CH103,0) -> 0 | DL103: =IF($CQ103="UNHESA LIQUIDOS",$AY103+$BH103+$BQ103+$BZ103+$CI103,0) -> 0 | DM103: =IF($CQ103="UNHESA LIQUIDOS",$AZ103+$BI103+$BR103+$CA103+$CJ103,0) -> 0 | DN103: =IF($CQ103="UNHESA LIQUIDOS",$BA103+$BJ103+$BS103+$CB103+$CK103,0) -> 0 | DO103: =IF($CQ103="UNHESA LIQUIDOS",$BB103+$BK103+$BT103+$CC103+$CL103,0) -> 0 | DP103: =IF($CQ103="UNHESA LIQUIDOS",$BC103+$BL103+$BU103+$CD103+$CM103,0) -> 0 | DQ103: =IF($CQ103="UNHESA LIQUIDOS",$BD103+$BM103+$BV103+$CE103+$CN103,0) -> 0 | DR103: =SUM(DJ103:DQ103)-DL103-DN103 -> 0 | DS103: =IF($CQ103="ECONACIONAL",$AW103+$BF103+$BO103+$BX103+$CG103,0) -> 0 | DT103: =IF($CQ103="ECONACIONAL",$AX103+$BG103+$BP103+$BY103+$CH103,0) -> 0 | DU103: =IF($CQ103="ECONACIONAL",$AY103+$BH103+$BQ103+$BZ103+$CI103,0) -> 0 | DV103: =IF($CQ103="ECONACIONAL",$AZ103+$BI103+$BR103+$CA103+$CJ103,0) -> 0 | DW103: =IF($CQ103="ECONACIONAL",$BA103+$BJ103+$BS103+$CB103+$CK103,0) -> 0 | DX103: =IF($CQ103="ECONACIONAL",$BB103+$BK103+$BT103+$CC103+$CL103,0) -> 0 | DY103: =IF($CQ103="ECONACIONAL",$BC103+$BL103+$BU103+$CD103+$CM103,0) -> 0 | DZ103: =IF($CQ103="ECONACIONAL",$BD103+$BM103+$BV103+$CE103+$CN103,0) -> 0 | EA103: =SUM(DS103:DZ103)-DU103-DW103 -> 0 | EB103: =IF($CQ103="CLEARTEC",$AW103+$BF103+$BO103+$BX103+$CG103,0) -> 0 | EC103: =IF($CQ103="CLEARTEC",$AX103+$BG103+$BP103+$BY103+$CH103,0) -> 0 | ED103: =IF($CQ103="CLEARTEC",$AY103+$BH103+$BQ103+$BZ103+$CI103,0) -> 0 | EE103: =IF($CQ103="CLEARTEC",$AZ103+$BI103+$BR103+$CA103+$CJ103,0) -> 0 | EF103: =IF($CQ103="CLEARTEC",$BA103+$BJ103+$BS103+$CB103+$CK103,0) -> 0 | EG103: =IF($CQ103="CLEARTEC",$BB103+$BK103+$BT103+$CC103+$CL103,0) -> 0 | EH103: =IF($CQ103="CLEARTEC",$BC103+$BL103+$BU103+$CD103+$CM103,0) -> 0 | EI103: =IF($CQ103="CLEARTEC",$BD103+$BM103+$BV103+$CE103+$CN103,0) -> 0 | EJ103: =SUM(EB103:EI103)-ED103-EF103 -> 0 | EL103: 318.48 | EO103: =75*2 -> 150 | EU103: =+EP103+EQ103+ER103 -> 0 | EW103: =IF($I103<=15,EL103/2,EL103) -> 159.24 | EX103: =IF($I103<=15,EM103/2,EM103) -> 0 | EY103: =IF($I103<=15,EN103/2,EN103) -> 0 | EZ103: =IF($I103<=15,EO103/2,EO103) -> 75 | FA103: =IF($I103<=15,EP103/2,EP103) -> 0 | FB103: =IF($I103<=15,EQ103/2,EQ103) -> 0 | FC103: =IF($I103<=15,ER103/2,ER103) -> 0 | FD103: =IF($I103<=15,ES103/2,ES103) -> 0 | ... FF103: =IF($I103<=15,EU103/2,EU103) -> 0 | FG103: 1 | FH103: 0 | FI103: 0 | FJ103: 0 | FK103: 0 | FL103: 1 | FN103: =(((F103/30/8)*1.5)*(Q103+U103+Y103))-(AZ103+BI103+BR103) -> 0 | FO103: =(((F103/30/8)*2)*(S103+W103+AA103))-(BB103+BK103+BT103) -> 0 | FP103: =(SUM(AW103:CF103))-(SUM(CR103:DR103)) -> 0 | FQ103: =(F103/30*I103)-(CR103+DA103+DJ103) -> 0 | FR103: =(SUM(EL103:EU103))-((SUM(EW103:FF103))*$FR$5) -> 234.24
A104: 201020 | F104: =+F103 -> 5000 | G104: =+G103 -> 250 | H104: =+H103 -> 5250 | Q104: =+Q103 -> 0 | R104: =+R103 -> 0 | S104: =+S103 -> 0 | T104: =+T103 -> 0 | U104: =+U103 -> 0 | V104: =+V103 -> 0 | W104: =+W103 -> 0 | X104: =+X103 -> 0 | ... FF104: =+FF103 -> 0
A105: 201020 | C105: Ruta Industria 1
A106: 201020 | B106: 25 | C106: Samayoa Chavarria Leslie Amabilia | D106: Asesor | E106: PROQUIMA | F106: 6000 | G106: =250 -> 250 | H106: =+F106+G106 -> 6250 | I106: 14 | J106: 1 | K106: 0 | L106: 0 | M106: 0 | N106: 0 | O106: =SUM(J106:N106) -> 1 | P106: descuento de dia x estar en negativo en vacas TODOS LOS MESES SE DESCUENTA 1 DIA INICIA FEB FINALIZA FEB 2027 | R106: =($F106/30/8*1.5)*Q106 -> 0 | S106: 0 | T106: =($F106/30/8*2)*S106 -> 0 | V106: =($F106/30/8*1.5)*U106 -> 0 | X106: =($F106/30/8*2)*W106 -> 0 | Z106: =(($F106/30/8)*1.5)*Y106 -> 0 | AB106: =(($F106/30/8)*2)*AA106 -> 0 | AD106: =(($F106/30/8)*1.5)*AC106 -> 0 | AF106: =(($F106/30/8)*2)*AE106 -> 0 | AH106: =(($F106/30/8)*1.5)*AG106 -> 0 | AJ106: =(($F106/30/8)*2)*AI106 -> 0 | AW106: =((F106/30)*I106)*$J106 -> 2800 | AX106: =((G106/30)*I106)*$J106+5250 -> 5366.6667 | AY106: =Q106 -> 0 | AZ106: =R106 -> 0 | BA106: =S106 -> 0 | BB106: =T106 -> 0 | BC106: =AK106+AP106 -> 0 | BD106: =(AW106+AZ106+BB106+BC106)*0.1267 -> 354.76 | BE106: =SUM(AW106:BD106)-AY106-BA106 -> 8521.4267 | BF106: =(($F106/30)*$I106)*$K106 -> 0 | BG106: =(($G106/30)*$I106)*$K106 -> 0 | BH106: =U106 -> 0 | BI106: =V106 -> 0 | BK106: =X106 -> 0 | BL106: 0 | BM106: =(+BF106+BI106+BK106+BL106)*0.1267 -> 0 | BN106: =SUM(BF106:BM106)-BH106-BJ106 -> 0 | BO106: =(($F106/30)*$I106)*$L106 -> 0 | BP106: =(($G106/30)*$I106)*$L106 -> 0 | BQ106: =Y106 -> 0 | BR106: =Z106 -> 0 | BS106: =AA106 -> 0 | BT106: =AB106 -> 0 | BU106: =AM106+AR106 -> 0 | BV106: =(BO106+BR106+BT106+BU106)*0.1267 -> 0 | BW106: =SUM(BO106:BV106)-BQ106-BS106 -> 0 | BX106: =(($F106/30)*$I106)*$M106 -> 0 | BY106: =(($G106/30)*$I106)*$M106 -> 0 | BZ106: =AC106 -> 0 | CA106: =AD106 -> 0 | CB106: =AE106 -> 0 | CC106: =AF106 -> 0 | CD106: =AN106+AS106 -> 0 | CE106: =(BX106+CA106+CC106)*0.1267 -> 0 | CF106: =SUM(BX106:CE106)-BZ106-CB106 -> 0 | CG106: =(($F106/30)*$I106)*N106 -> 0 | CH106: =(($G106/30)*$I106)*$N106 -> 0 | CI106: =+AG106 -> 0 | CJ106: =AH106 -> 0 | CK106: =AI106 -> 0 | CL106: =AJ106 -> 0 | CM106: =AO106+AT106 -> 0 | CN106: =(CG106+CJ106+CL106)*0.1267 -> 0 | CO106: =SUM(CG106:CN106)-CI106-CK106 -> 0 | CQ106: PROQUIMA | CR106: =IF($CQ106="PROQUIMA",$AW106+$BF106+$BO106+$BX106+$CG106,0) -> 2800 | CS106: =IF($CQ106="PROQUIMA",$AX106+$BG106+$BP106+$BY106+$CH106,0) -> 5366.6667 | CT106: =IF($CQ106="PROQUIMA",$AY106+$BH106+$BQ106+$BZ106+$CI106,0) -> 0 | CU106: =IF($CQ106="PROQUIMA",$AZ106+$BI106+$BR106+$CA106+$CJ106,0) -> 0 | CV106: =IF($CQ106="PROQUIMA",$BA106+$BJ106+$BS106+$CB106+$CK106,0) -> 0 | CW106: =IF($CQ106="PROQUIMA",$BB106+$BK106+$BT106+$CC106+$CL106,0) -> 0 | CX106: =IF($CQ106="PROQUIMA",$BC106+$BL106+$BU106+$CD106+$CM106,0) -> 0 | CY106: =IF($CQ106="PROQUIMA",$BD106+$BM106+$BV106+$CE106+CN106,0) -> 354.76 | CZ106: =SUM(CR106:CY106)-CT106-CV106 -> 8521.4267 | DA106: =IF($CQ106="UNHESA",$AW106+$BF106+$BO106+$BX106+$CG106,0) -> 0 | DB106: =IF($CQ106="UNHESA",$AX106+$BG106+$BP106+$BY106+$CH106,0) -> 0 | DC106: =IF($CQ106="UNHESA",$AY106+$BH106+$BQ106+$BZ106+$CI106,0) -> 0 | DD106: =IF($CQ106="UNHESA",$AZ106+$BI106+$BR106+$CA106+$CJ106,0) -> 0 | DE106: =IF($CQ106="UNHESA",$BA106+$BJ106+$BS106+$CB106+$CK106,0) -> 0 | DF106: =IF($CQ106="UNHESA",$BB106+$BK106+$BT106+$CC106+$CL106,0) -> 0 | DG106: =IF($CQ106="UNHESA",$BC106+$BL106+$BU106+$CD106+$CM106,0) -> 0 | DH106: =IF($CQ106="UNHESA",$BD106+$BM106+$BV106+$CE106+$CN106,0) -> 0 | DI106: =SUM(DA106:DH106)-DC106-DE106 -> 0 | DJ106: =IF($CQ106="UNHESA LIQUIDOS",$AW106+$BF106+$BO106+$BX106+$CG106,0) -> 0 | DK106: =IF($CQ106="UNHESA LIQUIDOS",$AX106+$BG106+$BP106+$BY106+$CH106,0) -> 0 | DL106: =IF($CQ106="UNHESA LIQUIDOS",$AY106+$BH106+$BQ106+$BZ106+$CI106,0) -> 0 | DM106: =IF($CQ106="UNHESA LIQUIDOS",$AZ106+$BI106+$BR106+$CA106+$CJ106,0) -> 0 | DN106: =IF($CQ106="UNHESA LIQUIDOS",$BA106+$BJ106+$BS106+$CB106+$CK106,0) -> 0 | DO106: =IF($CQ106="UNHESA LIQUIDOS",$BB106+$BK106+$BT106+$CC106+$CL106,0) -> 0 | DP106: =IF($CQ106="UNHESA LIQUIDOS",$BC106+$BL106+$BU106+$CD106+$CM106,0) -> 0 | DQ106: =IF($CQ106="UNHESA LIQUIDOS",$BD106+$BM106+$BV106+$CE106+$CN106,0) -> 0 | DR106: =SUM(DJ106:DQ106)-DL106-DN106 -> 0 | DS106: =IF($CQ106="ECONACIONAL",$AW106+$BF106+$BO106+$BX106+$CG106,0) -> 0 | DT106: =IF($CQ106="ECONACIONAL",$AX106+$BG106+$BP106+$BY106+$CH106,0) -> 0 | DU106: =IF($CQ106="ECONACIONAL",$AY106+$BH106+$BQ106+$BZ106+$CI106,0) -> 0 | DV106: =IF($CQ106="ECONACIONAL",$AZ106+$BI106+$BR106+$CA106+$CJ106,0) -> 0 | DW106: =IF($CQ106="ECONACIONAL",$BA106+$BJ106+$BS106+$CB106+$CK106,0) -> 0 | DX106: =IF($CQ106="ECONACIONAL",$BB106+$BK106+$BT106+$CC106+$CL106,0) -> 0 | DY106: =IF($CQ106="ECONACIONAL",$BC106+$BL106+$BU106+$CD106+$CM106,0) -> 0 | DZ106: =IF($CQ106="ECONACIONAL",$BD106+$BM106+$BV106+$CE106+$CN106,0) -> 0 | EA106: =SUM(DS106:DZ106)-DU106-DW106 -> 0 | EB106: =IF($CQ106="CLEARTEC",$AW106+$BF106+$BO106+$BX106+$CG106,0) -> 0 | EC106: =IF($CQ106="CLEARTEC",$AX106+$BG106+$BP106+$BY106+$CH106,0) -> 0 | ED106: =IF($CQ106="CLEARTEC",$AY106+$BH106+$BQ106+$BZ106+$CI106,0) -> 0 | EE106: =IF($CQ106="CLEARTEC",$AZ106+$BI106+$BR106+$CA106+$CJ106,0) -> 0 | EF106: =IF($CQ106="CLEARTEC",$BA106+$BJ106+$BS106+$CB106+$CK106,0) -> 0 | EG106: =IF($CQ106="CLEARTEC",$BB106+$BK106+$BT106+$CC106+$CL106,0) -> 0 | EH106: =IF($CQ106="CLEARTEC",$BC106+$BL106+$BU106+$CD106+$CM106,0) -> 0 | EI106: =IF($CQ106="CLEARTEC",$BD106+$BM106+$BV106+$CE106+$CN106,0) -> 0 | EJ106: =SUM(EB106:EI106)-ED106-EF106 -> 0 | EL106: 349.15 | EU106: =+EP106+EQ106+ER106 -> 0 | EW106: =IF($I106<=15,EL106/2,EL106) -> 174.575 | EX106: =IF($I106<=15,EM106/2,EM106) -> 0 | EY106: =IF($I106<=15,EN106/2,EN106) -> 0 | EZ106: =IF($I106<=15,EO106/2,EO106) -> 0 | FA106: =IF($I106<=15,EP106/2,EP106) -> 0 | FB106: =IF($I106<=15,EQ106/2,EQ106) -> 0 | FC106: =IF($I106<=15,ER106/2,ER106) -> 0 | FD106: =IF($I106<=15,ES106/2,ES106) -> 0 | ... FF106: =IF($I106<=15,EU106/2,EU106) -> 0 | FG106: 1 | FH106: 0 | FI106: 0 | FJ106: 0 | FK106: 0 | FL106: 1 | FN106: =(((F106/30/8)*1.5)*(Q106+U106+Y106))-(AZ106+BI106+BR106) -> 0 | FO106: =(((F106/30/8)*2)*(S106+W106+AA106))-(BB106+BK106+BT106) -> 0 | FP106: =(SUM(AW106:CF106))-(SUM(CR106:DR106)) -> 0 | FQ106: =(F106/30*I106)-(CR106+DA106+DJ106) -> 0 | FR106: =(SUM(EL106:EU106))-((SUM(EW106:FF106))*$FR$5) -> 174.575
A107: 201020 | F107: =+F106 -> 6000 | G107: =+G106 -> 250 | H107: =+H106 -> 6250 | Q107: =+Q106 -> 0 | R107: =+R106 -> 0 | S107: =+S106 -> 0 | T107: =+T106 -> 0 | U107: =+U106 -> 0 | V107: =+V106 -> 0 | W107: =+W106 -> 0 | X107: =+X106 -> 0 | ... FF107: =+FF106 -> 0
C108: Ruta Industria 2
C110: Franquicias
A113: 201030 | C113: 118-Ruta Sur-Occidente
A114: 201030 | B114: 26 | C114: Recinos Martinez Dany Gudiel | D114: Vendedor Mayorista | E114: UNHESA | F114: 4002.28 | G114: 500 | H114: =+F114+G114 -> 4502.28 | I114: 15 | K114: 1 | O114: =SUM(J114:N114) -> 1 | R114: =($F114/30/8*1.5)*Q114 -> 0 | T114: =($F114/30/8*2)*S114 -> 0 | V114: =($F114/30/8*1.5)*U114 -> 0 | X114: =($F114/30/8*2)*W114 -> 0 | Z114: =(($F114/30/8)*1.5)*Y114 -> 0 | AB114: =(($F114/30/8)*2)*AA114 -> 0 | AD114: =(($F114/30/8)*1.5)*AC114 -> 0 | AF114: =(($F114/30/8)*2)*AE114 -> 0 | AH114: =(($F114/30/8)*1.5)*AG114 -> 0 | AJ114: =(($F114/30/8)*2)*AI114 -> 0 | AW114: =((F114/30)*I114)*$J114 -> 0 | AX114: =((G114/30)*I114)*$J114 -> 0 | AY114: =Q114 -> 0 | AZ114: =R114 -> 0 | BA114: =S114 -> 0 | BB114: =T114 -> 0 | BC114: =AK114+AP114 -> 0 | BD114: =(AW114+AZ114+BB114+BC114)*0.1267 -> 0 | BE114: =SUM(AW114:BD114)-AY114-BA114 -> 0 | BF114: =(($F114/30)*$I114)*$K114 -> 2001.14 | BG114: =(($G114/30)*$I114)*$K114+2756.25 -> 3006.25 | BH114: =U114 -> 0 | BI114: =V114 -> 0 | BJ114: =W114 -> 0 | BK114: =X114 -> 0 | BL114: =AL114+AQ114 -> 0 | BM114: =(+BF114+BI114+BK114+BL114)*0.1267 -> 253.54444 | BN114: =SUM(BF114:BM114)-BH114-BJ114 -> 5260.9344 | BO114: =(($F114/30)*$I114)*$L114 -> 0 | BP114: =(($G114/30)*$I114)*$L114 -> 0 | BQ114: =Y114 -> 0 | BR114: =Z114 -> 0 | BS114: =AA114 -> 0 | BT114: =AB114 -> 0 | BU114: =AM114+AR114 -> 0 | BV114: =(BO114+BR114+BT114+BU114)*0.1267 -> 0 | BW114: =SUM(BO114:BV114)-BQ114-BS114 -> 0 | BX114: =(($F114/30)*$I114)*$M114 -> 0 | BY114: =(($G114/30)*$I114)*$M114 -> 0 | BZ114: =AC114 -> 0 | CA114: =AD114 -> 0 | CB114: =AE114 -> 0 | CC114: =AF114 -> 0 | CD114: =AN114+AS114 -> 0 | CE114: =(BX114+CA114+CC114)*0.1267 -> 0 | CF114: =SUM(BX114:CE114)-BZ114-CB114 -> 0 | CG114: =(($F114/30)*$I114)*N114 -> 0 | CH114: =(($G114/30)*$I114)*$N114 -> 0 | CI114: =+AG114 -> 0 | CJ114: =AH114 -> 0 | CK114: =AI114 -> 0 | CL114: =AJ114 -> 0 | CM114: =AO114+AT114 -> 0 | CN114: =(CG114+CJ114+CL114)*0.1267 -> 0 | CO114: =SUM(CG114:CN114)-CI114-CK114 -> 0 | CQ114: UNHESA | CR114: =IF($CQ114="PROQUIMA",$AW114+$BF114+$BO114+$BX114+$CG114,0) -> 0 | CS114: =IF($CQ114="PROQUIMA",$AX114+$BG114+$BP114+$BY114+$CH114,0) -> 0 | CT114: =IF($CQ114="PROQUIMA",$AY114+$BH114+$BQ114+$BZ114+$CI114,0) -> 0 | CU114: =IF($CQ114="PROQUIMA",$AZ114+$BI114+$BR114+$CA114+$CJ114,0) -> 0 | CV114: =IF($CQ114="PROQUIMA",$BA114+$BJ114+$BS114+$CB114+$CK114,0) -> 0 | CW114: =IF($CQ114="PROQUIMA",$BB114+$BK114+$BT114+$CC114+$CL114,0) -> 0 | CX114: =IF($CQ114="PROQUIMA",$BC114+$BL114+$BU114+$CD114+$CM114,0) -> 0 | CY114: =IF($CQ114="PROQUIMA",$BD114+$BM114+$BV114+$CE114+CN114,0) -> 0 | CZ114: =SUM(CR114:CY114)-CT114-CV114 -> 0 | DA114: =IF($CQ114="UNHESA",$AW114+$BF114+$BO114+$BX114+$CG114,0) -> 2001.14 | DB114: =IF($CQ114="UNHESA",$AX114+$BG114+$BP114+$BY114+$CH114,0) -> 3006.25 | DC114: =IF($CQ114="UNHESA",$AY114+$BH114+$BQ114+$BZ114+$CI114,0) -> 0 | DD114: =IF($CQ114="UNHESA",$AZ114+$BI114+$BR114+$CA114+$CJ114,0) -> 0 | DE114: =IF($CQ114="UNHESA",$BA114+$BJ114+$BS114+$CB114+$CK114,0) -> 0 | DF114: =IF($CQ114="UNHESA",$BB114+$BK114+$BT114+$CC114+$CL114,0) -> 0 | DG114: =IF($CQ114="UNHESA",$BC114+$BL114+$BU114+$CD114+$CM114,0) -> 0 | DH114: =IF($CQ114="UNHESA",$BD114+$BM114+$BV114+$CE114+$CN114,0) -> 253.54444 | DI114: =SUM(DA114:DH114)-DC114-DE114 -> 5260.9344 | DJ114: =IF($CQ114="UNHESA LIQUIDOS",$AW114+$BF114+$BO114+$BX114+$CG114,0) -> 0 | DK114: =IF($CQ114="UNHESA LIQUIDOS",$AX114+$BG114+$BP114+$BY114+$CH114,0) -> 0 | DL114: =IF($CQ114="UNHESA LIQUIDOS",$AY114+$BH114+$BQ114+$BZ114+$CI114,0) -> 0 | DM114: =IF($CQ114="UNHESA LIQUIDOS",$AZ114+$BI114+$BR114+$CA114+$CJ114,0) -> 0 | DN114: =IF($CQ114="UNHESA LIQUIDOS",$BA114+$BJ114+$BS114+$CB114+$CK114,0) -> 0 | DO114: =IF($CQ114="UNHESA LIQUIDOS",$BB114+$BK114+$BT114+$CC114+$CL114,0) -> 0 | DP114: =IF($CQ114="UNHESA LIQUIDOS",$BC114+$BL114+$BU114+$CD114+$CM114,0) -> 0 | DQ114: =IF($CQ114="UNHESA LIQUIDOS",$BD114+$BM114+$BV114+$CE114+$CN114,0) -> 0 | DR114: =SUM(DJ114:DQ114)-DL114-DN114 -> 0 | DS114: =IF($CQ114="ECONACIONAL",$AW114+$BF114+$BO114+$BX114+$CG114,0) -> 0 | DT114: =IF($CQ114="ECONACIONAL",$AX114+$BG114+$BP114+$BY114+$CH114,0) -> 0 | DU114: =IF($CQ114="ECONACIONAL",$AY114+$BH114+$BQ114+$BZ114+$CI114,0) -> 0 | DV114: =IF($CQ114="ECONACIONAL",$AZ114+$BI114+$BR114+$CA114+$CJ114,0) -> 0 | DW114: =IF($CQ114="ECONACIONAL",$BA114+$BJ114+$BS114+$CB114+$CK114,0) -> 0 | DX114: =IF($CQ114="ECONACIONAL",$BB114+$BK114+$BT114+$CC114+$CL114,0) -> 0 | DY114: =IF($CQ114="ECONACIONAL",$BC114+$BL114+$BU114+$CD114+$CM114,0) -> 0 | DZ114: =IF($CQ114="ECONACIONAL",$BD114+$BM114+$BV114+$CE114+$CN114,0) -> 0 | EA114: =SUM(DS114:DZ114)-DU114-DW114 -> 0 | EB114: =IF($CQ114="CLEARTEC",$AW114+$BF114+$BO114+$BX114+$CG114,0) -> 0 | EC114: =IF($CQ114="CLEARTEC",$AX114+$BG114+$BP114+$BY114+$CH114,0) -> 0 | ED114: =IF($CQ114="CLEARTEC",$AY114+$BH114+$BQ114+$BZ114+$CI114,0) -> 0 | EE114: =IF($CQ114="CLEARTEC",$AZ114+$BI114+$BR114+$CA114+$CJ114,0) -> 0 | EF114: =IF($CQ114="CLEARTEC",$BA114+$BJ114+$BS114+$CB114+$CK114,0) -> 0 | EG114: =IF($CQ114="CLEARTEC",$BB114+$BK114+$BT114+$CC114+$CL114,0) -> 0 | EH114: =IF($CQ114="CLEARTEC",$BC114+$BL114+$BU114+$CD114+$CM114,0) -> 0 | EI114: =IF($CQ114="CLEARTEC",$BD114+$BM114+$BV114+$CE114+$CN114,0) -> 0 | EJ114: =SUM(EB114:EI114)-ED114-EF114 -> 0 | EL114: 97.11 | EU114: =+EP114+EQ114+ER114 -> 0 | EW114: =IF($I114<=15,EL114/2,EL114) -> 48.555 | EX114: =IF($I114<=15,EM114/2,EM114) -> 0 | EY114: =IF($I114<=15,EN114/2,EN114) -> 0 | EZ114: =IF($I114<=15,EO114/2,EO114) -> 0 | FA114: =IF($I114<=15,EP114/2,EP114) -> 0 | FB114: =IF($I114<=15,EQ114/2,EQ114) -> 0 | FC114: =IF($I114<=15,ER114/2,ER114) -> 0 | FD114: =IF($I114<=15,ES114/2,ES114) -> 0 | ... FF114: =IF($I114<=15,EU114/2,EU114) -> 0 | FN114: =(((F114/30/8)*1.5)*(Q114+U114+Y114))-(AZ114+BI114+BR114) -> 0 | FO114: =(((F114/30/8)*2)*(S114+W114+AA114))-(BB114+BK114+BT114) -> 0 | FP114: =(SUM(AW114:CF114))-(SUM(CR114:DR114)) -> 0 | FQ114: =(F114/30*I114)-(CR114+DA114+DJ114) -> 0 | FR114: =(SUM(EL114:EU114))-((SUM(EW114:FF114))*$FR$5) -> 48.555
A115: 201030 | F115: =+F114 -> 4002.28 | G115: =+G114 -> 500 | H115: =+H114 -> 4502.28 | Q115: =+Q114 -> 0 | R115: =+R114 -> 0 | S115: =+S114 -> 0 | T115: =+T114 -> 0 | U115: =+U114 -> 0 | V115: =+V114 -> 0 | W115: =+W114 -> 0 | X115: =+X114 -> 0 | ... FF115: =+FF114 -> 0
A116: 201030 | C116: 127-Ruta Fri-Oso Mercado 2
A117: 201030 | B117: 34 | C117: Sarceño Folgar Rosa Maria | D117: Vendedor Mayorista | E117: UNHESA | F117: 4002.28 | G117: 500 | H117: =+F117+G117 -> 4502.28 | I117: 15 | J117: 0 | K117: 1 | L117: 0 | M117: 0 | N117: 0 | O117: =SUM(J117:N117) -> 1 | R117: =($F117/30/8*1.5)*Q117 -> 0 | T117: =($F117/30/8*2)*S117 -> 0 | V117: =($F117/30/8*1.5)*U117 -> 0 | X117: =($F117/30/8*2)*W117 -> 0 | Z117: =(($F117/30/8)*1.5)*Y117 -> 0 | AB117: =(($F117/30/8)*2)*AA117 -> 0 | AD117: =(($F117/30/8)*1.5)*AC117 -> 0 | AF117: =(($F117/30/8)*2)*AE117 -> 0 | AH117: =(($F117/30/8)*1.5)*AG117 -> 0 | AJ117: =(($F117/30/8)*2)*AI117 -> 0 | AW117: =((F117/30)*I117)*$J117 -> 0 | AX117: =((G117/30)*I117)*$J117 -> 0 | AY117: =Q117 -> 0 | AZ117: =R117 -> 0 | BA117: =S117 -> 0 | BB117: =T117 -> 0 | BC117: =AK117+AP117 -> 0 | BD117: =(AW117+AZ117+BB117+BC117)*0.1267 -> 0 | BE117: =SUM(AW117:BD117)-AY117-BA117 -> 0 | BF117: =(($F117/30)*$I117)*$K117 -> 2001.14 | BG117: =(($G117/30)*$I117)*$K117+1286.25 -> 1536.25 | BH117: =U117 -> 0 | BI117: =V117 -> 0 | BJ117: =W117 -> 0 | BK117: =X117 -> 0 | BL117: =AL117+AQ117 -> 0 | BM117: =(+BF117+BI117+BK117+BL117)*0.1267 -> 253.54444 | BN117: =SUM(BF117:BM117)-BH117-BJ117 -> 3790.9344 | BO117: =(($F117/30)*$I117)*$L117 -> 0 | BP117: =(($G117/30)*$I117)*$L117 -> 0 | BQ117: =Y117 -> 0 | BR117: =Z117 -> 0 | BS117: =AA117 -> 0 | BT117: =AB117 -> 0 | BU117: =AM117+AR117 -> 0 | BV117: =(BO117+BR117+BT117+BU117)*0.1267 -> 0 | BW117: =SUM(BO117:BV117)-BQ117-BS117 -> 0 | BX117: =(($F117/30)*$I117)*$M117 -> 0 | BY117: =(($G117/30)*$I117)*$M117 -> 0 | BZ117: =AC117 -> 0 | CA117: =AD117 -> 0 | CB117: =AE117 -> 0 | CC117: =AF117 -> 0 | CD117: =AN117+AS117 -> 0 | CE117: =(BX117+CA117+CC117)*0.1267 -> 0 | CF117: =SUM(BX117:CE117)-BZ117-CB117 -> 0 | CG117: =(($F117/30)*$I117)*N117 -> 0 | CH117: =(($G117/30)*$I117)*$N117 -> 0 | CI117: =+AG117 -> 0 | CJ117: =AH117 -> 0 | CK117: =AI117 -> 0 | CL117: =AJ117 -> 0 | CM117: =AO117+AT117 -> 0 | CN117: =(CG117+CJ117+CL117)*0.1267 -> 0 | CO117: =SUM(CG117:CN117)-CI117-CK117 -> 0 | CQ117: UNHESA | CR117: =IF($CQ117="PROQUIMA",$AW117+$BF117+$BO117+$BX117+$CG117,0) -> 0 | CS117: =IF($CQ117="PROQUIMA",$AX117+$BG117+$BP117+$BY117+$CH117,0) -> 0 | CT117: =IF($CQ117="PROQUIMA",$AY117+$BH117+$BQ117+$BZ117+$CI117,0) -> 0 | CU117: =IF($CQ117="PROQUIMA",$AZ117+$BI117+$BR117+$CA117+$CJ117,0) -> 0 | CV117: =IF($CQ117="PROQUIMA",$BA117+$BJ117+$BS117+$CB117+$CK117,0) -> 0 | CW117: =IF($CQ117="PROQUIMA",$BB117+$BK117+$BT117+$CC117+$CL117,0) -> 0 | CX117: =IF($CQ117="PROQUIMA",$BC117+$BL117+$BU117+$CD117+$CM117,0) -> 0 | CY117: =IF($CQ117="PROQUIMA",$BD117+$BM117+$BV117+$CE117+CN117,0) -> 0 | CZ117: =SUM(CR117:CY117)-CT117-CV117 -> 0 | DA117: =IF($CQ117="UNHESA",$AW117+$BF117+$BO117+$BX117+$CG117,0) -> 2001.14 | DB117: =IF($CQ117="UNHESA",$AX117+$BG117+$BP117+$BY117+$CH117,0) -> 1536.25 | DC117: =IF($CQ117="UNHESA",$AY117+$BH117+$BQ117+$BZ117+$CI117,0) -> 0 | DD117: =IF($CQ117="UNHESA",$AZ117+$BI117+$BR117+$CA117+$CJ117,0) -> 0 | DE117: =IF($CQ117="UNHESA",$BA117+$BJ117+$BS117+$CB117+$CK117,0) -> 0 | DF117: =IF($CQ117="UNHESA",$BB117+$BK117+$BT117+$CC117+$CL117,0) -> 0 | DG117: =IF($CQ117="UNHESA",$BC117+$BL117+$BU117+$CD117+$CM117,0) -> 0 | DH117: =IF($CQ117="UNHESA",$BD117+$BM117+$BV117+$CE117+$CN117,0) -> 253.54444 | DI117: =SUM(DA117:DH117)-DC117-DE117 -> 3790.9344 | DJ117: =IF($CQ117="UNHESA LIQUIDOS",$AW117+$BF117+$BO117+$BX117+$CG117,0) -> 0 | DK117: =IF($CQ117="UNHESA LIQUIDOS",$AX117+$BG117+$BP117+$BY117+$CH117,0) -> 0 | DL117: =IF($CQ117="UNHESA LIQUIDOS",$AY117+$BH117+$BQ117+$BZ117+$CI117,0) -> 0 | DM117: =IF($CQ117="UNHESA LIQUIDOS",$AZ117+$BI117+$BR117+$CA117+$CJ117,0) -> 0 | DN117: =IF($CQ117="UNHESA LIQUIDOS",$BA117+$BJ117+$BS117+$CB117+$CK117,0) -> 0 | DO117: =IF($CQ117="UNHESA LIQUIDOS",$BB117+$BK117+$BT117+$CC117+$CL117,0) -> 0 | DP117: =IF($CQ117="UNHESA LIQUIDOS",$BC117+$BL117+$BU117+$CD117+$CM117,0) -> 0 | DQ117: =IF($CQ117="UNHESA LIQUIDOS",$BD117+$BM117+$BV117+$CE117+$CN117,0) -> 0 | DR117: =SUM(DJ117:DQ117)-DL117-DN117 -> 0 | DS117: =IF($CQ117="ECONACIONAL",$AW117+$BF117+$BO117+$BX117+$CG117,0) -> 0 | DT117: =IF($CQ117="ECONACIONAL",$AX117+$BG117+$BP117+$BY117+$CH117,0) -> 0 | DU117: =IF($CQ117="ECONACIONAL",$AY117+$BH117+$BQ117+$BZ117+$CI117,0) -> 0 | DV117: =IF($CQ117="ECONACIONAL",$AZ117+$BI117+$BR117+$CA117+$CJ117,0) -> 0 | DW117: =IF($CQ117="ECONACIONAL",$BA117+$BJ117+$BS117+$CB117+$CK117,0) -> 0 | DX117: =IF($CQ117="ECONACIONAL",$BB117+$BK117+$BT117+$CC117+$CL117,0) -> 0 | DY117: =IF($CQ117="ECONACIONAL",$BC117+$BL117+$BU117+$CD117+$CM117,0) -> 0 | DZ117: =IF($CQ117="ECONACIONAL",$BD117+$BM117+$BV117+$CE117+$CN117,0) -> 0 | EA117: =SUM(DS117:DZ117)-DU117-DW117 -> 0 | EB117: =IF($CQ117="CLEARTEC",$AW117+$BF117+$BO117+$BX117+$CG117,0) -> 0 | EC117: =IF($CQ117="CLEARTEC",$AX117+$BG117+$BP117+$BY117+$CH117,0) -> 0 | ED117: =IF($CQ117="CLEARTEC",$AY117+$BH117+$BQ117+$BZ117+$CI117,0) -> 0 | EE117: =IF($CQ117="CLEARTEC",$AZ117+$BI117+$BR117+$CA117+$CJ117,0) -> 0 | EF117: =IF($CQ117="CLEARTEC",$BA117+$BJ117+$BS117+$CB117+$CK117,0) -> 0 | EG117: =IF($CQ117="CLEARTEC",$BB117+$BK117+$BT117+$CC117+$CL117,0) -> 0 | EH117: =IF($CQ117="CLEARTEC",$BC117+$BL117+$BU117+$CD117+$CM117,0) -> 0 | EI117: =IF($CQ117="CLEARTEC",$BD117+$BM117+$BV117+$CE117+$CN117,0) -> 0 | EJ117: =SUM(EB117:EI117)-ED117-EF117 -> 0 | EL117: 70.21 | EU117: =+EP117+EQ117+ER117 -> 0 | EW117: =IF($I117<=15,EL117/2,EL117) -> 35.105 | EX117: =IF($I117<=15,EM117/2,EM117) -> 0 | EY117: =IF($I117<=15,EN117/2,EN117) -> 0 | EZ117: =IF($I117<=15,EO117/2,EO117) -> 0 | FA117: =IF($I117<=15,EP117/2,EP117) -> 0 | FB117: =IF($I117<=15,EQ117/2,EQ117) -> 0 | FC117: =IF($I117<=15,ER117/2,ER117) -> 0 | FD117: =IF($I117<=15,ES117/2,ES117) -> 0 | ... FF117: =IF($I117<=15,EU117/2,EU117) -> 0 | FG117: 0 | FH117: 1 | FI117: 0 | FJ117: 0 | FK117: 0 | FL117: 1 | FN117: =(((F117/30/8)*1.5)*(Q117+U117+Y117))-(AZ117+BI117+BR117) -> 0 | FO117: =(((F117/30/8)*2)*(S117+W117+AA117))-(BB117+BK117+BT117) -> 0 | FP117: =(SUM(AW117:CF117))-(SUM(CR117:DR117)) -> 0 | FQ117: =(F117/30*I117)-(CR117+DA117+DJ117) -> 0 | FR117: =(SUM(EL117:EU117))-((SUM(EW117:FF117))*$FR$5) -> 35.105
A118: 201030 | C118: Godinez Ax Sonia Elizabeth | D118: Promovendedora | E118: UNHESA | F118: 4002.28 | G118: 250 | H118: =+F118+G118 -> 4252.28 | I118: 12 | J118: 0 | L118: 1 | M118: 0 | N118: 0 | O118: =SUM(J118:N118) -> 1 | P118: A.4.5.26 | R118: =($F118/30/8*1.5)*Q118 -> 0 | T118: =($F118/30/8*2)*S118 -> 0 | V118: =($F118/30/8*1.5)*U118 -> 0 | X118: =($F118/30/8*2)*W118 -> 0 | Z118: =(($F118/30/8)*1.5)*Y118 -> 0 | AB118: =(($F118/30/8)*2)*AA118 -> 0 | AD118: =(($F118/30/8)*1.5)*AC118 -> 0 | AF118: =(($F118/30/8)*2)*AE118 -> 0 | AH118: =(($F118/30/8)*1.5)*AG118 -> 0 | AJ118: =(($F118/30/8)*2)*AI118 -> 0 | AW118: =((F118/30)*I118)*$J118 -> 0 | AX118: =((G118/30)*I118)*$J118 -> 0 | AY118: =Q118 -> 0 | AZ118: =R118 -> 0 | BA118: =S118 -> 0 | BB118: =T118 -> 0 | BC118: =AK118+AP118 -> 0 | BD118: =(AW118+AZ118+BB118+BC118)*0.1267 -> 0 | BE118: =SUM(AW118:BD118)-AY118-BA118 -> 0 | BF118: =(($F118/30)*$I118)*$K118 -> 0 | BG118: =(($G118/30)*$I118)*$K118 -> 0 | BH118: =U118 -> 0 | BI118: =V118 -> 0 | BJ118: =W118 -> 0 | BK118: =X118 -> 0 | BL118: =AL118+AQ118 -> 0 | BM118: =(+BF118+BI118+BK118+BL118)*0.1267 -> 0 | BN118: =SUM(BF118:BM118)-BH118-BJ118 -> 0 | BO118: =(($F118/30)*$I118)*$L118 -> 1600.912 | BP118: =(($G118/30)*$I118)*$L118 -> 100 | BQ118: =Y118 -> 0 | BR118: =Z118 -> 0 | BS118: =AA118 -> 0 | BT118: =AB118 -> 0 | BU118: =AM118+AR118 -> 0 | BV118: =(BO118+BR118+BT118+BU118)*0.1267 -> 202.83555 | BW118: =SUM(BO118:BV118)-BQ118-BS118 -> 1903.7476 | BX118: =(($F118/30)*$I118)*$M118 -> 0 | BY118: =(($G118/30)*$I118)*$M118 -> 0 | BZ118: =AC118 -> 0 | CA118: =AD118 -> 0 | CB118: =AE118 -> 0 | CC118: =AF118 -> 0 | CD118: =AN118+AS118 -> 0 | CE118: =(BX118+CA118+CC118)*0.1267 -> 0 | CF118: =SUM(BX118:CE118)-BZ118-CB118 -> 0 | CG118: =(($F118/30)*$I118)*N118 -> 0 | CH118: =(($G118/30)*$I118)*$N118 -> 0 | CI118: =+AG118 -> 0 | CJ118: =AH118 -> 0 | CK118: =AI118 -> 0 | CL118: =AJ118 -> 0 | CM118: =AO118+AT118 -> 0 | CN118: =(CG118+CJ118+CL118)*0.1267 -> 0 | CO118: =SUM(CG118:CN118)-CI118-CK118 -> 0 | CQ118: UNHESA LIQUIDOS | CR118: =IF($CQ118="PROQUIMA",$AW118+$BF118+$BO118+$BX118+$CG118,0) -> 0 | CS118: =IF($CQ118="PROQUIMA",$AX118+$BG118+$BP118+$BY118+$CH118,0) -> 0 | CT118: =IF($CQ118="PROQUIMA",$AY118+$BH118+$BQ118+$BZ118+$CI118,0) -> 0 | CU118: =IF($CQ118="PROQUIMA",$AZ118+$BI118+$BR118+$CA118+$CJ118,0) -> 0 | CV118: =IF($CQ118="PROQUIMA",$BA118+$BJ118+$BS118+$CB118+$CK118,0) -> 0 | CW118: =IF($CQ118="PROQUIMA",$BB118+$BK118+$BT118+$CC118+$CL118,0) -> 0 | CX118: =IF($CQ118="PROQUIMA",$BC118+$BL118+$BU118+$CD118+$CM118,0) -> 0 | CY118: =IF($CQ118="PROQUIMA",$BD118+$BM118+$BV118+$CE118+CN118,0) -> 0 | CZ118: =SUM(CR118:CY118)-CT118-CV118 -> 0 | DA118: =IF($CQ118="UNHESA",$AW118+$BF118+$BO118+$BX118+$CG118,0) -> 0 | DB118: =IF($CQ118="UNHESA",$AX118+$BG118+$BP118+$BY118+$CH118,0) -> 0 | DC118: =IF($CQ118="UNHESA",$AY118+$BH118+$BQ118+$BZ118+$CI118,0) -> 0 | DD118: =IF($CQ118="UNHESA",$AZ118+$BI118+$BR118+$CA118+$CJ118,0) -> 0 | DE118: =IF($CQ118="UNHESA",$BA118+$BJ118+$BS118+$CB118+$CK118,0) -> 0 | DF118: =IF($CQ118="UNHESA",$BB118+$BK118+$BT118+$CC118+$CL118,0) -> 0 | DG118: =IF($CQ118="UNHESA",$BC118+$BL118+$BU118+$CD118+$CM118,0) -> 0 | DH118: =IF($CQ118="UNHESA",$BD118+$BM118+$BV118+$CE118+$CN118,0) -> 0 | DI118: =SUM(DA118:DH118)-DC118-DE118 -> 0 | DJ118: =IF($CQ118="UNHESA LIQUIDOS",$AW118+$BF118+$BO118+$BX118+$CG118,0) -> 1600.912 | DK118: =IF($CQ118="UNHESA LIQUIDOS",$AX118+$BG118+$BP118+$BY118+$CH118,0) -> 100 | DL118: =IF($CQ118="UNHESA LIQUIDOS",$AY118+$BH118+$BQ118+$BZ118+$CI118,0) -> 0 | DM118: =IF($CQ118="UNHESA LIQUIDOS",$AZ118+$BI118+$BR118+$CA118+$CJ118,0) -> 0 | DN118: =IF($CQ118="UNHESA LIQUIDOS",$BA118+$BJ118+$BS118+$CB118+$CK118,0) -> 0 | DO118: =IF($CQ118="UNHESA LIQUIDOS",$BB118+$BK118+$BT118+$CC118+$CL118,0) -> 0 | DP118: =IF($CQ118="UNHESA LIQUIDOS",$BC118+$BL118+$BU118+$CD118+$CM118,0) -> 0 | DQ118: =IF($CQ118="UNHESA LIQUIDOS",$BD118+$BM118+$BV118+$CE118+$CN118,0) -> 202.83555 | DR118: =SUM(DJ118:DQ118)-DL118-DN118 -> 1903.7476 | DS118: =IF($CQ118="ECONACIONAL",$AW118+$BF118+$BO118+$BX118+$CG118,0) -> 0 | DT118: =IF($CQ118="ECONACIONAL",$AX118+$BG118+$BP118+$BY118+$CH118,0) -> 0 | DU118: =IF($CQ118="ECONACIONAL",$AY118+$BH118+$BQ118+$BZ118+$CI118,0) -> 0 | DV118: =IF($CQ118="ECONACIONAL",$AZ118+$BI118+$BR118+$CA118+$CJ118,0) -> 0 | DW118: =IF($CQ118="ECONACIONAL",$BA118+$BJ118+$BS118+$CB118+$CK118,0) -> 0 | DX118: =IF($CQ118="ECONACIONAL",$BB118+$BK118+$BT118+$CC118+$CL118,0) -> 0 | DY118: =IF($CQ118="ECONACIONAL",$BC118+$BL118+$BU118+$CD118+$CM118,0) -> 0 | DZ118: =IF($CQ118="ECONACIONAL",$BD118+$BM118+$BV118+$CE118+$CN118,0) -> 0 | EA118: =SUM(DS118:DZ118)-DU118-DW118 -> 0 | EB118: =IF($CQ118="CLEARTEC",$AW118+$BF118+$BO118+$BX118+$CG118,0) -> 0 | EC118: =IF($CQ118="CLEARTEC",$AX118+$BG118+$BP118+$BY118+$CH118,0) -> 0 | ED118: =IF($CQ118="CLEARTEC",$AY118+$BH118+$BQ118+$BZ118+$CI118,0) -> 0 | EE118: =IF($CQ118="CLEARTEC",$AZ118+$BI118+$BR118+$CA118+$CJ118,0) -> 0 | EF118: =IF($CQ118="CLEARTEC",$BA118+$BJ118+$BS118+$CB118+$CK118,0) -> 0 | EG118: =IF($CQ118="CLEARTEC",$BB118+$BK118+$BT118+$CC118+$CL118,0) -> 0 | EH118: =IF($CQ118="CLEARTEC",$BC118+$BL118+$BU118+$CD118+$CM118,0) -> 0 | EI118: =IF($CQ118="CLEARTEC",$BD118+$BM118+$BV118+$CE118+$CN118,0) -> 0 | EJ118: =SUM(EB118:EI118)-ED118-EF118 -> 0 | EU118: =+EP118+EQ118+ER118 -> 0 | EW118: =IF($I118<=15,EL118/2,EL118) -> 0 | EX118: =IF($I118<=15,EM118/2,EM118) -> 0 | EY118: =IF($I118<=15,EN118/2,EN118) -> 0 | EZ118: =IF($I118<=15,EO118/2,EO118) -> 0 | FA118: =IF($I118<=15,EP118/2,EP118) -> 0 | FB118: =IF($I118<=15,EQ118/2,EQ118) -> 0 | FC118: =IF($I118<=15,ER118/2,ER118) -> 0 | FD118: =IF($I118<=15,ES118/2,ES118) -> 0 | ... FF118: =IF($I118<=15,EU118/2,EU118) -> 0 | FG118: 0 | FH118: 1 | FI118: 0 | FJ118: 0 | FK118: 0 | FL118: 1 | FN118: =(((F118/30/8)*1.5)*(Q118+U118+Y118))-(AZ118+BI118+BR118) -> 0 | FO118: =(((F118/30/8)*2)*(S118+W118+AA118))-(BB118+BK118+BT118) -> 0 | FP118: =(SUM(AW118:CF118))-(SUM(CR118:DR118)) -> 0 | FQ118: =(F118/30*I118)-(CR118+DA118+DJ118) -> 0 | FR118: =(SUM(EL118:EU118))-((SUM(EW118:FF118))*$FR$5) -> 0
F119: =SUM(F117:F118) -> 8004.56 | G119: =SUM(G117:G118) -> 750 | H119: =SUM(H117:H118) -> 8754.56 | Q119: =SUM(Q117:Q118) -> 0 | R119: =SUM(R117:R118) -> 0 | S119: =SUM(S117:S118) -> 0 | T119: =SUM(T117:T118) -> 0 | U119: =SUM(U117:U118) -> 0 | V119: =SUM(V117:V118) -> 0 | W119: =SUM(W117:W118) -> 0 | X119: =SUM(X117:X118) -> 0 | ... FF119: =SUM(FF117:FF118) -> 0
C121: Distribucion
C122: Mayoreo
A123: 201050 | C123: 107-Ruta Capital
...

Sheet Nomina Proquima
B1: 1 | C1: 2 | D1: 3 | E1: 4 | F1: 5 | G1: 6 | H1: 7 | I1: 8 | J1: 9 | K1: 10 | L1: 11 | M1: 12 | N1: 13 | O1: 14 | P1: 15 | Q1: 16 | R1: 17 | S1: 18 | T1: 19 | U1: 20 | V1: 21 | W1: 22 | X1: 23 | Y1: 24 | Z1: 25 | AA1: 26
A2: PROQUIMA, S.A.
A3: =+distribucion!C3 -> NOMINA MES DE: MAYO 2026 1ERA QUINCENA
A4: No. | B4: Nombre | C4: Puesto | D4: Salario afecto al IGSS | E4: Dias laborados | F4: REF. | G4: Salario Ordinario | H4: Bonificacion incentivo decreto 37-2001 y 78-89 | I4: Total devengado | J4: Horas Simples | K4: Valor Hora E. Simple | L4: Horas Dobles | M4: Valor Hora E. Doble | N4: otros ingresos | O4: Salario Total | P4: IGSS | Q4: ISR | R4: Cuotas Préstamos Bancos | S4: Celular | T4: UNIFORME | U4: CALZADO | V4: CAFETERIA | W4: Otros egresos | X4: Total Egresos | Y4: Liquido a Recibir | Z4: Primera Quincena | AA4: Segunda Quincena
B7: AREA ADMINISTRATIVA
B8: Gerencia General
A9: =+A8+1 -> 1 | B9: =+distribucion!C13 -> Estrada Robles Victor Gerardo1 | C9: =VLOOKUP(B9,distribucion!C$9:FL$331,2,0) -> Gerente General | D9: =G9+K9+M9 -> 0 | E9: =VLOOKUP(B9,distribucion!C$9:FL$331,7,0) -> 0 | F9: =+distribucion!#REF! -> #REF! | G9: =ROUND((VLOOKUP(B9,distribucion!C$9:EJ$331,94,0)),2) -> 0 | H9: =ROUND((VLOOKUP(B9,distribucion!C$9:EJ$331,95,0)),2) -> 0 | I9: =G9+H9 -> 0 | J9: =VLOOKUP(B9,distribucion!C$9:EJ$331,96,0) -> 0 | K9: =ROUND((VLOOKUP(B9,distribucion!C$9:EJ$331,97,0)),2) -> 0 | L9: =VLOOKUP(B9,distribucion!C$9:EJ$331,98,0) -> 0 | M9: =ROUND((VLOOKUP(B9,distribucion!C$9:EJ$331,99,0)),2) -> 0 | N9: =ROUND((VLOOKUP(B9,distribucion!C$9:EJ$331,100,0)),2) -> 0 | O9: =SUM(I9:N9)-J9-L9 -> 0 | P9: =ROUND(((G9+K9+M9+N9)*0.0483),2) -> 0 | Q9: =ROUND((VLOOKUP(B9,distribucion!C$8:FL$331,151,0)),2) -> 0 | R9: =ROUND((VLOOKUP(B9,distribucion!C$9:FL$331,152,0)),2) -> 0 | S9: =ROUND((VLOOKUP(B9,distribucion!C$9:FL$331,153,0)),2) -> 0 | T9: =ROUND((VLOOKUP(B9,distribucion!$C$4:$FF$336,159,0)),2) -> 0 | U9: =ROUND((VLOOKUP(B9,distribucion!$C$5:$FF$337,158,0)),2) -> 0 | V9: =ROUND((VLOOKUP(B9,distribucion!$C$7:$FF$342,154,0)),2) -> 0 | W9: =ROUND((VLOOKUP(B9,distribucion!C$9:FL$331,160,0)),2) -> 0 | X9: =SUM(P9:W9) -> 0 | Y9: =O9-X9 -> 0 | Z9: =+Y9 -> 0 | AA9: 0 | AD9: =Y9-Z9-AA9 -> 0 | AE9: =((G9+H9+K9+M9+N9)-SUM(P9:W9))-Y9 -> 0
B10: Asesoria | AD10: =Y10-Z10-AA10 -> 0 | AE10: =((G10+H10+K10+M10+N10)-SUM(P10:W10))-Y10 -> 0
A11: 2 | B11: =+distribucion!C16 -> Estrada Robles Juan Pablo | C11: =VLOOKUP(B11,distribucion!C$9:FL$331,2,0) -> Asesor | D11: =G11+K11+M11 -> 2500 | E11: =VLOOKUP(B11,distribucion!C$9:FL$331,7,0) -> 15 | F11: =+distribucion!P16 -> 0 | G11: =ROUND((VLOOKUP(B11,distribucion!C$9:EJ$331,94,0)),2) -> 2500 | H11: =ROUND((VLOOKUP(B11,distribucion!C$9:EJ$331,95,0)),2) -> 5000 | I11: =G11+H11 -> 7500 | J11: =VLOOKUP(B11,distribucion!C$9:EJ$331,96,0) -> 0 | K11: =ROUND((VLOOKUP(B11,distribucion!C$9:EJ$331,97,0)),2) -> 0 | L11: =VLOOKUP(B11,distribucion!C$9:EJ$331,98,0) -> 0 | M11: =ROUND((VLOOKUP(B11,distribucion!C$9:EJ$331,99,0)),2) -> 0 | N11: =ROUND((VLOOKUP(B11,distribucion!C$9:EJ$331,100,0)),2) -> 0 | O11: =SUM(I11:N11)-J11-L11 -> 7500 | P11: =ROUND(((G11+K11+M11+N11)*0.0483),2) -> 120.75 | Q11: =ROUND((VLOOKUP(B11,distribucion!C$8:FL$331,151,0)),2) -> 310.06 | R11: =ROUND((VLOOKUP(B11,distribucion!C$9:FL$331,152,0)),2) -> 0 | S11: =ROUND((VLOOKUP(B11,distribucion!C$9:FL$331,153,0)),2) -> 0 | T11: =ROUND((VLOOKUP(B11,distribucion!$C$4:$FF$336,159,0)),2) -> 0 | U11: =ROUND((VLOOKUP(B11,distribucion!$C$5:$FF$337,158,0)),2) -> 0 | V11: =ROUND((VLOOKUP(B11,distribucion!$C$7:$FF$342,154,0)),2) -> 0 | W11: =ROUND((VLOOKUP(B11,distribucion!C$9:FL$331,160,0)),2) -> 0 | X11: =SUM(P11:W11) -> 430.81 | Y11: =O11-X11 -> 7069.19 | Z11: =+Y11 -> 7069.19 | AA11: 0 | AD11: =Y11-Z11-AA11 -> 0 | AE11: =((G11+H11+K11+M11+N11)-SUM(P11:W11))-Y11 -> 0
B12: Administracion | AB12: =+Z12 -> 0 | AC12: =+AA12-AB12 -> 0 | AD12: =Y12-Z12-AA12 -> 0 | AE12: =((G12+H12+K12+M12+N12)-SUM(P12:W12))-Y12 -> 0
AD15: =Y15-Z15-AA15 -> 0 | AE15: =((G15+H15+K15+M15+N15)-SUM(P15:W15))-Y15 -> 0
B16: =+distribucion!C33 -> Conserjería Presidencia | AD16: =Y16-Z16-AA16 -> 0 | AE16: =((G16+H16+K16+M16+N16)-SUM(P16:W16))-Y16 -> 0
A17: 3 | B17: =+distribucion!C34 -> Cortez Ajcojon Sandra Edith | C17: =VLOOKUP(B17,distribucion!C$9:FL$331,2,0) -> Conserje | D17: =G17+K17+M17 -> 2001.14 | E17: =VLOOKUP(B17,distribucion!C$9:FL$331,7,0) -> 15 | F17: =+distribucion!#REF! -> #REF! | G17: =ROUND((VLOOKUP(B17,distribucion!C$9:EJ$331,94,0)),2) -> 2001.14 | H17: =ROUND((VLOOKUP(B17,distribucion!C$9:EJ$331,95,0)),2) -> 125 | I17: =G17+H17 -> 2126.14 | J17: =VLOOKUP(B17,distribucion!C$9:EJ$331,96,0) -> 0 | K17: =ROUND((VLOOKUP(B17,distribucion!C$9:EJ$331,97,0)),2) -> 0 | L17: =VLOOKUP(B17,distribucion!C$9:EJ$331,98,0) -> 0 | M17: =ROUND((VLOOKUP(B17,distribucion!C$9:EJ$331,99,0)),2) -> 0 | N17: =ROUND((VLOOKUP(B17,distribucion!C$9:EJ$331,100,0)),2) -> 0 | O17: =SUM(I17:N17)-J17-L17 -> 2126.14 | P17: =ROUND(((G17+K17+M17+N17)*0.0483),2) -> 96.66 | Q17: =ROUND((VLOOKUP(B17,distribucion!C$8:FL$331,151,0)),2) -> 1.48 | R17: =ROUND((VLOOKUP(B17,distribucion!C$9:FL$331,152,0)),2) -> 405.48 | S17: =ROUND((VLOOKUP(B17,distribucion!C$9:FL$331,153,0)),2) -> 0 | T17: =ROUND((VLOOKUP(B17,distribucion!$C$4:$FF$336,159,0)),2) -> 0 | U17: =ROUND((VLOOKUP(B17,distribucion!$C$5:$FF$337,158,0)),2) -> 0 | V17: =ROUND((VLOOKUP(B17,distribucion!$C$7:$FF$342,154,0)),2) -> 0 | W17: =ROUND((VLOOKUP(B17,distribucion!C$9:FL$331,160,0)),2) -> 0 | X17: =SUM(P17:W17) -> 503.62 | Y17: =O17-X17 -> 1622.52 | Z17: =+Y17 -> 1622.52 | AA17: 0 | AD17: =Y17-Z17-AA17 -> 0 | AE17: =((G17+H17+K17+M17+N17)-SUM(P17:W17))-Y17 -> 0
