Workbook
Name ECONACIONAL: 'Nomina Econacional'!$A$4:$AB$153
Name Excel_BuiltIn__FilterDatabase: 'boleto de ornato'!#REF!
Name Excel_BuiltIn__FilterDatabase: distribucion!$T$6:$T$153
Name Excel_BuiltIn__FilterDatabase: 'IGSS ECONACIONAL'!$B$5:$AB$6
Name Excel_BuiltIn__FilterDatabase: 'INCREMENTO SALARIO MINIMO '!#REF!
Name Excel_BuiltIn__FilterDatabase: 'RECIBO E IGSS ECONACIONAL'!$B$1:$AB$2

Sheet distribucion
G1: 1 | H1: 2 | I1: 3 | J1: 4 | K1: 5 | L1: 6 | M1: 7 | N1: 8 | O1: 9 | P1: 10 | Q1: 11 | R1: 12 | S1: 13 | T1: 14 | U1: 15 | V1: 16 | W1: 17 | X1: 18 | Y1: 19 | Z1: 20 | AA1: 21 | AB1: 22 | AC1: 23 | AD1: 24 | AE1: 25 | AF1: 26 | AG1: 27 | AH1: 28 | AI1: 29 | AJ1: 30 | AK1: 31 | AL1: 32 | AM1: 33 | AN1: 34 | AO1: 35 | AP1: 36 | AQ1: 37 | AR1: 38 | AS1: 39 | AT1: 40 | AU1: 41 | AV1: 42 | AW1: 43 | AX1: 44 | AY1: 45 | AZ1: 46 | BA1: 47 | BB1: 48 | BC1: 49 | BD1: 50 | BE1: 51 | BF1: 52 | BG1: 53 | BH1: 54 | BI1: 55 | BJ1: 56 | BK1: 57 | BL1: 58 | BM1: 59 | BN1: 60 | BO1: 61 | BP1: 62 | BQ1: 63 | BR1: 64 | BS1: 65 | BT1: 66 | BU1: 67 | BV1: 68 | BW1: 69 | BX1: 70 | BY1: 71 | BZ1: 72 | CA1: 73 | CB1: 74 | CC1: 75 | CD1: 76 | CE1: 77 | CF1: 78 | CG1: 79 | CH1: 80 | CI1: 81 | CJ1: 82 | CK1: 83 | CL1: 84 | CM1: 85 | CN1: 86 | CO1: 87 | CP1: 88 | CQ1: 89 | CR1: 90 | CS1: 91 | CT1: 92 | CU1: 93 | CV1: 94 | CW1: 95 | CX1: 96 | CY1: 97 | CZ1: 98 | DA1: 99 | DB1: 100 | DC1: 101 | DD1: 102 | DE1: 103 | DF1: 104 | DG1: 105 | DH1: 106 | DI1: 107 | DJ1: 108 | DK1: 109 | DL1: 110 | DM1: 111 | DN1: 112 | DO1: 113 | DP1: 114 | DQ1: 115 | DR1: 116 | DS1: 117 | DT1: 118 | DU1: 119 | DV1: 120 | DW1: 121 | DX1: 122 | DY1: 123 | DZ1: 124 | EA1: 125 | EB1: 126 | EC1: 127 | ED1: 128 | EE1: 129 | EF1: 130 | EG1: 131 | EH1: 132 | EI1: 133 | EJ1: 134 | EK1: 135 | EL1: 136 | EM1: 137 | EN1: 138 | EO1: 139 | EP1: 140 | EQ1: 141 | ER1: 142 | ES1: 143 | ET1: 144 | EU1: 145 | EV1: 146 | EW1: 147 | EX1: 148 | EY1: 149 | EZ1: 150 | FA1: 151 | FB1: 152 | FC1: 153 | FD1: 154 | FE1: 155 | FF1: 156 | FG1: 157 | FH1: 158 | FI1: 159 | FJ1: 160
G3: NOMINA ECONACIONAL, S. A. | R3: .
G4: JUNIO 2026 2da QUINCENA | BA4: NOMINAS SEGÚN DISTRIBUCION REAL | CV4: NOMINAS SEGÚN DISTRIBUCION CONTABILIDAD | FV4: QUINCENA: 2 MES: 1
G5: 2026 | J5: 5 | K5: 6 | U5: HORAS EXTRAS PROQUIMA | Y5: HORAS EXTRAS UNHESA | AC5: HORAS EXTRAS HIDROXON | AG5: HORAS EXTRAS CLEARTEC | AK5: HORAS EXTRAS PROQUIMA MAQUILA | AO5: Otros Ingresos | AT5: Comisiones | BA5: PROQUIMA | BJ5: UNHESA | BS5: HIDROXON | CB5: CLEARTEC | CV5: PROQUIMA | DE5: UNHESA | DN5: UNHESA LIQUIDOS | DW5: CLEARTEC | EF5: ECONACIONAL | FK5: DISTRIBUCION REAL | FV5: 2
I6: DISTRIBUCION DE EMPLEADOS | U6: H.E. Simples | V6: H.E. Simples | W6: H.E. Dobles | X6: H.E. Dobles | Y6: H.E. Simples | Z6: H.E. Simples | AA6: H.E. Dobles | AB6: H.E. Dobles | AC6: H.E. Simples | AD6: H.E. Simples | AE6: H.E. Dobles | AF6: H.E. Dobles | AG6: H.E. Simples | AH6: H.E. Simples | AI6: H.E. Dobles | AJ6: H.E. Dobles | AK6: H.E. Simples | AL6: H.E. Simples | AM6: H.E. Dobles | AN6: H.E. Dobles | AO6: Proquima | AP6: Unhesa | AQ6: Calidul | AR6: Econacional | AS6: Cleartec | AT6: Proquima | AU6: Unhesa | AV6: Calidul | AW6: Econacional | AX6: Cleartec | AY6: Otrros ingresos | AZ6: 0 | BA6: Salario | BB6: Bono | BC6: cantidad | BD6: Hrs. Extra | BE6: cantidad | BF6: Hrs. Extra | BG6: Comis / | BH6: Cuota | BI6: Total | BJ6: Salario | BK6: Bono | BL6: cantidad | BM6: Hrs. Extra | BN6: cantidad | BO6: Hrs. Extra | BP6: Comis / | BQ6: Cuota | BR6: Total | BS6: Salario | BT6: Bono | BU6: cantidad | BV6: Hrs. Extra | BW6: cantidad | BX6: Hrs. Extra | BY6: Comis / | BZ6: Cuota | CA6: Total | CB6: Salario | CC6: Bono | CD6: cantidad | CE6: Hrs. Extra | CF6: cantidad | CG6: Hrs. Extra | CH6: Comis / | CI6: Cuota | CJ6: Total | CK6: Salario | CL6: Bono | CM6: cantidad | CN6: Hrs. Extra | CO6: cantidad | CP6: Hrs. Extra | CQ6: Comis / | CR6: Cuota | CS6: Total | CU6: Nueva | CV6: Salario | CW6: Bono | CX6: cantidad | CY6: Hrs. Extra | CZ6: cantidad | DA6: Hrs. Extra | DB6: Comis / | DC6: Cuota | DD6: Total | DE6: Salario | DF6: Bono | DG6: cantidad | DH6: Hrs. Extra | DI6: cantidad | DJ6: Hrs. Extra | DK6: Comis / | DL6: Cuota | DM6: Total | DN6: Salario | DO6: Bono | DP6: cantidad | DQ6: Hrs. Extra | DR6: cantidad | DS6: Hrs. Extra | DT6: Comis / | DU6: Cuota | DV6: Total | DW6: Salario | DX6: Bono | DY6: cantidad | DZ6: Hrs. Extra | EA6: cantidad | EB6: Hrs. Extra | EC6: Comis / | ED6: Cuota | EE6: Total | EF6: Salario | EG6: Bono | EH6: cantidad | EI6: Hrs. Extra | EJ6: cantidad | EK6: Hrs. Extra | EL6: Comis / | EM6: Cuota | EN6: Total | EP6: EGRESOS MENSUALES | FA6: EGRESOS | FK6: % | FL6: % | FM6: % | FN6: % | FO6: % | FP6: %
A7: MES | B7: AÑO | C7: MES/AÑO | D7: CC | E7: Código División | G7: Nombre | H7: Puesto | I7: Empresa Real | J7: Salario Ordinario | K7: Bono Decreto | L7: Total | M7: Días Laborados | N7: % Proquima | O7: % Unhesa | P7: HIDROXON | Q7: % Cleartec | S7: Total % Distribución | T7: Observaciones | U7: Cantidad | V7: Valor | W7: Cantidad | X7: Valor | Y7: Cantidad | Z7: Valor | AA7: Cantidad | AB7: Valor | AC7: Cantidad | AD7: Valor | AE7: Cantidad | AF7: Valor | AG7: Cantidad | AH7: Valor | AI7: Cantidad | AJ7: Valor | AK7: Cantidad | AL7: Valor | AM7: Cantidad | AN7: Valor | BA7: Ordinario | BB7: Decreto | BC7: simples | BD7: simples | BE7: dobles | BF7: dobles | BG7: Otros | BH7: Patronal | BJ7: Ordinario | BK7: Decreto | BL7: simples | BM7: simples | BN7: dobles | BO7: dobles | BP7: Otros | BQ7: Patronal | BS7: Ordinario | BT7: Decreto | BU7: simples | BV7: simples | BW7: dobles | BX7: dobles | BY7: Otros | BZ7: Patronal | CB7: Ordinario | CC7: Decreto | CD7: simples | CE7: simples | CF7: dobles | CG7: dobles | CH7: Otros | CI7: Patronal | CK7: Ordinario | CL7: Decreto | CM7: simples | CN7: simples | CO7: dobles | CP7: dobles | CQ7: Otros | CR7: Patronal | CU7: Empresa | CV7: Ordinario | CW7: Decreto | CX7: simples | CY7: simples | CZ7: dobles | DA7: dobles | DB7: Otros | DC7: Patronal | DE7: Ordinario | DF7: Decreto | DG7: simples | DH7: simples | DI7: dobles | DJ7: dobles | DK7: Otros | DL7: Patronal | DN7: Ordinario | DO7: Decreto | DP7: simples | DQ7: simples | DR7: dobles | DS7: dobles | DT7: Otros | DU7: Patronal | DW7: Ordinario | DX7: Decreto | DY7: simples | DZ7: simples | EA7: dobles | EB7: dobles | EC7: Otros | ED7: Patronal | EF7: Ordinario | EG7: Decreto | EH7: simples | EI7: simples | EJ7: dobles | EK7: dobles | EL7: Otros | EM7: Patronal | EP7: ISR | EQ7: BANCOS | ER7: CELULAR | ES7: CAFETERIA | ET7: DESCUENTO producto | EU7: SEGURO/ tarjeta de salud/boleto de ornato | EV7: Otros Descuentos | EW7: CALZADO | EX7: UNIFORME | EY7: TOTAL EGRESOS Bol Ornato, Seguro, Otros | FA7: ISR | FB7: BANCOS | FC7: CELULAR | FD7: CAFETERIA | FE7: DESCUENTO PRODUCTO | FF7: SEGURO | FG7: Otros Descuentos | FH7: CALZADO | FI7: UNIFORME | FJ7: OTROS EGRESOS | FK7: % Proquima | FL7: % Unhesa | FM7: % Unhesa Liq. | FN7: % Econacional | FO7: % Ecomezclas | FP7: Total % Distribución
A8: =+$G$4 -> JUNIO 2026 2da QUINCENA | B8: =+$G$5 -> 2026 | C8: =A8 & B8 -> JUNIO 2026 2da QUINCENA2026 | D8: =+$G$8 -> ADMINISTRATIVO | E8: 102010 | G8: ADMINISTRATIVO
E9: 102010 | F9: 1 | G9: Hernandez Maria Andrea | H9: Asistente de Gerencia General | I9: ECONACIONAL | J9: 5000 | K9: 1000 | L9: =+J9+K9 -> 6000 | M9: 30 | N9: 0.5 | O9: 0.4 | P9: 0.1 | Q9: 0 | R9: 0 | S9: =SUM(N9:R9) -> 1 | V9: =($J9/30/8*1.5)*U9 -> 0 | X9: =($J9/30/8*2)*W9 -> 0 | Z9: =($J9/30/8*1.5)*Y9 -> 0 | AB9: =($J9/30/8*2)*AA9 -> 0 | AD9: =(($J9/30/8)*1.5)*AC9 -> 0 | AF9: =(($J9/30/8)*2)*AE9 -> 0 | AH9: =(($J9/30/8)*1.5)*AG9 -> 0 | AI9: 0 | AJ9: =(($J9/30/8)*2)*AI9 -> 0 | AL9: =(($J9/30/8)*1.5)*AK9 -> 0 | AN9: =(($J9/30/8)*2)*AM9 -> 0 | BA9: =(($J9/30)*$M9)*$N9 -> 2500 | BB9: =((K9/30)*M9)*$N9 -> 500 | BC9: =U9 -> 0 | BD9: =V9 -> 0 | BE9: =W9 -> 0 | BF9: =X9 -> 0 | BG9: =AO9+AT9 -> 0 | BH9: =(BA9+BD9+BF9+BG9)*0.1267 -> 316.75 | BI9: =SUM(BA9:BH9)-BC9-BE9 -> 3316.75 | BJ9: =(($J9/30)*$M9)*$O9 -> 2000 | BK9: =(($K9/30)*$M9)*$O9 -> 400 | BL9: =Y9 -> 0 | BM9: =Z9 -> 0 | BN9: =AA9 -> 0 | BO9: =AB9 -> 0 | BP9: =AP9+AU9 -> 0 | BQ9: =(+BJ9+BM9+BO9+BP9)*0.1267 -> 253.4 | BR9: =SUM(BJ9:BQ9)-BL9-BN9 -> 2653.4 | BS9: =(($J9/30)*$M9)*$P9 -> 500 | BT9: =(($K9/30)*$M9)*$P9 -> 100 | BU9: =AC9 -> 0 | BV9: =AD9 -> 0 | BW9: =AE9 -> 0 | BX9: =AF9 -> 0 | BY9: =AQ9+AV9 -> 0 | BZ9: =(BS9+BV9+BX9+BY9)*0.1267 -> 63.35 | CA9: =SUM(BS9:BZ9)-BU9-BW9 -> 663.35 | CB9: =(($J9/30)*$M9)*$Q9 -> 0 | CC9: =(($K9/30)*$M9)*$Q9 -> 0 | CD9: =AG9 -> 0 | CE9: =AH9 -> 0 | CF9: =AI9 -> 0 | CG9: =AJ9 -> 0 | CH9: =AR9+AW9 -> 0 | CI9: =(CB9+CE9+CG9+CH9)*0.1267 -> 0 | CJ9: =SUM(CB9:CI9)-CD9-CF9 -> 0 | CK9: =(($J9/30)*$M9)*R9 -> 0 | CL9: =(($K9/30)*$M9)*$R9 -> 0 | CM9: =+AK9 -> 0 | CN9: =AL9 -> 0 | CO9: =AM9 -> 0 | CP9: =AN9 -> 0 | CQ9: =AS9+AX9 -> 0 | CR9: =(CK9+CN9+CP9)*0.1267 -> 0 | CS9: =SUM(CK9:CR9)-CM9-CO9 -> 0 | CU9: ECONACIONAL | CV9: =IF($CU9="PROQUIMA",$BA9+$BJ9+$BS9+$CB9+$CK9,0) -> 0 | CW9: =IF($CU9="PROQUIMA",$BB9+$BK9+$BT9+$CC9+$CL9,0) -> 0 | CX9: =IF($CU9="PROQUIMA",$BC9+$BL9+$BU9+$CD9+$CM9,0) -> 0 | CY9: =IF($CU9="PROQUIMA",$BD9+$BM9+$BV9+$CE9+$CN9,0) -> 0 | CZ9: =IF($CU9="PROQUIMA",$BE9+$BN9+$BW9+$CF9+$CO9,0) -> 0 | DA9: =IF($CU9="PROQUIMA",$BF9+$BO9+$BX9+$CG9+$CP9,0) -> 0 | DB9: =IF($CU9="PROQUIMA",$BG9+$BP9+$BY9+$CH9+$CQ9,0) -> 0 | DC9: =IF($CU9="PROQUIMA",$BH9+$BQ9+$BZ9+$CI9+CR9,0) -> 0 | DD9: =SUM(CV9:DC9)-CX9-CZ9 -> 0 | DE9: =IF($CU9="UNHESA",$BA9+$BJ9+$BS9+$CB9+$CK9,0) -> 0 | DF9: =IF($CU9="UNHESA",$BB9+$BK9+$BT9+$CC9+$CL9,0) -> 0 | DG9: =IF($CU9="UNHESA",$BC9+$BL9+$BU9+$CD9+$CM9,0) -> 0 | DH9: =IF($CU9="UNHESA",$BD9+$BM9+$BV9+$CE9+$CN9,0) -> 0 | DI9: =IF($CU9="UNHESA",$BE9+$BN9+$BW9+$CF9+$CO9,0) -> 0 | DJ9: =IF($CU9="UNHESA",$BF9+$BO9+$BX9+$CG9+$CP9,0) -> 0 | DK9: =IF($CU9="UNHESA",$BG9+$BP9+$BY9+$CH9+$CQ9,0) -> 0 | DL9: =IF($CU9="UNHESA",$BH9+$BQ9+$BZ9+$CI9+$CR9,0) -> 0 | DM9: =SUM(DE9:DL9)-DG9-DI9 -> 0 | DN9: =SUM(DF9:DM9)-DH9-DJ9 -> 0 | DO9: =SUM(DG9:DN9)-DI9-DK9 -> 0 | DP9: =SUM(DH9:DO9)-DJ9-DL9 -> 0 | DQ9: =SUM(DI9:DP9)-DK9-DM9 -> 0 | DR9: =SUM(DJ9:DQ9)-DL9-DN9 -> 0 | DS9: =SUM(DK9:DR9)-DM9-DO9 -> 0 | DT9: =SUM(DL9:DS9)-DN9-DP9 -> 0 | ... DV9: =SUM(DN9:DU9)-DP9-DR9 -> 0 | DW9: =IF($CU9="CLEARTEC",$BA9+$BJ9+$BS9+$CB9+$CK9,0) -> 0 | DX9: =IF($CU9="CLEARTEC",$BA9+$BJ9+$BS9+$CB9+$CK9,0) -> 0 | DY9: =IF($CU9="CLEARTEC",$BA9+$BJ9+$BS9+$CB9+$CK9,0) -> 0 | DZ9: =IF($CU9="CLEARTEC",$BA9+$BJ9+$BS9+$CB9+$CK9,0) -> 0 | EA9: =IF($CU9="CLEARTEC",$BA9+$BJ9+$BS9+$CB9+$CK9,0) -> 0 | EB9: =IF($CU9="CLEARTEC",$BA9+$BJ9+$BS9+$CB9+$CK9,0) -> 0 | EC9: =IF($CU9="CLEARTEC",$BA9+$BJ9+$BS9+$CB9+$CK9,0) -> 0 | ED9: =IF($CU9="CLEARTEC",$BA9+$BJ9+$BS9+$CB9+$CK9,0) -> 0 | EE9: =IF($CU9="CLEARTEC",$BA9+$BJ9+$BS9+$CB9+$CK9,0) -> 0 | EF9: =IF(CU9="ECONACIONAL",$BA9+$BJ9+$BS9+$CB9+$CK9) -> 5000 | EG9: =IF($CU9="ECONACIONAL",$BB9+$BK9+$BT9+$CC9+$CL9,0) -> 1000 | EH9: =IF(CU9="ECONACIONAL",$BC9+$BL9+$BU9+$CD9+$CM9) -> 0 | EI9: =IF(CU9="ECONACIONAL",$BD9+$DH9+$DQ9+$DZ9+BM9+BV9+CE9+CN9) -> 0 | EJ9: =IF($CU9="CLEARTEC",$BE9+$BN9+$BW9+$CF9+$CO9,0) -> 0 | EK9: =IF(CU9="ECONACIONAL",$BF9+$BO9+$BX9+$CG9+$CP9) -> 0 | EL9: =IF(CU9="ECONACIONAL",$BG9+$BP9+$BY9+$CH9+$CQ9) -> 0 | EM9: =IF(CU9="ECONACIONAL",BH9+BQ9+BZ9+CI9+CR9) -> 633.5 | EN9: =SUM(EF9:EM9)-EH9-EJ9 -> 6633.5 | EP9: 87.92 | ES9: =165+60 -> 225 | EV9: 350 | EY9: =+ET9+EU9+EV9 -> 350 | FA9: =IF($M9<=15,EP9/2,EP9) -> 87.92 | FB9: =IF($M9<=15,EQ9/2,EQ9) -> 0 | FC9: =IF($M9<=15,ER9/2,ER9) -> 0 | FD9: =IF($M9<=15,ES9/2,ES9) -> 225 | FE9: =IF($M9<=15,ET9/2,ET9) -> 0 | FF9: =IF($M9<=15,EU9/2,EU9) -> 0 | FG9: =IF($M9<=15,EV9/2,EV9) -> 350 | FH9: =IF($M9<=15,EW9/2,EW9) -> 0 | ... FJ9: =IF($M9<=15,EY9/2,EY9) -> 350 | FR9: =(((J9/30/8)*1.5)*(U9+Y9+AC9))-(BD9+BM9+BV9) -> 0 | FS9: =(((J9/30/8)*2)*(W9+AA9+AE9))-(BF9+BO9+BX9) -> 0 | FT9: =(SUM(BA9:CJ9))-(SUM(EF9:EN9)) -> 0 | FU9: =(J9/30*M9)-(EF9) -> 0 | FV9: =(SUM(EP9:EY9))-((SUM(FA9:FJ9))*$FV$5) -> -1012.92
A10: =$G$4 -> JUNIO 2026 2da QUINCENA | B10: =+$G$5 -> 2026 | C10: =A10 & B10 -> JUNIO 2026 2da QUINCENA2026 | D10: =+$G$8 -> ADMINISTRATIVO | E10: 102050 | F10: 2 | G10: Pu Canto Domingo | H10: Conserje | I10: ECONACIONAL | J10: 4002.28 | K10: 250 | L10: =+J10+K10 -> 4252.28 | M10: 30 | N10: 0.5 | O10: 0.5 | P10: 0 | Q10: 0 | R10: 0 | S10: =SUM(N10:R10) -> 1 | V10: =($J10/30/8*1.5)*U10 -> 0 | X10: =($J10/30/8*2)*W10 -> 0 | Z10: =($J10/30/8*1.5)*Y10 -> 0 | AB10: =($J10/30/8*2)*AA10 -> 0 | AD10: =(($J10/30/8)*1.5)*AC10 -> 0 | AF10: =(($J10/30/8)*2)*AE10 -> 0 | AH10: =(($J10/30/8)*1.5)*AG10 -> 0 | AJ10: =(($J10/30/8)*2)*AI10 -> 0 | AL10: =(($J10/30/8)*1.5)*AK10 -> 0 | AN10: =(($J10/30/8)*2)*AM10 -> 0 | BA10: =((J10/30)*M10)*$N10 -> 2001.14 | BB10: =((K10/30)*M10)*$N10 -> 125 | BC10: =U10 -> 0 | BD10: =V10 -> 0 | BE10: =W10 -> 0 | BF10: =X10 -> 0 | BG10: =AO10+AT10 -> 0 | BH10: =(BA10+BD10+BF10+BG10)*0.1267 -> 253.54444 | BI10: =SUM(BA10:BH10)-BC10-BE10 -> 2379.6844 | BJ10: =(($J10/30)*$M10)*$O10 -> 2001.14 | BK10: =(($K10/30)*$M10)*$O10 -> 125 | BL10: =Y10 -> 0 | BM10: =Z10 -> 0 | BN10: =AA10 -> 0 | BO10: =AB10 -> 0 | BP10: =AP10+AU10 -> 0 | BQ10: =(+BJ10+BM10+BO10+BP10)*0.1267 -> 253.54444 | BR10: =SUM(BJ10:BQ10)-BL10-BN10 -> 2379.6844 | BS10: =(($J10/30)*$M10)*$P10 -> 0 | BT10: =(($K10/30)*$M10)*$P10 -> 0 | BU10: =AC10 -> 0 | BV10: =AD10 -> 0 | BW10: =AE10 -> 0 | BX10: =AF10 -> 0 | BY10: =AQ10+AV10 -> 0 | BZ10: =(BS10+BV10+BX10)*0.09 -> 0 | CA10: =SUM(BS10:BZ10)-BU10-BW10 -> 0 | CB10: =(($J10/30)*$M10)*$Q10 -> 0 | CC10: =(($K10/30)*$M10)*$Q10 -> 0 | CD10: =AG10 -> 0 | CE10: =AH10 -> 0 | CF10: =AI10 -> 0 | CG10: =AJ10 -> 0 | CH10: =AR10+AW10 -> 0 | CI10: =(CB10+CE10+CG10)*0.09 -> 0 | CJ10: =SUM(CB10:CI10)-CD10-CF10 -> 0 | CK10: =(($J10/30)*$M10)*R10 -> 0 | CL10: =(($K10/30)*$M10)*$R10 -> 0 | CM10: =+AK10 -> 0 | CN10: =AL10 -> 0 | CO10: =AM10 -> 0 | CP10: =AN10 -> 0 | CQ10: =AS10+AX10 -> 0 | CR10: =(CK10+CN10+CP10)*0.09 -> 0 | CS10: =SUM(CK10:CR10)-CM10-CO10 -> 0 | CU10: ECONACIONAL | CV10: =IF($CU10="PROQUIMA",$BA10+$BJ10+$BS10+$CB10+$CK10,0) -> 0 | CW10: =IF($CU10="PROQUIMA",$BB10+$BK10+$BT10+$CC10+$CL10,0) -> 0 | CX10: =IF($CU10="PROQUIMA",$BC10+$BL10+$BU10+$CD10+$CM10,0) -> 0 | CY10: =IF($CU10="PROQUIMA",$BD10+$BM10+$BV10+$CE10+$CN10,0) -> 0 | CZ10: =IF($CU10="PROQUIMA",$BE10+$BN10+$BW10+$CF10+$CO10,0) -> 0 | DA10: =IF($CU10="PROQUIMA",$BF10+$BO10+$BX10+$CG10+$CP10,0) -> 0 | DB10: =IF($CU10="PROQUIMA",$BG10+$BP10+$BY10+$CH10+$CQ10,0) -> 0 | DC10: =IF($CU10="PROQUIMA",$BH10+$BQ10+$BZ10+$CI10+CR10,0) -> 0 | DD10: =SUM(CV10:DC10)-CX10-CZ10 -> 0 | DE10: =IF($CU10="UNHESA",$BA10+$BJ10+$BS10+$CB10+$CK10,0) -> 0 | DF10: =IF($CU10="UNHESA",$BB10+$BK10+$BT10+$CC10+$CL10,0) -> 0 | DG10: =IF($CU10="UNHESA",$BC10+$BL10+$BU10+$CD10+$CM10,0) -> 0 | DH10: =IF($CU10="UNHESA",$BD10+$BM10+$BV10+$CE10+$CN10,0) -> 0 | DI10: =IF($CU10="UNHESA",$BE10+$BN10+$BW10+$CF10+$CO10,0) -> 0 | DJ10: =IF($CU10="UNHESA",$BF10+$BO10+$BX10+$CG10+$CP10,0) -> 0 | DK10: =IF($CU10="UNHESA",$BG10+$BP10+$BY10+$CH10+$CQ10,0) -> 0 | DL10: =IF($CU10="UNHESA",$BH10+$BQ10+$BZ10+$CI10+$CR10,0) -> 0 | DM10: =SUM(DE10:DL10)-DG10-DI10 -> 0 | DN10: =IF($CU10="UNHESA LIQUIDOS",$BA10+$BJ10+$BS10+$CB10+$CK10,0) -> 0 | DO10: =IF($CU10="CALIDUL",$BB10+$BK10+$BT10+$CC10+$CL10,0) -> 0 | DP10: =IF($CU10="CALIDUL",$BC10+$BL10+$BU10+$CD10+$CM10,0) -> 0 | DQ10: =IF($CU10="CALIDUL",$BD10+$BM10+$BV10+$CE10+$CN10,0) -> 0 | DR10: =IF($CU10="CALIDUL",$BE10+$BN10+$BW10+$CF10+$CO10,0) -> 0 | DS10: =IF($CU10="CALIDUL",$BF10+$BO10+$BX10+$CG10+$CP10,0) -> 0 | DT10: =IF($CU10="CALIDUL",$BG10+$BP10+$BY10+$CH10+$CQ10,0) -> 0 | DU10: =IF($CU10="CALIDUL",$BH10+$BQ10+$BZ10+$CI10+$CR10,0) -> 0 | DV10: =SUM(DN10:DU10)-DP10-DR10 -> 0 | DW10: =IF($CU10="CLEARTEC",$BA10+$BJ10+$BS10+$CB10+$CK10,0) -> 0 | DX10: =IF($CU10="CLEARTEC",$BA10+$BJ10+$BS10+$CB10+$CK10,0) -> 0 | DY10: =IF($CU10="CLEARTEC",$BA10+$BJ10+$BS10+$CB10+$CK10,0) -> 0 | DZ10: =IF($CU10="CLEARTEC",$BA10+$BJ10+$BS10+$CB10+$CK10,0) -> 0 | EA10: =IF($CU10="CLEARTEC",$BA10+$BJ10+$BS10+$CB10+$CK10,0) -> 0 | EB10: =IF($CU10="CLEARTEC",$BA10+$BJ10+$BS10+$CB10+$CK10,0) -> 0 | EC10: =IF($CU10="CLEARTEC",$BA10+$BJ10+$BS10+$CB10+$CK10,0) -> 0 | ED10: =IF($CU10="CLEARTEC",$BA10+$BJ10+$BS10+$CB10+$CK10,0) -> 0 | EE10: =IF($CU10="CLEARTEC",$BA10+$BJ10+$BS10+$CB10+$CK10,0) -> 0 | EF10: =IF(CU10="ECONACIONAL",$BA10+$BJ10+$BS10+$CB10+$CK10) -> 4002.28 | EG10: =IF($CU10="ECONACIONAL",$BB10+$BK10+$BT10+$CC10+$CL10,0) -> 250 | EH10: =IF(CU10="ECONACIONAL",$BC10+$BL10+$BU10+$CD10+$CM10) -> 0 | EI10: =IF(CU10="ECONACIONAL",$BD10+$DH10+$DQ10+$DZ10+BM10+BV10+CE10+CN10) -> 0 | EJ10: =IF($CU10="CLEARTEC",$BE10+$BN10+$BW10+$CF10+$CO10,0) -> 0 | EK10: =IF(CU10="ECONACIONAL",$BF10+$BO10+$BX10+$CG10+$CP10) -> 0 | EL10: =IF(CU10="ECONACIONAL",$BG10+$BP10+$BY10+$CH10+$CQ10) -> 0 | EM10: =IF(CU10="ECONACIONAL",BH10+BQ10+BZ10+CI10+CR10) -> 507.08888 | EN10: =SUM(EF10:EM10)-EH10-EJ10 -> 4759.3689 | EY10: =+ET10+EU10+EV10 -> 0 | FA10: =IF($M10<=15,EP10/2,EP10) -> 0 | FB10: =IF($M10<=15,EQ10/2,EQ10) -> 0 | FC10: =IF($M10<=15,ER10/2,ER10) -> 0 | FD10: =IF($M10<=15,ES10/2,ES10) -> 0 | FE10: =IF($M10<=15,ET10/2,ET10) -> 0 | FF10: =IF($M10<=15,EU10/2,EU10) -> 0 | FG10: =IF($M10<=15,EV10/2,EV10) -> 0 | FH10: =IF($M10<=15,EW10/2,EW10) -> 0 | ... FJ10: =IF($M10<=15,EY10/2,EY10) -> 0 | FK10: 0.5 | FL10: 0.5 | FM10: 0 | FN10: 0 | FO10: 0 | FP10: 1 | FR10: =(((J10/30/8)*1.5)*(U10+Y10+AC10))-(BD10+BM10+BV10) -> 0 | FS10: =(((J10/30/8)*2)*(W10+AA10+AE10))-(BF10+BO10+BX10) -> 0 | FT10: =(SUM(BA10:CJ10))-(SUM(EF10:EN10)) -> 0 | FU10: =(J10/30*M10)-(EF10) -> 0 | FV10: =(SUM(EP10:EY10))-((SUM(FA10:FJ10))*$FV$5) -> 0
E11: 102050 | G11: Choc Abrego Enma Leticia | H11: Conserje | I11: ECONACIONAL | J11: 4002.28 | K11: 250 | L11: =+J11+K11 -> 4252.28 | M11: 30 | N11: 0.5 | O11: 0.4 | P11: 0.1 | Q11: 0 | R11: 0 | S11: =SUM(N11:R11) -> 1 | T11: A.23/3 | V11: =($J11/30/8*1.5)*U11 -> 0 | X11: =($J11/30/8*2)*W11 -> 0 | Z11: =($J11/30/8*1.5)*Y11 -> 0 | AB11: =($J11/30/8*2)*AA11 -> 0 | AD11: =(($J11/30/8)*1.5)*AC11 -> 0 | AF11: =(($J11/30/8)*2)*AE11 -> 0 | AH11: =(($J11/30/8)*1.5)*AG11 -> 0 | AJ11: =(($J11/30/8)*2)*AI11 -> 0 | AL11: =(($J11/30/8)*1.5)*AK11 -> 0 | AN11: =(($J11/30/8)*2)*AM11 -> 0 | BA11: =((J11/30)*M11)*$N11 -> 2001.14 | BB11: =((K11/30)*M11)*$N11 -> 125 | BC11: =U11 -> 0 | BD11: =V11 -> 0 | BE11: =W11 -> 0 | BF11: =X11 -> 0 | BG11: =AO11+AT11 -> 0 | BH11: =(BA11+BD11+BF11+BG11)*0.1267 -> 253.54444 | BI11: =SUM(BA11:BH11)-BC11-BE11 -> 2379.6844 | BJ11: =(($J11/30)*$M11)*$O11 -> 1600.912 | BK11: =(($K11/30)*$M11)*$O11 -> 100 | BL11: =Y11 -> 0 | BM11: =Z11 -> 0 | BN11: =AA11 -> 0 | BO11: =AB11 -> 0 | BP11: =AP11+AU11 -> 0 | BQ11: =(+BJ11+BM11+BO11+BP11)*0.1267 -> 202.83555 | BR11: =SUM(BJ11:BQ11)-BL11-BN11 -> 1903.7476 | BS11: =(($J11/30)*$M11)*$P11 -> 400.228 | BT11: =(($K11/30)*$M11)*$P11 -> 25 | BU11: =AC11 -> 0 | BV11: =AD11 -> 0 | BW11: =AE11 -> 0 | BX11: =AF11 -> 0 | BY11: =AQ11+AV11 -> 0 | BZ11: =(BS11+BV11+BX11)*0.09 -> 36.02052 | CA11: =SUM(BS11:BZ11)-BU11-BW11 -> 461.24852 | CB11: =(($J11/30)*$M11)*$Q11 -> 0 | CC11: =(($K11/30)*$M11)*$Q11 -> 0 | CD11: =AG11 -> 0 | CE11: =AH11 -> 0 | CF11: =AI11 -> 0 | CG11: =AJ11 -> 0 | CH11: =AR11+AW11 -> 0 | CI11: =(CB11+CE11+CG11)*0.09 -> 0 | CJ11: =SUM(CB11:CI11)-CD11-CF11 -> 0 | CK11: =(($J11/30)*$M11)*R11 -> 0 | CL11: =(($K11/30)*$M11)*$R11 -> 0 | CM11: =+AK11 -> 0 | CN11: =AL11 -> 0 | CO11: =AM11 -> 0 | CP11: =AN11 -> 0 | CQ11: =AS11+AX11 -> 0 | CR11: =(CK11+CN11+CP11)*0.09 -> 0 | CS11: =SUM(CK11:CR11)-CM11-CO11 -> 0 | CU11: ECONACIONAL | CV11: =IF($CU11="PROQUIMA",$BA11+$BJ11+$BS11+$CB11+$CK11,0) -> 0 | CW11: =IF($CU11="PROQUIMA",$BB11+$BK11+$BT11+$CC11+$CL11,0) -> 0 | CX11: =IF($CU11="PROQUIMA",$BC11+$BL11+$BU11+$CD11+$CM11,0) -> 0 | CY11: =IF($CU11="PROQUIMA",$BD11+$BM11+$BV11+$CE11+$CN11,0) -> 0 | CZ11: =IF($CU11="PROQUIMA",$BE11+$BN11+$BW11+$CF11+$CO11,0) -> 0 | DA11: =IF($CU11="PROQUIMA",$BF11+$BO11+$BX11+$CG11+$CP11,0) -> 0 | DB11: =IF($CU11="PROQUIMA",$BG11+$BP11+$BY11+$CH11+$CQ11,0) -> 0 | DC11: =IF($CU11="PROQUIMA",$BH11+$BQ11+$BZ11+$CI11+CR11,0) -> 0 | DD11: =SUM(CV11:DC11)-CX11-CZ11 -> 0 | DE11: =IF($CU11="UNHESA",$BA11+$BJ11+$BS11+$CB11+$CK11,0) -> 0 | DF11: =IF($CU11="UNHESA",$BB11+$BK11+$BT11+$CC11+$CL11,0) -> 0 | DG11: =IF($CU11="UNHESA",$BC11+$BL11+$BU11+$CD11+$CM11,0) -> 0 | DH11: =IF($CU11="UNHESA",$BD11+$BM11+$BV11+$CE11+$CN11,0) -> 0 | DI11: =IF($CU11="UNHESA",$BE11+$BN11+$BW11+$CF11+$CO11,0) -> 0 | DJ11: =IF($CU11="UNHESA",$BF11+$BO11+$BX11+$CG11+$CP11,0) -> 0 | DK11: =IF($CU11="UNHESA",$BG11+$BP11+$BY11+$CH11+$CQ11,0) -> 0 | DL11: =IF($CU11="UNHESA",$BH11+$BQ11+$BZ11+$CI11+$CR11,0) -> 0 | DM11: =SUM(DE11:DL11)-DG11-DI11 -> 0 | DN11: =IF($CU11="UNHESA LIQUIDOS",$BA11+$BJ11+$BS11+$CB11+$CK11,0) -> 0 | DO11: =IF($CU11="CALIDUL",$BB11+$BK11+$BT11+$CC11+$CL11,0) -> 0 | DP11: =IF($CU11="CALIDUL",$BC11+$BL11+$BU11+$CD11+$CM11,0) -> 0 | DQ11: =IF($CU11="CALIDUL",$BD11+$BM11+$BV11+$CE11+$CN11,0) -> 0 | DR11: =IF($CU11="CALIDUL",$BE11+$BN11+$BW11+$CF11+$CO11,0) -> 0 | DS11: =IF($CU11="CALIDUL",$BF11+$BO11+$BX11+$CG11+$CP11,0) -> 0 | DT11: =IF($CU11="CALIDUL",$BG11+$BP11+$BY11+$CH11+$CQ11,0) -> 0 | DU11: =IF($CU11="CALIDUL",$BH11+$BQ11+$BZ11+$CI11+$CR11,0) -> 0 | DV11: =SUM(DN11:DU11)-DP11-DR11 -> 0 | DW11: =IF($CU11="CLEARTEC",$BA11+$BJ11+$BS11+$CB11+$CK11,0) -> 0 | DX11: =IF($CU11="CLEARTEC",$BA11+$BJ11+$BS11+$CB11+$CK11,0) -> 0 | DY11: =IF($CU11="CLEARTEC",$BA11+$BJ11+$BS11+$CB11+$CK11,0) -> 0 | DZ11: =IF($CU11="CLEARTEC",$BA11+$BJ11+$BS11+$CB11+$CK11,0) -> 0 | EA11: =IF($CU11="CLEARTEC",$BA11+$BJ11+$BS11+$CB11+$CK11,0) -> 0 | EB11: =IF($CU11="CLEARTEC",$BA11+$BJ11+$BS11+$CB11+$CK11,0) -> 0 | EC11: =IF($CU11="CLEARTEC",$BA11+$BJ11+$BS11+$CB11+$CK11,0) -> 0 | ED11: =IF($CU11="CLEARTEC",$BA11+$BJ11+$BS11+$CB11+$CK11,0) -> 0 | EE11: =IF($CU11="CLEARTEC",$BA11+$BJ11+$BS11+$CB11+$CK11,0) -> 0 | EF11: =IF(CU11="ECONACIONAL",$BA11+$BJ11+$BS11+$CB11+$CK11) -> 4002.28 | EG11: =IF($CU11="ECONACIONAL",$BB11+$BK11+$BT11+$CC11+$CL11,0) -> 250 | EH11: =IF(CU11="ECONACIONAL",$BC11+$BL11+$BU11+$CD11+$CM11) -> 0 | EI11: =IF(CU11="ECONACIONAL",$BD11+$DH11+$DQ11+$DZ11+BM11+BV11+CE11+CN11) -> 0 | EJ11: =IF($CU11="CLEARTEC",$BE11+$BN11+$BW11+$CF11+$CO11,0) -> 0 | EK11: =IF(CU11="ECONACIONAL",$BF11+$BO11+$BX11+$CG11+$CP11) -> 0 | EL11: =IF(CU11="ECONACIONAL",$BG11+$BP11+$BY11+$CH11+$CQ11) -> 0 | EM11: =IF(CU11="ECONACIONAL",BH11+BQ11+BZ11+CI11+CR11) -> 492.40051 | EN11: =SUM(EF11:EM11)-EH11-EJ11 -> 4744.6805 | EY11: =+ET11+EU11+EV11 -> 0 | FA11: =IF($M11<=15,EP11/2,EP11) -> 0 | FB11: =IF($M11<=15,EQ11/2,EQ11) -> 0 | FC11: =IF($M11<=15,ER11/2,ER11) -> 0 | FD11: =IF($M11<=15,ES11/2,ES11) -> 0 | FE11: =IF($M11<=15,ET11/2,ET11) -> 0 | FF11: =IF($M11<=15,EU11/2,EU11) -> 0 | FG11: =IF($M11<=15,EV11/2,EV11) -> 0 | FH11: =IF($M11<=15,EW11/2,EW11) -> 0 | ... FJ11: =IF($M11<=15,EY11/2,EY11) -> 0 | FK11: 0.5 | FL11: 0.5 | FM11: 0 | FN11: 0 | FO11: 0 | FP11: 1 | FR11: =(((J11/30/8)*1.5)*(U11+Y11+AC11))-(BD11+BM11+BV11) -> 0 | FS11: =(((J11/30/8)*2)*(W11+AA11+AE11))-(BF11+BO11+BX11) -> 0 | FT11: =(SUM(BA11:CJ11))-(SUM(EF11:EN11)) -> 0 | FU11: =(J11/30*M11)-(EF11) -> 0 | FV11: =(SUM(EP11:EY11))-((SUM(FA11:FJ11))*$FV$5) -> 0
H12: Administrativo | J12: =SUM(J9:J11) -> 13004.56 | K12: =SUM(K9:K11) -> 1500 | L12: =SUM(L9:L11) -> 14504.56 | T12: =SUM(T9:T11) -> 0 | U12: =SUM(U9:U11) -> 0 | V12: =SUM(V9:V11) -> 0 | W12: =SUM(W9:W11) -> 0 | X12: =SUM(X9:X11) -> 0 | Y12: =SUM(Y9:Y11) -> 0 | Z12: =SUM(Z9:Z11) -> 0 | AA12: =SUM(AA9:AA11) -> 0 | ... EN12: =SUM(EN9:EN11) -> 16137.549 | EP12: =SUM(EP9:EP11) -> 87.92 | EQ12: =SUM(EQ9:EQ11) -> 0 | ER12: =SUM(ER9:ER11) -> 0 | ES12: =SUM(ES9:ES11) -> 225 | ET12: =SUM(ET9:ET11) -> 0 | EU12: =SUM(EU9:EU11) -> 0 | EV12: =SUM(EV9:EV11) -> 350 | EW12: =SUM(EW9:EW11) -> 0 | ... EY12: =SUM(EY9:EY11) -> 350 | FA12: =SUM(FA9:FA11) -> 87.92 | FB12: =SUM(FB9:FB11) -> 0 | FC12: =SUM(FC9:FC11) -> 0 | FD12: =SUM(FD9:FD11) -> 225 | FE12: =SUM(FE9:FE11) -> 0 | FF12: =SUM(FF9:FF11) -> 0 | FG12: =SUM(FG9:FG11) -> 350 | FH12: =SUM(FH9:FH11) -> 0 | ... FP12: =SUM(FP9:FP11) -> 2
A13: =$G$4 -> JUNIO 2026 2da QUINCENA | B13: =+$G$5 -> 2026 | C13: =A13 & B13 -> JUNIO 2026 2da QUINCENA2026 | D13: =+$G$8 -> ADMINISTRATIVO | E13: 102030 | G13: RECEPCION
C15: =A15 & B15 | H15: Recepción | J15: =SUM(J14:J14) -> 0 | K15: =SUM(K14:K14) -> 0 | L15: =SUM(L14:L14) -> 0 | U15: =SUM(U14:U14) -> 0 | V15: =SUM(V14:V14) -> 0 | W15: =SUM(W14:W14) -> 0 | X15: =SUM(X14:X14) -> 0 | Y15: =SUM(Y14:Y14) -> 0 | Z15: =SUM(Z14:Z14) -> 0 | AA15: =SUM(AA14:AA14) -> 0 | AB15: =SUM(AB14:AB14) -> 0 | ... FP15: =SUM(FP14:FP14) -> 0
A16: =$G$4 -> JUNIO 2026 2da QUINCENA | B16: =+$G$5 -> 2026 | C16: =A16 & B16 -> JUNIO 2026 2da QUINCENA2026 | D16: =+G16 -> MENSAJERIA | E16: 102020 | G16: MENSAJERIA
E17: 102020 | G17: Julaj Ixcotoyac Angel Estuardo | H17: Mensajero | I17: ECONACIONAL | J17: 4002.28 | K17: 370 | L17: =+J17+K17 -> 4372.28 | M17: 9 | N17: 0.5 | O17: 0.3 | P17: 0.2 | Q17: 0 | R17: 0 | S17: =SUM(N17:R17) -> 1 | T17: A.23/3 | V17: =($J17/30/8*1.5)*U17 -> 0 | X17: =($J17/30/8*2)*W17 -> 0 | Z17: =($J17/30/8*1.5)*Y17 -> 0 | AB17: =($J17/30/8*2)*AA17 -> 0 | AD17: =(($J17/30/8)*1.5)*AC17 -> 0 | AF17: =(($J17/30/8)*2)*AE17 -> 0 | AH17: =(($J17/30/8)*1.5)*AG17 -> 0 | AJ17: =(($J17/30/8)*2)*AI17 -> 0 | AL17: =(($J17/30/8)*1.5)*AK17 -> 0 | AN17: =(($J17/30/8)*2)*AM17 -> 0 | BA17: =((J17/30)*M17)*$N17 -> 600.342 | BB17: =((K17/30)*M17)*$N17 -> 55.5 | BC17: =U17 -> 0 | BD17: =V17 -> 0 | BE17: =W17 -> 0 | BF17: =X17 -> 0 | BG17: =AO17+AT17 -> 0 | BH17: =(BA17+BD17+BF17+BG17)*0.1267 -> 76.063331 | BI17: =SUM(BA17:BH17)-BC17-BE17 -> 731.90533 | BJ17: =(($J17/30)*$M17)*$O17 -> 360.2052 | BK17: =(($K17/30)*$M17)*$O17 -> 33.3 | BL17: =Y17 -> 0 | BM17: =Z17 -> 0 | BN17: =AA17 -> 0 | BO17: =AB17 -> 0 | BP17: =AP17+AU17 -> 0 | BQ17: =(+BJ17+BM17+BO17+BP17)*0.1267 -> 45.637999 | BR17: =SUM(BJ17:BQ17)-BL17-BN17 -> 439.1432 | BS17: =(($J17/30)*$M17)*$P17 -> 240.1368 | BT17: =(($K17/30)*$M17)*$P17 -> 22.2 | BU17: =AC17 -> 0 | BV17: =AD17 -> 0 | BW17: =AE17 -> 0 | BX17: =AF17 -> 0 | BY17: =AQ17+AV17 -> 0 | BZ17: =(BS17+BV17+BX17)*0.09 -> 21.612312 | CA17: =SUM(BS17:BZ17)-BU17-BW17 -> 283.94911 | CB17: =(($J17/30)*$M17)*$Q17 -> 0 | CC17: =(($K17/30)*$M17)*$Q17 -> 0 | CD17: =AG17 -> 0 | CE17: =AH17 -> 0 | CF17: =AI17 -> 0 | CG17: =AJ17 -> 0 | CH17: =AR17+AW17 -> 0 | CI17: =(CB17+CE17+CG17)*0.09 -> 0 | CJ17: =SUM(CB17:CI17)-CD17-CF17 -> 0 | CK17: =(($J17/30)*$M17)*R17 -> 0 | CL17: =(($K17/30)*$M17)*$R17 -> 0 | CM17: =+AK17 -> 0 | CN17: =AL17 -> 0 | CO17: =AM17 -> 0 | CP17: =AN17 -> 0 | CQ17: =AS17+AX17 -> 0 | CR17: =(CK17+CN17+CP17)*0.09 -> 0 | CS17: =SUM(CK17:CR17)-CM17-CO17 -> 0 | CU17: ECONACIONAL | CV17: =IF($CU17="PROQUIMA",$BA17+$BJ17+$BS17+$CB17+$CK17,0) -> 0 | CW17: =IF($CU17="PROQUIMA",$BB17+$BK17+$BT17+$CC17+$CL17,0) -> 0 | CX17: =IF($CU17="PROQUIMA",$BC17+$BL17+$BU17+$CD17+$CM17,0) -> 0 | CY17: =IF($CU17="PROQUIMA",$BD17+$BM17+$BV17+$CE17+$CN17,0) -> 0 | CZ17: =IF($CU17="PROQUIMA",$BE17+$BN17+$BW17+$CF17+$CO17,0) -> 0 | DA17: =IF($CU17="PROQUIMA",$BF17+$BO17+$BX17+$CG17+$CP17,0) -> 0 | DB17: =IF($CU17="PROQUIMA",$BG17+$BP17+$BY17+$CH17+$CQ17,0) -> 0 | DC17: =IF($CU17="PROQUIMA",$BH17+$BQ17+$BZ17+$CI17+CR17,0) -> 0 | DD17: =SUM(CV17:DC17)-CX17-CZ17 -> 0 | DE17: =IF($CU17="UNHESA",$BA17+$BJ17+$BS17+$CB17+$CK17,0) -> 0 | DF17: =IF($CU17="UNHESA",$BB17+$BK17+$BT17+$CC17+$CL17,0) -> 0 | DG17: =IF($CU17="UNHESA",$BC17+$BL17+$BU17+$CD17+$CM17,0) -> 0 | DH17: =IF($CU17="UNHESA",$BD17+$BM17+$BV17+$CE17+$CN17,0) -> 0 | DI17: =IF($CU17="UNHESA",$BE17+$BN17+$BW17+$CF17+$CO17,0) -> 0 | DJ17: =IF($CU17="UNHESA",$BF17+$BO17+$BX17+$CG17+$CP17,0) -> 0 | DK17: =IF($CU17="UNHESA",$BG17+$BP17+$BY17+$CH17+$CQ17,0) -> 0 | DL17: =IF($CU17="UNHESA",$BH17+$BQ17+$BZ17+$CI17+$CR17,0) -> 0 | DM17: =SUM(DE17:DL17)-DG17-DI17 -> 0 | DN17: =IF($CU17="UNHESA LIQUIDOS",$BA17+$BJ17+$BS17+$CB17+$CK17,0) -> 0 | DO17: =IF($CU17="CALIDUL",$BB17+$BK17+$BT17+$CC17+$CL17,0) -> 0 | DP17: =IF($CU17="CALIDUL",$BC17+$BL17+$BU17+$CD17+$CM17,0) -> 0 | DQ17: =IF($CU17="CALIDUL",$BD17+$BM17+$BV17+$CE17+$CN17,0) -> 0 | DR17: =IF($CU17="CALIDUL",$BE17+$BN17+$BW17+$CF17+$CO17,0) -> 0 | DS17: =IF($CU17="CALIDUL",$BF17+$BO17+$BX17+$CG17+$CP17,0) -> 0 | DT17: =IF($CU17="CALIDUL",$BG17+$BP17+$BY17+$CH17+$CQ17,0) -> 0 | DU17: =IF($CU17="CALIDUL",$BH17+$BQ17+$BZ17+$CI17+$CR17,0) -> 0 | DV17: =SUM(DN17:DU17)-DP17-DR17 -> 0 | DW17: =IF($CU17="CLEARTEC",$BA17+$BJ17+$BS17+$CB17+$CK17,0) -> 0 | DX17: =IF($CU17="CLEARTEC",$BA17+$BJ17+$BS17+$CB17+$CK17,0) -> 0 | DY17: =IF($CU17="CLEARTEC",$BA17+$BJ17+$BS17+$CB17+$CK17,0) -> 0 | DZ17: =IF($CU17="CLEARTEC",$BA17+$BJ17+$BS17+$CB17+$CK17,0) -> 0 | EA17: =IF($CU17="CLEARTEC",$BA17+$BJ17+$BS17+$CB17+$CK17,0) -> 0 | EB17: =IF($CU17="CLEARTEC",$BA17+$BJ17+$BS17+$CB17+$CK17,0) -> 0 | EC17: =IF($CU17="CLEARTEC",$BA17+$BJ17+$BS17+$CB17+$CK17,0) -> 0 | ED17: =IF($CU17="CLEARTEC",$BA17+$BJ17+$BS17+$CB17+$CK17,0) -> 0 | EE17: =IF($CU17="CLEARTEC",$BA17+$BJ17+$BS17+$CB17+$CK17,0) -> 0 | EF17: =IF(CU17="ECONACIONAL",$BA17+$BJ17+$BS17+$CB17+$CK17) -> 1200.684 | EG17: =IF($CU17="ECONACIONAL",$BB17+$BK17+$BT17+$CC17+$CL17,0) -> 111 | EH17: =IF(CU17="ECONACIONAL",$BC17+$BL17+$BU17+$CD17+$CM17) -> 0 | EI17: =IF(CU17="ECONACIONAL",$BD17+$DH17+$DQ17+$DZ17+BM17+BV17+CE17+CN17) -> 0 | EJ17: =IF($CU17="CLEARTEC",$BE17+$BN17+$BW17+$CF17+$CO17,0) -> 0 | EK17: =IF(CU17="ECONACIONAL",$BF17+$BO17+$BX17+$CG17+$CP17) -> 0 | EL17: =IF(CU17="ECONACIONAL",$BG17+$BP17+$BY17+$CH17+$CQ17) -> 0 | EM17: =IF(CU17="ECONACIONAL",BH17+BQ17+BZ17+CI17+CR17) -> 143.31364 | EN17: =SUM(EF17:EM17)-EH17-EJ17 -> 1454.9976 | EY17: =+ET17+EU17+EV17 -> 0 | FA17: =IF($M17<=15,EP17/2,EP17) -> 0 | FB17: =IF($M17<=15,EQ17/2,EQ17) -> 0 | FC17: =IF($M17<=15,ER17/2,ER17) -> 0 | FD17: =IF($M17<=15,ES17/2,ES17) -> 0 | FE17: =IF($M17<=15,ET17/2,ET17) -> 0 | FF17: =IF($M17<=15,EU17/2,EU17) -> 0 | FG17: =IF($M17<=15,EV17/2,EV17) -> 0 | FH17: =IF($M17<=15,EW17/2,EW17) -> 0 | ... FJ17: =IF($M17<=15,EY17/2,EY17) -> 0 | FK17: 0.5 | FL17: 0.5 | FM17: 0 | FN17: 0 | FO17: 0 | FP17: 1 | FR17: =(((J17/30/8)*1.5)*(U17+Y17+AC17))-(BD17+BM17+BV17) -> 0 | FS17: =(((J17/30/8)*2)*(W17+AA17+AE17))-(BF17+BO17+BX17) -> 0 | FT17: =(SUM(BA17:CJ17))-(SUM(EF17:EN17)) -> 0 | FU17: =(J17/30*M17)-(EF17) -> 0 | FV17: =(SUM(EP17:EY17))-((SUM(FA17:FJ17))*$FV$5) -> 0
H18: Total | J18: =+J17 -> 4002.28 | K18: =+K17 -> 370 | L18: =+L17 -> 4372.28 | U18: =+U17 -> 0 | V18: =+V17 -> 0 | W18: =+W17 -> 0 | X18: =+X17 -> 0 | Y18: =+Y17 -> 0 | Z18: =+Z17 -> 0 | AA18: =+AA17 -> 0 | AB18: =+AB17 -> 0 | ... AZ18: =+AZ17 -> 0 | BA18: =SUM(BA17) -> 600.342 | BB18: =SUM(BB17) -> 55.5 | BC18: =SUM(BC17) -> 0 | BD18: =SUM(BD17) -> 0 | BE18: =SUM(BE17) -> 0 | BF18: =SUM(BF17) -> 0 | BG18: =SUM(BG17) -> 0 | BH18: =SUM(BH17) -> 76.063331 | ... CS18: =SUM(CS17) -> 0 | CT18: =+CT17 -> 0 | CU18: =+CU17 -> ECONACIONAL | CV18: =+CV17 -> 0 | CW18: =+CW17 -> 0 | CX18: =+CX17 -> 0 | CY18: =+CY17 -> 0 | CZ18: =+CZ17 -> 0 | DA18: =+DA17 -> 0 | ... EN18: =+EN17 -> 1454.9976 | EP18: =+EP17 -> 0 | EQ18: =+EQ17 -> 0 | ER18: =+ER17 -> 0 | ES18: =+ES17 -> 0 | ET18: =+ET17 -> 0 | EU18: =+EU17 -> 0 | EV18: =+EV17 -> 0 | EW18: =+EW17 -> 0 | ... EY18: =+EY17 -> 0 | FA18: =+FA17 -> 0 | FB18: =+FB17 -> 0 | FC18: =+FC17 -> 0 | FD18: =+FD17 -> 0 | FE18: =+FE17 -> 0 | FF18: =+FF17 -> 0 | FG18: =+FG17 -> 0 | FH18: =+FH17 -> 0 | ... FJ18: =+FJ17 -> 0
H19: Total Administrativo | J19: =+J12+J15+J18 -> 17006.84 | K19: =+K12+K15+K18 -> 1870 | L19: =+L12+L15+L18 -> 18876.84 | U19: =+U12+U15+U18 -> 0 | V19: =+V12+V15+V18 -> 0 | W19: =+W12+W15+W18 -> 0 | X19: =+X12+X15+X18 -> 0 | Y19: =+Y12+Y15+Y18 -> 0 | Z19: =+Z12+Z15+Z18 -> 0 | AA19: =+AA12+AA15+AA18 -> 0 | AB19: =+AB12+AB15+AB18 -> 0 | ... EN19: =+EN12+EN15+EN18 -> 17592.547 | EP19: =+EP12+EP15+EP18 -> 87.92 | EQ19: =+EQ12+EQ15+EQ18 -> 0 | ER19: =+ER12+ER15+ER18 -> 0 | ES19: =+ES12+ES15+ES18 -> 225 | ET19: =+ET12+ET15+ET18 -> 0 | EU19: =+EU12+EU15+EU18 -> 0 | EV19: =+EV12+EV15+EV18 -> 350 | EW19: =+EW12+EW15+EW18 -> 0 | ... EY19: =+EY12+EY15+EY18 -> 350 | FA19: =+FA12+FA15+FA18 -> 87.92 | FB19: =+FB12+FB15+FB18 -> 0 | FC19: =+FC12+FC15+FC18 -> 0 | FD19: =+FD12+FD15+FD18 -> 225 | FE19: =+FE12+FE15+FE18 -> 0 | FF19: =+FF12+FF15+FF18 -> 0 | FG19: =+FG12+FG15+FG18 -> 350 | FH19: =+FH12+FH15+FH18 -> 0 | ... FP19: =+FP12+FP15+FP18 -> 2
E20: 103010 | G20: RECURSOS HUMANOS
A21: =$G$4 -> JUNIO 2026 2da QUINCENA | B21: =+$G$5 -> 2026 | C21: =A21 & B21 -> JUNIO 2026 2da QUINCENA2026 | D21: =+$G$20 -> RECURSOS HUMANOS | E21: 103010 | G21: Administracion
A22: =$G$4 -> JUNIO 2026 2da QUINCENA | B22: =+$G$5 -> 2026 | C22: =A22 & B22 -> JUNIO 2026 2da QUINCENA2026 | D22: =+$G$20 -> RECURSOS HUMANOS | E22: 103010 | F22: =F17+1 -> 1 | G22: Hernandez de Lemus Iris Carolina | H22: Jefe de Recursos Humanos | I22: ECONACIONAL | J22: 9150 | K22: 4500 | L22: =+J22+K22 -> 13650 | M22: 30 | N22: 0.4 | O22: 0.35 | P22: 0.05 | Q22: 0.2 | R22: 0 | S22: =SUM(N22:R22) -> 1 | V22: =($J22/30/8*1.5)*U22 -> 0 | X22: =($J22/30/8*2)*W22 -> 0 | Z22: =($J22/30/8*1.5)*Y22 -> 0 | AB22: =($J22/30/8*2)*AA22 -> 0 | AD22: =(($J22/30/8)*1.5)*AC22 -> 0 | AF22: =(($J22/30/8)*2)*AE22 -> 0 | AH22: =(($J22/30/8)*1.5)*AG22 -> 0 | AJ22: =(($J22/30/8)*2)*AI22 -> 0 | AL22: =(($J22/30/8)*1.5)*AK22 -> 0 | AN22: =(($J22/30/8)*2)*AM22 -> 0 | BA22: =((J22/30)*M22)*$N22 -> 3660 | BB22: =((K22/30)*M22)*$N22 -> 1800 | BC22: =U22 -> 0 | BD22: =V22 -> 0 | BE22: =W22 -> 0 | BF22: =X22 -> 0 | BG22: =AO22+AT22 -> 0 | BH22: =(BA22+BD22+BF22+BG22)*0.1267 -> 463.722 | BI22: =SUM(BA22:BH22)-BC22-BE22 -> 5923.722 | BJ22: =(($J22/30)*$M22)*$O22 -> 3202.5 | BK22: =(($K22/30)*$M22)*$O22 -> 1575 | BL22: =Y22 -> 0 | BM22: =Z22 -> 0 | BN22: =AA22 -> 0 | BO22: =AB22 -> 0 | BP22: =AP22+AU22 -> 0 | BQ22: =(+BJ22+BM22+BO22+BP22)*0.1267 -> 405.75675 | BR22: =SUM(BJ22:BQ22)-BL22-BN22 -> 5183.2568 | BS22: =(($J22/30)*$M22)*$P22 -> 457.5 | BT22: =(($K22/30)*$M22)*$P22 -> 225 | BU22: =AC22 -> 0 | BV22: =AD22 -> 0 | BW22: =AE22 -> 0 | BX22: =AF22 -> 0 | BY22: =AQ22+AV22 -> 0 | BZ22: =(BS22+BV22+BX22+BY22)*0.1267 -> 57.96525 | CA22: =SUM(BS22:BZ22)-BU22-BW22 -> 740.46525 | CB22: =(($J22/30)*$M22)*$Q22 -> 1830 | CC22: =(($K22/30)*$M22)*$Q22 -> 900 | CD22: =AG22 -> 0 | CE22: =AH22 -> 0 | CF22: =AI22 -> 0 | CG22: =AJ22 -> 0 | CH22: =AR22+AW22 -> 0 | CI22: =(CB22+CE22+CG22+CH22)*0.1267 -> 231.861 | CJ22: =SUM(CB22:CI22)-CD22-CF22 -> 2961.861 | CK22: =(($J22/30)*$M22)*R22 -> 0 | CL22: =(($K22/30)*$M22)*$R22 -> 0 | CM22: =+AK22 -> 0 | CN22: =AL22 -> 0 | CO22: =AM22 -> 0 | CP22: =AN22 -> 0 | CQ22: =AS22+AX22 -> 0 | CR22: =(CK22+CN22+CP22)*0.1267 -> 0 | CS22: =SUM(CK22:CR22)-CM22-CO22 -> 0 | CU22: ECONACIONAL | CV22: =IF($CU22="PROQUIMA",$BA22+$BJ22+$BS22+$CB22+$CK22,0) -> 0 | CW22: =IF($CU22="PROQUIMA",$BB22+$BK22+$BT22+$CC22+$CL22,0) -> 0 | CX22: =IF($CU22="PROQUIMA",$BC22+$BL22+$BU22+$CD22+$CM22,0) -> 0 | CY22: =IF($CU22="PROQUIMA",$BD22+$BM22+$BV22+$CE22+$CN22,0) -> 0 | CZ22: =IF($CU22="PROQUIMA",$BE22+$BN22+$BW22+$CF22+$CO22,0) -> 0 | DA22: =IF($CU22="PROQUIMA",$BF22+$BO22+$BX22+$CG22+$CP22,0) -> 0 | DB22: =IF($CU22="PROQUIMA",$BG22+$BP22+$BY22+$CH22+$CQ22,0) -> 0 | DC22: =IF($CU22="PROQUIMA",$BH22+$BQ22+$BZ22+$CI22+CR22,0) -> 0 | DD22: =SUM(CV22:DC22)-CX22-CZ22 -> 0 | DE22: =IF($CU22="UNHESA",$BA22+$BJ22+$BS22+$CB22+$CK22,0) -> 0 | DF22: =IF($CU22="UNHESA",$BB22+$BK22+$BT22+$CC22+$CL22,0) -> 0 | DG22: =IF($CU22="UNHESA",$BC22+$BL22+$BU22+$CD22+$CM22,0) -> 0 | DH22: =IF($CU22="UNHESA",$BD22+$BM22+$BV22+$CE22+$CN22,0) -> 0 | DI22: =IF($CU22="UNHESA",$BE22+$BN22+$BW22+$CF22+$CO22,0) -> 0 | DJ22: =IF($CU22="UNHESA",$BF22+$BO22+$BX22+$CG22+$CP22,0) -> 0 | DK22: =IF($CU22="UNHESA",$BG22+$BP22+$BY22+$CH22+$CQ22,0) -> 0 | DL22: =IF($CU22="UNHESA",$BH22+$BQ22+$BZ22+$CI22+$CR22,0) -> 0 | DM22: =SUM(DE22:DL22)-DG22-DI22 -> 0 | DN22: =IF($CU22="UNHESA LIQUIDOS",$BA22+$BJ22+$BS22+$CB22+$CK22,0) -> 0 | DO22: =IF($CU22="UNHESA LIQUIDOS",$BB22+$BK22+$BT22+$CC22+$CL22,0) -> 0 | DP22: =IF($CU22="UNHESA LIQUIDOS",$BC22+$BL22+$BU22+$CD22+$CM22,0) -> 0 | DQ22: =IF($CU22="UNHESA LIQUIDOS",$BD22+$BM22+$BV22+$CE22+$CN22,0) -> 0 | DR22: =IF($CU22="UNHESA LIQUIDOS",$BE22+$BN22+$BW22+$CF22+$CO22,0) -> 0 | DS22: =IF($CU22="UNHESA LIQUIDOS",$BF22+$BO22+$BX22+$CG22+$CP22,0) -> 0 | DT22: =IF($CU22="UNHESA LIQUIDOS",$BG22+$BP22+$BY22+$CH22+$CQ22,0) -> 0 | DU22: =IF($CU22="UNHESA LIQUIDOS",$BH22+$BQ22+$BZ22+$CI22+$CR22,0) -> 0 | DV22: =SUM(DN22:DU22)-DP22-DR22 -> 0 | DW22: =IF($CU22="CLEARTEC",$BA22+$BJ22+$BS22+$CB22+$CK22,0) -> 0 | DX22: =IF($CU22="CLEARTEC",$BA22+$BJ22+$BS22+$CB22+$CK22,0) -> 0 | DY22: =IF($CU22="CLEARTEC",$BA22+$BJ22+$BS22+$CB22+$CK22,0) -> 0 | DZ22: =IF($CU22="CLEARTEC",$BA22+$BJ22+$BS22+$CB22+$CK22,0) -> 0 | EA22: =IF($CU22="CLEARTEC",$BA22+$BJ22+$BS22+$CB22+$CK22,0) -> 0 | EB22: =IF($CU22="CLEARTEC",$BA22+$BJ22+$BS22+$CB22+$CK22,0) -> 0 | EC22: =IF($CU22="CLEARTEC",$BA22+$BJ22+$BS22+$CB22+$CK22,0) -> 0 | ED22: =IF($CU22="CLEARTEC",$BA22+$BJ22+$BS22+$CB22+$CK22,0) -> 0 | EE22: =IF($CU22="CLEARTEC",$BA22+$BJ22+$BS22+$CB22+$CK22,0) -> 0 | EF22: =IF(CU22="ECONACIONAL",$BA22+$BJ22+$BS22+$CB22+$CK22) -> 9150 | EG22: =IF($CU22="ECONACIONAL",$BB22+$BK22+$BT22+$CC22+$CL22,0) -> 4500 | EH22: =IF(CU22="ECONACIONAL",$BC22+$BL22+$BU22+$CD22+$CM22) -> 0 | EI22: =IF(CU22="ECONACIONAL",$BD22+$DH22+$DQ22+$DZ22+BM22+BV22+CE22+CN22) -> 0 | EJ22: =IF($CU22="CLEARTEC",$BE22+$BN22+$BW22+$CF22+$CO22,0) -> 0 | EK22: =IF(CU22="ECONACIONAL",$BF22+$BO22+$BX22+$CG22+$CP22) -> 0 | EL22: =IF(CU22="ECONACIONAL",$BG22+$BP22+$BY22+$CH22+$CQ22) -> 0 | EM22: =IF(CU22="ECONACIONAL",BH22+BQ22+BZ22+CI22+CR22) -> 1159.305 | EN22: =SUM(EF22:EM22)-EH22-EJ22 -> 14809.305 | EP22: 429.5 | ES22: =300+302 -> 602 | EY22: =+ET22+EU22+EV22 -> 0 | FA22: =IF($M22<=15,EP22/2,EP22) -> 429.5 | FB22: =IF($M22<=15,EQ22/2,EQ22) -> 0 | FC22: =IF($M22<=15,ER22/2,ER22) -> 0 | FD22: =IF($M22<=15,ES22/2,ES22) -> 602 | FE22: =IF($M22<=15,ET22/2,ET22) -> 0 | FF22: =IF($M22<=15,EU22/2,EU22) -> 0 | FG22: =IF($M22<=15,EV22/2,EV22) -> 0 | FH22: =IF($M22<=15,EW22/2,EW22) -> 0 | ... FJ22: =IF($M22<=15,EY22/2,EY22) -> 0 | FK22: 0.5 | FL22: 0.5 | FM22: 0 | FN22: 0 | FO22: 0 | FP22: 1 | FR22: =(((J22/30/8)*1.5)*(U22+Y22+AC22))-(BD22+BM22+BV22) -> 0 | FS22: =(((J22/30/8)*2)*(W22+AA22+AE22))-(BF22+BO22+BX22) -> 0 | FT22: =(SUM(BA22:CJ22))-(SUM(EF22:EN22)) -> 0 | FU22: =(J22/30*M22)-(EF22) -> 0 | FV22: =(SUM(EP22:EY22))-((SUM(FA22:FJ22))*$FV$5) -> -1031.5
A23: =$G$4 -> JUNIO 2026 2da QUINCENA | B23: =+$G$5 -> 2026 | C23: =A23 & B23 -> JUNIO 2026 2da QUINCENA2026 | D23: =+$G$20 -> RECURSOS HUMANOS | E23: 103010 | F23: =+F22+1 -> 2 | G23: Perez Menendez Mayra Alejandra | H23: Asistente de Recursos Humanos | I23: ECONACIONAL | J23: 4850 | K23: 1500 | L23: =+J23+K23 -> 6350 | M23: 30 | N23: 0.4 | O23: 0.35 | P23: 0.05 | Q23: 0.2 | R23: 0 | S23: =SUM(N23:R23) -> 1 | V23: =($J23/30/8*1.5)*U23 -> 0 | X23: =($J23/30/8*2)*W23 -> 0 | Z23: =($J23/30/8*1.5)*Y23 -> 0 | AB23: =($J23/30/8*2)*AA23 -> 0 | AD23: =(($J23/30/8)*1.5)*AC23 -> 0 | AF23: =(($J23/30/8)*2)*AE23 -> 0 | AH23: =(($J23/30/8)*1.5)*AG23 -> 0 | AJ23: =(($J23/30/8)*2)*AI23 -> 0 | AL23: =(($J23/30/8)*1.5)*AK23 -> 0 | AN23: =(($J23/30/8)*2)*AM23 -> 0 | BA23: =((J23/30)*M23)*$N23 -> 1940 | BB23: =((K23/30)*M23)*$N23 -> 600 | BC23: =U23 -> 0 | BD23: =V23 -> 0 | BE23: =W23 -> 0 | BF23: =X23 -> 0 | BG23: =AO23+AT23 -> 0 | BH23: =(BA23+BD23+BF23+BG23)*0.1267 -> 245.798 | BI23: =SUM(BA23:BH23)-BC23-BE23 -> 2785.798 | BJ23: =(($J23/30)*$M23)*$O23 -> 1697.5 | BK23: =(($K23/30)*$M23)*$O23 -> 525 | BL23: =Y23 -> 0 | BM23: =Z23 -> 0 | BN23: =AA23 -> 0 | BO23: =AB23 -> 0 | BP23: =AP23+AU23 -> 0 | BQ23: =(+BJ23+BM23+BO23+BP23)*0.1267 -> 215.07325 | BR23: =SUM(BJ23:BQ23)-BL23-BN23 -> 2437.5732 | BS23: =(($J23/30)*$M23)*$P23 -> 242.5 | BT23: =(($K23/30)*$M23)*$P23 -> 75 | BU23: =AC23 -> 0 | BV23: =AD23 -> 0 | BW23: =AE23 -> 0 | BX23: =AF23 -> 0 | BY23: =AQ23+AV23 -> 0 | BZ23: =(BS23+BV23+BX23+BY23)*0.1267 -> 30.72475 | CA23: =SUM(BS23:BZ23)-BU23-BW23 -> 348.22475 | CB23: =(($J23/30)*$M23)*$Q23 -> 970 | CC23: =(($K23/30)*$M23)*$Q23 -> 300 | CD23: =AG23 -> 0 | CE23: =AH23 -> 0 | CF23: =AI23 -> 0 | CG23: =AJ23 -> 0 | CH23: =AR23+AW23 -> 0 | CI23: =(CB23+CE23+CG23+CH23)*0.1267 -> 122.899 | CJ23: =SUM(CB23:CI23)-CD23-CF23 -> 1392.899 | CK23: =(($J23/30)*$M23)*R23 -> 0 | CL23: =(($K23/30)*$M23)*$R23 -> 0 | CM23: =+AK23 -> 0 | CN23: =AL23 -> 0 | CO23: =AM23 -> 0 | CP23: =AN23 -> 0 | CQ23: =AS23+AX23 -> 0 | CR23: =(CK23+CN23+CP23)*0.1267 -> 0 | CS23: =SUM(CK23:CR23)-CM23-CO23 -> 0 | CU23: ECONACIONAL | CV23: =IF($CU23="PROQUIMA",$BA23+$BJ23+$BS23+$CB23+$CK23,0) -> 0 | CW23: =IF($CU23="PROQUIMA",$BB23+$BK23+$BT23+$CC23+$CL23,0) -> 0 | CX23: =IF($CU23="PROQUIMA",$BC23+$BL23+$BU23+$CD23+$CM23,0) -> 0 | CY23: =IF($CU23="PROQUIMA",$BD23+$BM23+$BV23+$CE23+$CN23,0) -> 0 | CZ23: =IF($CU23="PROQUIMA",$BE23+$BN23+$BW23+$CF23+$CO23,0) -> 0 | DA23: =IF($CU23="PROQUIMA",$BF23+$BO23+$BX23+$CG23+$CP23,0) -> 0 | DB23: =IF($CU23="PROQUIMA",$BG23+$BP23+$BY23+$CH23+$CQ23,0) -> 0 | DC23: =IF($CU23="PROQUIMA",$BH23+$BQ23+$BZ23+$CI23+CR23,0) -> 0 | DD23: =SUM(CV23:DC23)-CX23-CZ23 -> 0 | DE23: =IF($CU23="UNHESA",$BA23+$BJ23+$BS23+$CB23+$CK23,0) -> 0 | DF23: =IF($CU23="UNHESA",$BB23+$BK23+$BT23+$CC23+$CL23,0) -> 0 | DG23: =IF($CU23="UNHESA",$BC23+$BL23+$BU23+$CD23+$CM23,0) -> 0 | DH23: =IF($CU23="UNHESA",$BD23+$BM23+$BV23+$CE23+$CN23,0) -> 0 | DI23: =IF($CU23="UNHESA",$BE23+$BN23+$BW23+$CF23+$CO23,0) -> 0 | DJ23: =IF($CU23="UNHESA",$BF23+$BO23+$BX23+$CG23+$CP23,0) -> 0 | DK23: =IF($CU23="UNHESA",$BG23+$BP23+$BY23+$CH23+$CQ23,0) -> 0 | DL23: =IF($CU23="UNHESA",$BH23+$BQ23+$BZ23+$CI23+$CR23,0) -> 0 | DM23: =SUM(DE23:DL23)-DG23-DI23 -> 0 | DN23: =IF($CU23="UNHESA LIQUIDOS",$BA23+$BJ23+$BS23+$CB23+$CK23,0) -> 0 | DO23: =IF($CU23="UNHESA LIQUIDOS",$BB23+$BK23+$BT23+$CC23+$CL23,0) -> 0 | DP23: =IF($CU23="UNHESA LIQUIDOS",$BC23+$BL23+$BU23+$CD23+$CM23,0) -> 0 | DQ23: =IF($CU23="UNHESA LIQUIDOS",$BD23+$BM23+$BV23+$CE23+$CN23,0) -> 0 | DR23: =IF($CU23="UNHESA LIQUIDOS",$BE23+$BN23+$BW23+$CF23+$CO23,0) -> 0 | DS23: =IF($CU23="UNHESA LIQUIDOS",$BF23+$BO23+$BX23+$CG23+$CP23,0) -> 0 | DT23: =IF($CU23="UNHESA LIQUIDOS",$BG23+$BP23+$BY23+$CH23+$CQ23,0) -> 0 | DU23: =IF($CU23="UNHESA LIQUIDOS",$BH23+$BQ23+$BZ23+$CI23+$CR23,0) -> 0 | DV23: =SUM(DN23:DU23)-DP23-DR23 -> 0 | DW23: =IF($CU23="CLEARTEC",$BA23+$BJ23+$BS23+$CB23+$CK23,0) -> 0 | DX23: =IF($CU23="CLEARTEC",$BA23+$BJ23+$BS23+$CB23+$CK23,0) -> 0 | DY23: =IF($CU23="CLEARTEC",$BA23+$BJ23+$BS23+$CB23+$CK23,0) -> 0 | DZ23: =IF($CU23="CLEARTEC",$BA23+$BJ23+$BS23+$CB23+$CK23,0) -> 0 | EA23: =IF($CU23="CLEARTEC",$BA23+$BJ23+$BS23+$CB23+$CK23,0) -> 0 | EB23: =IF($CU23="CLEARTEC",$BA23+$BJ23+$BS23+$CB23+$CK23,0) -> 0 | EC23: =IF($CU23="CLEARTEC",$BA23+$BJ23+$BS23+$CB23+$CK23,0) -> 0 | ED23: =IF($CU23="CLEARTEC",$BA23+$BJ23+$BS23+$CB23+$CK23,0) -> 0 | EE23: =IF($CU23="CLEARTEC",$BA23+$BJ23+$BS23+$CB23+$CK23,0) -> 0 | EF23: =IF(CU23="ECONACIONAL",$BA23+$BJ23+$BS23+$CB23+$CK23) -> 4850 | EG23: =IF($CU23="ECONACIONAL",$BB23+$BK23+$BT23+$CC23+$CL23,0) -> 1500 | EH23: =IF(CU23="ECONACIONAL",$BC23+$BL23+$BU23+$CD23+$CM23) -> 0 | EI23: =IF(CU23="ECONACIONAL",$BD23+$DH23+$DQ23+$DZ23+BM23+BV23+CE23+CN23) -> 0 | EJ23: =IF($CU23="CLEARTEC",$BE23+$BN23+$BW23+$CF23+$CO23,0) -> 0 | EK23: =IF(CU23="ECONACIONAL",$BF23+$BO23+$BX23+$CG23+$CP23) -> 0 | EL23: =IF(CU23="ECONACIONAL",$BG23+$BP23+$BY23+$CH23+$CQ23) -> 0 | EM23: =IF(CU23="ECONACIONAL",BH23+BQ23+BZ23+CI23+CR23) -> 614.495 | EN23: =SUM(EF23:EM23)-EH23-EJ23 -> 6964.495 | EP23: 115.97 | ES23: =124+81.5 -> 205.5 | EV23: 350 | EX23: 313.43 | EY23: =+ET23+EU23+EV23 -> 350 | FA23: =IF($M23<=15,EP23/2,EP23) -> 115.97 | FB23: =IF($M23<=15,EQ23/2,EQ23) -> 0 | FC23: =IF($M23<=15,ER23/2,ER23) -> 0 | FD23: =IF($M23<=15,ES23/2,ES23) -> 205.5 | FE23: =IF($M23<=15,ET23/2,ET23) -> 0 | FF23: =IF($M23<=15,EU23/2,EU23) -> 0 | FG23: =IF($M23<=15,EV23/2,EV23) -> 350 | FH23: =IF($M23<=15,EW23/2,EW23) -> 0 | ... FJ23: =IF($M23<=15,EY23/2,EY23) -> 350 | FR23: =(((J23/30/8)*1.5)*(U23+Y23+AC23))-(BD23+BM23+BV23) -> 0 | FS23: =(((J23/30/8)*2)*(W23+AA23+AE23))-(BF23+BO23+BX23) -> 0 | FT23: =(SUM(BA23:CJ23))-(SUM(EF23:EN23)) -> 0 | FU23: =(J23/30*M23)-(EF23) -> 0 | FV23: =(SUM(EP23:EY23))-((SUM(FA23:FJ23))*$FV$5) -> -1334.9
A24: =$G$4 -> JUNIO 2026 2da QUINCENA | B24: =+$G$5 -> 2026 | C24: =A24 & B24 -> JUNIO 2026 2da QUINCENA2026 | D24: =+$G$8 -> ADMINISTRATIVO | E24: 103010 | F24: 4 | G24: Saenz Lemus Dulce Maria | H24: Recepcionista | I24: ECONACIONAL | J24: 4250.03 | K24: 250 | L24: =+J24+K24 -> 4500.03 | M24: 30 | N24: 0.5 | O24: 0.45 | P24: 0.05 | Q24: 0 | R24: 0 | S24: =SUM(N24:R24) -> 1 | V24: =($J24/30/8*1.5)*U24 -> 0 | X24: =($J24/30/8*2)*W24 -> 0 | Z24: =($J24/30/8*1.5)*Y24 -> 0 | AB24: =($J24/30/8*2)*AA24 -> 0 | AD24: =(($J24/30/8)*1.5)*AC24 -> 0 | AF24: =(($J24/30/8)*2)*AE24 -> 0 | AH24: =(($J24/30/8)*1.5)*AG24 -> 0 | AJ24: =(($J24/30/8)*2)*AI24 -> 0 | BA24: =((J24/30)*M24)*$N24 -> 2125.015 | BB24: =((K24/30)*M24)*$N24 -> 125 | BC24: =U24 -> 0 | BD24: =V24 -> 0 | BE24: =W24 -> 0 | BF24: =X24 -> 0 | BG24: =AO24+AT24 -> 0 | BH24: =(BA24+BD24+BF24+BG24)*0.1267 -> 269.2394 | BI24: =SUM(BA24:BH24)-BC24-BE24 -> 2519.2544 | BJ24: =(($J24/30)*$M24)*$O24 -> 1912.5135 | BK24: =(($K24/30)*$M24)*$O24 -> 112.5 | BL24: =Y24 -> 0 | BM24: =Z24 -> 0 | BN24: =AA24 -> 0 | BO24: =AB24 -> 0 | BP24: =AP24+AU24 -> 0 | BQ24: =(+BJ24+BM24+BO24+BP24)*0.1267 -> 242.31546 | BR24: =SUM(BJ24:BQ24)-BL24-BN24 -> 2267.329 | BS24: =(($J24/30)*$M24)*$P24 -> 212.5015 | BT24: =(($K24/30)*$M24)*$P24 -> 12.5 | BU24: =AC24 -> 0 | BV24: =AD24 -> 0 | BW24: =AE24 -> 0 | BX24: =AF24 -> 0 | BY24: =AQ24+AV24 -> 0 | BZ24: =(BS24+BV24+BX24+BY24)*0.1267 -> 26.92394 | CA24: =SUM(BS24:BZ24)-BU24-BW24 -> 251.92544 | CB24: =(($J24/30)*$M24)*$Q24 -> 0 | CC24: =(($K24/30)*$M24)*$Q24 -> 0 | CD24: =AG24 -> 0 | CE24: =AH24 -> 0 | CF24: =AI24 -> 0 | CG24: =AJ24 -> 0 | CH24: =AR24+AW24 -> 0 | CI24: =(CB24+CE24+CG24+CH24)*0.1267 -> 0 | CJ24: =SUM(CB24:CI24)-CD24-CF24 -> 0 | CU24: ECONACIONAL | CV24: =IF($CU24="PROQUIMA",$BA24+$BJ24+$BS24+$CB24+$CK24,0) -> 0 | CW24: =IF($CU24="PROQUIMA",$BB24+$BK24+$BT24+$CC24+$CL24,0) -> 0 | CX24: =IF($CU24="PROQUIMA",$BC24+$BL24+$BU24+$CD24+$CM24,0) -> 0 | CY24: =IF($CU24="PROQUIMA",$BD24+$BM24+$BV24+$CE24+$CN24,0) -> 0 | CZ24: =IF($CU24="PROQUIMA",$BE24+$BN24+$BW24+$CF24+$CO24,0) -> 0 | DA24: =IF($CU24="PROQUIMA",$BF24+$BO24+$BX24+$CG24+$CP24,0) -> 0 | DB24: =IF($CU24="PROQUIMA",$BG24+$BP24+$BY24+$CH24+$CQ24,0) -> 0 | DC24: =IF($CU24="PROQUIMA",$BH24+$BQ24+$BZ24+$CI24+CR24,0) -> 0 | DD24: =SUM(CV24:DC24)-CX24-CZ24 -> 0 | DE24: =IF($CU24="UNHESA",$BA24+$BJ24+$BS24+$CB24+$CK24,0) -> 0 | DF24: =IF($CU24="UNHESA",$BB24+$BK24+$BT24+$CC24+$CL24,0) -> 0 | DG24: =IF($CU24="UNHESA",$BC24+$BL24+$BU24+$CD24+$CM24,0) -> 0 | DH24: =IF($CU24="UNHESA",$BD24+$BM24+$BV24+$CE24+$CN24,0) -> 0 | DI24: =IF($CU24="UNHESA",$BE24+$BN24+$BW24+$CF24+$CO24,0) -> 0 | DJ24: =IF($CU24="UNHESA",$BF24+$BO24+$BX24+$CG24+$CP24,0) -> 0 | DK24: =IF($CU24="UNHESA",$BG24+$BP24+$BY24+$CH24+$CQ24,0) -> 0 | DL24: =IF($CU24="UNHESA",$BH24+$BQ24+$BZ24+$CI24+$CR24,0) -> 0 | DM24: =SUM(DE24:DL24)-DG24-DI24 -> 0 | DN24: =IF($CU24="UNHESA LIQUIDOS",$BA24+$BJ24+$BS24+$CB24+$CK24,0) -> 0 | DO24: =IF($CU24="CALIDUL",$BB24+$BK24+$BT24+$CC24+$CL24,0) -> 0 | DP24: =IF($CU24="CALIDUL",$BC24+$BL24+$BU24+$CD24+$CM24,0) -> 0 | DQ24: =IF($CU24="CALIDUL",$BD24+$BM24+$BV24+$CE24+$CN24,0) -> 0 | DR24: =IF($CU24="CALIDUL",$BE24+$BN24+$BW24+$CF24+$CO24,0) -> 0 | DS24: =IF($CU24="CALIDUL",$BF24+$BO24+$BX24+$CG24+$CP24,0) -> 0 | DT24: =IF($CU24="CALIDUL",$BG24+$BP24+$BY24+$CH24+$CQ24,0) -> 0 | DU24: =IF($CU24="CALIDUL",$BH24+$BQ24+$BZ24+$CI24+$CR24,0) -> 0 | DV24: =SUM(DN24:DU24)-DP24-DR24 -> 0 | DW24: =IF($CU24="CLEARTEC",$BA24+$BJ24+$BS24+$CB24+$CK24,0) -> 0 | DX24: =IF($CU24="CLEARTEC",$BA24+$BJ24+$BS24+$CB24+$CK24,0) -> 0 | DY24: =IF($CU24="CLEARTEC",$BA24+$BJ24+$BS24+$CB24+$CK24,0) -> 0 | DZ24: =IF($CU24="CLEARTEC",$BA24+$BJ24+$BS24+$CB24+$CK24,0) -> 0 | EA24: =IF($CU24="CLEARTEC",$BA24+$BJ24+$BS24+$CB24+$CK24,0) -> 0 | EB24: =IF($CU24="CLEARTEC",$BA24+$BJ24+$BS24+$CB24+$CK24,0) -> 0 | EC24: =IF($CU24="CLEARTEC",$BA24+$BJ24+$BS24+$CB24+$CK24,0) -> 0 | ED24: =IF($CU24="CLEARTEC",$BA24+$BJ24+$BS24+$CB24+$CK24,0) -> 0 | EE24: =SUM(DW24:ED24)-DY24-EA24 -> 0 | EF24: =IF(CU24="ECONACIONAL",$BA24+$BJ24+$BS24+$CB24+$CK24) -> 4250.03 | EG24: =IF($CU24="ECONACIONAL",$BB24+$BK24+$BT24+$CC24+$CL24,0) -> 250 | EH24: =IF(CU24="ECONACIONAL",$BC24+$BL24+$BU24+$CD24+$CM24) -> 0 | EI24: =IF(CU24="ECONACIONAL",$BD24+$DH24+$DQ24+$DZ24+BM24+BV24+CE24+CN24) -> 0 | EJ24: =IF($CU24="CLEARTEC",$BE24+$BN24+$BW24+$CF24+$CO24,0) -> 0 | EK24: =IF(CU24="ECONACIONAL",$BF24+$BO24+$BX24+$CG24+$CP24) -> 0 | EL24: =IF(CU24="ECONACIONAL",$BG24+$BP24+$BY24+$CH24+$CQ24) -> 0 | EM24: =IF(CU24="ECONACIONAL",BH24+BQ24+BZ24+CI24+CR24) -> 538.4788 | EN24: =SUM(EF24:EM24)-EH24-EJ24 -> 5038.5088 | EP24: 4.51 | ES24: =135.5+88.5 -> 224 | EY24: =+ET24+EU24+EV24 -> 0 | FA24: =IF($M24<=15,EP24/2,EP24) -> 4.51 | FB24: =IF($M24<=15,EQ24/2,EQ24) -> 0 | FC24: =IF($M24<=15,ER24/2,ER24) -> 0 | FD24: =IF($M24<=15,ES24/2,ES24) -> 224 | FE24: =IF($M24<=15,ET24/2,ET24) -> 0 | FF24: =IF($M24<=15,EU24/2,EU24) -> 0 | FG24: =IF($M24<=15,EV24/2,EV24) -> 0 | FH24: =IF($M24<=15,EW24/2,EW24) -> 0 | ... FJ24: =IF($M24<=15,EY24/2,EY24) -> 0 | FR24: =(((J24/30/8)*1.5)*(U24+Y24+AC24))-(BD24+BM24+BV24) -> 0 | FS24: =(((J24/30/8)*2)*(W24+AA24+AE24))-(BF24+BO24+BX24) -> 0 | FT24: =(SUM(BA24:CJ24))-(SUM(EF24:EN24)) -> 0 | FU24: =(J24/30*M24)-(EF24) -> 0 | FV24: =(SUM(EP24:EY24))-((SUM(FA24:FJ24))*$FV$5) -> -228.51
A25: =$G$4 -> JUNIO 2026 2da QUINCENA | B25: =+$G$5 -> 2026 | C25: =A25 & B25 -> JUNIO 2026 2da QUINCENA2026 | D25: =+$G$20 -> RECURSOS HUMANOS | E25: 103010 | F25: 9 | G25: Marroquin Rueda Jenneffer Ivonne | H25: Asistente de Reclutamiento | I25: ECONACIONAL | J25: 4725 | K25: 1000 | L25: =+J25+K25 -> 5725 | M25: 30 | N25: 0.4 | O25: 0.35 | P25: 0.05 | Q25: 0.2 | R25: 0 | S25: =SUM(N25:R25) -> 1 | V25: =($J25/30/8*1.5)*U25 -> 0 | X25: =($J25/30/8*2)*W25 -> 0 | Z25: =($J25/30/8*1.5)*Y25 -> 0 | AB25: =($J25/30/8*2)*AA25 -> 0 | AD25: =(($J25/30/8)*1.5)*AC25 -> 0 | AF25: =(($J25/30/8)*2)*AE25 -> 0 | AH25: =(($J25/30/8)*1.5)*AG25 -> 0 | AJ25: =(($J25/30/8)*2)*AI25 -> 0 | AL25: =(($J25/30/8)*1.5)*AK25 -> 0 | AN25: =(($J25/30/8)*2)*AM25 -> 0 | BA25: =((J25/30)*M25)*$N25 -> 1890 | BB25: =((K25/30)*M25)*$N25 -> 400 | BC25: =U25 -> 0 | BD25: =V25 -> 0 | BE25: =W25 -> 0 | BF25: =X25 -> 0 | BG25: =AO25+AT25 -> 0 | BH25: =(BA25+BD25+BF25+BG25)*0.1267 -> 239.463 | BI25: =SUM(BA25:BH25)-BC25-BE25 -> 2529.463 | BJ25: =(($J25/30)*$M25)*$O25 -> 1653.75 | BK25: =(($K25/30)*$M25)*$O25 -> 350 | BL25: =Y25 -> 0 | BM25: =Z25 -> 0 | BN25: =AA25 -> 0 | BO25: =AB25 -> 0 | BP25: =AP25+AU25 -> 0 | BQ25: =(+BJ25+BM25+BO25+BP25)*0.1267 -> 209.53012 | BR25: =SUM(BJ25:BQ25)-BL25-BN25 -> 2213.2801 | BS25: =(($J25/30)*$M25)*$P25 -> 236.25 | BT25: =(($K25/30)*$M25)*$P25 -> 50 | BU25: =AC25 -> 0 | BV25: =AD25 -> 0 | BW25: =AE25 -> 0 | BX25: =AF25 -> 0 | BY25: =AQ25+AV25 -> 0 | BZ25: =(BS25+BV25+BX25+BY25)*0.1267 -> 29.932875 | CA25: =SUM(BS25:BZ25)-BU25-BW25 -> 316.18288 | CB25: =(($J25/30)*$M25)*$Q25 -> 945 | CC25: =(($K25/30)*$M25)*$Q25 -> 200 | CD25: =AG25 -> 0 | CE25: =AH25 -> 0 | CF25: =AI25 -> 0 | CG25: =AJ25 -> 0 | CH25: =AR25+AW25 -> 0 | CI25: =(CB25+CE25+CG25+CH25)*0.1267 -> 119.7315 | CJ25: =SUM(CB25:CI25)-CD25-CF25 -> 1264.7315 | CK25: =(($J25/30)*$M25)*R25 -> 0 | CL25: =(($K25/30)*$M25)*$R25 -> 0 | CM25: =+AK25 -> 0 | CN25: =AL25 -> 0 | CO25: =AM25 -> 0 | CP25: =AN25 -> 0 | CQ25: =AS25+AX25 -> 0 | CR25: =(CK25+CN25+CP25)*0.1267 -> 0 | CS25: =SUM(CK25:CR25)-CM25-CO25 -> 0 | CU25: ECONACIONAL | CV25: =IF($CU25="PROQUIMA",$BA25+$BJ25+$BS25+$CB25+$CK25,0) -> 0 | CW25: =IF($CU25="PROQUIMA",$BB25+$BK25+$BT25+$CC25+$CL25,0) -> 0 | CX25: =IF($CU25="PROQUIMA",$BC25+$BL25+$BU25+$CD25+$CM25,0) -> 0 | CY25: =IF($CU25="PROQUIMA",$BD25+$BM25+$BV25+$CE25+$CN25,0) -> 0 | CZ25: =IF($CU25="PROQUIMA",$BE25+$BN25+$BW25+$CF25+$CO25,0) -> 0 | DA25: =IF($CU25="PROQUIMA",$BF25+$BO25+$BX25+$CG25+$CP25,0) -> 0 | DB25: =IF($CU25="PROQUIMA",$BG25+$BP25+$BY25+$CH25+$CQ25,0) -> 0 | DC25: =IF($CU25="PROQUIMA",$BH25+$BQ25+$BZ25+$CI25+CR25,0) -> 0 | DD25: =SUM(CV25:DC25)-CX25-CZ25 -> 0 | DE25: =IF($CU25="UNHESA",$BA25+$BJ25+$BS25+$CB25+$CK25,0) -> 0 | DF25: =IF($CU25="UNHESA",$BB25+$BK25+$BT25+$CC25+$CL25,0) -> 0 | DG25: =IF($CU25="UNHESA",$BC25+$BL25+$BU25+$CD25+$CM25,0) -> 0 | DH25: =IF($CU25="UNHESA",$BD25+$BM25+$BV25+$CE25+$CN25,0) -> 0 | DI25: =IF($CU25="UNHESA",$BE25+$BN25+$BW25+$CF25+$CO25,0) -> 0 | DJ25: =IF($CU25="UNHESA",$BF25+$BO25+$BX25+$CG25+$CP25,0) -> 0 | DK25: =IF($CU25="UNHESA",$BG25+$BP25+$BY25+$CH25+$CQ25,0) -> 0 | DL25: =IF($CU25="UNHESA",$BH25+$BQ25+$BZ25+$CI25+$CR25,0) -> 0 | DM25: =SUM(DE25:DL25)-DG25-DI25 -> 0 | DN25: =IF($CU25="UNHESA LIQUIDOS",$BA25+$BJ25+$BS25+$CB25+$CK25,0) -> 0 | DO25: =IF($CU25="UNHESA LIQUIDOS",$BB25+$BK25+$BT25+$CC25+$CL25,0) -> 0 | DP25: =IF($CU25="UNHESA LIQUIDOS",$BC25+$BL25+$BU25+$CD25+$CM25,0) -> 0 | DQ25: =IF($CU25="UNHESA LIQUIDOS",$BD25+$BM25+$BV25+$CE25+$CN25,0) -> 0 | DR25: =IF($CU25="UNHESA LIQUIDOS",$BE25+$BN25+$BW25+$CF25+$CO25,0) -> 0 | DS25: =IF($CU25="UNHESA LIQUIDOS",$BF25+$BO25+$BX25+$CG25+$CP25,0) -> 0 | DT25: =IF($CU25="UNHESA LIQUIDOS",$BG25+$BP25+$BY25+$CH25+$CQ25,0) -> 0 | DU25: =IF($CU25="UNHESA LIQUIDOS",$BH25+$BQ25+$BZ25+$CI25+$CR25,0) -> 0 | DV25: =SUM(DN25:DU25)-DP25-DR25 -> 0 | DW25: =IF($CU25="CLEARTEC",$BA25+$BJ25+$BS25+$CB25+$CK25,0) -> 0 | DX25: =IF($CU25="CLEARTEC",$BA25+$BJ25+$BS25+$CB25+$CK25,0) -> 0 | DY25: =IF($CU25="CLEARTEC",$BA25+$BJ25+$BS25+$CB25+$CK25,0) -> 0 | DZ25: =IF($CU25="CLEARTEC",$BA25+$BJ25+$BS25+$CB25+$CK25,0) -> 0 | EA25: =IF($CU25="CLEARTEC",$BA25+$BJ25+$BS25+$CB25+$CK25,0) -> 0 | EB25: =IF($CU25="CLEARTEC",$BA25+$BJ25+$BS25+$CB25+$CK25,0) -> 0 | EC25: =IF($CU25="CLEARTEC",$BA25+$BJ25+$BS25+$CB25+$CK25,0) -> 0 | ED25: =IF($CU25="CLEARTEC",$BA25+$BJ25+$BS25+$CB25+$CK25,0) -> 0 | EE25: =IF($CU25="CLEARTEC",$BA25+$BJ25+$BS25+$CB25+$CK25,0) -> 0 | EF25: =IF(CU25="ECONACIONAL",$BA25+$BJ25+$BS25+$CB25+$CK25) -> 4725 | EG25: =IF($CU25="ECONACIONAL",$BB25+$BK25+$BT25+$CC25+$CL25,0) -> 1000 | EH25: =IF(CU25="ECONACIONAL",$BC25+$BL25+$BU25+$CD25+$CM25) -> 0 | EI25: =IF(CU25="ECONACIONAL",$BD25+$DH25+$DQ25+$DZ25+BM25+BV25+CE25+CN25) -> 0 | EJ25: =IF($CU25="CLEARTEC",$BE25+$BN25+$BW25+$CF25+$CO25,0) -> 0 | EK25: =IF(CU25="ECONACIONAL",$BF25+$BO25+$BX25+$CG25+$CP25) -> 0 | EL25: =IF(CU25="ECONACIONAL",$BG25+$BP25+$BY25+$CH25+$CQ25) -> 0 | EM25: =IF(CU25="ECONACIONAL",BH25+BQ25+BZ25+CI25+CR25) -> 598.6575 | EN25: =SUM(EF25:EM25)-EH25-EJ25 -> 6323.6575 | EP25: 61.78 | ES25: =215.5+230 -> 445.5 | ET25: 82.5 | EX25: 313.43 | EY25: =+ET25+EU25+EV25 -> 82.5 | FA25: =IF($M25<=15,EP25/2,EP25) -> 61.78 | FB25: =IF($M25<=15,EQ25/2,EQ25) -> 0 | FC25: =IF($M25<=15,ER25/2,ER25) -> 0 | FD25: =IF($M25<=15,ES25/2,ES25) -> 445.5 | FE25: =IF($M25<=15,ET25/2,ET25) -> 82.5 | FF25: =IF($M25<=15,EU25/2,EU25) -> 0 | FG25: =IF($M25<=15,EV25/2,EV25) -> 0 | FH25: =IF($M25<=15,EW25/2,EW25) -> 0 | ... FJ25: =IF($M25<=15,EY25/2,EY25) -> 82.5 | FR25: =(((J25/30/8)*1.5)*(U25+Y25+AC25))-(BD25+BM25+BV25) -> 0 | FS25: =(((J25/30/8)*2)*(W25+AA25+AE25))-(BF25+BO25+BX25) -> 0 | FT25: =(SUM(BA25:CJ25))-(SUM(EF25:EN25)) -> 0 | FU25: =(J25/30*M25)-(EF25) -> 0 | FV25: =(SUM(EP25:EY25))-((SUM(FA25:FJ25))*$FV$5) -> -985.71
H26: TotaL Recursos Humanos | J26: =SUM(J22:J25) -> 22975.03 | K26: =SUM(K22:K25) -> 7250 | L26: =SUM(L22:L25) -> 30225.03 | U26: =SUM(U22:U25) -> 0 | V26: =SUM(V22:V25) -> 0 | W26: =SUM(W22:W25) -> 0 | X26: =SUM(X22:X25) -> 0 | Y26: =SUM(Y22:Y25) -> 0 | Z26: =SUM(Z22:Z25) -> 0 | AA26: =SUM(AA22:AA25) -> 0 | AB26: =SUM(AB22:AB25) -> 0 | ... EN26: =SUM(EN22:EN25) -> 33135.966 | EP26: =SUM(EP22:EP25) -> 611.76 | EQ26: =SUM(EQ22:EQ25) -> 0 | ER26: =SUM(ER22:ER25) -> 0 | ES26: =SUM(ES22:ES25) -> 1477 | ET26: =SUM(ET22:ET25) -> 82.5 | EU26: =SUM(EU22:EU25) -> 0 | EV26: =SUM(EV22:EV25) -> 350 | EW26: =SUM(EW22:EW25) -> 0 | ... EY26: =SUM(EY22:EY25) -> 432.5 | FA26: =SUM(FA22:FA25) -> 611.76 | FB26: =SUM(FB22:FB25) -> 0 | FC26: =SUM(FC22:FC25) -> 0 | FD26: =SUM(FD22:FD25) -> 1477 | FE26: =SUM(FE22:FE25) -> 82.5 | FF26: =SUM(FF22:FF25) -> 0 | FG26: =SUM(FG22:FG25) -> 350 | FH26: =SUM(FH22:FH25) -> 0 | ... FJ26: =SUM(FJ22:FJ25) -> 432.5
G27: INFORMATICA
A28: =$G$4 -> JUNIO 2026 2da QUINCENA | B28: =+$G$5 -> 2026 | C28: =A28 & B28 -> JUNIO 2026 2da QUINCENA2026 | D28: =+$G$27 -> INFORMATICA | E28: 104010 | G28: Administracion
A29: =$G$4 -> JUNIO 2026 2da QUINCENA | B29: =+$G$5 -> 2026 | C29: =A29 & B29 -> JUNIO 2026 2da QUINCENA2026 | D29: =+$G$27 -> INFORMATICA | E29: 104010 | F29: =F25+1 -> 10 | G29: Jimenez Sosa Luis Eduardo | H29: Jefe de Informática | I29: ECONACIONAL | J29: 8000 | K29: 7500 | L29: =+J29+K29 -> 15500 | M29: 30 | N29: 0.5 | O29: 0.45 | P29: 0.05 | R29: 0 | S29: =SUM(N29:R29) -> 1 | U29: 0 | V29: =($J29/30/8*1.5)*U29 -> 0 | X29: =($J29/30/8*2)*W29 -> 0 | Z29: =($J29/30/8*1.5)*Y29 -> 0 | AB29: =($J29/30/8*2)*AA29 -> 0 | AD29: =(($J29/30/8)*1.5)*AC29 -> 0 | AF29: =(($J29/30/8)*2)*AE29 -> 0 | AH29: =(($J29/30/8)*1.5)*AG29 -> 0 | AJ29: =(($J29/30/8)*2)*AI29 -> 0 | AL29: =(($J29/30/8)*1.5)*AK29 -> 0 | AN29: =(($J29/30/8)*2)*AM29 -> 0 | BA29: =((J29/30)*M29)*$N29 -> 4000 | BB29: =((K29/30)*M29)*$N29 -> 3750 | BC29: =U29 -> 0 | BD29: =V29 -> 0 | BE29: =W29 -> 0 | BF29: =X29 -> 0 | BG29: =AO29+AT29 -> 0 | BH29: =(BA29+BD29+BF29+BG29)*0.1267 -> 506.8 | BI29: =SUM(BA29:BH29)-BC29-BE29 -> 8256.8 | BJ29: =(($J29/30)*$M29)*$O29 -> 3600 | BK29: =(($K29/30)*$M29)*$O29 -> 3375 | BL29: =Y29 -> 0 | BM29: =Z29 -> 0 | BN29: =AA29 -> 0 | BO29: =AB29 -> 0 | BP29: =AP29+AU29 -> 0 | BQ29: =(+BJ29+BM29+BO29+BP29)*0.1267 -> 456.12 | BR29: =SUM(BJ29:BQ29)-BL29-BN29 -> 7431.12 | BS29: =(($J29/30)*$M29)*$P29 -> 400 | BT29: =(($K29/30)*$M29)*$P29 -> 375 | BU29: =AC29 -> 0 | BV29: =AD29 -> 0 | BW29: =AE29 -> 0 | BX29: =AF29 -> 0 | BY29: =AQ29+AV29 -> 0 | BZ29: =(BS29+BV29+BX29+BY29)*0.1267 -> 50.68 | CA29: =SUM(BS29:BZ29)-BU29-BW29 -> 825.68 | CB29: =(($J29/30)*$M29)*$Q29 -> 0 | CC29: =(($K29/30)*$M29)*$Q29 -> 0 | CD29: =AG29 -> 0 | CE29: =AH29 -> 0 | CF29: =AI29 -> 0 | CG29: =AJ29 -> 0 | CH29: =AR29+AW29 -> 0 | CI29: =(CB29+CE29+CG29+CH29)*0.1267 -> 0 | CJ29: =SUM(CB29:CI29)-CD29-CF29 -> 0 | CK29: =(($J29/30)*$M29)*R29 -> 0 | CL29: =(($K29/30)*$M29)*$R29 -> 0 | CM29: =+AK29 -> 0 | CN29: =AL29 -> 0 | CO29: =AM29 -> 0 | CP29: =AN29 -> 0 | CQ29: =AS29+AX29 -> 0 | CR29: =(CK29+CN29+CP29)*0.1267 -> 0 | CS29: =SUM(CK29:CR29)-CM29-CO29 -> 0 | CU29: ECONACIONAL | CV29: =IF($CU29="PROQUIMA",$BA29+$BJ29+$BS29+$CB29+$CK29,0) -> 0 | CW29: =IF($CU29="PROQUIMA",$BB29+$BK29+$BT29+$CC29+$CL29,0) -> 0 | CX29: =IF($CU29="PROQUIMA",$BC29+$BL29+$BU29+$CD29+$CM29,0) -> 0 | CY29: =IF($CU29="PROQUIMA",$BD29+$BM29+$BV29+$CE29+$CN29,0) -> 0 | CZ29: =IF($CU29="PROQUIMA",$BE29+$BN29+$BW29+$CF29+$CO29,0) -> 0 | DA29: =IF($CU29="PROQUIMA",$BF29+$BO29+$BX29+$CG29+$CP29,0) -> 0 | DB29: =IF($CU29="PROQUIMA",$BG29+$BP29+$BY29+$CH29+$CQ29,0) -> 0 | DC29: =IF($CU29="PROQUIMA",$BH29+$BQ29+$BZ29+$CI29+CR29,0) -> 0 | DD29: =SUM(CV29:DC29)-CX29-CZ29 -> 0 | DE29: =IF($CU29="UNHESA",$BA29+$BJ29+$BS29+$CB29+$CK29,0) -> 0 | DF29: =IF($CU29="UNHESA",$BB29+$BK29+$BT29+$CC29+$CL29,0) -> 0 | DG29: =IF($CU29="UNHESA",$BC29+$BL29+$BU29+$CD29+$CM29,0) -> 0 | DH29: =IF($CU29="UNHESA",$BD29+$BM29+$BV29+$CE29+$CN29,0) -> 0 | DI29: =IF($CU29="UNHESA",$BE29+$BN29+$BW29+$CF29+$CO29,0) -> 0 | DJ29: =IF($CU29="UNHESA",$BF29+$BO29+$BX29+$CG29+$CP29,0) -> 0 | DK29: =IF($CU29="UNHESA",$BG29+$BP29+$BY29+$CH29+$CQ29,0) -> 0 | DL29: =IF($CU29="UNHESA",$BH29+$BQ29+$BZ29+$CI29+$CR29,0) -> 0 | DM29: =SUM(DE29:DL29)-DG29-DI29 -> 0 | DN29: =IF($CU29="UNHESA LIQUIDOS",$BA29+$BJ29+$BS29+$CB29+$CK29,0) -> 0 | DO29: =IF($CU29="CALIDUL",$BB29+$BK29+$BT29+$CC29+$CL29,0) -> 0 | DP29: =IF($CU29="CALIDUL",$BC29+$BL29+$BU29+$CD29+$CM29,0) -> 0 | DQ29: =IF($CU29="CALIDUL",$BD29+$BM29+$BV29+$CE29+$CN29,0) -> 0 | DR29: =IF($CU29="CALIDUL",$BE29+$BN29+$BW29+$CF29+$CO29,0) -> 0 | DS29: =IF($CU29="CALIDUL",$BF29+$BO29+$BX29+$CG29+$CP29,0) -> 0 | DT29: =IF($CU29="CALIDUL",$BG29+$BP29+$BY29+$CH29+$CQ29,0) -> 0 | DU29: =IF($CU29="CALIDUL",$BH29+$BQ29+$BZ29+$CI29+$CR29,0) -> 0 | DV29: =SUM(DN29:DU29)-DP29-DR29 -> 0 | DW29: =IF($CU29="CLEARTEC",$BA29+$BJ29+$BS29+$CB29+$CK29,0) -> 0 | DX29: =IF($CU29="CLEARTEC",$BA29+$BJ29+$BS29+$CB29+$CK29,0) -> 0 | DY29: =IF($CU29="CLEARTEC",$BA29+$BJ29+$BS29+$CB29+$CK29,0) -> 0 | DZ29: =IF($CU29="CLEARTEC",$BA29+$BJ29+$BS29+$CB29+$CK29,0) -> 0 | EA29: =IF($CU29="CLEARTEC",$BA29+$BJ29+$BS29+$CB29+$CK29,0) -> 0 | EB29: =IF($CU29="CLEARTEC",$BA29+$BJ29+$BS29+$CB29+$CK29,0) -> 0 | EC29: =IF($CU29="CLEARTEC",$BA29+$BJ29+$BS29+$CB29+$CK29,0) -> 0 | ED29: =IF($CU29="CLEARTEC",$BA29+$BJ29+$BS29+$CB29+$CK29,0) -> 0 | EE29: =SUM(DW29:ED29)-DY29-EA29 -> 0 | EF29: =IF(CU29="ECONACIONAL",$BA29+$BJ29+$BS29+$CB29+$CK29) -> 8000 | EG29: =IF($CU29="ECONACIONAL",$BB29+$BK29+$BT29+$CC29+$CL29,0) -> 7500 | EH29: =IF(CU29="ECONACIONAL",$BC29+$BL29+$BU29+$CD29+$CM29) -> 0 | EI29: =IF(CU29="ECONACIONAL",$BD29+$DH29+$DQ29+$DZ29+BM29+BV29+CE29+CN29) -> 0 | EJ29: =IF($CU29="CLEARTEC",$BE29+$BN29+$BW29+$CF29+$CO29,0) -> 0 | EK29: =IF(CU29="ECONACIONAL",$BF29+$BO29+$BX29+$CG29+$CP29) -> 0 | EL29: =IF(CU29="ECONACIONAL",$BG29+$BP29+$BY29+$CH29+$CQ29) -> 0 | EM29: =IF(CU29="ECONACIONAL",BH29+BQ29+BZ29+CI29+CR29) -> 1013.6 | EN29: =SUM(EF29:EM29)-EH29-EJ29 -> 16513.6 | EP29: 493.18 | EQ29: 2633.75 | EY29: =+ET29+EU29+EV29 -> 0 | FA29: =IF($M29<=15,EP29/2,EP29) -> 493.18 | FB29: =IF($M29<=15,EQ29/2,EQ29) -> 2633.75 | FC29: =IF($M29<=15,ER29/2,ER29) -> 0 | FD29: =IF($M29<=15,ES29/2,ES29) -> 0 | FE29: =IF($M29<=15,ET29/2,ET29) -> 0 | FF29: =IF($M29<=15,EU29/2,EU29) -> 0 | FG29: =IF($M29<=15,EV29/2,EV29) -> 0 | FH29: =IF($M29<=15,EW29/2,EW29) -> 0 | ... FJ29: =IF($M29<=15,EY29/2,EY29) -> 0 | FK29: 0.7 | FL29: 0.3 | FM29: 0 | FN29: 0 | FO29: 0 | FP29: 1 | FR29: =(((J29/30/8)*1.5)*(U29+Y29+AC29))-(BD29+BM29+BV29) -> 0 | FS29: =(((J29/30/8)*2)*(W29+AA29+AE29))-(BF29+BO29+BX29) -> 0 | FT29: =(SUM(BA29:CJ29))-(SUM(EF29:EN29)) -> 0 | FU29: =(J29/30*M29)-(EF29) -> 0 | FV29: =(SUM(EP29:EY29))-((SUM(FA29:FJ29))*$FV$5) -> -3126.93
A30: =$G$4 -> JUNIO 2026 2da QUINCENA | B30: =+$G$5 -> 2026 | C30: =A30 & B30 -> JUNIO 2026 2da QUINCENA2026 | D30: =+$G$27 -> INFORMATICA | E30: 104020 | F30: 11 | G30: Yaxon Taquira Juan Pablo Angel | H30: Analista Programador | I30: ECONACIONAL | J30: 4200 | K30: 600 | L30: =+J30+K30 -> 4800 | M30: 30 | N30: 0.5 | O30: 0.45 | P30: 0.05 | R30: 0 | S30: =SUM(N30:R30) -> 1 | V30: =($J30/30/8*1.5)*U30 -> 0 | X30: =($J30/30/8*2)*W30 -> 0 | Z30: =($J30/30/8*1.5)*Y30 -> 0 | AB30: =($J30/30/8*2)*AA30 -> 0 | AD30: =(($J30/30/8)*1.5)*AC30 -> 0 | AF30: =(($J30/30/8)*2)*AE30 -> 0 | AH30: =(($J30/30/8)*1.5)*AG30 -> 0 | AJ30: =(($J30/30/8)*2)*AI30 -> 0 | AL30: =(($J30/30/8)*1.5)*AK30 -> 0 | AN30: =(($J30/30/8)*2)*AM30 -> 0 | BA30: =((J30/30)*M30)*$N30 -> 2100 | BB30: =((K30/30)*M30)*$N30 -> 300 | BC30: =U30 -> 0 | BD30: =V30 -> 0 | BE30: =W30 -> 0 | BF30: =X30 -> 0 | BG30: =AO30+AT30 -> 0 | BH30: =(BA30+BD30+BF30+BG30)*0.1267 -> 266.07 | BI30: =SUM(BA30:BH30)-BC30-BE30 -> 2666.07 | BJ30: =(($J30/30)*$M30)*$O30 -> 1890 | BK30: =(($K30/30)*$M30)*$O30 -> 270 | BL30: =Y30 -> 0 | BM30: =Z30 -> 0 | BN30: =AA30 -> 0 | BO30: =AB30 -> 0 | BP30: =AP30+AU30 -> 0 | BQ30: =(+BJ30+BM30+BO30+BP30)*0.1267 -> 239.463 | BR30: =SUM(BJ30:BQ30)-BL30-BN30 -> 2399.463 | BS30: =(($J30/30)*$M30)*$P30 -> 210 | BT30: =(($K30/30)*$M30)*$P30 -> 30 | BU30: =AC30 -> 0 | BV30: =AD30 -> 0 | BW30: =AE30 -> 0 | BX30: =AF30 -> 0 | BY30: =AQ30+AV30 -> 0 | BZ30: =(BS30+BV30+BX30+BY30)*0.1267 -> 26.607 | CA30: =SUM(BS30:BZ30)-BU30-BW30 -> 266.607 | CB30: =(($J30/30)*$M30)*$Q30 -> 0 | CC30: =(($K30/30)*$M30)*$Q30 -> 0 | CD30: =AG30 -> 0 | CE30: =AH30 -> 0 | CF30: =AI30 -> 0 | CG30: =AJ30 -> 0 | CH30: =AR30+AW30 -> 0 | CI30: =(CB30+CE30+CG30+CH30)*0.1267 -> 0 | CJ30: =SUM(CB30:CI30)-CD30-CF30 -> 0 | CK30: =(($J30/30)*$M30)*R30 -> 0 | CL30: =(($K30/30)*$M30)*$R30 -> 0 | CM30: =+AK30 -> 0 | CN30: =AL30 -> 0 | CO30: =AM30 -> 0 | CP30: =AN30 -> 0 | CQ30: =AS30+AX30 -> 0 | CR30: =(CK30+CN30+CP30)*0.1267 -> 0 | CS30: =SUM(CK30:CR30)-CM30-CO30 -> 0 | CU30: ECONACIONAL | CV30: =IF($CU30="PROQUIMA",$BA30+$BJ30+$BS30+$CB30+$CK30,0) -> 0 | CW30: =IF($CU30="PROQUIMA",$BB30+$BK30+$BT30+$CC30+$CL30,0) -> 0 | CX30: =IF($CU30="PROQUIMA",$BC30+$BL30+$BU30+$CD30+$CM30,0) -> 0 | CY30: =IF($CU30="PROQUIMA",$BD30+$BM30+$BV30+$CE30+$CN30,0) -> 0 | CZ30: =IF($CU30="PROQUIMA",$BE30+$BN30+$BW30+$CF30+$CO30,0) -> 0 | DA30: =IF($CU30="PROQUIMA",$BF30+$BO30+$BX30+$CG30+$CP30,0) -> 0 | DB30: =IF($CU30="PROQUIMA",$BG30+$BP30+$BY30+$CH30+$CQ30,0) -> 0 | DC30: =IF($CU30="PROQUIMA",$BH30+$BQ30+$BZ30+$CI30+CR30,0) -> 0 | DD30: =SUM(CV30:DC30)-CX30-CZ30 -> 0 | DE30: =IF($CU30="UNHESA",$BA30+$BJ30+$BS30+$CB30+$CK30,0) -> 0 | DF30: =IF($CU30="UNHESA",$BB30+$BK30+$BT30+$CC30+$CL30,0) -> 0 | DG30: =IF($CU30="UNHESA",$BC30+$BL30+$BU30+$CD30+$CM30,0) -> 0 | DH30: =IF($CU30="UNHESA",$BD30+$BM30+$BV30+$CE30+$CN30,0) -> 0 | DI30: =IF($CU30="UNHESA",$BE30+$BN30+$BW30+$CF30+$CO30,0) -> 0 | DJ30: =IF($CU30="UNHESA",$BF30+$BO30+$BX30+$CG30+$CP30,0) -> 0 | DK30: =IF($CU30="UNHESA",$BG30+$BP30+$BY30+$CH30+$CQ30,0) -> 0 | DL30: =IF($CU30="UNHESA",$BH30+$BQ30+$BZ30+$CI30+$CR30,0) -> 0 | DM30: =SUM(DE30:DL30)-DG30-DI30 -> 0 | DN30: =IF($CU30="UNHESA LIQUIDOS",$BA30+$BJ30+$BS30+$CB30+$CK30,0) -> 0 | DO30: =IF($CU30="CALIDUL",$BB30+$BK30+$BT30+$CC30+$CL30,0) -> 0 | DP30: =IF($CU30="CALIDUL",$BC30+$BL30+$BU30+$CD30+$CM30,0) -> 0 | DQ30: =IF($CU30="CALIDUL",$BD30+$BM30+$BV30+$CE30+$CN30,0) -> 0 | DR30: =IF($CU30="CALIDUL",$BE30+$BN30+$BW30+$CF30+$CO30,0) -> 0 | DS30: =IF($CU30="CALIDUL",$BF30+$BO30+$BX30+$CG30+$CP30,0) -> 0 | DT30: =IF($CU30="CALIDUL",$BG30+$BP30+$BY30+$CH30+$CQ30,0) -> 0 | DU30: =IF($CU30="CALIDUL",$BH30+$BQ30+$BZ30+$CI30+$CR30,0) -> 0 | DV30: =SUM(DN30:DU30)-DP30-DR30 -> 0 | DW30: =IF($CU30="CLEARTEC",$BA30+$BJ30+$BS30+$CB30+$CK30,0) -> 0 | DX30: =IF($CU30="CLEARTEC",$BA30+$BJ30+$BS30+$CB30+$CK30,0) -> 0 | DY30: =IF($CU30="CLEARTEC",$BA30+$BJ30+$BS30+$CB30+$CK30,0) -> 0 | DZ30: =IF($CU30="CLEARTEC",$BA30+$BJ30+$BS30+$CB30+$CK30,0) -> 0 | EA30: =IF($CU30="CLEARTEC",$BA30+$BJ30+$BS30+$CB30+$CK30,0) -> 0 | EB30: =IF($CU30="CLEARTEC",$BA30+$BJ30+$BS30+$CB30+$CK30,0) -> 0 | EC30: =IF($CU30="CLEARTEC",$BA30+$BJ30+$BS30+$CB30+$CK30,0) -> 0 | ED30: =IF($CU30="CLEARTEC",$BA30+$BJ30+$BS30+$CB30+$CK30,0) -> 0 | EE30: =SUM(DW30:ED30)-DY30-EA30 -> 0 | EF30: =IF(CU30="ECONACIONAL",$BA30+$BJ30+$BS30+$CB30+$CK30) -> 4200 | EG30: =IF($CU30="ECONACIONAL",$BB30+$BK30+$BT30+$CC30+$CL30,0) -> 600 | EH30: =IF(CU30="ECONACIONAL",$BC30+$BL30+$BU30+$CD30+$CM30) -> 0 | EI30: =IF(CU30="ECONACIONAL",$BD30+$DH30+$DQ30+$DZ30+BM30+BV30+CE30+CN30) -> 0 | EJ30: =IF($CU30="CLEARTEC",$BE30+$BN30+$BW30+$CF30+$CO30,0) -> 0 | EK30: =IF(CU30="ECONACIONAL",$BF30+$BO30+$BX30+$CG30+$CP30) -> 0 | EL30: =IF(CU30="ECONACIONAL",$BG30+$BP30+$BY30+$CH30+$CQ30) -> 0 | EM30: =IF(CU30="ECONACIONAL",BH30+BQ30+BZ30+CI30+CR30) -> 532.14 | EN30: =SUM(EF30:EM30)-EH30-EJ30 -> 5332.14 | EP30: 21 | EY30: =+ET30+EU30+EV30 -> 0 | FA30: =IF($M30<=15,EP30/2,EP30) -> 21 | FB30: =IF($M30<=15,EQ30/2,EQ30) -> 0 | FC30: =IF($M30<=15,ER30/2,ER30) -> 0 | FD30: =IF($M30<=15,ES30/2,ES30) -> 0 | FE30: =IF($M30<=15,ET30/2,ET30) -> 0 | FF30: =IF($M30<=15,EU30/2,EU30) -> 0 | FG30: =IF($M30<=15,EV30/2,EV30) -> 0 | FH30: =IF($M30<=15,EW30/2,EW30) -> 0 | ... FJ30: =IF($M30<=15,EY30/2,EY30) -> 0 | FR30: =(((J30/30/8)*1.5)*(U30+Y30+AC30))-(BD30+BM30+BV30) -> 0 | FS30: =(((J30/30/8)*2)*(W30+AA30+AE30))-(BF30+BO30+BX30) -> 0 | FT30: =(SUM(BA30:CJ30))-(SUM(EF30:EN30)) -> 0 | FU30: =(J30/30*M30)-(EF30) -> 0 | FV30: =(SUM(EP30:EY30))-((SUM(FA30:FJ30))*$FV$5) -> -21
A31: =$G$4 -> JUNIO 2026 2da QUINCENA | B31: =+$G$5 -> 2026 | C31: =A31 & B31 -> JUNIO 2026 2da QUINCENA2026 | D31: =+$G$27 -> INFORMATICA | E31: 104020 | F31: 12 | G31: Vega Ortega Cesar Javier Arnoldo | H31: Analista Programador | I31: ECONACIONAL | J31: 4200 | K31: 600 | L31: =+J31+K31 -> 4800 | M31: 30 | N31: 0.45 | O31: 0.37 | P31: 0.03 | Q31: 0.15 | R31: 0 | S31: =SUM(N31:R31) -> 1 | V31: =($J31/30/8*1.5)*U31 -> 0 | X31: =($J31/30/8*2)*W31 -> 0 | Z31: =($J31/30/8*1.5)*Y31 -> 0 | AB31: =($J31/30/8*2)*AA31 -> 0 | AD31: =(($J31/30/8)*1.5)*AC31 -> 0 | AF31: =(($J31/30/8)*2)*AE31 -> 0 | AH31: =(($J31/30/8)*1.5)*AG31 -> 0 | AJ31: =(($J31/30/8)*2)*AI31 -> 0 | AL31: =(($J31/30/8)*1.5)*AK31 -> 0 | AN31: =(($J31/30/8)*2)*AM31 -> 0 | BA31: =((J31/30)*M31)*$N31 -> 1890 | BB31: =((K31/30)*M31)*$N31 -> 270 | BC31: =U31 -> 0 | BD31: =V31 -> 0 | BE31: =W31 -> 0 | BF31: =X31 -> 0 | BG31: =AO31+AT31 -> 0 | BH31: =(BA31+BD31+BF31+BG31)*0.1267 -> 239.463 | BI31: =SUM(BA31:BH31)-BC31-BE31 -> 2399.463 | BJ31: =(($J31/30)*$M31)*$O31 -> 1554 | BK31: =(($K31/30)*$M31)*$O31 -> 222 | BL31: =Y31 -> 0 | BM31: =Z31 -> 0 | BN31: =AA31 -> 0 | BO31: =AB31 -> 0 | BP31: =AP31+AU31 -> 0 | BQ31: =(+BJ31+BM31+BO31+BP31)*0.1267 -> 196.8918 | BR31: =SUM(BJ31:BQ31)-BL31-BN31 -> 1972.8918 | BS31: =(($J31/30)*$M31)*$P31 -> 126 | BT31: =(($K31/30)*$M31)*$P31 -> 18 | BU31: =AC31 -> 0 | BV31: =AD31 -> 0 | BW31: =AE31 -> 0 | BX31: =AF31 -> 0 | BY31: =AQ31+AV31 -> 0 | BZ31: =(BS31+BV31+BX31+BY31)*0.1267 -> 15.9642 | CA31: =SUM(BS31:BZ31)-BU31-BW31 -> 159.9642 | CB31: =(($J31/30)*$M31)*$Q31 -> 630 | CC31: =(($K31/30)*$M31)*$Q31 -> 90 | CD31: =AG31 -> 0 | CE31: =AH31 -> 0 | CF31: =AI31 -> 0 | CG31: =AJ31 -> 0 | CH31: =AR31+AW31 -> 0 | CI31: =(CB31+CE31+CG31+CH31)*0.1267 -> 79.821 | CJ31: =SUM(CB31:CI31)-CD31-CF31 -> 799.821 | CK31: =(($J31/30)*$M31)*R31 -> 0 | CL31: =(($K31/30)*$M31)*$R31 -> 0 | CM31: =+AK31 -> 0 | CN31: =AL31 -> 0 | CO31: =AM31 -> 0 | CP31: =AN31 -> 0 | CQ31: =AS31+AX31 -> 0 | CR31: =(CK31+CN31+CP31)*0.1267 -> 0 | CS31: =SUM(CK31:CR31)-CM31-CO31 -> 0 | CU31: ECONACIONAL | CV31: =IF($CU31="PROQUIMA",$BA31+$BJ31+$BS31+$CB31+$CK31,0) -> 0 | CW31: =IF($CU31="PROQUIMA",$BB31+$BK31+$BT31+$CC31+$CL31,0) -> 0 | CX31: =IF($CU31="PROQUIMA",$BC31+$BL31+$BU31+$CD31+$CM31,0) -> 0 | CY31: =IF($CU31="PROQUIMA",$BD31+$BM31+$BV31+$CE31+$CN31,0) -> 0 | CZ31: =IF($CU31="PROQUIMA",$BE31+$BN31+$BW31+$CF31+$CO31,0) -> 0 | DA31: =IF($CU31="PROQUIMA",$BF31+$BO31+$BX31+$CG31+$CP31,0) -> 0 | DB31: =IF($CU31="PROQUIMA",$BG31+$BP31+$BY31+$CH31+$CQ31,0) -> 0 | DC31: =IF($CU31="PROQUIMA",$BH31+$BQ31+$BZ31+$CI31+CR31,0) -> 0 | DD31: =SUM(CV31:DC31)-CX31-CZ31 -> 0 | DE31: =IF($CU31="UNHESA",$BA31+$BJ31+$BS31+$CB31+$CK31,0) -> 0 | DF31: =IF($CU31="UNHESA",$BB31+$BK31+$BT31+$CC31+$CL31,0) -> 0 | DG31: =IF($CU31="UNHESA",$BC31+$BL31+$BU31+$CD31+$CM31,0) -> 0 | DH31: =IF($CU31="UNHESA",$BD31+$BM31+$BV31+$CE31+$CN31,0) -> 0 | DI31: =IF($CU31="UNHESA",$BE31+$BN31+$BW31+$CF31+$CO31,0) -> 0 | DJ31: =IF($CU31="UNHESA",$BF31+$BO31+$BX31+$CG31+$CP31,0) -> 0 | DK31: =IF($CU31="UNHESA",$BG31+$BP31+$BY31+$CH31+$CQ31,0) -> 0 | DL31: =IF($CU31="UNHESA",$BH31+$BQ31+$BZ31+$CI31+$CR31,0) -> 0 | DM31: =SUM(DE31:DL31)-DG31-DI31 -> 0 | DN31: =IF($CU31="UNHESA LIQUIDOS",$BA31+$BJ31+$BS31+$CB31+$CK31,0) -> 0 | DO31: =IF($CU31="CALIDUL",$BB31+$BK31+$BT31+$CC31+$CL31,0) -> 0 | DP31: =IF($CU31="CALIDUL",$BC31+$BL31+$BU31+$CD31+$CM31,0) -> 0 | DQ31: =IF($CU31="CALIDUL",$BD31+$BM31+$BV31+$CE31+$CN31,0) -> 0 | DR31: =IF($CU31="CALIDUL",$BE31+$BN31+$BW31+$CF31+$CO31,0) -> 0 | DS31: =IF($CU31="CALIDUL",$BF31+$BO31+$BX31+$CG31+$CP31,0) -> 0 | DT31: =IF($CU31="CALIDUL",$BG31+$BP31+$BY31+$CH31+$CQ31,0) -> 0 | DU31: =IF($CU31="CALIDUL",$BH31+$BQ31+$BZ31+$CI31+$CR31,0) -> 0 | DV31: =SUM(DN31:DU31)-DP31-DR31 -> 0 | DW31: =IF($CU31="CLEARTEC",$BA31+$BJ31+$BS31+$CB31+$CK31,0) -> 0 | DX31: =IF($CU31="CLEARTEC",$BA31+$BJ31+$BS31+$CB31+$CK31,0) -> 0 | DY31: =IF($CU31="CLEARTEC",$BA31+$BJ31+$BS31+$CB31+$CK31,0) -> 0 | DZ31: =IF($CU31="CLEARTEC",$BA31+$BJ31+$BS31+$CB31+$CK31,0) -> 0 | EA31: =IF($CU31="CLEARTEC",$BA31+$BJ31+$BS31+$CB31+$CK31,0) -> 0 | EB31: =IF($CU31="CLEARTEC",$BA31+$BJ31+$BS31+$CB31+$CK31,0) -> 0 | EC31: =IF($CU31="CLEARTEC",$BA31+$BJ31+$BS31+$CB31+$CK31,0) -> 0 | ED31: =IF($CU31="CLEARTEC",$BA31+$BJ31+$BS31+$CB31+$CK31,0) -> 0 | EE31: =SUM(DW31:ED31)-DY31-EA31 -> 0 | EF31: =IF(CU31="ECONACIONAL",$BA31+$BJ31+$BS31+$CB31+$CK31) -> 4200 | EG31: =IF($CU31="ECONACIONAL",$BB31+$BK31+$BT31+$CC31+$CL31,0) -> 600 | EH31: =IF(CU31="ECONACIONAL",$BC31+$BL31+$BU31+$CD31+$CM31) -> 0 | EI31: =IF(CU31="ECONACIONAL",$BD31+$DH31+$DQ31+$DZ31+BM31+BV31+CE31+CN31) -> 0 | EJ31: =IF($CU31="CLEARTEC",$BE31+$BN31+$BW31+$CF31+$CO31,0) -> 0 | EK31: =IF(CU31="ECONACIONAL",$BF31+$BO31+$BX31+$CG31+$CP31) -> 0 | EL31: =IF(CU31="ECONACIONAL",$BG31+$BP31+$BY31+$CH31+$CQ31) -> 0 | EM31: =IF(CU31="ECONACIONAL",BH31+BQ31+BZ31+CI31+CR31) -> 532.14 | EN31: =SUM(EF31:EM31)-EH31-EJ31 -> 5332.14 | EP31: 21 | EY31: =+ET31+EU31+EV31 -> 0 | FA31: =IF($M31<=15,EP31/2,EP31) -> 21 | FB31: =IF($M31<=15,EQ31/2,EQ31) -> 0 | FC31: =IF($M31<=15,ER31/2,ER31) -> 0 | FD31: =IF($M31<=15,ES31/2,ES31) -> 0 | FE31: =IF($M31<=15,ET31/2,ET31) -> 0 | FF31: =IF($M31<=15,EU31/2,EU31) -> 0 | FG31: =IF($M31<=15,EV31/2,EV31) -> 0 | FH31: =IF($M31<=15,EW31/2,EW31) -> 0 | ... FJ31: =IF($M31<=15,EY31/2,EY31) -> 0 | FR31: =(((J31/30/8)*1.5)*(U31+Y31+AC31))-(BD31+BM31+BV31) -> 0 | FS31: =(((J31/30/8)*2)*(W31+AA31+AE31))-(BF31+BO31+BX31) -> 0 | FT31: =(SUM(BA31:CJ31))-(SUM(EF31:EN31)) -> 0 | FU31: =(J31/30*M31)-(EF31) -> 0 | FV31: =(SUM(EP31:EY31))-((SUM(FA31:FJ31))*$FV$5) -> -21
C32: =A32 & B32 | H32: Total Informatica | J32: =+SUM(J29:J31) -> 16400 | K32: =+SUM(K29:K31) -> 8700 | L32: =+SUM(L29:L31) -> 25100 | U32: =+SUM(U29:U31) -> 0 | V32: =+SUM(V29:V31) -> 0 | W32: =+SUM(W29:W31) -> 0 | X32: =+SUM(X29:X31) -> 0 | Y32: =+SUM(Y29:Y31) -> 0 | Z32: =+SUM(Z29:Z31) -> 0 | AA32: =+SUM(AA29:AA31) -> 0 | AB32: =+SUM(AB29:AB31) -> 0 | ... EN32: =+SUM(EN29:EN31) -> 27177.88 | EP32: =+SUM(EP29:EP31) -> 535.18 | EQ32: =+SUM(EQ29:EQ31) -> 2633.75 | ER32: =+SUM(ER29:ER31) -> 0 | ES32: =+SUM(ES29:ES31) -> 0 | ET32: =+SUM(ET29:ET31) -> 0 | EU32: =+SUM(EU29:EU31) -> 0 | EV32: =+SUM(EV29:EV31) -> 0 | EW32: =+SUM(EW29:EW31) -> 0 | ... EY32: =+SUM(EY29:EY31) -> 0 | FA32: =+SUM(FA29:FA31) -> 535.18 | FB32: =+SUM(FB29:FB31) -> 2633.75 | FC32: =+SUM(FC29:FC31) -> 0 | FD32: =+SUM(FD29:FD31) -> 0 | FE32: =+SUM(FE29:FE31) -> 0 | FF32: =+SUM(FF29:FF31) -> 0 | FG32: =+SUM(FG29:FG31) -> 0 | FH32: =+SUM(FH29:FH31) -> 0 | ... FJ32: =+SUM(FJ29:FJ31) -> 0
C33: =A33 & B33 | E33: 105010 | G33: AUDITORIA INTERNA
A34: =$G$4 -> JUNIO 2026 2da QUINCENA | B34: =+$G$5 -> 2026 | C34: =A34 & B34 -> JUNIO 2026 2da QUINCENA2026 | D34: =+$G$33 -> AUDITORIA INTERNA | E34: 105010 | G34: Administracion
A35: =$G$4 -> JUNIO 2026 2da QUINCENA | B35: =+$G$5 -> 2026 | C35: =A35 & B35 -> JUNIO 2026 2da QUINCENA2026 | D35: =+$G$33 -> AUDITORIA INTERNA | E35: 105010 | F35: 13 | G35: Mendez Cruz Walter Emilio | H35: Auditor interno | I35: ECONACIONAL | J35: 8000 | K35: 4000 | L35: =+J35+K35 -> 12000 | M35: 30 | N35: 0.5 | O35: 0.35 | P35: 0.05 | Q35: 0.1 | R35: 0 | S35: =SUM(N35:R35) -> 1 | V35: =($J35/30/8*1.5)*U35 -> 0 | X35: =($J35/30/8*2)*W35 -> 0 | Z35: =($J35/30/8*1.5)*Y35 -> 0 | AB35: =($J35/30/8*2)*AA35 -> 0 | AD35: =(($J35/30/8)*1.5)*AC35 -> 0 | AF35: =(($J35/30/8)*2)*AE35 -> 0 | AH35: =(($J35/30/8)*1.5)*AG35 -> 0 | AJ35: =(($J35/30/8)*2)*AI35 -> 0 | AL35: =(($J35/30/8)*1.5)*AK35 -> 0 | AN35: =(($J35/30/8)*2)*AM35 -> 0 | BA35: =((J35/30)*M35)*$N35 -> 4000 | BB35: =((K35/30)*M35)*$N35 -> 2000 | BC35: =U35 -> 0 | BD35: =V35 -> 0 | BE35: =W35 -> 0 | BF35: =X35 -> 0 | BG35: =AO35+AT35 -> 0 | BH35: =(BA35+BD35+BF35+BG35)*0.1267 -> 506.8 | BI35: =SUM(BA35:BH35)-BC35-BE35 -> 6506.8 | BJ35: =(($J35/30)*$M35)*$O35 -> 2800 | BK35: =(($K35/30)*$M35)*$O35 -> 1400 | BL35: =Y35 -> 0 | BM35: =Z35 -> 0 | BN35: =AA35 -> 0 | BO35: =AB35 -> 0 | BP35: =AP35+AU35 -> 0 | BQ35: =(+BJ35+BM35+BO35+BP35)*0.1267 -> 354.76 | BR35: =SUM(BJ35:BQ35)-BL35-BN35 -> 4554.76 | BS35: =(($J35/30)*$M35)*$P35 -> 400 | BT35: =(($K35/30)*$M35)*$P35 -> 200 | BU35: =AC35 -> 0 | BV35: =AD35 -> 0 | BW35: =AE35 -> 0 | BX35: =AF35 -> 0 | BY35: =AQ35+AV35 -> 0 | BZ35: =(BS35+BV35+BX35+BY35)*0.1267 -> 50.68 | CA35: =SUM(BS35:BZ35)-BU35-BW35 -> 650.68 | CB35: =(($J35/30)*$M35)*$Q35 -> 800 | CC35: =(($K35/30)*$M35)*$Q35 -> 400 | CD35: =AG35 -> 0 | CE35: =AH35 -> 0 | CF35: =AI35 -> 0 | CG35: =AJ35 -> 0 | CH35: =AR35+AW35 -> 0 | CI35: =(CB35+CE35+CG35+CH35)*0.1267 -> 101.36 | CJ35: =SUM(CB35:CI35)-CD35-CF35 -> 1301.36 | CK35: =(($J35/30)*$M35)*R35 -> 0 | CL35: =(($K35/30)*$M35)*$R35 -> 0 | CM35: =+AK35 -> 0 | CN35: =AL35 -> 0 | CO35: =AM35 -> 0 | CP35: =AN35 -> 0 | CQ35: =AS35+AX35 -> 0 | CR35: =(CK35+CN35+CP35)*0.1267 -> 0 | CS35: =SUM(CK35:CR35)-CM35-CO35 -> 0 | CU35: ECONACIONAL | CV35: =IF($CU35="PROQUIMA",$BA35+$BJ35+$BS35+$CB35+$CK35,0) -> 0 | CW35: =IF($CU35="PROQUIMA",$BB35+$BK35+$BT35+$CC35+$CL35,0) -> 0 | CX35: =IF($CU35="PROQUIMA",$BC35+$BL35+$BU35+$CD35+$CM35,0) -> 0 | CY35: =IF($CU35="PROQUIMA",$BD35+$BM35+$BV35+$CE35+$CN35,0) -> 0 | CZ35: =IF($CU35="PROQUIMA",$BE35+$BN35+$BW35+$CF35+$CO35,0) -> 0 | DA35: =IF($CU35="PROQUIMA",$BF35+$BO35+$BX35+$CG35+$CP35,0) -> 0 | DB35: =IF($CU35="PROQUIMA",$BG35+$BP35+$BY35+$CH35+$CQ35,0) -> 0 | DC35: =IF($CU35="PROQUIMA",$BH35+$BQ35+$BZ35+$CI35+CR35,0) -> 0 | DD35: =SUM(CV35:DC35)-CX35-CZ35 -> 0 | DE35: =IF($CU35="UNHESA",$BA35+$BJ35+$BS35+$CB35+$CK35,0) -> 0 | DF35: =IF($CU35="UNHESA",$BB35+$BK35+$BT35+$CC35+$CL35,0) -> 0 | DG35: =IF($CU35="UNHESA",$BC35+$BL35+$BU35+$CD35+$CM35,0) -> 0 | DH35: =IF($CU35="UNHESA",$BD35+$BM35+$BV35+$CE35+$CN35,0) -> 0 | DI35: =IF($CU35="UNHESA",$BE35+$BN35+$BW35+$CF35+$CO35,0) -> 0 | DJ35: =IF($CU35="UNHESA",$BF35+$BO35+$BX35+$CG35+$CP35,0) -> 0 | DK35: =IF($CU35="UNHESA",$BG35+$BP35+$BY35+$CH35+$CQ35,0) -> 0 | DL35: =IF($CU35="UNHESA",$BH35+$BQ35+$BZ35+$CI35+$CR35,0) -> 0 | DM35: =SUM(DE35:DL35)-DG35-DI35 -> 0 | DN35: =IF($CU35="UNHESA LIQUIDOS",$BA35+$BJ35+$BS35+$CB35+$CK35,0) -> 0 | DO35: =IF($CU35="CALIDUL",$BB35+$BK35+$BT35+$CC35+$CL35,0) -> 0 | DP35: =IF($CU35="CALIDUL",$BC35+$BL35+$BU35+$CD35+$CM35,0) -> 0 | DQ35: =IF($CU35="CALIDUL",$BD35+$BM35+$BV35+$CE35+$CN35,0) -> 0 | DR35: =IF($CU35="CALIDUL",$BE35+$BN35+$BW35+$CF35+$CO35,0) -> 0 | DS35: =IF($CU35="CALIDUL",$BF35+$BO35+$BX35+$CG35+$CP35,0) -> 0 | DT35: =IF($CU35="CALIDUL",$BG35+$BP35+$BY35+$CH35+$CQ35,0) -> 0 | DU35: =IF($CU35="CALIDUL",$BH35+$BQ35+$BZ35+$CI35+$CR35,0) -> 0 | DV35: =SUM(DN35:DU35)-DP35-DR35 -> 0 | DW35: =IF($CU35="CLEARTEC",$BA35+$BJ35+$BS35+$CB35+$CK35,0) -> 0 | DX35: =IF($CU35="CLEARTEC",$BA35+$BJ35+$BS35+$CB35+$CK35,0) -> 0 | DY35: =IF($CU35="CLEARTEC",$BA35+$BJ35+$BS35+$CB35+$CK35,0) -> 0 | DZ35: =IF($CU35="CLEARTEC",$BA35+$BJ35+$BS35+$CB35+$CK35,0) -> 0 | EA35: =IF($CU35="CLEARTEC",$BA35+$BJ35+$BS35+$CB35+$CK35,0) -> 0 | EB35: =IF($CU35="CLEARTEC",$BA35+$BJ35+$BS35+$CB35+$CK35,0) -> 0 | EC35: =IF($CU35="CLEARTEC",$BA35+$BJ35+$BS35+$CB35+$CK35,0) -> 0 | ED35: =IF($CU35="CLEARTEC",$BA35+$BJ35+$BS35+$CB35+$CK35,0) -> 0 | EE35: =SUM(DW35:ED35)-DY35-EA35 -> 0 | EF35: =IF(CU35="ECONACIONAL",$BA35+$BJ35+$BS35+$CB35+$CK35) -> 8000 | EG35: =IF($CU35="ECONACIONAL",$BB35+$BK35+$BT35+$CC35+$CL35,0) -> 4000 | EH35: =IF(CU35="ECONACIONAL",$BC35+$BL35+$BU35+$CD35+$CM35) -> 0 | EI35: =IF(CU35="ECONACIONAL",$BD35+$DH35+$DQ35+$DZ35+BM35+BV35+CE35+CN35) -> 0 | EJ35: =IF($CU35="CLEARTEC",$BE35+$BN35+$BW35+$CF35+$CO35,0) -> 0 | EK35: =IF(CU35="ECONACIONAL",$BF35+$BO35+$BX35+$CG35+$CP35) -> 0 | EL35: =IF(CU35="ECONACIONAL",$BG35+$BP35+$BY35+$CH35+$CQ35) -> 0 | EM35: =IF(CU35="ECONACIONAL",BH35+BQ35+BZ35+CI35+CR35) -> 1013.6 | EN35: =SUM(EF35:EM35)-EH35-EJ35 -> 13013.6 | EP35: 358.88 | EV35: 350 | EY35: =+ET35+EU35+EV35 -> 350 | FA35: =IF($M35<=15,EP35/2,EP35) -> 358.88 | FB35: =IF($M35<=15,EQ35/2,EQ35) -> 0 | FC35: =IF($M35<=15,ER35/2,ER35) -> 0 | FD35: =IF($M35<=15,ES35/2,ES35) -> 0 | FE35: =IF($M35<=15,ET35/2,ET35) -> 0 | FF35: =IF($M35<=15,EU35/2,EU35) -> 0 | FG35: =IF($M35<=15,EV35/2,EV35) -> 350 | FH35: =IF($M35<=15,EW35/2,EW35) -> 0 | ... FJ35: =IF($M35<=15,EY35/2,EY35) -> 350 | FK35: 0.75 | FL35: 0.25 | FM35: 0 | FN35: 0 | FO35: 0 | FP35: 1 | FR35: =(((J35/30/8)*1.5)*(U35+Y35+AC35))-(BD35+BM35+BV35) -> 0 | FS35: =(((J35/30/8)*2)*(W35+AA35+AE35))-(BF35+BO35+BX35) -> 0 | FT35: =(SUM(BA35:CJ35))-(SUM(EF35:EN35)) -> 0 | FU35: =(J35/30*M35)-(EF35) -> 0 | FV35: =(SUM(EP35:EY35))-((SUM(FA35:FJ35))*$FV$5) -> -1058.88
E36: 105010 | G36: Roman Morales Mirta de los Angeles | H36: Operador de Monitoreo | I36: ECONACIONAL | J36: 4200 | K36: 250 | L36: =+J36+K36 -> 4450 | M36: 30 | N36: 0.5 | O36: 0.4 | P36: 0.1 | Q36: 0 | R36: 0 | S36: =SUM(N36:R36) -> 1 | V36: =($J36/30/8*1.5)*U36 -> 0 | X36: =($J36/30/8*2)*W36 -> 0 | Z36: =($J36/30/8*1.5)*Y36 -> 0 | AB36: =($J36/30/8*2)*AA36 -> 0 | AD36: =(($J36/30/8)*1.5)*AC36 -> 0 | AF36: =(($J36/30/8)*2)*AE36 -> 0 | AH36: =(($J36/30/8)*1.5)*AG36 -> 0 | AJ36: =(($J36/30/8)*2)*AI36 -> 0 | AL36: =(($J36/30/8)*1.5)*AK36 -> 0 | AN36: =(($J36/30/8)*2)*AM36 -> 0 | BA36: =((J36/30)*M36)*$N36 -> 2100 | BB36: =((K36/30)*M36)*$N36 -> 125 | BC36: =U36 -> 0 | BD36: =V36 -> 0 | BE36: =W36 -> 0 | BF36: =X36 -> 0 | BG36: =AO36+AT36 -> 0 | BH36: =(BA36+BD36+BF36+BG36)*0.1267 -> 266.07 | BI36: =SUM(BA36:BH36)-BC36-BE36 -> 2491.07 | BJ36: =(($J36/30)*$M36)*$O36 -> 1680 | BK36: =(($K36/30)*$M36)*$O36 -> 100 | BL36: =Y36 -> 0 | BM36: =Z36 -> 0 | BN36: =AA36 -> 0 | BO36: =AB36 -> 0 | BP36: =AP36+AU36 -> 0 | BQ36: =(+BJ36+BM36+BO36+BP36)*0.1267 -> 212.856 | BR36: =SUM(BJ36:BQ36)-BL36-BN36 -> 1992.856 | BS36: =(($J36/30)*$M36)*$P36 -> 420 | BT36: =(($K36/30)*$M36)*$P36 -> 25 | BU36: =AC36 -> 0 | BV36: =AD36 -> 0 | BW36: =AE36 -> 0 | BX36: =AF36 -> 0 | BY36: =AQ36+AV36 -> 0 | BZ36: =(BS36+BV36+BX36+BY36)*0.1267 -> 53.214 | CA36: =SUM(BS36:BZ36)-BU36-BW36 -> 498.214 | CB36: =(($J36/30)*$M36)*$Q36 -> 0 | CC36: =(($K36/30)*$M36)*$Q36 -> 0 | CD36: =AG36 -> 0 | CE36: =AH36 -> 0 | CF36: =AI36 -> 0 | CG36: =AJ36 -> 0 | CH36: =AR36+AW36 -> 0 | CI36: =(CB36+CE36+CG36+CH36)*0.1267 -> 0 | CJ36: =SUM(CB36:CI36)-CD36-CF36 -> 0 | CK36: =(($J36/30)*$M36)*R36 -> 0 | CL36: =(($K36/30)*$M36)*$R36 -> 0 | CM36: =+AK36 -> 0 | CN36: =AL36 -> 0 | CO36: =AM36 -> 0 | CP36: =AN36 -> 0 | CQ36: =AS36+AX36 -> 0 | CR36: =(CK36+CN36+CP36)*0.1267 -> 0 | CS36: =SUM(CK36:CR36)-CM36-CO36 -> 0 | CU36: ECONACIONAL | CV36: =IF($CU36="PROQUIMA",$BA36+$BJ36+$BS36+$CB36+$CK36,0) -> 0 | CW36: =IF($CU36="PROQUIMA",$BB36+$BK36+$BT36+$CC36+$CL36,0) -> 0 | CX36: =IF($CU36="PROQUIMA",$BC36+$BL36+$BU36+$CD36+$CM36,0) -> 0 | CY36: =IF($CU36="PROQUIMA",$BD36+$BM36+$BV36+$CE36+$CN36,0) -> 0 | CZ36: =IF($CU36="PROQUIMA",$BE36+$BN36+$BW36+$CF36+$CO36,0) -> 0 | DA36: =IF($CU36="PROQUIMA",$BF36+$BO36+$BX36+$CG36+$CP36,0) -> 0 | DB36: =IF($CU36="PROQUIMA",$BG36+$BP36+$BY36+$CH36+$CQ36,0) -> 0 | DC36: =IF($CU36="PROQUIMA",$BH36+$BQ36+$BZ36+$CI36+CR36,0) -> 0 | DD36: =SUM(CV36:DC36)-CX36-CZ36 -> 0 | DE36: =IF($CU36="UNHESA",$BA36+$BJ36+$BS36+$CB36+$CK36,0) -> 0 | DF36: =IF($CU36="UNHESA",$BB36+$BK36+$BT36+$CC36+$CL36,0) -> 0 | DG36: =IF($CU36="UNHESA",$BC36+$BL36+$BU36+$CD36+$CM36,0) -> 0 | DH36: =IF($CU36="UNHESA",$BD36+$BM36+$BV36+$CE36+$CN36,0) -> 0 | DI36: =IF($CU36="UNHESA",$BE36+$BN36+$BW36+$CF36+$CO36,0) -> 0 | DJ36: =IF($CU36="UNHESA",$BF36+$BO36+$BX36+$CG36+$CP36,0) -> 0 | DK36: =IF($CU36="UNHESA",$BG36+$BP36+$BY36+$CH36+$CQ36,0) -> 0 | DL36: =IF($CU36="UNHESA",$BH36+$BQ36+$BZ36+$CI36+$CR36,0) -> 0 | DM36: =SUM(DE36:DL36)-DG36-DI36 -> 0 | DN36: =IF($CU36="UNHESA LIQUIDOS",$BA36+$BJ36+$BS36+$CB36+$CK36,0) -> 0 | DO36: =IF($CU36="CALIDUL",$BB36+$BK36+$BT36+$CC36+$CL36,0) -> 0 | DP36: =IF($CU36="CALIDUL",$BC36+$BL36+$BU36+$CD36+$CM36,0) -> 0 | DQ36: =IF($CU36="CALIDUL",$BD36+$BM36+$BV36+$CE36+$CN36,0) -> 0 | DR36: =IF($CU36="CALIDUL",$BE36+$BN36+$BW36+$CF36+$CO36,0) -> 0 | DS36: =IF($CU36="CALIDUL",$BF36+$BO36+$BX36+$CG36+$CP36,0) -> 0 | DT36: =IF($CU36="CALIDUL",$BG36+$BP36+$BY36+$CH36+$CQ36,0) -> 0 | DU36: =IF($CU36="CALIDUL",$BH36+$BQ36+$BZ36+$CI36+$CR36,0) -> 0 | DV36: =SUM(DN36:DU36)-DP36-DR36 -> 0 | DW36: =IF($CU36="CLEARTEC",$BA36+$BJ36+$BS36+$CB36+$CK36,0) -> 0 | DX36: =IF($CU36="CLEARTEC",$BA36+$BJ36+$BS36+$CB36+$CK36,0) -> 0 | DY36: =IF($CU36="CLEARTEC",$BA36+$BJ36+$BS36+$CB36+$CK36,0) -> 0 | DZ36: =IF($CU36="CLEARTEC",$BA36+$BJ36+$BS36+$CB36+$CK36,0) -> 0 | EA36: =IF($CU36="CLEARTEC",$BA36+$BJ36+$BS36+$CB36+$CK36,0) -> 0 | EB36: =IF($CU36="CLEARTEC",$BA36+$BJ36+$BS36+$CB36+$CK36,0) -> 0 | EC36: =IF($CU36="CLEARTEC",$BA36+$BJ36+$BS36+$CB36+$CK36,0) -> 0 | ED36: =IF($CU36="CLEARTEC",$BA36+$BJ36+$BS36+$CB36+$CK36,0) -> 0 | EE36: =SUM(DW36:ED36)-DY36-EA36 -> 0 | EF36: =IF(CU36="ECONACIONAL",$BA36+$BJ36+$BS36+$CB36+$CK36) -> 4200 | EG36: =IF($CU36="ECONACIONAL",$BB36+$BK36+$BT36+$CC36+$CL36,0) -> 250 | EH36: =IF(CU36="ECONACIONAL",$BC36+$BL36+$BU36+$CD36+$CM36) -> 0 | EI36: =IF(CU36="ECONACIONAL",$BD36+$DH36+$DQ36+$DZ36+BM36+BV36+CE36+CN36) -> 0 | EJ36: =IF($CU36="CLEARTEC",$BE36+$BN36+$BW36+$CF36+$CO36,0) -> 0 | EK36: =IF(CU36="ECONACIONAL",$BF36+$BO36+$BX36+$CG36+$CP36) -> 0 | EL36: =IF(CU36="ECONACIONAL",$BG36+$BP36+$BY36+$CH36+$CQ36) -> 0 | EM36: =IF(CU36="ECONACIONAL",BH36+BQ36+BZ36+CI36+CR36) -> 532.14 | EN36: =SUM(EF36:EM36)-EH36-EJ36 -> 4982.14 | EY36: =+ET36+EU36+EV36 -> 0 | FA36: =IF($M36<=15,EP36/2,EP36) -> 0 | FB36: =IF($M36<=15,EQ36/2,EQ36) -> 0 | FC36: =IF($M36<=15,ER36/2,ER36) -> 0 | FD36: =IF($M36<=15,ES36/2,ES36) -> 0 | FE36: =IF($M36<=15,ET36/2,ET36) -> 0 | FF36: =IF($M36<=15,EU36/2,EU36) -> 0 | FG36: =IF($M36<=15,EV36/2,EV36) -> 0 | FH36: =IF($M36<=15,EW36/2,EW36) -> 0 | ... FJ36: =IF($M36<=15,EY36/2,EY36) -> 0 | FK36: 0.75 | FL36: 0.25 | FM36: 0 | FN36: 0 | FO36: 0 | FP36: 1 | FR36: =(((J36/30/8)*1.5)*(U36+Y36+AC36))-(BD36+BM36+BV36) -> 0 | FS36: =(((J36/30/8)*2)*(W36+AA36+AE36))-(BF36+BO36+BX36) -> 0 | FT36: =(SUM(BA36:CJ36))-(SUM(EF36:EN36)) -> 0 | FU36: =(J36/30*M36)-(EF36) -> 0 | FV36: =(SUM(EP36:EY36))-((SUM(FA36:FJ36))*$FV$5) -> 0
E37: 105010 | G37: Apen Escalante Ami Adriana | H37: Asistente de Auditoria Interna | I37: ECONACIONAL | J37: 4500 | K37: 500 | L37: =+J37+K37 -> 5000 | M37: 30 | N37: 0.5 | O37: 0.35 | P37: 0.05 | Q37: 0.1 | R37: 0 | S37: =SUM(N37:R37) -> 1 | V37: =($J37/30/8*1.5)*U37 -> 0 | X37: =($J37/30/8*2)*W37 -> 0 | Z37: =($J37/30/8*1.5)*Y37 -> 0 | AB37: =($J37/30/8*2)*AA37 -> 0 | AD37: =(($J37/30/8)*1.5)*AC37 -> 0 | AF37: =(($J37/30/8)*2)*AE37 -> 0 | AH37: =(($J37/30/8)*1.5)*AG37 -> 0 | AJ37: =(($J37/30/8)*2)*AI37 -> 0 | AL37: =(($J37/30/8)*1.5)*AK37 -> 0 | AN37: =(($J37/30/8)*2)*AM37 -> 0 | BA37: =((J37/30)*M37)*$N37 -> 2250 | BB37: =((K37/30)*M37)*$N37 -> 250 | BC37: =U37 -> 0 | BD37: =V37 -> 0 | BE37: =W37 -> 0 | BF37: =X37 -> 0 | BG37: =AO37+AT37 -> 0 | BH37: =(BA37+BD37+BF37+BG37)*0.1267 -> 285.075 | BI37: =SUM(BA37:BH37)-BC37-BE37 -> 2785.075 | BJ37: =(($J37/30)*$M37)*$O37 -> 1575 | BK37: =(($K37/30)*$M37)*$O37 -> 175 | BL37: =Y37 -> 0 | BM37: =Z37 -> 0 | BN37: =AA37 -> 0 | BO37: =AB37 -> 0 | BP37: =AP37+AU37 -> 0 | BQ37: =(+BJ37+BM37+BO37+BP37)*0.1267 -> 199.5525 | BR37: =SUM(BJ37:BQ37)-BL37-BN37 -> 1949.5525 | BS37: =(($J37/30)*$M37)*$P37 -> 225 | BT37: =(($K37/30)*$M37)*$P37 -> 25 | BU37: =AC37 -> 0 | BV37: =AD37 -> 0 | BW37: =AE37 -> 0 | BX37: =AF37 -> 0 | BY37: =AQ37+AV37 -> 0 | BZ37: =(BS37+BV37+BX37+BY37)*0.1267 -> 28.5075 | CA37: =SUM(BS37:BZ37)-BU37-BW37 -> 278.5075 | CB37: =(($J37/30)*$M37)*$Q37 -> 450 | CC37: =(($K37/30)*$M37)*$Q37 -> 50 | CD37: =AG37 -> 0 | CE37: =AH37 -> 0 | CF37: =AI37 -> 0 | CG37: =AJ37 -> 0 | CH37: =AR37+AW37 -> 0 | CI37: =(CB37+CE37+CG37+CH37)*0.1267 -> 57.015 | CJ37: =SUM(CB37:CI37)-CD37-CF37 -> 557.015 | CK37: =(($J37/30)*$M37)*R37 -> 0 | CL37: =(($K37/30)*$M37)*$R37 -> 0 | CM37: =+AK37 -> 0 | CN37: =AL37 -> 0 | CO37: =AM37 -> 0 | CP37: =AN37 -> 0 | CQ37: =AS37+AX37 -> 0 | CR37: =(CK37+CN37+CP37)*0.1267 -> 0 | CS37: =SUM(CK37:CR37)-CM37-CO37 -> 0 | CU37: ECONACIONAL | CV37: =IF($CU37="PROQUIMA",$BA37+$BJ37+$BS37+$CB37+$CK37,0) -> 0 | CW37: =IF($CU37="PROQUIMA",$BB37+$BK37+$BT37+$CC37+$CL37,0) -> 0 | CX37: =IF($CU37="PROQUIMA",$BC37+$BL37+$BU37+$CD37+$CM37,0) -> 0 | CY37: =IF($CU37="PROQUIMA",$BD37+$BM37+$BV37+$CE37+$CN37,0) -> 0 | CZ37: =IF($CU37="PROQUIMA",$BE37+$BN37+$BW37+$CF37+$CO37,0) -> 0 | DA37: =IF($CU37="PROQUIMA",$BF37+$BO37+$BX37+$CG37+$CP37,0) -> 0 | DB37: =IF($CU37="PROQUIMA",$BG37+$BP37+$BY37+$CH37+$CQ37,0) -> 0 | DC37: =IF($CU37="PROQUIMA",$BH37+$BQ37+$BZ37+$CI37+CR37,0) -> 0 | DD37: =SUM(CV37:DC37)-CX37-CZ37 -> 0 | DE37: =IF($CU37="UNHESA",$BA37+$BJ37+$BS37+$CB37+$CK37,0) -> 0 | DF37: =IF($CU37="UNHESA",$BB37+$BK37+$BT37+$CC37+$CL37,0) -> 0 | DG37: =IF($CU37="UNHESA",$BC37+$BL37+$BU37+$CD37+$CM37,0) -> 0 | DH37: =IF($CU37="UNHESA",$BD37+$BM37+$BV37+$CE37+$CN37,0) -> 0 | DI37: =IF($CU37="UNHESA",$BE37+$BN37+$BW37+$CF37+$CO37,0) -> 0 | DJ37: =IF($CU37="UNHESA",$BF37+$BO37+$BX37+$CG37+$CP37,0) -> 0 | DK37: =IF($CU37="UNHESA",$BG37+$BP37+$BY37+$CH37+$CQ37,0) -> 0 | DL37: =IF($CU37="UNHESA",$BH37+$BQ37+$BZ37+$CI37+$CR37,0) -> 0 | DM37: =SUM(DE37:DL37)-DG37-DI37 -> 0 | DN37: =IF($CU37="UNHESA LIQUIDOS",$BA37+$BJ37+$BS37+$CB37+$CK37,0) -> 0 | DO37: =IF($CU37="CALIDUL",$BB37+$BK37+$BT37+$CC37+$CL37,0) -> 0 | DP37: =IF($CU37="CALIDUL",$BC37+$BL37+$BU37+$CD37+$CM37,0) -> 0 | DQ37: =IF($CU37="CALIDUL",$BD37+$BM37+$BV37+$CE37+$CN37,0) -> 0 | DR37: =IF($CU37="CALIDUL",$BE37+$BN37+$BW37+$CF37+$CO37,0) -> 0 | DS37: =IF($CU37="CALIDUL",$BF37+$BO37+$BX37+$CG37+$CP37,0) -> 0 | DT37: =IF($CU37="CALIDUL",$BG37+$BP37+$BY37+$CH37+$CQ37,0) -> 0 | DU37: =IF($CU37="CALIDUL",$BH37+$BQ37+$BZ37+$CI37+$CR37,0) -> 0 | DV37: =SUM(DN37:DU37)-DP37-DR37 -> 0 | DW37: =IF($CU37="CLEARTEC",$BA37+$BJ37+$BS37+$CB37+$CK37,0) -> 0 | DX37: =IF($CU37="CLEARTEC",$BA37+$BJ37+$BS37+$CB37+$CK37,0) -> 0 | DY37: =IF($CU37="CLEARTEC",$BA37+$BJ37+$BS37+$CB37+$CK37,0) -> 0 | DZ37: =IF($CU37="CLEARTEC",$BA37+$BJ37+$BS37+$CB37+$CK37,0) -> 0 | EA37: =IF($CU37="CLEARTEC",$BA37+$BJ37+$BS37+$CB37+$CK37,0) -> 0 | EB37: =IF($CU37="CLEARTEC",$BA37+$BJ37+$BS37+$CB37+$CK37,0) -> 0 | EC37: =IF($CU37="CLEARTEC",$BA37+$BJ37+$BS37+$CB37+$CK37,0) -> 0 | ED37: =IF($CU37="CLEARTEC",$BA37+$BJ37+$BS37+$CB37+$CK37,0) -> 0 | EE37: =SUM(DW37:ED37)-DY37-EA37 -> 0 | EF37: =IF(CU37="ECONACIONAL",$BA37+$BJ37+$BS37+$CB37+$CK37) -> 4500 | EG37: =IF($CU37="ECONACIONAL",$BB37+$BK37+$BT37+$CC37+$CL37,0) -> 500 | EH37: =IF(CU37="ECONACIONAL",$BC37+$BL37+$BU37+$CD37+$CM37) -> 0 | EI37: =IF(CU37="ECONACIONAL",$BD37+$DH37+$DQ37+$DZ37+BM37+BV37+CE37+CN37) -> 0 | EJ37: =IF($CU37="CLEARTEC",$BE37+$BN37+$BW37+$CF37+$CO37,0) -> 0 | EK37: =IF(CU37="ECONACIONAL",$BF37+$BO37+$BX37+$CG37+$CP37) -> 0 | EL37: =IF(CU37="ECONACIONAL",$BG37+$BP37+$BY37+$CH37+$CQ37) -> 0 | EM37: =IF(CU37="ECONACIONAL",BH37+BQ37+BZ37+CI37+CR37) -> 570.15 | EN37: =SUM(EF37:EM37)-EH37-EJ37 -> 5570.15 | EV37: 350 | EY37: =+ET37+EU37+EV37 -> 350 | FA37: =IF($M37<=15,EP37/2,EP37) -> 0 | FB37: =IF($M37<=15,EQ37/2,EQ37) -> 0 | FC37: =IF($M37<=15,ER37/2,ER37) -> 0 | FD37: =IF($M37<=15,ES37/2,ES37) -> 0 | FE37: =IF($M37<=15,ET37/2,ET37) -> 0 | FF37: =IF($M37<=15,EU37/2,EU37) -> 0 | FG37: =IF($M37<=15,EV37/2,EV37) -> 350 | FH37: =IF($M37<=15,EW37/2,EW37) -> 0 | ... FJ37: =IF($M37<=15,EY37/2,EY37) -> 350 | FK37: 0.75 | FL37: 0.25 | FM37: 0 | FN37: 0 | FO37: 0 | FP37: 1 | FR37: =(((J37/30/8)*1.5)*(U37+Y37+AC37))-(BD37+BM37+BV37) -> 0 | FS37: =(((J37/30/8)*2)*(W37+AA37+AE37))-(BF37+BO37+BX37) -> 0 | FT37: =(SUM(BA37:CJ37))-(SUM(EF37:EN37)) -> 0 | FU37: =(J37/30*M37)-(EF37) -> 0 | FV37: =(SUM(EP37:EY37))-((SUM(FA37:FJ37))*$FV$5) -> -700
H38: Total Auditoria | J38: =SUM(J35:J37) -> 16700 | K38: =SUM(K35:K37) -> 4750 | L38: =SUM(L35:L37) -> 21450 | U38: =SUM(U35:U37) -> 0 | V38: =SUM(V35:V37) -> 0 | W38: =SUM(W35:W37) -> 0 | X38: =SUM(X35:X37) -> 0 | Y38: =SUM(Y35:Y37) -> 0 | Z38: =SUM(Z35:Z37) -> 0 | AA38: =SUM(AA35:AA37) -> 0 | AB38: =SUM(AB35:AB37) -> 0 | ... EN38: =SUM(EN35:EN37) -> 23565.89 | EP38: =SUM(EP35:EP37) -> 358.88 | EQ38: =SUM(EQ35:EQ37) -> 0 | ER38: =SUM(ER35:ER37) -> 0 | ES38: =SUM(ES35:ES37) -> 0 | ET38: =SUM(ET35:ET37) -> 0 | EU38: =SUM(EU35:EU37) -> 0 | EV38: =SUM(EV35:EV37) -> 700 | EW38: =SUM(EW35:EW37) -> 0 | ... EY38: =SUM(EY35:EY37) -> 700 | FA38: =SUM(FA35:FA37) -> 358.88 | FB38: =SUM(FB35:FB37) -> 0 | FC38: =SUM(FC35:FC37) -> 0 | FD38: =SUM(FD35:FD37) -> 0 | FE38: =SUM(FE35:FE37) -> 0 | FF38: =SUM(FF35:FF37) -> 0 | FG38: =SUM(FG35:FG37) -> 700 | FH38: =SUM(FH35:FH37) -> 0 | ... FP38: =SUM(FP35:FP37) -> 3
G39: CONTABLE FINANCIERO
A40: =$G$4 -> JUNIO 2026 2da QUINCENA | B40: =+$G$5 -> 2026 | C40: =A40 & B40 -> JUNIO 2026 2da QUINCENA2026 | D40: =+$G$39 -> CONTABLE FINANCIERO | E40: 106010 | G40: Administracion
A41: =$G$4 -> JUNIO 2026 2da QUINCENA | B41: =+$G$5 -> 2026 | C41: =A41 & B41 -> JUNIO 2026 2da QUINCENA2026 | D41: =+$G$39 -> CONTABLE FINANCIERO | E41: 106010 | F41: 16 | G41: Lorenzana Gonzalez Cesar Leonel | H41: Gerente Financiero | I41: ECONACIONAL | J41: 20000 | K41: 7000 | L41: =+J41+K41 -> 27000 | M41: 30 | N41: 0.45 | O41: 0.26 | P41: 0.04 | Q41: 0.25 | R41: 0 | S41: =SUM(N41:R41) -> 1 | V41: =($J41/30/8*1.5)*U41 -> 0 | X41: =($J41/30/8*2)*W41 -> 0 | Z41: =($J41/30/8*1.5)*Y41 -> 0 | AB41: =($J41/30/8*2)*AA41 -> 0 | AD41: =(($J41/30/8)*1.5)*AC41 -> 0 | AF41: =(($J41/30/8)*2)*AE41 -> 0 | AH41: =(($J41/30/8)*1.5)*AG41 -> 0 | AJ41: =(($J41/30/8)*2)*AI41 -> 0 | AL41: =(($J41/30/8)*1.5)*AK41 -> 0 | AN41: =(($J41/30/8)*2)*AM41 -> 0 | BA41: =((J41/30)*M41)*$N41 -> 9000 | BB41: =((K41/30)*M41)*$N41 -> 3150 | BC41: =U41 -> 0 | BD41: =V41 -> 0 | BE41: =W41 -> 0 | BF41: =X41 -> 0 | BG41: =AO41+AT41 -> 0 | BH41: =(BA41+BD41+BF41+BG41)*0.1267 -> 1140.3 | BI41: =SUM(BA41:BH41)-BC41-BE41 -> 13290.3 | BJ41: =(($J41/30)*$M41)*$O41 -> 5200 | BK41: =(($K41/30)*$M41)*$O41 -> 1820 | BL41: =Y41 -> 0 | BM41: =Z41 -> 0 | BN41: =AA41 -> 0 | BO41: =AB41 -> 0 | BP41: =AP41+AU41 -> 0 | BQ41: =(+BJ41+BM41+BO41+BP41)*0.1267 -> 658.84 | BR41: =SUM(BJ41:BQ41)-BL41-BN41 -> 7678.84 | BS41: =(($J41/30)*$M41)*$P41 -> 800 | BT41: =(($K41/30)*$M41)*$P41 -> 280 | BU41: =AC41 -> 0 | BV41: =AD41 -> 0 | BW41: =AE41 -> 0 | BX41: =AF41 -> 0 | BY41: =AQ41+AV41 -> 0 | BZ41: =(BS41+BV41+BX41+BY41)*0.1267 -> 101.36 | CA41: =SUM(BS41:BZ41)-BU41-BW41 -> 1181.36 | CB41: =(($J41/30)*$M41)*$Q41 -> 5000 | CC41: =((($K41/30*$M41)*$Q41)) -> 1750 | CD41: =AG41 -> 0 | CE41: =AH41 -> 0 | CF41: =AI41 -> 0 | CG41: =AJ41 -> 0 | CH41: =AR41+AW41 -> 0 | CI41: =(CB41+CE41+CG41+CH41)*0.1267 -> 633.5 | CJ41: =SUM(CB41:CI41)-CD41-CF41 -> 7383.5 | CK41: =(($J41/30)*$M41)*R41 -> 0 | CL41: =(($K41/30)*$M41)*$R41 -> 0 | CM41: =+AK41 -> 0 | CN41: =AL41 -> 0 | CO41: =AM41 -> 0 | CP41: =AN41 -> 0 | CQ41: =AS41+AX41 -> 0 | CR41: =(CK41+CN41+CP41)*0.1267 -> 0 | CS41: =SUM(CK41:CR41)-CM41-CO41 -> 0 | CU41: ECONACIONAL | CV41: =IF($CU41="PROQUIMA",$BA41+$BJ41+$BS41+$CB41+$CK41,0) -> 0 | CW41: =IF($CU41="PROQUIMA",$BB41+$BK41+$BT41+$CC41+$CL41,0) -> 0 | CX41: =IF($CU41="PROQUIMA",$BC41+$BL41+$BU41+$CD41+$CM41,0) -> 0 | CY41: =IF($CU41="PROQUIMA",$BD41+$BM41+$BV41+$CE41+$CN41,0) -> 0 | CZ41: =IF($CU41="PROQUIMA",$BE41+$BN41+$BW41+$CF41+$CO41,0) -> 0 | DA41: =IF($CU41="PROQUIMA",$BF41+$BO41+$BX41+$CG41+$CP41,0) -> 0 | DB41: =IF($CU41="PROQUIMA",$BG41+$BP41+$BY41+$CH41+$CQ41,0) -> 0 | DC41: =IF($CU41="PROQUIMA",$BH41+$BQ41+$BZ41+$CI41+CR41,0) -> 0 | DD41: =SUM(CV41:DC41)-CX41-CZ41 -> 0 | DE41: =IF($CU41="UNHESA",$BA41+$BJ41+$BS41+$CB41+$CK41,0) -> 0 | DF41: =IF($CU41="UNHESA",$BB41+$BK41+$BT41+$CC41+$CL41,0) -> 0 | DG41: =IF($CU41="UNHESA",$BC41+$BL41+$BU41+$CD41+$CM41,0) -> 0 | DH41: =IF($CU41="UNHESA",$BD41+$BM41+$BV41+$CE41+$CN41,0) -> 0 | DI41: =IF($CU41="UNHESA",$BE41+$BN41+$BW41+$CF41+$CO41,0) -> 0 | DJ41: =IF($CU41="UNHESA",$BF41+$BO41+$BX41+$CG41+$CP41,0) -> 0 | DK41: =IF($CU41="UNHESA",$BG41+$BP41+$BY41+$CH41+$CQ41,0) -> 0 | DL41: =IF($CU41="UNHESA",$BH41+$BQ41+$BZ41+$CI41+$CR41,0) -> 0 | DM41: =SUM(DE41:DL41)-DG41-DI41 -> 0 | DN41: =IF($CU41="UNHESA LIQUIDOS",$BA41+$BJ41+$BS41+$CB41+$CK41,0) -> 0 | DO41: =IF($CU41="CALIDUL",$BB41+$BK41+$BT41+$CC41+$CL41,0) -> 0 | DP41: =IF($CU41="CALIDUL",$BC41+$BL41+$BU41+$CD41+$CM41,0) -> 0 | DQ41: =IF($CU41="CALIDUL",$BD41+$BM41+$BV41+$CE41+$CN41,0) -> 0 | DR41: =IF($CU41="CALIDUL",$BE41+$BN41+$BW41+$CF41+$CO41,0) -> 0 | DS41: =IF($CU41="CALIDUL",$BF41+$BO41+$BX41+$CG41+$CP41,0) -> 0 | DT41: =IF($CU41="CALIDUL",$BG41+$BP41+$BY41+$CH41+$CQ41,0) -> 0 | DU41: =IF($CU41="CALIDUL",$BH41+$BQ41+$BZ41+$CI41+$CR41,0) -> 0 | DV41: =SUM(DN41:DU41)-DP41-DR41 -> 0 | DW41: =IF($CU41="CLEARTEC",$BA41+$BJ41+$BS41+$CB41+$CK41,0) -> 0 | DX41: =IF($CU41="CLEARTEC",$BA41+$BJ41+$BS41+$CB41+$CK41,0) -> 0 | DY41: =IF($CU41="CLEARTEC",$BA41+$BJ41+$BS41+$CB41+$CK41,0) -> 0 | DZ41: =IF($CU41="CLEARTEC",$BA41+$BJ41+$BS41+$CB41+$CK41,0) -> 0 | EA41: =IF($CU41="CLEARTEC",$BA41+$BJ41+$BS41+$CB41+$CK41,0) -> 0 | EB41: =IF($CU41="CLEARTEC",$BA41+$BJ41+$BS41+$CB41+$CK41,0) -> 0 | EC41: =IF($CU41="CLEARTEC",$BA41+$BJ41+$BS41+$CB41+$CK41,0) -> 0 | ED41: =IF($CU41="CLEARTEC",$BA41+$BJ41+$BS41+$CB41+$CK41,0) -> 0 | EE41: =SUM(DW41:ED41)-DY41-EA41 -> 0 | EF41: =IF(CU41="ECONACIONAL",$BA41+$BJ41+$BS41+$CB41+$CK41) -> 20000 | EG41: =IF($CU41="ECONACIONAL",$BB41+$BK41+$BT41+$CC41+$CL41,0) -> 7000 | EH41: =IF(CU41="ECONACIONAL",$BC41+$BL41+$BU41+$CD41+$CM41) -> 0 | EI41: =IF(CU41="ECONACIONAL",$BD41+$DH41+$DQ41+$DZ41+BM41+BV41+CE41+CN41) -> 0 | EJ41: =IF($CU41="CLEARTEC",$BE41+$BN41+$BW41+$CF41+$CO41,0) -> 0 | EK41: =IF(CU41="ECONACIONAL",$BF41+$BO41+$BX41+$CG41+$CP41) -> 0 | EL41: =IF(CU41="ECONACIONAL",$BG41+$BP41+$BY41+$CH41+$CQ41) -> 0 | EM41: =IF(CU41="ECONACIONAL",BH41+BQ41+BZ41+CI41+CR41) -> 2534 | EN41: =SUM(EF41:EM41)-EH41-EJ41 -> 29534 | EP41: 1108.97 | EQ41: 9519.84 | EY41: =+ET41+EU41+EV41 -> 0 | FA41: =IF($M41<=15,EP41/2,EP41) -> 1108.97 | FB41: =IF($M41<=15,EQ41/2,EQ41) -> 9519.84 | FC41: =IF($M41<=15,ER41/2,ER41) -> 0 | FD41: =IF($M41<=15,ES41/2,ES41) -> 0 | FE41: =IF($M41<=15,ET41/2,ET41) -> 0 | FF41: =IF($M41<=15,EU41/2,EU41) -> 0 | FG41: =IF($M41<=15,EV41/2,EV41) -> 0 | FH41: =IF($M41<=15,EW41/2,EW41) -> 0 | ... FJ41: =IF($M41<=15,EY41/2,EY41) -> 0 | FR41: =(((J41/30/8)*1.5)*(U41+Y41+AC41))-(BD41+BM41+BV41) -> 0 | FS41: =(((J41/30/8)*2)*(W41+AA41+AE41))-(BF41+BO41+BX41) -> 0 | FT41: =(SUM(BA41:CJ41))-(SUM(EF41:EN41)) -> 0 | FU41: =(J41/30*M41)-(EF41) -> 0 | FV41: =(SUM(EP41:EY41))-((SUM(FA41:FJ41))*$FV$5) -> -10628.81
E42: 106020 | G42: CONTABILIDAD
A43: =$G$4 -> JUNIO 2026 2da QUINCENA | B43: =+$G$5 -> 2026 | C43: =A43 & B43 -> JUNIO 2026 2da QUINCENA2026 | D43: =+$G$42 -> CONTABILIDAD | E43: 106020 | F43: =+F41+1 -> 17 | G43: Patzan Quib Lucrecia | H43: Jefe de Operaciones Contables | I43: ECONACIONAL | J43: 10500 | K43: 1800 | L43: =+J43+K43 -> 12300 | M43: 30 | N43: 0.57 | O43: 0.3 | P43: 0.03 | Q43: 0.1 | R43: 0 | S43: =SUM(N43:R43) -> 1 | V43: =($J43/30/8*1.5)*U43 -> 0 | X43: =($J43/30/8*2)*W43 -> 0 | Z43: =($J43/30/8*1.5)*Y43 -> 0 | AB43: =($J43/30/8*2)*AA43 -> 0 | AD43: =(($J43/30/8)*1.5)*AC43 -> 0 | AF43: =(($J43/30/8)*2)*AE43 -> 0 | AH43: =(($J43/30/8)*1.5)*AG43 -> 0 | AJ43: =(($J43/30/8)*2)*AI43 -> 0 | AL43: =(($J43/30/8)*1.5)*AK43 -> 0 | AN43: =(($J43/30/8)*2)*AM43 -> 0 | BA43: =((J43/30)*M43)*$N43 -> 5985 | BB43: =((K43/30)*M43)*$N43 -> 1026 | BC43: =U43 -> 0 | BD43: =V43 -> 0 | BE43: =W43 -> 0 | BF43: =X43 -> 0 | BG43: =AO43+AT43 -> 0 | BH43: =(BA43+BD43+BF43+BG43)*0.1267 -> 758.2995 | BI43: =SUM(BA43:BH43)-BC43-BE43 -> 7769.2995 | BJ43: =(($J43/30)*$M43)*$O43 -> 3150 | BK43: =(($K43/30)*$M43)*$O43 -> 540 | BL43: =Y43 -> 0 | BM43: =Z43 -> 0 | BN43: =AA43 -> 0 | BO43: =AB43 -> 0 | BP43: =AP43+AU43 -> 0 | BQ43: =(+BJ43+BM43+BO43+BP43)*0.1267 -> 399.105 | BR43: =SUM(BJ43:BQ43)-BL43-BN43 -> 4089.105 | BS43: =(($J43/30)*$M43)*$P43 -> 315 | BT43: =(($K43/30)*$M43)*$P43 -> 54 | BU43: =AC43 -> 0 | BV43: =AD43 -> 0 | BW43: =AE43 -> 0 | BX43: =AF43 -> 0 | BY43: =AQ43+AV43 -> 0 | BZ43: =(BS43+BV43+BX43+BY43)*0.1267 -> 39.9105 | CA43: =SUM(BS43:BZ43)-BU43-BW43 -> 408.9105 | CB43: =(($J43/30)*$M43)*$Q43 -> 1050 | CC43: =(($K43/30)*$M43)*$Q43 -> 180 | CD43: =AG43 -> 0 | CE43: =AH43 -> 0 | CF43: =AI43 -> 0 | CG43: =AJ43 -> 0 | CH43: =AR43+AW43 -> 0 | CI43: =(CB43+CE43+CG43+CH43)*0.1267 -> 133.035 | CJ43: =SUM(CB43:CI43)-CD43-CF43 -> 1363.035 | CK43: =(($J43/30)*$M43)*R43 -> 0 | CL43: =(($K43/30)*$M43)*$R43 -> 0 | CM43: =+AK43 -> 0 | CN43: =AL43 -> 0 | CO43: =AM43 -> 0 | CP43: =AN43 -> 0 | CQ43: =AS43+AX43 -> 0 | CR43: =(CK43+CN43+CP43)*0.1267 -> 0 | CS43: =SUM(CK43:CR43)-CM43-CO43 -> 0 | CU43: ECONACIONAL | CV43: =IF($CU43="PROQUIMA",$BA43+$BJ43+$BS43+$CB43+$CK43,0) -> 0 | CW43: =IF($CU43="PROQUIMA",$BB43+$BK43+$BT43+$CC43+$CL43,0) -> 0 | CX43: =IF($CU43="PROQUIMA",$BC43+$BL43+$BU43+$CD43+$CM43,0) -> 0 | CY43: =IF($CU43="PROQUIMA",$BD43+$BM43+$BV43+$CE43+$CN43,0) -> 0 | CZ43: =IF($CU43="PROQUIMA",$BE43+$BN43+$BW43+$CF43+$CO43,0) -> 0 | DA43: =IF($CU43="PROQUIMA",$BF43+$BO43+$BX43+$CG43+$CP43,0) -> 0 | DB43: =IF($CU43="PROQUIMA",$BG43+$BP43+$BY43+$CH43+$CQ43,0) -> 0 | DC43: =IF($CU43="PROQUIMA",$BH43+$BQ43+$BZ43+$CI43+CR43,0) -> 0 | DD43: =SUM(CV43:DC43)-CX43-CZ43 -> 0 | DE43: =IF($CU43="UNHESA",$BA43+$BJ43+$BS43+$CB43+$CK43,0) -> 0 | DF43: =IF($CU43="UNHESA",$BB43+$BK43+$BT43+$CC43+$CL43,0) -> 0 | DG43: =IF($CU43="UNHESA",$BC43+$BL43+$BU43+$CD43+$CM43,0) -> 0 | DH43: =IF($CU43="UNHESA",$BD43+$BM43+$BV43+$CE43+$CN43,0) -> 0 | DI43: =IF($CU43="UNHESA",$BE43+$BN43+$BW43+$CF43+$CO43,0) -> 0 | DJ43: =IF($CU43="UNHESA",$BF43+$BO43+$BX43+$CG43+$CP43,0) -> 0 | DK43: 0 | DL43: =IF($CU43="UNHESA",$BH43+$BQ43+$BZ43+$CI43+$CR43,0) -> 0 | DM43: =SUM(DE43:DL43)-DG43-DI43 -> 0 | DN43: =IF($CU43="UNHESA LIQUIDOS",$BA43+$BJ43+$BS43+$CB43+$CK43,0) -> 0 | DO43: =IF($CU43="CALIDUL",$BB43+$BK43+$BT43+$CC43+$CL43,0) -> 0 | DP43: =IF($CU43="CALIDUL",$BC43+$BL43+$BU43+$CD43+$CM43,0) -> 0 | DQ43: =IF($CU43="CALIDUL",$BD43+$BM43+$BV43+$CE43+$CN43,0) -> 0 | DR43: =IF($CU43="CALIDUL",$BE43+$BN43+$BW43+$CF43+$CO43,0) -> 0 | DS43: =IF($CU43="CALIDUL",$BF43+$BO43+$BX43+$CG43+$CP43,0) -> 0 | DT43: =IF($CU43="CALIDUL",$BG43+$BP43+$BY43+$CH43+$CQ43,0) -> 0 | DU43: =IF($CU43="CALIDUL",$BH43+$BQ43+$BZ43+$CI43+$CR43,0) -> 0 | DV43: =SUM(DN43:DU43)-DP43-DR43 -> 0 | DW43: =IF($CU43="CLEARTEC",$BA43+$BJ43+$BS43+$CB43+$CK43,0) -> 0 | DX43: =IF($CU43="CLEARTEC",$BA43+$BJ43+$BS43+$CB43+$CK43,0) -> 0 | DY43: =IF($CU43="CLEARTEC",$BA43+$BJ43+$BS43+$CB43+$CK43,0) -> 0 | DZ43: =IF($CU43="CLEARTEC",$BA43+$BJ43+$BS43+$CB43+$CK43,0) -> 0 | EA43: =IF($CU43="CLEARTEC",$BA43+$BJ43+$BS43+$CB43+$CK43,0) -> 0 | EB43: =IF($CU43="CLEARTEC",$BA43+$BJ43+$BS43+$CB43+$CK43,0) -> 0 | EC43: =IF($CU43="CLEARTEC",$BA43+$BJ43+$BS43+$CB43+$CK43,0) -> 0 | ED43: =IF($CU43="CLEARTEC",$BA43+$BJ43+$BS43+$CB43+$CK43,0) -> 0 | EE43: =SUM(DW43:ED43)-DY43-EA43 -> 0 | EF43: =IF(CU43="ECONACIONAL",$BA43+$BJ43+$BS43+$CB43+$CK43) -> 10500 | EG43: =IF($CU43="ECONACIONAL",$BB43+$BK43+$BT43+$CC43+$CL43,0) -> 1800 | EH43: =IF(CU43="ECONACIONAL",$BC43+$BL43+$BU43+$CD43+$CM43) -> 0 | EI43: =IF(CU43="ECONACIONAL",$BD43+$DH43+$DQ43+$DZ43+BM43+BV43+CE43+CN43) -> 0 | EJ43: =IF($CU43="CLEARTEC",$BE43+$BN43+$BW43+$CF43+$CO43,0) -> 0 | EK43: =IF(CU43="ECONACIONAL",$BF43+$BO43+$BX43+$CG43+$CP43) -> 0 | EL43: =IF(CU43="ECONACIONAL",$BG43+$BP43+$BY43+$CH43+$CQ43) -> 0 | EM43: =IF(CU43="ECONACIONAL",BH43+BQ43+BZ43+CI43+CR43) -> 1330.35 | EN43: =SUM(EF43:EM43)-EH43-EJ43 -> 13630.35 | EO43: 1068 FIN DE MES | EP43: 393.64 | ER43: 200 | EV43: 1068 | EY43: =+ET43+EU43+EV43 -> 1068 | FA43: =IF($M43<=15,EP43/2,EP43) -> 393.64 | FB43: =IF($M43<=15,EQ43/2,EQ43) -> 0 | FC43: =IF($M43<=15,ER43/2,ER43) -> 200 | FD43: =IF($M43<=15,ES43/2,ES43) -> 0 | FE43: =IF($M43<=15,ET43/2,ET43) -> 0 | FF43: =IF($M43<=15,EU43/2,EU43) -> 0 | FG43: =IF($M43<=15,EV43/2,EV43) -> 1068 | FH43: =IF($M43<=15,EW43/2,EW43) -> 0 | ... FJ43: =IF($M43<=15,EY43/2,EY43) -> 1068 | FK43: 0.65 | FL43: 0.35 | FN43: 0 | FO43: 0 | FP43: 1 | FR43: =(((J43/30/8)*1.5)*(U43+Y43+AC43))-(BD43+BM43+BV43) -> 0 | FS43: =(((J43/30/8)*2)*(W43+AA43+AE43))-(BF43+BO43+BX43) -> 0 | FT43: =(SUM(BA43:CJ43))-(SUM(EF43:EN43)) -> 0 | FU43: =(J43/30*M43)-(EF43) -> 0 | FV43: =(SUM(EP43:EY43))-((SUM(FA43:FJ43))*$FV$5) -> -2729.64
E44: 106020 | G44: Sumale Pelen Elio Rene | H44: Contador | I44: ECONACIONAL | J44: 5250 | K44: 1750 | L44: =+J44+K44 -> 7000 | M44: 30 | N44: 0.5 | O44: 0.4 | P44: 0 | Q44: 0.1 | R44: 0 | S44: =SUM(N44:R44) -> 1 | T44: A.13/4/2026 incremento de 500 en oct 26 y 500 en abril 2027 | V44: =($J44/30/8*1.5)*U44 -> 0 | X44: =($J44/30/8*2)*W44 -> 0 | Z44: =($J44/30/8*1.5)*Y44 -> 0 | AB44: =($J44/30/8*2)*AA44 -> 0 | AC44: 0 | AD44: =(($J44/30/8)*1.5)*AC44 -> 0 | AF44: =(($J44/30/8)*2)*AE44 -> 0 | AH44: =(($J44/30/8)*1.5)*AG44 -> 0 | AJ44: =(($J44/30/8)*2)*AI44 -> 0 | AL44: =(($J44/30/8)*1.5)*AK44 -> 0 | AN44: =(($J44/30/8)*2)*AM44 -> 0 | BA44: =((J44/30)*M44)*$N44 -> 2625 | BB44: =((K44/30)*M44)*$N44 -> 875 | BC44: =U44 -> 0 | BD44: =V44 -> 0 | BE44: =W44 -> 0 | BF44: =X44 -> 0 | BG44: =AO44+AT44 -> 0 | BH44: =(BA44+BD44+BF44+BG44)*0.1267 -> 332.5875 | BI44: =SUM(BA44:BH44)-BC44-BE44 -> 3832.5875 | BJ44: =(($J44/30)*$M44)*$O44 -> 2100 | BK44: =(($K44/30)*$M44)*$O44 -> 700 | BL44: =Y44 -> 0 | BM44: =Z44 -> 0 | BN44: =AA44 -> 0 | BO44: =AB44 -> 0 | BP44: =AP44+AU44 -> 0 | BQ44: =(+BJ44+BM44+BO44+BP44)*0.1267 -> 266.07 | BR44: =SUM(BJ44:BQ44)-BL44-BN44 -> 3066.07 | BS44: =(($J44/30)*$M44)*$P44 -> 0 | BT44: =(($K44/30)*$M44)*$P44 -> 0 | BU44: =AC44 -> 0 | BV44: =AD44 -> 0 | BW44: =AE44 -> 0 | BX44: =AF44 -> 0 | BY44: =AQ44+AV44 -> 0 | BZ44: =(BS44+BV44+BX44+BY44)*0.1267 -> 0 | CA44: =SUM(BS44:BZ44)-BU44-BW44 -> 0 | CB44: =(($J44/30)*$M44)*$Q44 -> 525 | CC44: =(($K44/30)*$M44)*$Q44 -> 175 | CD44: =AG44 -> 0 | CE44: =AH44 -> 0 | CF44: =AI44 -> 0 | CG44: =AJ44 -> 0 | CH44: =AR44+AW44 -> 0 | CI44: =(CB44+CE44+CG44+CH44)*0.1267 -> 66.5175 | CJ44: =SUM(CB44:CI44)-CD44-CF44 -> 766.5175 | CK44: =(($J44/30)*$M44)*R44 -> 0 | CL44: =(($K44/30)*$M44)*$R44 -> 0 | CM44: =+AK44 -> 0 | CN44: =AL44 -> 0 | CO44: =AM44 -> 0 | CP44: =AN44 -> 0 | CQ44: =AS44+AX44 -> 0 | CR44: =(CK44+CN44+CP44)*0.1267 -> 0 | CS44: =SUM(CK44:CR44)-CM44-CO44 -> 0 | CU44: ECONACIONAL | CV44: =IF($CU44="PROQUIMA",$BA44+$BJ44+$BS44+$CB44+$CK44,0) -> 0 | CW44: =IF($CU44="PROQUIMA",$BB44+$BK44+$BT44+$CC44+$CL44,0) -> 0 | CX44: =IF($CU44="PROQUIMA",$BC44+$BL44+$BU44+$CD44+$CM44,0) -> 0 | CY44: =IF($CU44="PROQUIMA",$BD44+$BM44+$BV44+$CE44+$CN44,0) -> 0 | CZ44: =IF($CU44="PROQUIMA",$BE44+$BN44+$BW44+$CF44+$CO44,0) -> 0 | DA44: =IF($CU44="PROQUIMA",$BF44+$BO44+$BX44+$CG44+$CP44,0) -> 0 | DB44: =IF($CU44="PROQUIMA",$BG44+$BP44+$BY44+$CH44+$CQ44,0) -> 0 | DC44: =IF($CU44="PROQUIMA",$BH44+$BQ44+$BZ44+$CI44+CR44,0) -> 0 | DD44: =SUM(CV44:DC44)-CX44-CZ44 -> 0 | DE44: =IF($CU44="UNHESA",$BA44+$BJ44+$BS44+$CB44+$CK44,0) -> 0 | DF44: =IF($CU44="UNHESA",$BB44+$BK44+$BT44+$CC44+$CL44,0) -> 0 | DG44: =IF($CU44="UNHESA",$BC44+$BL44+$BU44+$CD44+$CM44,0) -> 0 | DH44: =IF($CU44="UNHESA",$BD44+$BM44+$BV44+$CE44+$CN44,0) -> 0 | DI44: =IF($CU44="UNHESA",$BE44+$BN44+$BW44+$CF44+$CO44,0) -> 0 | DJ44: =IF($CU44="UNHESA",$BF44+$BO44+$BX44+$CG44+$CP44,0) -> 0 | DK44: =IF($CU44="UNHESA",$BG44+$BP44+$BY44+$CH44+$CQ44,0) -> 0 | DL44: =IF($CU44="UNHESA",$BH44+$BQ44+$BZ44+$CI44+$CR44,0) -> 0 | DM44: =SUM(DE44:DL44)-DG44-DI44 -> 0 | DN44: =IF($CU44="UNHESA LIQUIDOS",$BA44+$BJ44+$BS44+$CB44+$CK44,0) -> 0 | DO44: =IF($CU44="CALIDUL",$BB44+$BK44+$BT44+$CC44+$CL44,0) -> 0 | DP44: =IF($CU44="CALIDUL",$BC44+$BL44+$BU44+$CD44+$CM44,0) -> 0 | DQ44: =IF($CU44="CALIDUL",$BD44+$BM44+$BV44+$CE44+$CN44,0) -> 0 | DR44: =IF($CU44="CALIDUL",$BE44+$BN44+$BW44+$CF44+$CO44,0) -> 0 | DS44: =IF($CU44="CALIDUL",$BF44+$BO44+$BX44+$CG44+$CP44,0) -> 0 | DT44: =IF($CU44="CALIDUL",$BG44+$BP44+$BY44+$CH44+$CQ44,0) -> 0 | DU44: =IF($CU44="CALIDUL",$BH44+$BQ44+$BZ44+$CI44+$CR44,0) -> 0 | DV44: =SUM(DN44:DU44)-DP44-DR44 -> 0 | DW44: =IF($CU44="CLEARTEC",$BA44+$BJ44+$BS44+$CB44+$CK44,0) -> 0 | DX44: =IF($CU44="CLEARTEC",$BA44+$BJ44+$BS44+$CB44+$CK44,0) -> 0 | DY44: =IF($CU44="CLEARTEC",$BA44+$BJ44+$BS44+$CB44+$CK44,0) -> 0 | DZ44: =IF($CU44="CLEARTEC",$BA44+$BJ44+$BS44+$CB44+$CK44,0) -> 0 | EA44: =IF($CU44="CLEARTEC",$BA44+$BJ44+$BS44+$CB44+$CK44,0) -> 0 | EB44: =IF($CU44="CLEARTEC",$BA44+$BJ44+$BS44+$CB44+$CK44,0) -> 0 | EC44: =IF($CU44="CLEARTEC",$BA44+$BJ44+$BS44+$CB44+$CK44,0) -> 0 | ED44: =IF($CU44="CLEARTEC",$BA44+$BJ44+$BS44+$CB44+$CK44,0) -> 0 | EE44: =SUM(DW44:ED44)-DY44-EA44 -> 0 | EF44: =IF(CU44="ECONACIONAL",$BA44+$BJ44+$BS44+$CB44+$CK44) -> 5250 | EG44: =IF($CU44="ECONACIONAL",$BB44+$BK44+$BT44+$CC44+$CL44,0) -> 1750 | EH44: =IF(CU44="ECONACIONAL",$BC44+$BL44+$BU44+$CD44+$CM44) -> 0 | EI44: =IF(CU44="ECONACIONAL",$BD44+$DH44+$DQ44+$DZ44+BM44+BV44+CE44+CN44) -> 0 | EJ44: =IF($CU44="CLEARTEC",$BE44+$BN44+$BW44+$CF44+$CO44,0) -> 0 | EK44: =IF(CU44="ECONACIONAL",$BF44+$BO44+$BX44+$CG44+$CP44) -> 0 | EL44: =IF(CU44="ECONACIONAL",$BG44+$BP44+$BY44+$CH44+$CQ44) -> 0 | EM44: =IF(CU44="ECONACIONAL",BH44+BQ44+BZ44+CI44+CR44) -> 665.175 | EN44: =SUM(EF44:EM44)-EH44-EJ44 -> 7665.175 | EY44: =+ET44+EU44+EV44 -> 0 | FA44: =IF($M44<=15,EP44/2,EP44) -> 0 | FB44: =IF($M44<=15,EQ44/2,EQ44) -> 0 | FC44: =IF($M44<=15,ER44/2,ER44) -> 0 | FD44: =IF($M44<=15,ES44/2,ES44) -> 0 | FE44: =IF($M44<=15,ET44/2,ET44) -> 0 | FF44: =IF($M44<=15,EU44/2,EU44) -> 0 | FG44: =IF($M44<=15,EV44/2,EV44) -> 0 | FH44: =IF($M44<=15,EW44/2,EW44) -> 0 | ... FJ44: =IF($M44<=15,EY44/2,EY44) -> 0 | FK44: 1 | FL44: 0 | FM44: 0 | FN44: 0 | FO44: 0 | FP44: 1 | FR44: =(((J44/30/8)*1.5)*(U44+Y44+AC44))-(BD44+BM44+BV44) -> 0 | FS44: =(((J44/30/8)*2)*(W44+AA44+AE44))-(BF44+BO44+BX44) -> 0 | FT44: =(SUM(BA44:CJ44))-(SUM(EF44:EN44)) -> 0 | FU44: =(J44/30*M44)-(EF44) -> 0 | FV44: =(SUM(EP44:EY44))-((SUM(FA44:FJ44))*$FV$5) -> 0
A45: =$G$4 -> JUNIO 2026 2da QUINCENA | B45: =+$G$5 -> 2026 | C45: =A45 & B45 -> JUNIO 2026 2da QUINCENA2026 | D45: =+$G$42 -> CONTABILIDAD | E45: 106020 | F45: =+#REF!+1 -> #REF! | G45: Gonzalez Torres Tadeo Felix David | H45: Contador General | I45: ECONACIONAL | J45: 6000 | K45: 3000 | L45: =+J45+K45 -> 9000 | M45: 30 | N45: 0.45 | O45: 0.5 | P45: 0.05 | Q45: 0 | R45: 0 | S45: =SUM(N45:R45) -> 1 | V45: =($J45/30/8*1.5)*U45 -> 0 | X45: =($J45/30/8*2)*W45 -> 0 | Z45: =($J45/30/8*1.5)*Y45 -> 0 | AB45: =($J45/30/8*2)*AA45 -> 0 | AC45: 0 | AD45: =(($J45/30/8)*1.5)*AC45 -> 0 | AF45: =(($J45/30/8)*2)*AE45 -> 0 | AH45: =(($J45/30/8)*1.5)*AG45 -> 0 | AJ45: =(($J45/30/8)*2)*AI45 -> 0 | AL45: =(($J45/30/8)*1.5)*AK45 -> 0 | AN45: =(($J45/30/8)*2)*AM45 -> 0 | BA45: =((J45/30)*M45)*$N45 -> 2700 | BB45: =((K45/30)*M45)*$N45+450 -> 1800 | BC45: =U45 -> 0 | BD45: =V45 -> 0 | BE45: =W45 -> 0 | BF45: =X45 -> 0 | BG45: =AO45+AT45 -> 0 | BH45: =(BA45+BD45+BF45+BG45)*0.1267 -> 342.09 | BI45: =SUM(BA45:BH45)-BC45-BE45 -> 4842.09 | BJ45: =(($J45/30)*$M45)*$O45 -> 3000 | BK45: =(($K45/30)*$M45)*$O45+450 -> 1950 | BL45: =Y45 -> 0 | BM45: =Z45 -> 0 | BN45: =AA45 -> 0 | BO45: =AB45 -> 0 | BP45: =AP45+AU45 -> 0 | BQ45: =(+BJ45+BM45+BO45+BP45)*0.1267 -> 380.1 | BR45: =SUM(BJ45:BQ45)-BL45-BN45 -> 5330.1 | BS45: =(($J45/30)*$M45)*$P45 -> 300 | BT45: =(($K45/30)*$M45)*$P45+100 -> 250 | BU45: =AC45 -> 0 | BV45: =AD45 -> 0 | BW45: =AE45 -> 0 | BX45: =AF45 -> 0 | BY45: =AQ45+AV45 -> 0 | BZ45: =(BS45+BV45+BX45+BY45)*0.1267 -> 38.01 | CA45: =SUM(BS45:BZ45)-BU45-BW45 -> 588.01 | CB45: =(($J45/30)*$M45)*$Q45 -> 0 | CC45: =(($K45/30)*$M45)*$Q45 -> 0 | CD45: =AG45 -> 0 | CE45: =AH45 -> 0 | CF45: =AI45 -> 0 | CG45: =AJ45 -> 0 | CH45: =AR45+AW45 -> 0 | CI45: =(CB45+CE45+CG45+CH45)*0.1267 -> 0 | CJ45: =SUM(CB45:CI45)-CD45-CF45 -> 0 | CK45: =(($J45/30)*$M45)*R45 -> 0 | CL45: =(($K45/30)*$M45)*$R45 -> 0 | CM45: =+AK45 -> 0 | CN45: =AL45 -> 0 | CO45: =AM45 -> 0 | CP45: =AN45 -> 0 | CQ45: =AS45+AX45 -> 0 | CR45: =(CK45+CN45+CP45)*0.1267 -> 0 | CS45: =SUM(CK45:CR45)-CM45-CO45 -> 0 | CU45: ECONACIONAL | CV45: =IF($CU45="PROQUIMA",$BA45+$BJ45+$BS45+$CB45+$CK45,0) -> 0 | CW45: =IF($CU45="PROQUIMA",$BB45+$BK45+$BT45+$CC45+$CL45,0) -> 0 | CX45: =IF($CU45="PROQUIMA",$BC45+$BL45+$BU45+$CD45+$CM45,0) -> 0 | CY45: =IF($CU45="PROQUIMA",$BD45+$BM45+$BV45+$CE45+$CN45,0) -> 0 | CZ45: =IF($CU45="PROQUIMA",$BE45+$BN45+$BW45+$CF45+$CO45,0) -> 0 | DA45: =IF($CU45="PROQUIMA",$BF45+$BO45+$BX45+$CG45+$CP45,0) -> 0 | DB45: =IF($CU45="PROQUIMA",$BG45+$BP45+$BY45+$CH45+$CQ45,0) -> 0 | DC45: =IF($CU45="PROQUIMA",$BH45+$BQ45+$BZ45+$CI45+CR45,0) -> 0 | DD45: =SUM(CV45:DC45)-CX45-CZ45 -> 0 | DE45: =IF($CU45="UNHESA",$BA45+$BJ45+$BS45+$CB45+$CK45,0) -> 0 | DF45: =IF($CU45="UNHESA",$BB45+$BK45+$BT45+$CC45+$CL45,0) -> 0 | DG45: =IF($CU45="UNHESA",$BC45+$BL45+$BU45+$CD45+$CM45,0) -> 0 | DH45: =IF($CU45="UNHESA",$BD45+$BM45+$BV45+$CE45+$CN45,0) -> 0 | DI45: =IF($CU45="UNHESA",$BE45+$BN45+$BW45+$CF45+$CO45,0) -> 0 | DJ45: =IF($CU45="UNHESA",$BF45+$BO45+$BX45+$CG45+$CP45,0) -> 0 | DK45: =IF($CU45="UNHESA",$BG45+$BP45+$BY45+$CH45+$CQ45,0) -> 0 | DL45: =IF($CU45="UNHESA",$BH45+$BQ45+$BZ45+$CI45+$CR45,0) -> 0 | DM45: =SUM(DE45:DL45)-DG45-DI45 -> 0 | DN45: =IF($CU45="UNHESA LIQUIDOS",$BA45+$BJ45+$BS45+$CB45+$CK45,0) -> 0 | DO45: =IF($CU45="CALIDUL",$BB45+$BK45+$BT45+$CC45+$CL45,0) -> 0 | DP45: =IF($CU45="CALIDUL",$BC45+$BL45+$BU45+$CD45+$CM45,0) -> 0 | DQ45: =IF($CU45="CALIDUL",$BD45+$BM45+$BV45+$CE45+$CN45,0) -> 0 | DR45: =IF($CU45="CALIDUL",$BE45+$BN45+$BW45+$CF45+$CO45,0) -> 0 | DS45: =IF($CU45="CALIDUL",$BF45+$BO45+$BX45+$CG45+$CP45,0) -> 0 | DT45: =IF($CU45="CALIDUL",$BG45+$BP45+$BY45+$CH45+$CQ45,0) -> 0 | DU45: =IF($CU45="CALIDUL",$BH45+$BQ45+$BZ45+$CI45+$CR45,0) -> 0 | DV45: =SUM(DN45:DU45)-DP45-DR45 -> 0 | DW45: =IF($CU45="CLEARTEC",$BA45+$BJ45+$BS45+$CB45+$CK45,0) -> 0 | DX45: =IF($CU45="CLEARTEC",$BA45+$BJ45+$BS45+$CB45+$CK45,0) -> 0 | DY45: =IF($CU45="CLEARTEC",$BA45+$BJ45+$BS45+$CB45+$CK45,0) -> 0 | DZ45: =IF($CU45="CLEARTEC",$BA45+$BJ45+$BS45+$CB45+$CK45,0) -> 0 | EA45: =IF($CU45="CLEARTEC",$BA45+$BJ45+$BS45+$CB45+$CK45,0) -> 0 | EB45: =IF($CU45="CLEARTEC",$BA45+$BJ45+$BS45+$CB45+$CK45,0) -> 0 | EC45: =IF($CU45="CLEARTEC",$BA45+$BJ45+$BS45+$CB45+$CK45,0) -> 0 | ED45: =IF($CU45="CLEARTEC",$BA45+$BJ45+$BS45+$CB45+$CK45,0) -> 0 | EE45: =SUM(DW45:ED45)-DY45-EA45 -> 0 | EF45: =IF(CU45="ECONACIONAL",$BA45+$BJ45+$BS45+$CB45+$CK45) -> 6000 | EG45: =IF($CU45="ECONACIONAL",$BB45+$BK45+$BT45+$CC45+$CL45,0) -> 4000 | EH45: =IF(CU45="ECONACIONAL",$BC45+$BL45+$BU45+$CD45+$CM45) -> 0 | EI45: =IF(CU45="ECONACIONAL",$BD45+$DH45+$DQ45+$DZ45+BM45+BV45+CE45+CN45) -> 0 | EJ45: =IF($CU45="CLEARTEC",$BE45+$BN45+$BW45+$CF45+$CO45,0) -> 0 | EK45: =IF(CU45="ECONACIONAL",$BF45+$BO45+$BX45+$CG45+$CP45) -> 0 | EL45: =IF(CU45="ECONACIONAL",$BG45+$BP45+$BY45+$CH45+$CQ45) -> 0 | EM45: =IF(CU45="ECONACIONAL",BH45+BQ45+BZ45+CI45+CR45) -> 760.2 | EN45: =SUM(EF45:EM45)-EH45-EJ45 -> 10760.2 | EP45: 289.94 | EV45: 350 | EY45: =+ET45+EU45+EV45 -> 350 | FA45: =IF($M45<=15,EP45/2,EP45) -> 289.94 | FB45: =IF($M45<=15,EQ45/2,EQ45) -> 0 | FC45: =IF($M45<=15,ER45/2,ER45) -> 0 | FD45: =IF($M45<=15,ES45/2,ES45) -> 0 | FE45: =IF($M45<=15,ET45/2,ET45) -> 0 | FF45: =IF($M45<=15,EU45/2,EU45) -> 0 | FG45: =IF($M45<=15,EV45/2,EV45) -> 350 | FH45: =IF($M45<=15,EW45/2,EW45) -> 0 | ... FJ45: =IF($M45<=15,EY45/2,EY45) -> 350 | FR45: =(((J45/30/8)*1.5)*(U45+Y45+AC45))-(BD45+BM45+BV45) -> 0 | FS45: =(((J45/30/8)*2)*(W45+AA45+AE45))-(BF45+BO45+BX45) -> 0 | FT45: =(SUM(BA45:CJ45))-(SUM(EF45:EN45)) -> 0 | FU45: =(J45/30*M45)-(EF45) -> 0 | FV45: =(SUM(EP45:EY45))-((SUM(FA45:FJ45))*$FV$5) -> -989.94
E46: 106020 | G46: Perez Rivera Yoselyn Carolina | H46: Auxiliar Contable (digitador) | I46: ECONACIONAL | J46: 4002.28 | K46: 405.16 | L46: =+J46+K46 -> 4407.44 | M46: 30 | N46: 0.43 | O46: 0.42 | P46: 0.15 | Q46: 0 | R46: 0 | S46: =SUM(N46:R46) -> 1 | V46: =($J46/30/8*1.5)*U46 -> 0 | X46: =($J46/30/8*2)*W46 -> 0 | Z46: =($J46/30/8*1.5)*Y46 -> 0 | AB46: =($J46/30/8*2)*AA46 -> 0 | AC46: 0 | AD46: =(($J46/30/8)*1.5)*AC46 -> 0 | AF46: =(($J46/30/8)*2)*AE46 -> 0 | AH46: =(($J46/30/8)*1.5)*AG46 -> 0 | AJ46: =(($J46/30/8)*2)*AI46 -> 0 | AL46: =(($J46/30/8)*1.5)*AK46 -> 0 | AN46: =(($J46/30/8)*2)*AM46 -> 0 | BA46: =((J46/30)*M46)*$N46 -> 1720.9804 | BB46: =((K46/30)*M46)*$N46 -> 174.2188 | BC46: =U46 -> 0 | BD46: =V46 -> 0 | BE46: =W46 -> 0 | BF46: =X46 -> 0 | BG46: =AO46+AT46 -> 0 | BH46: =(BA46+BD46+BF46+BG46)*0.1267 -> 218.04822 | BI46: =SUM(BA46:BH46)-BC46-BE46 -> 2113.2474 | BJ46: =(($J46/30)*$M46)*$O46 -> 1680.9576 | BK46: =(($K46/30)*$M46)*$O46 -> 170.1672 | BL46: =Y46 -> 0 | BM46: =Z46 -> 0 | BN46: =AA46 -> 0 | BO46: =AB46 -> 0 | BP46: =AP46+AU46 -> 0 | BQ46: =(+BJ46+BM46+BO46+BP46)*0.1267 -> 212.97733 | BR46: =SUM(BJ46:BQ46)-BL46-BN46 -> 2064.1021 | BS46: =(($J46/30)*$M46)*$P46 -> 600.342 | BT46: =(($K46/30)*$M46)*$P46 -> 60.774 | BU46: =AC46 -> 0 | BV46: =AD46 -> 0 | BW46: =AE46 -> 0 | BX46: =AF46 -> 0 | BY46: =AQ46+AV46 -> 0 | BZ46: =(BS46+BV46+BX46+BY46)*0.1267 -> 76.063331 | CA46: =SUM(BS46:BZ46)-BU46-BW46 -> 737.17933 | CB46: =(($J46/30)*$M46)*$Q46 -> 0 | CC46: =(($K46/30)*$M46)*$Q46 -> 0 | CD46: =AG46 -> 0 | CE46: =AH46 -> 0 | CF46: =AI46 -> 0 | CG46: =AJ46 -> 0 | CH46: =AR46+AW46 -> 0 | CI46: =(CB46+CE46+CG46+CH46)*0.1267 -> 0 | CJ46: =SUM(CB46:CI46)-CD46-CF46 -> 0 | CK46: =(($J46/30)*$M46)*R46 -> 0 | CL46: =(($K46/30)*$M46)*$R46 -> 0 | CM46: =+AK46 -> 0 | CN46: =AL46 -> 0 | CO46: =AM46 -> 0 | CP46: =AN46 -> 0 | CQ46: =AS46+AX46 -> 0 | CR46: =(CK46+CN46+CP46)*0.1267 -> 0 | CS46: =SUM(CK46:CR46)-CM46-CO46 -> 0 | CU46: ECONACIONAL | CV46: =IF($CU46="PROQUIMA",$BA46+$BJ46+$BS46+$CB46+$CK46,0) -> 0 | CW46: =IF($CU46="PROQUIMA",$BB46+$BK46+$BT46+$CC46+$CL46,0) -> 0 | CX46: =IF($CU46="PROQUIMA",$BC46+$BL46+$BU46+$CD46+$CM46,0) -> 0 | CY46: =IF($CU46="PROQUIMA",$BD46+$BM46+$BV46+$CE46+$CN46,0) -> 0 | CZ46: =IF($CU46="PROQUIMA",$BE46+$BN46+$BW46+$CF46+$CO46,0) -> 0 | DA46: =IF($CU46="PROQUIMA",$BF46+$BO46+$BX46+$CG46+$CP46,0) -> 0 | DB46: =IF($CU46="PROQUIMA",$BG46+$BP46+$BY46+$CH46+$CQ46,0) -> 0 | DC46: =IF($CU46="PROQUIMA",$BH46+$BQ46+$BZ46+$CI46+CR46,0) -> 0 | DD46: =SUM(CV46:DC46)-CX46-CZ46 -> 0 | DE46: =IF($CU46="UNHESA",$BA46+$BJ46+$BS46+$CB46+$CK46,0) -> 0 | DF46: =IF($CU46="UNHESA",$BB46+$BK46+$BT46+$CC46+$CL46,0) -> 0 | DG46: =IF($CU46="UNHESA",$BC46+$BL46+$BU46+$CD46+$CM46,0) -> 0 | DH46: =IF($CU46="UNHESA",$BD46+$BM46+$BV46+$CE46+$CN46,0) -> 0 | DI46: =IF($CU46="UNHESA",$BE46+$BN46+$BW46+$CF46+$CO46,0) -> 0 | DJ46: =IF($CU46="UNHESA",$BF46+$BO46+$BX46+$CG46+$CP46,0) -> 0 | DK46: =IF($CU46="UNHESA",$BG46+$BP46+$BY46+$CH46+$CQ46,0) -> 0 | DL46: =IF($CU46="UNHESA",$BH46+$BQ46+$BZ46+$CI46+$CR46,0) -> 0 | DM46: =SUM(DE46:DL46)-DG46-DI46 -> 0 | DN46: =IF($CU46="UNHESA LIQUIDOS",$BA46+$BJ46+$BS46+$CB46+$CK46,0) -> 0 | DO46: =IF($CU46="CALIDUL",$BB46+$BK46+$BT46+$CC46+$CL46,0) -> 0 | DP46: =IF($CU46="CALIDUL",$BC46+$BL46+$BU46+$CD46+$CM46,0) -> 0 | DQ46: =IF($CU46="CALIDUL",$BD46+$BM46+$BV46+$CE46+$CN46,0) -> 0 | DR46: =IF($CU46="CALIDUL",$BE46+$BN46+$BW46+$CF46+$CO46,0) -> 0 | DS46: =IF($CU46="CALIDUL",$BF46+$BO46+$BX46+$CG46+$CP46,0) -> 0 | DT46: =IF($CU46="CALIDUL",$BG46+$BP46+$BY46+$CH46+$CQ46,0) -> 0 | DU46: =IF($CU46="CALIDUL",$BH46+$BQ46+$BZ46+$CI46+$CR46,0) -> 0 | DV46: =SUM(DN46:DU46)-DP46-DR46 -> 0 | DW46: =IF($CU46="CLEARTEC",$BA46+$BJ46+$BS46+$CB46+$CK46,0) -> 0 | DX46: =IF($CU46="CLEARTEC",$BA46+$BJ46+$BS46+$CB46+$CK46,0) -> 0 | DY46: =IF($CU46="CLEARTEC",$BA46+$BJ46+$BS46+$CB46+$CK46,0) -> 0 | DZ46: =IF($CU46="CLEARTEC",$BA46+$BJ46+$BS46+$CB46+$CK46,0) -> 0 | EA46: =IF($CU46="CLEARTEC",$BA46+$BJ46+$BS46+$CB46+$CK46,0) -> 0 | EB46: =IF($CU46="CLEARTEC",$BA46+$BJ46+$BS46+$CB46+$CK46,0) -> 0 | EC46: =IF($CU46="CLEARTEC",$BA46+$BJ46+$BS46+$CB46+$CK46,0) -> 0 | ED46: =IF($CU46="CLEARTEC",$BA46+$BJ46+$BS46+$CB46+$CK46,0) -> 0 | EE46: =SUM(DW46:ED46)-DY46-EA46 -> 0 | EF46: =IF(CU46="ECONACIONAL",$BA46+$BJ46+$BS46+$CB46+$CK46) -> 4002.28 | EG46: =IF($CU46="ECONACIONAL",$BB46+$BK46+$BT46+$CC46+$CL46,0) -> 405.16 | EH46: =IF(CU46="ECONACIONAL",$BC46+$BL46+$BU46+$CD46+$CM46) -> 0 | EI46: =IF(CU46="ECONACIONAL",$BD46+$DH46+$DQ46+$DZ46+BM46+BV46+CE46+CN46) -> 0 | EJ46: =IF($CU46="CLEARTEC",$BE46+$BN46+$BW46+$CF46+$CO46,0) -> 0 | EK46: =IF(CU46="ECONACIONAL",$BF46+$BO46+$BX46+$CG46+$CP46) -> 0 | EL46: =IF(CU46="ECONACIONAL",$BG46+$BP46+$BY46+$CH46+$CQ46) -> 0 | EM46: =IF(CU46="ECONACIONAL",BH46+BQ46+BZ46+CI46+CR46) -> 507.08888 | EN46: =SUM(EF46:EM46)-EH46-EJ46 -> 4914.5289 | EY46: =+ET46+EU46+EV46 -> 0 | FA46: =IF($M46<=15,EP46/2,EP46) -> 0 | FB46: =IF($M46<=15,EQ46/2,EQ46) -> 0 | FC46: =IF($M46<=15,ER46/2,ER46) -> 0 | FD46: =IF($M46<=15,ES46/2,ES46) -> 0 | FE46: =IF($M46<=15,ET46/2,ET46) -> 0 | FF46: =IF($M46<=15,EU46/2,EU46) -> 0 | FG46: =IF($M46<=15,EV46/2,EV46) -> 0 | FH46: =IF($M46<=15,EW46/2,EW46) -> 0 | ... FJ46: =IF($M46<=15,EY46/2,EY46) -> 0 | FR46: =(((J46/30/8)*1.5)*(U46+Y46+AC46))-(BD46+BM46+BV46) -> 0 | FS46: =(((J46/30/8)*2)*(W46+AA46+AE46))-(BF46+BO46+BX46) -> 0 | FT46: =(SUM(BA46:CJ46))-(SUM(EF46:EN46)) -> 0 | FU46: =(J46/30*M46)-(EF46) -> 0 | FV46: =(SUM(EP46:EY46))-((SUM(FA46:FJ46))*$FV$5) -> 0
H48: Contabilidad y Finanzas | J48: =SUM(J41:J47) -> 45752.28 | K48: =SUM(K41:K47) -> 13955.16 | L48: =SUM(L41:L47) -> 59707.44 | U48: =SUM(U41:U47) -> 0 | V48: =SUM(V41:V47) -> 0 | W48: =SUM(W41:W47) -> 0 | X48: =SUM(X41:X47) -> 0 | Y48: =SUM(Y41:Y47) -> 0 | Z48: =SUM(Z41:Z47) -> 0 | AA48: =SUM(AA41:AA47) -> 0 | AB48: =SUM(AB41:AB47) -> 0 | ... EN48: =SUM(EN41:EN47) -> 66504.254 | EP48: =SUM(EP41:EP47) -> 1792.55 | EQ48: =SUM(EQ41:EQ47) -> 9519.84 | ER48: =SUM(ER41:ER47) -> 200 | ES48: =SUM(ES41:ES47) -> 0 | ET48: =SUM(ET41:ET47) -> 0 | EU48: =SUM(EU41:EU47) -> 0 | EV48: =SUM(EV41:EV47) -> 1418 | EW48: =SUM(EW41:EW47) -> 0 | ... EY48: =SUM(EY41:EY47) -> 1418 | FA48: =SUM(FA41:FA47) -> 1792.55 | FB48: =SUM(FB41:FB47) -> 9519.84 | FC48: =SUM(FC41:FC47) -> 200 | FD48: =SUM(FD41:FD47) -> 0 | FE48: =SUM(FE41:FE47) -> 0 | FF48: =SUM(FF41:FF47) -> 0 | FG48: =SUM(FG41:FG47) -> 1418 | FH48: =SUM(FH41:FH47) -> 0 | ... FJ48: =SUM(FJ41:FJ47) -> 1418
A49: =$G$4 -> JUNIO 2026 2da QUINCENA | B49: =+$G$5 -> 2026 | C49: =A49 & B49 -> JUNIO 2026 2da QUINCENA2026 | E49: 106030 | G49: TESORERIA
E50: 106030 | F50: 22 | G50: Cruz Salguero Aramis Antonio | H50: Tesorero-Contador | I50: ECONACIONAL | J50: 4850 | K50: 900 | L50: =+J50+K50 -> 5750 | M50: 30 | N50: 0.45 | O50: 0.45 | P50: 0.05 | Q50: 0.05 | R50: 0 | S50: =SUM(N50:R50) -> 1 | V50: =($F50/30/8*1.5)*U50 -> 0 | X50: =($F50/30/8*2)*W50 -> 0 | Z50: =($F50/30/8*1.5)*Y50 -> 0 | AB50: =($F50/30/8*2)*AA50 -> 0 | AC50: 0 | AD50: =(($F50/30/8)*1.5)*AC50 -> 0 | AF50: =(($F50/30/8)*2)*AE50 -> 0 | AH50: =(($F50/30/8)*1.5)*AG50 -> 0 | AJ50: =(($F50/30/8)*2)*AI50 -> 0 | AL50: =(($F50/30/8)*1.5)*AK50 -> 0 | AN50: =(($F50/30/8)*2)*AM50 -> 0 | BA50: =((J50/30)*M50)*$N50 -> 2182.5 | BB50: =((K50/30)*M50)*$N50+450 -> 855 | BC50: =U50 -> 0 | BD50: =V50 -> 0 | BE50: =W50 -> 0 | BF50: =X50 -> 0 | BG50: =AO50+AT50 -> 0 | BH50: =(BA50+BD50+BF50+BG50)*0.1267 -> 276.52275 | BI50: =SUM(BA50:BH50)-BC50-BE50 -> 3314.0228 | BJ50: =(($J50/30)*$M50)*$O50 -> 2182.5 | BK50: =(($K50/30)*$M50)*$O50+450 -> 855 | BL50: =Y50 -> 0 | BM50: =Z50 -> 0 | BN50: =AA50 -> 0 | BO50: =AB50 -> 0 | BP50: =AP50+AU50 -> 0 | BQ50: =(+BJ50+BM50+BO50+BP50)*0.1267 -> 276.52275 | BR50: =SUM(BJ50:BQ50)-BL50-BN50 -> 3314.0228 | BS50: =(($J50/30)*$M50)*$P50 -> 242.5 | BT50: =(($K50/30)*$M50)*$P50+50 -> 95 | BU50: =AC50 -> 0 | BV50: =AD50 -> 0 | BW50: =AE50 -> 0 | BX50: =AF50 -> 0 | BY50: =AQ50+AV50 -> 0 | BZ50: =(BS50+BV50+BX50+BY50)*0.1267 -> 30.72475 | CA50: =SUM(BS50:BZ50)-BU50-BW50 -> 368.22475 | CB50: =(($J50/30)*$M50)*$Q50 -> 242.5 | CC50: =(($K50/30)*$M50)*$Q50+50 -> 95 | CD50: =AG50 -> 0 | CE50: =AH50 -> 0 | CF50: =AI50 -> 0 | CG50: =AJ50 -> 0 | CH50: =AR50+AW50 -> 0 | CI50: =(CB50+CE50+CG50+CH50)*0.1267 -> 30.72475 | CJ50: =SUM(CB50:CI50)-CD50-CF50 -> 368.22475 | CK50: =(($J50/30)*$M50)*R50 -> 0 | CL50: =(($K50/30)*$M50)*$R50 -> 0 | CM50: =+AK50 -> 0 | CN50: =AL50 -> 0 | CO50: =AM50 -> 0 | CP50: =AN50 -> 0 | CQ50: =AS50+AX50 -> 0 | CR50: =(CK50+CN50+CP50)*0.1267 -> 0 | CS50: =SUM(CK50:CR50)-CM50-CO50 -> 0 | CU50: ECONACIONAL | CV50: =IF($CU50="PROQUIMA",$BA50+$BJ50+$BS50+$CB50+$CK50,0) -> 0 | CW50: =IF($CU50="PROQUIMA",$BB50+$BK50+$BT50+$CC50+$CL50,0) -> 0 | CX50: =IF($CU50="PROQUIMA",$BC50+$BL50+$BU50+$CD50+$CM50,0) -> 0 | CY50: =IF($CU50="PROQUIMA",$BD50+$BM50+$BV50+$CE50+$CN50,0) -> 0 | CZ50: =IF($CU50="PROQUIMA",$BE50+$BN50+$BW50+$CF50+$CO50,0) -> 0 | DA50: =IF($CU50="PROQUIMA",$BF50+$BO50+$BX50+$CG50+$CP50,0) -> 0 | DB50: =IF($CU50="PROQUIMA",$BG50+$BP50+$BY50+$CH50+$CQ50,0) -> 0 | DC50: =IF($CU50="PROQUIMA",$BH50+$BQ50+$BZ50+$CI50+CR50,0) -> 0 | DD50: =SUM(CV50:DC50)-CX50-CZ50 -> 0 | DE50: =IF($CU50="UNHESA",$BA50+$BJ50+$BS50+$CB50+$CK50,0) -> 0 | DF50: =IF($CU50="UNHESA",$BB50+$BK50+$BT50+$CC50+$CL50,0) -> 0 | DG50: =IF($CU50="UNHESA",$BC50+$BL50+$BU50+$CD50+$CM50,0) -> 0 | DH50: =IF($CU50="UNHESA",$BD50+$BM50+$BV50+$CE50+$CN50,0) -> 0 | DI50: =IF($CU50="UNHESA",$BE50+$BN50+$BW50+$CF50+$CO50,0) -> 0 | DJ50: =IF($CU50="UNHESA",$BF50+$BO50+$BX50+$CG50+$CP50,0) -> 0 | DK50: =IF($CU50="UNHESA",$BG50+$BP50+$BY50+$CH50+$CQ50,0) -> 0 | DL50: =IF($CU50="UNHESA",$BH50+$BQ50+$BZ50+$CI50+$CR50,0) -> 0 | DM50: =SUM(DE50:DL50)-DG50-DI50 -> 0 | DN50: =IF($CU50="UNHESA LIQUIDOS",$BA50+$BJ50+$BS50+$CB50+$CK50,0) -> 0 | DO50: =IF($CU50="CALIDUL",$BB50+$BK50+$BT50+$CC50+$CL50,0) -> 0 | DP50: =IF($CU50="CALIDUL",$BC50+$BL50+$BU50+$CD50+$CM50,0) -> 0 | DQ50: =IF($CU50="CALIDUL",$BD50+$BM50+$BV50+$CE50+$CN50,0) -> 0 | DR50: =IF($CU50="CALIDUL",$BE50+$BN50+$BW50+$CF50+$CO50,0) -> 0 | DS50: =IF($CU50="CALIDUL",$BF50+$BO50+$BX50+$CG50+$CP50,0) -> 0 | DT50: =IF($CU50="CALIDUL",$BG50+$BP50+$BY50+$CH50+$CQ50,0) -> 0 | DU50: =IF($CU50="CALIDUL",$BH50+$BQ50+$BZ50+$CI50+$CR50,0) -> 0 | DV50: =SUM(DN50:DU50)-DP50-DR50 -> 0 | DW50: =IF($CU50="CLEARTEC",$BA50+$BJ50+$BS50+$CB50+$CK50,0) -> 0 | DX50: =IF($CU50="CLEARTEC",$BA50+$BJ50+$BS50+$CB50+$CK50,0) -> 0 | DY50: =IF($CU50="CLEARTEC",$BA50+$BJ50+$BS50+$CB50+$CK50,0) -> 0 | DZ50: =IF($CU50="CLEARTEC",$BA50+$BJ50+$BS50+$CB50+$CK50,0) -> 0 | EA50: =IF($CU50="CLEARTEC",$BA50+$BJ50+$BS50+$CB50+$CK50,0) -> 0 | EB50: =IF($CU50="CLEARTEC",$BA50+$BJ50+$BS50+$CB50+$CK50,0) -> 0 | EC50: =IF($CU50="CLEARTEC",$BA50+$BJ50+$BS50+$CB50+$CK50,0) -> 0 | ED50: =IF($CU50="CLEARTEC",$BA50+$BJ50+$BS50+$CB50+$CK50,0) -> 0 | EE50: =SUM(DW50:ED50)-DY50-EA50 -> 0 | EF50: =IF(CU50="ECONACIONAL",$BA50+$BJ50+$BS50+$CB50+$CK50) -> 4850 | EG50: =IF($CU50="ECONACIONAL",$BB50+$BK50+$BT50+$CC50+$CL50,0) -> 1900 | EH50: =IF(CU50="ECONACIONAL",$BC50+$BL50+$BU50+$CD50+$CM50) -> 0 | EI50: =IF(CU50="ECONACIONAL",$BD50+$DH50+$DQ50+$DZ50+BM50+BV50+CE50+CN50) -> 0 | EJ50: =IF($CU50="CLEARTEC",$BE50+$BN50+$BW50+$CF50+$CO50,0) -> 0 | EK50: =IF(CU50="ECONACIONAL",$BF50+$BO50+$BX50+$CG50+$CP50) -> 0 | EL50: =IF(CU50="ECONACIONAL",$BG50+$BP50+$BY50+$CH50+$CQ50) -> 0 | EM50: =IF(CU50="ECONACIONAL",BH50+BQ50+BZ50+CI50+CR50) -> 614.495 | EN50: =SUM(EF50:EM50)-EH50-EJ50 -> 7364.495 | EP50: 141.36 | ES50: =299+223 -> 522 | EV50: 350 | EY50: =+ET50+EU50+EV50 -> 350 | FA50: =IF($M50<=15,EP50/2,EP50) -> 141.36 | FB50: =IF($M50<=15,EQ50/2,EQ50) -> 0 | FC50: =IF($M50<=15,ER50/2,ER50) -> 0 | FD50: =IF($M50<=15,ES50/2,ES50) -> 522 | FE50: =IF($M50<=15,ET50/2,ET50) -> 0 | FF50: =IF($M50<=15,EU50/2,EU50) -> 0 | FG50: =IF($M50<=15,EV50/2,EV50) -> 350 | FH50: =IF($M50<=15,EW50/2,EW50) -> 0 | ... FJ50: =IF($M50<=15,EY50/2,EY50) -> 350 | FR50: =(((J50/30/8)*1.5)*(U50+Y50+AC50))-(BD50+BM50+BV50) -> 0 | FS50: =(((J50/30/8)*2)*(W50+AA50+AE50))-(BF50+BO50+BX50) -> 0 | FT50: =(SUM(BA50:CJ50))-(SUM(EF50:EN50)) -> 0 | FU50: =(J50/30*M50)-(EF50) -> 0 | FV50: =(SUM(EP50:EY50))-((SUM(FA50:FJ50))*$FV$5) -> -1363.36
H51: Tesoreria | J51: =+J50 -> 4850 | K51: =+K50 -> 900 | L51: =+L50 -> 5750 | U51: =+U50 -> 0 | V51: =+V50 -> 0 | W51: =+W50 -> 0 | X51: =+X50 -> 0 | Y51: =+Y50 -> 0 | Z51: =+Z50 -> 0 | AA51: =+AA50 -> 0 | AB51: =+AB50 -> 0 | ... EN51: =+EN50 -> 7364.495 | EP51: =+EP50 -> 141.36 | EQ51: =+EQ50 -> 0 | ER51: =+ER50 -> 0 | ES51: =+ES50 -> 522 | ET51: =+ET50 -> 0 | EU51: =+EU50 -> 0 | EV51: =+EV50 -> 350 | EW51: =+EW50 -> 0 | ... EY51: =+EY50 -> 350 | FA51: =+FA50 -> 141.36 | FB51: =+FB50 -> 0 | FC51: =+FC50 -> 0 | FD51: =+FD50 -> 522 | FE51: =+FE50 -> 0 | FF51: =+FF50 -> 0 | FG51: =+FG50 -> 350 | FH51: =+FH50 -> 0 | ... FJ51: =+FJ50 -> 350
A52: =$G$4 -> JUNIO 2026 2da QUINCENA | B52: =+$G$5 -> 2026 | C52: =A52 & B52 -> JUNIO 2026 2da QUINCENA2026 | E52: 106050 | G52: LEGAL
A53: =$G$4 -> JUNIO 2026 2da QUINCENA | B53: =+$G$5 -> 2026 | C53: =A53 & B53 -> JUNIO 2026 2da QUINCENA2026 | D53: =+$G$52 -> LEGAL | E53: 106050 | F53: 23 | G53: Cuello Pirir Jorge Renato | H53: Asistente Legal Administrativo | I53: ECONACIONAL | J53: 4500 | K53: 2000 | L53: =+J53+K53 -> 6500 | M53: 30 | N53: 0.5 | O53: 0.42 | P53: 0.03 | Q53: 0.05 | R53: 0 | S53: =SUM(N53:R53) -> 1 | V53: =($J53/30/8*1.5)*U53 -> 0 | X53: =($J53/30/8*2)*W53 -> 0 | Z53: =($J53/30/8*1.5)*Y53 -> 0 | AB53: =($J53/30/8*2)*AA53 -> 0 | AD53: =(($J53/30/8)*1.5)*AC53 -> 0 | AF53: =(($J53/30/8)*2)*AE53 -> 0 | AH53: =(($J53/30/8)*1.5)*AG53 -> 0 | AJ53: =(($J53/30/8)*2)*AI53 -> 0 | AL53: =(($J53/30/8)*1.5)*AK53 -> 0 | AN53: =(($J53/30/8)*2)*AM53 -> 0 | BA53: =((J53/30)*M53)*$N53 -> 2250 | BB53: =((K53/30)*M53)*$N53+250 -> 1250 | BC53: =U53 -> 0 | BD53: =V53 -> 0 | BE53: =W53 -> 0 | BF53: =X53 -> 0 | BG53: =AO53+AT53 -> 0 | BH53: =(BA53+BD53+BF53+BG53)*0.1267 -> 285.075 | BI53: =SUM(BA53:BH53)-BC53-BE53 -> 3785.075 | BJ53: =(($J53/30)*$M53)*$O53 -> 1890 | BK53: =(($K53/30)*$M53)*$O53+210 -> 1050 | BL53: =Y53 -> 0 | BM53: =Z53 -> 0 | BN53: =AA53 -> 0 | BO53: =AB53 -> 0 | BP53: =AP53+AU53 -> 0 | BQ53: =(+BJ53+BM53+BO53+BP53)*0.1267 -> 239.463 | BR53: =SUM(BJ53:BQ53)-BL53-BN53 -> 3179.463 | BS53: =(($J53/30)*$M53)*$P53 -> 135 | BT53: =(($K53/30)*$M53)*$P53+15 -> 75 | BU53: =AC53 -> 0 | BV53: =AD53 -> 0 | BW53: =AE53 -> 0 | BX53: =AF53 -> 0 | BY53: =AQ53+AV53 -> 0 | BZ53: =(BS53+BV53+BX53+BY53)*0.1267 -> 17.1045 | CA53: =SUM(BS53:BZ53)-BU53-BW53 -> 227.1045 | CB53: =(($J53/30)*$M53)*$Q53 -> 225 | CC53: =(($K53/30)*$M53)*$Q53+25 -> 125 | CD53: =AG53 -> 0 | CE53: =AH53 -> 0 | CF53: =AI53 -> 0 | CG53: =AJ53 -> 0 | CH53: =AR53+AW53 -> 0 | CI53: =(CB53+CE53+CG53+CH53)*0.1267 -> 28.5075 | CJ53: =SUM(CB53:CI53)-CD53-CF53 -> 378.5075 | CK53: =(($J53/30)*$M53)*R53 -> 0 | CL53: =(($K53/30)*$M53)*$R53 -> 0 | CM53: =+AK53 -> 0 | CN53: =AL53 -> 0 | CO53: =AM53 -> 0 | CP53: =AN53 -> 0 | CQ53: =AS53+AX53 -> 0 | CR53: =(CK53+CN53+CP53)*0.1267 -> 0 | CS53: =SUM(CK53:CR53)-CM53-CO53 -> 0 | CU53: ECONACIONAL | CV53: =IF($CU53="PROQUIMA",$BA53+$BJ53+$BS53+$CB53+$CK53,0) -> 0 | CW53: =IF($CU53="PROQUIMA",$BB53+$BK53+$BT53+$CC53+$CL53,0) -> 0 | CX53: =IF($CU53="PROQUIMA",$BC53+$BL53+$BU53+$CD53+$CM53,0) -> 0 | CY53: =IF($CU53="PROQUIMA",$BD53+$BM53+$BV53+$CE53+$CN53,0) -> 0 | CZ53: =IF($CU53="PROQUIMA",$BE53+$BN53+$BW53+$CF53+$CO53,0) -> 0 | DA53: =IF($CU53="PROQUIMA",$BF53+$BO53+$BX53+$CG53+$CP53,0) -> 0 | DB53: =IF($CU53="PROQUIMA",$BG53+$BP53+$BY53+$CH53+$CQ53,0) -> 0 | DC53: =IF($CU53="PROQUIMA",$BH53+$BQ53+$BZ53+$CI53+CR53,0) -> 0 | DD53: =SUM(CV53:DC53)-CX53-CZ53 -> 0 | DE53: =IF($CU53="UNHESA",$BA53+$BJ53+$BS53+$CB53+$CK53,0) -> 0 | DF53: =IF($CU53="UNHESA",$BB53+$BK53+$BT53+$CC53+$CL53,0) -> 0 | DG53: =IF($CU53="UNHESA",$BC53+$BL53+$BU53+$CD53+$CM53,0) -> 0 | DH53: =IF($CU53="UNHESA",$BD53+$BM53+$BV53+$CE53+$CN53,0) -> 0 | DI53: =IF($CU53="UNHESA",$BE53+$BN53+$BW53+$CF53+$CO53,0) -> 0 | DJ53: =IF($CU53="UNHESA",$BF53+$BO53+$BX53+$CG53+$CP53,0) -> 0 | DK53: =IF($CU53="UNHESA",$BG53+$BP53+$BY53+$CH53+$CQ53,0) -> 0 | DL53: =IF($CU53="UNHESA",$BH53+$BQ53+$BZ53+$CI53+$CR53,0) -> 0 | DM53: =SUM(DE53:DL53)-DG53-DI53 -> 0 | DN53: =IF($CU53="UNHESA LIQUIDOS",$BA53+$BJ53+$BS53+$CB53+$CK53,0) -> 0 | DO53: =IF($CU53="CALIDUL",$BB53+$BK53+$BT53+$CC53+$CL53,0) -> 0 | DP53: =IF($CU53="CALIDUL",$BC53+$BL53+$BU53+$CD53+$CM53,0) -> 0 | DQ53: =IF($CU53="CALIDUL",$BD53+$BM53+$BV53+$CE53+$CN53,0) -> 0 | DR53: =IF($CU53="CALIDUL",$BE53+$BN53+$BW53+$CF53+$CO53,0) -> 0 | DS53: =IF($CU53="CALIDUL",$BF53+$BO53+$BX53+$CG53+$CP53,0) -> 0 | DT53: =IF($CU53="CALIDUL",$BG53+$BP53+$BY53+$CH53+$CQ53,0) -> 0 | DU53: =IF($CU53="CALIDUL",$BH53+$BQ53+$BZ53+$CI53+$CR53,0) -> 0 | DV53: =SUM(DN53:DU53)-DP53-DR53 -> 0 | DW53: =IF($CU53="CLEARTEC",$BA53+$BJ53+$BS53+$CB53+$CK53,0) -> 0 | DX53: =IF($CU53="CLEARTEC",$BA53+$BJ53+$BS53+$CB53+$CK53,0) -> 0 | DY53: =IF($CU53="CLEARTEC",$BA53+$BJ53+$BS53+$CB53+$CK53,0) -> 0 | DZ53: =IF($CU53="CLEARTEC",$BA53+$BJ53+$BS53+$CB53+$CK53,0) -> 0 | EA53: =IF($CU53="CLEARTEC",$BA53+$BJ53+$BS53+$CB53+$CK53,0) -> 0 | EB53: =IF($CU53="CLEARTEC",$BA53+$BJ53+$BS53+$CB53+$CK53,0) -> 0 | EC53: =IF($CU53="CLEARTEC",$BA53+$BJ53+$BS53+$CB53+$CK53,0) -> 0 | ED53: =IF($CU53="CLEARTEC",$BA53+$BJ53+$BS53+$CB53+$CK53,0) -> 0 | EE53: =SUM(DW53:ED53)-DY53-EA53 -> 0 | EF53: =IF(CU53="ECONACIONAL",$BA53+$BJ53+$BS53+$CB53+$CK53) -> 4500 | EG53: =IF($CU53="ECONACIONAL",$BB53+$BK53+$BT53+$CC53+$CL53,0) -> 2500 | EH53: =IF(CU53="ECONACIONAL",$BC53+$BL53+$BU53+$CD53+$CM53) -> 0 | EI53: =IF(CU53="ECONACIONAL",$BD53+$DH53+$DQ53+$DZ53+BM53+BV53+CE53+CN53) -> 0 | EJ53: =IF($CU53="CLEARTEC",$BE53+$BN53+$BW53+$CF53+$CO53,0) -> 0 | EK53: =IF(CU53="ECONACIONAL",$BF53+$BO53+$BX53+$CG53+$CP53) -> 0 | EL53: =IF(CU53="ECONACIONAL",$BG53+$BP53+$BY53+$CH53+$CQ53) -> 0 | EM53: =IF(CU53="ECONACIONAL",BH53+BQ53+BZ53+CI53+CR53) -> 570.15 | EN53: =SUM(EF53:EM53)-EH53-EJ53 -> 7570.15 | EO53: 251.16 | EP53: 161.31 | EY53: =+ET53+EU53+EV53 -> 0 | FA53: =IF($M53<=15,EP53/2,EP53) -> 161.31 | FB53: =IF($M53<=15,EQ53/2,EQ53) -> 0 | FC53: =IF($M53<=15,ER53/2,ER53) -> 0 | FD53: =IF($M53<=15,ES53/2,ES53) -> 0 | FE53: =IF($M53<=15,ET53/2,ET53) -> 0 | FF53: =IF($M53<=15,EU53/2,EU53) -> 0 | FG53: =IF($M53<=15,EV53/2,EV53) -> 0 | FH53: =IF($M53<=15,EW53/2,EW53) -> 0 | ... FJ53: =IF($M53<=15,EY53/2,EY53) -> 0 | FR53: =(((J53/30/8)*1.5)*(U53+Y53+AC53))-(BD53+BM53+BV53) -> 0 | FS53: =(((J53/30/8)*2)*(W53+AA53+AE53))-(BF53+BO53+BX53) -> 0 | FT53: =(SUM(BA53:CJ53))-(SUM(EF53:EN53)) -> 0 | FU53: =(J53/30*M53)-(EF53) -> 0 | FV53: =(SUM(EP53:EY53))-((SUM(FA53:FJ53))*$FV$5) -> -161.31
H54: Créditos y cobros | J54: =+J53 -> 4500 | K54: =+K53 -> 2000 | L54: =+L53 -> 6500 | U54: =+U53 -> 0 | V54: =+V53 -> 0 | W54: =+W53 -> 0 | X54: =+X53 -> 0 | Y54: =+Y53 -> 0 | Z54: =+Z53 -> 0 | AA54: =+AA53 -> 0 | AB54: =+AB53 -> 0 | ... EN54: =+EN53 -> 7570.15 | EP54: =+EP53 -> 161.31 | EQ54: =+EQ53 -> 0 | ER54: =+ER53 -> 0 | ES54: =+ES53 -> 0 | ET54: =+ET53 -> 0 | EU54: =+EU53 -> 0 | EV54: =+EV53 -> 0 | EW54: =+EW53 -> 0 | ... EY54: =+EY53 -> 0 | FA54: =+FA53 -> 161.31 | FB54: =+FB53 -> 0 | FC54: =+FC53 -> 0 | FD54: =+FD53 -> 0 | FE54: =+FE53 -> 0 | FF54: =+FF53 -> 0 | FG54: =+FG53 -> 0 | FH54: =+FH53 -> 0 | ... FJ54: =+FJ53 -> 0
A55: =$G$4 -> JUNIO 2026 2da QUINCENA | B55: =+$G$5 -> 2026 | C55: =A55 & B55 -> JUNIO 2026 2da QUINCENA2026 | E55: 106060 | G55: COSTOS Y PRESUPUESTOS
E56: 106060 | F56: 24 | G56: Ordoñez Corado Paola Maritza | H56: Analista Financiera | I56: ECONACIONAL | J56: 6500 | K56: 3500 | L56: =+J56+K56 -> 10000 | M56: 30 | N56: 0.55 | O56: 0.35 | P56: 0.05 | Q56: 0.05 | R56: 0 | S56: =SUM(N56:R56) -> 1 | V56: =($J56/30/8*1.5)*U56 -> 0 | X56: =($J56/30/8*2)*W56 -> 0 | Z56: =($J56/30/8*1.5)*Y56 -> 0 | AB56: =($J56/30/8*2)*AA56 -> 0 | AD56: =(($J56/30/8)*1.5)*AC56 -> 0 | AF56: =(($J56/30/8)*2)*AE56 -> 0 | AH56: =(($J56/30/8)*1.5)*AG56 -> 0 | AJ56: =(($J56/30/8)*2)*AI56 -> 0 | AL56: =(($J56/30/8)*1.5)*AK56 -> 0 | AN56: =(($J56/30/8)*2)*AM56 -> 0 | BA56: =((J56/30)*M56)*$N56 -> 3575 | BB56: =((K56/30)*M56)*$N56+820.88 -> 2745.88 | BC56: =U56 -> 0 | BD56: =V56 -> 0 | BE56: =W56 -> 0 | BF56: =X56 -> 0 | BG56: =AO56+AT56 -> 0 | BH56: =(BA56+BD56+BF56+BG56)*0.1267 -> 452.9525 | BI56: =SUM(BA56:BH56)-BC56-BE56 -> 6773.8325 | BJ56: =(($J56/30)*$M56)*$O56 -> 2275 | BK56: =(($K56/30)*$M56)*$O56+522.38 -> 1747.38 | BL56: =Y56 -> 0 | BM56: =Z56 -> 0 | BN56: =AA56 -> 0 | BO56: =AB56 -> 0 | BP56: =AP56+AU56 -> 0 | BQ56: =(+BJ56+BM56+BO56+BP56)*0.1267 -> 288.2425 | BR56: =SUM(BJ56:BQ56)-BL56-BN56 -> 4310.6225 | BS56: =(($J56/30)*$M56)*$P56 -> 325 | BT56: =(($K56/30)*$M56)*$P56+74.63 -> 249.63 | BU56: =AC56 -> 0 | BV56: =AD56 -> 0 | BW56: =AE56 -> 0 | BX56: =AF56 -> 0 | BY56: =AQ56+AV56 -> 0 | BZ56: =(BS56+BV56+BX56+BY56)*0.1267 -> 41.1775 | CA56: =SUM(BS56:BZ56)-BU56-BW56 -> 615.8075 | CB56: =(($J56/30)*$M56)*$Q56 -> 325 | CC56: =(($K56/30)*$M56)*$Q56+74.63 -> 249.63 | CD56: =AG56 -> 0 | CE56: =AH56 -> 0 | CF56: =AI56 -> 0 | CG56: =AJ56 -> 0 | CH56: =AR56+AW56 -> 0 | CI56: =(CB56+CE56+CG56+CH56)*0.1267 -> 41.1775 | CJ56: =SUM(CB56:CI56)-CD56-CF56 -> 615.8075 | CK56: =(($J56/30)*$M56)*R56 -> 0 | CL56: =(($K56/30)*$M56)*$R56 -> 0 | CM56: =+AK56 -> 0 | CN56: =AL56 -> 0 | CO56: =AM56 -> 0 | CP56: =AN56 -> 0 | CQ56: =AS56+AX56 -> 0 | CR56: =(CK56+CN56+CP56)*0.1267 -> 0 | CS56: =SUM(CK56:CR56)-CM56-CO56 -> 0 | CU56: ECONACIONAL | CV56: =IF($CU56="PROQUIMA",$BA56+$BJ56+$BS56+$CB56+$CK56,0) -> 0 | CW56: =IF($CU56="PROQUIMA",$BB56+$BK56+$BT56+$CC56+$CL56,0) -> 0 | CX56: =IF($CU56="PROQUIMA",$BC56+$BL56+$BU56+$CD56+$CM56,0) -> 0 | CY56: =IF($CU56="PROQUIMA",$BD56+$BM56+$BV56+$CE56+$CN56,0) -> 0 | CZ56: =IF($CU56="PROQUIMA",$BE56+$BN56+$BW56+$CF56+$CO56,0) -> 0 | DA56: =IF($CU56="PROQUIMA",$BF56+$BO56+$BX56+$CG56+$CP56,0) -> 0 | DB56: =IF($CU56="PROQUIMA",$BG56+$BP56+$BY56+$CH56+$CQ56,0) -> 0 | DC56: =IF($CU56="PROQUIMA",$BH56+$BQ56+$BZ56+$CI56+CR56,0) -> 0 | DD56: =SUM(CV56:DC56)-CX56-CZ56 -> 0 | DE56: =IF($CU56="UNHESA",$BA56+$BJ56+$BS56+$CB56+$CK56,0) -> 0 | DF56: =IF($CU56="UNHESA",$BB56+$BK56+$BT56+$CC56+$CL56,0) -> 0 | DG56: =IF($CU56="UNHESA",$BC56+$BL56+$BU56+$CD56+$CM56,0) -> 0 | DH56: =IF($CU56="UNHESA",$BD56+$BM56+$BV56+$CE56+$CN56,0) -> 0 | DI56: =IF($CU56="UNHESA",$BE56+$BN56+$BW56+$CF56+$CO56,0) -> 0 | DJ56: =IF($CU56="UNHESA",$BF56+$BO56+$BX56+$CG56+$CP56,0) -> 0 | DK56: =IF($CU56="UNHESA",$BG56+$BP56+$BY56+$CH56+$CQ56,0) -> 0 | DL56: =IF($CU56="UNHESA",$BH56+$BQ56+$BZ56+$CI56+$CR56,0) -> 0 | DM56: =SUM(DE56:DL56)-DG56-DI56 -> 0 | DN56: =IF($CU56="UNHESA LIQUIDOS",$BA56+$BJ56+$BS56+$CB56+$CK56,0) -> 0 | DO56: =IF($CU56="CALIDUL",$BB56+$BK56+$BT56+$CC56+$CL56,0) -> 0 | DP56: =IF($CU56="CALIDUL",$BC56+$BL56+$BU56+$CD56+$CM56,0) -> 0 | DQ56: =IF($CU56="CALIDUL",$BD56+$BM56+$BV56+$CE56+$CN56,0) -> 0 | DR56: =IF($CU56="CALIDUL",$BE56+$BN56+$BW56+$CF56+$CO56,0) -> 0 | DS56: =IF($CU56="CALIDUL",$BF56+$BO56+$BX56+$CG56+$CP56,0) -> 0 | DT56: =IF($CU56="CALIDUL",$BG56+$BP56+$BY56+$CH56+$CQ56,0) -> 0 | DU56: =IF($CU56="CALIDUL",$BH56+$BQ56+$BZ56+$CI56+$CR56,0) -> 0 | DV56: =SUM(DN56:DU56)-DP56-DR56 -> 0 | DW56: =IF($CU56="CLEARTEC",$BA56+$BJ56+$BS56+$CB56+$CK56,0) -> 0 | DX56: =IF($CU56="CLEARTEC",$BA56+$BJ56+$BS56+$CB56+$CK56,0) -> 0 | DY56: =IF($CU56="CLEARTEC",$BA56+$BJ56+$BS56+$CB56+$CK56,0) -> 0 | DZ56: =IF($CU56="CLEARTEC",$BA56+$BJ56+$BS56+$CB56+$CK56,0) -> 0 | EA56: =IF($CU56="CLEARTEC",$BA56+$BJ56+$BS56+$CB56+$CK56,0) -> 0 | EB56: =IF($CU56="CLEARTEC",$BA56+$BJ56+$BS56+$CB56+$CK56,0) -> 0 | EC56: =IF($CU56="CLEARTEC",$BA56+$BJ56+$BS56+$CB56+$CK56,0) -> 0 | ED56: =IF($CU56="CLEARTEC",$BA56+$BJ56+$BS56+$CB56+$CK56,0) -> 0 | EE56: =SUM(DW56:ED56)-DY56-EA56 -> 0 | EF56: =IF(CU56="ECONACIONAL",$BA56+$BJ56+$BS56+$CB56+$CK56) -> 6500 | EG56: =IF($CU56="ECONACIONAL",$BB56+$BK56+$BT56+$CC56+$CL56,0) -> 4992.52 | EH56: =IF(CU56="ECONACIONAL",$BC56+$BL56+$BU56+$CD56+$CM56) -> 0 | EI56: =IF(CU56="ECONACIONAL",$BD56+$DH56+$DQ56+$DZ56+BM56+BV56+CE56+CN56) -> 0 | EJ56: =IF($CU56="CLEARTEC",$BE56+$BN56+$BW56+$CF56+$CO56,0) -> 0 | EK56: =IF(CU56="ECONACIONAL",$BF56+$BO56+$BX56+$CG56+$CP56) -> 0 | EL56: =IF(CU56="ECONACIONAL",$BG56+$BP56+$BY56+$CH56+$CQ56) -> 0 | EM56: =IF(CU56="ECONACIONAL",BH56+BQ56+BZ56+CI56+CR56) -> 823.55 | EN56: =SUM(EF56:EM56)-EH56-EJ56 -> 12316.07 | EP56: 367.44 | EV56: 350 | EY56: =+ET56+EU56+EV56 -> 350 | FA56: =IF($M56<=15,EP56/2,EP56) -> 367.44 | FB56: =IF($M56<=15,EQ56/2,EQ56) -> 0 | FC56: =IF($M56<=15,ER56/2,ER56) -> 0 | FD56: =IF($M56<=15,ES56/2,ES56) -> 0 | FE56: =IF($M56<=15,ET56/2,ET56) -> 0 | FF56: =IF($M56<=15,EU56/2,EU56) -> 0 | FG56: =IF($M56<=15,EV56/2,EV56) -> 350 | FH56: =IF($M56<=15,EW56/2,EW56) -> 0 | ... FJ56: =IF($M56<=15,EY56/2,EY56) -> 350 | FR56: =(((J56/30/8)*1.5)*(U56+Y56+AC56))-(BD56+BM56+BV56) -> 0 | FS56: =(((J56/30/8)*2)*(W56+AA56+AE56))-(BF56+BO56+BX56) -> 0 | FT56: =(SUM(BA56:CJ56))-(SUM(EF56:EN56)) -> 0 | FU56: =(J56/30*M56)-(EF56) -> 0 | FV56: =(SUM(EP56:EY56))-((SUM(FA56:FJ56))*$FV$5) -> -1067.44
H57: Costos y Presupuestos | J57: =SUM(J56) -> 6500 | K57: =SUM(K56) -> 3500 | L57: =SUM(L56) -> 10000 | U57: =SUM(U56) -> 0 | V57: =SUM(V56) -> 0 | W57: =SUM(W56) -> 0 | X57: =SUM(X56) -> 0 | Y57: =SUM(Y56) -> 0 | Z57: =SUM(Z56) -> 0 | AA57: =SUM(AA56) -> 0 | AB57: =SUM(AB56) -> 0 | ... EN57: =SUM(EN56) -> 12316.07 | EP57: =SUM(EP56) -> 367.44 | EQ57: =SUM(EQ56) -> 0 | ER57: =SUM(ER56) -> 0 | ES57: =SUM(ES56) -> 0 | ET57: =SUM(ET56) -> 0 | EU57: =SUM(EU56) -> 0 | EV57: =SUM(EV56) -> 350 | EW57: =SUM(EW56) -> 0 | ... EY57: =SUM(EY56) -> 350 | FA57: =SUM(FA56) -> 367.44 | FB57: =SUM(FB56) -> 0 | FC57: =SUM(FC56) -> 0 | FD57: =SUM(FD56) -> 0 | FE57: =SUM(FE56) -> 0 | FF57: =SUM(FF56) -> 0 | FG57: =SUM(FG56) -> 350 | FH57: =SUM(FH56) -> 0 | ... FP57: =SUM(FP56) -> 0
H58: Total Contabilidad y Finanzas | J58: =+J48+J51+J54+J57 -> 61602.28 | K58: =+K48+K51+K54+K57 -> 20355.16 | L58: =+L48+L51+L54+L57 -> 81957.44 | U58: =+U48+U51+U54+U57 -> 0 | V58: =+V48+V51+V54+V57 -> 0 | W58: =+W48+W51+W54+W57 -> 0 | X58: =+X48+X51+X54+X57 -> 0 | Y58: =+Y48+Y51+Y54+Y57 -> 0 | Z58: =+Z48+Z51+Z54+Z57 -> 0 | AA58: =+AA48+AA51+AA54+AA57 -> 0 | AB58: =+AB48+AB51+AB54+AB57 -> 0 | ... EN58: =+EN48+EN51+EN54+EN57 -> 93754.969 | EP58: =+EP48+EP51+EP54+EP57 -> 2462.66 | EQ58: =+EQ48+EQ51+EQ54+EQ57 -> 9519.84 | ER58: =+ER48+ER51+ER54+ER57 -> 200 | ES58: =+ES48+ES51+ES54+ES57 -> 522 | ET58: =+ET48+ET51+ET54+ET57 -> 0 | EU58: =+EU48+EU51+EU54+EU57 -> 0 | EV58: =+EV48+EV51+EV54+EV57 -> 2118 | EW58: =+EW48+EW51+EW54+EW57 -> 0 | ... EY58: =+EY48+EY51+EY54+EY57 -> 2118 | FA58: =+FA48+FA51+FA54+FA57 -> 2462.66 | FB58: =+FB48+FB51+FB54+FB57 -> 9519.84 | FC58: =+FC48+FC51+FC54+FC57 -> 200 | FD58: =+FD48+FD51+FD54+FD57 -> 522 | FE58: =+FE48+FE51+FE54+FE57 -> 0 | FF58: =+FF48+FF51+FF54+FF57 -> 0 | FG58: =+FG48+FG51+FG54+FG57 -> 2118 | FH58: =+FH48+FH51+FH54+FH57 -> 0 | ... FJ58: =+FJ48+FJ51+FJ54+FJ57 -> 2118
A59: =$G$4 -> JUNIO 2026 2da QUINCENA | B59: =+$G$5 -> 2026 | C59: =A59 & B59 -> JUNIO 2026 2da QUINCENA2026 | E59: 303030 | G59: Exportaciones
A60: =$G$4 -> JUNIO 2026 2da QUINCENA | B60: =+$G$5 -> 2026 | C60: =A60 & B60 -> JUNIO 2026 2da QUINCENA2026 | G60: Premezclas
A61: =$G$4 -> JUNIO 2026 2da QUINCENA | B61: =+$G$5 -> 2026 | C61: =A61 & B61 -> JUNIO 2026 2da QUINCENA2026 | G61: materias Primas
A62: =$G$4 -> JUNIO 2026 2da QUINCENA | B62: =+$G$5 -> 2026 | C62: =A62 & B62 -> JUNIO 2026 2da QUINCENA2026 | G62: Maquila
A63: =$G$4 -> JUNIO 2026 2da QUINCENA | B63: =+$G$5 -> 2026 | C63: =A63 & B63 -> JUNIO 2026 2da QUINCENA2026 | E63: 202010 | G63: Mercadeo
A64: =$G$4 -> JUNIO 2026 2da QUINCENA | B64: =+$G$5 -> 2026 | C64: =A64 & B64 -> JUNIO 2026 2da QUINCENA2026 | E64: 202010 | G64: Administracion
A66: =$G$4 -> JUNIO 2026 2da QUINCENA | B66: =+$G$5 -> 2026 | C66: =A66 & B66 -> JUNIO 2026 2da QUINCENA2026 | E66: 301010 | G66: Produccion
A67: =$G$4 -> JUNIO 2026 2da QUINCENA | B67: =+$G$5 -> 2026 | C67: =A67 & B67 -> JUNIO 2026 2da QUINCENA2026 | D67: =+$G$66 -> Produccion | E67: 301010 | G67: Administracion
E70: 301010 | J70: =SUM(J68:J69) -> 0 | K70: =SUM(K68:K69) -> 0 | L70: =SUM(L68:L69) -> 0 | U70: =SUM(U68:U69) -> 0 | V70: =SUM(V68:V69) -> 0 | W70: =SUM(W68:W69) -> 0 | X70: =SUM(X68:X69) -> 0 | Y70: =SUM(Y68:Y69) -> 0 | Z70: =SUM(Z68:Z69) -> 0 | AA70: =SUM(AA68:AA69) -> 0 | AB70: =SUM(AB68:AB69) -> 0 | ... EN70: =SUM(EN68:EN69) -> 0 | EP70: =SUM(EP68:EP69) -> 0 | EQ70: =SUM(EQ68:EQ69) -> 0 | ER70: =SUM(ER68:ER69) -> 0 | ES70: =SUM(ES68:ES69) -> 0 | ET70: =SUM(ET68:ET69) -> 0 | EU70: =SUM(EU68:EU69) -> 0 | EV70: =SUM(EV68:EV69) -> 0 | EW70: =SUM(EW68:EW69) -> 0 | ... EY70: =SUM(EY68:EY69) -> 0 | FA70: =SUM(FA68:FA69) -> 0 | FB70: =SUM(FB68:FB69) -> 0 | FC70: =SUM(FC68:FC69) -> 0 | FD70: =SUM(FD68:FD69) -> 0 | FE70: =SUM(FE68:FE69) -> 0 | FF70: =SUM(FF68:FF69) -> 0 | FG70: =SUM(FG68:FG69) -> 0 | FH70: =SUM(FH68:FH69) -> 0 | ... FP70: =SUM(FP68:FP69) -> 0
A71: =$G$4 -> JUNIO 2026 2da QUINCENA | B71: =+$G$5 -> 2026 | C71: =A71 & B71 -> JUNIO 2026 2da QUINCENA2026 | E71: 301020 | G71: Fabricacion Secos UNHESA | EF71: =IF($CU71="CLEARTEC",$BA71+$BJ71+$BS71+$CB71+$CK71,0) -> 0
E72: 301020 | EF72: 0 | EG72: =IF($CU72="ECONACIONAL",$BB72+$BK72+$BT72+$CC72+$CL72,0) -> 0 | EH72: 0 | EI72: 0 | EJ72: =IF($CU72="CLEARTEC",$BE72+$BN72+$BW72+$CF72+$CO72,0) -> 0 | EK72: 0 | EL72: 0 | EM72: 0 | EN72: =SUM(EF72:EM72)-EH72-EJ72 -> 0 | EY72: =+ET72+EU72+EV72 -> 0 | FR72: =(((J72/30/8)*1.5)*(U72+Y72+AC72))-(BD72+BM72+BV72) -> 0 | FS72: =(((J72/30/8)*2)*(W72+AA72+AE72))-(BF72+BO72+BX72) -> 0 | FT72: =(SUM(BA72:CJ72))-(SUM(EF72:EN72)) -> 0 | FU72: =(J72/30*M72)-(EF72) -> 0 | FV72: =(SUM(EP72:EY72))-((SUM(FA72:FJ72))*$FV$5) -> 0
A73: =$G$4 -> JUNIO 2026 2da QUINCENA | B73: =+$G$5 -> 2026 | C73: =A73 & B73 -> JUNIO 2026 2da QUINCENA2026 | E73: 301020 | H73: Fabricacion secos unhesas | J73: =SUM(J72:J72) -> 0 | K73: =SUM(K72:K72) -> 0 | L73: =SUM(L72:L72) -> 0 | U73: =SUM(U72:U72) -> 0 | V73: =SUM(V72:V72) -> 0 | W73: =SUM(W72:W72) -> 0 | X73: =SUM(X72:X72) -> 0 | Y73: =SUM(Y72:Y72) -> 0 | Z73: =SUM(Z72:Z72) -> 0 | AA73: =SUM(AA72:AA72) -> 0 | AB73: =SUM(AB72:AB72) -> 0 | ... EN73: =SUM(EN72:EN72) -> 0 | EP73: =SUM(EP72:EP72) -> 0 | EQ73: =SUM(EQ72:EQ72) -> 0 | ER73: =SUM(ER72:ER72) -> 0 | ES73: =SUM(ES72:ES72) -> 0 | ET73: =SUM(ET72:ET72) -> 0 | EU73: =SUM(EU72:EU72) -> 0 | EV73: =SUM(EV72:EV72) -> 0 | EW73: =SUM(EW72:EW72) -> 0 | ... EY73: =SUM(EY72:EY72) -> 0 | FA73: =SUM(FA72:FA72) -> 0 | FB73: =SUM(FB72:FB72) -> 0 | FC73: =SUM(FC72:FC72) -> 0 | FD73: =SUM(FD72:FD72) -> 0 | FE73: =SUM(FE72:FE72) -> 0 | FF73: =SUM(FF72:FF72) -> 0 | FG73: =SUM(FG72:FG72) -> 0 | FH73: =SUM(FH72:FH72) -> 0 | ... FP73: =SUM(FP72:FP72) -> 0
A74: =$G$4 -> JUNIO 2026 2da QUINCENA | B74: =+$G$5 -> 2026 | C74: =A74 & B74 -> JUNIO 2026 2da QUINCENA2026 | E74: 301030 | G74: Fabricacion Liquidos | EF74: =IF($CU74="CLEARTEC",$BA74+$BJ74+$BS74+$CB74+$CK74,0) -> 0
E75: 301030 | EF75: 0 | EG75: =IF($CU75="ECONACIONAL",$BB75+$BK75+$BT75+$CC75+$CL75,0) -> 0 | EH75: 0 | EI75: 0 | EJ75: =IF($CU75="CLEARTEC",$BE75+$BN75+$BW75+$CF75+$CO75,0) -> 0 | EK75: 0 | EL75: 0 | EM75: 0 | EN75: =SUM(EF75:EM75)-EH75-EJ75 -> 0 | EY75: =+ET75+EU75+EV75 -> 0
E76: 301030 | H76: Fabricacion liquidos | J76: =SUM(J75:J75) -> 0 | K76: =SUM(K75:K75) -> 0 | L76: =SUM(L75:L75) -> 0 | U76: =SUM(U75:U75) -> 0 | V76: =SUM(V75:V75) -> 0 | W76: =SUM(W75:W75) -> 0 | X76: =SUM(X75:X75) -> 0 | Y76: =SUM(Y75:Y75) -> 0 | Z76: =SUM(Z75:Z75) -> 0 | AA76: =SUM(AA75:AA75) -> 0 | AB76: =SUM(AB75:AB75) -> 0 | ... CS76: =SUM(CS75:CS75) -> 0 | CV76: =SUM(CV75:CV75) -> 0 | CW76: =SUM(CW75:CW75) -> 0 | CX76: =SUM(CX75:CX75) -> 0 | CY76: =SUM(CY75:CY75) -> 0 | CZ76: =SUM(CZ75:CZ75) -> 0 | DA76: =SUM(DA75:DA75) -> 0 | DB76: =SUM(DB75:DB75) -> 0 | DC76: =SUM(DC75:DC75) -> 0 | ... EN76: =SUM(EN75:EN75) -> 0 | EP76: =SUM(EP75:EP75) -> 0 | EQ76: =SUM(EQ75:EQ75) -> 0 | ER76: =SUM(ER75:ER75) -> 0 | ES76: =SUM(ES75:ES75) -> 0 | ET76: =SUM(ET75:ET75) -> 0 | EU76: =SUM(EU75:EU75) -> 0 | EV76: =SUM(EV75:EV75) -> 0 | EW76: =SUM(EW75:EW75) -> 0 | ... EY76: =SUM(EY75:EY75) -> 0 | FA76: =SUM(FA75:FA75) -> 0 | FB76: =SUM(FB75:FB75) -> 0 | FC76: =SUM(FC75:FC75) -> 0 | FD76: =SUM(FD75:FD75) -> 0 | FE76: =SUM(FE75:FE75) -> 0 | FF76: =SUM(FF75:FF75) -> 0 | FG76: =SUM(FG75:FG75) -> 0 | FH76: =SUM(FH75:FH75) -> 0 | ... FJ76: =SUM(FJ75:FJ75) -> 0
G77: Fabricacion liquidos maquilas
G78: fabricacion maquilas
H79: Total Producción | J79: =+J70+J73+J76 -> 0 | K79: =+K70+K73+K76 -> 0 | L79: =+L70+L73+L76 -> 0 | U79: =+U70+U73+U76 -> 0 | V79: =+V70+V73+V76 -> 0 | W79: =+W70+W73+W76 -> 0 | X79: =+X70+X73+X76 -> 0 | Y79: =+Y70+Y73+Y76 -> 0 | Z79: =+Z70+Z73+Z76 -> 0 | AA79: =+AA70+AA73+AA76 -> 0 | AB79: =+AB70+AB73+AB76 -> 0 | ... EN79: =+EN70+EN73+EN76 -> 0 | EP79: =+EP70+EP73+EP76 -> 0 | EQ79: =+EQ70+EQ73+EQ76 -> 0 | ER79: =+ER70+ER73+ER76 -> 0 | ES79: =+ES70+ES73+ES76 -> 0 | ET79: =+ET70+ET73+ET76 -> 0 | EU79: =+EU70+EU73+EU76 -> 0 | EV79: =+EV70+EV73+EV76 -> 0 | EW79: =+EW70+EW73+EW76 -> 0 | ... EY79: =+EY70+EY73+EY76 -> 0 | FA79: =+FA70+FA73+FA76 -> 0 | FB79: =+FB70+FB73+FB76 -> 0 | FC79: =+FC70+FC73+FC76 -> 0 | FD79: =+FD70+FD73+FD76 -> 0 | FE79: =+FE70+FE73+FE76 -> 0 | FF79: =+FF70+FF73+FF76 -> 0 | FG79: =+FG70+FG73+FG76 -> 0 | FH79: =+FH70+FH73+FH76 -> 0 | ... FJ79: =+FJ70+FJ73+FJ76 -> 0
A80: =$G$4 -> JUNIO 2026 2da QUINCENA | B80: =+$G$5 -> 2026 | C80: =A80 & B80 -> JUNIO 2026 2da QUINCENA2026 | E80: 302010 | G80: LOGISTICA
A81: =$G$4 -> JUNIO 2026 2da QUINCENA | B81: =+$G$5 -> 2026 | C81: =A81 & B81 -> JUNIO 2026 2da QUINCENA2026 | E81: 302010 | G81: Administracion
E82: 302010 | F82: 27 | G82: Ramos Pineda Alan Fernando | H82: Jefe de Logistica y Bodega | I82: ECONACIONAL | J82: 5500 | K82: 3500 | L82: =+J82+K82 -> 9000 | M82: 30 | N82: 0.35 | O82: 0.45 | P82: 0.2 | Q82: 0 | R82: 0 | S82: =SUM(N82:R82) -> 1 | T82: 500 pendientes de marzo como indicadores | V82: =($J82/30/8*1.5)*U82 -> 0 | X82: =($J82/30/8*2)*W82 -> 0 | Z82: =($J82/30/8*1.5)*Y82 -> 0 | AB82: =($J82/30/8*2)*AA82 -> 0 | AD82: =(($J82/30/8)*1.5)*AC82 -> 0 | AF82: =(($J82/30/8)*2)*AE82 -> 0 | AH82: =(($J82/30/8)*1.5)*AG82 -> 0 | AJ82: =(($J82/30/8)*2)*AI82 -> 0 | AL82: =(($J82/30/8)*1.5)*AK82 -> 0 | AN82: =(($J82/30/8)*2)*AM82 -> 0 | BA82: =((J82/30)*M82)*$N82 -> 1925 | BB82: =((K82/30)*M82)*$N82+350 -> 1575 | BC82: =U82 -> 0 | BD82: =V82 -> 0 | BE82: =W82 -> 0 | BF82: =X82 -> 0 | BG82: =AO82+AT82 -> 0 | BH82: =(BA82+BD82+BF82+BG82)*0.1267 -> 243.8975 | BI82: =SUM(BA82:BH82)-BC82-BE82 -> 3743.8975 | BJ82: =(($J82/30)*$M82)*$O82 -> 2475 | BK82: =(($K82/30)*$M82)*$O82+650 -> 2225 | BL82: =Y82 -> 0 | BM82: =Z82 -> 0 | BN82: =AA82 -> 0 | BO82: =AB82 -> 0 | BP82: 0 | BQ82: =(+BJ82+BM82+BO82+BP82)*0.1267 -> 313.5825 | BR82: =SUM(BJ82:BQ82)-BL82-BN82 -> 5013.5825 | BS82: =(($J82/30)*$M82)*$P82 -> 1100 | BT82: =(($K82/30)*$M82)*$P82 -> 700 | BU82: =AC82 -> 0 | BV82: =AD82 -> 0 | BW82: =AE82 -> 0 | BX82: =AF82 -> 0 | BY82: =AQ82+AV82 -> 0 | BZ82: =(BS82+BV82+BX82+BY82)*0.1267 -> 139.37 | CA82: =SUM(BS82:BZ82)-BU82-BW82 -> 1939.37 | CB82: =(($J82/30)*$M82)*$Q82 -> 0 | CC82: =(($K82/30)*$M82)*$Q82 -> 0 | CD82: =AG82 -> 0 | CE82: =AH82 -> 0 | CF82: =AI82 -> 0 | CG82: =AJ82 -> 0 | CH82: =AR82+AW82 -> 0 | CI82: =(CB82+CE82+CG82+CH82)*0.1267 -> 0 | CJ82: =SUM(CB82:CI82)-CD82-CF82 -> 0 | CK82: =(($J82/30)*$M82)*R82 -> 0 | CL82: =(($K82/30)*$M82)*$R82 -> 0 | CM82: =+AK82 -> 0 | CN82: =AL82 -> 0 | CO82: =AM82 -> 0 | CP82: =AN82 -> 0 | CQ82: =AS82+AX82 -> 0 | CR82: =(CK82+CN82+CP82)*0.1267 -> 0 | CS82: =SUM(CK82:CR82)-CM82-CO82 -> 0 | CU82: ECONACIONAL | CV82: =IF($CU82="PROQUIMA",$BA82+$BJ82+$BS82+$CB82+$CK82,0) -> 0 | CW82: =IF($CU82="PROQUIMA",$BB82+$BK82+$BT82+$CC82+$CL82,0) -> 0 | CX82: =IF($CU82="PROQUIMA",$BC82+$BL82+$BU82+$CD82+$CM82,0) -> 0 | CY82: =IF($CU82="PROQUIMA",$BD82+$BM82+$BV82+$CE82+$CN82,0) -> 0 | CZ82: =IF($CU82="PROQUIMA",$BE82+$BN82+$BW82+$CF82+$CO82,0) -> 0 | DA82: =IF($CU82="PROQUIMA",$BF82+$BO82+$BX82+$CG82+$CP82,0) -> 0 | DB82: =IF($CU82="PROQUIMA",$BG82+$BP82+$BY82+$CH82+$CQ82,0) -> 0 | DC82: =IF($CU82="PROQUIMA",$BH82+$BQ82+$BZ82+$CI82+CR82,0) -> 0 | DD82: =SUM(CV82:DC82)-CX82-CZ82 -> 0 | DE82: =IF($CU82="UNHESA",$BA82+$BJ82+$BS82+$CB82+$CK82,0) -> 0 | DF82: =IF($CU82="UNHESA",$BB82+$BK82+$BT82+$CC82+$CL82,0) -> 0 | DG82: =IF($CU82="UNHESA",$BC82+$BL82+$BU82+$CD82+$CM82,0) -> 0 | DH82: =IF($CU82="UNHESA",$BD82+$BM82+$BV82+$CE82+$CN82,0) -> 0 | DI82: =IF($CU82="UNHESA",$BE82+$BN82+$BW82+$CF82+$CO82,0) -> 0 | DJ82: =IF($CU82="UNHESA",$BF82+$BO82+$BX82+$CG82+$CP82,0) -> 0 | DK82: =IF($CU82="UNHESA",$BG82+$BP82+$BY82+$CH82+$CQ82,0) -> 0 | DL82: =IF($CU82="UNHESA",$BH82+$BQ82+$BZ82+$CI82+$CR82,0) -> 0 | DM82: =SUM(DE82:DL82)-DG82-DI82 -> 0 | DN82: =IF($CU82="UNHESA LIQUIDOS",$BA82+$BJ82+$BS82+$CB82+$CK82,0) -> 0 | DO82: =IF($CU82="UNHESA LIQUIDOS",$BB82+$BK82+$BT82+$CC82+$CL82,0) -> 0 | DP82: =IF($CU82="UNHESA LIQUIDOS",$BC82+$BL82+$BU82+$CD82+$CM82,0) -> 0 | DQ82: =IF($CU82="UNHESA LIQUIDOS",$BD82+$BM82+$BV82+$CE82+$CN82,0) -> 0 | DR82: =IF($CU82="UNHESA LIQUIDOS",$BE82+$BN82+$BW82+$CF82+$CO82,0) -> 0 | DS82: =IF($CU82="UNHESA LIQUIDOS",$BF82+$BO82+$BX82+$CG82+$CP82,0) -> 0 | DT82: =IF($CU82="UNHESA LIQUIDOS",$BG82+$BP82+$BY82+$CH82+$CQ82,0) -> 0 | DU82: =IF($CU82="UNHESA LIQUIDOS",$BH82+$BQ82+$BZ82+$CI82+$CR82,0) -> 0 | DV82: =SUM(DN82:DU82)-DP82-DR82 -> 0 | DW82: =IF($CU82="CLEARTEC",$BA82+$BJ82+$BS82+$CB82+$CK82,0) -> 0 | DX82: =IF($CU82="CLEARTEC",$BA82+$BJ82+$BS82+$CB82+$CK82,0) -> 0 | DY82: =IF($CU82="CLEARTEC",$BA82+$BJ82+$BS82+$CB82+$CK82,0) -> 0 | DZ82: =IF($CU82="CLEARTEC",$BA82+$BJ82+$BS82+$CB82+$CK82,0) -> 0 | EA82: =IF($CU82="CLEARTEC",$BA82+$BJ82+$BS82+$CB82+$CK82,0) -> 0 | EB82: =IF($CU82="CLEARTEC",$BA82+$BJ82+$BS82+$CB82+$CK82,0) -> 0 | EC82: =IF($CU82="CLEARTEC",$BA82+$BJ82+$BS82+$CB82+$CK82,0) -> 0 | ED82: =IF($CU82="CLEARTEC",$BA82+$BJ82+$BS82+$CB82+$CK82,0) -> 0 | EE82: =SUM(DW82:ED82)-DY82-EA82 -> 0 | EF82: =IF(CU82="ECONACIONAL",$BA82+$BJ82+$BS82+$CB82+$CK82) -> 5500 | EG82: =IF($CU82="ECONACIONAL",$BB82+$BK82+$BT82+$CC82+$CL82,0) -> 4500 | EH82: =IF(CU82="ECONACIONAL",$BC82+$BL82+$BU82+$CD82+$CM82) -> 0 | EI82: =IF(CU82="ECONACIONAL",$BD82+$DH82+$DQ82+$DZ82+BM82+BV82+CE82+CN82) -> 0 | EJ82: =IF($CU82="CLEARTEC",$BE82+$BN82+$BW82+$CF82+$CO82,0) -> 0 | EK82: =IF(CU82="ECONACIONAL",$BF82+$BO82+$BX82+$CG82+$CP82) -> 0 | EL82: =IF(CU82="ECONACIONAL",$BG82+$BP82+$BY82+$CH82+$CQ82) -> 0 | EM82: =IF(CU82="ECONACIONAL",BH82+BQ82+BZ82+CI82+CR82) -> 696.85 | EN82: =SUM(EF82:EM82)-EH82-EJ82 -> 10696.85 | EP82: 199.22 | EY82: =+ET82+EU82+EV82 -> 0 | FA82: =IF($M82<=15,EP82/2,EP82) -> 199.22 | FB82: =IF($M82<=15,EQ82/2,EQ82) -> 0 | FC82: =IF($M82<=15,ER82/2,ER82) -> 0 | FD82: =IF($M82<=15,ES82/2,ES82) -> 0 | FE82: =IF($M82<=15,ET82/2,ET82) -> 0 | FF82: =IF($M82<=15,EU82/2,EU82) -> 0 | FG82: =IF($M82<=15,EV82/2,EV82) -> 0 | FH82: =IF($M82<=15,EW82/2,EW82) -> 0 | ... FJ82: =IF($M82<=15,EY82/2,EY82) -> 0 | FR82: =(((J82/30/8)*1.5)*(U82+Y82+AC82))-(BD82+BM82+BV82) -> 0 | FS82: =(((J82/30/8)*2)*(W82+AA82+AE82))-(BF82+BO82+BX82) -> 0 | FT82: =(SUM(BA82:CJ82))-(SUM(EF82:EN82)) -> 0 | FU82: =(J82/30*M82)-(EF82) -> 0 | FV82: =(SUM(EP82:EY82))-((SUM(FA82:FJ82))*$FV$5) -> -199.22
A83: =$G$4 -> JUNIO 2026 2da QUINCENA | B83: =+$G$5 -> 2026 | C83: =A83 & B83 -> JUNIO 2026 2da QUINCENA2026 | D83: =+G80 -> LOGISTICA | E83: 302010 | F83: 28 | G83: Davila Morales Estiven Alexander | H83: Facturador | I83: ECONACIONAL | J83: 4100 | K83: 250 | L83: =+J83+K83 -> 4350 | M83: 30 | N83: 0.4 | O83: 0.4 | P83: 0.2 | Q83: 0 | R83: 0 | S83: =SUM(N83:R83) -> 1 | V83: =($J83/30/8*1.5)*U83 -> 0 | X83: =($J83/30/8*2)*W83 -> 0 | Y83: 24 | Z83: =($J83/30/8*1.5)*Y83 -> 615 | AB83: =($J83/30/8*2)*AA83 -> 0 | AD83: =(($J83/30/8)*1.5)*AC83 -> 0 | AF83: =(($J83/30/8)*2)*AE83 -> 0 | AH83: =(($J83/30/8)*1.5)*AG83 -> 0 | AJ83: =(($J83/30/8)*2)*AI83 -> 0 | AL83: =(($J83/30/8)*1.5)*AK83 -> 0 | AN83: =(($J83/30/8)*2)*AM83 -> 0 | BA83: =((J83/30)*M83)*$N83 -> 1640 | BB83: =((K83/30)*M83)*$N83+240 -> 340 | BC83: =U83 -> 0 | BD83: =V83 -> 0 | BE83: =W83 -> 0 | BF83: =X83 -> 0 | BG83: =AO83+AT83 -> 0 | BH83: =(BA83+BD83+BF83+BG83)*0.1267 -> 207.788 | BI83: =SUM(BA83:BH83)-BC83-BE83 -> 2187.788 | BJ83: =(($J83/30)*$M83)*$O83 -> 1640 | BK83: =(($K83/30)*$M83)*$O83+240 -> 340 | BL83: =Y83 -> 24 | BM83: =Z83 -> 615 | BN83: =AA83 -> 0 | BO83: =AB83 -> 0 | BP83: 0 | BQ83: =(+BJ83+BM83+BO83+BP83)*0.1267 -> 285.7085 | BR83: =SUM(BJ83:BQ83)-BL83-BN83 -> 2880.7085 | BS83: =(($J83/30)*$M83)*$P83 -> 820 | BT83: =(($K83/30)*$M83)*$P83 -> 50 | BU83: =AC83 -> 0 | BV83: =AD83 -> 0 | BW83: =AE83 -> 0 | BX83: =AF83 -> 0 | BY83: =AQ83+AV83 -> 0 | BZ83: =(BS83+BV83+BX83+BY83)*0.1267 -> 103.894 | CA83: =SUM(BS83:BZ83)-BU83-BW83 -> 973.894 | CB83: =(($J83/30)*$M83)*$Q83 -> 0 | CC83: =(($K83/30)*$M83)*$Q83 -> 0 | CD83: =AG83 -> 0 | CE83: =AH83 -> 0 | CF83: =AI83 -> 0 | CG83: =AJ83 -> 0 | CH83: =AR83+AW83 -> 0 | CI83: =(CB83+CE83+CG83+CH83)*0.1267 -> 0 | CJ83: =SUM(CB83:CI83)-CD83-CF83 -> 0 | CK83: =(($J83/30)*$M83)*R83 -> 0 | CL83: =(($K83/30)*$M83)*$R83 -> 0 | CM83: =+AK83 -> 0 | CN83: =AL83 -> 0 | CO83: =AM83 -> 0 | CP83: =AN83 -> 0 | CQ83: =AS83+AX83 -> 0 | CR83: =(CK83+CN83+CP83)*0.1267 -> 0 | CS83: =SUM(CK83:CR83)-CM83-CO83 -> 0 | CU83: ECONACIONAL | CV83: =IF($CU83="PROQUIMA",$BA83+$BJ83+$BS83+$CB83+$CK83,0) -> 0 | CW83: =IF($CU83="PROQUIMA",$BB83+$BK83+$BT83+$CC83+$CL83,0) -> 0 | CX83: =IF($CU83="PROQUIMA",$BC83+$BL83+$BU83+$CD83+$CM83,0) -> 0 | CY83: =IF($CU83="PROQUIMA",$BD83+$BM83+$BV83+$CE83+$CN83,0) -> 0 | CZ83: =IF($CU83="PROQUIMA",$BE83+$BN83+$BW83+$CF83+$CO83,0) -> 0 | DA83: =IF($CU83="PROQUIMA",$BF83+$BO83+$BX83+$CG83+$CP83,0) -> 0 | DB83: =IF($CU83="PROQUIMA",$BG83+$BP83+$BY83+$CH83+$CQ83,0) -> 0 | DC83: =IF($CU83="PROQUIMA",$BH83+$BQ83+$BZ83+$CI83+CR83,0) -> 0 | DD83: =SUM(CV83:DC83)-CX83-CZ83 -> 0 | DE83: =IF($CU83="UNHESA",$BA83+$BJ83+$BS83+$CB83+$CK83,0) -> 0 | DF83: =IF($CU83="UNHESA",$BB83+$BK83+$BT83+$CC83+$CL83,0) -> 0 | DG83: =IF($CU83="UNHESA",$BC83+$BL83+$BU83+$CD83+$CM83,0) -> 0 | DH83: =IF($CU83="UNHESA",$BD83+$BM83+$BV83+$CE83+$CN83,0) -> 0 | DI83: =IF($CU83="UNHESA",$BE83+$BN83+$BW83+$CF83+$CO83,0) -> 0 | DJ83: =IF($CU83="UNHESA",$BF83+$BO83+$BX83+$CG83+$CP83,0) -> 0 | DK83: =IF($CU83="UNHESA",$BG83+$BP83+$BY83+$CH83+$CQ83,0) -> 0 | DL83: =IF($CU83="UNHESA",$BH83+$BQ83+$BZ83+$CI83+$CR83,0) -> 0 | DM83: =SUM(DE83:DL83)-DG83-DI83 -> 0 | DN83: =IF($CU83="UNHESA LIQUIDOS",$BA83+$BJ83+$BS83+$CB83+$CK83,0) -> 0 | DO83: =IF($CU83="UNHESA LIQUIDOS",$BB83+$BK83+$BT83+$CC83+$CL83,0) -> 0 | DP83: =IF($CU83="UNHESA LIQUIDOS",$BC83+$BL83+$BU83+$CD83+$CM83,0) -> 0 | DQ83: =IF($CU83="UNHESA LIQUIDOS",$BD83+$BM83+$BV83+$CE83+$CN83,0) -> 0 | DR83: =IF($CU83="UNHESA LIQUIDOS",$BE83+$BN83+$BW83+$CF83+$CO83,0) -> 0 | DS83: =IF($CU83="UNHESA LIQUIDOS",$BF83+$BO83+$BX83+$CG83+$CP83,0) -> 0 | DT83: =IF($CU83="UNHESA LIQUIDOS",$BG83+$BP83+$BY83+$CH83+$CQ83,0) -> 0 | DU83: =IF($CU83="UNHESA LIQUIDOS",$BH83+$BQ83+$BZ83+$CI83+$CR83,0) -> 0 | DV83: =SUM(DN83:DU83)-DP83-DR83 -> 0 | DW83: =IF($CU83="CLEARTEC",$BA83+$BJ83+$BS83+$CB83+$CK83,0) -> 0 | DX83: =IF($CU83="CLEARTEC",$BA83+$BJ83+$BS83+$CB83+$CK83,0) -> 0 | DY83: =IF($CU83="CLEARTEC",$BA83+$BJ83+$BS83+$CB83+$CK83,0) -> 0 | DZ83: =IF($CU83="CLEARTEC",$BA83+$BJ83+$BS83+$CB83+$CK83,0) -> 0 | EA83: =IF($CU83="CLEARTEC",$BA83+$BJ83+$BS83+$CB83+$CK83,0) -> 0 | EB83: =IF($CU83="CLEARTEC",$BA83+$BJ83+$BS83+$CB83+$CK83,0) -> 0 | EC83: =IF($CU83="CLEARTEC",$BA83+$BJ83+$BS83+$CB83+$CK83,0) -> 0 | ED83: =IF($CU83="CLEARTEC",$BA83+$BJ83+$BS83+$CB83+$CK83,0) -> 0 | EE83: =SUM(DW83:ED83)-DY83-EA83 -> 0 | EF83: =IF(CU83="ECONACIONAL",$BA83+$BJ83+$BS83+$CB83+$CK83) -> 4100 | EG83: =IF($CU83="ECONACIONAL",$BB83+$BK83+$BT83+$CC83+$CL83,0) -> 730 | EH83: =IF(CU83="ECONACIONAL",$BC83+$BL83+$BU83+$CD83+$CM83) -> 24 | EI83: =IF(CU83="ECONACIONAL",$BD83+$DH83+$DQ83+$DZ83+BM83+BV83+CE83+CN83) -> 615 | EJ83: =IF($CU83="CLEARTEC",$BE83+$BN83+$BW83+$CF83+$CO83,0) -> 0 | EK83: =IF(CU83="ECONACIONAL",$BF83+$BO83+$BX83+$CG83+$CP83) -> 0 | EL83: =IF(CU83="ECONACIONAL",$BG83+$BP83+$BY83+$CH83+$CQ83) -> 0 | EM83: =IF(CU83="ECONACIONAL",BH83+BQ83+BZ83+CI83+CR83) -> 597.3905 | EN83: =SUM(EF83:EM83)-EH83-EJ83 -> 6042.3905 | EP83: 182 | EY83: =+ET83+EU83+EV83 -> 0 | FA83: =IF($M83<=15,EP83/2,EP83) -> 182 | FB83: =IF($M83<=15,EQ83/2,EQ83) -> 0 | FC83: =IF($M83<=15,ER83/2,ER83) -> 0 | FD83: =IF($M83<=15,ES83/2,ES83) -> 0 | FE83: =IF($M83<=15,ET83/2,ET83) -> 0 | FF83: =IF($M83<=15,EU83/2,EU83) -> 0 | FG83: =IF($M83<=15,EV83/2,EV83) -> 0 | FH83: =IF($M83<=15,EW83/2,EW83) -> 0 | ... FJ83: =IF($M83<=15,EY83/2,EY83) -> 0 | FR83: =(((J83/30/8)*1.5)*(U83+Y83+AC83))-(BD83+BM83+BV83) -> 0 | FS83: =(((J83/30/8)*2)*(W83+AA83+AE83))-(BF83+BO83+BX83) -> 0 | FT83: =(SUM(BA83:CJ83))-(SUM(EF83:EN83)) -> 0 | FU83: =(J83/30*M83)-(EF83) -> 0 | FV83: =(SUM(EP83:EY83))-((SUM(FA83:FJ83))*$FV$5) -> -182
H84: Admón. | J84: =SUM(J82:J83) -> 9600 | K84: =SUM(K82:K83) -> 3750 | L84: =SUM(L82:L83) -> 13350 | U84: =SUM(U82:U83) -> 0 | V84: =SUM(V82:V83) -> 0 | W84: =SUM(W82:W83) -> 0 | X84: =SUM(X82:X83) -> 0 | Y84: =SUM(Y82:Y83) -> 24 | Z84: =SUM(Z82:Z83) -> 615 | AA84: =SUM(AA82:AA83) -> 0 | AB84: =SUM(AB82:AB83) -> 0 | ... EN84: =SUM(EN82:EN83) -> 16739.24 | EP84: =SUM(EP82:EP83) -> 381.22 | EQ84: =SUM(EQ82:EQ83) -> 0 | ER84: =SUM(ER82:ER83) -> 0 | ES84: =SUM(ES82:ES83) -> 0 | ET84: =SUM(ET82:ET83) -> 0 | EU84: =SUM(EU82:EU83) -> 0 | EV84: =SUM(EV82:EV83) -> 0 | EW84: =SUM(EW82:EW83) -> 0 | ... EY84: =SUM(EY82:EY83) -> 0 | FA84: =SUM(FA82:FA83) -> 381.22 | FB84: =SUM(FB82:FB83) -> 0 | FC84: =SUM(FC82:FC83) -> 0 | FD84: =SUM(FD82:FD83) -> 0 | FE84: =SUM(FE82:FE83) -> 0 | FF84: =SUM(FF82:FF83) -> 0 | FG84: =SUM(FG82:FG83) -> 0 | FH84: =SUM(FH82:FH83) -> 0 | ... FP84: =SUM(FP82:FP83) -> 0
G85: BODEGA MP
A86: =$G$4 -> JUNIO 2026 2da QUINCENA | B86: =+$G$5 -> 2026 | C86: =A86 & B86 -> JUNIO 2026 2da QUINCENA2026 | D86: =+$G$85 -> BODEGA MP | E86: 302020 | F86: 29 | G86: Sanchez José Nelson | H86: Operador de montacargas | I86: ECONACIONAL | J86: 4500 | K86: 350 | L86: =+J86+K86 -> 4850 | M86: 26 | N86: 0.4 | O86: 0.4 | P86: 0.2 | Q86: 0 | R86: 0 | S86: =SUM(N86:R86) -> 1 | T86: susp del 2 al 5/ alta el 6 | U86: 8 | V86: =($J86/30/8*1.5)*U86 -> 225 | X86: =($J86/30/8*2)*W86 -> 0 | Z86: =($J86/30/8*1.5)*Y86 -> 0 | AB86: =($J86/30/8*2)*AA86 -> 0 | AD86: =(($J86/30/8)*1.5)*AC86 -> 0 | AF86: =(($J86/30/8)*2)*AE86 -> 0 | AH86: =(($J86/30/8)*1.5)*AG86 -> 0 | AJ86: =(($J86/30/8)*2)*AI86 -> 0 | AL86: =(($J86/30/8)*1.5)*AK86 -> 0 | AN86: =(($J86/30/8)*2)*AM86 -> 0 | BA86: =((J86/30)*M86)*$N86 -> 1560 | BB86: =((K86/30)*M86)*$N86+240 -> 361.33333 | BC86: =U86 -> 8 | BD86: =V86 -> 225 | BE86: =W86 -> 0 | BF86: =X86 -> 0 | BG86: =AO86+AT86 -> 0 | BH86: =(BA86+BD86+BF86+BG86)*0.1267 -> 226.1595 | BI86: =SUM(BA86:BH86)-BC86-BE86 -> 2372.4928 | BJ86: =(($J86/30)*$M86)*$O86 -> 1560 | BK86: =(($K86/30)*$M86)*$O86+480+1200 -> 1801.3333 | BL86: =Y86 -> 0 | BM86: =Z86 -> 0 | BN86: =AA86 -> 0 | BO86: =AB86 -> 0 | BP86: =AP86+AU86 -> 0 | BQ86: =(+BJ86+BM86+BO86+BP86)*0.1267 -> 197.652 | BR86: =SUM(BJ86:BQ86)-BL86-BN86 -> 3558.9853 | BS86: =(($J86/30)*$M86)*$P86 -> 780 | BT86: =(($K86/30)*$M86)*$P86 -> 60.666667 | BU86: =AC86 -> 0 | BV86: =AD86 -> 0 | BW86: =AE86 -> 0 | BX86: =AF86 -> 0 | BY86: =AQ86+AV86 -> 0 | BZ86: =(BS86+BV86+BX86+BY86)*0.1267 -> 98.826 | CA86: =SUM(BS86:BZ86)-BU86-BW86 -> 939.49267 | CB86: =(($J86/30)*$M86)*$Q86 -> 0 | CC86: =(($K86/30)*$M86)*$Q86 -> 0 | CD86: =AG86 -> 0 | CE86: =AH86 -> 0 | CF86: =AI86 -> 0 | CG86: =AJ86 -> 0 | CH86: =AR86+AW86 -> 0 | CI86: =(CB86+CE86+CG86+CH86)*0.1267 -> 0 | CJ86: =SUM(CB86:CI86)-CD86-CF86 -> 0 | CK86: =(($J86/30)*$M86)*R86 -> 0 | CL86: =(($K86/30)*$M86)*$R86 -> 0 | CM86: =+AK86 -> 0 | CN86: =AL86 -> 0 | CO86: =AM86 -> 0 | CP86: =AN86 -> 0 | CQ86: =AS86+AX86 -> 0 | CR86: =(CK86+CN86+CP86)*0.1267 -> 0 | CS86: =SUM(CK86:CR86)-CM86-CO86 -> 0 | CU86: ECONACIONAL | CV86: =IF($CU86="PROQUIMA",$BA86+$BJ86+$BS86+$CB86+$CK86,0) -> 0 | CW86: =IF($CU86="PROQUIMA",$BB86+$BK86+$BT86+$CC86+$CL86,0) -> 0 | CX86: =IF($CU86="PROQUIMA",$BC86+$BL86+$BU86+$CD86+$CM86,0) -> 0 | CY86: =IF($CU86="PROQUIMA",$BD86+$BM86+$BV86+$CE86+$CN86,0) -> 0 | CZ86: =IF($CU86="PROQUIMA",$BE86+$BN86+$BW86+$CF86+$CO86,0) -> 0 | DA86: =IF($CU86="PROQUIMA",$BF86+$BO86+$BX86+$CG86+$CP86,0) -> 0 | DB86: =IF($CU86="PROQUIMA",$BG86+$BP86+$BY86+$CH86+$CQ86,0) -> 0 | DC86: =IF($CU86="PROQUIMA",$BH86+$BQ86+$BZ86+$CI86+CR86,0) -> 0 | DD86: =SUM(CV86:DC86)-CX86-CZ86 -> 0 | DE86: =IF($CU86="UNHESA",$BA86+$BJ86+$BS86+$CB86+$CK86,0) -> 0 | DF86: =IF($CU86="UNHESA",$BB86+$BK86+$BT86+$CC86+$CL86,0) -> 0 | DG86: =IF($CU86="UNHESA",$BC86+$BL86+$BU86+$CD86+$CM86,0) -> 0 | DH86: =IF($CU86="UNHESA",$BD86+$BM86+$BV86+$CE86+$CN86,0) -> 0 | DI86: =IF($CU86="UNHESA",$BE86+$BN86+$BW86+$CF86+$CO86,0) -> 0 | DJ86: =IF($CU86="UNHESA",$BF86+$BO86+$BX86+$CG86+$CP86,0) -> 0 | DK86: =IF($CU86="UNHESA",$BG86+$BP86+$BY86+$CH86+$CQ86,0) -> 0 | DL86: =IF($CU86="UNHESA",$BH86+$BQ86+$BZ86+$CI86+$CR86,0) -> 0 | DM86: =SUM(DE86:DL86)-DG86-DI86 -> 0 | DN86: =IF($CU86="UNHESA LIQUIDOS",$BA86+$BJ86+$BS86+$CB86+$CK86,0) -> 0 | DO86: =IF($CU86="UNHESA LIQUIDOS",$BB86+$BK86+$BT86+$CC86+$CL86,0) -> 0 | DP86: =IF($CU86="UNHESA LIQUIDOS",$BC86+$BL86+$BU86+$CD86+$CM86,0) -> 0 | DQ86: =IF($CU86="UNHESA LIQUIDOS",$BD86+$BM86+$BV86+$CE86+$CN86,0) -> 0 | DR86: =IF($CU86="UNHESA LIQUIDOS",$BE86+$BN86+$BW86+$CF86+$CO86,0) -> 0 | DS86: =IF($CU86="UNHESA LIQUIDOS",$BF86+$BO86+$BX86+$CG86+$CP86,0) -> 0 | DT86: =IF($CU86="UNHESA LIQUIDOS",$BG86+$BP86+$BY86+$CH86+$CQ86,0) -> 0 | DU86: =IF($CU86="UNHESA LIQUIDOS",$BH86+$BQ86+$BZ86+$CI86+$CR86,0) -> 0 | DV86: =SUM(DN86:DU86)-DP86-DR86 -> 0 | DW86: =IF($CU86="CLEARTEC",$BA86+$BJ86+$BS86+$CB86+$CK86,0) -> 0 | DX86: =IF($CU86="CLEARTEC",$BA86+$BJ86+$BS86+$CB86+$CK86,0) -> 0 | DY86: =IF($CU86="CLEARTEC",$BA86+$BJ86+$BS86+$CB86+$CK86,0) -> 0 | DZ86: =IF($CU86="CLEARTEC",$BA86+$BJ86+$BS86+$CB86+$CK86,0) -> 0 | EA86: =IF($CU86="CLEARTEC",$BA86+$BJ86+$BS86+$CB86+$CK86,0) -> 0 | EB86: =IF($CU86="CLEARTEC",$BA86+$BJ86+$BS86+$CB86+$CK86,0) -> 0 | EC86: =IF($CU86="CLEARTEC",$BA86+$BJ86+$BS86+$CB86+$CK86,0) -> 0 | ED86: =IF($CU86="CLEARTEC",$BA86+$BJ86+$BS86+$CB86+$CK86,0) -> 0 | EE86: =SUM(DW86:ED86)-DY86-EA86 -> 0 | EF86: =IF(CU86="ECONACIONAL",$BA86+$BJ86+$BS86+$CB86+$CK86) -> 3900 | EG86: =IF($CU86="ECONACIONAL",$BB86+$BK86+$BT86+$CC86+$CL86,0) -> 2223.3333 | EH86: =IF(CU86="ECONACIONAL",$BC86+$BL86+$BU86+$CD86+$CM86) -> 8 | EI86: =IF(CU86="ECONACIONAL",$BD86+$DH86+$DQ86+$DZ86+BM86+BV86+CE86+CN86) -> 225 | EJ86: =IF($CU86="CLEARTEC",$BE86+$BN86+$BW86+$CF86+$CO86,0) -> 0 | EK86: =IF(CU86="ECONACIONAL",$BF86+$BO86+$BX86+$CG86+$CP86) -> 0 | EL86: =IF(CU86="ECONACIONAL",$BG86+$BP86+$BY86+$CH86+$CQ86) -> 0 | EM86: =IF(CU86="ECONACIONAL",BH86+BQ86+BZ86+CI86+CR86) -> 522.6375 | EN86: =SUM(EF86:EM86)-EH86-EJ86 -> 6870.9708 | EP86: 290 | EY86: =+ET86+EU86+EV86 -> 0 | FA86: =IF($M86<=15,EP86/2,EP86) -> 290 | FB86: =IF($M86<=15,EQ86/2,EQ86) -> 0 | FC86: =IF($M86<=15,ER86/2,ER86) -> 0 | FD86: =IF($M86<=15,ES86/2,ES86) -> 0 | FE86: =IF($M86<=15,ET86/2,ET86) -> 0 | FF86: =IF($M86<=15,EU86/2,EU86) -> 0 | FG86: =IF($M86<=15,EV86/2,EV86) -> 0 | FH86: =IF($M86<=15,EW86/2,EW86) -> 0 | ... FJ86: =IF($M86<=15,EY86/2,EY86) -> 0 | FK86: 0.4 | FL86: 0.4 | FM86: 0.2 | FN86: 0 | FO86: 0 | FP86: =FO86+FN86+FM86+FL86+FK86 -> 1 | FR86: =(((J86/30/8)*1.5)*(U86+Y86+AC86))-(BD86+BM86+BV86) -> 0 | FS86: =(((J86/30/8)*2)*(W86+AA86+AE86))-(BF86+BO86+BX86) -> 0 | FT86: =(SUM(BA86:CJ86))-(SUM(EF86:EN86)) -> 0 | FU86: =(J86/30*M86)-(EF86) -> 0 | FV86: =(SUM(EP86:EY86))-((SUM(FA86:FJ86))*$FV$5) -> -290
A87: =$G$4 -> JUNIO 2026 2da QUINCENA | B87: =+$G$5 -> 2026 | C87: =A87 & B87 -> JUNIO 2026 2da QUINCENA2026 | D87: =+$G$85 -> BODEGA MP | E87: 302020 | F87: =+F86+1 -> 30 | G87: Mendizabal Rosales Edgar Osvaldo | H87: Encargado de Bodega MP | I87: ECONACIONAL | J87: 4500 | K87: 502.28 | L87: =+J87+K87 -> 5002.28 | M87: 30 | N87: 0.5 | O87: 0.3 | P87: 0.2 | Q87: 0 | R87: 0 | S87: =SUM(N87:R87) -> 1 | U87: 7 | V87: =($J87/30/8*1.5)*U87 -> 196.875 | X87: =($J87/30/8*2)*W87 -> 0 | Z87: =($J87/30/8*1.5)*Y87 -> 0 | AB87: =($J87/30/8*2)*AA87 -> 0 | AD87: =(($J87/30/8)*1.5)*AC87 -> 0 | AF87: =(($J87/30/8)*2)*AE87 -> 0 | AH87: =(($J87/30/8)*1.5)*AG87 -> 0 | AJ87: =(($J87/30/8)*2)*AI87 -> 0 | AL87: =(($J87/30/8)*1.5)*AK87 -> 0 | AN87: =(($J87/30/8)*2)*AM87 -> 0 | BA87: =((J87/30)*M87)*$N87 -> 2250 | BB87: =((K87/30)*M87)*$N87+230 -> 481.14 | BC87: =U87 -> 7 | BD87: =V87 -> 196.875 | BE87: =W87 -> 0 | BF87: =X87 -> 0 | BG87: =AO87+AT87 -> 0 | BH87: =(BA87+BD87+BF87+BG87)*0.1267 -> 310.01906 | BI87: =SUM(BA87:BH87)-BC87-BE87 -> 3238.0341 | BJ87: =(($J87/30)*$M87)*$O87 -> 1350 | BK87: =(($K87/30)*$M87)*$O87+230 -> 380.684 | BL87: =Y87 -> 0 | BM87: =Z87 -> 0 | BN87: =AA87 -> 0 | BO87: =AB87 -> 0 | BP87: =AP87+AU87 -> 0 | BQ87: =(+BJ87+BM87+BO87+BP87)*0.1267 -> 171.045 | BR87: =SUM(BJ87:BQ87)-BL87-BN87 -> 1901.729 | BS87: =(($J87/30)*$M87)*$P87 -> 900 | BT87: =(($K87/30)*$M87)*$P87 -> 100.456 | BU87: =AC87 -> 0 | BV87: =AD87 -> 0 | BW87: =AE87 -> 0 | BX87: =AF87 -> 0 | BY87: =AQ87+AV87 -> 0 | BZ87: =(BS87+BV87+BX87+BY87)*0.1267 -> 114.03 | CA87: =SUM(BS87:BZ87)-BU87-BW87 -> 1114.486 | CB87: =(($J87/30)*$M87)*$Q87 -> 0 | CC87: =(($K87/30)*$M87)*$Q87 -> 0 | CD87: =AG87 -> 0 | CE87: =AH87 -> 0 | CF87: =AI87 -> 0 | CG87: =AJ87 -> 0 | CH87: =AR87+AW87 -> 0 | CI87: =(CB87+CE87+CG87+CH87)*0.1267 -> 0 | CJ87: =SUM(CB87:CI87)-CD87-CF87 -> 0 | CK87: =(($J87/30)*$M87)*R87 -> 0 | CL87: =(($K87/30)*$M87)*$R87 -> 0 | CM87: =+AK87 -> 0 | CN87: =AL87 -> 0 | CO87: =AM87 -> 0 | CP87: =AN87 -> 0 | CQ87: =AS87+AX87 -> 0 | CR87: =(CK87+CN87+CP87)*0.1267 -> 0 | CS87: =SUM(CK87:CR87)-CM87-CO87 -> 0 | CU87: ECONACIONAL | CV87: =IF($CU87="PROQUIMA",$BA87+$BJ87+$BS87+$CB87+$CK87,0) -> 0 | CW87: =IF($CU87="PROQUIMA",$BB87+$BK87+$BT87+$CC87+$CL87,0) -> 0 | CX87: =IF($CU87="PROQUIMA",$BC87+$BL87+$BU87+$CD87+$CM87,0) -> 0 | CY87: =IF($CU87="PROQUIMA",$BD87+$BM87+$BV87+$CE87+$CN87,0) -> 0 | CZ87: =IF($CU87="PROQUIMA",$BE87+$BN87+$BW87+$CF87+$CO87,0) -> 0 | DA87: =IF($CU87="PROQUIMA",$BF87+$BO87+$BX87+$CG87+$CP87,0) -> 0 | DB87: =IF($CU87="PROQUIMA",$BG87+$BP87+$BY87+$CH87+$CQ87,0) -> 0 | DC87: =IF($CU87="PROQUIMA",$BH87+$BQ87+$BZ87+$CI87+CR87,0) -> 0 | DD87: =SUM(CV87:DC87)-CX87-CZ87 -> 0 | DE87: =IF($CU87="UNHESA",$BA87+$BJ87+$BS87+$CB87+$CK87,0) -> 0 | DF87: =IF($CU87="UNHESA",$BB87+$BK87+$BT87+$CC87+$CL87,0) -> 0 | DG87: =IF($CU87="UNHESA",$BC87+$BL87+$BU87+$CD87+$CM87,0) -> 0 | DH87: =IF($CU87="UNHESA",$BD87+$BM87+$BV87+$CE87+$CN87,0) -> 0 | DI87: =IF($CU87="UNHESA",$BE87+$BN87+$BW87+$CF87+$CO87,0) -> 0 | DJ87: =IF($CU87="UNHESA",$BF87+$BO87+$BX87+$CG87+$CP87,0) -> 0 | DK87: =IF($CU87="UNHESA",$BG87+$BP87+$BY87+$CH87+$CQ87,0) -> 0 | DL87: =IF($CU87="UNHESA",$BH87+$BQ87+$BZ87+$CI87+$CR87,0) -> 0 | DM87: =SUM(DE87:DL87)-DG87-DI87 -> 0 | DN87: =IF($CU87="UNHESA LIQUIDOS",$BA87+$BJ87+$BS87+$CB87+$CK87,0) -> 0 | DO87: =IF($CU87="UNHESA LIQUIDOS",$BB87+$BK87+$BT87+$CC87+$CL87,0) -> 0 | DP87: =IF($CU87="UNHESA LIQUIDOS",$BC87+$BL87+$BU87+$CD87+$CM87,0) -> 0 | DQ87: =IF($CU87="UNHESA LIQUIDOS",$BD87+$BM87+$BV87+$CE87+$CN87,0) -> 0 | DR87: =IF($CU87="UNHESA LIQUIDOS",$BE87+$BN87+$BW87+$CF87+$CO87,0) -> 0 | DS87: =IF($CU87="UNHESA LIQUIDOS",$BF87+$BO87+$BX87+$CG87+$CP87,0) -> 0 | DT87: =IF($CU87="UNHESA LIQUIDOS",$BG87+$BP87+$BY87+$CH87+$CQ87,0) -> 0 | DU87: =IF($CU87="UNHESA LIQUIDOS",$BH87+$BQ87+$BZ87+$CI87+$CR87,0) -> 0 | DV87: =SUM(DN87:DU87)-DP87-DR87 -> 0 | DW87: =IF($CU87="CLEARTEC",$BA87+$BJ87+$BS87+$CB87+$CK87,0) -> 0 | DX87: =IF($CU87="CLEARTEC",$BA87+$BJ87+$BS87+$CB87+$CK87,0) -> 0 | DY87: =IF($CU87="CLEARTEC",$BA87+$BJ87+$BS87+$CB87+$CK87,0) -> 0 | DZ87: =IF($CU87="CLEARTEC",$BA87+$BJ87+$BS87+$CB87+$CK87,0) -> 0 | EA87: =IF($CU87="CLEARTEC",$BA87+$BJ87+$BS87+$CB87+$CK87,0) -> 0 | EB87: =IF($CU87="CLEARTEC",$BA87+$BJ87+$BS87+$CB87+$CK87,0) -> 0 | EC87: =IF($CU87="CLEARTEC",$BA87+$BJ87+$BS87+$CB87+$CK87,0) -> 0 | ED87: =IF($CU87="CLEARTEC",$BA87+$BJ87+$BS87+$CB87+$CK87,0) -> 0 | EE87: =SUM(DW87:ED87)-DY87-EA87 -> 0 | EF87: =IF(CU87="ECONACIONAL",$BA87+$BJ87+$BS87+$CB87+$CK87) -> 4500 | EG87: =IF($CU87="ECONACIONAL",$BB87+$BK87+$BT87+$CC87+$CL87,0) -> 962.28 | EH87: =IF(CU87="ECONACIONAL",$BC87+$BL87+$BU87+$CD87+$CM87) -> 7 | EI87: =IF(CU87="ECONACIONAL",$BD87+$DH87+$DQ87+$DZ87+BM87+BV87+CE87+CN87) -> 196.875 | EJ87: =IF($CU87="CLEARTEC",$BE87+$BN87+$BW87+$CF87+$CO87,0) -> 0 | EK87: =IF(CU87="ECONACIONAL",$BF87+$BO87+$BX87+$CG87+$CP87) -> 0 | EL87: =IF(CU87="ECONACIONAL",$BG87+$BP87+$BY87+$CH87+$CQ87) -> 0 | EM87: =IF(CU87="ECONACIONAL",BH87+BQ87+BZ87+CI87+CR87) -> 595.09406 | EN87: =SUM(EF87:EM87)-EH87-EJ87 -> 6254.2491 | EP87: 218 | ER87: 650 | ES87: =213.5+308.5 -> 522 | EY87: =+ET87+EU87+EV87 -> 0 | FA87: =IF($M87<=15,EP87/2,EP87) -> 218 | FB87: =IF($M87<=15,EQ87/2,EQ87) -> 0 | FC87: =IF($M87<=15,ER87/2,ER87) -> 650 | FD87: =IF($M87<=15,ES87/2,ES87) -> 522 | FE87: =IF($M87<=15,ET87/2,ET87) -> 0 | FF87: =IF($M87<=15,EU87/2,EU87) -> 0 | FG87: =IF($M87<=15,EV87/2,EV87) -> 0 | FH87: =IF($M87<=15,EW87/2,EW87) -> 0 | ... FJ87: =IF($M87<=15,EY87/2,EY87) -> 0 | FR87: =(((J87/30/8)*1.5)*(U87+Y87+AC87))-(BD87+BM87+BV87) -> 0 | FS87: =(((J87/30/8)*2)*(W87+AA87+AE87))-(BF87+BO87+BX87) -> 0 | FT87: =(SUM(BA87:CJ87))-(SUM(EF87:EN87)) -> 0 | FU87: =(J87/30*M87)-(EF87) -> 0 | FV87: =(SUM(EP87:EY87))-((SUM(FA87:FJ87))*$FV$5) -> -1390
E88: 302020 | G88: Quevedo Turcios Julio Cesar | H88: Auxiliar de Bodega | I88: ECONACIONAL | J88: 4002.28 | K88: 250 | L88: =+J88+K88 -> 4252.28 | M88: 30 | N88: 0.5 | O88: 0.3 | P88: 0.2 | Q88: 0 | R88: 0 | S88: =SUM(N88:R88) -> 1 | U88: 2 | V88: =($J88/30/8*1.5)*U88 -> 50.0285 | X88: =($F88/30/8*2)*W88 -> 0 | Z88: =($J88/30/8*1.5)*Y88 -> 0 | AB88: =($F88/30/8*2)*AA88 -> 0 | AD88: =(($F88/30/8)*1.5)*AC88 -> 0 | AF88: =(($F88/30/8)*2)*AE88 -> 0 | AH88: =(($F88/30/8)*1.5)*AG88 -> 0 | AJ88: =(($F88/30/8)*2)*AI88 -> 0 | AL88: =(($F88/30/8)*1.5)*AK88 -> 0 | AN88: =(($F88/30/8)*2)*AM88 -> 0 | BA88: =((J88/30)*M88)*$N88 -> 2001.14 | BB88: =((K88/30)*M88)*$N88+86.25 -> 211.25 | BC88: =U88 -> 2 | BD88: =V88 -> 50.0285 | BE88: =W88 -> 0 | BF88: =X88 -> 0 | BG88: =AO88+AT88 -> 0 | BH88: =(BA88+BD88+BF88+BG88)*0.1267 -> 259.88305 | BI88: =SUM(BA88:BH88)-BC88-BE88 -> 2522.3015 | BJ88: =(($J88/30)*$M88)*$O88 -> 1200.684 | BK88: =(($K88/30)*$M88)*$O88+86.25 -> 161.25 | BL88: =Y88 -> 0 | BM88: =Z88 -> 0 | BN88: =AA88 -> 0 | BO88: =AB88 -> 0 | BP88: =AP88+AU88 -> 0 | BQ88: =(+BJ88+BM88+BO88+BP88)*0.1267 -> 152.12666 | BR88: =SUM(BJ88:BQ88)-BL88-BN88 -> 1514.0607 | BS88: =(($J88/30)*$M88)*$P88 -> 800.456 | BT88: =(($K88/30)*$M88)*$P88 -> 50 | BU88: =AC88 -> 0 | BV88: =AD88 -> 0 | BW88: =AE88 -> 0 | BX88: =AF88 -> 0 | BY88: =AQ88+AV88 -> 0 | BZ88: =(BS88+BV88+BX88+BY88)*0.1267 -> 101.41778 | CA88: =SUM(BS88:BZ88)-BU88-BW88 -> 951.87378 | CB88: =(($J88/30)*$M88)*$Q88 -> 0 | CC88: =(($K88/30)*$M88)*$Q88 -> 0 | CD88: =AG88 -> 0 | CE88: =AH88 -> 0 | CF88: =AI88 -> 0 | CG88: =AJ88 -> 0 | CH88: =AR88+AW88 -> 0 | CI88: =(CB88+CE88+CG88+CH88)*0.1267 -> 0 | CJ88: =SUM(CB88:CI88)-CD88-CF88 -> 0 | CK88: =(($J88/30)*$M88)*R88 -> 0 | CL88: =(($K88/30)*$M88)*$R88 -> 0 | CM88: =+AK88 -> 0 | CN88: =AL88 -> 0 | CO88: =AM88 -> 0 | CP88: =AN88 -> 0 | CQ88: =AS88+AX88 -> 0 | CR88: =(CK88+CN88+CP88)*0.1267 -> 0 | CS88: =SUM(CK88:CR88)-CM88-CO88 -> 0 | CU88: ECONACIONAL | CV88: =IF($CU88="PROQUIMA",$BA88+$BJ88+$BS88+$CB88+$CK88,0) -> 0 | CW88: =IF($CU88="PROQUIMA",$BB88+$BK88+$BT88+$CC88+$CL88,0) -> 0 | CX88: =IF($CU88="PROQUIMA",$BC88+$BL88+$BU88+$CD88+$CM88,0) -> 0 | CY88: =IF($CU88="PROQUIMA",$BD88+$BM88+$BV88+$CE88+$CN88,0) -> 0 | CZ88: =IF($CU88="PROQUIMA",$BE88+$BN88+$BW88+$CF88+$CO88,0) -> 0 | DA88: =IF($CU88="PROQUIMA",$BF88+$BO88+$BX88+$CG88+$CP88,0) -> 0 | DB88: =IF($CU88="PROQUIMA",$BG88+$BP88+$BY88+$CH88+$CQ88,0) -> 0 | DC88: =IF($CU88="PROQUIMA",$BH88+$BQ88+$BZ88+$CI88+CR88,0) -> 0 | DD88: =SUM(CV88:DC88)-CX88-CZ88 -> 0 | DE88: =IF($CU88="UNHESA",$BA88+$BJ88+$BS88+$CB88+$CK88,0) -> 0 | DF88: =IF($CU88="UNHESA",$BB88+$BK88+$BT88+$CC88+$CL88,0) -> 0 | DG88: =IF($CU88="UNHESA",$BC88+$BL88+$BU88+$CD88+$CM88,0) -> 0 | DH88: =IF($CU88="UNHESA",$BD88+$BM88+$BV88+$CE88+$CN88,0) -> 0 | DI88: =IF($CU88="UNHESA",$BE88+$BN88+$BW88+$CF88+$CO88,0) -> 0 | DJ88: =IF($CU88="UNHESA",$BF88+$BO88+$BX88+$CG88+$CP88,0) -> 0 | DK88: =IF($CU88="UNHESA",$BG88+$BP88+$BY88+$CH88+$CQ88,0) -> 0 | DL88: =IF($CU88="UNHESA",$BH88+$BQ88+$BZ88+$CI88+$CR88,0) -> 0 | DM88: =SUM(DE88:DL88)-DG88-DI88 -> 0 | DN88: =IF($CU88="UNHESA LIQUIDOS",$BA88+$BJ88+$BS88+$CB88+$CK88,0) -> 0 | DO88: =IF($CU88="UNHESA LIQUIDOS",$BB88+$BK88+$BT88+$CC88+$CL88,0) -> 0 | DP88: =IF($CU88="UNHESA LIQUIDOS",$BC88+$BL88+$BU88+$CD88+$CM88,0) -> 0 | DQ88: =IF($CU88="UNHESA LIQUIDOS",$BD88+$BM88+$BV88+$CE88+$CN88,0) -> 0 | DR88: =IF($CU88="UNHESA LIQUIDOS",$BE88+$BN88+$BW88+$CF88+$CO88,0) -> 0 | DS88: =IF($CU88="UNHESA LIQUIDOS",$BF88+$BO88+$BX88+$CG88+$CP88,0) -> 0 | DT88: =IF($CU88="UNHESA LIQUIDOS",$BG88+$BP88+$BY88+$CH88+$CQ88,0) -> 0 | DU88: =IF($CU88="UNHESA LIQUIDOS",$BH88+$BQ88+$BZ88+$CI88+$CR88,0) -> 0 | DV88: =SUM(DN88:DU88)-DP88-DR88 -> 0 | DW88: =IF($CU88="CLEARTEC",$BA88+$BJ88+$BS88+$CB88+$CK88,0) -> 0 | DX88: =IF($CU88="CLEARTEC",$BA88+$BJ88+$BS88+$CB88+$CK88,0) -> 0 | DY88: =IF($CU88="CLEARTEC",$BA88+$BJ88+$BS88+$CB88+$CK88,0) -> 0 | DZ88: =IF($CU88="CLEARTEC",$BA88+$BJ88+$BS88+$CB88+$CK88,0) -> 0 | EA88: =IF($CU88="CLEARTEC",$BA88+$BJ88+$BS88+$CB88+$CK88,0) -> 0 | EB88: =IF($CU88="CLEARTEC",$BA88+$BJ88+$BS88+$CB88+$CK88,0) -> 0 | EC88: =IF($CU88="CLEARTEC",$BA88+$BJ88+$BS88+$CB88+$CK88,0) -> 0 | ED88: =IF($CU88="CLEARTEC",$BA88+$BJ88+$BS88+$CB88+$CK88,0) -> 0 | EE88: =SUM(DW88:ED88)-DY88-EA88 -> 0 | EF88: =IF(CU88="ECONACIONAL",$BA88+$BJ88+$BS88+$CB88+$CK88) -> 4002.28 | EG88: =IF($CU88="ECONACIONAL",$BB88+$BK88+$BT88+$CC88+$CL88,0) -> 422.5 | EH88: =IF(CU88="ECONACIONAL",$BC88+$BL88+$BU88+$CD88+$CM88) -> 2 | EI88: =IF(CU88="ECONACIONAL",$BD88+$DH88+$DQ88+$DZ88+BM88+BV88+CE88+CN88) -> 50.0285 | EJ88: =IF($CU88="CLEARTEC",$BE88+$BN88+$BW88+$CF88+$CO88,0) -> 0 | EK88: =IF(CU88="ECONACIONAL",$BF88+$BO88+$BX88+$CG88+$CP88) -> 0 | EL88: =IF(CU88="ECONACIONAL",$BG88+$BP88+$BY88+$CH88+$CQ88) -> 0 | EM88: =IF(CU88="ECONACIONAL",BH88+BQ88+BZ88+CI88+CR88) -> 513.42749 | EN88: =SUM(EF88:EM88)-EH88-EJ88 -> 4988.236 | ES88: =43 -> 43 | EY88: =+ET88+EU88+EV88 -> 0 | FA88: =IF($M88<=15,EP88/2,EP88) -> 0 | FB88: =IF($M88<=15,EQ88/2,EQ88) -> 0 | FC88: =IF($M88<=15,ER88/2,ER88) -> 0 | FD88: =IF($M88<=15,ES88/2,ES88) -> 43 | FE88: =IF($M88<=15,ET88/2,ET88) -> 0 | FF88: =IF($M88<=15,EU88/2,EU88) -> 0 | FG88: =IF($M88<=15,EV88/2,EV88) -> 0 | FH88: =IF($M88<=15,EW88/2,EW88) -> 0 | ... FJ88: =IF($M88<=15,EY88/2,EY88) -> 0 | FR88: =(((J88/30/8)*1.5)*(U88+Y88+AC88))-(BD88+BM88+BV88) -> 0 | FS88: =(((J88/30/8)*2)*(W88+AA88+AE88))-(BF88+BO88+BX88) -> 0 | FT88: =(SUM(BA88:CJ88))-(SUM(EF88:EN88)) -> 0 | FU88: =(J88/30*M88)-(EF88) -> 0 | FV88: =(SUM(EP88:EY88))-((SUM(FA88:FJ88))*$FV$5) -> -43
E89: 302020 | F89: =+F87+1 -> 31 | G89: Gonzalez Perez Alexis Damian | H89: Auxiliar de Bodega | I89: ECONACIONAL | J89: 4002.28 | K89: 250 | L89: =+J89+K89 -> 4252.28 | M89: 30 | N89: 0.5 | O89: 0.3 | P89: 0.2 | Q89: 0 | R89: 0 | S89: =SUM(N89:R89) -> 1 | V89: =($J89/30/8*1.5)*U89 -> 0 | X89: =($J89/30/8*2)*W89 -> 0 | Y89: 7 | Z89: =($J89/30/8*1.5)*Y89 -> 175.09975 | AB89: =($J89/30/8*2)*AA89 -> 0 | AD89: =(($J89/30/8)*1.5)*AC89 -> 0 | AF89: =(($J89/30/8)*2)*AE89 -> 0 | AH89: =(($J89/30/8)*1.5)*AG89 -> 0 | AJ89: =(($J89/30/8)*2)*AI89 -> 0 | AL89: =(($J89/30/8)*1.5)*AK89 -> 0 | AN89: =(($J89/30/8)*2)*AM89 -> 0 | BA89: =((J89/30)*M89)*$N89 -> 2001.14 | BB89: =((K89/30)*M89)*$N89+82.5 -> 207.5 | BC89: =U89 -> 0 | BD89: =V89 -> 0 | BE89: =W89 -> 0 | BF89: =X89 -> 0 | BG89: =AO89+AT89 -> 0 | BH89: =(BA89+BD89+BF89+BG89)*0.1267 -> 253.54444 | BI89: =SUM(BA89:BH89)-BC89-BE89 -> 2462.1844 | BJ89: =(($J89/30)*$M89)*$O89 -> 1200.684 | BK89: =(($K89/30)*$M89)*$O89+82.5 -> 157.5 | BL89: =Y89 -> 7 | BM89: =Z89 -> 175.09975 | BN89: =AA89 -> 0 | BO89: =AB89 -> 0 | BP89: =AP89+AU89 -> 0 | BQ89: =(+BJ89+BM89+BO89+BP89)*0.1267 -> 174.3118 | BR89: =SUM(BJ89:BQ89)-BL89-BN89 -> 1707.5956 | BS89: =(($J89/30)*$M89)*$P89 -> 800.456 | BT89: =(($K89/30)*$M89)*$P89 -> 50 | BU89: =AC89 -> 0 | BV89: =AD89 -> 0 | BW89: =AE89 -> 0 | BX89: =AF89 -> 0 | BY89: =AQ89+AV89 -> 0 | BZ89: =(BS89+BV89+BX89+BY89)*0.1267 -> 101.41778 | CA89: =SUM(BS89:BZ89)-BU89-BW89 -> 951.87378 | CB89: =(($J89/30)*$M89)*$Q89 -> 0 | CC89: =(($K89/30)*$M89)*$Q89 -> 0 | CD89: =AG89 -> 0 | CE89: =AH89 -> 0 | CF89: =AI89 -> 0 | CG89: =AJ89 -> 0 | CH89: =AR89+AW89 -> 0 | CI89: =(CB89+CE89+CG89+CH89)*0.1267 -> 0 | CJ89: =SUM(CB89:CI89)-CD89-CF89 -> 0 | CK89: =(($J89/30)*$M89)*R89 -> 0 | CL89: =(($K89/30)*$M89)*$R89 -> 0 | CM89: =+AK89 -> 0 | CN89: =AL89 -> 0 | CO89: =AM89 -> 0 | CP89: =AN89 -> 0 | CQ89: =AS89+AX89 -> 0 | CR89: =(CK89+CN89+CP89)*0.1267 -> 0 | CS89: =SUM(CK89:CR89)-CM89-CO89 -> 0 | CU89: ECONACIONAL | CV89: =IF($CU89="PROQUIMA",$BA89+$BJ89+$BS89+$CB89+$CK89,0) -> 0 | CW89: =IF($CU89="PROQUIMA",$BB89+$BK89+$BT89+$CC89+$CL89,0) -> 0 | CX89: =IF($CU89="PROQUIMA",$BC89+$BL89+$BU89+$CD89+$CM89,0) -> 0 | CY89: =IF($CU89="PROQUIMA",$BD89+$BM89+$BV89+$CE89+$CN89,0) -> 0 | CZ89: =IF($CU89="PROQUIMA",$BE89+$BN89+$BW89+$CF89+$CO89,0) -> 0 | DA89: =IF($CU89="PROQUIMA",$BF89+$BO89+$BX89+$CG89+$CP89,0) -> 0 | DB89: =IF($CU89="PROQUIMA",$BG89+$BP89+$BY89+$CH89+$CQ89,0) -> 0 | DC89: =IF($CU89="PROQUIMA",$BH89+$BQ89+$BZ89+$CI89+CR89,0) -> 0 | DD89: =SUM(CV89:DC89)-CX89-CZ89 -> 0 | DE89: =IF($CU89="UNHESA",$BA89+$BJ89+$BS89+$CB89+$CK89,0) -> 0 | DF89: =IF($CU89="UNHESA",$BB89+$BK89+$BT89+$CC89+$CL89,0) -> 0 | DG89: =IF($CU89="UNHESA",$BC89+$BL89+$BU89+$CD89+$CM89,0) -> 0 | DH89: =IF($CU89="UNHESA",$BD89+$BM89+$BV89+$CE89+$CN89,0) -> 0 | DI89: =IF($CU89="UNHESA",$BE89+$BN89+$BW89+$CF89+$CO89,0) -> 0 | DJ89: =IF($CU89="UNHESA",$BF89+$BO89+$BX89+$CG89+$CP89,0) -> 0 | DK89: =IF($CU89="UNHESA",$BG89+$BP89+$BY89+$CH89+$CQ89,0) -> 0 | DL89: =IF($CU89="UNHESA",$BH89+$BQ89+$BZ89+$CI89+$CR89,0) -> 0 | DM89: =SUM(DE89:DL89)-DG89-DI89 -> 0 | DN89: =IF($CU89="UNHESA LIQUIDOS",$BA89+$BJ89+$BS89+$CB89+$CK89,0) -> 0 | DO89: =IF($CU89="UNHESA LIQUIDOS",$BB89+$BK89+$BT89+$CC89+$CL89,0) -> 0 | DP89: =IF($CU89="UNHESA LIQUIDOS",$BC89+$BL89+$BU89+$CD89+$CM89,0) -> 0 | DQ89: =IF($CU89="UNHESA LIQUIDOS",$BD89+$BM89+$BV89+$CE89+$CN89,0) -> 0 | DR89: =IF($CU89="UNHESA LIQUIDOS",$BE89+$BN89+$BW89+$CF89+$CO89,0) -> 0 | DS89: =IF($CU89="UNHESA LIQUIDOS",$BF89+$BO89+$BX89+$CG89+$CP89,0) -> 0 | DT89: =IF($CU89="UNHESA LIQUIDOS",$BG89+$BP89+$BY89+$CH89+$CQ89,0) -> 0 | DU89: =IF($CU89="UNHESA LIQUIDOS",$BH89+$BQ89+$BZ89+$CI89+$CR89,0) -> 0 | DV89: =SUM(DN89:DU89)-DP89-DR89 -> 0 | DW89: =IF($CU89="CLEARTEC",$BA89+$BJ89+$BS89+$CB89+$CK89,0) -> 0 | DX89: =IF($CU89="CLEARTEC",$BA89+$BJ89+$BS89+$CB89+$CK89,0) -> 0 | DY89: =IF($CU89="CLEARTEC",$BA89+$BJ89+$BS89+$CB89+$CK89,0) -> 0 | DZ89: =IF($CU89="CLEARTEC",$BA89+$BJ89+$BS89+$CB89+$CK89,0) -> 0 | EA89: =IF($CU89="CLEARTEC",$BA89+$BJ89+$BS89+$CB89+$CK89,0) -> 0 | EB89: =IF($CU89="CLEARTEC",$BA89+$BJ89+$BS89+$CB89+$CK89,0) -> 0 | EC89: =IF($CU89="CLEARTEC",$BA89+$BJ89+$BS89+$CB89+$CK89,0) -> 0 | ED89: =IF($CU89="CLEARTEC",$BA89+$BJ89+$BS89+$CB89+$CK89,0) -> 0 | EE89: =SUM(DW89:ED89)-DY89-EA89 -> 0 | EF89: =IF(CU89="ECONACIONAL",$BA89+$BJ89+$BS89+$CB89+$CK89) -> 4002.28 | EG89: =IF($CU89="ECONACIONAL",$BB89+$BK89+$BT89+$CC89+$CL89,0) -> 415 | EH89: =IF(CU89="ECONACIONAL",$BC89+$BL89+$BU89+$CD89+$CM89) -> 7 | EI89: =IF(CU89="ECONACIONAL",$BD89+$DH89+$DQ89+$DZ89+BM89+BV89+CE89+CN89) -> 175.09975 | EJ89: =IF($CU89="CLEARTEC",$BE89+$BN89+$BW89+$CF89+$CO89,0) -> 0 | EK89: =IF(CU89="ECONACIONAL",$BF89+$BO89+$BX89+$CG89+$CP89) -> 0 | EL89: =IF(CU89="ECONACIONAL",$BG89+$BP89+$BY89+$CH89+$CQ89) -> 0 | EM89: =IF(CU89="ECONACIONAL",BH89+BQ89+BZ89+CI89+CR89) -> 529.27401 | EN89: =SUM(EF89:EM89)-EH89-EJ89 -> 5121.6538 | ES89: =285.5+380 -> 665.5 | EY89: =+ET89+EU89+EV89 -> 0 | FA89: =IF($M89<=15,EP89/2,EP89) -> 0 | FB89: =IF($M89<=15,EQ89/2,EQ89) -> 0 | FC89: =IF($M89<=15,ER89/2,ER89) -> 0 | FD89: =IF($M89<=15,ES89/2,ES89) -> 665.5 | FE89: =IF($M89<=15,ET89/2,ET89) -> 0 | FF89: =IF($M89<=15,EU89/2,EU89) -> 0 | FG89: =IF($M89<=15,EV89/2,EV89) -> 0 | FH89: =IF($M89<=15,EW89/2,EW89) -> 0 | ... FJ89: =IF($M89<=15,EY89/2,EY89) -> 0 | FK89: 1 | FL89: 0 | FM89: 0 | FN89: 0 | FO89: 0 | FP89: 1
H91: Bodega MP | J91: =SUM(J86:J90) -> 17004.56 | K91: =SUM(K86:K90) -> 1352.28 | L91: =SUM(L86:L90) -> 18356.84 | U91: =SUM(U86:U90) -> 17 | V91: =SUM(V86:V90) -> 471.9035 | W91: =SUM(W86:W90) -> 0 | X91: =SUM(X86:X90) -> 0 | Y91: =SUM(Y86:Y90) -> 7 | Z91: =SUM(Z86:Z90) -> 175.09975 | AA91: =SUM(AA86:AA90) -> 0 | AB91: =SUM(AB86:AB90) -> 0 | ... GB91: =SUM(GB86:GB90) -> 0
A92: =$G$4 -> JUNIO 2026 2da QUINCENA | B92: =+$G$5 -> 2026 | C92: =A92 & B92 -> JUNIO 2026 2da QUINCENA2026 | E92: 302030 | G92: BODEGA PT
E93: 302030 | G93: Perez Avilez Steven Andre | H93: Auxiliar de Bodega | I93: ECONACIONAL | J93: 4002.28 | K93: 250 | L93: =+J93+K93 -> 4252.28 | M93: 27 | N93: 0.5 | O93: 0.25 | P93: 0.25 | Q93: 0 | R93: 0 | S93: =SUM(N93:R93) -> 1 | T93: falta injustificada 2 dias mas sep | V93: =($J93/30/8*1.5)*U93 -> 0 | X93: =($J93/30/8*2)*W93 -> 0 | Y93: 34 | Z93: =($J93/30/8*1.5)*Y93 -> 850.4845 | AB93: =($J93/30/8*2)*AA93 -> 0 | AD93: =(($J93/30/8)*1.5)*AC93 -> 0 | AF93: =(($J93/30/8)*2)*AE93 -> 0 | AH93: =(($J93/30/8)*1.5)*AG93 -> 0 | AJ93: =(($J93/30/8)*2)*AI93 -> 0 | AL93: =(($J93/30/8)*1.5)*AK93 -> 0 | AN93: =(($J93/30/8)*2)*AM93 -> 0 | BA93: =((J93/30)*M93)*$N93 -> 1801.026 | BB93: =((K93/30)*M93)*$N93+75 -> 187.5 | BC93: =U93 -> 0 | BD93: =V93 -> 0 | BE93: =W93 -> 0 | BF93: =X93 -> 0 | BG93: =AO93+AT93 -> 0 | BH93: =(BA93+BD93+BF93+BG93)*0.1267 -> 228.18999 | BI93: =SUM(BA93:BH93)-BC93-BE93 -> 2216.716 | BJ93: =(($J93/30)*$M93)*$O93 -> 900.513 | BK93: =(($K93/30)*$M93)*$O93+75+480 -> 611.25 | BL93: =Y93 -> 34 | BM93: =Z93 -> 850.4845 | BN93: =AA93 -> 0 | BO93: =AB93 -> 0 | BP93: =AP93+AU93 -> 0 | BQ93: =(+BJ93+BM93+BO93+BP93)*0.1267 -> 221.85138 | BR93: =SUM(BJ93:BQ93)-BL93-BN93 -> 2584.0989 | BS93: =(($J93/30)*$M93)*$P93 -> 900.513 | BT93: =(($K93/30)*$M93)*$P93 -> 56.25 | BU93: =AC93 -> 0 | BV93: =AD93 -> 0 | BW93: =AE93 -> 0 | BX93: =AF93 -> 0 | BY93: =AQ93+AV93 -> 0 | BZ93: =(BS93+BV93+BX93+BY93)*0.1267 -> 114.095 | CA93: =SUM(BS93:BZ93)-BU93-BW93 -> 1070.858 | CB93: =(($J93/30)*$M93)*$Q93 -> 0 | CC93: =(($K93/30)*$M93)*$Q93 -> 0 | CD93: =AG93 -> 0 | CE93: =AH93 -> 0 | CF93: =AI93 -> 0 | CG93: =AJ93 -> 0 | CH93: =AR93+AW93 -> 0 | CI93: =(CB93+CE93+CG93+CH93)*0.1267 -> 0 | CJ93: =SUM(CB93:CI93)-CD93-CF93 -> 0 | CK93: =(($J93/30)*$M93)*R93 -> 0 | CL93: =(($K93/30)*$M93)*$R93 -> 0 | CM93: =+AK93 -> 0 | CN93: =AL93 -> 0 | CO93: =AM93 -> 0 | CP93: =AN93 -> 0 | CQ93: =AS93+AX93 -> 0 | CR93: =(CK93+CN93+CP93)*0.1267 -> 0 | CS93: =SUM(CK93:CR93)-CM93-CO93 -> 0 | CU93: ECONACIONAL | CV93: =IF($CU93="PROQUIMA",$BA93+$BJ93+$BS93+$CB93+$CK93,0) -> 0 | CW93: =IF($CU93="PROQUIMA",$BB93+$BK93+$BT93+$CC93+$CL93,0) -> 0 | CX93: =IF($CU93="PROQUIMA",$BC93+$BL93+$BU93+$CD93+$CM93,0) -> 0 | CY93: =IF($CU93="PROQUIMA",$BD93+$BM93+$BV93+$CE93+$CN93,0) -> 0 | CZ93: =IF($CU93="PROQUIMA",$BE93+$BN93+$BW93+$CF93+$CO93,0) -> 0 | DA93: =IF($CU93="PROQUIMA",$BF93+$BO93+$BX93+$CG93+$CP93,0) -> 0 | DB93: =IF($CU93="PROQUIMA",$BG93+$BP93+$BY93+$CH93+$CQ93,0) -> 0 | DC93: =IF($CU93="PROQUIMA",$BH93+$BQ93+$BZ93+$CI93+CR93,0) -> 0 | DD93: =SUM(CV93:DC93)-CX93-CZ93 -> 0 | DE93: =IF($CU93="UNHESA",$BA93+$BJ93+$BS93+$CB93+$CK93,0) -> 0 | DF93: =IF($CU93="UNHESA",$BB93+$BK93+$BT93+$CC93+$CL93,0) -> 0 | DG93: =IF($CU93="UNHESA",$BC93+$BL93+$BU93+$CD93+$CM93,0) -> 0 | DH93: =IF($CU93="UNHESA",$BD93+$BM93+$BV93+$CE93+$CN93,0) -> 0 | DI93: =IF($CU93="UNHESA",$BE93+$BN93+$BW93+$CF93+$CO93,0) -> 0 | DJ93: =IF($CU93="UNHESA",$BF93+$BO93+$BX93+$CG93+$CP93,0) -> 0 | DK93: =IF($CU93="UNHESA",$BG93+$BP93+$BY93+$CH93+$CQ93,0) -> 0 | DL93: =IF($CU93="UNHESA",$BH93+$BQ93+$BZ93+$CI93+$CR93,0) -> 0 | DM93: =SUM(DE93:DL93)-DG93-DI93 -> 0 | DN93: =IF($CU93="UNHESA LIQUIDOS",$BA93+$BJ93+$BS93+$CB93+$CK93,0) -> 0 | DO93: =IF($CU93="UNHESA LIQUIDOS",$BB93+$BK93+$BT93+$CC93+$CL93,0) -> 0 | DP93: =IF($CU93="UNHESA LIQUIDOS",$BC93+$BL93+$BU93+$CD93+$CM93,0) -> 0 | DQ93: =IF($CU93="UNHESA LIQUIDOS",$BD93+$BM93+$BV93+$CE93+$CN93,0) -> 0 | DR93: =IF($CU93="UNHESA LIQUIDOS",$BE93+$BN93+$BW93+$CF93+$CO93,0) -> 0 | DS93: =IF($CU93="UNHESA LIQUIDOS",$BF93+$BO93+$BX93+$CG93+$CP93,0) -> 0 | DT93: =IF($CU93="UNHESA LIQUIDOS",$BG93+$BP93+$BY93+$CH93+$CQ93,0) -> 0 | DU93: =IF($CU93="UNHESA LIQUIDOS",$BH93+$BQ93+$BZ93+$CI93+$CR93,0) -> 0 | DV93: =SUM(DN93:DU93)-DP93-DR93 -> 0 | DW93: =IF($CU93="CLEARTEC",$BA93+$BJ93+$BS93+$CB93+$CK93,0) -> 0 | DX93: =IF($CU93="CLEARTEC",$BA93+$BJ93+$BS93+$CB93+$CK93,0) -> 0 | DY93: =IF($CU93="CLEARTEC",$BA93+$BJ93+$BS93+$CB93+$CK93,0) -> 0 | DZ93: =IF($CU93="CLEARTEC",$BA93+$BJ93+$BS93+$CB93+$CK93,0) -> 0 | EA93: =IF($CU93="CLEARTEC",$BA93+$BJ93+$BS93+$CB93+$CK93,0) -> 0 | EB93: =IF($CU93="CLEARTEC",$BA93+$BJ93+$BS93+$CB93+$CK93,0) -> 0 | EC93: =IF($CU93="CLEARTEC",$BA93+$BJ93+$BS93+$CB93+$CK93,0) -> 0 | ED93: =IF($CU93="CLEARTEC",$BA93+$BJ93+$BS93+$CB93+$CK93,0) -> 0 | EE93: =SUM(DW93:ED93)-DY93-EA93 -> 0 | EF93: =IF(CU93="ECONACIONAL",$BA93+$BJ93+$BS93+$CB93+$CK93) -> 3602.052 | EG93: =IF($CU93="ECONACIONAL",$BB93+$BK93+$BT93+$CC93+$CL93,0) -> 855 | EH93: =IF(CU93="ECONACIONAL",$BC93+$BL93+$BU93+$CD93+$CM93) -> 34 | EI93: =IF(CU93="ECONACIONAL",$BD93+$DH93+$DQ93+$DZ93+BM93+BV93+CE93+CN93) -> 850.4845 | EJ93: =IF($CU93="CLEARTEC",$BE93+$BN93+$BW93+$CF93+$CO93,0) -> 0 | EK93: =IF(CU93="ECONACIONAL",$BF93+$BO93+$BX93+$CG93+$CP93) -> 0 | EL93: =IF(CU93="ECONACIONAL",$BG93+$BP93+$BY93+$CH93+$CQ93) -> 0 | EM93: =IF(CU93="ECONACIONAL",BH93+BQ93+BZ93+CI93+CR93) -> 564.13637 | EN93: =SUM(EF93:EM93)-EH93-EJ93 -> 5871.6729 | ES93: =773+973.5 -> 1746.5 | EY93: =+ET93+EU93+EV93 -> 0 | FA93: =IF($M93<=15,EP93/2,EP93) -> 0 | FB93: =IF($M93<=15,EQ93/2,EQ93) -> 0 | FC93: =IF($M93<=15,ER93/2,ER93) -> 0 | FD93: =IF($M93<=15,ES93/2,ES93) -> 1746.5 | FE93: =IF($M93<=15,ET93/2,ET93) -> 0 | FF93: =IF($M93<=15,EU93/2,EU93) -> 0 | FG93: =IF($M93<=15,EV93/2,EV93) -> 0 | FH93: =IF($M93<=15,EW93/2,EW93) -> 0 | ... FJ93: =IF($M93<=15,EY93/2,EY93) -> 0 | FR93: =(((J93/30/8)*1.5)*(U93+Y93+AC93))-(BD93+BM93+BV93) -> 0 | FS93: =(((J93/30/8)*2)*(W93+AA93+AE93))-(BF93+BO93+BX93) -> 0 | FT93: =(SUM(BA93:CJ93))-(SUM(EF93:EN93)) -> 0 | FU93: =(J93/30*M93)-(EF93) -> 0 | FV93: =(SUM(EP93:EY93))-((SUM(FA93:FJ93))*$FV$5) -> -1746.5
E94: 302030 | G94: Lopez Oxcal Kevin Jesus | H94: Auxiliar de Bodega | I94: ECONACIONAL | J94: 4002.28 | K94: 250 | L94: =+J94+K94 -> 4252.28 | M94: 30 | N94: 0.5 | O94: 0.5 | P94: 0 | Q94: 0 | R94: 0 | S94: =SUM(N94:R94) -> 1 | T94: A.11.5.26 | U94: 1 | V94: =($J94/30/8*1.5)*U94 -> 25.01425 | X94: =($J94/30/8*2)*W94 -> 0 | Y94: 45 | Z94: =($J94/30/8*1.5)*Y94 -> 1125.6413 | AB94: =($J94/30/8*2)*AA94 -> 0 | AD94: =(($J94/30/8)*1.5)*AC94 -> 0 | AF94: =(($J94/30/8)*2)*AE94 -> 0 | AH94: =(($J94/30/8)*1.5)*AG94 -> 0 | AJ94: =(($J94/30/8)*2)*AI94 -> 0 | AL94: =(($J94/30/8)*1.5)*AK94 -> 0 | AN94: =(($J94/30/8)*2)*AM94 -> 0 | BA94: =((J94/30)*M94)*$N94 -> 2001.14 | BB94: =((K94/30)*M94)*$N94+80 -> 205 | BC94: =U94 -> 1 | BD94: =V94 -> 25.01425 | BE94: =W94 -> 0 | BF94: =X94 -> 0 | BG94: =AO94+AT94 -> 0 | BH94: =(BA94+BD94+BF94+BG94)*0.1267 -> 256.71374 | BI94: =SUM(BA94:BH94)-BC94-BE94 -> 2487.868 | BJ94: =(($J94/30)*$M94)*$O94 -> 2001.14 | BK94: =(($K94/30)*$M94)*$O94+80+720 -> 925 | BL94: =Y94 -> 45 | BM94: =Z94 -> 1125.6413 | BN94: =AA94 -> 0 | BO94: =AB94 -> 0 | BP94: =AP94+AU94 -> 0 | BQ94: =(+BJ94+BM94+BO94+BP94)*0.1267 -> 396.16318 | BR94: =SUM(BJ94:BQ94)-BL94-BN94 -> 4447.9444 | BS94: =(($J94/30)*$M94)*$P94 -> 0 | BT94: =(($K94/30)*$M94)*$P94 -> 0 | BU94: =AC94 -> 0 | BV94: =AD94 -> 0 | BW94: =AE94 -> 0 | BX94: =AF94 -> 0 | BY94: =AQ94+AV94 -> 0 | BZ94: =(BS94+BV94+BX94+BY94)*0.1267 -> 0 | CA94: =SUM(BS94:BZ94)-BU94-BW94 -> 0 | CB94: =(($J94/30)*$M94)*$Q94 -> 0 | CC94: =(($K94/30)*$M94)*$Q94 -> 0 | CD94: =AG94 -> 0 | CE94: =AH94 -> 0 | CF94: =AI94 -> 0 | CG94: =AJ94 -> 0 | CH94: =AR94+AW94 -> 0 | CI94: =(CB94+CE94+CG94+CH94)*0.1267 -> 0 | CJ94: =SUM(CB94:CI94)-CD94-CF94 -> 0 | CK94: =(($J94/30)*$M94)*R94 -> 0 | CL94: =(($K94/30)*$M94)*$R94 -> 0 | CM94: =+AK94 -> 0 | CN94: =AL94 -> 0 | CO94: =AM94 -> 0 | CP94: =AN94 -> 0 | CQ94: =AS94+AX94 -> 0 | CR94: =(CK94+CN94+CP94)*0.1267 -> 0 | CS94: =SUM(CK94:CR94)-CM94-CO94 -> 0 | CU94: ECONACIONAL | CV94: =IF($CU94="PROQUIMA",$BA94+$BJ94+$BS94+$CB94+$CK94,0) -> 0 | CW94: =IF($CU94="PROQUIMA",$BB94+$BK94+$BT94+$CC94+$CL94,0) -> 0 | CX94: =IF($CU94="PROQUIMA",$BC94+$BL94+$BU94+$CD94+$CM94,0) -> 0 | CY94: =IF($CU94="PROQUIMA",$BD94+$BM94+$BV94+$CE94+$CN94,0) -> 0 | CZ94: =IF($CU94="PROQUIMA",$BE94+$BN94+$BW94+$CF94+$CO94,0) -> 0 | DA94: =IF($CU94="PROQUIMA",$BF94+$BO94+$BX94+$CG94+$CP94,0) -> 0 | DB94: =IF($CU94="PROQUIMA",$BG94+$BP94+$BY94+$CH94+$CQ94,0) -> 0 | DC94: =IF($CU94="PROQUIMA",$BH94+$BQ94+$BZ94+$CI94+CR94,0) -> 0 | DD94: =SUM(CV94:DC94)-CX94-CZ94 -> 0 | DE94: =IF($CU94="UNHESA",$BA94+$BJ94+$BS94+$CB94+$CK94,0) -> 0 | DF94: =IF($CU94="UNHESA",$BB94+$BK94+$BT94+$CC94+$CL94,0) -> 0 | DG94: =IF($CU94="UNHESA",$BC94+$BL94+$BU94+$CD94+$CM94,0) -> 0 | DH94: =IF($CU94="UNHESA",$BD94+$BM94+$BV94+$CE94+$CN94,0) -> 0 | DI94: =IF($CU94="UNHESA",$BE94+$BN94+$BW94+$CF94+$CO94,0) -> 0 | DJ94: =IF($CU94="UNHESA",$BF94+$BO94+$BX94+$CG94+$CP94,0) -> 0 | DK94: =IF($CU94="UNHESA",$BG94+$BP94+$BY94+$CH94+$CQ94,0) -> 0 | DL94: =IF($CU94="UNHESA",$BH94+$BQ94+$BZ94+$CI94+$CR94,0) -> 0 | DM94: =SUM(DE94:DL94)-DG94-DI94 -> 0 | DN94: =IF($CU94="UNHESA LIQUIDOS",$BA94+$BJ94+$BS94+$CB94+$CK94,0) -> 0 | DO94: =IF($CU94="UNHESA LIQUIDOS",$BB94+$BK94+$BT94+$CC94+$CL94,0) -> 0 | DP94: =IF($CU94="UNHESA LIQUIDOS",$BC94+$BL94+$BU94+$CD94+$CM94,0) -> 0 | DQ94: =IF($CU94="UNHESA LIQUIDOS",$BD94+$BM94+$BV94+$CE94+$CN94,0) -> 0 | DR94: =IF($CU94="UNHESA LIQUIDOS",$BE94+$BN94+$BW94+$CF94+$CO94,0) -> 0 | DS94: =IF($CU94="UNHESA LIQUIDOS",$BF94+$BO94+$BX94+$CG94+$CP94,0) -> 0 | DT94: =IF($CU94="UNHESA LIQUIDOS",$BG94+$BP94+$BY94+$CH94+$CQ94,0) -> 0 | DU94: =IF($CU94="UNHESA LIQUIDOS",$BH94+$BQ94+$BZ94+$CI94+$CR94,0) -> 0 | DV94: =SUM(DN94:DU94)-DP94-DR94 -> 0 | DW94: =IF($CU94="CLEARTEC",$BA94+$BJ94+$BS94+$CB94+$CK94,0) -> 0 | DX94: =IF($CU94="CLEARTEC",$BA94+$BJ94+$BS94+$CB94+$CK94,0) -> 0 | DY94: =IF($CU94="CLEARTEC",$BA94+$BJ94+$BS94+$CB94+$CK94,0) -> 0 | DZ94: =IF($CU94="CLEARTEC",$BA94+$BJ94+$BS94+$CB94+$CK94,0) -> 0 | EA94: =IF($CU94="CLEARTEC",$BA94+$BJ94+$BS94+$CB94+$CK94,0) -> 0 | EB94: =IF($CU94="CLEARTEC",$BA94+$BJ94+$BS94+$CB94+$CK94,0) -> 0 | EC94: =IF($CU94="CLEARTEC",$BA94+$BJ94+$BS94+$CB94+$CK94,0) -> 0 | ED94: =IF($CU94="CLEARTEC",$BA94+$BJ94+$BS94+$CB94+$CK94,0) -> 0 | EE94: =SUM(DW94:ED94)-DY94-EA94 -> 0 | EF94: =IF(CU94="ECONACIONAL",$BA94+$BJ94+$BS94+$CB94+$CK94) -> 4002.28 | EG94: =IF($CU94="ECONACIONAL",$BB94+$BK94+$BT94+$CC94+$CL94,0) -> 1130 | EH94: =IF(CU94="ECONACIONAL",$BC94+$BL94+$BU94+$CD94+$CM94) -> 46 | EI94: =IF(CU94="ECONACIONAL",$BD94+$DH94+$DQ94+$DZ94+BM94+BV94+CE94+CN94) -> 1150.6555 | EJ94: =IF($CU94="CLEARTEC",$BE94+$BN94+$BW94+$CF94+$CO94,0) -> 0 | EK94: =IF(CU94="ECONACIONAL",$BF94+$BO94+$BX94+$CG94+$CP94) -> 0 | EL94: =IF(CU94="ECONACIONAL",$BG94+$BP94+$BY94+$CH94+$CQ94) -> 0 | EM94: =IF(CU94="ECONACIONAL",BH94+BQ94+BZ94+CI94+CR94) -> 652.87693 | EN94: =SUM(EF94:EM94)-EH94-EJ94 -> 6935.8124 | EY94: =+ET94+EU94+EV94 -> 0 | FA94: =IF($M94<=15,EP94/2,EP94) -> 0 | FB94: =IF($M94<=15,EQ94/2,EQ94) -> 0 | FC94: =IF($M94<=15,ER94/2,ER94) -> 0 | FD94: =IF($M94<=15,ES94/2,ES94) -> 0 | FE94: =IF($M94<=15,ET94/2,ET94) -> 0 | FF94: =IF($M94<=15,EU94/2,EU94) -> 0 | FG94: =IF($M94<=15,EV94/2,EV94) -> 0 | FH94: =IF($M94<=15,EW94/2,EW94) -> 0 | ... FJ94: =IF($M94<=15,EY94/2,EY94) -> 0 | FR94: =(((J94/30/8)*1.5)*(U94+Y94+AC94))-(BD94+BM94+BV94) -> 0 | FS94: =(((J94/30/8)*2)*(W94+AA94+AE94))-(BF94+BO94+BX94) -> 0 | FT94: =(SUM(BA94:CJ94))-(SUM(EF94:EN94)) -> 0 | FU94: =(J94/30*M94)-(EF94) -> 0 | FV94: =(SUM(EP94:EY94))-((SUM(FA94:FJ94))*$FV$5) -> 0
