Workbook
Name ECONACIONAL: 'Nomina Econacional'!$A$4:$AB$153
Name Excel_BuiltIn__FilterDatabase: 'boleto de ornato'!#REF!
Name Excel_BuiltIn__FilterDatabase: distribucion!$O$6:$O$236
Name Excel_BuiltIn__FilterDatabase: 'INCREMENTO SALARIO MINIMO '!#REF!
Name Excel_BuiltIn__FilterDatabase: 'RECIBO E IGSS ECONACIONAL'!$B$1:$AB$2
Name Excel_BuiltIn__FilterDatabase: 'RECIBO E IGSS PROQUIMA'!$B$2:$AC$10
Name Excel_BuiltIn__FilterDatabase: 'RECIBO E IGSS UNHESA'!$B$2:$AB$4

Sheet distribucion
B1: 1 | C1: 2 | D1: 3 | E1: 4 | F1: 5 | G1: 6 | H1: 7 | I1: 8 | J1: 9 | K1: 10 | L1: 11 | M1: 12 | N1: 13 | O1: 14 | P1: 15 | Q1: 16 | R1: 17 | S1: 18 | T1: 19 | U1: 20 | V1: 21 | W1: 22 | X1: 23 | Y1: 24 | Z1: 25 | AA1: 26 | AB1: 27 | AC1: 28 | AD1: 29 | AE1: 30 | AF1: 31 | AG1: 32 | AH1: 33 | AI1: 34 | AJ1: 35 | AK1: 36 | AL1: 37 | AM1: 38 | AN1: 39 | AO1: 40 | AP1: 41 | AQ1: 42 | AR1: 43 | AS1: 44 | AT1: 45 | AU1: 46 | AV1: 47 | AW1: 48 | AX1: 49 | AY1: 50 | AZ1: 51 | BA1: 52 | BB1: 53 | BC1: 54 | BD1: 55 | BE1: 56 | BF1: 57 | BG1: 58 | BH1: 59 | BI1: 60 | BJ1: 61 | BK1: 62 | BL1: 63 | BM1: 64 | BN1: 65 | BO1: 66 | BP1: 67 | BQ1: 68 | BR1: 69 | BS1: 70 | BT1: 71 | BU1: 72 | BV1: 73 | BW1: 74 | BX1: 75 | BY1: 76 | BZ1: 77 | CA1: 78 | CB1: 79 | CC1: 80 | CD1: 81 | CE1: 82 | CF1: 83 | CG1: 84 | CH1: 85 | CI1: 86 | CJ1: 87 | CK1: 88 | CL1: 89 | CM1: 90 | CN1: 91 | CO1: 92 | CP1: 93 | CQ1: 94 | CR1: 95 | CS1: 96 | CT1: 97 | CU1: 98 | CV1: 99 | CW1: 100 | CX1: 101 | CY1: 102 | CZ1: 103 | DA1: 104 | DB1: 105 | DC1: 106 | DD1: 107 | DE1: 108 | DF1: 109 | DG1: 110 | DH1: 111 | DI1: 112 | DJ1: 113 | DK1: 114 | DL1: 115 | DM1: 116 | DN1: 117 | DO1: 118 | DP1: 119 | DQ1: 120 | DR1: 121 | DS1: 122 | DT1: 123 | DU1: 124 | DV1: 125 | DW1: 126 | DX1: 127 | DY1: 128 | DZ1: 129 | EA1: 130 | EB1: 131 | EC1: 132 | ED1: 133 | EE1: 134 | EF1: 135 | EG1: 136 | EH1: 137 | EI1: 138 | EJ1: 139 | EK1: 140 | EL1: 141 | EM1: 142 | EN1: 143 | EO1: 144 | EP1: 145 | EQ1: 146 | ER1: 147 | ES1: 148 | ET1: 149 | EU1: 150 | EV1: 151 | EW1: 152 | EX1: 153 | EY1: 154 | EZ1: 155 | FA1: 156 | FB1: 157 | FC1: 158 | FD1: 159 | FE1: 160
B2: DISTRIBUCION DE PERSONAL Y COSTO POR EMPRESA
B3: NOMINA MES DE: ENERO 2,023 2da Quincena) | M3: .
AV4: NOMINAS SEGÚN DISTRIBUCION REAL | CQ4: NOMINAS SEGÚN DISTRIBUCION CONTABILIDAD
E5: 5 | F5: 6 | P5: HORAS EXTRAS PROQUIMA | T5: HORAS EXTRAS UNHESA | X5: HORAS EXTRAS UNHESA LIQUIDOS | AB5: HORAS EXTRAS ECONACIONAL | AF5: HORAS EXTRAS PROQUIMA MAQUILA | AJ5: Otros Ingresos | AO5: Comisiones | AV5: PROQUIMA | BE5: UNHESA | BN5: UNHESA LIQUIDOS | BW5: ECONACIONAL | CF5: ECOMEZCLAS | CQ5: PROQUIMA | CZ5: UNHESA | DI5: UNHESA LIQUIDOS | DR5: ECONACIONAL | EA5: ECOMEZCLAS | FF5: DISTRIBUCION REAL
D6: DISTRIBUCION DE EMPLEADOS | P6: H.E. Simples | Q6: H.E. Simples | R6: H.E. Dobles | S6: H.E. Dobles | T6: H.E. Simples | U6: H.E. Simples | V6: H.E. Dobles | W6: H.E. Dobles | X6: H.E. Simples | Y6: H.E. Simples | Z6: H.E. Dobles | AA6: H.E. Dobles | AB6: H.E. Simples | AC6: H.E. Simples | AD6: H.E. Dobles | AE6: H.E. Dobles | AF6: H.E. Simples | AG6: H.E. Simples | AH6: H.E. Dobles | AI6: H.E. Dobles | AJ6: Proquima | AK6: Unhesa | AL6: Calidul | AM6: Econacional | AN6: Cleartec | AO6: Proquima | AP6: Unhesa | AQ6: Calidul | AR6: Econacional | AS6: Cleartec | AT6: Otrros ingresos | AU6: 0 | AV6: Salario | AW6: Bono | AX6: cantidad | AY6: Hrs. Extra | AZ6: cantidad | BA6: Hrs. Extra | BB6: Comis / | BC6: Cuota | BD6: Total | BE6: Salario | BF6: Bono | BG6: cantidad | BH6: Hrs. Extra | BI6: cantidad | BJ6: Hrs. Extra | BK6: Comis / | BL6: Cuota | BM6: Total | BN6: Salario | BO6: Bono | BP6: cantidad | BQ6: Hrs. Extra | BR6: cantidad | BS6: Hrs. Extra | BT6: Comis / | BU6: Cuota | BV6: Total | BW6: Salario | BX6: Bono | BY6: cantidad | BZ6: Hrs. Extra | CA6: cantidad | CB6: Hrs. Extra | CC6: Comis / | CD6: Cuota | CE6: Total | CF6: Salario | CG6: Bono | CH6: cantidad | CI6: Hrs. Extra | CJ6: cantidad | CK6: Hrs. Extra | CL6: Comis / | CM6: Cuota | CN6: Total | CP6: Nueva | CQ6: Salario | CR6: Bono | CS6: cantidad | CT6: Hrs. Extra | CU6: cantidad | CV6: Hrs. Extra | CW6: Comis / | CX6: Cuota | CY6: Total | CZ6: Salario | DA6: Bono | DB6: cantidad | DC6: Hrs. Extra | DD6: cantidad | DE6: Hrs. Extra | DF6: Comis / | DG6: Cuota | DH6: Total | DI6: Salario | DJ6: Bono | DK6: cantidad | DL6: Hrs. Extra | DM6: cantidad | DN6: Hrs. Extra | DO6: Comis / | DP6: Cuota | DQ6: Total | DR6: Salario | DS6: Bono | DT6: cantidad | DU6: Hrs. Extra | DV6: cantidad | DW6: Hrs. Extra | DX6: Comis / | DY6: Cuota | DZ6: Total | EA6: Salario | EB6: Bono | EC6: cantidad | ED6: Hrs. Extra | EE6: cantidad | EF6: Hrs. Extra | EG6: Comis / | EH6: Cuota | EI6: Total | EK6: EGRESOS MENSUALES | EV6: EGRESOS | FF6: % | FG6: % | FH6: % | FI6: % | FJ6: % | FK6: %
B7: Nombre | C7: Puesto | D7: Empresa Real | E7: Salario Ordinario | F7: Bono Decreto | G7: Total | H7: Días Laborados | I7: % Proquima | J7: % Unhesa | K7: % Unhesa Liq. | L7: % Econacional | M7: % Ecomezclas | N7: Total % Distribución | O7: Observaciones | P7: Cantidad | Q7: Valor | R7: Cantidad | S7: Valor | T7: Cantidad | U7: Valor | V7: Cantidad | W7: Valor | X7: Cantidad | Y7: Valor | Z7: Cantidad | AA7: Valor | AB7: Cantidad | AC7: Valor | AD7: Cantidad | AE7: Valor | AF7: Cantidad | AG7: Valor | AH7: Cantidad | AI7: Valor | AV7: Ordinario | AW7: Decreto | AX7: simples | AY7: simples | AZ7: dobles | BA7: dobles | BB7: Otros | BC7: Patronal | BE7: Ordinario | BF7: Decreto | BG7: simples | BH7: simples | BI7: dobles | BJ7: dobles | BK7: Otros | BL7: Patronal | BN7: Ordinario | BO7: Decreto | BP7: simples | BQ7: simples | BR7: dobles | BS7: dobles | BT7: Otros | BU7: Patronal | BW7: Ordinario | BX7: Decreto | BY7: simples | BZ7: simples | CA7: dobles | CB7: dobles | CC7: Otros | CD7: Patronal | CF7: Ordinario | CG7: Decreto | CH7: simples | CI7: simples | CJ7: dobles | CK7: dobles | CL7: Otros | CM7: Patronal | CP7: Empresa | CQ7: Ordinario | CR7: Decreto | CS7: simples | CT7: simples | CU7: dobles | CV7: dobles | CW7: Otros | CX7: Patronal | CZ7: Ordinario | DA7: Decreto | DB7: simples | DC7: simples | DD7: dobles | DE7: dobles | DF7: Otros | DG7: Patronal | DI7: Ordinario | DJ7: Decreto | DK7: simples | DL7: simples | DM7: dobles | DN7: dobles | DO7: Otros | DP7: Patronal | DR7: Ordinario | DS7: Decreto | DT7: simples | DU7: simples | DV7: dobles | DW7: dobles | DX7: Otros | DY7: Patronal | EA7: Ordinario | EB7: Decreto | EC7: simples | ED7: simples | EE7: dobles | EF7: dobles | EG7: Otros | EH7: Patronal | EK7: ISR | EL7: BANCOS | EM7: CELULAR | EN7: CAFETERIA | EO7: DESCUENTO producto | EP7: SEGURO/BOLETO ORNATO | EQ7: Otros Descuentos | ER7: CALZADO | ES7: UNIFORME | ET7: TOTAL EGRESOS Bol Ornato, Seguro, Otros | EV7: ISR | EW7: BANCOS | EX7: CELULAR | EY7: CAFETERIA | EZ7: DESCUENTO PRODUCTO | FA7: SEGURO | FB7: Otros Descuentos | FC7: CALZADO | FD7: UNIFORME | FE7: OTROS EGRESOS | FF7: % Proquima | FG7: % Unhesa | FH7: % Unhesa Liq. | FI7: % Econacional | FJ7: % Ecomezclas | FK7: Total % Distribución
B8: AREA ADMINISTRATIVA | FI8: cional
B9: PRESIDENCIA
A10: 1 | B10: Estrada Robles Victor Gerardo | C10: Presidente | D10: UNHESA | E10: 19750 | F10: 250 | G10: =+E10+F10 -> 20000 | H10: 30 | I10: 0 | J10: 1 | K10: 0 | L10: 0 | M10: 0 | N10: =SUM(I10:M10) -> 1 | Q10: =($E10/30/8*1.5)*P10 -> 0 | S10: 0 | U10: =($E10/30/8*1.5)*T10 -> 0 | W10: =($E10/30/8*2)*V10 -> 0 | Y10: =(($E10/30/8)*1.5)*X10 -> 0 | AA10: =(($E10/30/8)*2)*Z10 -> 0 | AC10: =(($E10/30/8)*1.5)*AB10 -> 0 | AE10: =(($E10/30/8)*2)*AD10 -> 0 | AG10: =(($E10/30/8)*1.5)*AF10 -> 0 | AI10: =(($E10/30/8)*2)*AH10 -> 0 | AV10: =(($E10/30)*$H10)*$I10 -> 0 | AW10: =(($F10/30)*$H10)*$I10 -> 0 | AX10: =P10 -> 0 | AY10: =Q10 -> 0 | AZ10: =R10 -> 0 | BA10: =S10 -> 0 | BB10: =AJ10+AO10 -> 0 | BC10: =(AV10+AY10+BA10)*0.1267 -> 0 | BD10: =SUM(AV10:BC10)-AX10-AZ10 -> 0 | BE10: =(($E10/30)*$H10)*$J10 -> 19750 | BF10: =(($F10/30)*$H10)*$J10 -> 250 | BG10: =T10 -> 0 | BH10: =U10 -> 0 | BI10: =V10 -> 0 | BJ10: =W10 -> 0 | BK10: =AK10+AP10 -> 0 | BL10: 0 | BM10: =SUM(BE10:BL10)-BG10-BI10 -> 20000 | BN10: =(($E10/30)*$H10)*$K10 -> 0 | BO10: =(($F10/30)*$H10)*$K10 -> 0 | BP10: =X10 -> 0 | BQ10: =Y10 -> 0 | BR10: =Z10 -> 0 | BS10: =AA10 -> 0 | BT10: =AL10+AQ10 -> 0 | BU10: 0 | BV10: =SUM(BN10:BU10)-BP10-BR10 -> 0 | BW10: =(($E10/30)*$H10)*$L10 -> 0 | BX10: =(($F10/30)*$H10)*$L10 -> 0 | BY10: =AB10 -> 0 | BZ10: =AC10 -> 0 | CA10: =AD10 -> 0 | CB10: =AE10 -> 0 | CC10: =AM10+AR10 -> 0 | CD10: =(BW10+BZ10+CB10)*0.1267 -> 0 | CE10: =SUM(BW10:CD10)-BY10-CA10 -> 0 | CF10: =(($E10/30)*$H10)*M10 -> 0 | CG10: =(($F10/30)*$H10)*$M10 -> 0 | CH10: =+AF10 -> 0 | CI10: =AG10 -> 0 | CJ10: =AH10 -> 0 | CK10: =AI10 -> 0 | CL10: =AN10+AS10 -> 0 | CM10: =(CF10+CI10+CK10)*0.1267 -> 0 | CN10: =SUM(CF10:CM10)-CH10-CJ10 -> 0 | CP10: UNHESA | CQ10: =IF($CP10="PROQUIMA",$AV10+$BE10+$BN10+$BW10+$CF10,0) -> 0 | CR10: =IF($CP10="PROQUIMA",$AW10+$BF10+$BO10+$BX10+$CG10,0) -> 0 | CS10: =IF($CP10="PROQUIMA",$AX10+$BG10+$BP10+$BY10+$CH10,0) -> 0 | CT10: =IF($CP10="PROQUIMA",$AY10+$BH10+$BQ10+$BZ10+$CI10,0) -> 0 | CU10: =IF($CP10="PROQUIMA",$AZ10+$BI10+$BR10+$CA10+$CJ10,0) -> 0 | CV10: =IF($CP10="PROQUIMA",$BA10+$BJ10+$BS10+$CB10+$CK10,0) -> 0 | CW10: =IF($CP10="PROQUIMA",$BB10+$BK10+$BT10+$CC10+$CL10,0) -> 0 | CX10: =IF($CP10="PROQUIMA",$BC10+$BL10+$BU10+$CD10+CM10,0) -> 0 | CY10: =SUM(CQ10:CX10)-CS10-CU10 -> 0 | CZ10: =IF($CP10="UNHESA",$AV10+$BE10+$BN10+$BW10+$CF10,0) -> 19750 | DA10: =IF($CP10="UNHESA",$AW10+$BF10+$BO10+$BX10+$CG10,0) -> 250 | DB10: =IF($CP10="UNHESA",$AX10+$BG10+$BP10+$BY10+$CH10,0) -> 0 | DC10: =IF($CP10="UNHESA",$AY10+$BH10+$BQ10+$BZ10+$CI10,0) -> 0 | DD10: =IF($CP10="UNHESA",$AZ10+$BI10+$BR10+$CA10+$CJ10,0) -> 0 | DE10: =IF($CP10="UNHESA",$BA10+$BJ10+$BS10+$CB10+$CK10,0) -> 0 | DF10: =IF($CP10="UNHESA",$BB10+$BK10+$BT10+$CC10+$CL10,0) -> 0 | DG10: =IF($CP10="UNHESA",$BC10+$BL10+$BU10+$CD10+$CM10,0) -> 0 | DH10: =SUM(CZ10:DG10)-DB10-DD10 -> 20000 | DI10: =IF($CP10="UNHESA LIQUIDOS",$AV10+$BE10+$BN10+$BW10+$CF10,0) -> 0 | DJ10: =IF($CP10="CALIDUL",$AW10+$BF10+$BO10+$BX10+$CG10,0) -> 0 | DK10: =IF($CP10="CALIDUL",$AX10+$BG10+$BP10+$BY10+$CH10,0) -> 0 | DL10: =IF($CP10="CALIDUL",$AY10+$BH10+$BQ10+$BZ10+$CI10,0) -> 0 | DM10: =IF($CP10="CALIDUL",$AZ10+$BI10+$BR10+$CA10+$CJ10,0) -> 0 | DN10: =IF($CP10="CALIDUL",$BA10+$BJ10+$BS10+$CB10+$CK10,0) -> 0 | DO10: =IF($CP10="CALIDUL",$BB10+$BK10+$BT10+$CC10+$CL10,0) -> 0 | DP10: =IF($CP10="CALIDUL",$BC10+$BL10+$BU10+$CD10+$CM10,0) -> 0 | DQ10: =SUM(DI10:DP10)-DK10-DM10 -> 0 | DR10: =IF($CP10="ECONACIONAL",$AV10+$BE10+$BN10+$BW10+$CF10,0) -> 0 | DS10: =IF($CP10="ECONACIONAL",$AW10+$BF10+$BO10+$BX10+$CG10,0) -> 0 | DT10: =IF($CP10="ECONACIONAL",$AX10+$BG10+$BP10+$BY10+$CH10,0) -> 0 | DU10: =IF($CP10="ECONACIONAL",$AY10+$BH10+$BQ10+$BZ10+$CI10,0) -> 0 | DV10: =IF($CP10="ECONACIONAL",$AZ10+$BI10+$BR10+$CA10+$CJ10,0) -> 0 | DW10: =IF($CP10="ECONACIONAL",$BA10+$BJ10+$BS10+$CB10+$CK10,0) -> 0 | DX10: =IF($CP10="ECONACIONAL",$BB10+$BK10+$BT10+$CC10+$CL10,0) -> 0 | DY10: =IF($CP10="ECONACIONAL",$BC10+$BL10+$BU10+$CD10+$CM10,0) -> 0 | DZ10: =SUM(DR10:DY10)-DT10-DV10 -> 0 | EA10: =IF($CP10="CLEARTEC",$AV10+$BE10+$BN10+$BW10+$CF10,0) -> 0 | EB10: =IF($CP10="CLEARTEC",$AW10+$BF10+$BO10+$BX10+$CG10,0) -> 0 | EC10: =IF($CP10="CLEARTEC",$AX10+$BG10+$BP10+$BY10+$CH10,0) -> 0 | ED10: =IF($CP10="CLEARTEC",$AY10+$BH10+$BQ10+$BZ10+$CI10,0) -> 0 | EE10: =IF($CP10="CLEARTEC",$AZ10+$BI10+$BR10+$CA10+$CJ10,0) -> 0 | EF10: =IF($CP10="CLEARTEC",$BA10+$BJ10+$BS10+$CB10+$CK10,0) -> 0 | EG10: =IF($CP10="CLEARTEC",$BB10+$BK10+$BT10+$CC10+$CL10,0) -> 0 | EH10: =IF($CP10="CLEARTEC",$BC10+$BL10+$BU10+$CD10+$CM10,0) -> 0 | EI10: =SUM(EA10:EH10)-EC10-EE10 -> 0 | ET10: =+EO10+EP10+EQ10 -> 0 | EV10: =IF($H10<=15,EK10/2,EK10) -> 0 | EW10: =IF($H10<=15,EL10/2,EL10) -> 0 | EX10: =IF($H10<=15,EM10/2,EM10) -> 0 | EY10: =IF($H10<=15,EN10/2,EN10) -> 0 | EZ10: =IF($H10<=15,EO10/2,EO10) -> 0 | FA10: =IF($H10<=15,EP10/2,EP10) -> 0 | FB10: =IF($H10<=15,EQ10/2,EQ10) -> 0 | FC10: =IF($H10<=15,ER10/2,ER10) -> 0 | ... FE10: =IF($H10<=15,ET10/2,ET10) -> 0 | FF10: 0 | FG10: 1 | FH10: 0 | FI10: 0 | FJ10: 0 | FK10: 1 | FL10: =+EP10-FA10 -> 0
A11: =+A10+1 -> 2 | B11: Estrada Robles Victor Gerardo1 | C11: Gerente General | D11: PROQUIMA | E11: 61000 | F11: 250 | G11: =+E11+F11 -> 61250 | H11: 30 | I11: 1 | J11: 0 | K11: 0 | L11: 0 | M11: 0 | N11: =SUM(I11:M11) -> 1 | Q11: =($E11/30/8*1.5)*P11 -> 0 | S11: =($E11/30/8*2)*R11 -> 0 | U11: =($E11/30/8*1.5)*T11 -> 0 | W11: =($E11/30/8*2)*V11 -> 0 | Y11: =(($E11/30/8)*1.5)*X11 -> 0 | AA11: =(($E11/30/8)*2)*Z11 -> 0 | AC11: =(($E11/30/8)*1.5)*AB11 -> 0 | AE11: =(($E11/30/8)*2)*AD11 -> 0 | AG11: =(($E11/30/8)*1.5)*AF11 -> 0 | AI11: =(($E11/30/8)*2)*AH11 -> 0 | AV11: =(($E11/30)*$H11)*$I11 -> 61000 | AW11: =(($F11/30)*$H11)*$I11 -> 250 | AX11: =P11 -> 0 | AY11: =Q11 -> 0 | AZ11: =R11 -> 0 | BA11: =S11 -> 0 | BB11: =AJ11+AO11 -> 0 | BC11: =(AV11+AY11+BA11)*0.1267 -> 7728.7 | BD11: =SUM(AV11:BC11)-AX11-AZ11 -> 68978.7 | BE11: =(($E11/30)*$H11)*$J11 -> 0 | BF11: =(($F11/30)*$H11)*$J11 -> 0 | BG11: =T11 -> 0 | BH11: =U11 -> 0 | BI11: =V11 -> 0 | BJ11: =W11 -> 0 | BK11: =AK11+AP11 -> 0 | BL11: 0 | BM11: =SUM(BE11:BL11)-BG11-BI11 -> 0 | BN11: =(($E11/30)*$H11)*$K11 -> 0 | BO11: =(($F11/30)*$H11)*$K11 -> 0 | BP11: =X11 -> 0 | BQ11: =Y11 -> 0 | BR11: =Z11 -> 0 | BS11: =AA11 -> 0 | BT11: =AL11+AQ11 -> 0 | BU11: 0 | BV11: =SUM(BN11:BU11)-BP11-BR11 -> 0 | BW11: =(($E11/30)*$H11)*$L11 -> 0 | BX11: =(($F11/30)*$H11)*$L11 -> 0 | BY11: =AB11 -> 0 | BZ11: =AC11 -> 0 | CA11: =AD11 -> 0 | CB11: =AE11 -> 0 | CC11: =AM11+AR11 -> 0 | CD11: =(BW11+BZ11+CB11)*0.1267 -> 0 | CE11: =SUM(BW11:CD11)-BY11-CA11 -> 0 | CF11: =(($E11/30)*$H11)*M11 -> 0 | CG11: =(($F11/30)*$H11)*$M11 -> 0 | CH11: =+AF11 -> 0 | CI11: =AG11 -> 0 | CJ11: =AH11 -> 0 | CK11: =AI11 -> 0 | CL11: =AN11+AS11 -> 0 | CM11: =(CF11+CI11+CK11)*0.1267 -> 0 | CN11: =SUM(CF11:CM11)-CH11-CJ11 -> 0 | CP11: PROQUIMA | CQ11: =IF($CP11="PROQUIMA",$AV11+$BE11+$BN11+$BW11+$CF11,0) -> 61000 | CR11: =IF($CP11="PROQUIMA",$AW11+$BF11+$BO11+$BX11+$CG11,0) -> 250 | CS11: =IF($CP11="PROQUIMA",$AX11+$BG11+$BP11+$BY11+$CH11,0) -> 0 | CT11: =IF($CP11="PROQUIMA",$AY11+$BH11+$BQ11+$BZ11+$CI11,0) -> 0 | CU11: =IF($CP11="PROQUIMA",$AZ11+$BI11+$BR11+$CA11+$CJ11,0) -> 0 | CV11: =IF($CP11="PROQUIMA",$BA11+$BJ11+$BS11+$CB11+$CK11,0) -> 0 | CW11: =IF($CP11="PROQUIMA",$BB11+$BK11+$BT11+$CC11+$CL11,0) -> 0 | CX11: =IF($CP11="PROQUIMA",$BC11+$BL11+$BU11+$CD11+CM11,0) -> 7728.7 | CY11: =SUM(CQ11:CX11)-CS11-CU11 -> 68978.7 | CZ11: =IF($CP11="UNHESA",$AV11+$BE11+$BN11+$BW11+$CF11,0) -> 0 | DA11: =IF($CP11="UNHESA",$AW11+$BF11+$BO11+$BX11+$CG11,0) -> 0 | DB11: =IF($CP11="UNHESA",$AX11+$BG11+$BP11+$BY11+$CH11,0) -> 0 | DC11: =IF($CP11="UNHESA",$AY11+$BH11+$BQ11+$BZ11+$CI11,0) -> 0 | DD11: =IF($CP11="UNHESA",$AZ11+$BI11+$BR11+$CA11+$CJ11,0) -> 0 | DE11: =IF($CP11="UNHESA",$BA11+$BJ11+$BS11+$CB11+$CK11,0) -> 0 | DF11: =IF($CP11="UNHESA",$BB11+$BK11+$BT11+$CC11+$CL11,0) -> 0 | DG11: =IF($CP11="UNHESA",$BC11+$BL11+$BU11+$CD11+$CM11,0) -> 0 | DH11: =SUM(CZ11:DG11)-DB11-DD11 -> 0 | EK11: 3507.5 | ET11: =+EO11+EP11+EQ11 -> 0 | EV11: =IF($H11<=15,EK11/2,EK11) -> 3507.5 | EW11: =IF($H11<=15,EL11/2,EL11) -> 0 | EX11: =IF($H11<=15,EM11/2,EM11) -> 0 | EY11: =IF($H11<=15,EN11/2,EN11) -> 0 | EZ11: =IF($H11<=15,EO11/2,EO11) -> 0 | FA11: =IF($H11<=15,EP11/2,EP11) -> 0 | FB11: =IF($H11<=15,EQ11/2,EQ11) -> 0 | FC11: =IF($H11<=15,ER11/2,ER11) -> 0 | ... FE11: =IF($H11<=15,ET11/2,ET11) -> 0
A12: =+A11+1 -> 3 | B12: Estrada Robles Juan Pablo | C12: Asesor | D12: PROQUIMA | E12: 15000 | F12: 155000 | G12: =+E12+F12 -> 170000 | H12: 30 | I12: 1 | J12: 0 | K12: 0 | L12: 0 | M12: 0 | N12: =SUM(I12:M12) -> 1 | Q12: =($E12/30/8*1.5)*P12 -> 0 | S12: =($E12/30/8*2)*R12 -> 0 | U12: =($E12/30/8*1.5)*T12 -> 0 | W12: =($E12/30/8*2)*V12 -> 0 | Y12: =(($E12/30/8)*1.5)*X12 -> 0 | AA12: =(($E12/30/8)*2)*Z12 -> 0 | AC12: =(($E12/30/8)*1.5)*AB12 -> 0 | AE12: =(($E12/30/8)*2)*AD12 -> 0 | AG12: =(($E12/30/8)*1.5)*AF12 -> 0 | AI12: =(($E12/30/8)*2)*AH12 -> 0 | AV12: =(($E12/30)*$H12)*$I12 -> 15000 | AW12: =(($F12/30)*$H12)*$I12+10923.87+3645 -> 169568.87 | AX12: =P12 -> 0 | AY12: =Q12 -> 0 | AZ12: =R12 -> 0 | BA12: =S12 -> 0 | BB12: =AJ12+AO12 -> 0 | BC12: =(AV12+AY12+BA12)*0.1267 -> 1900.5 | BD12: =SUM(AV12:BC12)-AX12-AZ12 -> 186469.37 | BE12: =(($E12/30)*$H12)*$J12 -> 0 | BF12: =(($F12/30)*$H12)*$J12 -> 0 | BG12: =T12 -> 0 | BH12: =U12 -> 0 | BI12: =V12 -> 0 | BJ12: =W12 -> 0 | BK12: =AK12+AP12 -> 0 | BL12: 0 | BM12: =SUM(BE12:BL12)-BG12-BI12 -> 0 | BN12: =(($E12/30)*$H12)*$K12 -> 0 | BO12: =(($F12/30)*$H12)*$K12 -> 0 | BP12: =X12 -> 0 | BQ12: =Y12 -> 0 | BR12: =Z12 -> 0 | BS12: =AA12 -> 0 | BT12: =AL12+AQ12 -> 0 | BU12: 0 | BV12: =SUM(BN12:BU12)-BP12-BR12 -> 0 | BW12: =(($E12/30)*$H12)*$L12 -> 0 | BX12: =(($F12/30)*$H12)*$L12 -> 0 | BY12: =AB12 -> 0 | BZ12: =AC12 -> 0 | CA12: =AD12 -> 0 | CB12: =AE12 -> 0 | CC12: =AM12+AR12 -> 0 | CD12: =(BW12+BZ12+CB12)*0.1267 -> 0 | CE12: =SUM(BW12:CD12)-BY12-CA12 -> 0 | CF12: =(($E12/30)*$H12)*M12 -> 0 | CG12: =(($F12/30)*$H12)*$M12 -> 0 | CH12: =+AF12 -> 0 | CI12: =AG12 -> 0 | CJ12: =AH12 -> 0 | CK12: =AI12 -> 0 | CL12: =AN12+AS12 -> 0 | CM12: =(CF12+CI12+CK12)*0.1267 -> 0 | CN12: =SUM(CF12:CM12)-CH12-CJ12 -> 0 | CP12: PROQUIMA | CQ12: =IF($CP12="PROQUIMA",$AV12+$BE12+$BN12+$BW12+$CF12,0) -> 15000 | CR12: =IF($CP12="PROQUIMA",$AW12+$BF12+$BO12+$BX12+$CG12,0) -> 169568.87 | CS12: =IF($CP12="PROQUIMA",$AX12+$BG12+$BP12+$BY12+$CH12,0) -> 0 | CT12: =IF($CP12="PROQUIMA",$AY12+$BH12+$BQ12+$BZ12+$CI12,0) -> 0 | CU12: =IF($CP12="PROQUIMA",$AZ12+$BI12+$BR12+$CA12+$CJ12,0) -> 0 | CV12: =IF($CP12="PROQUIMA",$BA12+$BJ12+$BS12+$CB12+$CK12,0) -> 0 | CW12: =IF($CP12="PROQUIMA",$BB12+$BK12+$BT12+$CC12+$CL12,0) -> 0 | CX12: =IF($CP12="PROQUIMA",$BC12+$BL12+$BU12+$CD12+CM12,0) -> 1900.5 | CY12: =SUM(CQ12:CX12)-CS12-CU12 -> 186469.37 | CZ12: =IF($CP12="UNHESA",$AV12+$BE12+$BN12+$BW12+$CF12,0) -> 0 | DA12: =IF($CP12="UNHESA",$AW12+$BF12+$BO12+$BX12+$CG12,0) -> 0 | DB12: =IF($CP12="UNHESA",$AX12+$BG12+$BP12+$BY12+$CH12,0) -> 0 | DC12: =IF($CP12="UNHESA",$AY12+$BH12+$BQ12+$BZ12+$CI12,0) -> 0 | DD12: =IF($CP12="UNHESA",$AZ12+$BI12+$BR12+$CA12+$CJ12,0) -> 0 | DE12: =IF($CP12="UNHESA",$BA12+$BJ12+$BS12+$CB12+$CK12,0) -> 0 | DF12: =IF($CP12="UNHESA",$BB12+$BK12+$BT12+$CC12+$CL12,0) -> 0 | DG12: =IF($CP12="UNHESA",$BC12+$BL12+$BU12+$CD12+$CM12,0) -> 0 | DH12: =SUM(CZ12:DG12)-DB12-DD12 -> 0 | EK12: 15719.44 | ET12: =+EO12+EP12+EQ12 -> 0 | EV12: =IF($H12<=15,EK12/2,EK12) -> 15719.44 | EW12: =IF($H12<=15,EL12/2,EL12) -> 0 | EX12: =IF($H12<=15,EM12/2,EM12) -> 0 | EY12: =IF($H12<=15,EN12/2,EN12) -> 0 | EZ12: =IF($H12<=15,EO12/2,EO12) -> 0 | FA12: =IF($H12<=15,EP12/2,EP12) -> 0 | FB12: =IF($H12<=15,EQ12/2,EQ12) -> 0 | FC12: =IF($H12<=15,ER12/2,ER12) -> 0 | ... FE12: =IF($H12<=15,ET12/2,ET12) -> 0
A13: =+A12+1 -> 4 | B13: Alvarez Caceros Genesis Arleth | C13: Asistente de Gerencia | D13: PROQUIMA | E13: 3500 | F13: 1500 | G13: =+E13+F13 -> 5000 | H13: 30 | I13: 0.5 | J13: 0.5 | K13: 0 | L13: 0 | M13: 0 | N13: =SUM(I13:M13) -> 1 | Q13: =($E13/30/8*1.5)*P13 -> 0 | S13: =($E13/30/8*2)*R13 -> 0 | U13: =($E13/30/8*1.5)*T13 -> 0 | W13: =($E13/30/8*2)*V13 -> 0 | Y13: =(($E13/30/8)*1.5)*X13 -> 0 | AA13: =(($E13/30/8)*2)*Z13 -> 0 | AC13: =(($E13/30/8)*1.5)*AB13 -> 0 | AD13: 0 | AE13: =(($E13/30/8)*2)*AD13 -> 0 | AG13: =(($E13/30/8)*1.5)*AF13 -> 0 | AI13: =(($E13/30/8)*2)*AH13 -> 0 | AV13: =(($E13/30)*$H13)*$I13 -> 1750 | AW13: =(($F13/30)*$H13)*$I13 -> 750 | AX13: =P13 -> 0 | AY13: =Q13 -> 0 | AZ13: =R13 -> 0 | BA13: =S13 -> 0 | BB13: =AJ13+AO13 -> 0 | BC13: =(AV13+AY13+BA13)*0.1267 -> 221.725 | BD13: =SUM(AV13:BC13)-AX13-AZ13 -> 2721.725 | BE13: =(($E13/30)*$H13)*$J13 -> 1750 | BF13: =(($F13/30)*$H13)*$J13 -> 750 | BG13: =T13 -> 0 | BH13: =U13 -> 0 | BI13: =V13 -> 0 | BJ13: =W13 -> 0 | BK13: =AK13+AP13 -> 0 | BL13: 0 | BM13: =SUM(BE13:BL13)-BG13-BI13 -> 2500 | BN13: =(($E13/30)*$H13)*$K13 -> 0 | BO13: =(($F13/30)*$H13)*$K13 -> 0 | BP13: =X13 -> 0 | BQ13: =Y13 -> 0 | BR13: =Z13 -> 0 | BS13: =AA13 -> 0 | BT13: =AL13+AQ13 -> 0 | BU13: 0 | BV13: =SUM(BN13:BU13)-BP13-BR13 -> 0 | BW13: =(($E13/30)*$H13)*$L13 -> 0 | BX13: =(($F13/30)*$H13)*$L13 -> 0 | BY13: =AB13 -> 0 | BZ13: =AC13 -> 0 | CA13: =AD13 -> 0 | CB13: =AE13 -> 0 | CC13: =AM13+AR13 -> 0 | CD13: =(BW13+BZ13+CB13)*0.1267 -> 0 | CE13: =SUM(BW13:CD13)-BY13-CA13 -> 0 | CF13: =(($E13/30)*$H13)*M13 -> 0 | CG13: =(($F13/30)*$H13)*$M13 -> 0 | CH13: =+AF13 -> 0 | CI13: =AG13 -> 0 | CJ13: =AH13 -> 0 | CK13: =AI13 -> 0 | CL13: =AN13+AS13 -> 0 | CM13: =(CF13+CI13+CK13)*0.1267 -> 0 | CN13: =SUM(CF13:CM13)-CH13-CJ13 -> 0 | CP13: PROQUIMA | CQ13: =IF($CP13="PROQUIMA",$AV13+$BE13+$BN13+$BW13+$CF13,0) -> 3500 | CR13: =IF($CP13="PROQUIMA",$AW13+$BF13+$BO13+$BX13+$CG13,0) -> 1500 | CS13: =IF($CP13="PROQUIMA",$AX13+$BG13+$BP13+$BY13+$CH13,0) -> 0 | CT13: =IF($CP13="PROQUIMA",$AY13+$BH13+$BQ13+$BZ13+$CI13,0) -> 0 | CU13: =IF($CP13="PROQUIMA",$AZ13+$BI13+$BR13+$CA13+$CJ13,0) -> 0 | CV13: =IF($CP13="PROQUIMA",$BA13+$BJ13+$BS13+$CB13+$CK13,0) -> 0 | CW13: =IF($CP13="PROQUIMA",$BB13+$BK13+$BT13+$CC13+$CL13,0) -> 0 | CX13: =IF($CP13="PROQUIMA",$BC13+$BL13+$BU13+$CD13+CM13,0) -> 221.725 | CY13: =SUM(CQ13:CX13)-CS13-CU13 -> 5221.725 | CZ13: =IF($CP13="UNHESA",$AV13+$BE13+$BN13+$BW13+$CF13,0) -> 0 | DA13: =IF($CP13="UNHESA",$AW13+$BF13+$BO13+$BX13+$CG13,0) -> 0 | DB13: =IF($CP13="UNHESA",$AX13+$BG13+$BP13+$BY13+$CH13,0) -> 0 | DC13: =IF($CP13="UNHESA",$AY13+$BH13+$BQ13+$BZ13+$CI13,0) -> 0 | DD13: =IF($CP13="UNHESA",$AZ13+$BI13+$BR13+$CA13+$CJ13,0) -> 0 | DE13: =IF($CP13="UNHESA",$BA13+$BJ13+$BS13+$CB13+$CK13,0) -> 0 | DF13: =IF($CP13="UNHESA",$BB13+$BK13+$BT13+$CC13+$CL13,0) -> 0 | DG13: =IF($CP13="UNHESA",$BC13+$BL13+$BU13+$CD13+$CM13,0) -> 0 | DH13: =SUM(CZ13:DG13)-DB13-DD13 -> 0 | EK13: 41.55 | EN13: 17 | EO13: 165 | EP13: 50 | ET13: =+EO13+EP13+EQ13 -> 215 | EV13: =IF($H13<=15,EK13/2,EK13) -> 41.55 | EW13: =IF($H13<=15,EL13/2,EL13) -> 0 | EX13: =IF($H13<=15,EM13/2,EM13) -> 0 | EY13: =IF($H13<=15,EN13/2,EN13) -> 17 | EZ13: =IF($H13<=15,EO13/2,EO13) -> 165 | FA13: =IF($H13<=15,EP13/2,EP13) -> 50 | FB13: =IF($H13<=15,EQ13/2,EQ13) -> 0 | FC13: =IF($H13<=15,ER13/2,ER13) -> 0 | ... FE13: =IF($H13<=15,ET13/2,ET13) -> 215
A14: =+A13+1 -> 5 | B14: Muñoz Laparra Orly Gabriela | D14: UNHESA | E14: 5000 | F14: 4000 | G14: =+E14+F14 -> 9000 | H14: 30 | I14: 0.35 | J14: 0.35 | K14: 0 | L14: 0.3 | M14: 0 | N14: =SUM(I14:M14) -> 1 | Q14: =($E14/30/8*1.5)*P14 -> 0 | S14: =($E14/30/8*2)*R14 -> 0 | U14: =($E14/30/8*1.5)*T14 -> 0 | W14: =($E14/30/8*2)*V14 -> 0 | Y14: =(($E14/30/8)*1.5)*X14 -> 0 | AA14: =(($E14/30/8)*2)*Z14 -> 0 | AC14: =(($E14/30/8)*1.5)*AB14 -> 0 | AD14: 0 | AE14: =(($E14/30/8)*2)*AD14 -> 0 | AG14: =(($E14/30/8)*1.5)*AF14 -> 0 | AI14: =(($E14/30/8)*2)*AH14 -> 0 | AV14: =(($E14/30)*$H14)*$I14 -> 1750 | AW14: =(($F14/30)*$H14)*$I14 -> 1400 | AX14: =P14 -> 0 | AY14: =Q14 -> 0 | AZ14: =R14 -> 0 | BA14: =S14 -> 0 | BB14: =AJ14+AO14 -> 0 | BC14: =(AV14+AY14+BA14)*0.1267 -> 221.725 | BD14: =SUM(AV14:BC14)-AX14-AZ14 -> 3371.725 | BE14: =(($E14/30)*$H14)*$J14 -> 1750 | BF14: =(($F14/30)*$H14)*$J14 -> 1400 | BG14: =T14 -> 0 | BH14: =U14 -> 0 | BI14: =V14 -> 0 | BJ14: =W14 -> 0 | BK14: =AK14+AP14 -> 0 | BL14: 0 | BM14: =SUM(BE14:BL14)-BG14-BI14 -> 3150 | BN14: =(($E14/30)*$H14)*$K14 -> 0 | BO14: =(($F14/30)*$H14)*$K14 -> 0 | BP14: =X14 -> 0 | BQ14: =Y14 -> 0 | BR14: =Z14 -> 0 | BS14: =AA14 -> 0 | BT14: =AL14+AQ14 -> 0 | BU14: 0 | BV14: =SUM(BN14:BU14)-BP14-BR14 -> 0 | BW14: =(($E14/30)*$H14)*$L14 -> 1500 | BX14: =(($F14/30)*$H14)*$L14 -> 1200 | BY14: =AB14 -> 0 | BZ14: =AC14 -> 0 | CA14: =AD14 -> 0 | CB14: =AE14 -> 0 | CC14: =AM14+AR14 -> 0 | CD14: =(BW14+BZ14+CB14)*0.1267 -> 190.05 | CE14: =SUM(BW14:CD14)-BY14-CA14 -> 2890.05 | CF14: =(($E14/30)*$H14)*M14 -> 0 | CG14: =(($F14/30)*$H14)*$M14 -> 0 | CH14: =+AF14 -> 0 | CI14: =AG14 -> 0 | CJ14: =AH14 -> 0 | CK14: =AI14 -> 0 | CL14: =AN14+AS14 -> 0 | CM14: =(CF14+CI14+CK14)*0.1267 -> 0 | CN14: =SUM(CF14:CM14)-CH14-CJ14 -> 0 | CP14: UNHESA | CQ14: =IF($CP14="PROQUIMA",$AV14+$BE14+$BN14+$BW14+$CF14,0) -> 0 | CR14: =IF($CP14="PROQUIMA",$AW14+$BF14+$BO14+$BX14+$CG14,0) -> 0 | CS14: =IF($CP14="PROQUIMA",$AX14+$BG14+$BP14+$BY14+$CH14,0) -> 0 | CT14: =IF($CP14="PROQUIMA",$AY14+$BH14+$BQ14+$BZ14+$CI14,0) -> 0 | CU14: =IF($CP14="PROQUIMA",$AZ14+$BI14+$BR14+$CA14+$CJ14,0) -> 0 | CV14: =IF($CP14="PROQUIMA",$BA14+$BJ14+$BS14+$CB14+$CK14,0) -> 0 | CW14: =IF($CP14="PROQUIMA",$BB14+$BK14+$BT14+$CC14+$CL14,0) -> 0 | CX14: =IF($CP14="PROQUIMA",$BC14+$BL14+$BU14+$CD14+CM14,0) -> 0 | CY14: =SUM(CQ14:CX14)-CS14-CU14 -> 0 | CZ14: =IF($CP14="UNHESA",$AV14+$BE14+$BN14+$BW14+$CF14,0) -> 5000 | DA14: =IF($CP14="UNHESA",$AW14+$BF14+$BO14+$BX14+$CG14,0) -> 4000 | DB14: =IF($CP14="UNHESA",$AX14+$BG14+$BP14+$BY14+$CH14,0) -> 0 | DC14: =IF($CP14="UNHESA",$AY14+$BH14+$BQ14+$BZ14+$CI14,0) -> 0 | DD14: =IF($CP14="UNHESA",$AZ14+$BI14+$BR14+$CA14+$CJ14,0) -> 0 | DE14: =IF($CP14="UNHESA",$BA14+$BJ14+$BS14+$CB14+$CK14,0) -> 0 | DF14: =IF($CP14="UNHESA",$BB14+$BK14+$BT14+$CC14+$CL14,0) -> 0 | DG14: =IF($CP14="UNHESA",$BC14+$BL14+$BU14+$CD14+$CM14,0) -> 411.775 | DH14: =SUM(CZ14:DG14)-DB14-DD14 -> 9411.775 | EK14: 237.93 | EN14: =27+53 -> 80 | EP14: 75 | EQ14: =240 -> 240 | ET14: =+EO14+EP14+EQ14 -> 315 | EV14: =IF($H14<=15,EK14/2,EK14) -> 237.93 | EW14: =IF($H14<=15,EL14/2,EL14) -> 0 | EX14: =IF($H14<=15,EM14/2,EM14) -> 0 | EY14: =IF($H14<=15,EN14/2,EN14) -> 80 | EZ14: =IF($H14<=15,EO14/2,EO14) -> 0 | FA14: =IF($H14<=15,EP14/2,EP14) -> 75 | FB14: =IF($H14<=15,EQ14/2,EQ14) -> 240 | FC14: =IF($H14<=15,ER14/2,ER14) -> 0 | ... FE14: =IF($H14<=15,ET14/2,ET14) -> 315
A15: =+A14+1 -> 6 | B15: Quevedo Lopez Ingrid Aracely | C15: Conserje | D15: UNHESA | E15: 3166.38 | F15: 250 | G15: =+E15+F15 -> 3416.38 | H15: 30 | I15: 0 | J15: 1 | K15: 0 | L15: 0 | M15: 0 | N15: =SUM(I15:M15) -> 1 | Q15: =($E15/30/8*1.5)*P15 -> 0 | S15: =($E15/30/8*2)*R15 -> 0 | U15: =($E15/30/8*1.5)*T15 -> 0 | W15: =($E15/30/8*2)*V15 -> 0 | Y15: =(($E15/30/8)*1.5)*X15 -> 0 | AA15: =(($E15/30/8)*2)*Z15 -> 0 | AC15: =(($E15/30/8)*1.5)*AB15 -> 0 | AE15: =(($E15/30/8)*2)*AD15 -> 0 | AG15: =(($E15/30/8)*1.5)*AF15 -> 0 | AI15: =(($E15/30/8)*2)*AH15 -> 0 | AV15: =((E15/30)*H15)*$I15 -> 0 | AW15: =((F15/30)*H15)*$I15 -> 0 | AX15: =P15 -> 0 | AY15: =Q15 -> 0 | AZ15: =R15 -> 0 | BA15: =S15 -> 0 | BB15: =AJ15+AO15 -> 0 | BC15: =(AV15+AY15+BA15)*0.1267 -> 0 | BD15: =SUM(AV15:BC15)-AX15-AZ15 -> 0 | BE15: =(($E15/30)*$H15)*$J15 -> 3166.38 | BF15: =(($F15/30)*$H15)*$J15 -> 250 | BG15: =T15 -> 0 | BH15: =U15 -> 0 | BI15: =V15 -> 0 | BJ15: =W15 -> 0 | BK15: =AK15+AP15 -> 0 | BL15: =(+BE15+BH15+BJ15+BK15)*0.1267 -> 401.18035 | BM15: =SUM(BE15:BL15)-BG15-BI15 -> 3817.5603 | BN15: =(($E15/30)*$H15)*$K15 -> 0 | BO15: =(($F15/30)*$H15)*$K15 -> 0 | BP15: =X15 -> 0 | BQ15: =Y15 -> 0 | BR15: =Z15 -> 0 | BS15: =AA15 -> 0 | BT15: =AL15+AQ15 -> 0 | BU15: =(BN15+BQ15+BS15)*0.1267 -> 0 | BV15: =SUM(BN15:BU15)-BP15-BR15 -> 0 | BW15: =(($E15/30)*$H15)*$L15 -> 0 | BX15: =(($F15/30)*$H15)*$L15 -> 0 | BY15: =AB15 -> 0 | BZ15: =AC15 -> 0 | CA15: =AD15 -> 0 | CB15: =AE15 -> 0 | CC15: =AM15+AR15 -> 0 | CD15: =(BW15+BZ15+CB15)*0.1267 -> 0 | CE15: =SUM(BW15:CD15)-BY15-CA15 -> 0 | CF15: =(($E15/30)*$H15)*M15 -> 0 | CG15: =(($F15/30)*$H15)*$M15 -> 0 | CH15: =+AF15 -> 0 | CI15: =AG15 -> 0 | CJ15: =AH15 -> 0 | CK15: =AI15 -> 0 | CL15: =AN15+AS15 -> 0 | CM15: =(CF15+CI15+CK15)*0.1267 -> 0 | CN15: =SUM(CF15:CM15)-CH15-CJ15 -> 0 | CP15: UNHESA | CQ15: =IF($CP15="PROQUIMA",$AV15+$BE15+$BN15+$BW15+$CF15,0) -> 0 | CR15: =IF($CP15="PROQUIMA",$AW15+$BF15+$BO15+$BX15+$CG15,0) -> 0 | CS15: =IF($CP15="PROQUIMA",$AX15+$BG15+$BP15+$BY15+$CH15,0) -> 0 | CT15: =IF($CP15="PROQUIMA",$AY15+$BH15+$BQ15+$BZ15+$CI15,0) -> 0 | CU15: =IF($CP15="PROQUIMA",$AZ15+$BI15+$BR15+$CA15+$CJ15,0) -> 0 | CV15: =IF($CP15="PROQUIMA",$BA15+$BJ15+$BS15+$CB15+$CK15,0) -> 0 | CW15: =IF($CP15="PROQUIMA",$BB15+$BK15+$BT15+$CC15+$CL15,0) -> 0 | CX15: =IF($CP15="PROQUIMA",$BC15+$BL15+$BU15+$CD15+CM15,0) -> 0 | CY15: =SUM(CQ15:CX15)-CS15-CU15 -> 0 | CZ15: =IF($CP15="UNHESA",$AV15+$BE15+$BN15+$BW15+$CF15,0) -> 3166.38 | DA15: =IF($CP15="UNHESA",$AW15+$BF15+$BO15+$BX15+$CG15,0) -> 250 | DB15: =IF($CP15="UNHESA",$AX15+$BG15+$BP15+$BY15+$CH15,0) -> 0 | DC15: =IF($CP15="UNHESA",$AY15+$BH15+$BQ15+$BZ15+$CI15,0) -> 0 | DD15: =IF($CP15="UNHESA",$AZ15+$BI15+$BR15+$CA15+$CJ15,0) -> 0 | DE15: =IF($CP15="UNHESA",$BA15+$BJ15+$BS15+$CB15+$CK15,0) -> 0 | DF15: =IF($CP15="UNHESA",$BB15+$BK15+$BT15+$CC15+$CL15,0) -> 0 | DG15: =IF($CP15="UNHESA",$BC15+$BL15+$BU15+$CD15+$CM15,0) -> 401.18035 | DH15: =SUM(CZ15:DG15)-DB15-DD15 -> 3817.5603 | DI15: =IF($CP15="UNHESA LIQUIDOS",$AV15+$BE15+$BN15+$BW15+$CF15,0) -> 0 | DJ15: =IF($CP15="CALIDUL",$AW15+$BF15+$BO15+$BX15+$CG15,0) -> 0 | DK15: =IF($CP15="CALIDUL",$AX15+$BG15+$BP15+$BY15+$CH15,0) -> 0 | DL15: =IF($CP15="CALIDUL",$AY15+$BH15+$BQ15+$BZ15+$CI15,0) -> 0 | DM15: =IF($CP15="CALIDUL",$AZ15+$BI15+$BR15+$CA15+$CJ15,0) -> 0 | DN15: =IF($CP15="CALIDUL",$BA15+$BJ15+$BS15+$CB15+$CK15,0) -> 0 | DO15: =IF($CP15="CALIDUL",$BB15+$BK15+$BT15+$CC15+$CL15,0) -> 0 | DP15: =IF($CP15="CALIDUL",$BC15+$BL15+$BU15+$CD15+$CM15,0) -> 0 | DQ15: =SUM(DI15:DP15)-DK15-DM15 -> 0 | DR15: =IF($CP15="ECONACIONAL",$AV15+$BE15+$BN15+$BW15+$CF15,0) -> 0 | DS15: =IF($CP15="ECONACIONAL",$AW15+$BF15+$BO15+$BX15+$CG15,0) -> 0 | DT15: =IF($CP15="ECONACIONAL",$AX15+$BG15+$BP15+$BY15+$CH15,0) -> 0 | DU15: =IF($CP15="ECONACIONAL",$AY15+$BH15+$BQ15+$BZ15+$CI15,0) -> 0 | DV15: =IF($CP15="ECONACIONAL",$AZ15+$BI15+$BR15+$CA15+$CJ15,0) -> 0 | DW15: =IF($CP15="ECONACIONAL",$BA15+$BJ15+$BS15+$CB15+$CK15,0) -> 0 | DX15: =IF($CP15="ECONACIONAL",$BB15+$BK15+$BT15+$CC15+$CL15,0) -> 0 | DY15: =IF($CP15="ECONACIONAL",$BC15+$BL15+$BU15+$CD15+$CM15,0) -> 0 | DZ15: =SUM(DR15:DY15)-DT15-DV15 -> 0 | EA15: =IF($CP15="CLEARTEC",$AV15+$BE15+$BN15+$BW15+$CF15,0) -> 0 | EB15: =IF($CP15="CLEARTEC",$AW15+$BF15+$BO15+$BX15+$CG15,0) -> 0 | EC15: =IF($CP15="CLEARTEC",$AX15+$BG15+$BP15+$BY15+$CH15,0) -> 0 | ED15: =IF($CP15="CLEARTEC",$AY15+$BH15+$BQ15+$BZ15+$CI15,0) -> 0 | EE15: =IF($CP15="CLEARTEC",$AZ15+$BI15+$BR15+$CA15+$CJ15,0) -> 0 | EF15: =IF($CP15="CLEARTEC",$BA15+$BJ15+$BS15+$CB15+$CK15,0) -> 0 | EG15: =IF($CP15="CLEARTEC",$BB15+$BK15+$BT15+$CC15+$CL15,0) -> 0 | EH15: =IF($CP15="CLEARTEC",$BC15+$BL15+$BU15+$CD15+$CM15,0) -> 0 | EI15: =SUM(EA15:EH15)-EC15-EE15 -> 0 | EP15: 50 | ET15: =+EO15+EP15+EQ15 -> 50 | EV15: =IF($H15<=15,EK15/2,EK15) -> 0 | EW15: =IF($H15<=15,EL15/2,EL15) -> 0 | EX15: =IF($H15<=15,EM15/2,EM15) -> 0 | EY15: =IF($H15<=15,EN15/2,EN15) -> 0 | EZ15: =IF($H15<=15,EO15/2,EO15) -> 0 | FA15: =IF($H15<=15,EP15/2,EP15) -> 50 | FB15: =IF($H15<=15,EQ15/2,EQ15) -> 0 | FC15: =IF($H15<=15,ER15/2,ER15) -> 0 | ... FE15: =IF($H15<=15,ET15/2,ET15) -> 50
A16: =+A15+1 -> 7 | B16: Morales Alvarez Yony | C16: Conserje | D16: UNHESA | E16: 3166.38 | F16: 250 | G16: =+E16+F16 -> 3416.38 | H16: 30 | I16: 0 | J16: 1 | K16: 0 | L16: 0 | M16: 0 | N16: =SUM(I16:M16) -> 1 | Q16: =($E16/30/8*1.5)*P16 -> 0 | S16: =($E16/30/8*2)*R16 -> 0 | U16: =($E16/30/8*1.5)*T16 -> 0 | W16: =($E16/30/8*2)*V16 -> 0 | Y16: =(($E16/30/8)*1.5)*X16 -> 0 | AA16: =(($E16/30/8)*2)*Z16 -> 0 | AC16: =(($E16/30/8)*1.5)*AB16 -> 0 | AE16: =(($E16/30/8)*2)*AD16 -> 0 | AG16: =(($E16/30/8)*1.5)*AF16 -> 0 | AI16: =(($E16/30/8)*2)*AH16 -> 0 | AV16: =((E16/30)*H16)*$I16 -> 0 | AW16: =((F16/30)*H16)*$I16 -> 0 | AX16: =P16 -> 0 | AY16: =Q16 -> 0 | AZ16: =R16 -> 0 | BA16: =S16 -> 0 | BB16: =AJ16+AO16 -> 0 | BC16: =(AV16+AY16+BA16)*0.1267 -> 0 | BD16: =SUM(AV16:BC16)-AX16-AZ16 -> 0 | BE16: =(($E16/30)*$H16)*$J16 -> 3166.38 | BF16: =(($F16/30)*$H16)*$J16 -> 250 | BG16: =T16 -> 0 | BH16: =U16 -> 0 | BI16: =V16 -> 0 | BJ16: =W16 -> 0 | BK16: =AK16+AP16 -> 0 | BL16: =(+BE16+BH16+BJ16+BK16)*0.1267 -> 401.18035 | BM16: =SUM(BE16:BL16)-BG16-BI16 -> 3817.5603 | BN16: =(($E16/30)*$H16)*$K16 -> 0 | BO16: =(($F16/30)*$H16)*$K16 -> 0 | BP16: =X16 -> 0 | BQ16: =Y16 -> 0 | BR16: =Z16 -> 0 | BS16: =AA16 -> 0 | BT16: =AL16+AQ16 -> 0 | BU16: =(BN16+BQ16+BS16)*0.1267 -> 0 | BV16: =SUM(BN16:BU16)-BP16-BR16 -> 0 | BW16: =(($E16/30)*$H16)*$L16 -> 0 | BX16: =(($F16/30)*$H16)*$L16 -> 0 | BY16: =AB16 -> 0 | BZ16: =AC16 -> 0 | CA16: =AD16 -> 0 | CB16: =AE16 -> 0 | CC16: =AM16+AR16 -> 0 | CD16: =(BW16+BZ16+CB16)*0.1267 -> 0 | CE16: =SUM(BW16:CD16)-BY16-CA16 -> 0 | CF16: =(($E16/30)*$H16)*M16 -> 0 | CG16: =(($F16/30)*$H16)*$M16 -> 0 | CH16: =+AF16 -> 0 | CI16: =AG16 -> 0 | CJ16: =AH16 -> 0 | CK16: =AI16 -> 0 | CL16: =AN16+AS16 -> 0 | CM16: =(CF16+CI16+CK16)*0.1267 -> 0 | CN16: =SUM(CF16:CM16)-CH16-CJ16 -> 0 | CP16: UNHESA | CQ16: =IF($CP16="PROQUIMA",$AV16+$BE16+$BN16+$BW16+$CF16,0) -> 0 | CR16: =IF($CP16="PROQUIMA",$AW16+$BF16+$BO16+$BX16+$CG16,0) -> 0 | CS16: =IF($CP16="PROQUIMA",$AX16+$BG16+$BP16+$BY16+$CH16,0) -> 0 | CT16: =IF($CP16="PROQUIMA",$AY16+$BH16+$BQ16+$BZ16+$CI16,0) -> 0 | CU16: =IF($CP16="PROQUIMA",$AZ16+$BI16+$BR16+$CA16+$CJ16,0) -> 0 | CV16: =IF($CP16="PROQUIMA",$BA16+$BJ16+$BS16+$CB16+$CK16,0) -> 0 | CW16: =IF($CP16="PROQUIMA",$BB16+$BK16+$BT16+$CC16+$CL16,0) -> 0 | CX16: =IF($CP16="PROQUIMA",$BC16+$BL16+$BU16+$CD16+CM16,0) -> 0 | CY16: =SUM(CQ16:CX16)-CS16-CU16 -> 0 | CZ16: =IF($CP16="UNHESA",$AV16+$BE16+$BN16+$BW16+$CF16,0) -> 3166.38 | DA16: =IF($CP16="UNHESA",$AW16+$BF16+$BO16+$BX16+$CG16,0) -> 250 | DB16: =IF($CP16="UNHESA",$AX16+$BG16+$BP16+$BY16+$CH16,0) -> 0 | DC16: =IF($CP16="UNHESA",$AY16+$BH16+$BQ16+$BZ16+$CI16,0) -> 0 | DD16: =IF($CP16="UNHESA",$AZ16+$BI16+$BR16+$CA16+$CJ16,0) -> 0 | DE16: =IF($CP16="UNHESA",$BA16+$BJ16+$BS16+$CB16+$CK16,0) -> 0 | DF16: =IF($CP16="UNHESA",$BB16+$BK16+$BT16+$CC16+$CL16,0) -> 0 | DG16: =IF($CP16="UNHESA",$BC16+$BL16+$BU16+$CD16+$CM16,0) -> 401.18035 | DH16: =SUM(CZ16:DG16)-DB16-DD16 -> 3817.5603 | DI16: =IF($CP16="UNHESA LIQUIDOS",$AV16+$BE16+$BN16+$BW16+$CF16,0) -> 0 | DJ16: =IF($CP16="CALIDUL",$AW16+$BF16+$BO16+$BX16+$CG16,0) -> 0 | DK16: =IF($CP16="CALIDUL",$AX16+$BG16+$BP16+$BY16+$CH16,0) -> 0 | DL16: =IF($CP16="CALIDUL",$AY16+$BH16+$BQ16+$BZ16+$CI16,0) -> 0 | DM16: =IF($CP16="CALIDUL",$AZ16+$BI16+$BR16+$CA16+$CJ16,0) -> 0 | DN16: =IF($CP16="CALIDUL",$BA16+$BJ16+$BS16+$CB16+$CK16,0) -> 0 | DO16: =IF($CP16="CALIDUL",$BB16+$BK16+$BT16+$CC16+$CL16,0) -> 0 | DP16: =IF($CP16="CALIDUL",$BC16+$BL16+$BU16+$CD16+$CM16,0) -> 0 | DQ16: =SUM(DI16:DP16)-DK16-DM16 -> 0 | DR16: =IF($CP16="ECONACIONAL",$AV16+$BE16+$BN16+$BW16+$CF16,0) -> 0 | DS16: =IF($CP16="ECONACIONAL",$AW16+$BF16+$BO16+$BX16+$CG16,0) -> 0 | DT16: =IF($CP16="ECONACIONAL",$AX16+$BG16+$BP16+$BY16+$CH16,0) -> 0 | DU16: =IF($CP16="ECONACIONAL",$AY16+$BH16+$BQ16+$BZ16+$CI16,0) -> 0 | DV16: =IF($CP16="ECONACIONAL",$AZ16+$BI16+$BR16+$CA16+$CJ16,0) -> 0 | DW16: =IF($CP16="ECONACIONAL",$BA16+$BJ16+$BS16+$CB16+$CK16,0) -> 0 | DX16: =IF($CP16="ECONACIONAL",$BB16+$BK16+$BT16+$CC16+$CL16,0) -> 0 | DY16: =IF($CP16="ECONACIONAL",$BC16+$BL16+$BU16+$CD16+$CM16,0) -> 0 | DZ16: =SUM(DR16:DY16)-DT16-DV16 -> 0 | EA16: =IF($CP16="CLEARTEC",$AV16+$BE16+$BN16+$BW16+$CF16,0) -> 0 | EB16: =IF($CP16="CLEARTEC",$AW16+$BF16+$BO16+$BX16+$CG16,0) -> 0 | EC16: =IF($CP16="CLEARTEC",$AX16+$BG16+$BP16+$BY16+$CH16,0) -> 0 | ED16: =IF($CP16="CLEARTEC",$AY16+$BH16+$BQ16+$BZ16+$CI16,0) -> 0 | EE16: =IF($CP16="CLEARTEC",$AZ16+$BI16+$BR16+$CA16+$CJ16,0) -> 0 | EF16: =IF($CP16="CLEARTEC",$BA16+$BJ16+$BS16+$CB16+$CK16,0) -> 0 | EG16: =IF($CP16="CLEARTEC",$BB16+$BK16+$BT16+$CC16+$CL16,0) -> 0 | EH16: =IF($CP16="CLEARTEC",$BC16+$BL16+$BU16+$CD16+$CM16,0) -> 0 | EI16: =SUM(EA16:EH16)-EC16-EE16 -> 0 | EP16: 50 | ET16: =+EO16+EP16+EQ16 -> 50 | EV16: =IF($H16<=15,EK16/2,EK16) -> 0 | EW16: =IF($H16<=15,EL16/2,EL16) -> 0 | EX16: =IF($H16<=15,EM16/2,EM16) -> 0 | EY16: =IF($H16<=15,EN16/2,EN16) -> 0 | EZ16: =IF($H16<=15,EO16/2,EO16) -> 0 | FA16: =IF($H16<=15,EP16/2,EP16) -> 50 | FB16: =IF($H16<=15,EQ16/2,EQ16) -> 0 | FC16: =IF($H16<=15,ER16/2,ER16) -> 0 | ... FE16: =IF($H16<=15,ET16/2,ET16) -> 50
A17: =+A16+1 -> 8 | B17: Veliz Carias Elder Danilo | C17: Piloto | D17: UNHESA | E17: 3166.38 | F17: 250 | G17: =+E17+F17 -> 3416.38 | H17: 30 | I17: 0 | J17: 1 | K17: 0 | L17: 0 | M17: 0 | N17: =SUM(I17:M17) -> 1 | Q17: =($E17/30/8*1.5)*P17 -> 0 | S17: =($E17/30/8*2)*R17 -> 0 | U17: =($E17/30/8*1.5)*T17 -> 0 | W17: =($E17/30/8*2)*V17 -> 0 | Y17: =(($E17/30/8)*1.5)*X17 -> 0 | AA17: =(($E17/30/8)*2)*Z17 -> 0 | AC17: =(($E17/30/8)*1.5)*AB17 -> 0 | AE17: =(($E17/30/8)*2)*AD17 -> 0 | AG17: =(($E17/30/8)*1.5)*AF17 -> 0 | AI17: =(($E17/30/8)*2)*AH17 -> 0 | AV17: =((E17/30)*H17)*$I17 -> 0 | AW17: =((F17/30)*H17)*$I17 -> 0 | AX17: =P17 -> 0 | AY17: =Q17 -> 0 | AZ17: =R17 -> 0 | BA17: =S17 -> 0 | BB17: =AJ17+AO17 -> 0 | BC17: =(AV17+AY17+BA17)*0.1267 -> 0 | BD17: =SUM(AV17:BC17)-AX17-AZ17 -> 0 | BE17: =(($E17/30)*$H17)*$J17 -> 3166.38 | BF17: =(($F17/30)*$H17)*$J17 -> 250 | BG17: =T17 -> 0 | BH17: =U17 -> 0 | BI17: =V17 -> 0 | BJ17: =W17 -> 0 | BK17: =AK17+AP17 -> 0 | BL17: =(+BE17+BH17+BJ17+BK17)*0.1267 -> 401.18035 | BM17: =SUM(BE17:BL17)-BG17-BI17 -> 3817.5603 | BN17: =(($E17/30)*$H17)*$K17 -> 0 | BO17: =(($F17/30)*$H17)*$K17 -> 0 | BP17: =X17 -> 0 | BQ17: =Y17 -> 0 | BR17: =Z17 -> 0 | BS17: =AA17 -> 0 | BT17: =AL17+AQ17 -> 0 | BU17: =(BN17+BQ17+BS17)*0.1267 -> 0 | BV17: =SUM(BN17:BU17)-BP17-BR17 -> 0 | BW17: =(($E17/30)*$H17)*$L17 -> 0 | BX17: =(($F17/30)*$H17)*$L17 -> 0 | BY17: =AB17 -> 0 | BZ17: =AC17 -> 0 | CA17: =AD17 -> 0 | CB17: =AE17 -> 0 | CC17: =AM17+AR17 -> 0 | CD17: =(BW17+BZ17+CB17)*0.1267 -> 0 | CE17: =SUM(BW17:CD17)-BY17-CA17 -> 0 | CF17: =(($E17/30)*$H17)*M17 -> 0 | CG17: =(($F17/30)*$H17)*$M17 -> 0 | CH17: =+AF17 -> 0 | CI17: =AG17 -> 0 | CJ17: =AH17 -> 0 | CK17: =AI17 -> 0 | CL17: =AN17+AS17 -> 0 | CM17: =(CF17+CI17+CK17)*0.1267 -> 0 | CN17: =SUM(CF17:CM17)-CH17-CJ17 -> 0 | CP17: UNHESA | CQ17: =IF($CP17="PROQUIMA",$AV17+$BE17+$BN17+$BW17+$CF17,0) -> 0 | CR17: =IF($CP17="PROQUIMA",$AW17+$BF17+$BO17+$BX17+$CG17,0) -> 0 | CS17: =IF($CP17="PROQUIMA",$AX17+$BG17+$BP17+$BY17+$CH17,0) -> 0 | CT17: =IF($CP17="PROQUIMA",$AY17+$BH17+$BQ17+$BZ17+$CI17,0) -> 0 | CU17: =IF($CP17="PROQUIMA",$AZ17+$BI17+$BR17+$CA17+$CJ17,0) -> 0 | CV17: =IF($CP17="PROQUIMA",$BA17+$BJ17+$BS17+$CB17+$CK17,0) -> 0 | CW17: =IF($CP17="PROQUIMA",$BB17+$BK17+$BT17+$CC17+$CL17,0) -> 0 | CX17: =IF($CP17="PROQUIMA",$BC17+$BL17+$BU17+$CD17+CM17,0) -> 0 | CY17: =SUM(CQ17:CX17)-CS17-CU17 -> 0 | CZ17: =IF($CP17="UNHESA",$AV17+$BE17+$BN17+$BW17+$CF17,0) -> 3166.38 | DA17: =IF($CP17="UNHESA",$AW17+$BF17+$BO17+$BX17+$CG17,0) -> 250 | DB17: =IF($CP17="UNHESA",$AX17+$BG17+$BP17+$BY17+$CH17,0) -> 0 | DC17: =IF($CP17="UNHESA",$AY17+$BH17+$BQ17+$BZ17+$CI17,0) -> 0 | DD17: =IF($CP17="UNHESA",$AZ17+$BI17+$BR17+$CA17+$CJ17,0) -> 0 | DE17: =IF($CP17="UNHESA",$BA17+$BJ17+$BS17+$CB17+$CK17,0) -> 0 | DF17: =IF($CP17="UNHESA",$BB17+$BK17+$BT17+$CC17+$CL17,0) -> 0 | DG17: =IF($CP17="UNHESA",$BC17+$BL17+$BU17+$CD17+$CM17,0) -> 401.18035 | DH17: =SUM(CZ17:DG17)-DB17-DD17 -> 3817.5603 | DI17: =IF($CP17="UNHESA LIQUIDOS",$AV17+$BE17+$BN17+$BW17+$CF17,0) -> 0 | DJ17: =IF($CP17="CALIDUL",$AW17+$BF17+$BO17+$BX17+$CG17,0) -> 0 | DK17: =IF($CP17="CALIDUL",$AX17+$BG17+$BP17+$BY17+$CH17,0) -> 0 | DL17: =IF($CP17="CALIDUL",$AY17+$BH17+$BQ17+$BZ17+$CI17,0) -> 0 | DM17: =IF($CP17="CALIDUL",$AZ17+$BI17+$BR17+$CA17+$CJ17,0) -> 0 | DN17: =IF($CP17="CALIDUL",$BA17+$BJ17+$BS17+$CB17+$CK17,0) -> 0 | DO17: =IF($CP17="CALIDUL",$BB17+$BK17+$BT17+$CC17+$CL17,0) -> 0 | DP17: =IF($CP17="CALIDUL",$BC17+$BL17+$BU17+$CD17+$CM17,0) -> 0 | DQ17: =SUM(DI17:DP17)-DK17-DM17 -> 0 | DR17: =IF($CP17="ECONACIONAL",$AV17+$BE17+$BN17+$BW17+$CF17,0) -> 0 | DS17: =IF($CP17="ECONACIONAL",$AW17+$BF17+$BO17+$BX17+$CG17,0) -> 0 | DT17: =IF($CP17="ECONACIONAL",$AX17+$BG17+$BP17+$BY17+$CH17,0) -> 0 | DU17: =IF($CP17="ECONACIONAL",$AY17+$BH17+$BQ17+$BZ17+$CI17,0) -> 0 | DV17: =IF($CP17="ECONACIONAL",$AZ17+$BI17+$BR17+$CA17+$CJ17,0) -> 0 | DW17: =IF($CP17="ECONACIONAL",$BA17+$BJ17+$BS17+$CB17+$CK17,0) -> 0 | DX17: =IF($CP17="ECONACIONAL",$BB17+$BK17+$BT17+$CC17+$CL17,0) -> 0 | DY17: =IF($CP17="ECONACIONAL",$BC17+$BL17+$BU17+$CD17+$CM17,0) -> 0 | DZ17: =SUM(DR17:DY17)-DT17-DV17 -> 0 | EA17: =IF($CP17="CLEARTEC",$AV17+$BE17+$BN17+$BW17+$CF17,0) -> 0 | EB17: =IF($CP17="CLEARTEC",$AW17+$BF17+$BO17+$BX17+$CG17,0) -> 0 | EC17: =IF($CP17="CLEARTEC",$AX17+$BG17+$BP17+$BY17+$CH17,0) -> 0 | ED17: =IF($CP17="CLEARTEC",$AY17+$BH17+$BQ17+$BZ17+$CI17,0) -> 0 | EE17: =IF($CP17="CLEARTEC",$AZ17+$BI17+$BR17+$CA17+$CJ17,0) -> 0 | EF17: =IF($CP17="CLEARTEC",$BA17+$BJ17+$BS17+$CB17+$CK17,0) -> 0 | EG17: =IF($CP17="CLEARTEC",$BB17+$BK17+$BT17+$CC17+$CL17,0) -> 0 | EH17: =IF($CP17="CLEARTEC",$BC17+$BL17+$BU17+$CD17+$CM17,0) -> 0 | EI17: =SUM(EA17:EH17)-EC17-EE17 -> 0 | EP17: 50 | ET17: =+EO17+EP17+EQ17 -> 50 | EV17: =IF($H17<=15,EK17/2,EK17) -> 0 | EW17: =IF($H17<=15,EL17/2,EL17) -> 0 | EX17: =IF($H17<=15,EM17/2,EM17) -> 0 | EY17: =IF($H17<=15,EN17/2,EN17) -> 0 | EZ17: =IF($H17<=15,EO17/2,EO17) -> 0 | FA17: =IF($H17<=15,EP17/2,EP17) -> 50 | FB17: =IF($H17<=15,EQ17/2,EQ17) -> 0 | FC17: =IF($H17<=15,ER17/2,ER17) -> 0 | ... FE17: =IF($H17<=15,ET17/2,ET17) -> 50 | FF17: 0 | FG17: 1 | FH17: 0 | FI17: 0 | FJ17: 0 | FK17: 1 | FL17: =+EP17-FA17 -> 0
A18: =+A17+1 -> 9 | B18: Alvarez Fajardo Erick Geovanni | C18: Piloto | D18: PROQUIMA | E18: 3166.38 | F18: 1540.76 | G18: =+E18+F18 -> 4707.14 | H18: 9 | I18: 1 | J18: 0 | K18: 0 | L18: 0 | M18: 0 | N18: =SUM(I18:M18) -> 1 | O18: B.9.1.23 | Q18: =($E18/30/8*1.5)*P18 -> 0 | S18: =($E18/30/8*2)*R18 -> 0 | U18: =($E18/30/8*1.5)*T18 -> 0 | W18: =($E18/30/8*2)*V18 -> 0 | Y18: =(($E18/30/8)*1.5)*X18 -> 0 | AA18: =(($E18/30/8)*2)*Z18 -> 0 | AC18: =(($E18/30/8)*1.5)*AB18 -> 0 | AE18: =(($E18/30/8)*2)*AD18 -> 0 | AG18: =(($E18/30/8)*1.5)*AF18 -> 0 | AI18: =(($E18/30/8)*2)*AH18 -> 0 | AV18: =((E18/30)*H18)*$I18 -> 949.914 | AW18: =((F18/30)*H18)*$I18 -> 462.228 | AX18: =P18 -> 0 | AY18: =Q18 -> 0 | AZ18: =R18 -> 0 | BA18: =S18 -> 0 | BB18: =AJ18+AO18 -> 0 | BC18: =(AV18+AY18+BA18)*0.1267 -> 120.3541 | BD18: =SUM(AV18:BC18)-AX18-AZ18 -> 1532.4961 | BE18: =(($E18/30)*$H18)*$J18 -> 0 | BF18: =(($F18/30)*$H18)*$J18 -> 0 | BG18: =T18 -> 0 | BH18: =U18 -> 0 | BI18: =V18 -> 0 | BJ18: =W18 -> 0 | BK18: =AK18+AP18 -> 0 | BL18: =(+BE18+BH18+BJ18+BK18)*0.1267 -> 0 | BM18: =SUM(BE18:BL18)-BG18-BI18 -> 0 | BN18: =(($E18/30)*$H18)*$K18 -> 0 | BO18: =(($F18/30)*$H18)*$K18 -> 0 | BP18: =X18 -> 0 | BQ18: =Y18 -> 0 | BR18: =Z18 -> 0 | BS18: =AA18 -> 0 | BT18: =AL18+AQ18 -> 0 | BU18: =(BN18+BQ18+BS18)*0.1267 -> 0 | BV18: =SUM(BN18:BU18)-BP18-BR18 -> 0 | BW18: =(($E18/30)*$H18)*$L18 -> 0 | BX18: =(($F18/30)*$H18)*$L18 -> 0 | BY18: =AB18 -> 0 | BZ18: =AC18 -> 0 | CA18: =AD18 -> 0 | CB18: =AE18 -> 0 | CC18: =AM18+AR18 -> 0 | CD18: =(BW18+BZ18+CB18)*0.1267 -> 0 | CE18: =SUM(BW18:CD18)-BY18-CA18 -> 0 | CF18: =(($E18/30)*$H18)*M18 -> 0 | CG18: =(($F18/30)*$H18)*$M18 -> 0 | CH18: =+AF18 -> 0 | CI18: =AG18 -> 0 | CJ18: =AH18 -> 0 | CK18: =AI18 -> 0 | CL18: =AN18+AS18 -> 0 | CM18: =(CF18+CI18+CK18)*0.1267 -> 0 | CN18: =SUM(CF18:CM18)-CH18-CJ18 -> 0 | CP18: PROQUIMA | CQ18: =IF($CP18="PROQUIMA",$AV18+$BE18+$BN18+$BW18+$CF18,0) -> 949.914 | CR18: =IF($CP18="PROQUIMA",$AW18+$BF18+$BO18+$BX18+$CG18,0) -> 462.228 | CS18: =IF($CP18="PROQUIMA",$AX18+$BG18+$BP18+$BY18+$CH18,0) -> 0 | CT18: =IF($CP18="PROQUIMA",$AY18+$BH18+$BQ18+$BZ18+$CI18,0) -> 0 | CU18: =IF($CP18="PROQUIMA",$AZ18+$BI18+$BR18+$CA18+$CJ18,0) -> 0 | CV18: =IF($CP18="PROQUIMA",$BA18+$BJ18+$BS18+$CB18+$CK18,0) -> 0 | CW18: =IF($CP18="PROQUIMA",$BB18+$BK18+$BT18+$CC18+$CL18,0) -> 0 | CX18: =IF($CP18="PROQUIMA",$BC18+$BL18+$BU18+$CD18+CM18,0) -> 120.3541 | CY18: =SUM(CQ18:CX18)-CS18-CU18 -> 1532.4961 | CZ18: =IF($CP18="UNHESA",$AV18+$BE18+$BN18+$BW18+$CF18,0) -> 0 | DA18: =IF($CP18="UNHESA",$AW18+$BF18+$BO18+$BX18+$CG18,0) -> 0 | DB18: =IF($CP18="UNHESA",$AX18+$BG18+$BP18+$BY18+$CH18,0) -> 0 | DC18: =IF($CP18="UNHESA",$AY18+$BH18+$BQ18+$BZ18+$CI18,0) -> 0 | DD18: =IF($CP18="UNHESA",$AZ18+$BI18+$BR18+$CA18+$CJ18,0) -> 0 | DE18: =IF($CP18="UNHESA",$BA18+$BJ18+$BS18+$CB18+$CK18,0) -> 0 | DF18: =IF($CP18="UNHESA",$BB18+$BK18+$BT18+$CC18+$CL18,0) -> 0 | DG18: =IF($CP18="UNHESA",$BC18+$BL18+$BU18+$CD18+$CM18,0) -> 0 | DH18: =SUM(CZ18:DG18)-DB18-DD18 -> 0 | DI18: =IF($CP18="UNHESA LIQUIDOS",$AV18+$BE18+$BN18+$BW18+$CF18,0) -> 0 | DJ18: =IF($CP18="CALIDUL",$AW18+$BF18+$BO18+$BX18+$CG18,0) -> 0 | DK18: =IF($CP18="CALIDUL",$AX18+$BG18+$BP18+$BY18+$CH18,0) -> 0 | DL18: =IF($CP18="CALIDUL",$AY18+$BH18+$BQ18+$BZ18+$CI18,0) -> 0 | DM18: =IF($CP18="CALIDUL",$AZ18+$BI18+$BR18+$CA18+$CJ18,0) -> 0 | DN18: =IF($CP18="CALIDUL",$BA18+$BJ18+$BS18+$CB18+$CK18,0) -> 0 | DO18: =IF($CP18="CALIDUL",$BB18+$BK18+$BT18+$CC18+$CL18,0) -> 0 | DP18: =IF($CP18="CALIDUL",$BC18+$BL18+$BU18+$CD18+$CM18,0) -> 0 | DQ18: =SUM(DI18:DP18)-DK18-DM18 -> 0 | DR18: =IF($CP18="ECONACIONAL",$AV18+$BE18+$BN18+$BW18+$CF18,0) -> 0 | DS18: =IF($CP18="ECONACIONAL",$AW18+$BF18+$BO18+$BX18+$CG18,0) -> 0 | DT18: =IF($CP18="ECONACIONAL",$AX18+$BG18+$BP18+$BY18+$CH18,0) -> 0 | DU18: =IF($CP18="ECONACIONAL",$AY18+$BH18+$BQ18+$BZ18+$CI18,0) -> 0 | DV18: =IF($CP18="ECONACIONAL",$AZ18+$BI18+$BR18+$CA18+$CJ18,0) -> 0 | DW18: =IF($CP18="ECONACIONAL",$BA18+$BJ18+$BS18+$CB18+$CK18,0) -> 0 | DX18: =IF($CP18="ECONACIONAL",$BB18+$BK18+$BT18+$CC18+$CL18,0) -> 0 | DY18: =IF($CP18="ECONACIONAL",$BC18+$BL18+$BU18+$CD18+$CM18,0) -> 0 | DZ18: =SUM(DR18:DY18)-DT18-DV18 -> 0 | EA18: =IF($CP18="CLEARTEC",$AV18+$BE18+$BN18+$BW18+$CF18,0) -> 0 | EB18: =IF($CP18="CLEARTEC",$AW18+$BF18+$BO18+$BX18+$CG18,0) -> 0 | EC18: =IF($CP18="CLEARTEC",$AX18+$BG18+$BP18+$BY18+$CH18,0) -> 0 | ED18: =IF($CP18="CLEARTEC",$AY18+$BH18+$BQ18+$BZ18+$CI18,0) -> 0 | EE18: =IF($CP18="CLEARTEC",$AZ18+$BI18+$BR18+$CA18+$CJ18,0) -> 0 | EF18: =IF($CP18="CLEARTEC",$BA18+$BJ18+$BS18+$CB18+$CK18,0) -> 0 | EG18: =IF($CP18="CLEARTEC",$BB18+$BK18+$BT18+$CC18+$CL18,0) -> 0 | EH18: =IF($CP18="CLEARTEC",$BC18+$BL18+$BU18+$CD18+$CM18,0) -> 0 | EI18: =SUM(EA18:EH18)-EC18-EE18 -> 0 | ET18: =+EO18+EP18+EQ18 -> 0 | EV18: =IF($H18<=15,EK18/2,EK18) -> 0 | EW18: =IF($H18<=15,EL18/2,EL18) -> 0 | EX18: =IF($H18<=15,EM18/2,EM18) -> 0 | EY18: =IF($H18<=15,EN18/2,EN18) -> 0 | EZ18: =IF($H18<=15,EO18/2,EO18) -> 0 | FA18: =IF($H18<=15,EP18/2,EP18) -> 0 | FB18: =IF($H18<=15,EQ18/2,EQ18) -> 0 | FC18: =IF($H18<=15,ER18/2,ER18) -> 0 | ... FE18: =IF($H18<=15,ET18/2,ET18) -> 0
C19: Total Presidencia | E19: =SUM(E10:E18) -> 116915.52 | F19: =SUM(F10:F18) -> 163290.76 | G19: =SUM(G10:G18) -> 280206.28 | P19: =SUM(P10:P18) -> 0 | Q19: =SUM(Q10:Q18) -> 0 | R19: =SUM(R10:R18) -> 0 | S19: =SUM(S10:S18) -> 0 | T19: =SUM(T10:T18) -> 0 | U19: =SUM(U10:U18) -> 0 | V19: =SUM(V10:V18) -> 0 | W19: =SUM(W10:W18) -> 0 | ... AA19: =SUM(AA10:AA18) -> 0 | AB19: =SUM(AB10:AB17) -> 0 | AC19: =SUM(AC10:AC17) -> 0 | AD19: =SUM(AD10:AD17) -> 0 | AE19: =SUM(AE10:AE17) -> 0 | AF19: =SUM(AF10:AF17) -> 0 | AG19: =SUM(AG10:AG17) -> 0 | AH19: =SUM(AH10:AH17) -> 0 | AI19: =SUM(AI10:AI17) -> 0 | ... AT19: =SUM(AT10:AT17) -> 0 | AV19: =SUM(AV10:AV18) -> 80449.914 | AW19: =SUM(AW10:AW18) -> 172431.1 | AX19: =SUM(AX10:AX18) -> 0 | AY19: =SUM(AY10:AY18) -> 0 | AZ19: =SUM(AZ10:AZ18) -> 0 | BA19: =SUM(BA10:BA18) -> 0 | BB19: =SUM(BB10:BB18) -> 0 | BC19: =SUM(BC10:BC18) -> 10193.004 | ... BV19: =SUM(BV10:BV18) -> 0 | BW19: =SUM(BW10:BW17) -> 1500 | BX19: =SUM(BX10:BX17) -> 1200 | BY19: =SUM(BY10:BY17) -> 0 | BZ19: =SUM(BZ10:BZ17) -> 0 | CA19: =SUM(CA10:CA17) -> 0 | CB19: =SUM(CB10:CB17) -> 0 | CC19: =SUM(CC10:CC17) -> 0 | CD19: =SUM(CD10:CD18) -> 190.05 | CE19: =SUM(CE10:CE18) -> 2890.05 | CF19: =SUM(CF10:CF17) -> 0 | CG19: =SUM(CG10:CG17) -> 0 | CH19: =SUM(CH10:CH17) -> 0 | CI19: =SUM(CI10:CI17) -> 0 | CJ19: =SUM(CJ10:CJ17) -> 0 | CK19: =SUM(CK10:CK17) -> 0 | CL19: =SUM(CL10:CL17) -> 0 | CM19: =SUM(CM10:CM17) -> 0 | CN19: =SUM(CN10:CN17) -> 0 | CQ19: =SUM(CQ10:CQ18) -> 80449.914 | CR19: =SUM(CR10:CR18) -> 171781.1 | CS19: =SUM(CS10:CS18) -> 0 | CT19: =SUM(CT10:CT18) -> 0 | CU19: =SUM(CU10:CU18) -> 0 | CV19: =SUM(CV10:CV18) -> 0 | CW19: =SUM(CW10:CW18) -> 0 | CX19: =SUM(CX10:CX18) -> 9971.2791 | ... DQ19: =SUM(DQ10:DQ18) -> 0 | DR19: =SUM(DR10:DR17) -> 0 | DS19: =SUM(DS10:DS17) -> 0 | DT19: =SUM(DT10:DT17) -> 0 | DU19: =SUM(DU10:DU17) -> 0 | DV19: =SUM(DV10:DV17) -> 0 | DW19: =SUM(DW10:DW17) -> 0 | DX19: =SUM(DX10:DX17) -> 0 | DY19: =SUM(DY10:DY17) -> 0 | ... EI19: =SUM(EI10:EI17) -> 0 | EK19: =SUM(EK10:EK18) -> 19506.42 | EL19: =SUM(EL10:EL18) -> 0 | EM19: =SUM(EM10:EM18) -> 0 | EN19: =SUM(EN10:EN18) -> 97 | EO19: =SUM(EO10:EO18) -> 165 | EP19: =SUM(EP10:EP18) -> 275 | EQ19: =SUM(EQ10:EQ18) -> 240 | ER19: =SUM(ER10:ER18) -> 0 | ... ET19: =SUM(ET10:ET18) -> 680 | EV19: =SUM(EV10:EV18) -> 19506.42 | EW19: =SUM(EW10:EW18) -> 0 | EX19: =SUM(EX10:EX18) -> 0 | EY19: =SUM(EY10:EY18) -> 97 | EZ19: =SUM(EZ10:EZ18) -> 165 | FA19: =SUM(FA10:FA18) -> 275 | FB19: =SUM(FB10:FB18) -> 240 | FC19: =SUM(FC10:FC18) -> 0 | ... FE19: =SUM(FE10:FE18) -> 680 | FL19: =+EP19-FA19 -> 0
FL20: =+EP20-FA20 -> 0
B21: ADMINISTRATIVO | FL21: =+EP21-FA21 -> 0
A22: 10 | B22: Gaitan Hernandez Luis Daniel | C22: Piloto de Presidencia | D22: PROQUIMA | E22: 3262.5 | F22: 2250 | G22: =+E22+F22 -> 5512.5 | H22: 30 | I22: 1 | J22: 0 | K22: 0 | L22: 0 | M22: 0 | N22: =SUM(I22:M22) -> 1 | Q22: =($E22/30/8*1.5)*P22 -> 0 | S22: =($E22/30/8*2)*R22 -> 0 | U22: =($E22/30/8*1.5)*T22 -> 0 | W22: =($E22/30/8*2)*V22 -> 0 | Y22: =(($E22/30/8)*1.5)*X22 -> 0 | AA22: =(($E22/30/8)*2)*Z22 -> 0 | AC22: =(($E22/30/8)*1.5)*AB22 -> 0 | AE22: =(($E22/30/8)*2)*AD22 -> 0 | AG22: =(($E22/30/8)*1.5)*AF22 -> 0 | AI22: =(($E22/30/8)*2)*AH22 -> 0 | AV22: =((E22/30)*H22)*$I22 -> 3262.5 | AW22: =((F22/30)*H22)*$I22 -> 2250 | AX22: =P22 -> 0 | AY22: =Q22 -> 0 | AZ22: =R22 -> 0 | BA22: =S22 -> 0 | BB22: =AJ22+AO22 -> 0 | BC22: =(AV22+AY22+BA22)*0.1267 -> 413.35875 | BD22: =SUM(AV22:BC22)-AX22-AZ22 -> 5925.8588 | BE22: =(($E22/30)*$H22)*$J22 -> 0 | BF22: =(($F22/30)*$H22)*$J22 -> 0 | BG22: =T22 -> 0 | BH22: =U22 -> 0 | BI22: =V22 -> 0 | BJ22: =W22 -> 0 | BK22: =AK22+AP22 -> 0 | BL22: =(+BE22+BH22+BJ22+BK22)*0.1267 -> 0 | BM22: =SUM(BE22:BL22)-BG22-BI22 -> 0 | BN22: =(($E22/30)*$H22)*$K22 -> 0 | BO22: =(($F22/30)*$H22)*$K22 -> 0 | BP22: =X22 -> 0 | BQ22: =Y22 -> 0 | BR22: =Z22 -> 0 | BS22: =AA22 -> 0 | BT22: =AL22+AQ22 -> 0 | BU22: =(BN22+BQ22+BS22)*0.1267 -> 0 | BV22: =SUM(BN22:BU22)-BP22-BR22 -> 0 | BW22: =(($E22/30)*$H22)*$L22 -> 0 | BX22: =(($F22/30)*$H22)*$L22 -> 0 | BY22: =AB22 -> 0 | BZ22: =AC22 -> 0 | CA22: =AD22 -> 0 | CB22: =AE22 -> 0 | CC22: =AM22+AR22 -> 0 | CD22: =(BW22+BZ22+CB22)*0.1267 -> 0 | CE22: =SUM(BW22:CD22)-BY22-CA22 -> 0 | CF22: =(($E22/30)*$H22)*M22 -> 0 | CG22: =(($F22/30)*$H22)*$M22 -> 0 | CH22: =+AF22 -> 0 | CI22: =AG22 -> 0 | CJ22: =AH22 -> 0 | CK22: =AI22 -> 0 | CL22: =AN22+AS22 -> 0 | CM22: =(CF22+CI22+CK22)*0.1267 -> 0 | CN22: =SUM(CF22:CM22)-CH22-CJ22 -> 0 | CP22: PROQUIMA | CQ22: =IF($CP22="PROQUIMA",$AV22+$BE22+$BN22+$BW22+$CF22,0) -> 3262.5 | CR22: =IF($CP22="PROQUIMA",$AW22+$BF22+$BO22+$BX22+$CG22,0) -> 2250 | CS22: =IF($CP22="PROQUIMA",$AX22+$BG22+$BP22+$BY22+$CH22,0) -> 0 | CT22: =IF($CP22="PROQUIMA",$AY22+$BH22+$BQ22+$BZ22+$CI22,0) -> 0 | CU22: =IF($CP22="PROQUIMA",$AZ22+$BI22+$BR22+$CA22+$CJ22,0) -> 0 | CV22: =IF($CP22="PROQUIMA",$BA22+$BJ22+$BS22+$CB22+$CK22,0) -> 0 | CW22: =IF($CP22="PROQUIMA",$BB22+$BK22+$BT22+$CC22+$CL22,0) -> 0 | CX22: =IF($CP22="PROQUIMA",$BC22+$BL22+$BU22+$CD22+CM22,0) -> 413.35875 | CY22: =SUM(CQ22:CX22)-CS22-CU22 -> 5925.8588 | CZ22: =IF($CP22="UNHESA",$AV22+$BE22+$BN22+$BW22+$CF22,0) -> 0 | DA22: =IF($CP22="UNHESA",$AW22+$BF22+$BO22+$BX22+$CG22,0) -> 0 | DB22: =IF($CP22="UNHESA",$AX22+$BG22+$BP22+$BY22+$CH22,0) -> 0 | DC22: =IF($CP22="UNHESA",$AY22+$BH22+$BQ22+$BZ22+$CI22,0) -> 0 | DD22: =IF($CP22="UNHESA",$AZ22+$BI22+$BR22+$CA22+$CJ22,0) -> 0 | DE22: =IF($CP22="UNHESA",$BA22+$BJ22+$BS22+$CB22+$CK22,0) -> 0 | DF22: =IF($CP22="UNHESA",$BB22+$BK22+$BT22+$CC22+$CL22,0) -> 0 | DG22: =IF($CP22="UNHESA",$BC22+$BL22+$BU22+$CD22+$CM22,0) -> 0 | DH22: =SUM(CZ22:DG22)-DB22-DD22 -> 0 | DI22: =IF($CP22="UNHESA LIQUIDOS",$AV22+$BE22+$BN22+$BW22+$CF22,0) -> 0 | DJ22: =IF($CP22="CALIDUL",$AW22+$BF22+$BO22+$BX22+$CG22,0) -> 0 | DK22: =IF($CP22="CALIDUL",$AX22+$BG22+$BP22+$BY22+$CH22,0) -> 0 | DL22: =IF($CP22="CALIDUL",$AY22+$BH22+$BQ22+$BZ22+$CI22,0) -> 0 | DM22: =IF($CP22="CALIDUL",$AZ22+$BI22+$BR22+$CA22+$CJ22,0) -> 0 | DN22: =IF($CP22="CALIDUL",$BA22+$BJ22+$BS22+$CB22+$CK22,0) -> 0 | DO22: =IF($CP22="CALIDUL",$BB22+$BK22+$BT22+$CC22+$CL22,0) -> 0 | DP22: =IF($CP22="CALIDUL",$BC22+$BL22+$BU22+$CD22+$CM22,0) -> 0 | DQ22: =SUM(DI22:DP22)-DK22-DM22 -> 0 | DR22: =IF($CP22="ECONACIONAL",$AV22+$BE22+$BN22+$BW22+$CF22,0) -> 0 | DS22: =IF($CP22="ECONACIONAL",$AW22+$BF22+$BO22+$BX22+$CG22,0) -> 0 | DT22: =IF($CP22="ECONACIONAL",$AX22+$BG22+$BP22+$BY22+$CH22,0) -> 0 | DU22: =IF($CP22="ECONACIONAL",$AY22+$BH22+$BQ22+$BZ22+$CI22,0) -> 0 | DV22: =IF($CP22="ECONACIONAL",$AZ22+$BI22+$BR22+$CA22+$CJ22,0) -> 0 | DW22: =IF($CP22="ECONACIONAL",$BA22+$BJ22+$BS22+$CB22+$CK22,0) -> 0 | DX22: =IF($CP22="ECONACIONAL",$BB22+$BK22+$BT22+$CC22+$CL22,0) -> 0 | DY22: =IF($CP22="ECONACIONAL",$BC22+$BL22+$BU22+$CD22+$CM22,0) -> 0 | DZ22: =SUM(DR22:DY22)-DT22-DV22 -> 0 | EA22: =IF($CP22="CLEARTEC",$AV22+$BE22+$BN22+$BW22+$CF22,0) -> 0 | EB22: =IF($CP22="CLEARTEC",$AW22+$BF22+$BO22+$BX22+$CG22,0) -> 0 | EC22: =IF($CP22="CLEARTEC",$AX22+$BG22+$BP22+$BY22+$CH22,0) -> 0 | ED22: =IF($CP22="CLEARTEC",$AY22+$BH22+$BQ22+$BZ22+$CI22,0) -> 0 | EE22: =IF($CP22="CLEARTEC",$AZ22+$BI22+$BR22+$CA22+$CJ22,0) -> 0 | EF22: =IF($CP22="CLEARTEC",$BA22+$BJ22+$BS22+$CB22+$CK22,0) -> 0 | EG22: =IF($CP22="CLEARTEC",$BB22+$BK22+$BT22+$CC22+$CL22,0) -> 0 | EH22: =IF($CP22="CLEARTEC",$BC22+$BL22+$BU22+$CD22+$CM22,0) -> 0 | EI22: =SUM(EA22:EH22)-EC22-EE22 -> 0 | EK22: 67.75 | EP22: 50 | ET22: =+EO22+EP22+EQ22 -> 50 | EV22: =IF($H22<=15,EK22/2,EK22) -> 67.75 | EW22: =IF($H22<=15,EL22/2,EL22) -> 0 | EX22: =IF($H22<=15,EM22/2,EM22) -> 0 | EY22: =IF($H22<=15,EN22/2,EN22) -> 0 | EZ22: =IF($H22<=15,EO22/2,EO22) -> 0 | FA22: =IF($H22<=15,EP22/2,EP22) -> 50 | FB22: =IF($H22<=15,EQ22/2,EQ22) -> 0 | FC22: =IF($H22<=15,ER22/2,ER22) -> 0 | ... FE22: =IF($H22<=15,ET22/2,ET22) -> 50 | FF22: 1 | FG22: 0 | FH22: 0 | FI22: 0 | FJ22: 0 | FK22: 1 | FL22: =+EP22-FA22 -> 0
A23: =+A22+1 -> 11 | B23: Saenz Lemus Dulce Maria | C23: Recepcionista | D23: PROQUIMA | E23: 3166.38 | F23: 250 | G23: =+E23+F23 -> 3416.38 | H23: 30 | I23: 0.5 | J23: 0.5 | K23: 0 | L23: 0 | M23: 0 | N23: =SUM(I23:M23) -> 1 | Q23: =($E23/30/8*1.5)*P23 -> 0 | S23: =($E23/30/8*2)*R23 -> 0 | U23: =($E23/30/8*1.5)*T23 -> 0 | W23: =($E23/30/8*2)*V23 -> 0 | Y23: =(($E23/30/8)*1.5)*X23 -> 0 | AA23: =(($E23/30/8)*2)*Z23 -> 0 | AC23: =(($E23/30/8)*1.5)*AB23 -> 0 | AE23: =(($E23/30/8)*2)*AD23 -> 0 | AV23: =((E23/30)*H23)*$I23 -> 1583.19 | AW23: =((F23/30)*H23)*$I23 -> 125 | AX23: =P23 -> 0 | AY23: =Q23 -> 0 | AZ23: =R23 -> 0 | BA23: =S23 -> 0 | BB23: =AJ23+AO23 -> 0 | BC23: =(AV23+AY23+BA23)*0.1267 -> 200.59017 | BD23: =SUM(AV23:BC23)-AX23-AZ23 -> 1908.7802 | BE23: =(($E23/30)*$H23)*$J23 -> 1583.19 | BF23: =(($F23/30)*$H23)*$J23 -> 125 | BG23: =T23 -> 0 | BH23: =U23 -> 0 | BI23: =V23 -> 0 | BJ23: =W23 -> 0 | BK23: =AK23+AP23 -> 0 | BL23: =(+BE23+BH23+BJ23+BK23)*0.1267 -> 200.59017 | BM23: =SUM(BE23:BL23)-BG23-BI23 -> 1908.7802 | BN23: =(($E23/30)*$H23)*$K23 -> 0 | BO23: =(($F23/30)*$H23)*$K23 -> 0 | BP23: =X23 -> 0 | BQ23: =Y23 -> 0 | BR23: =Z23 -> 0 | BS23: =AA23 -> 0 | BT23: =AL23+AQ23 -> 0 | BU23: =(BN23+BQ23+BS23)*0.1267 -> 0 | BV23: =SUM(BN23:BU23)-BP23-BR23 -> 0 | BW23: =(($E23/30)*$H23)*$L23 -> 0 | BX23: =(($F23/30)*$H23)*$L23 -> 0 | BY23: =AB23 -> 0 | BZ23: =AC23 -> 0 | CA23: =AD23 -> 0 | CB23: =AE23 -> 0 | CC23: =AM23+AR23 -> 0 | CD23: =(BW23+BZ23+CB23)*0.1267 -> 0 | CE23: =SUM(BW23:CD23)-BY23-CA23 -> 0 | CP23: PROQUIMA | CQ23: =IF($CP23="PROQUIMA",$AV23+$BE23+$BN23+$BW23+$CF23,0) -> 3166.38 | CR23: =IF($CP23="PROQUIMA",$AW23+$BF23+$BO23+$BX23+$CG23,0) -> 250 | CS23: =IF($CP23="PROQUIMA",$AX23+$BG23+$BP23+$BY23+$CH23,0) -> 0 | CT23: =IF($CP23="PROQUIMA",$AY23+$BH23+$BQ23+$BZ23+$CI23,0) -> 0 | CU23: =IF($CP23="PROQUIMA",$AZ23+$BI23+$BR23+$CA23+$CJ23,0) -> 0 | CV23: =IF($CP23="PROQUIMA",$BA23+$BJ23+$BS23+$CB23+$CK23,0) -> 0 | CW23: =IF($CP23="PROQUIMA",$BB23+$BK23+$BT23+$CC23+$CL23,0) -> 0 | CX23: =IF($CP23="PROQUIMA",$BC23+$BL23+$BU23+$CD23+CM23,0) -> 401.18035 | CY23: =SUM(CQ23:CX23)-CS23-CU23 -> 3817.5603 | CZ23: =IF($CP23="UNHESA",$AV23+$BE23+$BN23+$BW23+$CF23,0) -> 0 | DA23: =IF($CP23="UNHESA",$AW23+$BF23+$BO23+$BX23+$CG23,0) -> 0 | DB23: =IF($CP23="UNHESA",$AX23+$BG23+$BP23+$BY23+$CH23,0) -> 0 | DC23: =IF($CP23="UNHESA",$AY23+$BH23+$BQ23+$BZ23+$CI23,0) -> 0 | DD23: =IF($CP23="UNHESA",$AZ23+$BI23+$BR23+$CA23+$CJ23,0) -> 0 | DE23: =IF($CP23="UNHESA",$BA23+$BJ23+$BS23+$CB23+$CK23,0) -> 0 | DF23: =IF($CP23="UNHESA",$BB23+$BK23+$BT23+$CC23+$CL23,0) -> 0 | DG23: =IF($CP23="UNHESA",$BC23+$BL23+$BU23+$CD23+$CM23,0) -> 0 | DH23: =SUM(CZ23:DG23)-DB23-DD23 -> 0 | DI23: =IF($CP23="UNHESA LIQUIDOS",$AV23+$BE23+$BN23+$BW23+$CF23,0) -> 0 | DJ23: =IF($CP23="CALIDUL",$AW23+$BF23+$BO23+$BX23+$CG23,0) -> 0 | DK23: =IF($CP23="CALIDUL",$AX23+$BG23+$BP23+$BY23+$CH23,0) -> 0 | DL23: =IF($CP23="CALIDUL",$AY23+$BH23+$BQ23+$BZ23+$CI23,0) -> 0 | DM23: =IF($CP23="CALIDUL",$AZ23+$BI23+$BR23+$CA23+$CJ23,0) -> 0 | DN23: =IF($CP23="CALIDUL",$BA23+$BJ23+$BS23+$CB23+$CK23,0) -> 0 | DO23: =IF($CP23="CALIDUL",$BB23+$BK23+$BT23+$CC23+$CL23,0) -> 0 | DP23: =IF($CP23="CALIDUL",$BC23+$BL23+$BU23+$CD23+$CM23,0) -> 0 | DQ23: =SUM(DI23:DP23)-DK23-DM23 -> 0 | EP23: 50 | ET23: =+EO23+EP23+EQ23 -> 50 | EV23: =IF($H23<=15,EK23/2,EK23) -> 0 | EW23: =IF($H23<=15,EL23/2,EL23) -> 0 | EX23: =IF($H23<=15,EM23/2,EM23) -> 0 | EY23: =IF($H23<=15,EN23/2,EN23) -> 0 | EZ23: =IF($H23<=15,EO23/2,EO23) -> 0 | FA23: =IF($H23<=15,EP23/2,EP23) -> 50 | FB23: =IF($H23<=15,EQ23/2,EQ23) -> 0 | FC23: =IF($H23<=15,ER23/2,ER23) -> 0 | ... FE23: =IF($H23<=15,ET23/2,ET23) -> 50
A24: =+A23+1 -> 12 | B24: Pu Canto Domingo | C24: Conserje | D24: PROQUIMA | E24: 3166.38 | F24: 250 | G24: =+E24+F24 -> 3416.38 | H24: 30 | I24: 0.5 | J24: 0.5 | K24: 0 | L24: 0 | M24: 0 | N24: =SUM(I24:M24) -> 1 | Q24: =($E24/30/8*1.5)*P24 -> 0 | S24: =($E24/30/8*2)*R24 -> 0 | U24: =($E24/30/8*1.5)*T24 -> 0 | W24: =($E24/30/8*2)*V24 -> 0 | Y24: =(($E24/30/8)*1.5)*X24 -> 0 | AA24: =(($E24/30/8)*2)*Z24 -> 0 | AC24: =(($E24/30/8)*1.5)*AB24 -> 0 | AE24: =(($E24/30/8)*2)*AD24 -> 0 | AG24: =(($E24/30/8)*1.5)*AF24 -> 0 | AI24: =(($E24/30/8)*2)*AH24 -> 0 | AV24: =((E24/30)*H24)*$I24 -> 1583.19 | AW24: =((F24/30)*H24)*$I24 -> 125 | AX24: =P24 -> 0 | AY24: =Q24 -> 0 | AZ24: =R24 -> 0 | BA24: =S24 -> 0 | BB24: =AJ24+AO24 -> 0 | BC24: =(AV24+AY24+BA24)*0.1267 -> 200.59017 | BD24: =SUM(AV24:BC24)-AX24-AZ24 -> 1908.7802 | BE24: =(($E24/30)*$H24)*$J24 -> 1583.19 | BF24: =(($F24/30)*$H24)*$J24 -> 125 | BG24: =T24 -> 0 | BH24: =U24 -> 0 | BI24: =V24 -> 0 | BJ24: =W24 -> 0 | BK24: =AK24+AP24 -> 0 | BL24: =(+BE24+BH24+BJ24+BK24)*0.1267 -> 200.59017 | BM24: =SUM(BE24:BL24)-BG24-BI24 -> 1908.7802 | BN24: =(($E24/30)*$H24)*$K24 -> 0 | BO24: =(($F24/30)*$H24)*$K24 -> 0 | BP24: =X24 -> 0 | BQ24: =Y24 -> 0 | BR24: =Z24 -> 0 | BS24: =AA24 -> 0 | BT24: =AL24+AQ24 -> 0 | BU24: =(BN24+BQ24+BS24)*0.09 -> 0 | BV24: =SUM(BN24:BU24)-BP24-BR24 -> 0 | BW24: =(($E24/30)*$H24)*$L24 -> 0 | BX24: =(($F24/30)*$H24)*$L24 -> 0 | BY24: =AB24 -> 0 | BZ24: =AC24 -> 0 | CA24: =AD24 -> 0 | CB24: =AE24 -> 0 | CC24: =AM24+AR24 -> 0 | CD24: =(BW24+BZ24+CB24)*0.09 -> 0 | CE24: =SUM(BW24:CD24)-BY24-CA24 -> 0 | CF24: =(($E24/30)*$H24)*M24 -> 0 | CG24: =(($F24/30)*$H24)*$M24 -> 0 | CH24: =+AF24 -> 0 | CI24: =AG24 -> 0 | CJ24: =AH24 -> 0 | CK24: =AI24 -> 0 | CL24: =AN24+AS24 -> 0 | CM24: =(CF24+CI24+CK24)*0.09 -> 0 | CN24: =SUM(CF24:CM24)-CH24-CJ24 -> 0 | CP24: PROQUIMA | CQ24: =IF($CP24="PROQUIMA",$AV24+$BE24+$BN24+$BW24+$CF24,0) -> 3166.38 | CR24: =IF($CP24="PROQUIMA",$AW24+$BF24+$BO24+$BX24+$CG24,0) -> 250 | CS24: =IF($CP24="PROQUIMA",$AX24+$BG24+$BP24+$BY24+$CH24,0) -> 0 | CT24: =IF($CP24="PROQUIMA",$AY24+$BH24+$BQ24+$BZ24+$CI24,0) -> 0 | CU24: =IF($CP24="PROQUIMA",$AZ24+$BI24+$BR24+$CA24+$CJ24,0) -> 0 | CV24: =IF($CP24="PROQUIMA",$BA24+$BJ24+$BS24+$CB24+$CK24,0) -> 0 | CW24: =IF($CP24="PROQUIMA",$BB24+$BK24+$BT24+$CC24+$CL24,0) -> 0 | CX24: =IF($CP24="PROQUIMA",$BC24+$BL24+$BU24+$CD24+CM24,0) -> 401.18035 | CY24: =SUM(CQ24:CX24)-CS24-CU24 -> 3817.5603 | CZ24: =IF($CP24="UNHESA",$AV24+$BE24+$BN24+$BW24+$CF24,0) -> 0 | DA24: =IF($CP24="UNHESA",$AW24+$BF24+$BO24+$BX24+$CG24,0) -> 0 | DB24: =IF($CP24="UNHESA",$AX24+$BG24+$BP24+$BY24+$CH24,0) -> 0 | DC24: =IF($CP24="UNHESA",$AY24+$BH24+$BQ24+$BZ24+$CI24,0) -> 0 | DD24: =IF($CP24="UNHESA",$AZ24+$BI24+$BR24+$CA24+$CJ24,0) -> 0 | DE24: =IF($CP24="UNHESA",$BA24+$BJ24+$BS24+$CB24+$CK24,0) -> 0 | DF24: =IF($CP24="UNHESA",$BB24+$BK24+$BT24+$CC24+$CL24,0) -> 0 | DG24: =IF($CP24="UNHESA",$BC24+$BL24+$BU24+$CD24+$CM24,0) -> 0 | DH24: =SUM(CZ24:DG24)-DB24-DD24 -> 0 | DI24: =IF($CP24="UNHESA LIQUIDOS",$AV24+$BE24+$BN24+$BW24+$CF24,0) -> 0 | DJ24: =IF($CP24="CALIDUL",$AW24+$BF24+$BO24+$BX24+$CG24,0) -> 0 | DK24: =IF($CP24="CALIDUL",$AX24+$BG24+$BP24+$BY24+$CH24,0) -> 0 | DL24: =IF($CP24="CALIDUL",$AY24+$BH24+$BQ24+$BZ24+$CI24,0) -> 0 | DM24: =IF($CP24="CALIDUL",$AZ24+$BI24+$BR24+$CA24+$CJ24,0) -> 0 | DN24: =IF($CP24="CALIDUL",$BA24+$BJ24+$BS24+$CB24+$CK24,0) -> 0 | DO24: =IF($CP24="CALIDUL",$BB24+$BK24+$BT24+$CC24+$CL24,0) -> 0 | DP24: =IF($CP24="CALIDUL",$BC24+$BL24+$BU24+$CD24+$CM24,0) -> 0 | DQ24: =SUM(DI24:DP24)-DK24-DM24 -> 0 | DR24: =IF($CP24="ECONACIONAL",$AV24+$BE24+$BN24+$BW24+$CF24,0) -> 0 | DS24: =IF($CP24="ECONACIONAL",$AW24+$BF24+$BO24+$BX24+$CG24,0) -> 0 | DT24: =IF($CP24="ECONACIONAL",$AX24+$BG24+$BP24+$BY24+$CH24,0) -> 0 | DU24: =IF($CP24="ECONACIONAL",$AY24+$BH24+$BQ24+$BZ24+$CI24,0) -> 0 | DV24: =IF($CP24="ECONACIONAL",$AZ24+$BI24+$BR24+$CA24+$CJ24,0) -> 0 | DW24: =IF($CP24="ECONACIONAL",$BA24+$BJ24+$BS24+$CB24+$CK24,0) -> 0 | DX24: =IF($CP24="ECONACIONAL",$BB24+$BK24+$BT24+$CC24+$CL24,0) -> 0 | DY24: =IF($CP24="ECONACIONAL",$BC24+$BL24+$BU24+$CD24+$CM24,0) -> 0 | DZ24: =SUM(DR24:DY24)-DT24-DV24 -> 0 | EA24: =IF($CP24="CLEARTEC",$AV24+$BE24+$BN24+$BW24+$CF24,0) -> 0 | EB24: =IF($CP24="CLEARTEC",$AW24+$BF24+$BO24+$BX24+$CG24,0) -> 0 | EC24: =IF($CP24="CLEARTEC",$AX24+$BG24+$BP24+$BY24+$CH24,0) -> 0 | ED24: =IF($CP24="CLEARTEC",$AY24+$BH24+$BQ24+$BZ24+$CI24,0) -> 0 | EE24: =IF($CP24="CLEARTEC",$AZ24+$BI24+$BR24+$CA24+$CJ24,0) -> 0 | EF24: =IF($CP24="CLEARTEC",$BA24+$BJ24+$BS24+$CB24+$CK24,0) -> 0 | EG24: =IF($CP24="CLEARTEC",$BB24+$BK24+$BT24+$CC24+$CL24,0) -> 0 | EH24: =IF($CP24="CLEARTEC",$BC24+$BL24+$BU24+$CD24+$CM24,0) -> 0 | EI24: =SUM(EA24:EH24)-EC24-EE24 -> 0 | EO24: 82.5 | EP24: 50 | EQ24: 306.62 | ET24: =+EO24+EP24+EQ24 -> 439.12 | EV24: =IF($H24<=15,EK24/2,EK24) -> 0 | EW24: =IF($H24<=15,EL24/2,EL24) -> 0 | EX24: =IF($H24<=15,EM24/2,EM24) -> 0 | EY24: =IF($H24<=15,EN24/2,EN24) -> 0 | EZ24: =IF($H24<=15,EO24/2,EO24) -> 82.5 | FA24: =IF($H24<=15,EP24/2,EP24) -> 50 | FB24: =IF($H24<=15,EQ24/2,EQ24) -> 306.62 | FC24: =IF($H24<=15,ER24/2,ER24) -> 0 | ... FE24: =IF($H24<=15,ET24/2,ET24) -> 439.12 | FF24: 0.5 | FG24: 0.5 | FH24: 0 | FI24: 0 | FJ24: 0 | FK24: 1 | FL24: =+EP24-FA24 -> 0
A25: =+#REF!+1 -> #REF! | B25: Chamay Gomez Susana Noemi | C25: conserje | D25: UNHESA | E25: 3166.38 | F25: 250 | G25: =+E25+F25 -> 3416.38 | H25: 30 | I25: 0.5 | J25: 0.5 | K25: 0 | L25: 0 | M25: 0 | N25: =SUM(I25:M25) -> 1 | Q25: =($E25/30/8*1.5)*P25 -> 0 | S25: =($E25/30/8*2)*R25 -> 0 | U25: =($E25/30/8*1.5)*T25 -> 0 | W25: =($E25/30/8*2)*V25 -> 0 | Y25: =(($E25/30/8)*1.5)*X25 -> 0 | AA25: =(($E25/30/8)*2)*Z25 -> 0 | AC25: =(($E25/30/8)*1.5)*AB25 -> 0 | AE25: =(($E25/30/8)*2)*AD25 -> 0 | AG25: =(($E25/30/8)*1.5)*AF25 -> 0 | AI25: =(($E25/30/8)*2)*AH25 -> 0 | AV25: =((E25/30)*H25)*$I25 -> 1583.19 | AW25: =((F25/30)*H25)*$I25 -> 125 | AX25: =P25 -> 0 | AY25: =Q25 -> 0 | AZ25: =R25 -> 0 | BA25: =S25 -> 0 | BB25: =AJ25+AO25 -> 0 | BC25: =(AV25+AY25+BA25)*0.1267 -> 200.59017 | BD25: =SUM(AV25:BC25)-AX25-AZ25 -> 1908.7802 | BE25: =(($E25/30)*$H25)*$J25 -> 1583.19 | BF25: =(($F25/30)*$H25)*$J25 -> 125 | BG25: =T25 -> 0 | BH25: =U25 -> 0 | BI25: =V25 -> 0 | BJ25: =W25 -> 0 | BK25: =AK25+AP25 -> 0 | BL25: =(+BE25+BH25+BJ25+BK25)*0.1267 -> 200.59017 | BM25: =SUM(BE25:BL25)-BG25-BI25 -> 1908.7802 | BN25: =(($E25/30)*$H25)*$K25 -> 0 | BO25: =(($F25/30)*$H25)*$K25 -> 0 | BP25: =X25 -> 0 | BQ25: =Y25 -> 0 | BR25: =Z25 -> 0 | BS25: =AA25 -> 0 | BT25: =AL25+AQ25 -> 0 | BU25: =(BN25+BQ25+BS25)*0.09 -> 0 | BV25: =SUM(BN25:BU25)-BP25-BR25 -> 0 | BW25: =(($E25/30)*$H25)*$L25 -> 0 | BX25: =(($F25/30)*$H25)*$L25 -> 0 | BY25: =AB25 -> 0 | BZ25: =AC25 -> 0 | CA25: =AD25 -> 0 | CB25: =AE25 -> 0 | CC25: =AM25+AR25 -> 0 | CD25: =(BW25+BZ25+CB25)*0.09 -> 0 | CE25: =SUM(BW25:CD25)-BY25-CA25 -> 0 | CF25: =(($E25/30)*$H25)*M25 -> 0 | CG25: =(($F25/30)*$H25)*$M25 -> 0 | CH25: =+AF25 -> 0 | CI25: =AG25 -> 0 | CJ25: =AH25 -> 0 | CK25: =AI25 -> 0 | CL25: =AN25+AS25 -> 0 | CM25: =(CF25+CI25+CK25)*0.09 -> 0 | CN25: =SUM(CF25:CM25)-CH25-CJ25 -> 0 | CP25: UNHESA | CQ25: =IF($CP25="PROQUIMA",$AV25+$BE25+$BN25+$BW25+$CF25,0) -> 0 | CR25: =IF($CP25="PROQUIMA",$AW25+$BF25+$BO25+$BX25+$CG25,0) -> 0 | CS25: =IF($CP25="PROQUIMA",$AX25+$BG25+$BP25+$BY25+$CH25,0) -> 0 | CT25: =IF($CP25="PROQUIMA",$AY25+$BH25+$BQ25+$BZ25+$CI25,0) -> 0 | CU25: =IF($CP25="PROQUIMA",$AZ25+$BI25+$BR25+$CA25+$CJ25,0) -> 0 | CV25: =IF($CP25="PROQUIMA",$BA25+$BJ25+$BS25+$CB25+$CK25,0) -> 0 | CW25: =IF($CP25="PROQUIMA",$BB25+$BK25+$BT25+$CC25+$CL25,0) -> 0 | CX25: =IF($CP25="PROQUIMA",$BC25+$BL25+$BU25+$CD25+CM25,0) -> 0 | CY25: =SUM(CQ25:CX25)-CS25-CU25 -> 0 | CZ25: =IF($CP25="UNHESA",$AV25+$BE25+$BN25+$BW25+$CF25,0) -> 3166.38 | DA25: =IF($CP25="UNHESA",$AW25+$BF25+$BO25+$BX25+$CG25,0) -> 250 | DB25: =IF($CP25="UNHESA",$AX25+$BG25+$BP25+$BY25+$CH25,0) -> 0 | DC25: =IF($CP25="UNHESA",$AY25+$BH25+$BQ25+$BZ25+$CI25,0) -> 0 | DD25: =IF($CP25="UNHESA",$AZ25+$BI25+$BR25+$CA25+$CJ25,0) -> 0 | DE25: =IF($CP25="UNHESA",$BA25+$BJ25+$BS25+$CB25+$CK25,0) -> 0 | DF25: =IF($CP25="UNHESA",$BB25+$BK25+$BT25+$CC25+$CL25,0) -> 0 | DG25: =IF($CP25="UNHESA",$BC25+$BL25+$BU25+$CD25+$CM25,0) -> 401.18035 | DH25: =SUM(CZ25:DG25)-DB25-DD25 -> 3817.5603 | DI25: =IF($CP25="UNHESA LIQUIDOS",$AV25+$BE25+$BN25+$BW25+$CF25,0) -> 0 | DJ25: =IF($CP25="CALIDUL",$AW25+$BF25+$BO25+$BX25+$CG25,0) -> 0 | DK25: =IF($CP25="CALIDUL",$AX25+$BG25+$BP25+$BY25+$CH25,0) -> 0 | DL25: =IF($CP25="CALIDUL",$AY25+$BH25+$BQ25+$BZ25+$CI25,0) -> 0 | DM25: =IF($CP25="CALIDUL",$AZ25+$BI25+$BR25+$CA25+$CJ25,0) -> 0 | DN25: =IF($CP25="CALIDUL",$BA25+$BJ25+$BS25+$CB25+$CK25,0) -> 0 | DO25: =IF($CP25="CALIDUL",$BB25+$BK25+$BT25+$CC25+$CL25,0) -> 0 | DP25: =IF($CP25="CALIDUL",$BC25+$BL25+$BU25+$CD25+$CM25,0) -> 0 | DQ25: =SUM(DI25:DP25)-DK25-DM25 -> 0 | DR25: =IF($CP25="ECONACIONAL",$AV25+$BE25+$BN25+$BW25+$CF25,0) -> 0 | DS25: =IF($CP25="ECONACIONAL",$AW25+$BF25+$BO25+$BX25+$CG25,0) -> 0 | DT25: =IF($CP25="ECONACIONAL",$AX25+$BG25+$BP25+$BY25+$CH25,0) -> 0 | DU25: =IF($CP25="ECONACIONAL",$AY25+$BH25+$BQ25+$BZ25+$CI25,0) -> 0 | DV25: =IF($CP25="ECONACIONAL",$AZ25+$BI25+$BR25+$CA25+$CJ25,0) -> 0 | DW25: =IF($CP25="ECONACIONAL",$BA25+$BJ25+$BS25+$CB25+$CK25,0) -> 0 | DX25: =IF($CP25="ECONACIONAL",$BB25+$BK25+$BT25+$CC25+$CL25,0) -> 0 | DY25: =IF($CP25="ECONACIONAL",$BC25+$BL25+$BU25+$CD25+$CM25,0) -> 0 | DZ25: =SUM(DR25:DY25)-DT25-DV25 -> 0 | EA25: =IF($CP25="CLEARTEC",$AV25+$BE25+$BN25+$BW25+$CF25,0) -> 0 | EB25: =IF($CP25="CLEARTEC",$AW25+$BF25+$BO25+$BX25+$CG25,0) -> 0 | EC25: =IF($CP25="CLEARTEC",$AX25+$BG25+$BP25+$BY25+$CH25,0) -> 0 | ED25: =IF($CP25="CLEARTEC",$AY25+$BH25+$BQ25+$BZ25+$CI25,0) -> 0 | EE25: =IF($CP25="CLEARTEC",$AZ25+$BI25+$BR25+$CA25+$CJ25,0) -> 0 | EF25: =IF($CP25="CLEARTEC",$BA25+$BJ25+$BS25+$CB25+$CK25,0) -> 0 | EG25: =IF($CP25="CLEARTEC",$BB25+$BK25+$BT25+$CC25+$CL25,0) -> 0 | EH25: =IF($CP25="CLEARTEC",$BC25+$BL25+$BU25+$CD25+$CM25,0) -> 0 | EI25: =SUM(EA25:EH25)-EC25-EE25 -> 0 | EO25: 120 | EP25: 50 | ET25: =+EO25+EP25+EQ25 -> 170 | EV25: =IF($H25<=15,EK25/2,EK25) -> 0 | EW25: =IF($H25<=15,EL25/2,EL25) -> 0 | EX25: =IF($H25<=15,EM25/2,EM25) -> 0 | EY25: =IF($H25<=15,EN25/2,EN25) -> 0 | EZ25: =IF($H25<=15,EO25/2,EO25) -> 120 | FA25: =IF($H25<=15,EP25/2,EP25) -> 50 | FB25: =IF($H25<=15,EQ25/2,EQ25) -> 0 | FC25: =IF($H25<=15,ER25/2,ER25) -> 0 | ... FE25: =IF($H25<=15,ET25/2,ET25) -> 170 | FF25: 0 | FG25: 1 | FH25: 0 | FI25: 0 | FJ25: 0 | FK25: 1 | FL25: =+EP25-FA25 -> 0
A26: =+A25+1 -> #REF! | B26: Cruz Juarez Santos Ernesto | C26: Mensajero | D26: PROQUIMA | E26: 3166.38 | F26: =250+120 -> 370 | G26: =+E26+F26 -> 3536.38 | H26: 30 | I26: 1 | J26: 0 | K26: 0 | L26: 0 | M26: 0 | N26: =SUM(I26:M26) -> 1 | Q26: =($E26/30/8*1.5)*P26 -> 0 | S26: =($E26/30/8*2)*R26 -> 0 | U26: =($E26/30/8*1.5)*T26 -> 0 | W26: =($E26/30/8*2)*V26 -> 0 | Y26: =(($E26/30/8)*1.5)*X26 -> 0 | AA26: =(($E26/30/8)*2)*Z26 -> 0 | AC26: =(($E26/30/8)*1.5)*AB26 -> 0 | AE26: =(($E26/30/8)*2)*AD26 -> 0 | AG26: =(($E26/30/8)*1.5)*AF26 -> 0 | AI26: =(($E26/30/8)*2)*AH26 -> 0 | AJ26: 0 | AV26: =((E26/30)*H26)*$I26 -> 3166.38 | AW26: =((F26/30)*H26)*$I26 -> 370 | AX26: =P26 -> 0 | AY26: =Q26 -> 0 | AZ26: =R26 -> 0 | BA26: =S26 -> 0 | BB26: =AJ26+AO26 -> 0 | BC26: =(AV26+AY26+BA26)*0.1267 -> 401.18035 | BD26: =SUM(AV26:BC26)-AX26-AZ26 -> 3937.5603 | BE26: =(($E26/30)*$H26)*$J26 -> 0 | BF26: =(($F26/30)*$H26)*$J26 -> 0 | BG26: =T26 -> 0 | BH26: =U26 -> 0 | BI26: =V26 -> 0 | BJ26: =W26 -> 0 | BK26: =AK26+AP26 -> 0 | BL26: =(+BE26+BH26+BJ26+BK26)*0.1267 -> 0 | BM26: =SUM(BE26:BL26)-BG26-BI26 -> 0 | BN26: =(($E26/30)*$H26)*$K26 -> 0 | BO26: =(($F26/30)*$H26)*$K26 -> 0 | BP26: =X26 -> 0 | BQ26: =Y26 -> 0 | BR26: =Z26 -> 0 | BS26: =AA26 -> 0 | BT26: =AL26+AQ26 -> 0 | BU26: =(BN26+BQ26+BS26)*0.09 -> 0 | BV26: =SUM(BN26:BU26)-BP26-BR26 -> 0 | BW26: =(($E26/30)*$H26)*$L26 -> 0 | BX26: =(($F26/30)*$H26)*$L26 -> 0 | BY26: =AB26 -> 0 | BZ26: =AC26 -> 0 | CA26: =AD26 -> 0 | CB26: =AE26 -> 0 | CC26: =AM26+AR26 -> 0 | CD26: =(BW26+BZ26+CB26)*0.09 -> 0 | CE26: =SUM(BW26:CD26)-BY26-CA26 -> 0 | CF26: =(($E26/30)*$H26)*M26 -> 0 | CG26: =(($F26/30)*$H26)*$M26 -> 0 | CH26: =+AF26 -> 0 | CI26: =AG26 -> 0 | CJ26: =AH26 -> 0 | CK26: =AI26 -> 0 | CL26: =AN26+AS26 -> 0 | CM26: =(CF26+CI26+CK26)*0.09 -> 0 | CN26: =SUM(CF26:CM26)-CH26-CJ26 -> 0 | CP26: PROQUIMA | CQ26: =IF($CP26="PROQUIMA",$AV26+$BE26+$BN26+$BW26+$CF26,0) -> 3166.38 | CR26: =IF($CP26="PROQUIMA",$AW26+$BF26+$BO26+$BX26+$CG26,0) -> 370 | CS26: =IF($CP26="PROQUIMA",$AX26+$BG26+$BP26+$BY26+$CH26,0) -> 0 | CT26: =IF($CP26="PROQUIMA",$AY26+$BH26+$BQ26+$BZ26+$CI26,0) -> 0 | CU26: =IF($CP26="PROQUIMA",$AZ26+$BI26+$BR26+$CA26+$CJ26,0) -> 0 | CV26: =IF($CP26="PROQUIMA",$BA26+$BJ26+$BS26+$CB26+$CK26,0) -> 0 | CW26: =IF($CP26="PROQUIMA",$BB26+$BK26+$BT26+$CC26+$CL26,0) -> 0 | CX26: =IF($CP26="PROQUIMA",$BC26+$BL26+$BU26+$CD26+CM26,0) -> 401.18035 | CY26: =SUM(CQ26:CX26)-CS26-CU26 -> 3937.5603 | CZ26: =IF($CP26="UNHESA",$AV26+$BE26+$BN26+$BW26+$CF26,0) -> 0 | DA26: =IF($CP26="UNHESA",$AW26+$BF26+$BO26+$BX26+$CG26,0) -> 0 | DB26: =IF($CP26="UNHESA",$AX26+$BG26+$BP26+$BY26+$CH26,0) -> 0 | DC26: =IF($CP26="UNHESA",$AY26+$BH26+$BQ26+$BZ26+$CI26,0) -> 0 | DD26: =IF($CP26="UNHESA",$AZ26+$BI26+$BR26+$CA26+$CJ26,0) -> 0 | DE26: =IF($CP26="UNHESA",$BA26+$BJ26+$BS26+$CB26+$CK26,0) -> 0 | DF26: =IF($CP26="UNHESA",$BB26+$BK26+$BT26+$CC26+$CL26,0) -> 0 | DG26: =IF($CP26="UNHESA",$BC26+$BL26+$BU26+$CD26+$CM26,0) -> 0 | DH26: =SUM(CZ26:DG26)-DB26-DD26 -> 0 | DI26: =IF($CP26="UNHESA LIQUIDOS",$AV26+$BE26+$BN26+$BW26+$CF26,0) -> 0 | DJ26: =IF($CP26="CALIDUL",$AW26+$BF26+$BO26+$BX26+$CG26,0) -> 0 | DK26: =IF($CP26="CALIDUL",$AX26+$BG26+$BP26+$BY26+$CH26,0) -> 0 | DL26: =IF($CP26="CALIDUL",$AY26+$BH26+$BQ26+$BZ26+$CI26,0) -> 0 | DM26: =IF($CP26="CALIDUL",$AZ26+$BI26+$BR26+$CA26+$CJ26,0) -> 0 | DN26: =IF($CP26="CALIDUL",$BA26+$BJ26+$BS26+$CB26+$CK26,0) -> 0 | DO26: =IF($CP26="CALIDUL",$BB26+$BK26+$BT26+$CC26+$CL26,0) -> 0 | DP26: =IF($CP26="CALIDUL",$BC26+$BL26+$BU26+$CD26+$CM26,0) -> 0 | DQ26: =SUM(DI26:DP26)-DK26-DM26 -> 0 | DR26: =IF($CP26="ECONACIONAL",$AV26+$BE26+$BN26+$BW26+$CF26,0) -> 0 | DS26: =IF($CP26="ECONACIONAL",$AW26+$BF26+$BO26+$BX26+$CG26,0) -> 0 | DT26: =IF($CP26="ECONACIONAL",$AX26+$BG26+$BP26+$BY26+$CH26,0) -> 0 | DU26: =IF($CP26="ECONACIONAL",$AY26+$BH26+$BQ26+$BZ26+$CI26,0) -> 0 | DV26: =IF($CP26="ECONACIONAL",$AZ26+$BI26+$BR26+$CA26+$CJ26,0) -> 0 | DW26: =IF($CP26="ECONACIONAL",$BA26+$BJ26+$BS26+$CB26+$CK26,0) -> 0 | DX26: =IF($CP26="ECONACIONAL",$BB26+$BK26+$BT26+$CC26+$CL26,0) -> 0 | DY26: =IF($CP26="ECONACIONAL",$BC26+$BL26+$BU26+$CD26+$CM26,0) -> 0 | DZ26: =SUM(DR26:DY26)-DT26-DV26 -> 0 | EA26: =IF($CP26="CLEARTEC",$AV26+$BE26+$BN26+$BW26+$CF26,0) -> 0 | EB26: =IF($CP26="CLEARTEC",$AW26+$BF26+$BO26+$BX26+$CG26,0) -> 0 | EC26: =IF($CP26="CLEARTEC",$AX26+$BG26+$BP26+$BY26+$CH26,0) -> 0 | ED26: =IF($CP26="CLEARTEC",$AY26+$BH26+$BQ26+$BZ26+$CI26,0) -> 0 | EE26: =IF($CP26="CLEARTEC",$AZ26+$BI26+$BR26+$CA26+$CJ26,0) -> 0 | EF26: =IF($CP26="CLEARTEC",$BA26+$BJ26+$BS26+$CB26+$CK26,0) -> 0 | EG26: =IF($CP26="CLEARTEC",$BB26+$BK26+$BT26+$CC26+$CL26,0) -> 0 | EH26: =IF($CP26="CLEARTEC",$BC26+$BL26+$BU26+$CD26+$CM26,0) -> 0 | EI26: =SUM(EA26:EH26)-EC26-EE26 -> 0 | ET26: =+EO26+EP26+EQ26 -> 0 | EV26: =IF($H26<=15,EK26/2,EK26) -> 0 | EW26: =IF($H26<=15,EL26/2,EL26) -> 0 | EX26: =IF($H26<=15,EM26/2,EM26) -> 0 | EY26: =IF($H26<=15,EN26/2,EN26) -> 0 | EZ26: =IF($H26<=15,EO26/2,EO26) -> 0 | FA26: =IF($H26<=15,EP26/2,EP26) -> 0 | FB26: =IF($H26<=15,EQ26/2,EQ26) -> 0 | FC26: =IF($H26<=15,ER26/2,ER26) -> 0 | ... FE26: =IF($H26<=15,ET26/2,ET26) -> 0 | FF26: 1 | FK26: 1 | FL26: =+EP26-FA26 -> 0
A27: =+A26+1 -> #REF! | B27: Alpuaque Aragon Sergio Antonio | C27: Mensajero | D27: PROQUIMA | E27: 3166.38 | F27: 370 | G27: =+E27+F27 -> 3536.38 | H27: 30 | I27: 1 | J27: 0 | K27: 0 | L27: 0 | M27: 0 | N27: =SUM(I27:M27) -> 1 | Q27: =($E27/30/8*1.5)*P27 -> 0 | S27: =($E27/30/8*2)*R27 -> 0 | U27: =($E27/30/8*1.5)*T27 -> 0 | W27: =($E27/30/8*2)*V27 -> 0 | Y27: =(($E27/30/8)*1.5)*X27 -> 0 | AA27: =(($E27/30/8)*2)*Z27 -> 0 | AC27: =(($E27/30/8)*1.5)*AB27 -> 0 | AE27: =(($E27/30/8)*2)*AD27 -> 0 | AG27: =(($E27/30/8)*1.5)*AF27 -> 0 | AI27: =(($E27/30/8)*2)*AH27 -> 0 | AV27: =((E27/30)*H27)*$I27 -> 3166.38 | AW27: =((F27/30)*H27)*$I27 -> 370 | AX27: =P27 -> 0 | AY27: =Q27 -> 0 | AZ27: =R27 -> 0 | BA27: =S27 -> 0 | BB27: =AJ27+AO27 -> 0 | BC27: =(AV27+AY27+BA27)*0.1267 -> 401.18035 | BD27: =SUM(AV27:BC27)-AX27-AZ27 -> 3937.5603 | BE27: =(($E27/30)*$H27)*$J27 -> 0 | BF27: =(($F27/30)*$H27)*$J27 -> 0 | BG27: =T27 -> 0 | BH27: =U27 -> 0 | BI27: =V27 -> 0 | BJ27: =W27 -> 0 | BK27: =AK27+AP27 -> 0 | BL27: =(+BE27+BH27+BJ27+BK27)*0.1267 -> 0 | BM27: =SUM(BE27:BL27)-BG27-BI27 -> 0 | BN27: =(($E27/30)*$H27)*$K27 -> 0 | BO27: =(($F27/30)*$H27)*$K27 -> 0 | BP27: =X27 -> 0 | BQ27: =Y27 -> 0 | BR27: =Z27 -> 0 | BS27: =AA27 -> 0 | BT27: =AL27+AQ27 -> 0 | BU27: =(BN27+BQ27+BS27)*0.09 -> 0 | BV27: =SUM(BN27:BU27)-BP27-BR27 -> 0 | BW27: =(($E27/30)*$H27)*$L27 -> 0 | BX27: =(($F27/30)*$H27)*$L27 -> 0 | BY27: =AB27 -> 0 | BZ27: =AC27 -> 0 | CA27: =AD27 -> 0 | CB27: =AE27 -> 0 | CC27: =AM27+AR27 -> 0 | CD27: =(BW27+BZ27+CB27)*0.09 -> 0 | CE27: =SUM(BW27:CD27)-BY27-CA27 -> 0 | CF27: =(($E27/30)*$H27)*M27 -> 0 | CG27: =(($F27/30)*$H27)*$M27 -> 0 | CH27: =+AF27 -> 0 | CI27: =AG27 -> 0 | CJ27: =AH27 -> 0 | CK27: =AI27 -> 0 | CL27: =AN27+AS27 -> 0 | CM27: =(CF27+CI27+CK27)*0.09 -> 0 | CN27: =SUM(CF27:CM27)-CH27-CJ27 -> 0 | CP27: PROQUIMA | CQ27: =IF($CP27="PROQUIMA",$AV27+$BE27+$BN27+$BW27+$CF27,0) -> 3166.38 | CR27: =IF($CP27="PROQUIMA",$AW27+$BF27+$BO27+$BX27+$CG27,0) -> 370 | CS27: =IF($CP27="PROQUIMA",$AX27+$BG27+$BP27+$BY27+$CH27,0) -> 0 | CT27: =IF($CP27="PROQUIMA",$AY27+$BH27+$BQ27+$BZ27+$CI27,0) -> 0 | CU27: =IF($CP27="PROQUIMA",$AZ27+$BI27+$BR27+$CA27+$CJ27,0) -> 0 | CV27: =IF($CP27="PROQUIMA",$BA27+$BJ27+$BS27+$CB27+$CK27,0) -> 0 | CW27: =IF($CP27="PROQUIMA",$BB27+$BK27+$BT27+$CC27+$CL27,0) -> 0 | CX27: =IF($CP27="PROQUIMA",$BC27+$BL27+$BU27+$CD27+CM27,0) -> 401.18035 | CY27: =SUM(CQ27:CX27)-CS27-CU27 -> 3937.5603 | CZ27: =IF($CP27="UNHESA",$AV27+$BE27+$BN27+$BW27+$CF27,0) -> 0 | DA27: =IF($CP27="UNHESA",$AW27+$BF27+$BO27+$BX27+$CG27,0) -> 0 | DB27: =IF($CP27="UNHESA",$AX27+$BG27+$BP27+$BY27+$CH27,0) -> 0 | DC27: =IF($CP27="UNHESA",$AY27+$BH27+$BQ27+$BZ27+$CI27,0) -> 0 | DD27: =IF($CP27="UNHESA",$AZ27+$BI27+$BR27+$CA27+$CJ27,0) -> 0 | DE27: =IF($CP27="UNHESA",$BA27+$BJ27+$BS27+$CB27+$CK27,0) -> 0 | DF27: =IF($CP27="UNHESA",$BB27+$BK27+$BT27+$CC27+$CL27,0) -> 0 | DG27: =IF($CP27="UNHESA",$BC27+$BL27+$BU27+$CD27+$CM27,0) -> 0 | DH27: =SUM(CZ27:DG27)-DB27-DD27 -> 0 | DI27: =IF($CP27="UNHESA LIQUIDOS",$AV27+$BE27+$BN27+$BW27+$CF27,0) -> 0 | DJ27: =IF($CP27="CALIDUL",$AW27+$BF27+$BO27+$BX27+$CG27,0) -> 0 | DK27: =IF($CP27="CALIDUL",$AX27+$BG27+$BP27+$BY27+$CH27,0) -> 0 | DL27: =IF($CP27="CALIDUL",$AY27+$BH27+$BQ27+$BZ27+$CI27,0) -> 0 | DM27: =IF($CP27="CALIDUL",$AZ27+$BI27+$BR27+$CA27+$CJ27,0) -> 0 | DN27: =IF($CP27="CALIDUL",$BA27+$BJ27+$BS27+$CB27+$CK27,0) -> 0 | DO27: =IF($CP27="CALIDUL",$BB27+$BK27+$BT27+$CC27+$CL27,0) -> 0 | DP27: =IF($CP27="CALIDUL",$BC27+$BL27+$BU27+$CD27+$CM27,0) -> 0 | DQ27: =SUM(DI27:DP27)-DK27-DM27 -> 0 | DR27: =IF($CP27="ECONACIONAL",$AV27+$BE27+$BN27+$BW27+$CF27,0) -> 0 | DS27: =IF($CP27="ECONACIONAL",$AW27+$BF27+$BO27+$BX27+$CG27,0) -> 0 | DT27: =IF($CP27="ECONACIONAL",$AX27+$BG27+$BP27+$BY27+$CH27,0) -> 0 | DU27: =IF($CP27="ECONACIONAL",$AY27+$BH27+$BQ27+$BZ27+$CI27,0) -> 0 | DV27: =IF($CP27="ECONACIONAL",$AZ27+$BI27+$BR27+$CA27+$CJ27,0) -> 0 | DW27: =IF($CP27="ECONACIONAL",$BA27+$BJ27+$BS27+$CB27+$CK27,0) -> 0 | DX27: =IF($CP27="ECONACIONAL",$BB27+$BK27+$BT27+$CC27+$CL27,0) -> 0 | DY27: =IF($CP27="ECONACIONAL",$BC27+$BL27+$BU27+$CD27+$CM27,0) -> 0 | DZ27: =SUM(DR27:DY27)-DT27-DV27 -> 0 | EA27: =IF($CP27="CLEARTEC",$AV27+$BE27+$BN27+$BW27+$CF27,0) -> 0 | EB27: =IF($CP27="CLEARTEC",$AW27+$BF27+$BO27+$BX27+$CG27,0) -> 0 | EC27: =IF($CP27="CLEARTEC",$AX27+$BG27+$BP27+$BY27+$CH27,0) -> 0 | ED27: =IF($CP27="CLEARTEC",$AY27+$BH27+$BQ27+$BZ27+$CI27,0) -> 0 | EE27: =IF($CP27="CLEARTEC",$AZ27+$BI27+$BR27+$CA27+$CJ27,0) -> 0 | EF27: =IF($CP27="CLEARTEC",$BA27+$BJ27+$BS27+$CB27+$CK27,0) -> 0 | EG27: =IF($CP27="CLEARTEC",$BB27+$BK27+$BT27+$CC27+$CL27,0) -> 0 | EH27: =IF($CP27="CLEARTEC",$BC27+$BL27+$BU27+$CD27+$CM27,0) -> 0 | EI27: =SUM(EA27:EH27)-EC27-EE27 -> 0 | EP27: 50 | EQ27: 400 | ET27: =+EO27+EP27+EQ27 -> 450 | EV27: =IF($H27<=15,EK27/2,EK27) -> 0 | EW27: =IF($H27<=15,EL27/2,EL27) -> 0 | EX27: =IF($H27<=15,EM27/2,EM27) -> 0 | EY27: =IF($H27<=15,EN27/2,EN27) -> 0 | EZ27: =IF($H27<=15,EO27/2,EO27) -> 0 | FA27: =IF($H27<=15,EP27/2,EP27) -> 50 | FB27: =IF($H27<=15,EQ27/2,EQ27) -> 400 | FC27: =IF($H27<=15,ER27/2,ER27) -> 0 | ... FE27: =IF($H27<=15,ET27/2,ET27) -> 450 | FF27: 1 | FG27: 0 | FH27: 0 | FI27: 0 | FJ27: 0 | FK27: 1 | FL27: =+EP27-FA27 -> 0
C28: Total Administrativo | E28: =SUM(E22:E27) -> 19094.4 | F28: =SUM(F22:F27) -> 3740 | G28: =SUM(G22:G27) -> 22834.4 | P28: =SUM(P22:P27) -> 0 | Q28: =SUM(Q22:Q27) -> 0 | R28: =SUM(R22:R27) -> 0 | S28: =SUM(S22:S27) -> 0 | T28: =SUM(T22:T27) -> 0 | U28: =SUM(U22:U27) -> 0 | V28: =SUM(V22:V27) -> 0 | W28: =SUM(W22:W27) -> 0 | ... AT28: =SUM(AT22:AT27) -> 0 | AV28: =SUM(AV22:AV27) -> 14344.83 | AW28: =SUM(AW22:AW27) -> 3365 | AX28: =SUM(AX22:AX27) -> 0 | AY28: =SUM(AY22:AY27) -> 0 | AZ28: =SUM(AZ22:AZ27) -> 0 | BA28: =SUM(BA22:BA27) -> 0 | BB28: =SUM(BB22:BB27) -> 0 | BC28: =SUM(BC22:BC27) -> 1817.49 | ... CN28: =SUM(CN22:CN27) -> 0 | CQ28: =SUM(CQ22:CQ27) -> 15928.02 | CR28: =SUM(CR22:CR27) -> 3490 | CS28: =SUM(CS22:CS27) -> 0 | CT28: =SUM(CT22:CT27) -> 0 | CU28: =SUM(CU22:CU27) -> 0 | CV28: =SUM(CV22:CV27) -> 0 | CW28: =SUM(CW22:CW27) -> 0 | CX28: =SUM(CX22:CX27) -> 2018.0801 | ... EI28: =SUM(EI22:EI27) -> 0 | EK28: =SUM(EK22:EK27) -> 67.75 | EL28: =SUM(EL22:EL27) -> 0 | EM28: =SUM(EM22:EM27) -> 0 | EN28: =SUM(EN22:EN27) -> 0 | EO28: =SUM(EO22:EO27) -> 202.5 | EP28: =SUM(EP22:EP27) -> 250 | ER28: =SUM(ER22:ER27) -> 0 | ES28: =SUM(ES22:ES27) -> 0 | ET28: =SUM(ET22:ET27) -> 1159.12 | EV28: =SUM(EV22:EV27) -> 67.75 | EW28: =SUM(EW22:EW27) -> 0 | EX28: =SUM(EX22:EX27) -> 0 | EY28: =SUM(EY22:EY27) -> 0 | EZ28: =SUM(EZ22:EZ27) -> 202.5 | FA28: =SUM(FA22:FA27) -> 250 | FB28: =SUM(FB22:FB27) -> 706.62 | FC28: =SUM(FC22:FC27) -> 0 | ... FE28: =SUM(FE22:FE27) -> 1159.12 | FL28: =+EP28-FA28 -> 0
FL29: =+EP29-FA29 -> 0
B30: CONTABILIDAD Y FINANZAS | FL30: =+EP30-FA30 -> 0
A31: =A27+1 -> #REF! | B31: Patzan Quib Lucrecia | C31: Contador General | D31: UNHESA | E31: 10036.54 | F31: 657.7 | G31: =+E31+F31 -> 10694.24 | H31: 30 | I31: 0.45 | J31: 0.45 | K31: 0 | L31: 0.1 | M31: 0 | N31: =SUM(I31:M31) -> 1 | Q31: =($E31/30/8*1.5)*P31 -> 0 | S31: =($E31/30/8*2)*R31 -> 0 | U31: =($E31/30/8*1.5)*T31 -> 0 | W31: =($E31/30/8*2)*V31 -> 0 | Y31: =(($E31/30/8)*1.5)*X31 -> 0 | AA31: =(($E31/30/8)*2)*Z31 -> 0 | AC31: =(($E31/30/8)*1.5)*AB31 -> 0 | AE31: =(($E31/30/8)*2)*AD31 -> 0 | AG31: =(($E31/30/8)*1.5)*AF31 -> 0 | AI31: =(($E31/30/8)*2)*AH31 -> 0 | AV31: =((E31/30)*H31)*$I31 -> 4516.443 | AW31: =((F31/30)*H31)*$I31 -> 295.965 | AX31: =P31 -> 0 | AY31: =Q31 -> 0 | AZ31: =R31 -> 0 | BA31: =S31 -> 0 | BB31: =AJ31+AO31 -> 0 | BC31: =(AV31+AY31+BA31)*0.1267 -> 572.23333 | BD31: =SUM(AV31:BC31)-AX31-AZ31 -> 5384.6413 | BE31: =(($E31/30)*$H31)*$J31 -> 4516.443 | BF31: =(($F31/30)*$H31)*$J31 -> 295.965 | BG31: =T31 -> 0 | BH31: =U31 -> 0 | BI31: =V31 -> 0 | BJ31: =W31 -> 0 | BK31: 0 | BL31: =(+BE31+BH31+BJ31+BK31)*0.1267 -> 572.23333 | BM31: =SUM(BE31:BL31)-BG31-BI31 -> 5384.6413 | BN31: =(($E31/30)*$H31)*$K31 -> 0 | BO31: =(($F31/30)*$H31)*$K31 -> 0 | BP31: =X31 -> 0 | BQ31: =Y31 -> 0 | BR31: =Z31 -> 0 | BS31: =AA31 -> 0 | BT31: =AL31+AQ31 -> 0 | BU31: =(BN31+BQ31+BS31)*0.1267 -> 0 | BV31: =SUM(BN31:BU31)-BP31-BR31 -> 0 | BW31: =(($E31/30)*$H31)*$L31 -> 1003.654 | BX31: =(($F31/30)*$H31)*$L31 -> 65.77 | BY31: =AB31 -> 0 | BZ31: =AC31 -> 0 | CA31: =AD31 -> 0 | CB31: =AE31 -> 0 | CC31: =AM31+AR31 -> 0 | CD31: =(BW31+BZ31+CB31)*0.1267 -> 127.16296 | CE31: =SUM(BW31:CD31)-BY31-CA31 -> 1196.587 | CF31: =(($E31/30)*$H31)*M31 -> 0 | CG31: =(($F31/30)*$H31)*$M31 -> 0 | CH31: =+AF31 -> 0 | CI31: =AG31 -> 0 | CJ31: =AH31 -> 0 | CK31: =AI31 -> 0 | CL31: =AN31+AS31 -> 0 | CM31: =(CF31+CI31+CK31)*0.1267 -> 0 | CN31: =SUM(CF31:CM31)-CH31-CJ31 -> 0 | CP31: UNHESA | CQ31: =IF($CP31="PROQUIMA",$AV31+$BE31+$BN31+$BW31+$CF31,0) -> 0 | CR31: =IF($CP31="PROQUIMA",$AW31+$BF31+$BO31+$BX31+$CG31,0) -> 0 | CS31: =IF($CP31="PROQUIMA",$AX31+$BG31+$BP31+$BY31+$CH31,0) -> 0 | CT31: =IF($CP31="PROQUIMA",$AY31+$BH31+$BQ31+$BZ31+$CI31,0) -> 0 | CU31: =IF($CP31="PROQUIMA",$AZ31+$BI31+$BR31+$CA31+$CJ31,0) -> 0 | CV31: =IF($CP31="PROQUIMA",$BA31+$BJ31+$BS31+$CB31+$CK31,0) -> 0 | CW31: =IF($CP31="PROQUIMA",$BB31+$BK31+$BT31+$CC31+$CL31,0) -> 0 | CX31: =IF($CP31="PROQUIMA",$BC31+$BL31+$BU31+$CD31+CM31,0) -> 0 | CY31: =SUM(CQ31:CX31)-CS31-CU31 -> 0 | CZ31: =IF($CP31="UNHESA",$AV31+$BE31+$BN31+$BW31+$CF31,0) -> 10036.54 | DA31: =IF($CP31="UNHESA",$AW31+$BF31+$BO31+$BX31+$CG31,0) -> 657.7 | DB31: =IF($CP31="UNHESA",$AX31+$BG31+$BP31+$BY31+$CH31,0) -> 0 | DC31: =IF($CP31="UNHESA",$AY31+$BH31+$BQ31+$BZ31+$CI31,0) -> 0 | DD31: =IF($CP31="UNHESA",$AZ31+$BI31+$BR31+$CA31+$CJ31,0) -> 0 | DE31: =IF($CP31="UNHESA",$BA31+$BJ31+$BS31+$CB31+$CK31,0) -> 0 | DF31: 0 | DG31: =IF($CP31="UNHESA",$BC31+$BL31+$BU31+$CD31+$CM31,0) -> 1271.6296 | DH31: =SUM(CZ31:DG31)-DB31-DD31 -> 11965.87 | DI31: =IF($CP31="UNHESA LIQUIDOS",$AV31+$BE31+$BN31+$BW31+$CF31,0) -> 0 | DJ31: =IF($CP31="CALIDUL",$AW31+$BF31+$BO31+$BX31+$CG31,0) -> 0 | DK31: =IF($CP31="CALIDUL",$AX31+$BG31+$BP31+$BY31+$CH31,0) -> 0 | DL31: =IF($CP31="CALIDUL",$AY31+$BH31+$BQ31+$BZ31+$CI31,0) -> 0 | DM31: =IF($CP31="CALIDUL",$AZ31+$BI31+$BR31+$CA31+$CJ31,0) -> 0 | DN31: =IF($CP31="CALIDUL",$BA31+$BJ31+$BS31+$CB31+$CK31,0) -> 0 | DO31: =IF($CP31="CALIDUL",$BB31+$BK31+$BT31+$CC31+$CL31,0) -> 0 | DP31: =IF($CP31="CALIDUL",$BC31+$BL31+$BU31+$CD31+$CM31,0) -> 0 | DQ31: =SUM(DI31:DP31)-DK31-DM31 -> 0 | DR31: =IF($CP31="ECONACIONAL",$AV31+$BE31+$BN31+$BW31+$CF31,0) -> 0 | DS31: =IF($CP31="ECONACIONAL",$AW31+$BF31+$BO31+$BX31+$CG31,0) -> 0 | DT31: =IF($CP31="ECONACIONAL",$AX31+$BG31+$BP31+$BY31+$CH31,0) -> 0 | DU31: =IF($CP31="ECONACIONAL",$AY31+$BH31+$BQ31+$BZ31+$CI31,0) -> 0 | DV31: =IF($CP31="ECONACIONAL",$AZ31+$BI31+$BR31+$CA31+$CJ31,0) -> 0 | DW31: =IF($CP31="ECONACIONAL",$BA31+$BJ31+$BS31+$CB31+$CK31,0) -> 0 | DX31: =IF($CP31="ECONACIONAL",$BB31+$BK31+$BT31+$CC31+$CL31,0) -> 0 | DY31: =IF($CP31="ECONACIONAL",$BC31+$BL31+$BU31+$CD31+$CM31,0) -> 0 | DZ31: =SUM(DR31:DY31)-DT31-DV31 -> 0 | EA31: =IF($CP31="CLEARTEC",$AV31+$BE31+$BN31+$BW31+$CF31,0) -> 0 | EB31: =IF($CP31="CLEARTEC",$AW31+$BF31+$BO31+$BX31+$CG31,0) -> 0 | EC31: =IF($CP31="CLEARTEC",$AX31+$BG31+$BP31+$BY31+$CH31,0) -> 0 | ED31: =IF($CP31="CLEARTEC",$AY31+$BH31+$BQ31+$BZ31+$CI31,0) -> 0 | EE31: =IF($CP31="CLEARTEC",$AZ31+$BI31+$BR31+$CA31+$CJ31,0) -> 0 | EF31: =IF($CP31="CLEARTEC",$BA31+$BJ31+$BS31+$CB31+$CK31,0) -> 0 | EG31: =IF($CP31="CLEARTEC",$BB31+$BK31+$BT31+$CC31+$CL31,0) -> 0 | EH31: =IF($CP31="CLEARTEC",$BC31+$BL31+$BU31+$CD31+$CM31,0) -> 0 | EI31: =SUM(EA31:EH31)-EC31-EE31 -> 0 | EK31: 310.47 | EL31: 1484.26 | EM31: =199+199+199+199 -> 796 | EP31: 100 | ET31: =+EO31+EP31+EQ31 -> 100 | EV31: =IF($H31<=15,EK31/2,EK31) -> 310.47 | EW31: =IF($H31<=15,EL31/2,EL31) -> 1484.26 | EX31: =IF($H31<=15,EM31/2,EM31) -> 796 | EY31: =IF($H31<=15,EN31/2,EN31) -> 0 | EZ31: =IF($H31<=15,EO31/2,EO31) -> 0 | FA31: =IF($H31<=15,EP31/2,EP31) -> 100 | FB31: =IF($H31<=15,EQ31/2,EQ31) -> 0 | FC31: =IF($H31<=15,ER31/2,ER31) -> 0 | ... FE31: =IF($H31<=15,ET31/2,ET31) -> 100 | FF31: 0.65 | FG31: 0.35 | FI31: 0 | FJ31: 0 | FK31: 1 | FL31: =+EP31-FA31 -> 0
A32: =+A31+1 -> #REF! | B32: Lorenzana Gonzalez Cesar Leonel | C32: Gerente Financiero | D32: UNHESA | E32: 18000 | F32: 5000 | G32: =+E32+F32 -> 23000 | H32: 30 | I32: 0.6 | J32: 0.3 | K32: 0 | L32: 0.1 | M32: 0 | N32: =SUM(I32:M32) -> 1 | Q32: =($E32/30/8*1.5)*P32 -> 0 | S32: =($E32/30/8*2)*R32 -> 0 | U32: =($E32/30/8*1.5)*T32 -> 0 | W32: =($E32/30/8*2)*V32 -> 0 | Y32: =(($E32/30/8)*1.5)*X32 -> 0 | AA32: =(($E32/30/8)*2)*Z32 -> 0 | AC32: =(($E32/30/8)*1.5)*AB32 -> 0 | AE32: =(($E32/30/8)*2)*AD32 -> 0 | AG32: =(($E32/30/8)*1.5)*AF32 -> 0 | AI32: =(($E32/30/8)*2)*AH32 -> 0 | AV32: =((E32/30)*H32)*$I32 -> 10800 | AW32: =((F32/30)*H32)*$I32 -> 3000 | AX32: =P32 -> 0 | AY32: =Q32 -> 0 | AZ32: =R32 -> 0 | BA32: =S32 -> 0 | BB32: =AJ32+AO32 -> 0 | BC32: =(AV32+AY32+BA32)*0.1267 -> 1368.36 | BD32: =SUM(AV32:BC32)-AX32-AZ32 -> 15168.36 | BE32: =(($E32/30)*$H32)*$J32 -> 5400 | BF32: =(($F32/30)*$H32)*$J32 -> 1500 | BG32: =T32 -> 0 | BH32: =U32 -> 0 | BI32: =V32 -> 0 | BJ32: =W32 -> 0 | BK32: =AK32+AP32 -> 0 | BL32: =(+BE32+BH32+BJ32+BK32)*0.1267 -> 684.18 | BM32: =SUM(BE32:BL32)-BG32-BI32 -> 7584.18 | BN32: =(($E32/30)*$H32)*$K32 -> 0 | BO32: =(($F32/30)*$H32)*$K32 -> 0 | BP32: =X32 -> 0 | BQ32: =Y32 -> 0 | BR32: =Z32 -> 0 | BS32: =AA32 -> 0 | BT32: =AL32+AQ32 -> 0 | BU32: =(BN32+BQ32+BS32)*0.1267 -> 0 | BV32: =SUM(BN32:BU32)-BP32-BR32 -> 0 | BW32: =(($E32/30)*$H32)*$L32 -> 1800 | BX32: =(($F32/30)*$H32)*$L32 -> 500 | BY32: =AB32 -> 0 | BZ32: =AC32 -> 0 | CA32: =AD32 -> 0 | CB32: =AE32 -> 0 | CC32: =AM32+AR32 -> 0 | CD32: =(BW32+BZ32+CB32)*0.1267 -> 228.06 | CE32: =SUM(BW32:CD32)-BY32-CA32 -> 2528.06 | CF32: =(($E32/30)*$H32)*M32 -> 0 | CG32: =(($F32/30)*$H32)*$M32 -> 0 | CH32: =+AF32 -> 0 | CI32: =AG32 -> 0 | CJ32: =AH32 -> 0 | CK32: =AI32 -> 0 | CL32: =AN32+AS32 -> 0 | CM32: =(CF32+CI32+CK32)*0.1267 -> 0 | CN32: =SUM(CF32:CM32)-CH32-CJ32 -> 0 | CP32: UNHESA | CQ32: =IF($CP32="PROQUIMA",$AV32+$BE32+$BN32+$BW32+$CF32,0) -> 0 | CR32: =IF($CP32="PROQUIMA",$AW32+$BF32+$BO32+$BX32+$CG32,0) -> 0 | CS32: =IF($CP32="PROQUIMA",$AX32+$BG32+$BP32+$BY32+$CH32,0) -> 0 | CT32: =IF($CP32="PROQUIMA",$AY32+$BH32+$BQ32+$BZ32+$CI32,0) -> 0 | CU32: =IF($CP32="PROQUIMA",$AZ32+$BI32+$BR32+$CA32+$CJ32,0) -> 0 | CV32: =IF($CP32="PROQUIMA",$BA32+$BJ32+$BS32+$CB32+$CK32,0) -> 0 | CW32: =IF($CP32="PROQUIMA",$BB32+$BK32+$BT32+$CC32+$CL32,0) -> 0 | CX32: =IF($CP32="PROQUIMA",$BC32+$BL32+$BU32+$CD32+CM32,0) -> 0 | CY32: =SUM(CQ32:CX32)-CS32-CU32 -> 0 | CZ32: =IF($CP32="UNHESA",$AV32+$BE32+$BN32+$BW32+$CF32,0) -> 18000 | DA32: =IF($CP32="UNHESA",$AW32+$BF32+$BO32+$BX32+$CG32,0) -> 5000 | DB32: =IF($CP32="UNHESA",$AX32+$BG32+$BP32+$BY32+$CH32,0) -> 0 | DC32: =IF($CP32="UNHESA",$AY32+$BH32+$BQ32+$BZ32+$CI32,0) -> 0 | DD32: =IF($CP32="UNHESA",$AZ32+$BI32+$BR32+$CA32+$CJ32,0) -> 0 | DE32: =IF($CP32="UNHESA",$BA32+$BJ32+$BS32+$CB32+$CK32,0) -> 0 | DF32: =IF($CP32="UNHESA",$BB32+$BK32+$BT32+$CC32+$CL32,0) -> 0 | DG32: =IF($CP32="UNHESA",$BC32+$BL32+$BU32+$CD32+$CM32,0) -> 2280.6 | DH32: =SUM(CZ32:DG32)-DB32-DD32 -> 25280.6 | DI32: =IF($CP32="UNHESA LIQUIDOS",$AV32+$BE32+$BN32+$BW32+$CF32,0) -> 0 | DJ32: =IF($CP32="CALIDUL",$AW32+$BF32+$BO32+$BX32+$CG32,0) -> 0 | DK32: =IF($CP32="CALIDUL",$AX32+$BG32+$BP32+$BY32+$CH32,0) -> 0 | DL32: =IF($CP32="CALIDUL",$AY32+$BH32+$BQ32+$BZ32+$CI32,0) -> 0 | DM32: =IF($CP32="CALIDUL",$AZ32+$BI32+$BR32+$CA32+$CJ32,0) -> 0 | DN32: =IF($CP32="CALIDUL",$BA32+$BJ32+$BS32+$CB32+$CK32,0) -> 0 | DO32: =IF($CP32="CALIDUL",$BB32+$BK32+$BT32+$CC32+$CL32,0) -> 0 | DP32: =IF($CP32="CALIDUL",$BC32+$BL32+$BU32+$CD32+$CM32,0) -> 0 | DQ32: =SUM(DI32:DP32)-DK32-DM32 -> 0 | DR32: =IF($CP32="ECONACIONAL",$AV32+$BE32+$BN32+$BW32+$CF32,0) -> 0 | DS32: =IF($CP32="ECONACIONAL",$AW32+$BF32+$BO32+$BX32+$CG32,0) -> 0 | DT32: =IF($CP32="ECONACIONAL",$AX32+$BG32+$BP32+$BY32+$CH32,0) -> 0 | DU32: =IF($CP32="ECONACIONAL",$AY32+$BH32+$BQ32+$BZ32+$CI32,0) -> 0 | DV32: =IF($CP32="ECONACIONAL",$AZ32+$BI32+$BR32+$CA32+$CJ32,0) -> 0 | DW32: =IF($CP32="ECONACIONAL",$BA32+$BJ32+$BS32+$CB32+$CK32,0) -> 0 | DX32: =IF($CP32="ECONACIONAL",$BB32+$BK32+$BT32+$CC32+$CL32,0) -> 0 | DY32: =IF($CP32="ECONACIONAL",$BC32+$BL32+$BU32+$CD32+$CM32,0) -> 0 | DZ32: =SUM(DR32:DY32)-DT32-DV32 -> 0 | EA32: =IF($CP32="CLEARTEC",$AV32+$BE32+$BN32+$BW32+$CF32,0) -> 0 | EB32: =IF($CP32="CLEARTEC",$AW32+$BF32+$BO32+$BX32+$CG32,0) -> 0 | EC32: =IF($CP32="CLEARTEC",$AX32+$BG32+$BP32+$BY32+$CH32,0) -> 0 | ED32: =IF($CP32="CLEARTEC",$AY32+$BH32+$BQ32+$BZ32+$CI32,0) -> 0 | EE32: =IF($CP32="CLEARTEC",$AZ32+$BI32+$BR32+$CA32+$CJ32,0) -> 0 | EF32: =IF($CP32="CLEARTEC",$BA32+$BJ32+$BS32+$CB32+$CK32,0) -> 0 | EG32: =IF($CP32="CLEARTEC",$BB32+$BK32+$BT32+$CC32+$CL32,0) -> 0 | EH32: =IF($CP32="CLEARTEC",$BC32+$BL32+$BU32+$CD32+$CM32,0) -> 0 | EI32: =SUM(EA32:EH32)-EC32-EE32 -> 0 | EK32: 906.53 | EP32: 150 | ET32: =+EO32+EP32+EQ32 -> 150 | EV32: =IF($H32<=15,EK32/2,EK32) -> 906.53 | EW32: =IF($H32<=15,EL32/2,EL32) -> 0 | EX32: =IF($H32<=15,EM32/2,EM32) -> 0 | EY32: =IF($H32<=15,EN32/2,EN32) -> 0 | EZ32: =IF($H32<=15,EO32/2,EO32) -> 0 | FA32: =IF($H32<=15,EP32/2,EP32) -> 150 | FB32: =IF($H32<=15,EQ32/2,EQ32) -> 0 | FC32: =IF($H32<=15,ER32/2,ER32) -> 0 | ... FE32: =IF($H32<=15,ET32/2,ET32) -> 150
B33: Yoc Barillas Luis Estuardo | C33: Contador | D33: PROQUIMA | E33: 5000 | F33: 2500 | G33: =+E33+F33 -> 7500 | H33: 29 | I33: 0.15 | J33: 0.15 | K33: 0 | L33: 0.7 | M33: 0 | N33: =SUM(I33:M33) -> 1 | O33: A.2/1/2023 | Q33: =($E33/30/8*1.5)*P33 -> 0 | S33: =($E33/30/8*2)*R33 -> 0 | U33: =($E33/30/8*1.5)*T33 -> 0 | W33: =($E33/30/8*2)*V33 -> 0 | Y33: =(($E33/30/8)*1.5)*X33 -> 0 | AA33: =(($E33/30/8)*2)*Z33 -> 0 | AC33: =(($E33/30/8)*1.5)*AB33 -> 0 | AE33: =(($E33/30/8)*2)*AD33 -> 0 | AG33: =(($E33/30/8)*1.5)*AF33 -> 0 | AI33: =(($E33/30/8)*2)*AH33 -> 0 | AV33: =((E33/30)*H33)*$I33 -> 725 | AW33: =((F33/30)*H33)*$I33+150 -> 512.5 | AX33: =P33 -> 0 | AY33: =Q33 -> 0 | AZ33: =R33 -> 0 | BA33: =S33 -> 0 | BB33: =AJ33+AO33 -> 0 | BC33: =(AV33+AY33+BA33)*0.1267 -> 91.8575 | BD33: =SUM(AV33:BC33)-AX33-AZ33 -> 1329.3575 | BE33: =(($E33/30)*$H33)*$J33 -> 725 | BF33: =(($F33/30)*$H33)*$J33+150 -> 512.5 | BG33: =T33 -> 0 | BH33: =U33 -> 0 | BI33: =V33 -> 0 | BJ33: =W33 -> 0 | BK33: =AK33+AP33 -> 0 | BL33: =(+BE33+BH33+BJ33+BK33)*0.1267 -> 91.8575 | BM33: =SUM(BE33:BL33)-BG33-BI33 -> 1329.3575 | BN33: =(($E33/30)*$H33)*$K33 -> 0 | BO33: =(($F33/30)*$H33)*$K33 -> 0 | BP33: =X33 -> 0 | BQ33: =Y33 -> 0 | BR33: =Z33 -> 0 | BS33: =AA33 -> 0 | BT33: =AL33+AQ33 -> 0 | BU33: =(BN33+BQ33+BS33)*0.1267 -> 0 | BV33: =SUM(BN33:BU33)-BP33-BR33 -> 0 | BW33: =(($E33/30)*$H33)*$L33 -> 3383.3333 | BX33: =(($F33/30)*$H33)*$L33+700 -> 2391.6667 | BY33: =AB33 -> 0 | BZ33: =AC33 -> 0 | CA33: =AD33 -> 0 | CB33: =AE33 -> 0 | CC33: =AM33+AR33 -> 0 | CD33: =(BW33+BZ33+CB33)*0.1267 -> 428.66833 | CE33: =SUM(BW33:CD33)-BY33-CA33 -> 6203.6683 | CF33: =(($E33/30)*$H33)*M33 -> 0 | CG33: =(($F33/30)*$H33)*$M33 -> 0 | CH33: =+AF33 -> 0 | CI33: =AG33 -> 0 | CJ33: =AH33 -> 0 | CK33: =AI33 -> 0 | CL33: =AN33+AS33 -> 0 | CM33: =(CF33+CI33+CK33)*0.1267 -> 0 | CN33: =SUM(CF33:CM33)-CH33-CJ33 -> 0 | CP33: PROQUIMA | CQ33: =IF($CP33="PROQUIMA",$AV33+$BE33+$BN33+$BW33+$CF33,0) -> 4833.3333 | CR33: =IF($CP33="PROQUIMA",$AW33+$BF33+$BO33+$BX33+$CG33,0) -> 3416.6667 | CS33: =IF($CP33="PROQUIMA",$AX33+$BG33+$BP33+$BY33+$CH33,0) -> 0 | CT33: =IF($CP33="PROQUIMA",$AY33+$BH33+$BQ33+$BZ33+$CI33,0) -> 0 | CU33: =IF($CP33="PROQUIMA",$AZ33+$BI33+$BR33+$CA33+$CJ33,0) -> 0 | CV33: =IF($CP33="PROQUIMA",$BA33+$BJ33+$BS33+$CB33+$CK33,0) -> 0 | CW33: =IF($CP33="PROQUIMA",$BB33+$BK33+$BT33+$CC33+$CL33,0) -> 0 | CX33: =IF($CP33="PROQUIMA",$BC33+$BL33+$BU33+$CD33+CM33,0) -> 612.38333 | CY33: =SUM(CQ33:CX33)-CS33-CU33 -> 8862.3833 | CZ33: =IF($CP33="UNHESA",$AV33+$BE33+$BN33+$BW33+$CF33,0) -> 0 | DA33: =IF($CP33="UNHESA",$AW33+$BF33+$BO33+$BX33+$CG33,0) -> 0 | DB33: =IF($CP33="UNHESA",$AX33+$BG33+$BP33+$BY33+$CH33,0) -> 0 | DC33: =IF($CP33="UNHESA",$AY33+$BH33+$BQ33+$BZ33+$CI33,0) -> 0 | DD33: =IF($CP33="UNHESA",$AZ33+$BI33+$BR33+$CA33+$CJ33,0) -> 0 | DE33: =IF($CP33="UNHESA",$BA33+$BJ33+$BS33+$CB33+$CK33,0) -> 0 | DF33: =IF($CP33="UNHESA",$BB33+$BK33+$BT33+$CC33+$CL33,0) -> 0 | DG33: =IF($CP33="UNHESA",$BC33+$BL33+$BU33+$CD33+$CM33,0) -> 0 | DH33: =SUM(CZ33:DG33)-DB33-DD33 -> 0 | DI33: =IF($CP33="UNHESA LIQUIDOS",$AV33+$BE33+$BN33+$BW33+$CF33,0) -> 0 | DJ33: =IF($CP33="CALIDUL",$AW33+$BF33+$BO33+$BX33+$CG33,0) -> 0 | DK33: =IF($CP33="CALIDUL",$AX33+$BG33+$BP33+$BY33+$CH33,0) -> 0 | DL33: =IF($CP33="CALIDUL",$AY33+$BH33+$BQ33+$BZ33+$CI33,0) -> 0 | DM33: =IF($CP33="CALIDUL",$AZ33+$BI33+$BR33+$CA33+$CJ33,0) -> 0 | DN33: =IF($CP33="CALIDUL",$BA33+$BJ33+$BS33+$CB33+$CK33,0) -> 0 | DO33: =IF($CP33="CALIDUL",$BB33+$BK33+$BT33+$CC33+$CL33,0) -> 0 | DP33: =IF($CP33="CALIDUL",$BC33+$BL33+$BU33+$CD33+$CM33,0) -> 0 | DQ33: =SUM(DI33:DP33)-DK33-DM33 -> 0 | DR33: =IF($CP33="ECONACIONAL",$AV33+$BE33+$BN33+$BW33+$CF33,0) -> 0 | DS33: =IF($CP33="ECONACIONAL",$AW33+$BF33+$BO33+$BX33+$CG33,0) -> 0 | DT33: =IF($CP33="ECONACIONAL",$AX33+$BG33+$BP33+$BY33+$CH33,0) -> 0 | DU33: =IF($CP33="ECONACIONAL",$AY33+$BH33+$BQ33+$BZ33+$CI33,0) -> 0 | DV33: =IF($CP33="ECONACIONAL",$AZ33+$BI33+$BR33+$CA33+$CJ33,0) -> 0 | DW33: =IF($CP33="ECONACIONAL",$BA33+$BJ33+$BS33+$CB33+$CK33,0) -> 0 | DX33: =IF($CP33="ECONACIONAL",$BB33+$BK33+$BT33+$CC33+$CL33,0) -> 0 | DY33: =IF($CP33="ECONACIONAL",$BC33+$BL33+$BU33+$CD33+$CM33,0) -> 0 | DZ33: =SUM(DR33:DY33)-DT33-DV33 -> 0 | EA33: =IF($CP33="CLEARTEC",$AV33+$BE33+$BN33+$BW33+$CF33,0) -> 0 | EB33: =IF($CP33="CLEARTEC",$AW33+$BF33+$BO33+$BX33+$CG33,0) -> 0 | EC33: =IF($CP33="CLEARTEC",$AX33+$BG33+$BP33+$BY33+$CH33,0) -> 0 | ED33: =IF($CP33="CLEARTEC",$AY33+$BH33+$BQ33+$BZ33+$CI33,0) -> 0 | EE33: =IF($CP33="CLEARTEC",$AZ33+$BI33+$BR33+$CA33+$CJ33,0) -> 0 | EF33: =IF($CP33="CLEARTEC",$BA33+$BJ33+$BS33+$CB33+$CK33,0) -> 0 | EG33: =IF($CP33="CLEARTEC",$BB33+$BK33+$BT33+$CC33+$CL33,0) -> 0 | EH33: =IF($CP33="CLEARTEC",$BC33+$BL33+$BU33+$CD33+$CM33,0) -> 0 | EI33: =SUM(EA33:EH33)-EC33-EE33 -> 0 | EK33: 162.93 | EP33: 75 | EQ33: =240 -> 240 | ES33: 135 | ET33: =+EO33+EP33+EQ33 -> 315 | EV33: =IF($H33<=15,EK33/2,EK33) -> 162.93 | EW33: =IF($H33<=15,EL33/2,EL33) -> 0 | EX33: =IF($H33<=15,EM33/2,EM33) -> 0 | EY33: =IF($H33<=15,EN33/2,EN33) -> 0 | EZ33: =IF($H33<=15,EO33/2,EO33) -> 0 | FA33: =IF($H33<=15,EP33/2,EP33) -> 75 | FB33: =IF($H33<=15,EQ33/2,EQ33) -> 240 | FC33: =IF($H33<=15,ER33/2,ER33) -> 0 | ... FE33: =IF($H33<=15,ET33/2,ET33) -> 315
A34: =+A32+1 -> #REF! | B34: Cuello Pirir Jorge Renato | C34: Aux Creiditos y Cobros | D34: PROQUIMA | E34: 3500 | F34: 500 | G34: =+E34+F34 -> 4000 | H34: 30 | I34: 0.5 | J34: 0.5 | K34: 0 | L34: 0 | M34: 0 | N34: =SUM(I34:M34) -> 1 | Q34: =($E34/30/8*1.5)*P34 -> 0 | S34: =($E34/30/8*2)*R34 -> 0 | U34: =($E34/30/8*1.5)*T34 -> 0 | W34: =($E34/30/8*2)*V34 -> 0 | Y34: =(($E34/30/8)*1.5)*X34 -> 0 | AA34: =(($E34/30/8)*2)*Z34 -> 0 | AC34: =(($E34/30/8)*1.5)*AB34 -> 0 | AE34: =(($E34/30/8)*2)*AD34 -> 0 | AG34: =(($E34/30/8)*1.5)*AF34 -> 0 | AI34: =(($E34/30/8)*2)*AH34 -> 0 | AV34: =((E34/30)*H34)*$I34 -> 1750 | AW34: =((F34/30)*H34)*$I34 -> 250 | AX34: =P34 -> 0 | AY34: =Q34 -> 0 | AZ34: =R34 -> 0 | BA34: =S34 -> 0 | BB34: =AJ34+AO34 -> 0 | BC34: =(AV34+AY34+BA34)*0.1267 -> 221.725 | BD34: =SUM(AV34:BC34)-AX34-AZ34 -> 2221.725 | BE34: =(($E34/30)*$H34)*$J34 -> 1750 | BF34: =(($F34/30)*$H34)*$J34 -> 250 | BG34: =T34 -> 0 | BH34: =U34 -> 0 | BI34: =V34 -> 0 | BJ34: =W34 -> 0 | BK34: =AK34+AP34 -> 0 | BL34: =(+BE34+BH34+BJ34+BK34)*0.1267 -> 221.725 | BM34: =SUM(BE34:BL34)-BG34-BI34 -> 2221.725 | BN34: =(($E34/30)*$H34)*$K34 -> 0 | BO34: =(($F34/30)*$H34)*$K34 -> 0 | BP34: =X34 -> 0 | BQ34: =Y34 -> 0 | BR34: =Z34 -> 0 | BS34: =AA34 -> 0 | BT34: =AL34+AQ34 -> 0 | BU34: =(BN34+BQ34+BS34)*0.1267 -> 0 | BV34: =SUM(BN34:BU34)-BP34-BR34 -> 0 | BW34: =(($E34/30)*$H34)*$L34 -> 0 | BX34: =(($F34/30)*$H34)*$L34 -> 0 | BY34: =AB34 -> 0 | BZ34: =AC34 -> 0 | CA34: =AD34 -> 0 | CB34: =AE34 -> 0 | CC34: =AM34+AR34 -> 0 | CD34: =(BW34+BZ34+CB34)*0.1267 -> 0 | CE34: =SUM(BW34:CD34)-BY34-CA34 -> 0 | CF34: =(($E34/30)*$H34)*M34 -> 0 | CG34: =(($F34/30)*$H34)*$M34 -> 0 | CH34: =+AF34 -> 0 | CI34: =AG34 -> 0 | CJ34: =AH34 -> 0 | CK34: =AI34 -> 0 | CL34: =AN34+AS34 -> 0 | CM34: =(CF34+CI34+CK34)*0.1267 -> 0 | CN34: =SUM(CF34:CM34)-CH34-CJ34 -> 0 | CP34: PROQUIMA | CQ34: =IF($CP34="PROQUIMA",$AV34+$BE34+$BN34+$BW34+$CF34,0) -> 3500 | CR34: =IF($CP34="PROQUIMA",$AW34+$BF34+$BO34+$BX34+$CG34,0) -> 500 | CS34: =IF($CP34="PROQUIMA",$AX34+$BG34+$BP34+$BY34+$CH34,0) -> 0 | CT34: =IF($CP34="PROQUIMA",$AY34+$BH34+$BQ34+$BZ34+$CI34,0) -> 0 | CU34: =IF($CP34="PROQUIMA",$AZ34+$BI34+$BR34+$CA34+$CJ34,0) -> 0 | CV34: =IF($CP34="PROQUIMA",$BA34+$BJ34+$BS34+$CB34+$CK34,0) -> 0 | CW34: =IF($CP34="PROQUIMA",$BB34+$BK34+$BT34+$CC34+$CL34,0) -> 0 | CX34: =IF($CP34="PROQUIMA",$BC34+$BL34+$BU34+$CD34+CM34,0) -> 443.45 | CY34: =SUM(CQ34:CX34)-CS34-CU34 -> 4443.45 | CZ34: =IF($CP34="UNHESA",$AV34+$BE34+$BN34+$BW34+$CF34,0) -> 0 | DA34: =IF($CP34="UNHESA",$AW34+$BF34+$BO34+$BX34+$CG34,0) -> 0 | DB34: =IF($CP34="UNHESA",$AX34+$BG34+$BP34+$BY34+$CH34,0) -> 0 | DC34: =IF($CP34="UNHESA",$AY34+$BH34+$BQ34+$BZ34+$CI34,0) -> 0 | DD34: =IF($CP34="UNHESA",$AZ34+$BI34+$BR34+$CA34+$CJ34,0) -> 0 | DE34: =IF($CP34="UNHESA",$BA34+$BJ34+$BS34+$CB34+$CK34,0) -> 0 | DF34: =IF($CP34="UNHESA",$BB34+$BK34+$BT34+$CC34+$CL34,0) -> 0 | DG34: =IF($CP34="UNHESA",$BC34+$BL34+$BU34+$CD34+$CM34,0) -> 0 | DH34: =SUM(CZ34:DG34)-DB34-DD34 -> 0 | DI34: =IF($CP34="UNHESA LIQUIDOS",$AV34+$BE34+$BN34+$BW34+$CF34,0) -> 0 | DJ34: =IF($CP34="CALIDUL",$AW34+$BF34+$BO34+$BX34+$CG34,0) -> 0 | DK34: =IF($CP34="CALIDUL",$AX34+$BG34+$BP34+$BY34+$CH34,0) -> 0 | DL34: =IF($CP34="CALIDUL",$AY34+$BH34+$BQ34+$BZ34+$CI34,0) -> 0 | DM34: =IF($CP34="CALIDUL",$AZ34+$BI34+$BR34+$CA34+$CJ34,0) -> 0 | DN34: =IF($CP34="CALIDUL",$BA34+$BJ34+$BS34+$CB34+$CK34,0) -> 0 | DO34: =IF($CP34="CALIDUL",$BB34+$BK34+$BT34+$CC34+$CL34,0) -> 0 | DP34: =IF($CP34="CALIDUL",$BC34+$BL34+$BU34+$CD34+$CM34,0) -> 0 | DQ34: =SUM(DI34:DP34)-DK34-DM34 -> 0 | DR34: =IF($CP34="ECONACIONAL",$AV34+$BE34+$BN34+$BW34+$CF34,0) -> 0 | DS34: =IF($CP34="ECONACIONAL",$AW34+$BF34+$BO34+$BX34+$CG34,0) -> 0 | DT34: =IF($CP34="ECONACIONAL",$AX34+$BG34+$BP34+$BY34+$CH34,0) -> 0 | DU34: =IF($CP34="ECONACIONAL",$AY34+$BH34+$BQ34+$BZ34+$CI34,0) -> 0 | DV34: =IF($CP34="ECONACIONAL",$AZ34+$BI34+$BR34+$CA34+$CJ34,0) -> 0 | DW34: =IF($CP34="ECONACIONAL",$BA34+$BJ34+$BS34+$CB34+$CK34,0) -> 0 | DX34: =IF($CP34="ECONACIONAL",$BB34+$BK34+$BT34+$CC34+$CL34,0) -> 0 | DY34: =IF($CP34="ECONACIONAL",$BC34+$BL34+$BU34+$CD34+$CM34,0) -> 0 | DZ34: =SUM(DR34:DY34)-DT34-DV34 -> 0 | EA34: =IF($CP34="CLEARTEC",$AV34+$BE34+$BN34+$BW34+$CF34,0) -> 0 | EB34: =IF($CP34="CLEARTEC",$AW34+$BF34+$BO34+$BX34+$CG34,0) -> 0 | EC34: =IF($CP34="CLEARTEC",$AX34+$BG34+$BP34+$BY34+$CH34,0) -> 0 | ED34: =IF($CP34="CLEARTEC",$AY34+$BH34+$BQ34+$BZ34+$CI34,0) -> 0 | EE34: =IF($CP34="CLEARTEC",$AZ34+$BI34+$BR34+$CA34+$CJ34,0) -> 0 | EF34: =IF($CP34="CLEARTEC",$BA34+$BJ34+$BS34+$CB34+$CK34,0) -> 0 | EG34: =IF($CP34="CLEARTEC",$BB34+$BK34+$BT34+$CC34+$CL34,0) -> 0 | EH34: =IF($CP34="CLEARTEC",$BC34+$BL34+$BU34+$CD34+$CM34,0) -> 0 | EI34: =SUM(EA34:EH34)-EC34-EE34 -> 0 | EP34: 50 | ET34: =+EO34+EP34+EQ34 -> 50 | EV34: =IF($H34<=15,EK34/2,EK34) -> 0 | EW34: =IF($H34<=15,EL34/2,EL34) -> 0 | EX34: =IF($H34<=15,EM34/2,EM34) -> 0 | EY34: =IF($H34<=15,EN34/2,EN34) -> 0 | EZ34: =IF($H34<=15,EO34/2,EO34) -> 0 | FA34: =IF($H34<=15,EP34/2,EP34) -> 50 | FB34: =IF($H34<=15,EQ34/2,EQ34) -> 0 | FC34: =IF($H34<=15,ER34/2,ER34) -> 0 | ... FE34: =IF($H34<=15,ET34/2,ET34) -> 50
A35: =+A34+1 -> #REF! | B35: Castañeda Osorio Estela Angelina | C35: Tesorera-Contador | D35: UNHESA | E35: 3250 | F35: 1750 | G35: =+E35+F35 -> 5000 | H35: 30 | I35: 0.45 | J35: 0.45 | K35: 0 | L35: 0.1 | M35: 0 | N35: =SUM(I35:M35) -> 1 | Q35: =($E35/30/8*1.5)*P35 -> 0 | S35: =($E35/30/8*2)*R35 -> 0 | U35: =($E35/30/8*1.5)*T35 -> 0 | W35: =($E35/30/8*2)*V35 -> 0 | Y35: =(($E35/30/8)*1.5)*X35 -> 0 | AA35: =(($E35/30/8)*2)*Z35 -> 0 | AC35: =(($E35/30/8)*1.5)*AB35 -> 0 | AE35: =(($E35/30/8)*2)*AD35 -> 0 | AG35: =(($E35/30/8)*1.5)*AF35 -> 0 | AI35: =(($E35/30/8)*2)*AH35 -> 0 | AV35: =((E35/30)*H35)*$I35 -> 1462.5 | AW35: =((F35/30)*H35)*$I35 -> 787.5 | AX35: =P35 -> 0 | AY35: =Q35 -> 0 | AZ35: =R35 -> 0 | BA35: =S35 -> 0 | BB35: =AJ35+AO35 -> 0 | BC35: =(AV35+AY35+BA35)*0.1267 -> 185.29875 | BD35: =SUM(AV35:BC35)-AX35-AZ35 -> 2435.2987 | BE35: =(($E35/30)*$H35)*$J35 -> 1462.5 | BF35: =(($F35/30)*$H35)*$J35 -> 787.5 | BG35: =T35 -> 0 | BH35: =U35 -> 0 | BI35: =V35 -> 0 | BJ35: =W35 -> 0 | BK35: =AK35+AP35 -> 0 | BL35: =(+BE35+BH35+BJ35+BK35)*0.1267 -> 185.29875 | BM35: =SUM(BE35:BL35)-BG35-BI35 -> 2435.2987 | BN35: =(($E35/30)*$H35)*$K35 -> 0 | BO35: =(($F35/30)*$H35)*$K35 -> 0 | BP35: =X35 -> 0 | BQ35: =Y35 -> 0 | BR35: =Z35 -> 0 | BS35: =AA35 -> 0 | BT35: =AL35+AQ35 -> 0 | BU35: =(BN35+BQ35+BS35)*0.1267 -> 0 | BV35: =SUM(BN35:BU35)-BP35-BR35 -> 0 | BW35: =(($E35/30)*$H35)*$L35 -> 325 | BX35: =(($F35/30)*$H35)*$L35 -> 175 | BY35: =AB35 -> 0 | BZ35: =AC35 -> 0 | CA35: =AD35 -> 0 | CB35: =AE35 -> 0 | CC35: =AM35+AR35 -> 0 | CD35: =(BW35+BZ35+CB35)*0.1267 -> 41.1775 | CE35: =SUM(BW35:CD35)-BY35-CA35 -> 541.1775 | CF35: =(($E35/30)*$H35)*M35 -> 0 | CG35: =(($F35/30)*$H35)*$M35 -> 0 | CH35: =+AF35 -> 0 | CI35: =AG35 -> 0 | CJ35: =AH35 -> 0 | CK35: =AI35 -> 0 | CL35: =AN35+AS35 -> 0 | CM35: =(CF35+CI35+CK35)*0.1267 -> 0 | CN35: =SUM(CF35:CM35)-CH35-CJ35 -> 0 | CP35: UNHESA | CQ35: =IF($CP35="PROQUIMA",$AV35+$BE35+$BN35+$BW35+$CF35,0) -> 0 | CR35: =IF($CP35="PROQUIMA",$AW35+$BF35+$BO35+$BX35+$CG35,0) -> 0 | CS35: =IF($CP35="PROQUIMA",$AX35+$BG35+$BP35+$BY35+$CH35,0) -> 0 | CT35: =IF($CP35="PROQUIMA",$AY35+$BH35+$BQ35+$BZ35+$CI35,0) -> 0 | CU35: =IF($CP35="PROQUIMA",$AZ35+$BI35+$BR35+$CA35+$CJ35,0) -> 0 | CV35: =IF($CP35="PROQUIMA",$BA35+$BJ35+$BS35+$CB35+$CK35,0) -> 0 | CW35: =IF($CP35="PROQUIMA",$BB35+$BK35+$BT35+$CC35+$CL35,0) -> 0 | CX35: =IF($CP35="PROQUIMA",$BC35+$BL35+$BU35+$CD35+CM35,0) -> 0 | CY35: =SUM(CQ35:CX35)-CS35-CU35 -> 0 | CZ35: =IF($CP35="UNHESA",$AV35+$BE35+$BN35+$BW35+$CF35,0) -> 3250 | DA35: =IF($CP35="UNHESA",$AW35+$BF35+$BO35+$BX35+$CG35,0) -> 1750 | DB35: =IF($CP35="UNHESA",$AX35+$BG35+$BP35+$BY35+$CH35,0) -> 0 | DC35: =IF($CP35="UNHESA",$AY35+$BH35+$BQ35+$BZ35+$CI35,0) -> 0 | DD35: =IF($CP35="UNHESA",$AZ35+$BI35+$BR35+$CA35+$CJ35,0) -> 0 | DE35: =IF($CP35="UNHESA",$BA35+$BJ35+$BS35+$CB35+$CK35,0) -> 0 | DF35: =IF($CP35="UNHESA",$BB35+$BK35+$BT35+$CC35+$CL35,0) -> 0 | DG35: =IF($CP35="UNHESA",$BC35+$BL35+$BU35+$CD35+$CM35,0) -> 411.775 | DH35: =SUM(CZ35:DG35)-DB35-DD35 -> 5411.775 | DI35: =IF($CP35="UNHESA LIQUIDOS",$AV35+$BE35+$BN35+$BW35+$CF35,0) -> 0 | DJ35: =IF($CP35="CALIDUL",$AW35+$BF35+$BO35+$BX35+$CG35,0) -> 0 | DK35: =IF($CP35="CALIDUL",$AX35+$BG35+$BP35+$BY35+$CH35,0) -> 0 | DL35: =IF($CP35="CALIDUL",$AY35+$BH35+$BQ35+$BZ35+$CI35,0) -> 0 | DM35: =IF($CP35="CALIDUL",$AZ35+$BI35+$BR35+$CA35+$CJ35,0) -> 0 | DN35: =IF($CP35="CALIDUL",$BA35+$BJ35+$BS35+$CB35+$CK35,0) -> 0 | DO35: =IF($CP35="CALIDUL",$BB35+$BK35+$BT35+$CC35+$CL35,0) -> 0 | DP35: =IF($CP35="CALIDUL",$BC35+$BL35+$BU35+$CD35+$CM35,0) -> 0 | DQ35: =SUM(DI35:DP35)-DK35-DM35 -> 0 | DR35: =IF($CP35="ECONACIONAL",$AV35+$BE35+$BN35+$BW35+$CF35,0) -> 0 | DS35: =IF($CP35="ECONACIONAL",$AW35+$BF35+$BO35+$BX35+$CG35,0) -> 0 | DT35: =IF($CP35="ECONACIONAL",$AX35+$BG35+$BP35+$BY35+$CH35,0) -> 0 | DU35: =IF($CP35="ECONACIONAL",$AY35+$BH35+$BQ35+$BZ35+$CI35,0) -> 0 | DV35: =IF($CP35="ECONACIONAL",$AZ35+$BI35+$BR35+$CA35+$CJ35,0) -> 0 | DW35: =IF($CP35="ECONACIONAL",$BA35+$BJ35+$BS35+$CB35+$CK35,0) -> 0 | DX35: =IF($CP35="ECONACIONAL",$BB35+$BK35+$BT35+$CC35+$CL35,0) -> 0 | DY35: =IF($CP35="ECONACIONAL",$BC35+$BL35+$BU35+$CD35+$CM35,0) -> 0 | DZ35: =SUM(DR35:DY35)-DT35-DV35 -> 0 | EA35: =IF($CP35="CLEARTEC",$AV35+$BE35+$BN35+$BW35+$CF35,0) -> 0 | EB35: =IF($CP35="CLEARTEC",$AW35+$BF35+$BO35+$BX35+$CG35,0) -> 0 | EC35: =IF($CP35="CLEARTEC",$AX35+$BG35+$BP35+$BY35+$CH35,0) -> 0 | ED35: =IF($CP35="CLEARTEC",$AY35+$BH35+$BQ35+$BZ35+$CI35,0) -> 0 | EE35: =IF($CP35="CLEARTEC",$AZ35+$BI35+$BR35+$CA35+$CJ35,0) -> 0 | EF35: =IF($CP35="CLEARTEC",$BA35+$BJ35+$BS35+$CB35+$CK35,0) -> 0 | EG35: =IF($CP35="CLEARTEC",$BB35+$BK35+$BT35+$CC35+$CL35,0) -> 0 | EH35: =IF($CP35="CLEARTEC",$BC35+$BL35+$BU35+$CD35+$CM35,0) -> 0 | EI35: =SUM(EA35:EH35)-EC35-EE35 -> 0 | EK35: 42.15 | EL35: 538.59 | EN35: =175.5+209.5 -> 385 | EP35: 50 | EQ35: 150 | ET35: =+EO35+EP35+EQ35 -> 200 | EV35: =IF($H35<=15,EK35/2,EK35) -> 42.15 | EW35: =IF($H35<=15,EL35/2,EL35) -> 538.59 | EX35: =IF($H35<=15,EM35/2,EM35) -> 0 | EY35: =IF($H35<=15,EN35/2,EN35) -> 385 | EZ35: =IF($H35<=15,EO35/2,EO35) -> 0 | FA35: =IF($H35<=15,EP35/2,EP35) -> 50 | FB35: =IF($H35<=15,EQ35/2,EQ35) -> 150 | FC35: =IF($H35<=15,ER35/2,ER35) -> 0 | ... FE35: =IF($H35<=15,ET35/2,ET35) -> 200 | FF35: 0.52 | FG35: 0.48 | FH35: 0 | FI35: 0 | FJ35: 0 | FK35: 1 | FL35: =+EP35-FA35 -> 0
A36: =+A35+1 -> #REF! | B36: Gómez Laparra Glenda Esmeralda | C36: Supervisor Contable | D36: PROQUIMA | E36: 3720 | F36: 2480 | G36: =+E36+F36 -> 6200 | H36: 30 | I36: 0.5 | J36: 0.5 | K36: 0 | L36: 0 | M36: 0 | N36: =SUM(I36:M36) -> 1 | Q36: =($E36/30/8*1.5)*P36 -> 0 | S36: =($E36/30/8*2)*R36 -> 0 | U36: =($E36/30/8*1.5)*T36 -> 0 | W36: =($E36/30/8*2)*V36 -> 0 | X36: 0 | Y36: =(($E36/30/8)*1.5)*X36 -> 0 | AA36: =(($E36/30/8)*2)*Z36 -> 0 | AC36: =(($E36/30/8)*1.5)*AB36 -> 0 | AE36: =(($E36/30/8)*2)*AD36 -> 0 | AG36: =(($E36/30/8)*1.5)*AF36 -> 0 | AI36: =(($E36/30/8)*2)*AH36 -> 0 | AV36: =((E36/30)*H36)*$I36 -> 1860 | AW36: =((F36/30)*H36)*$I36 -> 1240 | AX36: =P36 -> 0 | AY36: =Q36 -> 0 | AZ36: =R36 -> 0 | BA36: =S36 -> 0 | BB36: =AJ36+AO36 -> 0 | BC36: =(AV36+AY36+BA36)*0.1267 -> 235.662 | BD36: =SUM(AV36:BC36)-AX36-AZ36 -> 3335.662 | BE36: =(($E36/30)*$H36)*$J36 -> 1860 | BF36: =(($F36/30)*$H36)*$J36 -> 1240 | BG36: =T36 -> 0 | BH36: =U36 -> 0 | BI36: =V36 -> 0 | BJ36: =W36 -> 0 | BK36: =AK36+AP36 -> 0 | BL36: =(+BE36+BH36+BJ36+BK36)*0.1267 -> 235.662 | BM36: =SUM(BE36:BL36)-BG36-BI36 -> 3335.662 | BN36: =(($E36/30)*$H36)*$K36 -> 0 | BO36: =(($F36/30)*$H36)*$K36 -> 0 | BP36: =X36 -> 0 | BQ36: =Y36 -> 0 | BR36: =Z36 -> 0 | BS36: =AA36 -> 0 | BT36: =AL36+AQ36 -> 0 | BU36: =(BN36+BQ36+BS36)*0.1267 -> 0 | BV36: =SUM(BN36:BU36)-BP36-BR36 -> 0 | BW36: =(($E36/30)*$H36)*$L36 -> 0 | BX36: =(($F36/30)*$H36)*$L36 -> 0 | BY36: =AB36 -> 0 | BZ36: =AC36 -> 0 | CA36: =AD36 -> 0 | CB36: =AE36 -> 0 | CC36: =AM36+AR36 -> 0 | CD36: =(BW36+BZ36+CB36)*0.1267 -> 0 | CE36: =SUM(BW36:CD36)-BY36-CA36 -> 0 | CF36: =(($E36/30)*$H36)*M36 -> 0 | CG36: =(($F36/30)*$H36)*$M36 -> 0 | CH36: =+AF36 -> 0 | CI36: =AG36 -> 0 | CJ36: =AH36 -> 0 | CK36: =AI36 -> 0 | CL36: =AN36+AS36 -> 0 | CM36: =(CF36+CI36+CK36)*0.1267 -> 0 | CN36: =SUM(CF36:CM36)-CH36-CJ36 -> 0 | CP36: PROQUIMA | CQ36: =IF($CP36="PROQUIMA",$AV36+$BE36+$BN36+$BW36+$CF36,0) -> 3720 | CR36: =IF($CP36="PROQUIMA",$AW36+$BF36+$BO36+$BX36+$CG36,0) -> 2480 | CS36: =IF($CP36="PROQUIMA",$AX36+$BG36+$BP36+$BY36+$CH36,0) -> 0 | CT36: =IF($CP36="PROQUIMA",$AY36+$BH36+$BQ36+$BZ36+$CI36,0) -> 0 | CU36: =IF($CP36="PROQUIMA",$AZ36+$BI36+$BR36+$CA36+$CJ36,0) -> 0 | CV36: =IF($CP36="PROQUIMA",$BA36+$BJ36+$BS36+$CB36+$CK36,0) -> 0 | CW36: =IF($CP36="PROQUIMA",$BB36+$BK36+$BT36+$CC36+$CL36,0) -> 0 | CX36: =IF($CP36="PROQUIMA",$BC36+$BL36+$BU36+$CD36+CM36,0) -> 471.324 | CY36: =SUM(CQ36:CX36)-CS36-CU36 -> 6671.324 | CZ36: =IF($CP36="UNHESA",$AV36+$BE36+$BN36+$BW36+$CF36,0) -> 0 | DA36: =IF($CP36="UNHESA",$AW36+$BF36+$BO36+$BX36+$CG36,0) -> 0 | DB36: =IF($CP36="UNHESA",$AX36+$BG36+$BP36+$BY36+$CH36,0) -> 0 | DC36: =IF($CP36="UNHESA",$AY36+$BH36+$BQ36+$BZ36+$CI36,0) -> 0 | DD36: =IF($CP36="UNHESA",$AZ36+$BI36+$BR36+$CA36+$CJ36,0) -> 0 | DE36: =IF($CP36="UNHESA",$BA36+$BJ36+$BS36+$CB36+$CK36,0) -> 0 | DF36: =IF($CP36="UNHESA",$BB36+$BK36+$BT36+$CC36+$CL36,0) -> 0 | DG36: =IF($CP36="UNHESA",$BC36+$BL36+$BU36+$CD36+$CM36,0) -> 0 | DH36: =SUM(CZ36:DG36)-DB36-DD36 -> 0 | DI36: =IF($CP36="UNHESA LIQUIDOS",$AV36+$BE36+$BN36+$BW36+$CF36,0) -> 0 | DJ36: =IF($CP36="CALIDUL",$AW36+$BF36+$BO36+$BX36+$CG36,0) -> 0 | DK36: =IF($CP36="CALIDUL",$AX36+$BG36+$BP36+$BY36+$CH36,0) -> 0 | DL36: =IF($CP36="CALIDUL",$AY36+$BH36+$BQ36+$BZ36+$CI36,0) -> 0 | DM36: =IF($CP36="CALIDUL",$AZ36+$BI36+$BR36+$CA36+$CJ36,0) -> 0 | DN36: =IF($CP36="CALIDUL",$BA36+$BJ36+$BS36+$CB36+$CK36,0) -> 0 | DO36: =IF($CP36="CALIDUL",$BB36+$BK36+$BT36+$CC36+$CL36,0) -> 0 | DP36: =IF($CP36="CALIDUL",$BC36+$BL36+$BU36+$CD36+$CM36,0) -> 0 | DQ36: =SUM(DI36:DP36)-DK36-DM36 -> 0 | DR36: =IF($CP36="ECONACIONAL",$AV36+$BE36+$BN36+$BW36+$CF36,0) -> 0 | DS36: =IF($CP36="ECONACIONAL",$AW36+$BF36+$BO36+$BX36+$CG36,0) -> 0 | DT36: =IF($CP36="ECONACIONAL",$AX36+$BG36+$BP36+$BY36+$CH36,0) -> 0 | DU36: =IF($CP36="ECONACIONAL",$AY36+$BH36+$BQ36+$BZ36+$CI36,0) -> 0 | DV36: =IF($CP36="ECONACIONAL",$AZ36+$BI36+$BR36+$CA36+$CJ36,0) -> 0 | DW36: =IF($CP36="ECONACIONAL",$BA36+$BJ36+$BS36+$CB36+$CK36,0) -> 0 | DX36: =IF($CP36="ECONACIONAL",$BB36+$BK36+$BT36+$CC36+$CL36,0) -> 0 | DY36: =IF($CP36="ECONACIONAL",$BC36+$BL36+$BU36+$CD36+$CM36,0) -> 0 | DZ36: =SUM(DR36:DY36)-DT36-DV36 -> 0 | EA36: =IF($CP36="CLEARTEC",$AV36+$BE36+$BN36+$BW36+$CF36,0) -> 0 | EB36: =IF($CP36="CLEARTEC",$AW36+$BF36+$BO36+$BX36+$CG36,0) -> 0 | EC36: =IF($CP36="CLEARTEC",$AX36+$BG36+$BP36+$BY36+$CH36,0) -> 0 | ED36: =IF($CP36="CLEARTEC",$AY36+$BH36+$BQ36+$BZ36+$CI36,0) -> 0 | EE36: =IF($CP36="CLEARTEC",$AZ36+$BI36+$BR36+$CA36+$CJ36,0) -> 0 | EF36: =IF($CP36="CLEARTEC",$BA36+$BJ36+$BS36+$CB36+$CK36,0) -> 0 | EG36: =IF($CP36="CLEARTEC",$BB36+$BK36+$BT36+$CC36+$CL36,0) -> 0 | EH36: =IF($CP36="CLEARTEC",$BC36+$BL36+$BU36+$CD36+$CM36,0) -> 0 | EI36: =SUM(EA36:EH36)-EC36-EE36 -> 0 | EK36: 101.02 | EN36: =34+17 -> 51 | EP36: 75 | ET36: =+EO36+EP36+EQ36 -> 75 | EV36: =IF($H36<=15,EK36/2,EK36) -> 101.02 | EW36: =IF($H36<=15,EL36/2,EL36) -> 0 | EX36: =IF($H36<=15,EM36/2,EM36) -> 0 | EY36: =IF($H36<=15,EN36/2,EN36) -> 51 | EZ36: =IF($H36<=15,EO36/2,EO36) -> 0 | FA36: =IF($H36<=15,EP36/2,EP36) -> 75 | FB36: =IF($H36<=15,EQ36/2,EQ36) -> 0 | FC36: =IF($H36<=15,ER36/2,ER36) -> 0 | ... FE36: =IF($H36<=15,ET36/2,ET36) -> 75 | FF36: 1 | FG36: 0 | FH36: 0 | FI36: 0 | FJ36: 0 | FK36: 1 | FL36: =+EP36-FA36 -> 0
A37: =+A36+1 -> #REF! | B37: Hernandez Reyes Astrid Verenice | C37: Auxiliar Contable | D37: PROQUIMA | E37: 3166.38 | F37: 1233.62 | G37: =+E37+F37 -> 4400 | H37: 30 | I37: 1 | J37: 0 | K37: 0 | L37: 0 | M37: 0 | N37: =SUM(I37:M37) -> 1 | Q37: =($E37/30/8*1.5)*P37 -> 0 | S37: =($E37/30/8*2)*R37 -> 0 | U37: =($E37/30/8*1.5)*T37 -> 0 | W37: =($E37/30/8*2)*V37 -> 0 | X37: 0 | Y37: =(($E37/30/8)*1.5)*X37 -> 0 | AA37: =(($E37/30/8)*2)*Z37 -> 0 | AC37: =(($E37/30/8)*1.5)*AB37 -> 0 | AE37: =(($E37/30/8)*2)*AD37 -> 0 | AG37: =(($E37/30/8)*1.5)*AF37 -> 0 | AI37: =(($E37/30/8)*2)*AH37 -> 0 | AV37: =((E37/30)*H37)*$I37 -> 3166.38 | AW37: =((F37/30)*H37)*$I37 -> 1233.62 | AX37: =P37 -> 0 | AY37: =Q37 -> 0 | AZ37: =R37 -> 0 | BA37: =S37 -> 0 | BB37: =AJ37+AO37 -> 0 | BC37: =(AV37+AY37+BA37)*0.1267 -> 401.18035 | BD37: =SUM(AV37:BC37)-AX37-AZ37 -> 4801.1803 | BE37: =(($E37/30)*$H37)*$J37 -> 0 | BF37: =(($F37/30)*$H37)*$J37 -> 0 | BG37: =T37 -> 0 | BH37: =U37 -> 0 | BI37: =V37 -> 0 | BJ37: =W37 -> 0 | BK37: =AK37+AP37 -> 0 | BL37: =(+BE37+BH37+BJ37+BK37)*0.1267 -> 0 | BM37: =SUM(BE37:BL37)-BG37-BI37 -> 0 | BN37: =(($E37/30)*$H37)*$K37 -> 0 | BO37: =(($F37/30)*$H37)*$K37 -> 0 | BP37: =X37 -> 0 | BQ37: =Y37 -> 0 | BR37: =Z37 -> 0 | BS37: =AA37 -> 0 | BT37: =AL37+AQ37 -> 0 | BU37: =(BN37+BQ37+BS37)*0.1267 -> 0 | BV37: =SUM(BN37:BU37)-BP37-BR37 -> 0 | BW37: =(($E37/30)*$H37)*$L37 -> 0 | BX37: =(($F37/30)*$H37)*$L37 -> 0 | BY37: =AB37 -> 0 | BZ37: =AC37 -> 0 | CA37: =AD37 -> 0 | CB37: =AE37 -> 0 | CC37: =AM37+AR37 -> 0 | CD37: =(BW37+BZ37+CB37)*0.1267 -> 0 | CE37: =SUM(BW37:CD37)-BY37-CA37 -> 0 | CF37: =(($E37/30)*$H37)*M37 -> 0 | CG37: =(($F37/30)*$H37)*$M37 -> 0 | CH37: =+AF37 -> 0 | CI37: =AG37 -> 0 | CJ37: =AH37 -> 0 | CK37: =AI37 -> 0 | CL37: =AN37+AS37 -> 0 | CM37: =(CF37+CI37+CK37)*0.1267 -> 0 | CN37: =SUM(CF37:CM37)-CH37-CJ37 -> 0 | CP37: PROQUIMA | CQ37: =IF($CP37="PROQUIMA",$AV37+$BE37+$BN37+$BW37+$CF37,0) -> 3166.38 | CR37: =IF($CP37="PROQUIMA",$AW37+$BF37+$BO37+$BX37+$CG37,0) -> 1233.62 | CS37: =IF($CP37="PROQUIMA",$AX37+$BG37+$BP37+$BY37+$CH37,0) -> 0 | CT37: =IF($CP37="PROQUIMA",$AY37+$BH37+$BQ37+$BZ37+$CI37,0) -> 0 | CU37: =IF($CP37="PROQUIMA",$AZ37+$BI37+$BR37+$CA37+$CJ37,0) -> 0 | CV37: =IF($CP37="PROQUIMA",$BA37+$BJ37+$BS37+$CB37+$CK37,0) -> 0 | CW37: =IF($CP37="PROQUIMA",$BB37+$BK37+$BT37+$CC37+$CL37,0) -> 0 | CX37: =IF($CP37="PROQUIMA",$BC37+$BL37+$BU37+$CD37+CM37,0) -> 401.18035 | CY37: =SUM(CQ37:CX37)-CS37-CU37 -> 4801.1803 | CZ37: =IF($CP37="UNHESA",$AV37+$BE37+$BN37+$BW37+$CF37,0) -> 0 | DA37: =IF($CP37="UNHESA",$AW37+$BF37+$BO37+$BX37+$CG37,0) -> 0 | DB37: =IF($CP37="UNHESA",$AX37+$BG37+$BP37+$BY37+$CH37,0) -> 0 | DC37: =IF($CP37="UNHESA",$AY37+$BH37+$BQ37+$BZ37+$CI37,0) -> 0 | DD37: =IF($CP37="UNHESA",$AZ37+$BI37+$BR37+$CA37+$CJ37,0) -> 0 | DE37: =IF($CP37="UNHESA",$BA37+$BJ37+$BS37+$CB37+$CK37,0) -> 0 | DF37: =IF($CP37="UNHESA",$BB37+$BK37+$BT37+$CC37+$CL37,0) -> 0 | DG37: =IF($CP37="UNHESA",$BC37+$BL37+$BU37+$CD37+$CM37,0) -> 0 | DH37: =SUM(CZ37:DG37)-DB37-DD37 -> 0 | DI37: =IF($CP37="UNHESA LIQUIDOS",$AV37+$BE37+$BN37+$BW37+$CF37,0) -> 0 | DJ37: =IF($CP37="CALIDUL",$AW37+$BF37+$BO37+$BX37+$CG37,0) -> 0 | DK37: =IF($CP37="CALIDUL",$AX37+$BG37+$BP37+$BY37+$CH37,0) -> 0 | DL37: =IF($CP37="CALIDUL",$AY37+$BH37+$BQ37+$BZ37+$CI37,0) -> 0 | DM37: =IF($CP37="CALIDUL",$AZ37+$BI37+$BR37+$CA37+$CJ37,0) -> 0 | DN37: =IF($CP37="CALIDUL",$BA37+$BJ37+$BS37+$CB37+$CK37,0) -> 0 | DO37: =IF($CP37="CALIDUL",$BB37+$BK37+$BT37+$CC37+$CL37,0) -> 0 | DP37: =IF($CP37="CALIDUL",$BC37+$BL37+$BU37+$CD37+$CM37,0) -> 0 | DQ37: =SUM(DI37:DP37)-DK37-DM37 -> 0 | DR37: =IF($CP37="ECONACIONAL",$AV37+$BE37+$BN37+$BW37+$CF37,0) -> 0 | DS37: =IF($CP37="ECONACIONAL",$AW37+$BF37+$BO37+$BX37+$CG37,0) -> 0 | DT37: =IF($CP37="ECONACIONAL",$AX37+$BG37+$BP37+$BY37+$CH37,0) -> 0 | DU37: =IF($CP37="ECONACIONAL",$AY37+$BH37+$BQ37+$BZ37+$CI37,0) -> 0 | DV37: =IF($CP37="ECONACIONAL",$AZ37+$BI37+$BR37+$CA37+$CJ37,0) -> 0 | DW37: =IF($CP37="ECONACIONAL",$BA37+$BJ37+$BS37+$CB37+$CK37,0) -> 0 | DX37: =IF($CP37="ECONACIONAL",$BB37+$BK37+$BT37+$CC37+$CL37,0) -> 0 | DY37: =IF($CP37="ECONACIONAL",$BC37+$BL37+$BU37+$CD37+$CM37,0) -> 0 | DZ37: =SUM(DR37:DY37)-DT37-DV37 -> 0 | EA37: =IF($CP37="CLEARTEC",$AV37+$BE37+$BN37+$BW37+$CF37,0) -> 0 | EB37: =IF($CP37="CLEARTEC",$AW37+$BF37+$BO37+$BX37+$CG37,0) -> 0 | EC37: =IF($CP37="CLEARTEC",$AX37+$BG37+$BP37+$BY37+$CH37,0) -> 0 | ED37: =IF($CP37="CLEARTEC",$AY37+$BH37+$BQ37+$BZ37+$CI37,0) -> 0 | EE37: =IF($CP37="CLEARTEC",$AZ37+$BI37+$BR37+$CA37+$CJ37,0) -> 0 | EF37: =IF($CP37="CLEARTEC",$BA37+$BJ37+$BS37+$CB37+$CK37,0) -> 0 | EG37: =IF($CP37="CLEARTEC",$BB37+$BK37+$BT37+$CC37+$CL37,0) -> 0 | EH37: =IF($CP37="CLEARTEC",$BC37+$BL37+$BU37+$CD37+$CM37,0) -> 0 | EI37: =SUM(EA37:EH37)-EC37-EE37 -> 0 | EK37: 12.35 | EP37: 50 | ET37: =+EO37+EP37+EQ37 -> 50 | EV37: =IF($H37<=15,EK37/2,EK37) -> 12.35 | EW37: =IF($H37<=15,EL37/2,EL37) -> 0 | EX37: =IF($H37<=15,EM37/2,EM37) -> 0 | EY37: =IF($H37<=15,EN37/2,EN37) -> 0 | EZ37: =IF($H37<=15,EO37/2,EO37) -> 0 | FA37: =IF($H37<=15,EP37/2,EP37) -> 50 | FB37: =IF($H37<=15,EQ37/2,EQ37) -> 0 | FC37: =IF($H37<=15,ER37/2,ER37) -> 0 | ... FE37: =IF($H37<=15,ET37/2,ET37) -> 50
A38: =+A37+1 -> #REF! | B38: Cruz Salguero Aramis Antonio | C38: Auxiliar Contable | D38: UNHESA | E38: 3166.38 | F38: 833.62 | G38: =+E38+F38 -> 4000 | H38: 30 | I38: 0 | J38: 1 | K38: 0 | L38: 0 | M38: 0 | N38: =SUM(I38:M38) -> 1 | O38: INCREMENTO | Q38: =($E38/30/8*1.5)*P38 -> 0 | S38: =($E38/30/8*2)*R38 -> 0 | U38: =($E38/30/8*1.5)*T38 -> 0 | W38: =($E38/30/8*2)*V38 -> 0 | X38: 0 | Y38: =(($E38/30/8)*1.5)*X38 -> 0 | AA38: =(($E38/30/8)*2)*Z38 -> 0 | AC38: =(($E38/30/8)*1.5)*AB38 -> 0 | AE38: =(($E38/30/8)*2)*AD38 -> 0 | AG38: =(($E38/30/8)*1.5)*AF38 -> 0 | AI38: =(($E38/30/8)*2)*AH38 -> 0 | AV38: =((E38/30)*H38)*$I38 -> 0 | AW38: =((F38/30)*H38)*$I38 -> 0 | AX38: =P38 -> 0 | AY38: =Q38 -> 0 | AZ38: =R38 -> 0 | BA38: =S38 -> 0 | BB38: =AJ38+AO38 -> 0 | BC38: =(AV38+AY38+BA38)*0.1267 -> 0 | BD38: =SUM(AV38:BC38)-AX38-AZ38 -> 0 | BE38: =(($E38/30)*$H38)*$J38 -> 3166.38 | BF38: =(($F38/30)*$H38)*$J38 -> 833.62 | BG38: =T38 -> 0 | BH38: =U38 -> 0 | BI38: =V38 -> 0 | BJ38: =W38 -> 0 | BK38: =AK38+AP38 -> 0 | BL38: =(+BE38+BH38+BJ38+BK38)*0.1267 -> 401.18035 | BM38: =SUM(BE38:BL38)-BG38-BI38 -> 4401.1803 | BN38: =(($E38/30)*$H38)*$K38 -> 0 | BO38: =(($F38/30)*$H38)*$K38 -> 0 | BP38: =X38 -> 0 | BQ38: =Y38 -> 0 | BR38: =Z38 -> 0 | BS38: =AA38 -> 0 | BT38: =AL38+AQ38 -> 0 | BU38: =(BN38+BQ38+BS38)*0.1267 -> 0 | BV38: =SUM(BN38:BU38)-BP38-BR38 -> 0 | BW38: =(($E38/30)*$H38)*$L38 -> 0 | BX38: =(($F38/30)*$H38)*$L38 -> 0 | BY38: =AB38 -> 0 | BZ38: =AC38 -> 0 | CA38: =AD38 -> 0 | CB38: =AE38 -> 0 | CC38: =AM38+AR38 -> 0 | CD38: =(BW38+BZ38+CB38)*0.1267 -> 0 | CE38: =SUM(BW38:CD38)-BY38-CA38 -> 0 | CF38: =(($E38/30)*$H38)*M38 -> 0 | CG38: =(($F38/30)*$H38)*$M38 -> 0 | CH38: =+AF38 -> 0 | CI38: =AG38 -> 0 | CJ38: =AH38 -> 0 | CK38: =AI38 -> 0 | CL38: =AN38+AS38 -> 0 | CM38: =(CF38+CI38+CK38)*0.1267 -> 0 | CN38: =SUM(CF38:CM38)-CH38-CJ38 -> 0 | CP38: UNHESA | CQ38: =IF($CP38="PROQUIMA",$AV38+$BE38+$BN38+$BW38+$CF38,0) -> 0 | CR38: =IF($CP38="PROQUIMA",$AW38+$BF38+$BO38+$BX38+$CG38,0) -> 0 | CS38: =IF($CP38="PROQUIMA",$AX38+$BG38+$BP38+$BY38+$CH38,0) -> 0 | CT38: =IF($CP38="PROQUIMA",$AY38+$BH38+$BQ38+$BZ38+$CI38,0) -> 0 | CU38: =IF($CP38="PROQUIMA",$AZ38+$BI38+$BR38+$CA38+$CJ38,0) -> 0 | CV38: =IF($CP38="PROQUIMA",$BA38+$BJ38+$BS38+$CB38+$CK38,0) -> 0 | CW38: =IF($CP38="PROQUIMA",$BB38+$BK38+$BT38+$CC38+$CL38,0) -> 0 | CX38: =IF($CP38="PROQUIMA",$BC38+$BL38+$BU38+$CD38+CM38,0) -> 0 | CY38: =SUM(CQ38:CX38)-CS38-CU38 -> 0 | CZ38: =IF($CP38="UNHESA",$AV38+$BE38+$BN38+$BW38+$CF38,0) -> 3166.38 | DA38: =IF($CP38="UNHESA",$AW38+$BF38+$BO38+$BX38+$CG38,0) -> 833.62 | DB38: =IF($CP38="UNHESA",$AX38+$BG38+$BP38+$BY38+$CH38,0) -> 0 | DC38: =IF($CP38="UNHESA",$AY38+$BH38+$BQ38+$BZ38+$CI38,0) -> 0 | DD38: =IF($CP38="UNHESA",$AZ38+$BI38+$BR38+$CA38+$CJ38,0) -> 0 | DE38: =IF($CP38="UNHESA",$BA38+$BJ38+$BS38+$CB38+$CK38,0) -> 0 | DF38: =IF($CP38="UNHESA",$BB38+$BK38+$BT38+$CC38+$CL38,0) -> 0 | DG38: =IF($CP38="UNHESA",$BC38+$BL38+$BU38+$CD38+$CM38,0) -> 401.18035 | DH38: =SUM(CZ38:DG38)-DB38-DD38 -> 4401.1803 | DI38: =IF($CP38="UNHESA LIQUIDOS",$AV38+$BE38+$BN38+$BW38+$CF38,0) -> 0 | DJ38: =IF($CP38="CALIDUL",$AW38+$BF38+$BO38+$BX38+$CG38,0) -> 0 | DK38: =IF($CP38="CALIDUL",$AX38+$BG38+$BP38+$BY38+$CH38,0) -> 0 | DL38: =IF($CP38="CALIDUL",$AY38+$BH38+$BQ38+$BZ38+$CI38,0) -> 0 | DM38: =IF($CP38="CALIDUL",$AZ38+$BI38+$BR38+$CA38+$CJ38,0) -> 0 | DN38: =IF($CP38="CALIDUL",$BA38+$BJ38+$BS38+$CB38+$CK38,0) -> 0 | DO38: =IF($CP38="CALIDUL",$BB38+$BK38+$BT38+$CC38+$CL38,0) -> 0 | DP38: =IF($CP38="CALIDUL",$BC38+$BL38+$BU38+$CD38+$CM38,0) -> 0 | DQ38: =SUM(DI38:DP38)-DK38-DM38 -> 0 | DR38: =IF($CP38="ECONACIONAL",$AV38+$BE38+$BN38+$BW38+$CF38,0) -> 0 | DS38: =IF($CP38="ECONACIONAL",$AW38+$BF38+$BO38+$BX38+$CG38,0) -> 0 | DT38: =IF($CP38="ECONACIONAL",$AX38+$BG38+$BP38+$BY38+$CH38,0) -> 0 | DU38: =IF($CP38="ECONACIONAL",$AY38+$BH38+$BQ38+$BZ38+$CI38,0) -> 0 | DV38: =IF($CP38="ECONACIONAL",$AZ38+$BI38+$BR38+$CA38+$CJ38,0) -> 0 | DW38: =IF($CP38="ECONACIONAL",$BA38+$BJ38+$BS38+$CB38+$CK38,0) -> 0 | DX38: =IF($CP38="ECONACIONAL",$BB38+$BK38+$BT38+$CC38+$CL38,0) -> 0 | DY38: =IF($CP38="ECONACIONAL",$BC38+$BL38+$BU38+$CD38+$CM38,0) -> 0 | DZ38: =SUM(DR38:DY38)-DT38-DV38 -> 0 | EA38: =IF($CP38="CLEARTEC",$AV38+$BE38+$BN38+$BW38+$CF38,0) -> 0 | EB38: =IF($CP38="CLEARTEC",$AW38+$BF38+$BO38+$BX38+$CG38,0) -> 0 | EC38: =IF($CP38="CLEARTEC",$AX38+$BG38+$BP38+$BY38+$CH38,0) -> 0 | ED38: =IF($CP38="CLEARTEC",$AY38+$BH38+$BQ38+$BZ38+$CI38,0) -> 0 | EE38: =IF($CP38="CLEARTEC",$AZ38+$BI38+$BR38+$CA38+$CJ38,0) -> 0 | EF38: =IF($CP38="CLEARTEC",$BA38+$BJ38+$BS38+$CB38+$CK38,0) -> 0 | EG38: =IF($CP38="CLEARTEC",$BB38+$BK38+$BT38+$CC38+$CL38,0) -> 0 | EH38: =IF($CP38="CLEARTEC",$BC38+$BL38+$BU38+$CD38+$CM38,0) -> 0 | EI38: =SUM(EA38:EH38)-EC38-EE38 -> 0 | EP38: 50 | ET38: =+EO38+EP38+EQ38 -> 50 | EV38: =IF($H38<=15,EK38/2,EK38) -> 0 | EW38: =IF($H38<=15,EL38/2,EL38) -> 0 | EX38: =IF($H38<=15,EM38/2,EM38) -> 0 | EY38: =IF($H38<=15,EN38/2,EN38) -> 0 | EZ38: =IF($H38<=15,EO38/2,EO38) -> 0 | FA38: =IF($H38<=15,EP38/2,EP38) -> 50 | FB38: =IF($H38<=15,EQ38/2,EQ38) -> 0 | FC38: =IF($H38<=15,ER38/2,ER38) -> 0 | ... FE38: =IF($H38<=15,ET38/2,ET38) -> 50
A39: =+A38+1 -> #REF! | B39: Chavez Garcia Benner Amilcar | C39: Auxiliar Contable | D39: UNHESA | E39: 3166.38 | F39: 740.76 | G39: =+E39+F39 -> 3907.14 | H39: 30 | I39: 0.5 | J39: 0.5 | K39: 0 | L39: 0 | M39: 0 | N39: =SUM(I39:M39) -> 1 | Q39: =($E39/30/8*1.5)*P39 -> 0 | S39: =($E39/30/8*2)*R39 -> 0 | U39: =($E39/30/8*1.5)*T39 -> 0 | W39: =($E39/30/8*2)*V39 -> 0 | X39: 0 | Y39: =(($E39/30/8)*1.5)*X39 -> 0 | AA39: =(($E39/30/8)*2)*Z39 -> 0 | AC39: =(($E39/30/8)*1.5)*AB39 -> 0 | AE39: =(($E39/30/8)*2)*AD39 -> 0 | AG39: =(($E39/30/8)*1.5)*AF39 -> 0 | AI39: =(($E39/30/8)*2)*AH39 -> 0 | AV39: =((E39/30)*H39)*$I39 -> 1583.19 | AW39: =((F39/30)*H39)*$I39 -> 370.38 | AX39: =P39 -> 0 | AY39: =Q39 -> 0 | AZ39: =R39 -> 0 | BA39: =S39 -> 0 | BB39: =AJ39+AO39 -> 0 | BC39: =(AV39+AY39+BA39)*0.1267 -> 200.59017 | BD39: =SUM(AV39:BC39)-AX39-AZ39 -> 2154.1602 | BE39: =(($E39/30)*$H39)*$J39 -> 1583.19 | BF39: =(($F39/30)*$H39)*$J39 -> 370.38 | BG39: =T39 -> 0 | BH39: =U39 -> 0 | BI39: =V39 -> 0 | BJ39: =W39 -> 0 | BK39: =AK39+AP39 -> 0 | BL39: =(+BE39+BH39+BJ39+BK39)*0.1267 -> 200.59017 | BM39: =SUM(BE39:BL39)-BG39-BI39 -> 2154.1602 | BN39: =(($E39/30)*$H39)*$K39 -> 0 | BO39: =(($F39/30)*$H39)*$K39 -> 0 | BP39: =X39 -> 0 | BQ39: =Y39 -> 0 | BR39: =Z39 -> 0 | BS39: =AA39 -> 0 | BT39: =AL39+AQ39 -> 0 | BU39: =(BN39+BQ39+BS39)*0.1267 -> 0 | BV39: =SUM(BN39:BU39)-BP39-BR39 -> 0 | BW39: =(($E39/30)*$H39)*$L39 -> 0 | BX39: =(($F39/30)*$H39)*$L39 -> 0 | BY39: =AB39 -> 0 | BZ39: =AC39 -> 0 | CA39: =AD39 -> 0 | CB39: =AE39 -> 0 | CC39: =AM39+AR39 -> 0 | CD39: =(BW39+BZ39+CB39)*0.1267 -> 0 | CE39: =SUM(BW39:CD39)-BY39-CA39 -> 0 | CF39: =(($E39/30)*$H39)*M39 -> 0 | CG39: =(($F39/30)*$H39)*$M39 -> 0 | CH39: =+AF39 -> 0 | CI39: =AG39 -> 0 | CJ39: =AH39 -> 0 | CK39: =AI39 -> 0 | CL39: =AN39+AS39 -> 0 | CM39: =(CF39+CI39+CK39)*0.1267 -> 0 | CN39: =SUM(CF39:CM39)-CH39-CJ39 -> 0 | CP39: UNHESA | CQ39: =IF($CP39="PROQUIMA",$AV39+$BE39+$BN39+$BW39+$CF39,0) -> 0 | CR39: =IF($CP39="PROQUIMA",$AW39+$BF39+$BO39+$BX39+$CG39,0) -> 0 | CS39: =IF($CP39="PROQUIMA",$AX39+$BG39+$BP39+$BY39+$CH39,0) -> 0 | CT39: =IF($CP39="PROQUIMA",$AY39+$BH39+$BQ39+$BZ39+$CI39,0) -> 0 | CU39: =IF($CP39="PROQUIMA",$AZ39+$BI39+$BR39+$CA39+$CJ39,0) -> 0 | CV39: =IF($CP39="PROQUIMA",$BA39+$BJ39+$BS39+$CB39+$CK39,0) -> 0 | CW39: =IF($CP39="PROQUIMA",$BB39+$BK39+$BT39+$CC39+$CL39,0) -> 0 | CX39: =IF($CP39="PROQUIMA",$BC39+$BL39+$BU39+$CD39+CM39,0) -> 0 | CY39: =SUM(CQ39:CX39)-CS39-CU39 -> 0 | CZ39: =IF($CP39="UNHESA",$AV39+$BE39+$BN39+$BW39+$CF39,0) -> 3166.38 | DA39: =IF($CP39="UNHESA",$AW39+$BF39+$BO39+$BX39+$CG39,0) -> 740.76 | DB39: =IF($CP39="UNHESA",$AX39+$BG39+$BP39+$BY39+$CH39,0) -> 0 | DC39: =IF($CP39="UNHESA",$AY39+$BH39+$BQ39+$BZ39+$CI39,0) -> 0 | DD39: =IF($CP39="UNHESA",$AZ39+$BI39+$BR39+$CA39+$CJ39,0) -> 0 | DE39: =IF($CP39="UNHESA",$BA39+$BJ39+$BS39+$CB39+$CK39,0) -> 0 | DF39: =IF($CP39="UNHESA",$BB39+$BK39+$BT39+$CC39+$CL39,0) -> 0 | DG39: =IF($CP39="UNHESA",$BC39+$BL39+$BU39+$CD39+$CM39,0) -> 401.18035 | DH39: =SUM(CZ39:DG39)-DB39-DD39 -> 4308.3203 | DI39: =IF($CP39="UNHESA LIQUIDOS",$AV39+$BE39+$BN39+$BW39+$CF39,0) -> 0 | DJ39: =IF($CP39="CALIDUL",$AW39+$BF39+$BO39+$BX39+$CG39,0) -> 0 | DK39: =IF($CP39="CALIDUL",$AX39+$BG39+$BP39+$BY39+$CH39,0) -> 0 | DL39: =IF($CP39="CALIDUL",$AY39+$BH39+$BQ39+$BZ39+$CI39,0) -> 0 | DM39: =IF($CP39="CALIDUL",$AZ39+$BI39+$BR39+$CA39+$CJ39,0) -> 0 | DN39: =IF($CP39="CALIDUL",$BA39+$BJ39+$BS39+$CB39+$CK39,0) -> 0 | DO39: =IF($CP39="CALIDUL",$BB39+$BK39+$BT39+$CC39+$CL39,0) -> 0 | DP39: =IF($CP39="CALIDUL",$BC39+$BL39+$BU39+$CD39+$CM39,0) -> 0 | DQ39: =SUM(DI39:DP39)-DK39-DM39 -> 0 | DR39: =IF($CP39="ECONACIONAL",$AV39+$BE39+$BN39+$BW39+$CF39,0) -> 0 | DS39: =IF($CP39="ECONACIONAL",$AW39+$BF39+$BO39+$BX39+$CG39,0) -> 0 | DT39: =IF($CP39="ECONACIONAL",$AX39+$BG39+$BP39+$BY39+$CH39,0) -> 0 | DU39: =IF($CP39="ECONACIONAL",$AY39+$BH39+$BQ39+$BZ39+$CI39,0) -> 0 | DV39: =IF($CP39="ECONACIONAL",$AZ39+$BI39+$BR39+$CA39+$CJ39,0) -> 0 | DW39: =IF($CP39="ECONACIONAL",$BA39+$BJ39+$BS39+$CB39+$CK39,0) -> 0 | DX39: =IF($CP39="ECONACIONAL",$BB39+$BK39+$BT39+$CC39+$CL39,0) -> 0 | DY39: =IF($CP39="ECONACIONAL",$BC39+$BL39+$BU39+$CD39+$CM39,0) -> 0 | DZ39: =SUM(DR39:DY39)-DT39-DV39 -> 0 | EA39: =IF($CP39="CLEARTEC",$AV39+$BE39+$BN39+$BW39+$CF39,0) -> 0 | EB39: =IF($CP39="CLEARTEC",$AW39+$BF39+$BO39+$BX39+$CG39,0) -> 0 | EC39: =IF($CP39="CLEARTEC",$AX39+$BG39+$BP39+$BY39+$CH39,0) -> 0 | ED39: =IF($CP39="CLEARTEC",$AY39+$BH39+$BQ39+$BZ39+$CI39,0) -> 0 | EE39: =IF($CP39="CLEARTEC",$AZ39+$BI39+$BR39+$CA39+$CJ39,0) -> 0 | EF39: =IF($CP39="CLEARTEC",$BA39+$BJ39+$BS39+$CB39+$CK39,0) -> 0 | EG39: =IF($CP39="CLEARTEC",$BB39+$BK39+$BT39+$CC39+$CL39,0) -> 0 | EH39: =IF($CP39="CLEARTEC",$BC39+$BL39+$BU39+$CD39+$CM39,0) -> 0 | EI39: =SUM(EA39:EH39)-EC39-EE39 -> 0 | EN39: =172+266 -> 438 | EP39: 50 | EQ39: 75 | ET39: =+EO39+EP39+EQ39 -> 125 | EV39: =IF($H39<=15,EK39/2,EK39) -> 0 | EW39: =IF($H39<=15,EL39/2,EL39) -> 0 | EX39: =IF($H39<=15,EM39/2,EM39) -> 0 | EY39: =IF($H39<=15,EN39/2,EN39) -> 438 | EZ39: =IF($H39<=15,EO39/2,EO39) -> 0 | FA39: =IF($H39<=15,EP39/2,EP39) -> 50 | FB39: =IF($H39<=15,EQ39/2,EQ39) -> 75 | FC39: =IF($H39<=15,ER39/2,ER39) -> 0 | ... FE39: =IF($H39<=15,ET39/2,ET39) -> 125 | FF39: 0.5 | FG39: 0.5 | FH39: 0 | FI39: 0 | FJ39: 0 | FK39: 1 | FL39: =+EP39-FA39 -> 0
A40: =+A39+1 -> #REF! | B40: Mendez Cruz Walter Emilio | C40: Auditor interno | D40: PROQUIMA | E40: 6000 | F40: 4000 | G40: =+E40+F40 -> 10000 | H40: 30 | I40: 0.65 | J40: 0.35 | K40: 0 | L40: 0 | M40: 0 | N40: =SUM(I40:M40) -> 1 | Q40: =($E40/30/8*1.5)*P40 -> 0 | S40: =($E40/30/8*2)*R40 -> 0 | U40: =($E40/30/8*1.5)*T40 -> 0 | W40: =($E40/30/8*2)*V40 -> 0 | Y40: =(($E40/30/8)*1.5)*X40 -> 0 | AA40: =(($E40/30/8)*2)*Z40 -> 0 | AC40: =(($E40/30/8)*1.5)*AB40 -> 0 | AE40: =(($E40/30/8)*2)*AD40 -> 0 | AG40: =(($E40/30/8)*1.5)*AF40 -> 0 | AI40: =(($E40/30/8)*2)*AH40 -> 0 | AV40: =((E40/30)*H40)*$I40 -> 3900 | AW40: =((F40/30)*H40)*$I40 -> 2600 | AX40: =P40 -> 0 | AY40: =Q40 -> 0 | AZ40: =R40 -> 0 | BA40: =S40 -> 0 | BB40: =AJ40+AO40 -> 0 | BC40: =(AV40+AY40+BA40)*0.1267 -> 494.13 | BD40: =SUM(AV40:BC40)-AX40-AZ40 -> 6994.13 | BE40: =(($E40/30)*$H40)*$J40 -> 2100 | BF40: =(($F40/30)*$H40)*$J40 -> 1400 | BG40: =T40 -> 0 | BH40: =U40 -> 0 | BI40: =V40 -> 0 | BJ40: =W40 -> 0 | BK40: =AK40+AP40 -> 0 | BL40: =(+BE40+BH40+BJ40+BK40)*0.1267 -> 266.07 | BM40: =SUM(BE40:BL40)-BG40-BI40 -> 3766.07 | BN40: =(($E40/30)*$H40)*$K40 -> 0 | BO40: =(($F40/30)*$H40)*$K40 -> 0 | BP40: =X40 -> 0 | BQ40: =Y40 -> 0 | BR40: =Z40 -> 0 | BS40: =AA40 -> 0 | BT40: =AL40+AQ40 -> 0 | BU40: =(BN40+BQ40+BS40)*0.1267 -> 0 | BV40: =SUM(BN40:BU40)-BP40-BR40 -> 0 | BW40: =(($E40/30)*$H40)*$L40 -> 0 | BX40: =(($F40/30)*$H40)*$L40 -> 0 | BY40: =AB40 -> 0 | BZ40: =AC40 -> 0 | CA40: =AD40 -> 0 | CB40: =AE40 -> 0 | CC40: =AM40+AR40 -> 0 | CD40: =(BW40+BZ40+CB40)*0.1267 -> 0 | CE40: =SUM(BW40:CD40)-BY40-CA40 -> 0 | CF40: =(($E40/30)*$H40)*M40 -> 0 | CG40: =(($F40/30)*$H40)*$M40 -> 0 | CH40: =+AF40 -> 0 | CI40: =AG40 -> 0 | CJ40: =AH40 -> 0 | CK40: =AI40 -> 0 | CL40: =AN40+AS40 -> 0 | CM40: =(CF40+CI40+CK40)*0.1267 -> 0 | CN40: =SUM(CF40:CM40)-CH40-CJ40 -> 0 | CP40: PROQUIMA | CQ40: =IF($CP40="PROQUIMA",$AV40+$BE40+$BN40+$BW40+$CF40,0) -> 6000 | CR40: =IF($CP40="PROQUIMA",$AW40+$BF40+$BO40+$BX40+$CG40,0) -> 4000 | CS40: =IF($CP40="PROQUIMA",$AX40+$BG40+$BP40+$BY40+$CH40,0) -> 0 | CT40: =IF($CP40="PROQUIMA",$AY40+$BH40+$BQ40+$BZ40+$CI40,0) -> 0 | CU40: =IF($CP40="PROQUIMA",$AZ40+$BI40+$BR40+$CA40+$CJ40,0) -> 0 | CV40: =IF($CP40="PROQUIMA",$BA40+$BJ40+$BS40+$CB40+$CK40,0) -> 0 | CW40: =IF($CP40="PROQUIMA",$BB40+$BK40+$BT40+$CC40+$CL40,0) -> 0 | CX40: =IF($CP40="PROQUIMA",$BC40+$BL40+$BU40+$CD40+CM40,0) -> 760.2 | CY40: =SUM(CQ40:CX40)-CS40-CU40 -> 10760.2 | CZ40: =IF($CP40="UNHESA",$AV40+$BE40+$BN40+$BW40+$CF40,0) -> 0 | DA40: =IF($CP40="UNHESA",$AW40+$BF40+$BO40+$BX40+$CG40,0) -> 0 | DB40: =IF($CP40="UNHESA",$AX40+$BG40+$BP40+$BY40+$CH40,0) -> 0 | DC40: =IF($CP40="UNHESA",$AY40+$BH40+$BQ40+$BZ40+$CI40,0) -> 0 | DD40: =IF($CP40="UNHESA",$AZ40+$BI40+$BR40+$CA40+$CJ40,0) -> 0 | DE40: =IF($CP40="UNHESA",$BA40+$BJ40+$BS40+$CB40+$CK40,0) -> 0 | DF40: =IF($CP40="UNHESA",$BB40+$BK40+$BT40+$CC40+$CL40,0) -> 0 | DG40: =IF($CP40="UNHESA",$BC40+$BL40+$BU40+$CD40+$CM40,0) -> 0 | DH40: =SUM(CZ40:DG40)-DB40-DD40 -> 0 | DI40: =IF($CP40="UNHESA LIQUIDOS",$AV40+$BE40+$BN40+$BW40+$CF40,0) -> 0 | DJ40: =IF($CP40="CALIDUL",$AW40+$BF40+$BO40+$BX40+$CG40,0) -> 0 | DK40: =IF($CP40="CALIDUL",$AX40+$BG40+$BP40+$BY40+$CH40,0) -> 0 | DL40: =IF($CP40="CALIDUL",$AY40+$BH40+$BQ40+$BZ40+$CI40,0) -> 0 | DM40: =IF($CP40="CALIDUL",$AZ40+$BI40+$BR40+$CA40+$CJ40,0) -> 0 | DN40: =IF($CP40="CALIDUL",$BA40+$BJ40+$BS40+$CB40+$CK40,0) -> 0 | DO40: =IF($CP40="CALIDUL",$BB40+$BK40+$BT40+$CC40+$CL40,0) -> 0 | DP40: =IF($CP40="CALIDUL",$BC40+$BL40+$BU40+$CD40+$CM40,0) -> 0 | DQ40: =SUM(DI40:DP40)-DK40-DM40 -> 0 | DR40: =IF($CP40="ECONACIONAL",$AV40+$BE40+$BN40+$BW40+$CF40,0) -> 0 | DS40: =IF($CP40="ECONACIONAL",$AW40+$BF40+$BO40+$BX40+$CG40,0) -> 0 | DT40: =IF($CP40="ECONACIONAL",$AX40+$BG40+$BP40+$BY40+$CH40,0) -> 0 | DU40: =IF($CP40="ECONACIONAL",$AY40+$BH40+$BQ40+$BZ40+$CI40,0) -> 0 | DV40: =IF($CP40="ECONACIONAL",$AZ40+$BI40+$BR40+$CA40+$CJ40,0) -> 0 | DW40: =IF($CP40="ECONACIONAL",$BA40+$BJ40+$BS40+$CB40+$CK40,0) -> 0 | DX40: =IF($CP40="ECONACIONAL",$BB40+$BK40+$BT40+$CC40+$CL40,0) -> 0 | DY40: =IF($CP40="ECONACIONAL",$BC40+$BL40+$BU40+$CD40+$CM40,0) -> 0 | DZ40: =SUM(DR40:DY40)-DT40-DV40 -> 0 | EA40: =IF($CP40="CLEARTEC",$AV40+$BE40+$BN40+$BW40+$CF40,0) -> 0 | EB40: =IF($CP40="CLEARTEC",$AW40+$BF40+$BO40+$BX40+$CG40,0) -> 0 | EC40: =IF($CP40="CLEARTEC",$AX40+$BG40+$BP40+$BY40+$CH40,0) -> 0 | ED40: =IF($CP40="CLEARTEC",$AY40+$BH40+$BQ40+$BZ40+$CI40,0) -> 0 | EE40: =IF($CP40="CLEARTEC",$AZ40+$BI40+$BR40+$CA40+$CJ40,0) -> 0 | EF40: =IF($CP40="CLEARTEC",$BA40+$BJ40+$BS40+$CB40+$CK40,0) -> 0 | EG40: =IF($CP40="CLEARTEC",$BB40+$BK40+$BT40+$CC40+$CL40,0) -> 0 | EH40: =IF($CP40="CLEARTEC",$BC40+$BL40+$BU40+$CD40+$CM40,0) -> 0 | EI40: =SUM(EA40:EH40)-EC40-EE40 -> 0 | EK40: 285.51 | EP40: 100 | EQ40: =240 -> 240 | ET40: =+EO40+EP40+EQ40 -> 340 | EV40: =IF($H40<=15,EK40/2,EK40) -> 285.51 | EW40: =IF($H40<=15,EL40/2,EL40) -> 0 | EX40: =IF($H40<=15,EM40/2,EM40) -> 0 | EY40: =IF($H40<=15,EN40/2,EN40) -> 0 | EZ40: =IF($H40<=15,EO40/2,EO40) -> 0 | FA40: =IF($H40<=15,EP40/2,EP40) -> 100 | FB40: =IF($H40<=15,EQ40/2,EQ40) -> 240 | FC40: =IF($H40<=15,ER40/2,ER40) -> 0 | ... FE40: =IF($H40<=15,ET40/2,ET40) -> 340 | FF40: 0.75 | FG40: 0.25 | FH40: 0 | FI40: 0 | FJ40: 0 | FK40: 1 | FL40: =+EP40-FA40 -> 0
A41: =+A40+1 -> #REF! | B41: Lopez Teletor Josue Leonel | C41: Asistente de Auditoria Interna | D41: UNHESA | E41: 3750 | F41: 250 | G41: =+E41+F41 -> 4000 | H41: 30 | I41: 0.4 | J41: 0.6 | K41: 0 | L41: 0 | M41: 0 | N41: =SUM(I41:M41) -> 1 | Q41: =($E41/30/8*1.5)*P41 -> 0 | S41: =($E41/30/8*2)*R41 -> 0 | U41: =($E41/30/8*1.5)*T41 -> 0 | W41: =($E41/30/8*2)*V41 -> 0 | Y41: =(($E41/30/8)*1.5)*X41 -> 0 | AA41: =(($E41/30/8)*2)*Z41 -> 0 | AC41: =(($E41/30/8)*1.5)*AB41 -> 0 | AE41: =(($E41/30/8)*2)*AD41 -> 0 | AG41: =(($E41/30/8)*1.5)*AF41 -> 0 | AI41: =(($E41/30/8)*2)*AH41 -> 0 | AV41: =((E41/30)*H41)*$I41 -> 1500 | AW41: =((F41/30)*H41)*$I41 -> 100 | AX41: =P41 -> 0 | AY41: =Q41 -> 0 | AZ41: =R41 -> 0 | BA41: =S41 -> 0 | BB41: =AJ41+AO41 -> 0 | BC41: =(AV41+AY41+BA41)*0.1267 -> 190.05 | BD41: =SUM(AV41:BC41)-AX41-AZ41 -> 1790.05 | BE41: =(($E41/30)*$H41)*$J41 -> 2250 | BF41: =(($F41/30)*$H41)*$J41 -> 150 | BG41: =T41 -> 0 | BH41: =U41 -> 0 | BI41: =V41 -> 0 | BJ41: =W41 -> 0 | BK41: =AK41+AP41 -> 0 | BL41: =(+BE41+BH41+BJ41+BK41)*0.1267 -> 285.075 | BM41: =SUM(BE41:BL41)-BG41-BI41 -> 2685.075 | BN41: =(($E41/30)*$H41)*$K41 -> 0 | BO41: =(($F41/30)*$H41)*$K41 -> 0 | BP41: =X41 -> 0 | BQ41: =Y41 -> 0 | BR41: =Z41 -> 0 | BS41: =AA41 -> 0 | BT41: =AL41+AQ41 -> 0 | BU41: =(BN41+BQ41+BS41)*0.1267 -> 0 | BV41: =SUM(BN41:BU41)-BP41-BR41 -> 0 | BW41: =(($E41/30)*$H41)*$L41 -> 0 | BX41: =(($F41/30)*$H41)*$L41 -> 0 | BY41: =AB41 -> 0 | BZ41: =AC41 -> 0 | CA41: =AD41 -> 0 | CB41: =AE41 -> 0 | CC41: =AM41+AR41 -> 0 | CD41: =(BW41+BZ41+CB41)*0.1267 -> 0 | CE41: =SUM(BW41:CD41)-BY41-CA41 -> 0 | CF41: =(($E41/30)*$H41)*M41 -> 0 | CG41: =(($F41/30)*$H41)*$M41 -> 0 | CH41: =+AF41 -> 0 | CI41: =AG41 -> 0 | CJ41: =AH41 -> 0 | CK41: =AI41 -> 0 | CL41: =AN41+AS41 -> 0 | CM41: =(CF41+CI41+CK41)*0.1267 -> 0 | CN41: =SUM(CF41:CM41)-CH41-CJ41 -> 0 | CP41: UNHESA | CQ41: =IF($CP41="PROQUIMA",$AV41+$BE41+$BN41+$BW41+$CF41,0) -> 0 | CR41: =IF($CP41="PROQUIMA",$AW41+$BF41+$BO41+$BX41+$CG41,0) -> 0 | CS41: =IF($CP41="PROQUIMA",$AX41+$BG41+$BP41+$BY41+$CH41,0) -> 0 | CT41: =IF($CP41="PROQUIMA",$AY41+$BH41+$BQ41+$BZ41+$CI41,0) -> 0 | CU41: =IF($CP41="PROQUIMA",$AZ41+$BI41+$BR41+$CA41+$CJ41,0) -> 0 | CV41: =IF($CP41="PROQUIMA",$BA41+$BJ41+$BS41+$CB41+$CK41,0) -> 0 | CW41: =IF($CP41="PROQUIMA",$BB41+$BK41+$BT41+$CC41+$CL41,0) -> 0 | CX41: =IF($CP41="PROQUIMA",$BC41+$BL41+$BU41+$CD41+CM41,0) -> 0 | CY41: =SUM(CQ41:CX41)-CS41-CU41 -> 0 | CZ41: =IF($CP41="UNHESA",$AV41+$BE41+$BN41+$BW41+$CF41,0) -> 3750 | DA41: =IF($CP41="UNHESA",$AW41+$BF41+$BO41+$BX41+$CG41,0) -> 250 | DB41: =IF($CP41="UNHESA",$AX41+$BG41+$BP41+$BY41+$CH41,0) -> 0 | DC41: =IF($CP41="UNHESA",$AY41+$BH41+$BQ41+$BZ41+$CI41,0) -> 0 | DD41: =IF($CP41="UNHESA",$AZ41+$BI41+$BR41+$CA41+$CJ41,0) -> 0 | DE41: =IF($CP41="UNHESA",$BA41+$BJ41+$BS41+$CB41+$CK41,0) -> 0 | DF41: =IF($CP41="UNHESA",$BB41+$BK41+$BT41+$CC41+$CL41,0) -> 0 | DG41: =IF($CP41="UNHESA",$BC41+$BL41+$BU41+$CD41+$CM41,0) -> 475.125 | DH41: =SUM(CZ41:DG41)-DB41-DD41 -> 4475.125 | DI41: =IF($CP41="UNHESA LIQUIDOS",$AV41+$BE41+$BN41+$BW41+$CF41,0) -> 0 | DJ41: =IF($CP41="CALIDUL",$AW41+$BF41+$BO41+$BX41+$CG41,0) -> 0 | DK41: =IF($CP41="CALIDUL",$AX41+$BG41+$BP41+$BY41+$CH41,0) -> 0 | DL41: =IF($CP41="CALIDUL",$AY41+$BH41+$BQ41+$BZ41+$CI41,0) -> 0 | DM41: =IF($CP41="CALIDUL",$AZ41+$BI41+$BR41+$CA41+$CJ41,0) -> 0 | DN41: =IF($CP41="CALIDUL",$BA41+$BJ41+$BS41+$CB41+$CK41,0) -> 0 | DO41: =IF($CP41="CALIDUL",$BB41+$BK41+$BT41+$CC41+$CL41,0) -> 0 | DP41: =IF($CP41="CALIDUL",$BC41+$BL41+$BU41+$CD41+$CM41,0) -> 0 | DQ41: =SUM(DI41:DP41)-DK41-DM41 -> 0 | DR41: =IF($CP41="ECONACIONAL",$AV41+$BE41+$BN41+$BW41+$CF41,0) -> 0 | DS41: =IF($CP41="ECONACIONAL",$AW41+$BF41+$BO41+$BX41+$CG41,0) -> 0 | DT41: =IF($CP41="ECONACIONAL",$AX41+$BG41+$BP41+$BY41+$CH41,0) -> 0 | DU41: =IF($CP41="ECONACIONAL",$AY41+$BH41+$BQ41+$BZ41+$CI41,0) -> 0 | DV41: =IF($CP41="ECONACIONAL",$AZ41+$BI41+$BR41+$CA41+$CJ41,0) -> 0 | DW41: =IF($CP41="ECONACIONAL",$BA41+$BJ41+$BS41+$CB41+$CK41,0) -> 0 | DX41: =IF($CP41="ECONACIONAL",$BB41+$BK41+$BT41+$CC41+$CL41,0) -> 0 | DY41: =IF($CP41="ECONACIONAL",$BC41+$BL41+$BU41+$CD41+$CM41,0) -> 0 | DZ41: =SUM(DR41:DY41)-DT41-DV41 -> 0 | EA41: =IF($CP41="CLEARTEC",$AV41+$BE41+$BN41+$BW41+$CF41,0) -> 0 | EB41: =IF($CP41="CLEARTEC",$AW41+$BF41+$BO41+$BX41+$CG41,0) -> 0 | EC41: =IF($CP41="CLEARTEC",$AX41+$BG41+$BP41+$BY41+$CH41,0) -> 0 | ED41: =IF($CP41="CLEARTEC",$AY41+$BH41+$BQ41+$BZ41+$CI41,0) -> 0 | EE41: =IF($CP41="CLEARTEC",$AZ41+$BI41+$BR41+$CA41+$CJ41,0) -> 0 | EF41: =IF($CP41="CLEARTEC",$BA41+$BJ41+$BS41+$CB41+$CK41,0) -> 0 | EG41: =IF($CP41="CLEARTEC",$BB41+$BK41+$BT41+$CC41+$CL41,0) -> 0 | EH41: =IF($CP41="CLEARTEC",$BC41+$BL41+$BU41+$CD41+$CM41,0) -> 0 | EI41: =SUM(EA41:EH41)-EC41-EE41 -> 0 | EP41: 50 | ET41: =+EO41+EP41+EQ41 -> 50 | EV41: =IF($H41<=15,EK41/2,EK41) -> 0 | EW41: =IF($H41<=15,EL41/2,EL41) -> 0 | EX41: =IF($H41<=15,EM41/2,EM41) -> 0 | EY41: =IF($H41<=15,EN41/2,EN41) -> 0 | EZ41: =IF($H41<=15,EO41/2,EO41) -> 0 | FA41: =IF($H41<=15,EP41/2,EP41) -> 50 | FB41: =IF($H41<=15,EQ41/2,EQ41) -> 0 | FC41: =IF($H41<=15,ER41/2,ER41) -> 0 | ... FE41: =IF($H41<=15,ET41/2,ET41) -> 50
C42: Total Contabilidad y Finanzas | E42: =SUM(E31:E41) -> 62755.68 | F42: =SUM(F31:F41) -> 19945.7 | G42: =SUM(G31:G41) -> 82701.38 | P42: =SUM(P31:P41) -> 0 | Q42: =SUM(Q31:Q41) -> 0 | R42: =SUM(R31:R41) -> 0 | S42: =SUM(S31:S41) -> 0 | T42: =SUM(T31:T41) -> 0 | U42: =SUM(U31:U41) -> 0 | V42: =SUM(V31:V41) -> 0 | W42: =SUM(W31:W41) -> 0 | ... AA42: =SUM(AA31:AA41) -> 0 | AB42: =SUM(AB31:AB40) -> 0 | AC42: =SUM(AC31:AC40) -> 0 | AD42: =SUM(AD31:AD40) -> 0 | AE42: =SUM(AE31:AE40) -> 0 | AF42: =SUM(AF31:AF40) -> 0 | AG42: =SUM(AG31:AG40) -> 0 | AH42: =SUM(AH31:AH40) -> 0 | AI42: =SUM(AI31:AI40) -> 0 | ... AT42: =SUM(AT31:AT40) -> 0 | AV42: =SUM(AV31:AV41) -> 31263.513 | AW42: =SUM(AW31:AW41) -> 10389.965 | AX42: =SUM(AX31:AX41) -> 0 | AY42: =SUM(AY31:AY41) -> 0 | AZ42: =SUM(AZ31:AZ41) -> 0 | BA42: =SUM(BA31:BA41) -> 0 | BB42: =SUM(BB31:BB41) -> 0 | BC42: =SUM(BC31:BC41) -> 3961.0871 | ... CE42: =SUM(CE31:CE41) -> 10469.493 | CF42: =SUM(CF31:CF40) -> 0 | CG42: =SUM(CG31:CG40) -> 0 | CH42: =SUM(CH31:CH40) -> 0 | CI42: =SUM(CI31:CI40) -> 0 | CJ42: =SUM(CJ31:CJ40) -> 0 | CK42: =SUM(CK31:CK40) -> 0 | CL42: =SUM(CL31:CL40) -> 0 | CM42: =SUM(CM31:CM40) -> 0 | CN42: =SUM(CN31:CN40) -> 0 | CQ42: =SUM(CQ31:CQ41) -> 21219.713 | CR42: =SUM(CR31:CR41) -> 11630.287 | CS42: =SUM(CS31:CS41) -> 0 | CT42: =SUM(CT31:CT41) -> 0 | CU42: =SUM(CU31:CU41) -> 0 | CV42: =SUM(CV31:CV41) -> 0 | CW42: =SUM(CW31:CW41) -> 0 | CX42: =SUM(CX31:CX41) -> 2688.5377 | ... DR42: =SUM(DR31:DR41) -> 0 | DS42: =SUM(DS31:DS40) -> 0 | DT42: =SUM(DT31:DT40) -> 0 | DU42: =SUM(DU31:DU40) -> 0 | DV42: =SUM(DV31:DV40) -> 0 | DW42: =SUM(DW31:DW40) -> 0 | DX42: =SUM(DX31:DX40) -> 0 | DY42: =SUM(DY31:DY40) -> 0 | DZ42: =SUM(DZ31:DZ40) -> 0 | ... EI42: =SUM(EI31:EI40) -> 0 | EK42: =SUM(EK31:EK41) -> 1820.96 | EL42: =SUM(EL31:EL41) -> 2022.85 | EM42: =SUM(EM31:EM41) -> 796 | EN42: =SUM(EN31:EN41) -> 874 | EO42: =SUM(EO31:EO41) -> 0 | EP42: =SUM(EP31:EP41) -> 800 | EQ42: =SUM(EQ31:EQ41) -> 705 | ER42: =SUM(ER31:ER41) -> 0 | ... ET42: =SUM(ET31:ET41) -> 1505 | EV42: =SUM(EV31:EV41) -> 1820.96 | EW42: =SUM(EW31:EW41) -> 2022.85 | EX42: =SUM(EX31:EX41) -> 796 | EY42: =SUM(EY31:EY41) -> 874 | EZ42: =SUM(EZ31:EZ41) -> 0 | FA42: =SUM(FA31:FA41) -> 800 | FB42: =SUM(FB31:FB41) -> 705 | FC42: =SUM(FC31:FC41) -> 0 | ... FE42: =SUM(FE31:FE41) -> 1505 | FL42: =+EP42-FA42 -> 0
FL43: =+EP43-FA43 -> 0
B44: INVESTIGACION Y DESARROLLO | FL44: =+EP44-FA44 -> 0
A45: 27 | B45: De Floran Rodas Luis Arnau Estanislao | C45: Jefe I & D | D45: PROQUIMA | E45: 8000 | F45: 3000 | G45: =+E45+F45 -> 11000 | H45: 30 | I45: 1 | J45: 0 | K45: 0 | L45: 0 | M45: 0 | N45: =SUM(I45:M45) -> 1 | Q45: =($E45/30/8*1.5)*P45 -> 0 | S45: =($E45/30/8*2)*R45 -> 0 | U45: =($E45/30/8*1.5)*T45 -> 0 | W45: =($E45/30/8*2)*V45 -> 0 | Y45: =(($E45/30/8)*1.5)*X45 -> 0 | AA45: =(($E45/30/8)*2)*Z45 -> 0 | AC45: =(($E45/30/8)*1.5)*AB45 -> 0 | AE45: =(($E45/30/8)*2)*AD45 -> 0 | AG45: =(($E45/30/8)*1.5)*AF45 -> 0 | AI45: =(($E45/30/8)*2)*AH45 -> 0 | AV45: =((E45/30)*H45)*$I45 -> 8000 | AW45: =((F45/30)*H45)*$I45 -> 3000 | AX45: =P45 -> 0 | AY45: =Q45 -> 0 | AZ45: =R45 -> 0 | BA45: =S45 -> 0 | BB45: =AJ45+AO45 -> 0 | BC45: =(AV45+AY45+BA45)*0.1267 -> 1013.6 | BD45: =SUM(AV45:BC45)-AX45-AZ45 -> 12013.6 | BE45: =(($E45/30)*$H45)*$J45 -> 0 | BF45: =(($F45/30)*$H45)*$J45 -> 0 | BG45: =T45 -> 0 | BH45: =U45 -> 0 | BI45: =V45 -> 0 | BJ45: =W45 -> 0 | BK45: =AK45+AP45 -> 0 | BL45: =(+BE45+BH45+BJ45+BK45)*0.1267 -> 0 | BM45: =SUM(BE45:BL45)-BG45-BI45 -> 0 | BN45: =(($E45/30)*$H45)*$K45 -> 0 | BO45: =(($F45/30)*$H45)*$K45 -> 0 | BP45: =X45 -> 0 | BQ45: =Y45 -> 0 | BR45: =Z45 -> 0 | BS45: =AA45 -> 0 | BT45: =AL45+AQ45 -> 0 | BU45: =(BN45+BQ45+BS45)*0.1267 -> 0 | BV45: =SUM(BN45:BU45)-BP45-BR45 -> 0 | BW45: =(($E45/30)*$H45)*$L45 -> 0 | BX45: =(($F45/30)*$H45)*$L45 -> 0 | BY45: =AB45 -> 0 | BZ45: =AC45 -> 0 | CA45: =AD45 -> 0 | CB45: =AE45 -> 0 | CC45: =AM45+AR45 -> 0 | CD45: =(BW45+BZ45+CB45)*0.1267 -> 0 | CE45: =SUM(BW45:CD45)-BY45-CA45 -> 0 | CF45: =(($E45/30)*$H45)*M45 -> 0 | CG45: =(($F45/30)*$H45)*$M45 -> 0 | CH45: =+AF45 -> 0 | CI45: =AG45 -> 0 | CJ45: =AH45 -> 0 | CK45: =AI45 -> 0 | CL45: =AN45+AS45 -> 0 | CM45: =(CF45+CI45+CK45)*0.1267 -> 0 | CN45: =SUM(CF45:CM45)-CH45-CJ45 -> 0 | CP45: PROQUIMA | CQ45: =IF($CP45="PROQUIMA",$AV45+$BE45+$BN45+$BW45+$CF45,0) -> 8000 | CR45: =IF($CP45="PROQUIMA",$AW45+$BF45+$BO45+$BX45+$CG45,0) -> 3000 | CS45: =IF($CP45="PROQUIMA",$AX45+$BG45+$BP45+$BY45+$CH45,0) -> 0 | CT45: =IF($CP45="PROQUIMA",$AY45+$BH45+$BQ45+$BZ45+$CI45,0) -> 0 | CU45: =IF($CP45="PROQUIMA",$AZ45+$BI45+$BR45+$CA45+$CJ45,0) -> 0 | CV45: =IF($CP45="PROQUIMA",$BA45+$BJ45+$BS45+$CB45+$CK45,0) -> 0 | CW45: =IF($CP45="PROQUIMA",$BB45+$BK45+$BT45+$CC45+$CL45,0) -> 0 | CX45: =IF($CP45="PROQUIMA",$BC45+$BL45+$BU45+$CD45+CM45,0) -> 1013.6 | CY45: =SUM(CQ45:CX45)-CS45-CU45 -> 12013.6 | CZ45: =IF($CP45="UNHESA",$AV45+$BE45+$BN45+$BW45+$CF45,0) -> 0 | DA45: =IF($CP45="UNHESA",$AW45+$BF45+$BO45+$BX45+$CG45,0) -> 0 | DB45: =IF($CP45="UNHESA",$AX45+$BG45+$BP45+$BY45+$CH45,0) -> 0 | DC45: =IF($CP45="UNHESA",$AY45+$BH45+$BQ45+$BZ45+$CI45,0) -> 0 | DD45: =IF($CP45="UNHESA",$AZ45+$BI45+$BR45+$CA45+$CJ45,0) -> 0 | DE45: =IF($CP45="UNHESA",$BA45+$BJ45+$BS45+$CB45+$CK45,0) -> 0 | DF45: =IF($CP45="UNHESA",$BB45+$BK45+$BT45+$CC45+$CL45,0) -> 0 | DG45: =IF($CP45="UNHESA",$BC45+$BL45+$BU45+$CD45+$CM45,0) -> 0 | DH45: =SUM(CZ45:DG45)-DB45-DD45 -> 0 | DI45: =IF($CP45="UNHESA LIQUIDOS",$AV45+$BE45+$BN45+$BW45+$CF45,0) -> 0 | DJ45: =IF($CP45="CALIDUL",$AW45+$BF45+$BO45+$BX45+$CG45,0) -> 0 | DK45: =IF($CP45="CALIDUL",$AX45+$BG45+$BP45+$BY45+$CH45,0) -> 0 | DL45: =IF($CP45="CALIDUL",$AY45+$BH45+$BQ45+$BZ45+$CI45,0) -> 0 | DM45: =IF($CP45="CALIDUL",$AZ45+$BI45+$BR45+$CA45+$CJ45,0) -> 0 | DN45: =IF($CP45="CALIDUL",$BA45+$BJ45+$BS45+$CB45+$CK45,0) -> 0 | DO45: =IF($CP45="CALIDUL",$BB45+$BK45+$BT45+$CC45+$CL45,0) -> 0 | DP45: =IF($CP45="CALIDUL",$BC45+$BL45+$BU45+$CD45+$CM45,0) -> 0 | DQ45: =SUM(DI45:DP45)-DK45-DM45 -> 0 | DR45: =IF($CP45="ECONACIONAL",$AV45+$BE45+$BN45+$BW45+$CF45,0) -> 0 | DS45: =IF($CP45="ECONACIONAL",$AW45+$BF45+$BO45+$BX45+$CG45,0) -> 0 | DT45: =IF($CP45="ECONACIONAL",$AX45+$BG45+$BP45+$BY45+$CH45,0) -> 0 | DU45: =IF($CP45="ECONACIONAL",$AY45+$BH45+$BQ45+$BZ45+$CI45,0) -> 0 | DV45: =IF($CP45="ECONACIONAL",$AZ45+$BI45+$BR45+$CA45+$CJ45,0) -> 0 | DW45: =IF($CP45="ECONACIONAL",$BA45+$BJ45+$BS45+$CB45+$CK45,0) -> 0 | DX45: =IF($CP45="ECONACIONAL",$BB45+$BK45+$BT45+$CC45+$CL45,0) -> 0 | DY45: =IF($CP45="ECONACIONAL",$BC45+$BL45+$BU45+$CD45+$CM45,0) -> 0 | DZ45: =SUM(DR45:DY45)-DT45-DV45 -> 0 | EA45: =IF($CP45="CLEARTEC",$AV45+$BE45+$BN45+$BW45+$CF45,0) -> 0 | EB45: =IF($CP45="CLEARTEC",$AW45+$BF45+$BO45+$BX45+$CG45,0) -> 0 | EC45: =IF($CP45="CLEARTEC",$AX45+$BG45+$BP45+$BY45+$CH45,0) -> 0 | ED45: =IF($CP45="CLEARTEC",$AY45+$BH45+$BQ45+$BZ45+$CI45,0) -> 0 | EE45: =IF($CP45="CLEARTEC",$AZ45+$BI45+$BR45+$CA45+$CJ45,0) -> 0 | EF45: =IF($CP45="CLEARTEC",$BA45+$BJ45+$BS45+$CB45+$CK45,0) -> 0 | EG45: =IF($CP45="CLEARTEC",$BB45+$BK45+$BT45+$CC45+$CL45,0) -> 0 | EH45: =IF($CP45="CLEARTEC",$BC45+$BL45+$BU45+$CD45+$CM45,0) -> 0 | EI45: =SUM(EA45:EH45)-EC45-EE45 -> 0 | EK45: 330.68 | EN45: =30 -> 30 | EP45: 100 | EQ45: =240 -> 240 | ET45: =+EO45+EP45+EQ45 -> 340 | EV45: =IF($H45<=15,EK45/2,EK45) -> 330.68 | EW45: =IF($H45<=15,EL45/2,EL45) -> 0 | EX45: =IF($H45<=15,EM45/2,EM45) -> 0 | EY45: =IF($H45<=15,EN45/2,EN45) -> 30 | EZ45: =IF($H45<=15,EO45/2,EO45) -> 0 | FA45: =IF($H45<=15,EP45/2,EP45) -> 100 | FB45: =IF($H45<=15,EQ45/2,EQ45) -> 240 | FC45: =IF($H45<=15,ER45/2,ER45) -> 0 | ... FE45: =IF($H45<=15,ET45/2,ET45) -> 340 | FF45: 0.78 | FG45: 0.22 | FH45: 0 | FI45: 0 | FJ45: 0 | FK45: 1 | FL45: =+EP45-FA45 -> 0
A46: =+A45+1 -> 28 | B46: Castro Aceituno Rodrigo Jose | C46: Asistente de Investigacion y Desarrollo | D46: PROQUIMA | E46: 4000 | F46: 1000 | G46: =+E46+F46 -> 5000 | H46: 30 | I46: 1 | J46: 0 | K46: 0 | L46: 0 | M46: 0 | N46: =SUM(I46:M46) -> 1 | Q46: =($E46/30/8*1.5)*P46 -> 0 | S46: =($E46/30/8*2)*R46 -> 0 | U46: =($E46/30/8*1.5)*T46 -> 0 | W46: =($E46/30/8*2)*V46 -> 0 | Y46: =(($E46/30/8)*1.5)*X46 -> 0 | AA46: =(($E46/30/8)*2)*Z46 -> 0 | AC46: =(($E46/30/8)*1.5)*AB46 -> 0 | AE46: =(($E46/30/8)*2)*AD46 -> 0 | AG46: =(($E46/30/8)*1.5)*AF46 -> 0 | AI46: =(($E46/30/8)*2)*AH46 -> 0 | AV46: =((E46/30)*H46)*$I46 -> 4000 | AW46: =((F46/30)*H46)*$I46 -> 1000 | AX46: =P46 -> 0 | AY46: =Q46 -> 0 | AZ46: =R46 -> 0 | BA46: =S46 -> 0 | BB46: =AJ46+AO46 -> 0 | BC46: =(AV46+AY46+BA46)*0.1267 -> 506.8 | BD46: =SUM(AV46:BC46)-AX46-AZ46 -> 5506.8 | BE46: =(($E46/30)*$H46)*$J46 -> 0 | BF46: =(($F46/30)*$H46)*$J46 -> 0 | BG46: =T46 -> 0 | BH46: =U46 -> 0 | BI46: =V46 -> 0 | BJ46: =W46 -> 0 | BK46: =AK46+AP46 -> 0 | BL46: =(+BE46+BH46+BJ46+BK46)*0.1267 -> 0 | BM46: =SUM(BE46:BL46)-BG46-BI46 -> 0 | BN46: =(($E46/30)*$H46)*$K46 -> 0 | BO46: =(($F46/30)*$H46)*$K46 -> 0 | BP46: =X46 -> 0 | BQ46: =Y46 -> 0 | BR46: =Z46 -> 0 | BS46: =AA46 -> 0 | BT46: =AL46+AQ46 -> 0 | BU46: =(BN46+BQ46+BS46)*0.1267 -> 0 | BV46: =SUM(BN46:BU46)-BP46-BR46 -> 0 | BW46: =(($E46/30)*$H46)*$L46 -> 0 | BX46: =(($F46/30)*$H46)*$L46 -> 0 | BY46: =AB46 -> 0 | BZ46: =AC46 -> 0 | CA46: =AD46 -> 0 | CB46: =AE46 -> 0 | CC46: =AM46+AR46 -> 0 | CD46: =(BW46+BZ46+CB46)*0.1267 -> 0 | CE46: =SUM(BW46:CD46)-BY46-CA46 -> 0 | CF46: =(($E46/30)*$H46)*M46 -> 0 | CG46: =(($F46/30)*$H46)*$M46 -> 0 | CH46: =+AF46 -> 0 | CI46: =AG46 -> 0 | CJ46: =AH46 -> 0 | CK46: =AI46 -> 0 | CL46: =AN46+AS46 -> 0 | CM46: =(CF46+CI46+CK46)*0.1267 -> 0 | CN46: =SUM(CF46:CM46)-CH46-CJ46 -> 0 | CP46: PROQUIMA | CQ46: =IF($CP46="PROQUIMA",$AV46+$BE46+$BN46+$BW46+$CF46,0) -> 4000 | CR46: =IF($CP46="PROQUIMA",$AW46+$BF46+$BO46+$BX46+$CG46,0) -> 1000 | CS46: =IF($CP46="PROQUIMA",$AX46+$BG46+$BP46+$BY46+$CH46,0) -> 0 | CT46: =IF($CP46="PROQUIMA",$AY46+$BH46+$BQ46+$BZ46+$CI46,0) -> 0 | CU46: =IF($CP46="PROQUIMA",$AZ46+$BI46+$BR46+$CA46+$CJ46,0) -> 0 | CV46: =IF($CP46="PROQUIMA",$BA46+$BJ46+$BS46+$CB46+$CK46,0) -> 0 | CW46: =IF($CP46="PROQUIMA",$BB46+$BK46+$BT46+$CC46+$CL46,0) -> 0 | CX46: =IF($CP46="PROQUIMA",$BC46+$BL46+$BU46+$CD46+CM46,0) -> 506.8 | CY46: =SUM(CQ46:CX46)-CS46-CU46 -> 5506.8 | CZ46: =IF($CP46="UNHESA",$AV46+$BE46+$BN46+$BW46+$CF46,0) -> 0 | DA46: =IF($CP46="UNHESA",$AW46+$BF46+$BO46+$BX46+$CG46,0) -> 0 | DB46: =IF($CP46="UNHESA",$AX46+$BG46+$BP46+$BY46+$CH46,0) -> 0 | DC46: =IF($CP46="UNHESA",$AY46+$BH46+$BQ46+$BZ46+$CI46,0) -> 0 | DD46: =IF($CP46="UNHESA",$AZ46+$BI46+$BR46+$CA46+$CJ46,0) -> 0 | DE46: =IF($CP46="UNHESA",$BA46+$BJ46+$BS46+$CB46+$CK46,0) -> 0 | DF46: =IF($CP46="UNHESA",$BB46+$BK46+$BT46+$CC46+$CL46,0) -> 0 | DG46: =IF($CP46="UNHESA",$BC46+$BL46+$BU46+$CD46+$CM46,0) -> 0 | DH46: =SUM(CZ46:DG46)-DB46-DD46 -> 0 | DI46: =IF($CP46="UNHESA LIQUIDOS",$AV46+$BE46+$BN46+$BW46+$CF46,0) -> 0 | DJ46: =IF($CP46="CALIDUL",$AW46+$BF46+$BO46+$BX46+$CG46,0) -> 0 | DK46: =IF($CP46="CALIDUL",$AX46+$BG46+$BP46+$BY46+$CH46,0) -> 0 | DL46: =IF($CP46="CALIDUL",$AY46+$BH46+$BQ46+$BZ46+$CI46,0) -> 0 | DM46: =IF($CP46="CALIDUL",$AZ46+$BI46+$BR46+$CA46+$CJ46,0) -> 0 | DN46: =IF($CP46="CALIDUL",$BA46+$BJ46+$BS46+$CB46+$CK46,0) -> 0 | DO46: =IF($CP46="CALIDUL",$BB46+$BK46+$BT46+$CC46+$CL46,0) -> 0 | DP46: =IF($CP46="CALIDUL",$BC46+$BL46+$BU46+$CD46+$CM46,0) -> 0 | DQ46: =SUM(DI46:DP46)-DK46-DM46 -> 0 | DR46: =IF($CP46="ECONACIONAL",$AV46+$BE46+$BN46+$BW46+$CF46,0) -> 0 | DS46: =IF($CP46="ECONACIONAL",$AW46+$BF46+$BO46+$BX46+$CG46,0) -> 0 | DT46: =IF($CP46="ECONACIONAL",$AX46+$BG46+$BP46+$BY46+$CH46,0) -> 0 | DU46: =IF($CP46="ECONACIONAL",$AY46+$BH46+$BQ46+$BZ46+$CI46,0) -> 0 | DV46: =IF($CP46="ECONACIONAL",$AZ46+$BI46+$BR46+$CA46+$CJ46,0) -> 0 | DW46: =IF($CP46="ECONACIONAL",$BA46+$BJ46+$BS46+$CB46+$CK46,0) -> 0 | DX46: =IF($CP46="ECONACIONAL",$BB46+$BK46+$BT46+$CC46+$CL46,0) -> 0 | DY46: =IF($CP46="ECONACIONAL",$BC46+$BL46+$BU46+$CD46+$CM46,0) -> 0 | DZ46: =SUM(DR46:DY46)-DT46-DV46 -> 0 | EA46: =IF($CP46="CLEARTEC",$AV46+$BE46+$BN46+$BW46+$CF46,0) -> 0 | EB46: =IF($CP46="CLEARTEC",$AW46+$BF46+$BO46+$BX46+$CG46,0) -> 0 | EC46: =IF($CP46="CLEARTEC",$AX46+$BG46+$BP46+$BY46+$CH46,0) -> 0 | ED46: =IF($CP46="CLEARTEC",$AY46+$BH46+$BQ46+$BZ46+$CI46,0) -> 0 | EE46: =IF($CP46="CLEARTEC",$AZ46+$BI46+$BR46+$CA46+$CJ46,0) -> 0 | EF46: =IF($CP46="CLEARTEC",$BA46+$BJ46+$BS46+$CB46+$CK46,0) -> 0 | EG46: =IF($CP46="CLEARTEC",$BB46+$BK46+$BT46+$CC46+$CL46,0) -> 0 | EH46: =IF($CP46="CLEARTEC",$BC46+$BL46+$BU46+$CD46+$CM46,0) -> 0 | EI46: =SUM(EA46:EH46)-EC46-EE46 -> 0 | EK46: 40.34 | EP46: 50 | EQ46: =240 -> 240 | ET46: =+EO46+EP46+EQ46 -> 290 | EV46: =IF($H46<=15,EK46/2,EK46) -> 40.34 | EW46: =IF($H46<=15,EL46/2,EL46) -> 0 | EX46: =IF($H46<=15,EM46/2,EM46) -> 0 | EY46: =IF($H46<=15,EN46/2,EN46) -> 0 | EZ46: =IF($H46<=15,EO46/2,EO46) -> 0 | FA46: =IF($H46<=15,EP46/2,EP46) -> 50 | FB46: =IF($H46<=15,EQ46/2,EQ46) -> 240 | FC46: =IF($H46<=15,ER46/2,ER46) -> 0 | ... FE46: =IF($H46<=15,ET46/2,ET46) -> 290
A47: =+A46+1 -> 29 | B47: Mendez Gonzalez Grecia Marbella | C47: Auxiliar de Investigacion y Desarrollo | D47: PROQUIMA | E47: 3250 | F47: 250 | G47: =+E47+F47 -> 3500 | H47: 30 | I47: 1 | J47: 0 | K47: 0 | L47: 0 | M47: 0 | N47: =SUM(I47:M47) -> 1 | Q47: =($E47/30/8*1.5)*P47 -> 0 | S47: =($E47/30/8*2)*R47 -> 0 | U47: =($E47/30/8*1.5)*T47 -> 0 | W47: =($E47/30/8*2)*V47 -> 0 | Y47: =(($E47/30/8)*1.5)*X47 -> 0 | AA47: =(($E47/30/8)*2)*Z47 -> 0 | AC47: =(($E47/30/8)*1.5)*AB47 -> 0 | AE47: =(($E47/30/8)*2)*AD47 -> 0 | AG47: =(($E47/30/8)*1.5)*AF47 -> 0 | AI47: =(($E47/30/8)*2)*AH47 -> 0 | AV47: =((E47/30)*H47)*$I47 -> 3250 | AW47: =((F47/30)*H47)*$I47 -> 250 | AX47: =P47 -> 0 | AY47: =Q47 -> 0 | AZ47: =R47 -> 0 | BA47: =S47 -> 0 | BB47: =AJ47+AO47 -> 0 | BC47: =(AV47+AY47+BA47)*0.1267 -> 411.775 | BD47: =SUM(AV47:BC47)-AX47-AZ47 -> 3911.775 | BE47: =(($E47/30)*$H47)*$J47 -> 0 | BF47: =(($F47/30)*$H47)*$J47 -> 0 | BG47: =T47 -> 0 | BH47: =U47 -> 0 | BI47: =V47 -> 0 | BJ47: =W47 -> 0 | BK47: =AK47+AP47 -> 0 | BL47: =(+BE47+BH47+BJ47+BK47)*0.1267 -> 0 | BM47: =SUM(BE47:BL47)-BG47-BI47 -> 0 | BN47: =(($E47/30)*$H47)*$K47 -> 0 | BO47: =(($F47/30)*$H47)*$K47 -> 0 | BP47: =X47 -> 0 | BQ47: =Y47 -> 0 | BR47: =Z47 -> 0 | BS47: =AA47 -> 0 | BT47: =AL47+AQ47 -> 0 | BU47: =(BN47+BQ47+BS47)*0.1267 -> 0 | BV47: =SUM(BN47:BU47)-BP47-BR47 -> 0 | BW47: =(($E47/30)*$H47)*$L47 -> 0 | BX47: =(($F47/30)*$H47)*$L47 -> 0 | BY47: =AB47 -> 0 | BZ47: =AC47 -> 0 | CA47: =AD47 -> 0 | CB47: =AE47 -> 0 | CC47: =AM47+AR47 -> 0 | CD47: =(BW47+BZ47+CB47)*0.1267 -> 0 | CE47: =SUM(BW47:CD47)-BY47-CA47 -> 0 | CF47: =(($E47/30)*$H47)*M47 -> 0 | CG47: =(($F47/30)*$H47)*$M47 -> 0 | CH47: =+AF47 -> 0 | CI47: =AG47 -> 0 | CJ47: =AH47 -> 0 | CK47: =AI47 -> 0 | CL47: =AN47+AS47 -> 0 | CM47: =(CF47+CI47+CK47)*0.1267 -> 0 | CN47: =SUM(CF47:CM47)-CH47-CJ47 -> 0 | CP47: PROQUIMA | CQ47: =IF($CP47="PROQUIMA",$AV47+$BE47+$BN47+$BW47+$CF47,0) -> 3250 | CR47: =IF($CP47="PROQUIMA",$AW47+$BF47+$BO47+$BX47+$CG47,0) -> 250 | CS47: =IF($CP47="PROQUIMA",$AX47+$BG47+$BP47+$BY47+$CH47,0) -> 0 | CT47: =IF($CP47="PROQUIMA",$AY47+$BH47+$BQ47+$BZ47+$CI47,0) -> 0 | CU47: =IF($CP47="PROQUIMA",$AZ47+$BI47+$BR47+$CA47+$CJ47,0) -> 0 | CV47: =IF($CP47="PROQUIMA",$BA47+$BJ47+$BS47+$CB47+$CK47,0) -> 0 | CW47: =IF($CP47="PROQUIMA",$BB47+$BK47+$BT47+$CC47+$CL47,0) -> 0 | CX47: =IF($CP47="PROQUIMA",$BC47+$BL47+$BU47+$CD47+CM47,0) -> 411.775 | CY47: =SUM(CQ47:CX47)-CS47-CU47 -> 3911.775 | CZ47: =IF($CP47="UNHESA",$AV47+$BE47+$BN47+$BW47+$CF47,0) -> 0 | DA47: =IF($CP47="UNHESA",$AW47+$BF47+$BO47+$BX47+$CG47,0) -> 0 | DB47: =IF($CP47="UNHESA",$AX47+$BG47+$BP47+$BY47+$CH47,0) -> 0 | DC47: =IF($CP47="UNHESA",$AY47+$BH47+$BQ47+$BZ47+$CI47,0) -> 0 | DD47: =IF($CP47="UNHESA",$AZ47+$BI47+$BR47+$CA47+$CJ47,0) -> 0 | DE47: =IF($CP47="UNHESA",$BA47+$BJ47+$BS47+$CB47+$CK47,0) -> 0 | DF47: =IF($CP47="UNHESA",$BB47+$BK47+$BT47+$CC47+$CL47,0) -> 0 | DG47: =IF($CP47="UNHESA",$BC47+$BL47+$BU47+$CD47+$CM47,0) -> 0 | DH47: =SUM(CZ47:DG47)-DB47-DD47 -> 0 | DI47: =IF($CP47="UNHESA LIQUIDOS",$AV47+$BE47+$BN47+$BW47+$CF47,0) -> 0 | DJ47: =IF($CP47="CALIDUL",$AW47+$BF47+$BO47+$BX47+$CG47,0) -> 0 | DK47: =IF($CP47="CALIDUL",$AX47+$BG47+$BP47+$BY47+$CH47,0) -> 0 | DL47: =IF($CP47="CALIDUL",$AY47+$BH47+$BQ47+$BZ47+$CI47,0) -> 0 | DM47: =IF($CP47="CALIDUL",$AZ47+$BI47+$BR47+$CA47+$CJ47,0) -> 0 | DN47: =IF($CP47="CALIDUL",$BA47+$BJ47+$BS47+$CB47+$CK47,0) -> 0 | DO47: =IF($CP47="CALIDUL",$BB47+$BK47+$BT47+$CC47+$CL47,0) -> 0 | DP47: =IF($CP47="CALIDUL",$BC47+$BL47+$BU47+$CD47+$CM47,0) -> 0 | DQ47: =SUM(DI47:DP47)-DK47-DM47 -> 0 | DR47: =IF($CP47="ECONACIONAL",$AV47+$BE47+$BN47+$BW47+$CF47,0) -> 0 | DS47: =IF($CP47="ECONACIONAL",$AW47+$BF47+$BO47+$BX47+$CG47,0) -> 0 | DT47: =IF($CP47="ECONACIONAL",$AX47+$BG47+$BP47+$BY47+$CH47,0) -> 0 | DU47: =IF($CP47="ECONACIONAL",$AY47+$BH47+$BQ47+$BZ47+$CI47,0) -> 0 | DV47: =IF($CP47="ECONACIONAL",$AZ47+$BI47+$BR47+$CA47+$CJ47,0) -> 0 | DW47: =IF($CP47="ECONACIONAL",$BA47+$BJ47+$BS47+$CB47+$CK47,0) -> 0 | DX47: =IF($CP47="ECONACIONAL",$BB47+$BK47+$BT47+$CC47+$CL47,0) -> 0 | DY47: =IF($CP47="ECONACIONAL",$BC47+$BL47+$BU47+$CD47+$CM47,0) -> 0 | DZ47: =SUM(DR47:DY47)-DT47-DV47 -> 0 | EA47: =IF($CP47="CLEARTEC",$AV47+$BE47+$BN47+$BW47+$CF47,0) -> 0 | EB47: =IF($CP47="CLEARTEC",$AW47+$BF47+$BO47+$BX47+$CG47,0) -> 0 | EC47: =IF($CP47="CLEARTEC",$AX47+$BG47+$BP47+$BY47+$CH47,0) -> 0 | ED47: =IF($CP47="CLEARTEC",$AY47+$BH47+$BQ47+$BZ47+$CI47,0) -> 0 | EE47: =IF($CP47="CLEARTEC",$AZ47+$BI47+$BR47+$CA47+$CJ47,0) -> 0 | EF47: =IF($CP47="CLEARTEC",$BA47+$BJ47+$BS47+$CB47+$CK47,0) -> 0 | EG47: =IF($CP47="CLEARTEC",$BB47+$BK47+$BT47+$CC47+$CL47,0) -> 0 | EH47: =IF($CP47="CLEARTEC",$BC47+$BL47+$BU47+$CD47+$CM47,0) -> 0 | EI47: =SUM(EA47:EH47)-EC47-EE47 -> 0 | EP47: 50 | ET47: =+EO47+EP47+EQ47 -> 50 | EV47: =IF($H47<=15,EK47/2,EK47) -> 0 | EW47: =IF($H47<=15,EL47/2,EL47) -> 0 | EX47: =IF($H47<=15,EM47/2,EM47) -> 0 | EY47: =IF($H47<=15,EN47/2,EN47) -> 0 | EZ47: =IF($H47<=15,EO47/2,EO47) -> 0 | FA47: =IF($H47<=15,EP47/2,EP47) -> 50 | FB47: =IF($H47<=15,EQ47/2,EQ47) -> 0 | FC47: =IF($H47<=15,ER47/2,ER47) -> 0 | ... FE47: =IF($H47<=15,ET47/2,ET47) -> 50
A48: =+A47+1 -> 30 | B48: Rodas Coronado Karen Daniela | C48: Analista de Investigacion y Desarrollo | D48: PROQUIMA | E48: 3750 | F48: 250 | G48: =+E48+F48 -> 4000 | H48: 30 | I48: 1 | J48: 0 | K48: 0 | L48: 0 | M48: 0 | N48: =SUM(I48:M48) -> 1 | Q48: =($E48/30/8*1.5)*P48 -> 0 | S48: =($E48/30/8*2)*R48 -> 0 | U48: =($E48/30/8*1.5)*T48 -> 0 | W48: =($E48/30/8*2)*V48 -> 0 | Y48: =(($E48/30/8)*1.5)*X48 -> 0 | AA48: =(($E48/30/8)*2)*Z48 -> 0 | AC48: =(($E48/30/8)*1.5)*AB48 -> 0 | AE48: =(($E48/30/8)*2)*AD48 -> 0 | AG48: =(($E48/30/8)*1.5)*AF48 -> 0 | AI48: =(($E48/30/8)*2)*AH48 -> 0 | AV48: =((E48/30)*H48)*$I48 -> 3750 | AW48: =((F48/30)*H48)*$I48 -> 250 | AX48: =P48 -> 0 | AY48: =Q48 -> 0 | AZ48: =R48 -> 0 | BA48: =S48 -> 0 | BB48: =AJ48+AO48 -> 0 | BC48: =(AV48+AY48+BA48)*0.1267 -> 475.125 | BD48: =SUM(AV48:BC48)-AX48-AZ48 -> 4475.125 | BE48: =(($E48/30)*$H48)*$J48 -> 0 | BF48: =(($F48/30)*$H48)*$J48 -> 0 | BG48: =T48 -> 0 | BH48: =U48 -> 0 | BI48: =V48 -> 0 | BJ48: =W48 -> 0 | BK48: =AK48+AP48 -> 0 | BL48: =(+BE48+BH48+BJ48+BK48)*0.1267 -> 0 | BM48: =SUM(BE48:BL48)-BG48-BI48 -> 0 | BN48: =(($E48/30)*$H48)*$K48 -> 0 | BO48: =(($F48/30)*$H48)*$K48 -> 0 | BP48: =X48 -> 0 | BQ48: =Y48 -> 0 | BR48: =Z48 -> 0 | BS48: =AA48 -> 0 | BT48: =AL48+AQ48 -> 0 | BU48: =(BN48+BQ48+BS48)*0.1267 -> 0 | BV48: =SUM(BN48:BU48)-BP48-BR48 -> 0 | BW48: =(($E48/30)*$H48)*$L48 -> 0 | BX48: =(($F48/30)*$H48)*$L48 -> 0 | BY48: =AB48 -> 0 | BZ48: =AC48 -> 0 | CA48: =AD48 -> 0 | CB48: =AE48 -> 0 | CC48: =AM48+AR48 -> 0 | CD48: =(BW48+BZ48+CB48)*0.1267 -> 0 | CE48: =SUM(BW48:CD48)-BY48-CA48 -> 0 | CF48: =(($E48/30)*$H48)*M48 -> 0 | CG48: =(($F48/30)*$H48)*$M48 -> 0 | CH48: =+AF48 -> 0 | CI48: =AG48 -> 0 | CJ48: =AH48 -> 0 | CK48: =AI48 -> 0 | CL48: =AN48+AS48 -> 0 | CM48: =(CF48+CI48+CK48)*0.1267 -> 0 | CN48: =SUM(CF48:CM48)-CH48-CJ48 -> 0 | CP48: PROQUIMA | CQ48: =IF($CP48="PROQUIMA",$AV48+$BE48+$BN48+$BW48+$CF48,0) -> 3750 | CR48: =IF($CP48="PROQUIMA",$AW48+$BF48+$BO48+$BX48+$CG48,0) -> 250 | CS48: =IF($CP48="PROQUIMA",$AX48+$BG48+$BP48+$BY48+$CH48,0) -> 0 | CT48: =IF($CP48="PROQUIMA",$AY48+$BH48+$BQ48+$BZ48+$CI48,0) -> 0 | CU48: =IF($CP48="PROQUIMA",$AZ48+$BI48+$BR48+$CA48+$CJ48,0) -> 0 | CV48: =IF($CP48="PROQUIMA",$BA48+$BJ48+$BS48+$CB48+$CK48,0) -> 0 | CW48: =IF($CP48="PROQUIMA",$BB48+$BK48+$BT48+$CC48+$CL48,0) -> 0 | CX48: =IF($CP48="PROQUIMA",$BC48+$BL48+$BU48+$CD48+CM48,0) -> 475.125 | CY48: =SUM(CQ48:CX48)-CS48-CU48 -> 4475.125 | CZ48: =IF($CP48="UNHESA",$AV48+$BE48+$BN48+$BW48+$CF48,0) -> 0 | DA48: =IF($CP48="UNHESA",$AW48+$BF48+$BO48+$BX48+$CG48,0) -> 0 | DB48: =IF($CP48="UNHESA",$AX48+$BG48+$BP48+$BY48+$CH48,0) -> 0 | DC48: =IF($CP48="UNHESA",$AY48+$BH48+$BQ48+$BZ48+$CI48,0) -> 0 | DD48: =IF($CP48="UNHESA",$AZ48+$BI48+$BR48+$CA48+$CJ48,0) -> 0 | DE48: =IF($CP48="UNHESA",$BA48+$BJ48+$BS48+$CB48+$CK48,0) -> 0 | DF48: =IF($CP48="UNHESA",$BB48+$BK48+$BT48+$CC48+$CL48,0) -> 0 | DG48: =IF($CP48="UNHESA",$BC48+$BL48+$BU48+$CD48+$CM48,0) -> 0 | DH48: =SUM(CZ48:DG48)-DB48-DD48 -> 0 | DI48: =IF($CP48="UNHESA LIQUIDOS",$AV48+$BE48+$BN48+$BW48+$CF48,0) -> 0 | DJ48: =IF($CP48="CALIDUL",$AW48+$BF48+$BO48+$BX48+$CG48,0) -> 0 | DK48: =IF($CP48="CALIDUL",$AX48+$BG48+$BP48+$BY48+$CH48,0) -> 0 | DL48: =IF($CP48="CALIDUL",$AY48+$BH48+$BQ48+$BZ48+$CI48,0) -> 0 | DM48: =IF($CP48="CALIDUL",$AZ48+$BI48+$BR48+$CA48+$CJ48,0) -> 0 | DN48: =IF($CP48="CALIDUL",$BA48+$BJ48+$BS48+$CB48+$CK48,0) -> 0 | DO48: =IF($CP48="CALIDUL",$BB48+$BK48+$BT48+$CC48+$CL48,0) -> 0 | DP48: =IF($CP48="CALIDUL",$BC48+$BL48+$BU48+$CD48+$CM48,0) -> 0 | DQ48: =SUM(DI48:DP48)-DK48-DM48 -> 0 | DR48: =IF($CP48="ECONACIONAL",$AV48+$BE48+$BN48+$BW48+$CF48,0) -> 0 | DS48: =IF($CP48="ECONACIONAL",$AW48+$BF48+$BO48+$BX48+$CG48,0) -> 0 | DT48: =IF($CP48="ECONACIONAL",$AX48+$BG48+$BP48+$BY48+$CH48,0) -> 0 | DU48: =IF($CP48="ECONACIONAL",$AY48+$BH48+$BQ48+$BZ48+$CI48,0) -> 0 | DV48: =IF($CP48="ECONACIONAL",$AZ48+$BI48+$BR48+$CA48+$CJ48,0) -> 0 | DW48: =IF($CP48="ECONACIONAL",$BA48+$BJ48+$BS48+$CB48+$CK48,0) -> 0 | DX48: =IF($CP48="ECONACIONAL",$BB48+$BK48+$BT48+$CC48+$CL48,0) -> 0 | DY48: =IF($CP48="ECONACIONAL",$BC48+$BL48+$BU48+$CD48+$CM48,0) -> 0 | DZ48: =SUM(DR48:DY48)-DT48-DV48 -> 0 | EA48: =IF($CP48="CLEARTEC",$AV48+$BE48+$BN48+$BW48+$CF48,0) -> 0 | EB48: =IF($CP48="CLEARTEC",$AW48+$BF48+$BO48+$BX48+$CG48,0) -> 0 | EC48: =IF($CP48="CLEARTEC",$AX48+$BG48+$BP48+$BY48+$CH48,0) -> 0 | ED48: =IF($CP48="CLEARTEC",$AY48+$BH48+$BQ48+$BZ48+$CI48,0) -> 0 | EE48: =IF($CP48="CLEARTEC",$AZ48+$BI48+$BR48+$CA48+$CJ48,0) -> 0 | EF48: =IF($CP48="CLEARTEC",$BA48+$BJ48+$BS48+$CB48+$CK48,0) -> 0 | EG48: =IF($CP48="CLEARTEC",$BB48+$BK48+$BT48+$CC48+$CL48,0) -> 0 | EH48: =IF($CP48="CLEARTEC",$BC48+$BL48+$BU48+$CD48+$CM48,0) -> 0 | EI48: =SUM(EA48:EH48)-EC48-EE48 -> 0 | EP48: 50 | ET48: =+EO48+EP48+EQ48 -> 50 | EV48: =IF($H48<=15,EK48/2,EK48) -> 0 | EW48: =IF($H48<=15,EL48/2,EL48) -> 0 | EX48: =IF($H48<=15,EM48/2,EM48) -> 0 | EY48: =IF($H48<=15,EN48/2,EN48) -> 0 | EZ48: =IF($H48<=15,EO48/2,EO48) -> 0 | FA48: =IF($H48<=15,EP48/2,EP48) -> 50 | FB48: =IF($H48<=15,EQ48/2,EQ48) -> 0 | FC48: =IF($H48<=15,ER48/2,ER48) -> 0 | ... FE48: =IF($H48<=15,ET48/2,ET48) -> 50
A49: =+A48+1 -> 31 | B49: Garcia Cruz Cesar Antonio | C49: Investigación y Desarrollo | D49: PROQUIMA | E49: 8269.49 | F49: 6789.8 | G49: =+E49+F49 -> 15059.29 | H49: 30 | I49: 1 | J49: 0 | K49: 0 | L49: 0 | M49: 0 | N49: =SUM(I49:M49) -> 1 | Q49: 0 | S49: 0 | U49: 0 | W49: 0 | Y49: 0 | AA49: =(($E49/30/8)*2)*Z49 -> 0 | AC49: =(($E49/30/8)*1.5)*AB49 -> 0 | AE49: =(($E49/30/8)*2)*AD49 -> 0 | AG49: 0 | AI49: 0 | AV49: =((E49/30)*H49)*$I49 -> 8269.49 | AW49: =((F49/30)*H49)*$I49 -> 6789.8 | AX49: =P49 -> 0 | AY49: =Q49 -> 0 | AZ49: =R49 -> 0 | BA49: =S49 -> 0 | BB49: =AJ49+AO49 -> 0 | BC49: =(AV49+AY49+BA49)*0.1267 -> 1047.7444 | BD49: =SUM(AV49:BC49)-AX49-AZ49 -> 16107.034 | BE49: =(($E49/30)*$H49)*$J49 -> 0 | BF49: =(($F49/30)*$H49)*$J49 -> 0 | BG49: =T49 -> 0 | BH49: =U49 -> 0 | BI49: =V49 -> 0 | BJ49: =W49 -> 0 | BK49: =AK49+AP49 -> 0 | BL49: =(+BE49+BH49+BJ49+BK49)*0.1267 -> 0 | BM49: =SUM(BE49:BL49)-BG49-BI49 -> 0 | BN49: =(($E49/30)*$H49)*$K49 -> 0 | BO49: =(($F49/30)*$H49)*$K49 -> 0 | BP49: =X49 -> 0 | BQ49: =Y49 -> 0 | BR49: =Z49 -> 0 | BS49: =AA49 -> 0 | BT49: =AL49+AQ49 -> 0 | BU49: =(BN49+BQ49+BS49)*0.1267 -> 0 | BV49: =SUM(BN49:BU49)-BP49-BR49 -> 0 | BW49: 0 | BX49: =(($F49/30)*$H49)*$L49 -> 0 | BY49: =AB49 -> 0 | BZ49: =AC49 -> 0 | CA49: =AD49 -> 0 | CB49: =AE49 -> 0 | CC49: =AM49+AR49 -> 0 | CD49: =(BW49+BZ49+CB49)*0.1267 -> 0 | CE49: =SUM(BW49:CD49)-BY49-CA49 -> 0 | CF49: 0 | CG49: 0 | CH49: 0 | CI49: 0 | CJ49: 0 | CK49: 0 | CL49: 0 | CM49: 0 | CN49: 0 | CP49: PROQUIMA | CQ49: =IF($CP49="PROQUIMA",$AV49+$BE49+$BN49+$BW49+$CF49,0) -> 8269.49 | CR49: =IF($CP49="PROQUIMA",$AW49+$BF49+$BO49+$BX49+$CG49,0) -> 6789.8 | CS49: =IF($CP49="PROQUIMA",$AX49+$BG49+$BP49+$BY49+$CH49,0) -> 0 | CT49: =IF($CP49="PROQUIMA",$AY49+$BH49+$BQ49+$BZ49+$CI49,0) -> 0 | CU49: =IF($CP49="PROQUIMA",$AZ49+$BI49+$BR49+$CA49+$CJ49,0) -> 0 | CV49: =IF($CP49="PROQUIMA",$BA49+$BJ49+$BS49+$CB49+$CK49,0) -> 0 | CW49: =IF($CP49="PROQUIMA",$BB49+$BK49+$BT49+$CC49+$CL49,0) -> 0 | CX49: =IF($CP49="PROQUIMA",$BC49+$BL49+$BU49+$CD49+CM49,0) -> 1047.7444 | CY49: =SUM(CQ49:CX49)-CS49-CU49 -> 16107.034 | CZ49: =IF($CP49="UNHESA",$AV49+$BE49+$BN49+$BW49+$CF49,0) -> 0 | DA49: =IF($CP49="UNHESA",$AW49+$BF49+$BO49+$BX49+$CG49,0) -> 0 | DB49: =IF($CP49="UNHESA",$AX49+$BG49+$BP49+$BY49+$CH49,0) -> 0 | DC49: =IF($CP49="UNHESA",$AY49+$BH49+$BQ49+$BZ49+$CI49,0) -> 0 | DD49: =IF($CP49="UNHESA",$AZ49+$BI49+$BR49+$CA49+$CJ49,0) -> 0 | DE49: =IF($CP49="UNHESA",$BA49+$BJ49+$BS49+$CB49+$CK49,0) -> 0 | DF49: =IF($CP49="UNHESA",$BB49+$BK49+$BT49+$CC49+$CL49,0) -> 0 | DG49: =IF($CP49="UNHESA",$BC49+$BL49+$BU49+$CD49+$CM49,0) -> 0 | DH49: =SUM(CZ49:DG49)-DB49-DD49 -> 0 | DI49: 0 | DJ49: 0 | DK49: 0 | DL49: 0 | DM49: 0 | DN49: 0 | DO49: 0 | DP49: 0 | DQ49: 0 | DR49: 0 | DS49: 0 | DT49: 0 | DU49: 0 | DV49: 0 | DW49: 0 | DX49: 0 | DY49: 0 | DZ49: 0 | EA49: 0 | EB49: 0 | EC49: 0 | ED49: 0 | EE49: 0 | EF49: 0 | EG49: 0 | EH49: 0 | EI49: =SUM(EA49:EH49)-EC49-EE49 -> 0 | EK49: 540.56 | EM49: =199+49+199+199+49+199 -> 894 | ET49: =+EO49+EP49+EQ49 -> 0 | EV49: =IF($H49<=15,EK49/2,EK49) -> 540.56 | EW49: =IF($H49<=15,EL49/2,EL49) -> 0 | EX49: =IF($H49<=15,EM49/2,EM49) -> 894 | EY49: =IF($H49<=15,EN49/2,EN49) -> 0 | EZ49: =IF($H49<=15,EO49/2,EO49) -> 0 | FA49: =IF($H49<=15,EP49/2,EP49) -> 0 | FB49: =IF($H49<=15,EQ49/2,EQ49) -> 0 | FC49: =IF($H49<=15,ER49/2,ER49) -> 0 | ... FE49: =IF($H49<=15,ET49/2,ET49) -> 0 | FF49: 1 | FG49: 0 | FH49: 0 | FI49: 0 | FJ49: 0 | FK49: 1 | FL49: 0
C50: TotaL Investigacion y desarrollo | E50: =SUM(E45:E49) -> 27269.49 | F50: =SUM(F45:F49) -> 11289.8 | G50: =SUM(G45:G49) -> 38559.29 | P50: =SUM(P45:P49) -> 0 | Q50: =SUM(Q45:Q49) -> 0 | R50: =SUM(R45:R49) -> 0 | S50: =SUM(S45:S49) -> 0 | T50: =SUM(T45:T49) -> 0 | U50: =SUM(U45:U49) -> 0 | V50: =SUM(V45:V49) -> 0 | W50: =SUM(W45:W49) -> 0 | ... AT50: =SUM(AT45:AT49) -> 0 | AV50: =SUM(AV45:AV49) -> 27269.49 | AW50: =SUM(AW45:AW49) -> 11289.8 | AX50: =SUM(AX45:AX49) -> 0 | AY50: =SUM(AY45:AY49) -> 0 | AZ50: =SUM(AZ45:AZ49) -> 0 | BA50: =SUM(BA45:BA49) -> 0 | BB50: =SUM(BB45:BB49) -> 0 | BC50: =SUM(BC45:BC49) -> 3455.0444 | ... CN50: =SUM(CN45:CN49) -> 0 | CQ50: =SUM(CQ45:CQ49) -> 27269.49 | CR50: =SUM(CR45:CR49) -> 11289.8 | CS50: =SUM(CS45:CS49) -> 0 | CT50: =SUM(CT45:CT49) -> 0 | CU50: =SUM(CU45:CU49) -> 0 | CV50: =SUM(CV45:CV49) -> 0 | CW50: =SUM(CW45:CW49) -> 0 | CX50: =SUM(CX45:CX49) -> 3455.0444 | ... EI50: =SUM(EI45:EI49) -> 0 | EK50: =SUM(EK45:EK49) -> 911.58 | EL50: =SUM(EL45:EL49) -> 0 | EM50: =SUM(EM45:EM49) -> 894 | EN50: =SUM(EN45:EN49) -> 30 | EO50: =SUM(EO45:EO49) -> 0 | EP50: =SUM(EP45:EP49) -> 250 | EQ50: =SUM(EQ45:EQ49) -> 480 | ER50: =SUM(ER45:ER49) -> 0 | ... ET50: =SUM(ET45:ET49) -> 730 | EV50: =SUM(EV45:EV49) -> 911.58 | EW50: =SUM(EW45:EW49) -> 0 | EX50: =SUM(EX45:EX49) -> 894 | EY50: =SUM(EY45:EY49) -> 30 | EZ50: =SUM(EZ45:EZ49) -> 0 | FA50: =SUM(FA45:FA49) -> 250 | FB50: =SUM(FB45:FB49) -> 480 | FC50: =SUM(FC45:FC49) -> 0 | ... FE50: =SUM(FE45:FE49) -> 730 | FL50: =+EP50-FA50 -> 0
FL51: =+EP51-FA51 -> 0
B52: CONTROL DE CALIDAD | FL52: =+EP52-FA52 -> 0
A53: 32 | B53: Saban Culajay Edson Omar | C53: Jefe de Gestion de calidad | D53: PROQUIMA | E53: 5250 | F53: =2750 -> 2750 | G53: =+E53+F53 -> 8000 | H53: 30 | I53: 0.35 | J53: 0.6 | K53: 0 | L53: 0.05 | M53: 0 | N53: =SUM(I53:M53) -> 1 | Q53: =($E53/30/8*1.5)*P53 -> 0 | R53: 0 | S53: =($E53/30/8*2)*R53 -> 0 | U53: =($E53/30/8*1.5)*T53 -> 0 | W53: =($E53/30/8*2)*V53 -> 0 | Y53: =(($E53/30/8)*1.5)*X53 -> 0 | AA53: =(($E53/30/8)*2)*Z53 -> 0 | AC53: =(($E53/30/8)*1.5)*AB53 -> 0 | AE53: =(($E53/30/8)*2)*AD53 -> 0 | AG53: =(($E53/30/8)*1.5)*AF53 -> 0 | AI53: =(($E53/30/8)*2)*AH53 -> 0 | AV53: =((E53/30)*H53)*$I53 -> 1837.5 | AW53: =((F53/30)*H53)*$I53 -> 962.5 | AX53: =P53 -> 0 | AY53: =Q53 -> 0 | AZ53: =R53 -> 0 | BA53: =S53 -> 0 | BB53: =AJ53+AO53 -> 0 | BC53: =(AV53+AY53+BA53)*0.1267 -> 232.81125 | BD53: =SUM(AV53:BC53)-AX53-AZ53 -> 3032.8112 | BE53: =(($E53/30)*$H53)*$J53 -> 3150 | BF53: =(($F53/30)*$H53)*$J53 -> 1650 | BG53: =T53 -> 0 | BH53: =U53 -> 0 | BI53: =V53 -> 0 | BJ53: =W53 -> 0 | BK53: =AK53+AP53 -> 0 | BL53: =(+BE53+BH53+BJ53+BK53)*0.1267 -> 399.105 | BM53: =SUM(BE53:BL53)-BG53-BI53 -> 5199.105 | BN53: =(($E53/30)*$H53)*$K53 -> 0 | BO53: =(($F53/30)*$H53)*$K53 -> 0 | BP53: =X53 -> 0 | BQ53: =Y53 -> 0 | BR53: =Z53 -> 0 | BS53: =AA53 -> 0 | BT53: =AL53+AQ53 -> 0 | BU53: =(BN53+BQ53+BS53)*0.1267 -> 0 | BV53: =SUM(BN53:BU53)-BP53-BR53 -> 0 | BW53: =(($E53/30)*$H53)*$L53 -> 262.5 | BX53: =(($F53/30)*$H53)*$L53 -> 137.5 | BZ53: =AC53 -> 0 | CB53: =AE53 -> 0 | CD53: =(BW53+BZ53+CB53)*0.1267 -> 33.25875 | CE53: =SUM(BW53:CD53) -> 433.25875 | CF53: =(($E53/30)*$H53)*M53 -> 0 | CG53: =(($F53/30)*$H53)*$M53 -> 0 | CI53: =AG53 -> 0 | CK53: =AI53 -> 0 | CM53: =(CF53+CI53+CK53)*0.1267 -> 0 | CP53: PROQUIMA | CQ53: =IF($CP53="PROQUIMA",$AV53+$BE53+$BN53+$BW53+$CF53,0) -> 5250 | CR53: =IF($CP53="PROQUIMA",$AW53+$BF53+$BO53+$BX53+$CG53,0) -> 2750 | CS53: =IF($CP53="PROQUIMA",$AX53+$BG53+$BP53+$BY53+$CH53,0) -> 0 | CT53: =IF($CP53="PROQUIMA",$AY53+$BH53+$BQ53+$BZ53+$CI53,0) -> 0 | CU53: =IF($CP53="PROQUIMA",$AZ53+$BI53+$BR53+$CA53+$CJ53,0) -> 0 | CV53: =IF($CP53="PROQUIMA",$BA53+$BJ53+$BS53+$CB53+$CK53,0) -> 0 | CW53: =IF($CP53="PROQUIMA",$BB53+$BK53+$BT53+$CC53+$CL53,0) -> 0 | CX53: =IF($CP53="PROQUIMA",$BC53+$BL53+$BU53+$CD53+CM53,0) -> 665.175 | CY53: =SUM(CQ53:CX53)-CS53-CU53 -> 8665.175 | CZ53: =IF($CP53="UNHESA",$AV53+$BE53+$BN53+$BW53+$CF53,0) -> 0 | DA53: =IF($CP53="UNHESA",$AW53+$BF53+$BO53+$BX53+$CG53,0) -> 0 | DB53: =IF($CP53="UNHESA",$AX53+$BG53+$BP53+$BY53+$CH53,0) -> 0 | DC53: =IF($CP53="UNHESA",$AY53+$BH53+$BQ53+$BZ53+$CI53,0) -> 0 | DD53: =IF($CP53="UNHESA",$AZ53+$BI53+$BR53+$CA53+$CJ53,0) -> 0 | DE53: =IF($CP53="UNHESA",$BA53+$BJ53+$BS53+$CB53+$CK53,0) -> 0 | DF53: =IF($CP53="UNHESA",$BB53+$BK53+$BT53+$CC53+$CL53,0) -> 0 | DG53: =IF($CP53="UNHESA",$BC53+$BL53+$BU53+$CD53+$CM53,0) -> 0 | DH53: =SUM(CZ53:DG53)-DB53-DD53 -> 0 | DI53: =IF($CP53="UNHESA LIQUIDOS",$AV53+$BE53+$BN53+$BW53+$CF53,0) -> 0 | DJ53: =IF($CP53="CALIDUL",$AW53+$BF53+$BO53+$BX53+$CG53,0) -> 0 | DK53: =IF($CP53="CALIDUL",$AX53+$BG53+$BP53+$BY53+$CH53,0) -> 0 | DL53: =IF($CP53="CALIDUL",$AY53+$BH53+$BQ53+$BZ53+$CI53,0) -> 0 | DM53: =IF($CP53="CALIDUL",$AZ53+$BI53+$BR53+$CA53+$CJ53,0) -> 0 | DN53: =IF($CP53="CALIDUL",$BA53+$BJ53+$BS53+$CB53+$CK53,0) -> 0 | DO53: =IF($CP53="CALIDUL",$BB53+$BK53+$BT53+$CC53+$CL53,0) -> 0 | DP53: =IF($CP53="CALIDUL",$BC53+$BL53+$BU53+$CD53+$CM53,0) -> 0 | DQ53: =SUM(DI53:DP53)-DK53-DM53 -> 0 | DR53: =IF($CP53="ECONACIONAL",$AV53+$BE53+$BN53+$BW53+$CF53,0) -> 0 | DS53: =IF($CP53="ECONACIONAL",$AW53+$BF53+$BO53+$BX53+$CG53,0) -> 0 | DT53: =IF($CP53="ECONACIONAL",$AX53+$BG53+$BP53+$BY53+$CH53,0) -> 0 | DU53: =IF($CP53="ECONACIONAL",$AY53+$BH53+$BQ53+$BZ53+$CI53,0) -> 0 | DV53: =IF($CP53="ECONACIONAL",$AZ53+$BI53+$BR53+$CA53+$CJ53,0) -> 0 | DW53: =IF($CP53="ECONACIONAL",$BA53+$BJ53+$BS53+$CB53+$CK53,0) -> 0 | DX53: =IF($CP53="ECONACIONAL",$BB53+$BK53+$BT53+$CC53+$CL53,0) -> 0 | DY53: =IF($CP53="ECONACIONAL",$BC53+$BL53+$BU53+$CD53+$CM53,0) -> 0 | DZ53: 0 | EI53: =SUM(EA53:EH53)-EC53-EE53 -> 0 | EK53: 187.32 | EP53: 75 | EQ53: =240 -> 240 | ET53: =+EO53+EP53+EQ53 -> 315 | EV53: =IF($H53<=15,EK53/2,EK53) -> 187.32 | EW53: =IF($H53<=15,EL53/2,EL53) -> 0 | EX53: =IF($H53<=15,EM53/2,EM53) -> 0 | EY53: =IF($H53<=15,EN53/2,EN53) -> 0 | EZ53: =IF($H53<=15,EO53/2,EO53) -> 0 | FA53: =IF($H53<=15,EP53/2,EP53) -> 75 | FB53: =IF($H53<=15,EQ53/2,EQ53) -> 240 | FC53: =IF($H53<=15,ER53/2,ER53) -> 0 | ... FE53: =IF($H53<=15,ET53/2,ET53) -> 315
A54: =+A53+1 -> 33 | B54: Gomez Aldana Jenifer Melissa | C54: Asistente de Aseguramiento de Calidad | D54: UNHESA | E54: =4250+250 -> 4500 | F54: 500 | G54: =+E54+F54 -> 5000 | H54: 30 | I54: 0.4 | J54: 0.45 | K54: 0 | L54: 0.15 | M54: 0 | N54: =SUM(I54:M54) -> 1 | Q54: =($E54/30/8*1.5)*P54 -> 0 | S54: =($E54/30/8*2)*R54 -> 0 | T54: 8 | U54: =($E54/30/8*1.5)*T54 -> 225 | W54: =($E54/30/8*2)*V54 -> 0 | Y54: =(($E54/30/8)*1.5)*X54 -> 0 | AA54: =(($E54/30/8)*2)*Z54 -> 0 | AC54: =(($E54/30/8)*1.5)*AB54 -> 0 | AE54: =(($E54/30/8)*2)*AD54 -> 0 | AG54: =(($E54/30/8)*1.5)*AF54 -> 0 | AI54: =(($E54/30/8)*2)*AH54 -> 0 | AV54: =((E54/30)*H54)*$I54 -> 1800 | AW54: =((F54/30)*H54)*$I54 -> 200 | AX54: =P54 -> 0 | AY54: =Q54 -> 0 | AZ54: =R54 -> 0 | BA54: =S54 -> 0 | BB54: =AJ54+AO54 -> 0 | BC54: =(AV54+AY54+BA54)*0.1267 -> 228.06 | BD54: =SUM(AV54:BC54)-AX54-AZ54 -> 2228.06 | BE54: =(($E54/30)*$H54)*$J54 -> 2025 | BF54: =(($F54/30)*$H54)*$J54 -> 225 | BG54: =T54 -> 8 | BH54: =U54 -> 225 | BI54: =V54 -> 0 | BJ54: =W54 -> 0 | BK54: =AK54+AP54 -> 0 | BL54: =(+BE54+BH54+BJ54+BK54)*0.1267 -> 285.075 | BM54: =SUM(BE54:BL54)-BG54-BI54 -> 2760.075 | BN54: =(($E54/30)*$H54)*$K54 -> 0 | BO54: =(($F54/30)*$H54)*$K54 -> 0 | BP54: =X54 -> 0 | BQ54: =Y54 -> 0 | BR54: =Z54 -> 0 | BS54: =AA54 -> 0 | BT54: =AL54+AQ54 -> 0 | BU54: =(BN54+BQ54+BS54)*0.1267 -> 0 | BV54: =SUM(BN54:BU54)-BP54-BR54 -> 0 | BW54: =(($E54/30)*$H54)*$L54 -> 675 | BX54: =(($F54/30)*$H54)*$L54 -> 75 | BZ54: =AC54 -> 0 | CB54: =AE54 -> 0 | CD54: =(BW54+BZ54+CB54)*0.1267 -> 85.5225 | CE54: =SUM(BW54:CD54) -> 835.5225 | CF54: =(($E54/30)*$H54)*M54 -> 0 | CG54: =(($F54/30)*$H54)*$M54 -> 0 | CI54: =AG54 -> 0 | CK54: =AI54 -> 0 | CM54: =(CF54+CI54+CK54)*0.1267 -> 0 | CP54: UNHESA | CQ54: =IF($CP54="PROQUIMA",$AV54+$BE54+$BN54+$BW54+$CF54,0) -> 0 | CR54: =IF($CP54="PROQUIMA",$AW54+$BF54+$BO54+$BX54+$CG54,0) -> 0 | CS54: =IF($CP54="PROQUIMA",$AX54+$BG54+$BP54+$BY54+$CH54,0) -> 0 | CT54: =IF($CP54="PROQUIMA",$AY54+$BH54+$BQ54+$BZ54+$CI54,0) -> 0 | CU54: =IF($CP54="PROQUIMA",$AZ54+$BI54+$BR54+$CA54+$CJ54,0) -> 0 | CV54: =IF($CP54="PROQUIMA",$BA54+$BJ54+$BS54+$CB54+$CK54,0) -> 0 | CW54: =IF($CP54="PROQUIMA",$BB54+$BK54+$BT54+$CC54+$CL54,0) -> 0 | CX54: =IF($CP54="PROQUIMA",$BC54+$BL54+$BU54+$CD54+CM54,0) -> 0 | CY54: =SUM(CQ54:CX54)-CS54-CU54 -> 0 | CZ54: =IF($CP54="UNHESA",$AV54+$BE54+$BN54+$BW54+$CF54,0) -> 4500 | DA54: =IF($CP54="UNHESA",$AW54+$BF54+$BO54+$BX54+$CG54,0) -> 500 | DB54: =IF($CP54="UNHESA",$AX54+$BG54+$BP54+$BY54+$CH54,0) -> 8 | DC54: =IF($CP54="UNHESA",$AY54+$BH54+$BQ54+$BZ54+$CI54,0) -> 225 | DD54: =IF($CP54="UNHESA",$AZ54+$BI54+$BR54+$CA54+$CJ54,0) -> 0 | DE54: =IF($CP54="UNHESA",$BA54+$BJ54+$BS54+$CB54+$CK54,0) -> 0 | DF54: =IF($CP54="UNHESA",$BB54+$BK54+$BT54+$CC54+$CL54,0) -> 0 | DG54: =IF($CP54="UNHESA",$BC54+$BL54+$BU54+$CD54+$CM54,0) -> 598.6575 | DH54: =SUM(CZ54:DG54)-DB54-DD54 -> 5823.6575 | DI54: =IF($CP54="UNHESA LIQUIDOS",$AV54+$BE54+$BN54+$BW54+$CF54,0) -> 0 | DJ54: =IF($CP54="CALIDUL",$AW54+$BF54+$BO54+$BX54+$CG54,0) -> 0 | DK54: =IF($CP54="CALIDUL",$AX54+$BG54+$BP54+$BY54+$CH54,0) -> 0 | DL54: =IF($CP54="CALIDUL",$AY54+$BH54+$BQ54+$BZ54+$CI54,0) -> 0 | DM54: =IF($CP54="CALIDUL",$AZ54+$BI54+$BR54+$CA54+$CJ54,0) -> 0 | DN54: =IF($CP54="CALIDUL",$BA54+$BJ54+$BS54+$CB54+$CK54,0) -> 0 | DO54: =IF($CP54="CALIDUL",$BB54+$BK54+$BT54+$CC54+$CL54,0) -> 0 | DP54: =IF($CP54="CALIDUL",$BC54+$BL54+$BU54+$CD54+$CM54,0) -> 0 | DQ54: =SUM(DI54:DP54)-DK54-DM54 -> 0 | DR54: 0 | DS54: 0 | DT54: 0 | DU54: 0 | DV54: 0 | DW54: 0 | DX54: 0 | DY54: 0 | DZ54: 0 | EI54: =SUM(EA54:EH54)-EC54-EE54 -> 0 | EK54: 39.13 | EN54: =82.5+108.5 -> 191 | EP54: 50 | ET54: =+EO54+EP54+EQ54 -> 50 | EV54: =IF($H54<=15,EK54/2,EK54) -> 39.13 | EW54: =IF($H54<=15,EL54/2,EL54) -> 0 | EX54: =IF($H54<=15,EM54/2,EM54) -> 0 | EY54: =IF($H54<=15,EN54/2,EN54) -> 191 | EZ54: =IF($H54<=15,EO54/2,EO54) -> 0 | FA54: =IF($H54<=15,EP54/2,EP54) -> 50 | FB54: =IF($H54<=15,EQ54/2,EQ54) -> 0 | FC54: =IF($H54<=15,ER54/2,ER54) -> 0 | ... FE54: =IF($H54<=15,ET54/2,ET54) -> 50
A55: =+A54+1 -> 34 | B55: Curruchiche Aguilar Triana Maria | C55: Auxiliar de Control De Calidad | D55: UNHESA | E55: 3166.38 | F55: 833.62 | G55: =+E55+F55 -> 4000 | H55: 30 | I55: 0 | J55: 1 | K55: 0 | L55: 0 | M55: 0 | N55: =SUM(I55:M55) -> 1 | Q55: =($E55/30/8*1.5)*P55 -> 0 | S55: =($E55/30/8*2)*R55 -> 0 | T55: 10.5 | U55: =($E55/30/8*1.5)*T55 -> 207.79369 | W55: =($E55/30/8*2)*V55 -> 0 | Y55: =(($E55/30/8)*1.5)*X55 -> 0 | AA55: =(($E55/30/8)*2)*Z55 -> 0 | AC55: =(($E55/30/8)*1.5)*AB55 -> 0 | AE55: =(($E55/30/8)*2)*AD55 -> 0 | AG55: =(($E55/30/8)*1.5)*AF55 -> 0 | AI55: =(($E55/30/8)*2)*AH55 -> 0 | AV55: =((E55/30)*H55)*$I55 -> 0 | AW55: =((F55/30)*H55)*$I55 -> 0 | AX55: =P55 -> 0 | AY55: =Q55 -> 0 | AZ55: =R55 -> 0 | BA55: =S55 -> 0 | BB55: =AJ55+AO55 -> 0 | BC55: =(AV55+AY55+BA55)*0.1267 -> 0 | BD55: =SUM(AV55:BC55)-AX55-AZ55 -> 0 | BE55: =(($E55/30)*$H55)*$J55 -> 3166.38 | BF55: =(($F55/30)*$H55)*$J55 -> 833.62 | BG55: =T55 -> 10.5 | BH55: =U55 -> 207.79369 | BI55: =V55 -> 0 | BJ55: =W55 -> 0 | BK55: =AK55+AP55 -> 0 | BL55: =(+BE55+BH55+BJ55+BK55)*0.1267 -> 427.50781 | BM55: =SUM(BE55:BL55)-BG55-BI55 -> 4635.3015 | BN55: =(($E55/30)*$H55)*$K55 -> 0 | BO55: =(($F55/30)*$H55)*$K55 -> 0 | BP55: =X55 -> 0 | BQ55: =Y55 -> 0 | BR55: =Z55 -> 0 | BS55: =AA55 -> 0 | BT55: =AL55+AQ55 -> 0 | BU55: =(BN55+BQ55+BS55)*0.1267 -> 0 | BV55: =SUM(BN55:BU55)-BP55-BR55 -> 0 | BW55: =(($E55/30)*$H55)*$L55 -> 0 | BX55: =(($F55/30)*$H55)*$L55 -> 0 | BZ55: =AC55 -> 0 | CB55: =AE55 -> 0 | CD55: =(BW55+BZ55+CB55)*0.1267 -> 0 | CE55: =SUM(BW55:CD55) -> 0 | CF55: =(($E55/30)*$H55)*M55 -> 0 | CG55: =(($F55/30)*$H55)*$M55 -> 0 | CI55: =AG55 -> 0 | CK55: =AI55 -> 0 | CM55: =(CF55+CI55+CK55)*0.1267 -> 0 | CP55: UNHESA | CQ55: =IF($CP55="PROQUIMA",$AV55+$BE55+$BN55+$BW55+$CF55,0) -> 0 | CR55: =IF($CP55="PROQUIMA",$AW55+$BF55+$BO55+$BX55+$CG55,0) -> 0 | CS55: =IF($CP55="PROQUIMA",$AX55+$BG55+$BP55+$BY55+$CH55,0) -> 0 | CT55: =IF($CP55="PROQUIMA",$AY55+$BH55+$BQ55+$BZ55+$CI55,0) -> 0 | CU55: =IF($CP55="PROQUIMA",$AZ55+$BI55+$BR55+$CA55+$CJ55,0) -> 0 | CV55: =IF($CP55="PROQUIMA",$BA55+$BJ55+$BS55+$CB55+$CK55,0) -> 0 | CW55: =IF($CP55="PROQUIMA",$BB55+$BK55+$BT55+$CC55+$CL55,0) -> 0 | CX55: =IF($CP55="PROQUIMA",$BC55+$BL55+$BU55+$CD55+CM55,0) -> 0 | CY55: =SUM(CQ55:CX55)-CS55-CU55 -> 0 | CZ55: =IF($CP55="UNHESA",$AV55+$BE55+$BN55+$BW55+$CF55,0) -> 3166.38 | DA55: =IF($CP55="UNHESA",$AW55+$BF55+$BO55+$BX55+$CG55,0) -> 833.62 | DB55: =IF($CP55="UNHESA",$AX55+$BG55+$BP55+$BY55+$CH55,0) -> 10.5 | DC55: =IF($CP55="UNHESA",$AY55+$BH55+$BQ55+$BZ55+$CI55,0) -> 207.79369 | DD55: =IF($CP55="UNHESA",$AZ55+$BI55+$BR55+$CA55+$CJ55,0) -> 0 | DE55: =IF($CP55="UNHESA",$BA55+$BJ55+$BS55+$CB55+$CK55,0) -> 0 | DF55: =IF($CP55="UNHESA",$BB55+$BK55+$BT55+$CC55+$CL55,0) -> 0 | DG55: =IF($CP55="UNHESA",$BC55+$BL55+$BU55+$CD55+$CM55,0) -> 427.50781 | DH55: =SUM(CZ55:DG55)-DB55-DD55 -> 4635.3015 | DI55: =IF($CP55="UNHESA LIQUIDOS",$AV55+$BE55+$BN55+$BW55+$CF55,0) -> 0 | DJ55: =IF($CP55="CALIDUL",$AW55+$BF55+$BO55+$BX55+$CG55,0) -> 0 | DK55: =IF($CP55="CALIDUL",$AX55+$BG55+$BP55+$BY55+$CH55,0) -> 0 | DL55: =IF($CP55="CALIDUL",$AY55+$BH55+$BQ55+$BZ55+$CI55,0) -> 0 | DM55: =IF($CP55="CALIDUL",$AZ55+$BI55+$BR55+$CA55+$CJ55,0) -> 0 | DN55: =IF($CP55="CALIDUL",$BA55+$BJ55+$BS55+$CB55+$CK55,0) -> 0 | DO55: =IF($CP55="CALIDUL",$BB55+$BK55+$BT55+$CC55+$CL55,0) -> 0 | DP55: =IF($CP55="CALIDUL",$BC55+$BL55+$BU55+$CD55+$CM55,0) -> 0 | DQ55: =SUM(DI55:DP55)-DK55-DM55 -> 0 | DR55: 0 | DS55: 0 | DT55: 0 | DU55: 0 | DV55: 0 | DW55: 0 | DX55: 0 | DY55: 0 | DZ55: 0 | EI55: =SUM(EA55:EH55)-EC55-EE55 -> 0 | EN55: 71.5 | EP55: 50 | EQ55: =240 -> 240 | ET55: =+EO55+EP55+EQ55 -> 290 | EV55: =IF($H55<=15,EK55/2,EK55) -> 0 | EW55: =IF($H55<=15,EL55/2,EL55) -> 0 | EX55: =IF($H55<=15,EM55/2,EM55) -> 0 | EY55: =IF($H55<=15,EN55/2,EN55) -> 71.5 | EZ55: =IF($H55<=15,EO55/2,EO55) -> 0 | FA55: =IF($H55<=15,EP55/2,EP55) -> 50 | FB55: =IF($H55<=15,EQ55/2,EQ55) -> 240 | FC55: =IF($H55<=15,ER55/2,ER55) -> 0 | ... FE55: =IF($H55<=15,ET55/2,ET55) -> 290
A56: =+A55+1 -> 35 | B56: Hernandez Brenes Juan Pablo Jose | C56: Asistente de Control de Calidad | D56: UNHESA | E56: 4000 | F56: 1000 | G56: =+E56+F56 -> 5000 | H56: 15 | I56: 1 | J56: 0 | K56: 0 | L56: 0 | M56: 0 | N56: =SUM(I56:M56) -> 1 | O56: B.15.1.23 | Q56: =($E56/30/8*1.5)*P56 -> 0 | S56: =($E56/30/8*2)*R56 -> 0 | T56: 2 | U56: =($E56/30/8*1.5)*T56 -> 50 | W56: =($E56/30/8*2)*V56 -> 0 | Y56: =(($E56/30/8)*1.5)*X56 -> 0 | AA56: =(($E56/30/8)*2)*Z56 -> 0 | AC56: =(($E56/30/8)*1.5)*AB56 -> 0 | AE56: =(($E56/30/8)*2)*AD56 -> 0 | AG56: =(($E56/30/8)*1.5)*AF56 -> 0 | AI56: =(($E56/30/8)*2)*AH56 -> 0 | AV56: =((E56/30)*H56)*$I56 -> 2000 | AW56: =((F56/30)*H56)*$I56 -> 500 | AX56: =P56 -> 0 | AY56: =Q56 -> 0 | AZ56: =R56 -> 0 | BA56: =S56 -> 0 | BB56: =AJ56+AO56 -> 0 | BC56: =(AV56+AY56+BA56)*0.1267 -> 253.4 | BD56: =SUM(AV56:BC56)-AX56-AZ56 -> 2753.4 | BE56: =(($E56/30)*$H56)*$J56 -> 0 | BF56: =(($F56/30)*$H56)*$J56 -> 0 | BG56: =T56 -> 2 | BH56: =U56 -> 50 | BI56: =V56 -> 0 | BJ56: =W56 -> 0 | BK56: =AK56+AP56 -> 0 | BL56: =(+BE56+BH56+BJ56+BK56)*0.1267 -> 6.335 | BM56: =SUM(BE56:BL56)-BG56-BI56 -> 56.335 | BN56: =(($E56/30)*$H56)*$K56 -> 0 | BO56: =(($F56/30)*$H56)*$K56 -> 0 | BP56: =X56 -> 0 | BQ56: =Y56 -> 0 | BR56: =Z56 -> 0 | BS56: =AA56 -> 0 | BT56: =AL56+AQ56 -> 0 | BU56: =(BN56+BQ56+BS56)*0.1267 -> 0 | BV56: =SUM(BN56:BU56)-BP56-BR56 -> 0 | BW56: =(($E56/30)*$H56)*$L56 -> 0 | BX56: =(($F56/30)*$H56)*$L56 -> 0 | BZ56: =AC56 -> 0 | CB56: =AE56 -> 0 | CD56: =(BW56+BZ56+CB56)*0.1267 -> 0 | CE56: =SUM(BW56:CD56) -> 0 | CF56: =(($E56/30)*$H56)*M56 -> 0 | CG56: =(($F56/30)*$H56)*$M56 -> 0 | CI56: =AG56 -> 0 | CK56: =AI56 -> 0 | CM56: =(CF56+CI56+CK56)*0.1267 -> 0 | CP56: UNHESA | CQ56: =IF($CP56="PROQUIMA",$AV56+$BE56+$BN56+$BW56+$CF56,0) -> 0 | CR56: =IF($CP56="PROQUIMA",$AW56+$BF56+$BO56+$BX56+$CG56,0) -> 0 | CS56: =IF($CP56="PROQUIMA",$AX56+$BG56+$BP56+$BY56+$CH56,0) -> 0 | CT56: =IF($CP56="PROQUIMA",$AY56+$BH56+$BQ56+$BZ56+$CI56,0) -> 0 | CU56: =IF($CP56="PROQUIMA",$AZ56+$BI56+$BR56+$CA56+$CJ56,0) -> 0 | CV56: =IF($CP56="PROQUIMA",$BA56+$BJ56+$BS56+$CB56+$CK56,0) -> 0 | CW56: =IF($CP56="PROQUIMA",$BB56+$BK56+$BT56+$CC56+$CL56,0) -> 0 | CX56: =IF($CP56="PROQUIMA",$BC56+$BL56+$BU56+$CD56+CM56,0) -> 0 | CY56: =SUM(CQ56:CX56)-CS56-CU56 -> 0 | CZ56: =IF($CP56="UNHESA",$AV56+$BE56+$BN56+$BW56+$CF56,0) -> 2000 | DA56: =IF($CP56="UNHESA",$AW56+$BF56+$BO56+$BX56+$CG56,0) -> 500 | DB56: =IF($CP56="UNHESA",$AX56+$BG56+$BP56+$BY56+$CH56,0) -> 2 | DC56: =IF($CP56="UNHESA",$AY56+$BH56+$BQ56+$BZ56+$CI56,0) -> 50 | DD56: =IF($CP56="UNHESA",$AZ56+$BI56+$BR56+$CA56+$CJ56,0) -> 0 | DE56: =IF($CP56="UNHESA",$BA56+$BJ56+$BS56+$CB56+$CK56,0) -> 0 | DF56: =IF($CP56="UNHESA",$BB56+$BK56+$BT56+$CC56+$CL56,0) -> 0 | DG56: =IF($CP56="UNHESA",$BC56+$BL56+$BU56+$CD56+$CM56,0) -> 259.735 | DH56: =SUM(CZ56:DG56)-DB56-DD56 -> 2809.735 | DI56: =IF($CP56="UNHESA LIQUIDOS",$AV56+$BE56+$BN56+$BW56+$CF56,0) -> 0 | DJ56: =IF($CP56="CALIDUL",$AW56+$BF56+$BO56+$BX56+$CG56,0) -> 0 | DK56: =IF($CP56="CALIDUL",$AX56+$BG56+$BP56+$BY56+$CH56,0) -> 0 | DL56: =IF($CP56="CALIDUL",$AY56+$BH56+$BQ56+$BZ56+$CI56,0) -> 0 | DM56: =IF($CP56="CALIDUL",$AZ56+$BI56+$BR56+$CA56+$CJ56,0) -> 0 | DN56: =IF($CP56="CALIDUL",$BA56+$BJ56+$BS56+$CB56+$CK56,0) -> 0 | DO56: =IF($CP56="CALIDUL",$BB56+$BK56+$BT56+$CC56+$CL56,0) -> 0 | DP56: =IF($CP56="CALIDUL",$BC56+$BL56+$BU56+$CD56+$CM56,0) -> 0 | DQ56: =SUM(DI56:DP56)-DK56-DM56 -> 0 | DR56: 0 | DS56: 0 | DT56: 0 | DU56: 0 | DV56: 0 | DW56: 0 | DX56: 0 | DY56: 0 | DZ56: 0 | EI56: =SUM(EA56:EH56)-EC56-EE56 -> 0 | ET56: =+EO56+EP56+EQ56 -> 0 | EV56: =IF($H56<=15,EK56/2,EK56) -> 0 | EW56: =IF($H56<=15,EL56/2,EL56) -> 0 | EX56: =IF($H56<=15,EM56/2,EM56) -> 0 | EY56: =IF($H56<=15,EN56/2,EN56) -> 0 | EZ56: =IF($H56<=15,EO56/2,EO56) -> 0 | FA56: =IF($H56<=15,EP56/2,EP56) -> 0 | FB56: =IF($H56<=15,EQ56/2,EQ56) -> 0 | FC56: =IF($H56<=15,ER56/2,ER56) -> 0 | ... FE56: =IF($H56<=15,ET56/2,ET56) -> 0
A57: =+A56+1 -> 36 | B57: Guzman Hernandez Edgar Geovanni | C57: Auxiliar de control de calidad | D57: PROQUIMA | E57: 3166.38 | F57: 600 | G57: =+E57+F57 -> 3766.38 | H57: 30 | I57: 0.6 | J57: 0.4 | K57: 0 | L57: 0 | M57: 0 | N57: =SUM(I57:M57) -> 1 | P57: 1 | Q57: =($E57/30/8*1.5)*P57 -> 19.789875 | R57: 0 | S57: =($E57/30/8*2)*R57 -> 0 | U57: =($E57/30/8*1.5)*T57 -> 0 | W57: =($E57/30/8*2)*V57 -> 0 | Y57: =(($E57/30/8)*1.5)*X57 -> 0 | AA57: =(($E57/30/8)*2)*Z57 -> 0 | AC57: =(($E57/30/8)*1.5)*AB57 -> 0 | AE57: =(($E57/30/8)*2)*AD57 -> 0 | AG57: =(($E57/30/8)*1.5)*AF57 -> 0 | AI57: =(($E57/30/8)*2)*AH57 -> 0 | AV57: =((E57/30)*H57)*$I57 -> 1899.828 | AW57: =((F57/30)*H57)*$I57 -> 360 | AX57: =P57 -> 1 | AY57: =Q57 -> 19.789875 | AZ57: =R57 -> 0 | BA57: =S57 -> 0 | BB57: =AJ57+AO57 -> 0 | BC57: =(AV57+AY57+BA57)*0.1267 -> 243.21558 | BD57: =SUM(AV57:BC57)-AX57-AZ57 -> 2522.8335 | BE57: =(($E57/30)*$H57)*$J57 -> 1266.552 | BF57: =(($F57/30)*$H57)*$J57 -> 240 | BG57: =T57 -> 0 | BH57: =U57 -> 0 | BI57: =V57 -> 0 | BJ57: =W57 -> 0 | BK57: =AK57+AP57 -> 0 | BL57: =(+BE57+BH57+BJ57+BK57)*0.1267 -> 160.47214 | BM57: =SUM(BE57:BL57)-BG57-BI57 -> 1667.0241 | BN57: =(($E57/30)*$H57)*$K57 -> 0 | BO57: =(($F57/30)*$H57)*$K57 -> 0 | BP57: =X57 -> 0 | BQ57: =Y57 -> 0 | BR57: =Z57 -> 0 | BS57: =AA57 -> 0 | BT57: =AL57+AQ57 -> 0 | BU57: =(BN57+BQ57+BS57)*0.1267 -> 0 | BV57: =SUM(BN57:BU57)-BP57-BR57 -> 0 | BW57: =(($E57/30)*$H57)*$L57 -> 0 | BX57: =(($F57/30)*$H57)*$L57 -> 0 | BZ57: =AC57 -> 0 | CB57: =AE57 -> 0 | CD57: =(BW57+BZ57+CB57)*0.1267 -> 0 | CE57: =SUM(BW57:CD57) -> 0 | CF57: =(($E57/30)*$H57)*M57 -> 0 | CG57: =(($F57/30)*$H57)*$M57 -> 0 | CI57: =AG57 -> 0 | CK57: =AI57 -> 0 | CM57: =(CF57+CI57+CK57)*0.1267 -> 0 | CP57: PROQUIMA | CQ57: =IF($CP57="PROQUIMA",$AV57+$BE57+$BN57+$BW57+$CF57,0) -> 3166.38 | CR57: =IF($CP57="PROQUIMA",$AW57+$BF57+$BO57+$BX57+$CG57,0) -> 600 | CS57: =IF($CP57="PROQUIMA",$AX57+$BG57+$BP57+$BY57+$CH57,0) -> 1 | CT57: =IF($CP57="PROQUIMA",$AY57+$BH57+$BQ57+$BZ57+$CI57,0) -> 19.789875 | CU57: =IF($CP57="PROQUIMA",$AZ57+$BI57+$BR57+$CA57+$CJ57,0) -> 0 | CV57: =IF($CP57="PROQUIMA",$BA57+$BJ57+$BS57+$CB57+$CK57,0) -> 0 | CW57: =IF($CP57="PROQUIMA",$BB57+$BK57+$BT57+$CC57+$CL57,0) -> 0 | CX57: =IF($CP57="PROQUIMA",$BC57+$BL57+$BU57+$CD57+CM57,0) -> 403.68772 | CY57: =SUM(CQ57:CX57)-CS57-CU57 -> 4189.8576 | CZ57: =IF($CP57="UNHESA",$AV57+$BE57+$BN57+$BW57+$CF57,0) -> 0 | DA57: =IF($CP57="UNHESA",$AW57+$BF57+$BO57+$BX57+$CG57,0) -> 0 | DB57: =IF($CP57="UNHESA",$AX57+$BG57+$BP57+$BY57+$CH57,0) -> 0 | DC57: =IF($CP57="UNHESA",$AY57+$BH57+$BQ57+$BZ57+$CI57,0) -> 0 | DD57: =IF($CP57="UNHESA",$AZ57+$BI57+$BR57+$CA57+$CJ57,0) -> 0 | DE57: =IF($CP57="UNHESA",$BA57+$BJ57+$BS57+$CB57+$CK57,0) -> 0 | DF57: =IF($CP57="UNHESA",$BB57+$BK57+$BT57+$CC57+$CL57,0) -> 0 | DG57: =IF($CP57="UNHESA",$BC57+$BL57+$BU57+$CD57+$CM57,0) -> 0 | DH57: =SUM(CZ57:DG57)-DB57-DD57 -> 0 | DI57: =IF($CP57="UNHESA LIQUIDOS",$AV57+$BE57+$BN57+$BW57+$CF57,0) -> 0 | DJ57: =IF($CP57="CALIDUL",$AW57+$BF57+$BO57+$BX57+$CG57,0) -> 0 | DK57: =IF($CP57="CALIDUL",$AX57+$BG57+$BP57+$BY57+$CH57,0) -> 0 | DL57: =IF($CP57="CALIDUL",$AY57+$BH57+$BQ57+$BZ57+$CI57,0) -> 0 | DM57: =IF($CP57="CALIDUL",$AZ57+$BI57+$BR57+$CA57+$CJ57,0) -> 0 | DN57: =IF($CP57="CALIDUL",$BA57+$BJ57+$BS57+$CB57+$CK57,0) -> 0 | DO57: =IF($CP57="CALIDUL",$BB57+$BK57+$BT57+$CC57+$CL57,0) -> 0 | DP57: =IF($CP57="CALIDUL",$BC57+$BL57+$BU57+$CD57+$CM57,0) -> 0 | DQ57: =SUM(DI57:DP57)-DK57-DM57 -> 0 | DR57: 0 | DS57: 0 | DT57: 0 | DU57: 0 | DV57: 0 | DW57: 0 | DX57: 0 | DY57: 0 | DZ57: 0 | EI57: =SUM(EA57:EH57)-EC57-EE57 -> 0 | EL57: 702.56 | EN57: =59.75+72 -> 131.75 | EO57: 82.5 | EP57: =60+50 -> 110 | EQ57: =125 -> 125 | ET57: =+EO57+EP57+EQ57 -> 317.5 | EV57: =IF($H57<=15,EK57/2,EK57) -> 0 | EW57: =IF($H57<=15,EL57/2,EL57) -> 702.56 | EX57: =IF($H57<=15,EM57/2,EM57) -> 0 | EY57: =IF($H57<=15,EN57/2,EN57) -> 131.75 | EZ57: =IF($H57<=15,EO57/2,EO57) -> 82.5 | FA57: =IF($H57<=15,EP57/2,EP57) -> 110 | FB57: =IF($H57<=15,EQ57/2,EQ57) -> 125 | FC57: =IF($H57<=15,ER57/2,ER57) -> 0 | ... FE57: =IF($H57<=15,ET57/2,ET57) -> 317.5 | FF57: 0.6 | FG57: 0.4 | FH57: 0 | FI57: 0 | FJ57: 0 | FK57: 1 | FL57: =+EP57-FA57 -> 0
A58: =+A57+1 -> 37 | B58: Martinez Garcia Erick Rolando | C58: Auxiliar de control de calidad | D58: PROQUIMA | E58: 3166.38 | F58: 750 | G58: =+E58+F58 -> 3916.38 | H58: 30 | I58: 0.7 | J58: 0.3 | K58: 0 | L58: 0 | M58: 0 | N58: =SUM(I58:M58) -> 1 | P58: 12.5 | Q58: =($E58/30/8*1.5)*P58 -> 247.37344 | R58: 0 | S58: =($E58/30/8*2)*R58 -> 0 | U58: =($E58/30/8*1.5)*T58 -> 0 | W58: =($E58/30/8*2)*V58 -> 0 | Y58: =(($E58/30/8)*1.5)*X58 -> 0 | AA58: =(($E58/30/8)*2)*Z58 -> 0 | AC58: =(($E58/30/8)*1.5)*AB58 -> 0 | AE58: =(($E58/30/8)*2)*AD58 -> 0 | AG58: =(($E58/30/8)*1.5)*AF58 -> 0 | AI58: =(($E58/30/8)*2)*AH58 -> 0 | AV58: =((E58/30)*H58)*$I58 -> 2216.466 | AW58: =((F58/30)*H58)*$I58 -> 525 | AX58: =P58 -> 12.5 | AY58: =Q58 -> 247.37344 | AZ58: =R58 -> 0 | BA58: =S58 -> 0 | BB58: =AJ58+AO58 -> 0 | BC58: =(AV58+AY58+BA58)*0.1267 -> 312.16846 | BD58: =SUM(AV58:BC58)-AX58-AZ58 -> 3301.0079 | BE58: =(($E58/30)*$H58)*$J58 -> 949.914 | BF58: =(($F58/30)*$H58)*$J58 -> 225 | BG58: =T58 -> 0 | BH58: =U58 -> 0 | BI58: =V58 -> 0 | BJ58: =W58 -> 0 | BK58: =AK58+AP58 -> 0 | BL58: =(+BE58+BH58+BJ58+BK58)*0.1267 -> 120.3541 | BM58: =SUM(BE58:BL58)-BG58-BI58 -> 1295.2681 | BN58: =(($E58/30)*$H58)*$K58 -> 0 | BO58: =(($F58/30)*$H58)*$K58 -> 0 | BP58: =X58 -> 0 | BQ58: =Y58 -> 0 | BR58: =Z58 -> 0 | BS58: =AA58 -> 0 | BT58: =AL58+AQ58 -> 0 | BU58: =(BN58+BQ58+BS58)*0.1267 -> 0 | BV58: =SUM(BN58:BU58)-BP58-BR58 -> 0 | BW58: =(($E58/30)*$H58)*$L58 -> 0 | BX58: =(($F58/30)*$H58)*$L58 -> 0 | BZ58: =AC58 -> 0 | CB58: =AE58 -> 0 | CD58: =(BW58+BZ58+CB58)*0.1267 -> 0 | CE58: =SUM(BW58:CD58) -> 0 | CF58: =(($E58/30)*$H58)*M58 -> 0 | CG58: =(($F58/30)*$H58)*$M58 -> 0 | CI58: =AG58 -> 0 | CK58: =AI58 -> 0 | CM58: =(CF58+CI58+CK58)*0.1267 -> 0 | CP58: PROQUIMA | CQ58: =IF($CP58="PROQUIMA",$AV58+$BE58+$BN58+$BW58+$CF58,0) -> 3166.38 | CR58: =IF($CP58="PROQUIMA",$AW58+$BF58+$BO58+$BX58+$CG58,0) -> 750 | CS58: =IF($CP58="PROQUIMA",$AX58+$BG58+$BP58+$BY58+$CH58,0) -> 12.5 | CT58: =IF($CP58="PROQUIMA",$AY58+$BH58+$BQ58+$BZ58+$CI58,0) -> 247.37344 | CU58: =IF($CP58="PROQUIMA",$AZ58+$BI58+$BR58+$CA58+$CJ58,0) -> 0 | CV58: =IF($CP58="PROQUIMA",$BA58+$BJ58+$BS58+$CB58+$CK58,0) -> 0 | CW58: =IF($CP58="PROQUIMA",$BB58+$BK58+$BT58+$CC58+$CL58,0) -> 0 | CX58: =IF($CP58="PROQUIMA",$BC58+$BL58+$BU58+$CD58+CM58,0) -> 432.52256 | CY58: =SUM(CQ58:CX58)-CS58-CU58 -> 4596.276 | CZ58: =IF($CP58="UNHESA",$AV58+$BE58+$BN58+$BW58+$CF58,0) -> 0 | DA58: =IF($CP58="UNHESA",$AW58+$BF58+$BO58+$BX58+$CG58,0) -> 0 | DB58: =IF($CP58="UNHESA",$AX58+$BG58+$BP58+$BY58+$CH58,0) -> 0 | DC58: =IF($CP58="UNHESA",$AY58+$BH58+$BQ58+$BZ58+$CI58,0) -> 0 | DD58: =IF($CP58="UNHESA",$AZ58+$BI58+$BR58+$CA58+$CJ58,0) -> 0 | DE58: =IF($CP58="UNHESA",$BA58+$BJ58+$BS58+$CB58+$CK58,0) -> 0 | DF58: =IF($CP58="UNHESA",$BB58+$BK58+$BT58+$CC58+$CL58,0) -> 0 | DG58: =IF($CP58="UNHESA",$BC58+$BL58+$BU58+$CD58+$CM58,0) -> 0 | DH58: =SUM(CZ58:DG58)-DB58-DD58 -> 0 | DI58: =IF($CP58="UNHESA LIQUIDOS",$AV58+$BE58+$BN58+$BW58+$CF58,0) -> 0 | DJ58: =IF($CP58="CALIDUL",$AW58+$BF58+$BO58+$BX58+$CG58,0) -> 0 | DK58: =IF($CP58="CALIDUL",$AX58+$BG58+$BP58+$BY58+$CH58,0) -> 0 | DL58: =IF($CP58="CALIDUL",$AY58+$BH58+$BQ58+$BZ58+$CI58,0) -> 0 | DM58: =IF($CP58="CALIDUL",$AZ58+$BI58+$BR58+$CA58+$CJ58,0) -> 0 | DN58: =IF($CP58="CALIDUL",$BA58+$BJ58+$BS58+$CB58+$CK58,0) -> 0 | DO58: =IF($CP58="CALIDUL",$BB58+$BK58+$BT58+$CC58+$CL58,0) -> 0 | DP58: =IF($CP58="CALIDUL",$BC58+$BL58+$BU58+$CD58+$CM58,0) -> 0 | DQ58: =SUM(DI58:DP58)-DK58-DM58 -> 0 | DR58: 0 | DS58: 0 | DT58: 0 | DU58: 0 | DV58: 0 | DW58: 0 | DX58: 0 | DY58: 0 | DZ58: 0 | EI58: =SUM(EA58:EH58)-EC58-EE58 -> 0 | EN58: =82.5+270 -> 352.5 | EP58: 50 | ET58: =+EO58+EP58+EQ58 -> 50 | EV58: =IF($H58<=15,EK58/2,EK58) -> 0 | EW58: =IF($H58<=15,EL58/2,EL58) -> 0 | EX58: =IF($H58<=15,EM58/2,EM58) -> 0 | EY58: =IF($H58<=15,EN58/2,EN58) -> 352.5 | EZ58: =IF($H58<=15,EO58/2,EO58) -> 0 | FA58: =IF($H58<=15,EP58/2,EP58) -> 50 | FB58: =IF($H58<=15,EQ58/2,EQ58) -> 0 | FC58: =IF($H58<=15,ER58/2,ER58) -> 0 | ... FE58: =IF($H58<=15,ET58/2,ET58) -> 50 | FF58: 0.6 | FG58: 0.4 | FH58: 0 | FI58: 0 | FJ58: 0 | FK58: 1 | FL58: =+EP58-FA58 -> 0
C59: TotaL Control de Calidad | E59: =SUM(E53:E58) -> 23249.14 | F59: =SUM(F53:F58) -> 6433.62 | G59: =SUM(G53:G58) -> 29682.76 | P59: =SUM(P53:P58) -> 13.5 | Q59: =SUM(Q53:Q58) -> 267.16331 | R59: =SUM(R53:R58) -> 0 | S59: =SUM(S53:S58) -> 0 | T59: =SUM(T53:T58) -> 20.5 | U59: =SUM(U53:U58) -> 482.79369 | V59: =SUM(V53:V58) -> 0 | W59: =SUM(W53:W58) -> 0 | ... AA59: =SUM(AA53:AA58) -> 0 | AB59: =SUM(AB53:AB53) -> 0 | AC59: =SUM(AC53:AC53) -> 0 | AD59: =SUM(AD53:AD53) -> 0 | AE59: =SUM(AE53:AE53) -> 0 | AF59: =SUM(AF53:AF53) -> 0 | AG59: =SUM(AG53:AG53) -> 0 | AH59: =SUM(AH53:AH53) -> 0 | AI59: =SUM(AI53:AI53) -> 0 | ... AS59: =SUM(AS53:AS53) -> 0 | AT59: =SUM(#REF!) -> #REF! | AV59: =SUM(AV53:AV58) -> 9753.794 | AW59: =SUM(AW53:AW58) -> 2547.5 | AX59: =SUM(AX53:AX58) -> 13.5 | AY59: =SUM(AY53:AY58) -> 267.16331 | AZ59: =SUM(AZ53:AZ58) -> 0 | BA59: =SUM(BA53:BA58) -> 0 | BB59: =SUM(BB53:BB58) -> 0 | BC59: =SUM(BC53:BC58) -> 1269.6553 | ... CE59: =SUM(CE53:CE58) -> 1268.7812 | CF59: =SUM(CF53:CF53) -> 0 | CG59: =SUM(CG53:CG53) -> 0 | CH59: =SUM(CH53:CH53) -> 0 | CI59: =SUM(CI53:CI53) -> 0 | CJ59: =SUM(CJ53:CJ53) -> 0 | CK59: =SUM(CK53:CK53) -> 0 | CL59: =SUM(CL53:CL53) -> 0 | CM59: =SUM(CM53:CM53) -> 0 | CN59: =SUM(CN53:CN53) -> 0 | CQ59: =SUM(CQ53:CQ58) -> 11582.76 | CR59: =SUM(CR53:CR58) -> 4100 | CS59: =SUM(CS53:CS58) -> 13.5 | CT59: =SUM(CT53:CT58) -> 267.16331 | CU59: =SUM(CU53:CU58) -> 0 | CV59: =SUM(CV53:CV58) -> 0 | CW59: =SUM(CW53:CW58) -> 0 | CX59: =SUM(CX53:CX58) -> 1501.3853 | ... EI59: =SUM(EI53:EI58) -> 0 | EK59: =SUM(EK53:EK58) -> 226.45 | EL59: =SUM(EL53:EL58) -> 702.56 | EM59: =SUM(EM53:EM58) -> 0 | EN59: =SUM(EN53:EN58) -> 746.75 | EO59: =SUM(EO53:EO58) -> 82.5 | EP59: =SUM(EP53:EP58) -> 335 | EQ59: =SUM(EQ53:EQ58) -> 605 | ER59: =SUM(ER53:ER58) -> 0 | ... ET59: =SUM(ET53:ET58) -> 1022.5 | EV59: =SUM(EV53:EV58) -> 226.45 | EW59: =SUM(EW53:EW58) -> 702.56 | EX59: =SUM(EX53:EX58) -> 0 | EY59: =SUM(EY53:EY58) -> 746.75 | EZ59: =SUM(EZ53:EZ58) -> 82.5 | FA59: =SUM(FA53:FA58) -> 335 | FB59: =SUM(FB53:FB58) -> 605 | FC59: =SUM(FC53:FC58) -> 0 | ... FE59: =SUM(FE53:FE58) -> 1022.5 | FL59: =+EP59-FA59 -> 0
F60: =+F57-250 -> 350 | FL60: =+EP60-FA60 -> 0
B61: INFORMATICA | FL61: =+EP61-FA61 -> 0
A62: =A58+1 -> 38 | B62: Jimenez Sosa Luis Eduardo | C62: Jefe de Informática | D62: PROQUIMA | E62: 7000 | F62: 5250 | G62: =+E62+F62 -> 12250 | H62: 30 | I62: 0.45 | J62: 0.4 | K62: 0 | L62: 0.15 | M62: 0 | N62: =SUM(I62:M62) -> 1 | P62: 0 | Q62: =($E62/30/8*1.5)*P62 -> 0 | S62: =($E62/30/8*2)*R62 -> 0 | U62: =($E62/30/8*1.5)*T62 -> 0 | W62: =($E62/30/8*2)*V62 -> 0 | Y62: =(($E62/30/8)*1.5)*X62 -> 0 | AA62: =(($E62/30/8)*2)*Z62 -> 0 | AC62: =(($E62/30/8)*1.5)*AB62 -> 0 | AE62: =(($E62/30/8)*2)*AD62 -> 0 | AG62: =(($E62/30/8)*1.5)*AF62 -> 0 | AI62: =(($E62/30/8)*2)*AH62 -> 0 | AV62: =((E62/30)*H62)*$I62 -> 3150 | AW62: =((F62/30)*H62)*$I62 -> 2362.5 | AX62: =P62 -> 0 | AY62: =Q62 -> 0 | AZ62: =R62 -> 0 | BA62: =S62 -> 0 | BB62: =AJ62+AO62 -> 0 | BC62: =(AV62+AY62+BA62)*0.1267 -> 399.105 | BD62: =SUM(AV62:BC62)-AX62-AZ62 -> 5911.605 | BE62: =(($E62/30)*$H62)*$J62 -> 2800 | BF62: =(($F62/30)*$H62)*$J62 -> 2100 | BG62: =T62 -> 0 | BH62: =U62 -> 0 | BI62: =V62 -> 0 | BJ62: =W62 -> 0 | BK62: =AK62+AP62 -> 0 | BL62: =(+BE62+BH62+BK62)*0.1267 -> 354.76 | BM62: =SUM(BE62:BL62)-BG62-BI62 -> 5254.76 | BN62: =(($E62/30)*$H62)*$K62 -> 0 | BO62: =(($F62/30)*$H62)*$K62 -> 0 | BP62: =X62 -> 0 | BQ62: =Y62 -> 0 | BR62: =Z62 -> 0 | BS62: =AA62 -> 0 | BT62: =AL62+AQ62 -> 0 | BU62: =(BN62+BQ62+BS62)*0.1267 -> 0 | BV62: =SUM(BN62:BU62)-BP62-BR62 -> 0 | BW62: =(($E62/30)*$H62)*$L62 -> 1050 | BX62: =(($F62/30)*$H62)*$L62 -> 787.5 | BY62: =AB62 -> 0 | BZ62: =AC62 -> 0 | CA62: =AD62 -> 0 | CB62: =AE62 -> 0 | CC62: =AM62+AR62 -> 0 | CD62: =(BW62+BZ62+CB62)*0.1267 -> 133.035 | CE62: =SUM(BW62:CD62)-BY62-CA62 -> 1970.535 | CF62: =(($E62/30)*$H62)*M62 -> 0 | CG62: =(($F62/30)*$H62)*$M62 -> 0 | CH62: =+AF62 -> 0 | CI62: =AG62 -> 0 | CJ62: =AH62 -> 0 | CK62: =AI62 -> 0 | CL62: =AN62+AS62 -> 0 | CM62: =(CF62+CI62+CK62)*0.1267 -> 0 | CN62: =SUM(CF62:CM62)-CH62-CJ62 -> 0 | CP62: PROQUIMA | CQ62: =IF($CP62="PROQUIMA",$AV62+$BE62+$BN62+$BW62+$CF62,0) -> 7000 | CR62: =IF($CP62="PROQUIMA",$AW62+$BF62+$BO62+$BX62+$CG62,0) -> 5250 | CS62: =IF($CP62="PROQUIMA",$AX62+$BG62+$BP62+$BY62+$CH62,0) -> 0 | CT62: =IF($CP62="PROQUIMA",$AY62+$BH62+$BQ62+$BZ62+$CI62,0) -> 0 | CU62: =IF($CP62="PROQUIMA",$AZ62+$BI62+$BR62+$CA62+$CJ62,0) -> 0 | CV62: =IF($CP62="PROQUIMA",$BA62+$BJ62+$BS62+$CB62+$CK62,0) -> 0 | CW62: =IF($CP62="PROQUIMA",$BB62+$BK62+$BT62+$CC62+$CL62,0) -> 0 | CX62: =IF($CP62="PROQUIMA",$BC62+$BL62+$BU62+$CD62+CM62,0) -> 886.9 | CY62: =SUM(CQ62:CX62)-CS62-CU62 -> 13136.9 | CZ62: =IF($CP62="UNHESA",$AV62+$BE62+$BN62+$BW62+$CF62,0) -> 0 | DA62: =IF($CP62="UNHESA",$AW62+$BF62+$BO62+$BX62+$CG62,0) -> 0 | DB62: =IF($CP62="UNHESA",$AX62+$BG62+$BP62+$BY62+$CH62,0) -> 0 | DC62: =IF($CP62="UNHESA",$AY62+$BH62+$BQ62+$BZ62+$CI62,0) -> 0 | DD62: =IF($CP62="UNHESA",$AZ62+$BI62+$BR62+$CA62+$CJ62,0) -> 0 | DE62: =IF($CP62="UNHESA",$BA62+$BJ62+$BS62+$CB62+$CK62,0) -> 0 | DF62: =IF($CP62="UNHESA",$BB62+$BK62+$BT62+$CC62+$CL62,0) -> 0 | DG62: =IF($CP62="UNHESA",$BC62+$BL62+$BU62+$CD62+$CM62,0) -> 0 | DH62: =SUM(CZ62:DG62)-DB62-DD62 -> 0 | DI62: =IF($CP62="UNHESA LIQUIDOS",$AV62+$BE62+$BN62+$BW62+$CF62,0) -> 0 | DJ62: =IF($CP62="CALIDUL",$AW62+$BF62+$BO62+$BX62+$CG62,0) -> 0 | DK62: =IF($CP62="CALIDUL",$AX62+$BG62+$BP62+$BY62+$CH62,0) -> 0 | DL62: =IF($CP62="CALIDUL",$AY62+$BH62+$BQ62+$BZ62+$CI62,0) -> 0 | DM62: =IF($CP62="CALIDUL",$AZ62+$BI62+$BR62+$CA62+$CJ62,0) -> 0 | DN62: =IF($CP62="CALIDUL",$BA62+$BJ62+$BS62+$CB62+$CK62,0) -> 0 | DO62: =IF($CP62="CALIDUL",$BB62+$BK62+$BT62+$CC62+$CL62,0) -> 0 | DP62: =IF($CP62="CALIDUL",$BC62+$BL62+$BU62+$CD62+$CM62,0) -> 0 | DQ62: =SUM(DI62:DP62)-DK62-DM62 -> 0 | DR62: =IF($CP62="ECONACIONAL",$AV62+$BE62+$BN62+$BW62+$CF62,0) -> 0 | DS62: =IF($CP62="ECONACIONAL",$AW62+$BF62+$BO62+$BX62+$CG62,0) -> 0 | DT62: =IF($CP62="ECONACIONAL",$AX62+$BG62+$BP62+$BY62+$CH62,0) -> 0 | DU62: =IF($CP62="ECONACIONAL",$AY62+$BH62+$BQ62+$BZ62+$CI62,0) -> 0 | DV62: =IF($CP62="ECONACIONAL",$AZ62+$BI62+$BR62+$CA62+$CJ62,0) -> 0 | DW62: =IF($CP62="ECONACIONAL",$BA62+$BJ62+$BS62+$CB62+$CK62,0) -> 0 | DX62: =IF($CP62="ECONACIONAL",$BB62+$BK62+$BT62+$CC62+$CL62,0) -> 0 | DY62: =IF($CP62="ECONACIONAL",$BC62+$BL62+$BU62+$CD62+$CM62,0) -> 0 | DZ62: =SUM(DR62:DY62)-DT62-DV62 -> 0 | EA62: =IF($CP62="CLEARTEC",$AV62+$BE62+$BN62+$BW62+$CF62,0) -> 0 | EB62: =IF($CP62="CLEARTEC",$AW62+$BF62+$BO62+$BX62+$CG62,0) -> 0 | EC62: =IF($CP62="CLEARTEC",$AX62+$BG62+$BP62+$BY62+$CH62,0) -> 0 | ED62: =IF($CP62="CLEARTEC",$AY62+$BH62+$BQ62+$BZ62+$CI62,0) -> 0 | EE62: =IF($CP62="CLEARTEC",$AZ62+$BI62+$BR62+$CA62+$CJ62,0) -> 0 | EF62: =IF($CP62="CLEARTEC",$BA62+$BJ62+$BS62+$CB62+$CK62,0) -> 0 | EG62: =IF($CP62="CLEARTEC",$BB62+$BK62+$BT62+$CC62+$CL62,0) -> 0 | EH62: =IF($CP62="CLEARTEC",$BC62+$BL62+$BU62+$CD62+$CM62,0) -> 0 | EI62: =SUM(EA62:EH62)-EC62-EE62 -> 0 | EK62: 395.6 | EL62: =839.96+651.8 -> 1491.76 | EP62: 150 | EQ62: =112.5+75 -> 187.5 | ET62: =+EO62+EP62+EQ62 -> 337.5 | EV62: =IF($H62<=15,EK62/2,EK62) -> 395.6 | EW62: =IF($H62<=15,EL62/2,EL62) -> 1491.76 | EX62: =IF($H62<=15,EM62/2,EM62) -> 0 | EY62: =IF($H62<=15,EN62/2,EN62) -> 0 | EZ62: =IF($H62<=15,EO62/2,EO62) -> 0 | FA62: =IF($H62<=15,EP62/2,EP62) -> 150 | FB62: =IF($H62<=15,EQ62/2,EQ62) -> 187.5 | FC62: =IF($H62<=15,ER62/2,ER62) -> 0 | ... FE62: =IF($H62<=15,ET62/2,ET62) -> 337.5 | FF62: 0.7 | FG62: 0.3 | FH62: 0 | FI62: 0 | FJ62: 0 | FK62: 1 | FL62: =+EP62-FA62 -> 0
